Workbook

Sheet Resumo
A1: Categoria | B1: 01.25 | C1: 02.25 | D1: 03.25 | E1: 04.25 | F1: 05.25 | G1: 06.25 | H1: 07.25 | I1: 08.25 | J1: 09.25 | K1: 10.25 | L1: 11.25 | M1: 12.25 | N1: Total | R1: Pólo | S1: Regional
A2: Enviado | B2: =COUNTIF(INDIRECT(B$1&"!E2:E1000"),$A2) | C2: =COUNTIF(INDIRECT(C$1&"!E2:E1000"),$A2) | D2: =COUNTIF(INDIRECT(D$1&"!E2:E1000"),$A2) | E2: =COUNTIF(INDIRECT(E$1&"!E2:E1000"),$A2) | F2: =COUNTIF(INDIRECT(F$1&"!E2:E1000"),$A2) | G2: =COUNTIF(INDIRECT(G$1&"!E2:E1000"),$A2) | H2: =COUNTIF(INDIRECT(H$1&"!E2:E1000"),$A2) | I2: =COUNTIF(INDIRECT(I$1&"!E2:E1000"),$A2) | ... M2: =COUNTIF(INDIRECT(M$1&"!E2:E1000"),$A2) | N2: =SUM(B2:M2) | R2: Curitiba | S2: Kelly
A3: Atrasado | B3: =COUNTIF(INDIRECT(B$1&"!E2:E1000"),$A3) | C3: =COUNTIF(INDIRECT(C$1&"!E2:E1000"),$A3) | D3: =COUNTIF(INDIRECT(D$1&"!E2:E1000"),$A3) | E3: =COUNTIF(INDIRECT(E$1&"!E2:E1000"),$A3) | F3: =COUNTIF(INDIRECT(F$1&"!E2:E1000"),$A3) | G3: =COUNTIF(INDIRECT(G$1&"!E2:E1000"),$A3) | H3: =COUNTIF(INDIRECT(H$1&"!E2:E1000"),$A3) | I3: =COUNTIF(INDIRECT(I$1&"!E2:E1000"),$A3) | ... M3: =COUNTIF(INDIRECT(M$1&"!E2:E1000"),$A3) | N3: =SUM(B3:M3) | R3: Francisco Beltrão | S3: Vanessa
A4: Atrasado >= 2 | B4: =COUNTIF(INDIRECT(B$1&"!E2:E1000"),$A4) | C4: =COUNTIF(INDIRECT(C$1&"!E2:E1000"),$A4) | D4: =COUNTIF(INDIRECT(D$1&"!E2:E1000"),$A4) | E4: =COUNTIF(INDIRECT(E$1&"!E2:E1000"),$A4) | F4: =COUNTIF(INDIRECT(F$1&"!E2:E1000"),$A4) | G4: =COUNTIF(INDIRECT(G$1&"!E2:E1000"),$A4) | H4: =COUNTIF(INDIRECT(H$1&"!E2:E1000"),$A4) | I4: =COUNTIF(INDIRECT(I$1&"!E2:E1000"),$A4) | ... M4: =COUNTIF(INDIRECT(M$1&"!E2:E1000"),$A4) | N4: =SUM(B4:M4) | R4: Guarapuava I | S4: Juliane
A5: Duplicado | B5: =COUNTIF(INDIRECT(B$1&"!E2:E1000"),$A5) | C5: =COUNTIF(INDIRECT(C$1&"!E2:E1000"),$A5) | D5: =COUNTIF(INDIRECT(D$1&"!E2:E1000"),$A5) | E5: =COUNTIF(INDIRECT(E$1&"!E2:E1000"),$A5) | F5: =COUNTIF(INDIRECT(F$1&"!E2:E1000"),$A5) | G5: =COUNTIF(INDIRECT(G$1&"!E2:E1000"),$A5) | H5: =COUNTIF(INDIRECT(H$1&"!E2:E1000"),$A5) | I5: =COUNTIF(INDIRECT(I$1&"!E2:E1000"),$A5) | ... M5: =COUNTIF(INDIRECT(M$1&"!E2:E1000"),$A5) | N5: =SUM(B5:M5) | R5: Guarapuava II | S5: Aramis
A6: Outras Ocorrências | B6: =COUNTIF(INDIRECT(B$1&"!E2:E1000"),$A6) | C6: =COUNTIF(INDIRECT(C$1&"!E2:E1000"),$A6) | D6: =COUNTIF(INDIRECT(D$1&"!E2:E1000"),$A6) | E6: =COUNTIF(INDIRECT(E$1&"!E2:E1000"),$A6) | F6: =COUNTIF(INDIRECT(F$1&"!E2:E1000"),$A6) | G6: =COUNTIF(INDIRECT(G$1&"!E2:E1000"),$A6) | H6: =COUNTIF(INDIRECT(H$1&"!E2:E1000"),$A6) | I6: =COUNTIF(INDIRECT(I$1&"!E2:E1000"),$A6) | ... M6: =COUNTIF(INDIRECT(M$1&"!E2:E1000"),$A6) | N6: =SUM(B6:M6) | R6: Londrina | S6: Johvanny
A7: Sem Técnico | B7: =COUNTIF(INDIRECT(B$1&"!E2:E1000"),$A7) | C7: =COUNTIF(INDIRECT(C$1&"!E2:E1000"),$A7) | D7: =COUNTIF(INDIRECT(D$1&"!E2:E1000"),$A7) | E7: =COUNTIF(INDIRECT(E$1&"!E2:E1000"),$A7) | F7: =COUNTIF(INDIRECT(F$1&"!E2:E1000"),$A7) | G7: =COUNTIF(INDIRECT(G$1&"!E2:E1000"),$A7) | H7: =COUNTIF(INDIRECT(H$1&"!E2:E1000"),$A7) | I7: =COUNTIF(INDIRECT(I$1&"!E2:E1000"),$A7) | ... M7: =COUNTIF(INDIRECT(M$1&"!E2:E1000"),$A7) | N7: =SUM(B7:M7) | R7: Maringá | S7: Diana
A8: Total | B8: =SUM(B2:B7) | C8: =SUM(C2:C7) | D8: =SUM(D2:D7) | E8: =SUM(E2:E7) | F8: =SUM(F2:F7) | G8: =SUM(G2:G7) | H8: =SUM(H2:H7) | I8: =SUM(I2:I7) | ... M8: =SUM(M2:M7) | N8: =SUM(B8:M8) | R8: Paranavaí | S8: Mário
A11: Digite o Mês de Referência | C11: Mês de Referência | K11: Acumulado (Total) | R11: Resumo por Regional
A12: 10.25 | C12: Monitoramento (Envios) | K12: Monitoramento (Envios) | R12: Regional | T12: Curitiba
C13: Regional | D13: Envi. | E13: Atra. | F13: Atra. >= 2 | G13: Dup. | H13: Out. Ocor. | I13: Sem Tec. | K13: Envi. | L13: Atra. | M13: Atra. >= 2 | N13: Dup. | O13: Out. Ocor. | P13: Sem Tec. | R13: =_xlfn.CONCAT("Envios - Mês de Referência - ", A12)
C14: Curitiba | D14: {=IFERROR(ROWS(_xlfn._xlws.FILTER(INDIRECT($A$12&"!A2:E100"),(INDIRECT($A$12&"!A2:A100")=$C14)*(INDIRECT($A$12&"!E2:E100")="Enviado"))), 0)} | E14: {=IFERROR(ROWS(_xlfn._xlws.FILTER(INDIRECT($A$12&"!A2:E100"),(INDIRECT($A$12&"!A2:A100")=$C14)*(INDIRECT($A$12&"!E2:E100")="Atrasado"))), 0)} | F14: {=IFERROR(ROWS(_xlfn._xlws.FILTER(INDIRECT($A$12&"!A2:E100"),(INDIRECT($A$12&"!A2:A100")=$C14)*(INDIRECT($A$12&"!E2:E100")="Atrasado >= 2"))), 0)} | G14: {=IFERROR(ROWS(_xlfn._xlws.FILTER(INDIRECT($A$12&"!A2:E100"),(INDIRECT($A$12&"!A2:A100")=$C14)*(INDIRECT($A$12&"!E2:E100")="Duplicado"))), 0)} | H14: {=IFERROR(ROWS(_xlfn._xlws.FILTER(INDIRECT($A$12&"!A2:E100"),(INDIRECT($A$12&"!A2:A100")=$C14)*(INDIRECT($A$12&"!E2:E100")="Outras Ocorrências"))), 0)} | I14: {=IFERROR(ROWS(_xlfn._xlws.FILTER(INDIRECT($A$12&"!A2:E100"),(INDIRECT($A$12&"!A2:A100")=$C14)*(INDIRECT($A$12&"!E2:E100")="Sem Técnico"))), 0)} | K14: =COUNTIF(INDIRECT("Monitoramento!$D$2:$P$14"), "Enviado") | L14: =COUNTIF(INDIRECT("Monitoramento!$D$2:$P$14"), "Atrasado") | M14: =COUNTIF(INDIRECT("Monitoramento!$D$2:$P$14"), "Atrasado >= 2") | N14: =COUNTIF(INDIRECT("Monitoramento!$D$2:$P$14"), "Duplicado") | O14: =COUNTIF(INDIRECT("Monitoramento!$D$2:$P$14"), "Outras Ocorrências") | P14: =COUNTIF(INDIRECT("Monitoramento!$D$2:$P$14"), "Sem Técnico") | R14: Enviados | S14: =VLOOKUP($T$12,$C$14:$I$18,2, FALSE) | T14: =S14/SUM($S$14:$S$19)
C15: Francisco Beltrão | D15: {=IFERROR(ROWS(_xlfn._xlws.FILTER(INDIRECT($A$12&"!A2:E100"),(INDIRECT($A$12&"!A2:A100")=$C15)*(INDIRECT($A$12&"!E2:E100")="Enviado"))), 0)} | E15: {=IFERROR(ROWS(_xlfn._xlws.FILTER(INDIRECT($A$12&"!A2:E100"),(INDIRECT($A$12&"!A2:A100")=$C15)*(INDIRECT($A$12&"!E2:E100")="Atrasado"))), 0)} | F15: {=IFERROR(ROWS(_xlfn._xlws.FILTER(INDIRECT($A$12&"!A2:E100"),(INDIRECT($A$12&"!A2:A100")=$C15)*(INDIRECT($A$12&"!E2:E100")="Atrasado >= 2"))), 0)} | G15: {=IFERROR(ROWS(_xlfn._xlws.FILTER(INDIRECT($A$12&"!A2:E100"),(INDIRECT($A$12&"!A2:A100")=$C15)*(INDIRECT($A$12&"!E2:E100")="Duplicado"))), 0)} | H15: {=IFERROR(ROWS(_xlfn._xlws.FILTER(INDIRECT($A$12&"!A2:E100"),(INDIRECT($A$12&"!A2:A100")=$C15)*(INDIRECT($A$12&"!E2:E100")="Outras Ocorrências"))), 0)} | I15: {=IFERROR(ROWS(_xlfn._xlws.FILTER(INDIRECT($A$12&"!A2:E100"),(INDIRECT($A$12&"!A2:A100")=$C15)*(INDIRECT($A$12&"!E2:E100")="Sem Técnico"))), 0)} | K15: =COUNTIF(INDIRECT("Monitoramento!$D$17:$P$26"), "Enviado") | L15: =COUNTIF(INDIRECT("Monitoramento!$D$17:$P$26"), "Atrasado") | M15: =COUNTIF(INDIRECT("Monitoramento!$D$17:$P$26"), "Atrasado >= 2") | N15: =COUNTIF(INDIRECT("Monitoramento!$D$17:$P$26"), "Duplicado") | O15: =COUNTIF(INDIRECT("Monitoramento!$D$17:$P$26"), "Outras Ocorrências") | P15: =COUNTIF(INDIRECT("Monitoramento!$D$17:$P$26"), "Sem Técnico") | R15: Atrasados | S15: =VLOOKUP($T$12,$C$14:$I$18,3,FALSE) | T15: =S15/SUM($S$14:$S$19)
C16: Guarapuava I | D16: {=IFERROR(ROWS(_xlfn._xlws.FILTER(INDIRECT($A$12&"!A2:E100"),(INDIRECT($A$12&"!A2:A100")=$C16)*(INDIRECT($A$12&"!E2:E100")="Enviado"))), 0)} | E16: {=IFERROR(ROWS(_xlfn._xlws.FILTER(INDIRECT($A$12&"!A2:E100"),(INDIRECT($A$12&"!A2:A100")=$C16)*(INDIRECT($A$12&"!E2:E100")="Atrasado"))), 0)} | F16: {=IFERROR(ROWS(_xlfn._xlws.FILTER(INDIRECT($A$12&"!A2:E100"),(INDIRECT($A$12&"!A2:A100")=$C16)*(INDIRECT($A$12&"!E2:E100")="Atrasado >= 2"))), 0)} | G16: {=IFERROR(ROWS(_xlfn._xlws.FILTER(INDIRECT($A$12&"!A2:E100"),(INDIRECT($A$12&"!A2:A100")=$C16)*(INDIRECT($A$12&"!E2:E100")="Duplicado"))), 0)} | H16: {=IFERROR(ROWS(_xlfn._xlws.FILTER(INDIRECT($A$12&"!A2:E100"),(INDIRECT($A$12&"!A2:A100")=$C16)*(INDIRECT($A$12&"!E2:E100")="Outras Ocorrências"))), 0)} | I16: {=IFERROR(ROWS(_xlfn._xlws.FILTER(INDIRECT($A$12&"!A2:E100"),(INDIRECT($A$12&"!A2:A100")=$C16)*(INDIRECT($A$12&"!E2:E100")="Sem Técnico"))), 0)} | K16: =COUNTIF(INDIRECT("Monitoramento!$D$29:$P$30"), "Enviado") | L16: =COUNTIF(INDIRECT("Monitoramento!$D$29:$P$30"), "Atrasado") | M16: =COUNTIF(INDIRECT("Monitoramento!$D$29:$P$30"), "Atrasado >= 2") | N16: =COUNTIF(INDIRECT("Monitoramento!$D$29:$P$30"), "Duplicado") | O16: =COUNTIF(INDIRECT("Monitoramento!$D$29:$P$30"), "Outras Ocorrências") | P16: =COUNTIF(INDIRECT("Monitoramento!$D$29:$P$30"), "Sem Técnico") | R16: Atrasados >= 2 | S16: =VLOOKUP($T$12,$C$14:$I$18,4,FALSE) | T16: =S16/SUM($S$14:$S$19)
C17: Guarapuava II | D17: {=IFERROR(ROWS(_xlfn._xlws.FILTER(INDIRECT($A$12&"!A2:E100"),(INDIRECT($A$12&"!A2:A100")=$C17)*(INDIRECT($A$12&"!E2:E100")="Enviado"))), 0)} | E17: {=IFERROR(ROWS(_xlfn._xlws.FILTER(INDIRECT($A$12&"!A2:E100"),(INDIRECT($A$12&"!A2:A100")=$C17)*(INDIRECT($A$12&"!E2:E100")="Atrasado"))), 0)} | F17: {=IFERROR(ROWS(_xlfn._xlws.FILTER(INDIRECT($A$12&"!A2:E100"),(INDIRECT($A$12&"!A2:A100")=$C17)*(INDIRECT($A$12&"!E2:E100")="Atrasado >= 2"))), 0)} | G17: {=IFERROR(ROWS(_xlfn._xlws.FILTER(INDIRECT($A$12&"!A2:E100"),(INDIRECT($A$12&"!A2:A100")=$C17)*(INDIRECT($A$12&"!E2:E100")="Duplicado"))), 0)} | H17: {=IFERROR(ROWS(_xlfn._xlws.FILTER(INDIRECT($A$12&"!A2:E100"),(INDIRECT($A$12&"!A2:A100")=$C17)*(INDIRECT($A$12&"!E2:E100")="Outras Ocorrências"))), 0)} | I17: {=IFERROR(ROWS(_xlfn._xlws.FILTER(INDIRECT($A$12&"!A2:E100"),(INDIRECT($A$12&"!A2:A100")=$C17)*(INDIRECT($A$12&"!E2:E100")="Sem Técnico"))), 0)} | K17: =COUNTIF(INDIRECT("Monitoramento!$D$33:$P$39"), "Enviado") | L17: =COUNTIF(INDIRECT("Monitoramento!$D$33:$P$39"), "Atrasado") | M17: =COUNTIF(INDIRECT("Monitoramento!$D$33:$P$39"), "Atrasado >= 2") | N17: =COUNTIF(INDIRECT("Monitoramento!$D$33:$P$39"), "Duplicado") | O17: =COUNTIF(INDIRECT("Monitoramento!$D$33:$P$39"), "Outras Ocorrências") | P17: =COUNTIF(INDIRECT("Monitoramento!$D$33:$P$39"), "Sem Técnico") | R17: Duplicados | S17: =VLOOKUP($T$12,$C$14:$I$18,5,FALSE) | T17: =S17/SUM($S$14:$S$19)
C18: Londrina | D18: {=IFERROR(ROWS(_xlfn._xlws.FILTER(INDIRECT($A$12&"!A2:E100"),(INDIRECT($A$12&"!A2:A100")=$C18)*(INDIRECT($A$12&"!E2:E100")="Enviado"))), 0)} | E18: {=IFERROR(ROWS(_xlfn._xlws.FILTER(INDIRECT($A$12&"!A2:E100"),(INDIRECT($A$12&"!A2:A100")=$C18)*(INDIRECT($A$12&"!E2:E100")="Atrasado"))), 0)} | F18: {=IFERROR(ROWS(_xlfn._xlws.FILTER(INDIRECT($A$12&"!A2:E100"),(INDIRECT($A$12&"!A2:A100")=$C18)*(INDIRECT($A$12&"!E2:E100")="Atrasado >= 2"))), 0)} | G18: {=IFERROR(ROWS(_xlfn._xlws.FILTER(INDIRECT($A$12&"!A2:E100"),(INDIRECT($A$12&"!A2:A100")=$C18)*(INDIRECT($A$12&"!E2:E100")="Duplicado"))), 0)} | H18: {=IFERROR(ROWS(_xlfn._xlws.FILTER(INDIRECT($A$12&"!A2:E100"),(INDIRECT($A$12&"!A2:A100")=$C18)*(INDIRECT($A$12&"!E2:E100")="Outras Ocorrências"))), 0)} | I18: {=IFERROR(ROWS(_xlfn._xlws.FILTER(INDIRECT($A$12&"!A2:E100"),(INDIRECT($A$12&"!A2:A100")=$C18)*(INDIRECT($A$12&"!E2:E100")="Sem Técnico"))), 0)} | K18: =COUNTIF(INDIRECT("Monitoramento!$D$42:$P$49"), "Enviado") | L18: =COUNTIF(INDIRECT("Monitoramento!$D$42:$P$49"), "Atrasado") | M18: =COUNTIF(INDIRECT("Monitoramento!$D$42:$P$49"), "Atrasado >= 2") | N18: =COUNTIF(INDIRECT("Monitoramento!$D$42:$P$49"), "Duplicado") | O18: =COUNTIF(INDIRECT("Monitoramento!$D$42:$P$49"), "Outras Ocorrências") | P18: =COUNTIF(INDIRECT("Monitoramento!$D$42:$P$49"), "Sem Técnico") | R18: Outas Ocorrências | S18: =VLOOKUP($T$12,$C$14:$I$18,6,FALSE) | T18: =S18/SUM($S$14:$S$19)
C19: Maringá | D19: {=IFERROR(ROWS(_xlfn._xlws.FILTER(INDIRECT($A$12&"!A2:E100"),(INDIRECT($A$12&"!A2:A100")=$C19)*(INDIRECT($A$12&"!E2:E100")="Enviado"))), 0)} | E19: {=IFERROR(ROWS(_xlfn._xlws.FILTER(INDIRECT($A$12&"!A2:E100"),(INDIRECT($A$12&"!A2:A100")=$C19)*(INDIRECT($A$12&"!E2:E100")="Atrasado"))), 0)} | F19: {=IFERROR(ROWS(_xlfn._xlws.FILTER(INDIRECT($A$12&"!A2:E100"),(INDIRECT($A$12&"!A2:A100")=$C19)*(INDIRECT($A$12&"!E2:E100")="Atrasado >= 2"))), 0)} | G19: {=IFERROR(ROWS(_xlfn._xlws.FILTER(INDIRECT($A$12&"!A2:E100"),(INDIRECT($A$12&"!A2:A100")=$C19)*(INDIRECT($A$12&"!E2:E100")="Duplicado"))), 0)} | H19: {=IFERROR(ROWS(_xlfn._xlws.FILTER(INDIRECT($A$12&"!A2:E100"),(INDIRECT($A$12&"!A2:A100")=$C19)*(INDIRECT($A$12&"!E2:E100")="Outras Ocorrências"))), 0)} | I19: {=IFERROR(ROWS(_xlfn._xlws.FILTER(INDIRECT($A$12&"!A2:E100"),(INDIRECT($A$12&"!A2:A100")=$C19)*(INDIRECT($A$12&"!E2:E100")="Sem Técnico"))), 0)} | K19: =COUNTIF(INDIRECT("Monitoramento!$D$52:$P$60"), "Enviado") | L19: =COUNTIF(INDIRECT("Monitoramento!$D$52:$P$60"), "Atrasado") | M19: =COUNTIF(INDIRECT("Monitoramento!$D$52:$P$60"), "Atrasado >= 2") | N19: =COUNTIF(INDIRECT("Monitoramento!$D$52:$P$60"), "Duplicado") | O19: =COUNTIF(INDIRECT("Monitoramento!$D$52:$P$60"), "Outras Ocorrências") | P19: =COUNTIF(INDIRECT("Monitoramento!$D$52:$P$60"), "Sem Técnico") | R19: Sem Técnico | S19: =VLOOKUP($T$12,$C$14:$I$18,7,FALSE) | T19: =S19/SUM($S$14:$S$19)
C20: Paranavaí | D20: {=IFERROR(ROWS(_xlfn._xlws.FILTER(INDIRECT($A$12&"!A2:E100"),(INDIRECT($A$12&"!A2:A100")=$C20)*(INDIRECT($A$12&"!E2:E100")="Enviado"))), 0)} | E20: {=IFERROR(ROWS(_xlfn._xlws.FILTER(INDIRECT($A$12&"!A2:E100"),(INDIRECT($A$12&"!A2:A100")=$C20)*(INDIRECT($A$12&"!E2:E100")="Atrasado"))), 0)} | F20: {=IFERROR(ROWS(_xlfn._xlws.FILTER(INDIRECT($A$12&"!A2:E100"),(INDIRECT($A$12&"!A2:A100")=$C20)*(INDIRECT($A$12&"!E2:E100")="Atrasado >= 2"))), 0)} | G20: {=IFERROR(ROWS(_xlfn._xlws.FILTER(INDIRECT($A$12&"!A2:E100"),(INDIRECT($A$12&"!A2:A100")=$C20)*(INDIRECT($A$12&"!E2:E100")="Duplicado"))), 0)} | H20: {=IFERROR(ROWS(_xlfn._xlws.FILTER(INDIRECT($A$12&"!A2:E100"),(INDIRECT($A$12&"!A2:A100")=$C20)*(INDIRECT($A$12&"!E2:E100")="Outras Ocorrências"))), 0)} | I20: {=IFERROR(ROWS(_xlfn._xlws.FILTER(INDIRECT($A$12&"!A2:E100"),(INDIRECT($A$12&"!A2:A100")=$C20)*(INDIRECT($A$12&"!E2:E100")="Sem Técnico"))), 0)} | K20: =COUNTIF(INDIRECT("Monitoramento!$D$63:$Q$70"), "Enviado") | L20: =COUNTIF(INDIRECT("Monitoramento!$D$63:$Q$70"), "Atrasado") | M20: =COUNTIF(INDIRECT("Monitoramento!$D$63:$Q$70"), "Atrasado >= 2") | N20: =COUNTIF(INDIRECT("Monitoramento!$D$63:$Q$70"), "Duplicado") | O20: =COUNTIF(INDIRECT("Monitoramento!$D$63:$Q$70"), "Outras Ocorrências") | P20: =COUNTIF(INDIRECT("Monitoramento!$D$63:$Q$70"), "Sem Técnico") | R20: % Validação | S20: =VLOOKUP($T$12,$C$23:$I$27,7,FALSE)
C21: Regionais (Validações) | K21: Regionais (Validações) | R21: Envios - Acumulado (Total)
C22: Regional | E22: Validados | G22: Não Validados | I22: % Val. | K22: Validados | M22: Não Validados | O22: % Validados | R22: Enviados | S22: =VLOOKUP($T$12,$C$13:$P$18,9,FALSE) | T22: =S22/SUM($S$22:$S$27)
C23: Curitiba | E23: {=IFERROR(ROWS(_xlfn._xlws.FILTER(INDIRECT($A$12&"!A2:E100"),(INDIRECT($A$12&"!A2:A100")=$C23)*(INDIRECT($A$12&"!G2:G100")="Sim"))), 0)} | G23: {=IFERROR(ROWS(_xlfn._xlws.FILTER(INDIRECT($A$12&"!A2:E100"),(INDIRECT($A$12&"!A2:A100")=$C23)*(INDIRECT($A$12&"!G2:G100")="Não")))-E14, 0)} | I23: =IFERROR(E23/SUM(E23:H23),0) | K23: =COUNTIF(INDIRECT("Regionais!D2:P14"), "Sim") | M23: =COUNTIF(INDIRECT("Regionais!D2:P14"), "Não")-SUM(L14:M14) | O23: =IFERROR(K23/SUM(K23:N23), 0) | R23: Atrasados | S23: =VLOOKUP($T$12,$C$13:$P$18,10,FALSE) | T23: =S23/SUM($S$22:$S$27)
C24: Francisco Beltrão | E24: {=IFERROR(ROWS(_xlfn._xlws.FILTER(INDIRECT($A$12&"!A2:E100"),(INDIRECT($A$12&"!A2:A100")=$C24)*(INDIRECT($A$12&"!G2:G100")="Sim"))), 0)} | G24: {=IFERROR(ROWS(_xlfn._xlws.FILTER(INDIRECT($A$12&"!A2:E100"),(INDIRECT($A$12&"!A2:A100")=$C24)*(INDIRECT($A$12&"!G2:G100")="Não")))-E15, 0)} | I24: =IFERROR(E24/SUM(E24:H24),0) | K24: =COUNTIF(INDIRECT("Regionais!D17:P26"), "Sim") | M24: =COUNTIF(INDIRECT("Regionais!D17:P26"), "Não")-SUM(L15:M15) | O24: =IFERROR(K24/SUM(K24:N24), 0) | R24: Atrasados >= 2 | S24: =VLOOKUP($T$12,$C$13:$P$18,11,FALSE) | T24: =S24/SUM($S$22:$S$27)
C25: Guarapuava I | E25: {=IFERROR(ROWS(_xlfn._xlws.FILTER(INDIRECT($A$12&"!A2:E100"),(INDIRECT($A$12&"!A2:A100")=$C25)*(INDIRECT($A$12&"!G2:G100")="Sim"))), 0)} | G25: {=IFERROR(ROWS(_xlfn._xlws.FILTER(INDIRECT($A$12&"!A2:E100"),(INDIRECT($A$12&"!A2:A100")=$C25)*(INDIRECT($A$12&"!G2:G100")="Não")))-E16, 0)} | I25: =IFERROR(E25/SUM(E25:H25),0) | K25: =COUNTIF(INDIRECT("Regionais!D29:P30"), "Sim") | M25: =COUNTIF(INDIRECT("Regionais!D29:P30"), "Não")-SUM(L16:M16) | O25: =IFERROR(K25/SUM(K25:N25), 0) | R25: Duplicados | S25: =VLOOKUP($T$12,$C$13:$P$18,12,FALSE) | T25: =S25/SUM($S$22:$S$27)
C26: Guarapuava II | E26: {=IFERROR(ROWS(_xlfn._xlws.FILTER(INDIRECT($A$12&"!A2:E100"),(INDIRECT($A$12&"!A2:A100")=$C26)*(INDIRECT($A$12&"!G2:G100")="Sim"))), 0)} | G26: {=IFERROR(ROWS(_xlfn._xlws.FILTER(INDIRECT($A$12&"!A2:E100"),(INDIRECT($A$12&"!A2:A100")=$C26)*(INDIRECT($A$12&"!G2:G100")="Não")))-E17, 0)} | I26: =IFERROR(E26/SUM(E26:H26),0) | K26: =COUNTIF(INDIRECT("Regionais!D33:P39"), "Sim") | M26: =COUNTIF(INDIRECT("Regionais!D33:P39"), "Não")-SUM(L17:M17) | O26: =IFERROR(K26/SUM(K26:N26), 0) | R26: Outas Ocorrências | S26: =VLOOKUP($T$12,$C$13:$P$18,13,FALSE) | T26: =S26/SUM($S$22:$S$27)
C27: Londrina | E27: {=IFERROR(ROWS(_xlfn._xlws.FILTER(INDIRECT($A$12&"!A2:E100"),(INDIRECT($A$12&"!A2:A100")=$C27)*(INDIRECT($A$12&"!G2:G100")="Sim"))), 0)} | G27: {=IFERROR(ROWS(_xlfn._xlws.FILTER(INDIRECT($A$12&"!A2:E100"),(INDIRECT($A$12&"!A2:A100")=$C27)*(INDIRECT($A$12&"!G2:G100")="Não")))-E18, 0)} | I27: =IFERROR(E27/SUM(E27:H27),0) | K27: =COUNTIF(INDIRECT("Regionais!D42:P49"), "Sim") | M27: =COUNTIF(INDIRECT("Regionais!D42:P49"), "Não")-SUM(L18:M18) | O27: =IFERROR(K27/SUM(K27:N27), 0) | R27: Sem Técnico | S27: =VLOOKUP($T$12,$C$13:$P$18,14,FALSE) | T27: =S27/SUM($S$22:$S$27)
C28: Maringá | E28: {=IFERROR(ROWS(_xlfn._xlws.FILTER(INDIRECT($A$12&"!A2:E100"),(INDIRECT($A$12&"!A2:A100")=$C28)*(INDIRECT($A$12&"!G2:G100")="Sim"))), 0)} | G28: {=IFERROR(ROWS(_xlfn._xlws.FILTER(INDIRECT($A$12&"!A2:E100"),(INDIRECT($A$12&"!A2:A100")=$C28)*(INDIRECT($A$12&"!G2:G100")="Não")))-E19, 0)} | I28: =IFERROR(E28/SUM(E28:H28),0) | K28: =COUNTIF(INDIRECT("Regionais!D52:P60"), "Sim") | M28: =COUNTIF(INDIRECT("Regionais!D52:P60"), "Não")-SUM(L19:M19) | O28: =IFERROR(K28/SUM(K28:N28), 0) | R28: % Validação | S28: =VLOOKUP($T$12,$C$22:$P$29,13,FALSE)
C29: Paranavaí | E29: {=IFERROR(ROWS(_xlfn._xlws.FILTER(INDIRECT($A$12&"!A2:E100"),(INDIRECT($A$12&"!A2:A100")=$C29)*(INDIRECT($A$12&"!G2:G100")="Sim"))), 0)} | G29: {=IFERROR(ROWS(_xlfn._xlws.FILTER(INDIRECT($A$12&"!A2:E100"),(INDIRECT($A$12&"!A2:A100")=$C29)*(INDIRECT($A$12&"!G2:G100")="Não")))-E20, 0)} | I29: =IFERROR(E29/SUM(E29:H29),0) | K29: =COUNTIF(INDIRECT("Regionais!D63:P70"), "Sim") | M29: =COUNTIF(INDIRECT("Regionais!D63:P70"), "Não")-SUM(L20:M20) | O29: =IFERROR(K29/SUM(K29:N29), 0)
C33: Formulários | E33: Enviado | F33: Atrasado | G33: Sem Téc | H33: Outras | I33: Total
C34: 4 - Receitas (11/24) | E34: - | F34: - | G34: - | H34: -
C35: 4 - Receitas (12/24) | E35: - | F35: - | G35: - | H35: -
C36: 4 - Receitas (01/25) | E36: =B$2+B$5 | F36: =B$3+B$4 | G36: =B$7 | H36: =B6 | I36: =SUM(E36:H36)
C37: 4 - Receitas (02/25) | E37: =C$2+C$5 | F37: =C$3+C$4 | G37: =C$7 | H37: =C$6 | I37: =SUM(E37:H37)
C38: 4 - Receitas (03/25) | E38: =D$2+D$5 | F38: =D$3+D$4 | G38: =D$7 | H38: =D$6 | I38: =SUM(E38:H38)
C39: 4 - Receitas (04/25) | E39: =E$2+E$5 | F39: =E$3+E$4 | G39: =E$7 | H39: =E$6 | I39: =SUM(E39:H39)
C40: 4 - Receitas (05/25) | E40: =F$2+F$5 | F40: =F$3+F$4 | G40: =F$7 | H40: =F$6 | I40: =SUM(E40:H40)
C41: 4 - Receitas (06/25) | E41: =G$2+G$5 | F41: =G$3+G$4 | G41: =G$7 | H41: =G$6 | I41: =SUM(E41:H41)
C42: 4 - Receitas (07/25) | E42: =H$2+H$5 | F42: =H$3+H$4 | G42: =H$7 | H42: =H$6 | I42: =SUM(E42:H42)
C43: 4 - Receitas (08/25) | E43: =I$2+I$5 | F43: =I$3+I$4 | G43: =I$7 | H43: =I$6 | I43: =SUM(E43:H43)
C44: 4 - Receitas (09/25) | E44: =J$2+J$5 | F44: =J$3+J$4 | G44: =J$7 | H44: =J$6 | I44: =SUM(E44:H44)
C45: 4 - Receitas (10/25) | E45: =K$2+K$5 | F45: =K$3+K$4 | G45: =K$7 | H45: =K$6 | I45: =SUM(E45:H45)
C46: 4 - Receitas (11/25) | E46: =L$2+L$5 | F46: =L$3+L$4 | G46: =L$7 | H46: =L$6 | I46: =SUM(E46:H46)
C47: 4 - Receitas (12/25) | E47: =M$2+M$5 | F47: =M$3+M$4 | G47: =M$7 | H47: =M$6 | I47: =SUM(E47:H47)

Sheet Monitoramento
A1: Kelly | B1: Municípios | C1: UVR | D1: 01.25 | E1: 02.25 | F1: 03.25 | G1: 04.25 | H1: 05.25 | I1: 06.25 | J1: 07.25 | K1: 08.25 | L1: 09.25 | M1: 10.25 | N1: 11.25 | O1: 12.25
A2: Curitiba | B2: Campo Largo | C2: 01 | D2: {=IF( VLOOKUP( $A2, _xlfn._xlws.FILTER( INDIRECT("'"&D$62&"'!A2:E1000"), (INDIRECT("'"&D$62&"'!B2:B1000")=$B2) * (INDIRECT("'"&D$62&"'!C2:C1000")=$C2) ), 5, FALSE )=0, "", VLOOKUP( $A2, _xlfn._xlws.FILTER( INDIRECT("'"&D$62&"'!A2:E1000"), (INDIRECT("'"&D$62&"'!B2:B1000")=$B2) * (INDIRECT("'"&D$62&"'!C2:C1000")=$C2) ), 5, FALSE ) )} | E2: {=IF( VLOOKUP( $A2, _xlfn._xlws.FILTER( INDIRECT("'"&E$62&"'!A2:E1000"), (INDIRECT("'"&E$62&"'!B2:B1000")=$B2) * (INDIRECT("'"&E$62&"'!C2:C1000")=$C2) ), 5, FALSE )=0, "", VLOOKUP( $A2, _xlfn._xlws.FILTER( INDIRECT("'"&E$62&"'!A2:E1000"), (INDIRECT("'"&E$62&"'!B2:B1000")=$B2) * (INDIRECT("'"&E$62&"'!C2:C1000")=$C2) ), 5, FALSE ) )} | F2: {=IF( VLOOKUP( $A2, _xlfn._xlws.FILTER( INDIRECT("'"&F$62&"'!A2:E1000"), (INDIRECT("'"&F$62&"'!B2:B1000")=$B2) * (INDIRECT("'"&F$62&"'!C2:C1000")=$C2) ), 5, FALSE )=0, "", VLOOKUP( $A2, _xlfn._xlws.FILTER( INDIRECT("'"&F$62&"'!A2:E1000"), (INDIRECT("'"&F$62&"'!B2:B1000")=$B2) * (INDIRECT("'"&F$62&"'!C2:C1000")=$C2) ), 5, FALSE ) )} | G2: {=IF( VLOOKUP( $A2, _xlfn._xlws.FILTER( INDIRECT("'"&G$62&"'!A2:E1000"), (INDIRECT("'"&G$62&"'!B2:B1000")=$B2) * (INDIRECT("'"&G$62&"'!C2:C1000")=$C2) ), 5, FALSE )=0, "", VLOOKUP( $A2, _xlfn._xlws.FILTER( INDIRECT("'"&G$62&"'!A2:E1000"), (INDIRECT("'"&G$62&"'!B2:B1000")=$B2) * (INDIRECT("'"&G$62&"'!C2:C1000")=$C2) ), 5, FALSE ) )} | H2: {=IF( VLOOKUP( $A2, _xlfn._xlws.FILTER( INDIRECT("'"&H$62&"'!A2:E1000"), (INDIRECT("'"&H$62&"'!B2:B1000")=$B2) * (INDIRECT("'"&H$62&"'!C2:C1000")=$C2) ), 5, FALSE )=0, "", VLOOKUP( $A2, _xlfn._xlws.FILTER( INDIRECT("'"&H$62&"'!A2:E1000"), (INDIRECT("'"&H$62&"'!B2:B1000")=$B2) * (INDIRECT("'"&H$62&"'!C2:C1000")=$C2) ), 5, FALSE ) )} | I2: {=IF( VLOOKUP( $A2, _xlfn._xlws.FILTER( INDIRECT("'"&I$62&"'!A2:E1000"), (INDIRECT("'"&I$62&"'!B2:B1000")=$B2) * (INDIRECT("'"&I$62&"'!C2:C1000")=$C2) ), 5, FALSE )=0, "", VLOOKUP( $A2, _xlfn._xlws.FILTER( INDIRECT("'"&I$62&"'!A2:E1000"), (INDIRECT("'"&I$62&"'!B2:B1000")=$B2) * (INDIRECT("'"&I$62&"'!C2:C1000")=$C2) ), 5, FALSE ) )} | J2: {=IF( VLOOKUP( $A2, _xlfn._xlws.FILTER( INDIRECT("'"&J$62&"'!A2:E1000"), (INDIRECT("'"&J$62&"'!B2:B1000")=$B2) * (INDIRECT("'"&J$62&"'!C2:C1000")=$C2) ), 5, FALSE )=0, "", VLOOKUP( $A2, _xlfn._xlws.FILTER( INDIRECT("'"&J$62&"'!A2:E1000"), (INDIRECT("'"&J$62&"'!B2:B1000")=$B2) * (INDIRECT("'"&J$62&"'!C2:C1000")=$C2) ), 5, FALSE ) )} | K2: {=IF( VLOOKUP( $A2, _xlfn._xlws.FILTER( INDIRECT("'"&K$62&"'!A2:E1000"), (INDIRECT("'"&K$62&"'!B2:B1000")=$B2) * (INDIRECT("'"&K$62&"'!C2:C1000")=$C2) ), 5, FALSE )=0, "", VLOOKUP( $A2, _xlfn._xlws.FILTER( INDIRECT("'"&K$62&"'!A2:E1000"), (INDIRECT("'"&K$62&"'!B2:B1000")=$B2) * (INDIRECT("'"&K$62&"'!C2:C1000")=$C2) ), 5, FALSE ) )} | ... O2: {=IF( VLOOKUP( $A2, _xlfn._xlws.FILTER( INDIRECT("'"&O$62&"'!A2:E1000"), (INDIRECT("'"&O$62&"'!B2:B1000")=$B2) * (INDIRECT("'"&O$62&"'!C2:C1000")=$C2) ), 5, FALSE )=0, "", VLOOKUP( $A2, _xlfn._xlws.FILTER( INDIRECT("'"&O$62&"'!A2:E1000"), (INDIRECT("'"&O$62&"'!B2:B1000")=$B2) * (INDIRECT("'"&O$62&"'!C2:C1000")=$C2) ), 5, FALSE ) )}
A3: Curitiba | B3: Campo Largo | C3: 02 | D3: {=IF( VLOOKUP( $A3, _xlfn._xlws.FILTER( INDIRECT("'"&D$62&"'!A2:E1000"), (INDIRECT("'"&D$62&"'!B2:B1000")=$B3) * (INDIRECT("'"&D$62&"'!C2:C1000")=$C3) ), 5, FALSE )=0, "", VLOOKUP( $A3, _xlfn._xlws.FILTER( INDIRECT("'"&D$62&"'!A2:E1000"), (INDIRECT("'"&D$62&"'!B2:B1000")=$B3) * (INDIRECT("'"&D$62&"'!C2:C1000")=$C3) ), 5, FALSE ) )} | E3: {=IF( VLOOKUP( $A3, _xlfn._xlws.FILTER( INDIRECT("'"&E$62&"'!A2:E1000"), (INDIRECT("'"&E$62&"'!B2:B1000")=$B3) * (INDIRECT("'"&E$62&"'!C2:C1000")=$C3) ), 5, FALSE )=0, "", VLOOKUP( $A3, _xlfn._xlws.FILTER( INDIRECT("'"&E$62&"'!A2:E1000"), (INDIRECT("'"&E$62&"'!B2:B1000")=$B3) * (INDIRECT("'"&E$62&"'!C2:C1000")=$C3) ), 5, FALSE ) )} | F3: {=IF( VLOOKUP( $A3, _xlfn._xlws.FILTER( INDIRECT("'"&F$62&"'!A2:E1000"), (INDIRECT("'"&F$62&"'!B2:B1000")=$B3) * (INDIRECT("'"&F$62&"'!C2:C1000")=$C3) ), 5, FALSE )=0, "", VLOOKUP( $A3, _xlfn._xlws.FILTER( INDIRECT("'"&F$62&"'!A2:E1000"), (INDIRECT("'"&F$62&"'!B2:B1000")=$B3) * (INDIRECT("'"&F$62&"'!C2:C1000")=$C3) ), 5, FALSE ) )} | G3: {=IF( VLOOKUP( $A3, _xlfn._xlws.FILTER( INDIRECT("'"&G$62&"'!A2:E1000"), (INDIRECT("'"&G$62&"'!B2:B1000")=$B3) * (INDIRECT("'"&G$62&"'!C2:C1000")=$C3) ), 5, FALSE )=0, "", VLOOKUP( $A3, _xlfn._xlws.FILTER( INDIRECT("'"&G$62&"'!A2:E1000"), (INDIRECT("'"&G$62&"'!B2:B1000")=$B3) * (INDIRECT("'"&G$62&"'!C2:C1000")=$C3) ), 5, FALSE ) )} | H3: {=IF( VLOOKUP( $A3, _xlfn._xlws.FILTER( INDIRECT("'"&H$62&"'!A2:E1000"), (INDIRECT("'"&H$62&"'!B2:B1000")=$B3) * (INDIRECT("'"&H$62&"'!C2:C1000")=$C3) ), 5, FALSE )=0, "", VLOOKUP( $A3, _xlfn._xlws.FILTER( INDIRECT("'"&H$62&"'!A2:E1000"), (INDIRECT("'"&H$62&"'!B2:B1000")=$B3) * (INDIRECT("'"&H$62&"'!C2:C1000")=$C3) ), 5, FALSE ) )} | I3: {=IF( VLOOKUP( $A3, _xlfn._xlws.FILTER( INDIRECT("'"&I$62&"'!A2:E1000"), (INDIRECT("'"&I$62&"'!B2:B1000")=$B3) * (INDIRECT("'"&I$62&"'!C2:C1000")=$C3) ), 5, FALSE )=0, "", VLOOKUP( $A3, _xlfn._xlws.FILTER( INDIRECT("'"&I$62&"'!A2:E1000"), (INDIRECT("'"&I$62&"'!B2:B1000")=$B3) * (INDIRECT("'"&I$62&"'!C2:C1000")=$C3) ), 5, FALSE ) )} | J3: {=IF( VLOOKUP( $A3, _xlfn._xlws.FILTER( INDIRECT("'"&J$62&"'!A2:E1000"), (INDIRECT("'"&J$62&"'!B2:B1000")=$B3) * (INDIRECT("'"&J$62&"'!C2:C1000")=$C3) ), 5, FALSE )=0, "", VLOOKUP( $A3, _xlfn._xlws.FILTER( INDIRECT("'"&J$62&"'!A2:E1000"), (INDIRECT("'"&J$62&"'!B2:B1000")=$B3) * (INDIRECT("'"&J$62&"'!C2:C1000")=$C3) ), 5, FALSE ) )} | K3: {=IF( VLOOKUP( $A3, _xlfn._xlws.FILTER( INDIRECT("'"&K$62&"'!A2:E1000"), (INDIRECT("'"&K$62&"'!B2:B1000")=$B3) * (INDIRECT("'"&K$62&"'!C2:C1000")=$C3) ), 5, FALSE )=0, "", VLOOKUP( $A3, _xlfn._xlws.FILTER( INDIRECT("'"&K$62&"'!A2:E1000"), (INDIRECT("'"&K$62&"'!B2:B1000")=$B3) * (INDIRECT("'"&K$62&"'!C2:C1000")=$C3) ), 5, FALSE ) )} | ... O3: {=IF( VLOOKUP( $A3, _xlfn._xlws.FILTER( INDIRECT("'"&O$62&"'!A2:E1000"), (INDIRECT("'"&O$62&"'!B2:B1000")=$B3) * (INDIRECT("'"&O$62&"'!C2:C1000")=$C3) ), 5, FALSE )=0, "", VLOOKUP( $A3, _xlfn._xlws.FILTER( INDIRECT("'"&O$62&"'!A2:E1000"), (INDIRECT("'"&O$62&"'!B2:B1000")=$B3) * (INDIRECT("'"&O$62&"'!C2:C1000")=$C3) ), 5, FALSE ) )}
A4: Curitiba | B4: Campo Largo | C4: 03 | D4: {=IF( VLOOKUP( $A4, _xlfn._xlws.FILTER( INDIRECT("'"&D$62&"'!A2:E1000"), (INDIRECT("'"&D$62&"'!B2:B1000")=$B4) * (INDIRECT("'"&D$62&"'!C2:C1000")=$C4) ), 5, FALSE )=0, "", VLOOKUP( $A4, _xlfn._xlws.FILTER( INDIRECT("'"&D$62&"'!A2:E1000"), (INDIRECT("'"&D$62&"'!B2:B1000")=$B4) * (INDIRECT("'"&D$62&"'!C2:C1000")=$C4) ), 5, FALSE ) )} | E4: {=IF( VLOOKUP( $A4, _xlfn._xlws.FILTER( INDIRECT("'"&E$62&"'!A2:E1000"), (INDIRECT("'"&E$62&"'!B2:B1000")=$B4) * (INDIRECT("'"&E$62&"'!C2:C1000")=$C4) ), 5, FALSE )=0, "", VLOOKUP( $A4, _xlfn._xlws.FILTER( INDIRECT("'"&E$62&"'!A2:E1000"), (INDIRECT("'"&E$62&"'!B2:B1000")=$B4) * (INDIRECT("'"&E$62&"'!C2:C1000")=$C4) ), 5, FALSE ) )} | F4: {=IF( VLOOKUP( $A4, _xlfn._xlws.FILTER( INDIRECT("'"&F$62&"'!A2:E1000"), (INDIRECT("'"&F$62&"'!B2:B1000")=$B4) * (INDIRECT("'"&F$62&"'!C2:C1000")=$C4) ), 5, FALSE )=0, "", VLOOKUP( $A4, _xlfn._xlws.FILTER( INDIRECT("'"&F$62&"'!A2:E1000"), (INDIRECT("'"&F$62&"'!B2:B1000")=$B4) * (INDIRECT("'"&F$62&"'!C2:C1000")=$C4) ), 5, FALSE ) )} | G4: {=IF( VLOOKUP( $A4, _xlfn._xlws.FILTER( INDIRECT("'"&G$62&"'!A2:E1000"), (INDIRECT("'"&G$62&"'!B2:B1000")=$B4) * (INDIRECT("'"&G$62&"'!C2:C1000")=$C4) ), 5, FALSE )=0, "", VLOOKUP( $A4, _xlfn._xlws.FILTER( INDIRECT("'"&G$62&"'!A2:E1000"), (INDIRECT("'"&G$62&"'!B2:B1000")=$B4) * (INDIRECT("'"&G$62&"'!C2:C1000")=$C4) ), 5, FALSE ) )} | H4: {=IF( VLOOKUP( $A4, _xlfn._xlws.FILTER( INDIRECT("'"&H$62&"'!A2:E1000"), (INDIRECT("'"&H$62&"'!B2:B1000")=$B4) * (INDIRECT("'"&H$62&"'!C2:C1000")=$C4) ), 5, FALSE )=0, "", VLOOKUP( $A4, _xlfn._xlws.FILTER( INDIRECT("'"&H$62&"'!A2:E1000"), (INDIRECT("'"&H$62&"'!B2:B1000")=$B4) * (INDIRECT("'"&H$62&"'!C2:C1000")=$C4) ), 5, FALSE ) )} | I4: {=IF( VLOOKUP( $A4, _xlfn._xlws.FILTER( INDIRECT("'"&I$62&"'!A2:E1000"), (INDIRECT("'"&I$62&"'!B2:B1000")=$B4) * (INDIRECT("'"&I$62&"'!C2:C1000")=$C4) ), 5, FALSE )=0, "", VLOOKUP( $A4, _xlfn._xlws.FILTER( INDIRECT("'"&I$62&"'!A2:E1000"), (INDIRECT("'"&I$62&"'!B2:B1000")=$B4) * (INDIRECT("'"&I$62&"'!C2:C1000")=$C4) ), 5, FALSE ) )} | J4: {=IF( VLOOKUP( $A4, _xlfn._xlws.FILTER( INDIRECT("'"&J$62&"'!A2:E1000"), (INDIRECT("'"&J$62&"'!B2:B1000")=$B4) * (INDIRECT("'"&J$62&"'!C2:C1000")=$C4) ), 5, FALSE )=0, "", VLOOKUP( $A4, _xlfn._xlws.FILTER( INDIRECT("'"&J$62&"'!A2:E1000"), (INDIRECT("'"&J$62&"'!B2:B1000")=$B4) * (INDIRECT("'"&J$62&"'!C2:C1000")=$C4) ), 5, FALSE ) )} | K4: {=IF( VLOOKUP( $A4, _xlfn._xlws.FILTER( INDIRECT("'"&K$62&"'!A2:E1000"), (INDIRECT("'"&K$62&"'!B2:B1000")=$B4) * (INDIRECT("'"&K$62&"'!C2:C1000")=$C4) ), 5, FALSE )=0, "", VLOOKUP( $A4, _xlfn._xlws.FILTER( INDIRECT("'"&K$62&"'!A2:E1000"), (INDIRECT("'"&K$62&"'!B2:B1000")=$B4) * (INDIRECT("'"&K$62&"'!C2:C1000")=$C4) ), 5, FALSE ) )} | ... O4: {=IF( VLOOKUP( $A4, _xlfn._xlws.FILTER( INDIRECT("'"&O$62&"'!A2:E1000"), (INDIRECT("'"&O$62&"'!B2:B1000")=$B4) * (INDIRECT("'"&O$62&"'!C2:C1000")=$C4) ), 5, FALSE )=0, "", VLOOKUP( $A4, _xlfn._xlws.FILTER( INDIRECT("'"&O$62&"'!A2:E1000"), (INDIRECT("'"&O$62&"'!B2:B1000")=$B4) * (INDIRECT("'"&O$62&"'!C2:C1000")=$C4) ), 5, FALSE ) )}
A5: Curitiba | B5: Campo Largo | C5: 04 | D5: {=IF( VLOOKUP( $A5, _xlfn._xlws.FILTER( INDIRECT("'"&D$62&"'!A2:E1000"), (INDIRECT("'"&D$62&"'!B2:B1000")=$B5) * (INDIRECT("'"&D$62&"'!C2:C1000")=$C5) ), 5, FALSE )=0, "", VLOOKUP( $A5, _xlfn._xlws.FILTER( INDIRECT("'"&D$62&"'!A2:E1000"), (INDIRECT("'"&D$62&"'!B2:B1000")=$B5) * (INDIRECT("'"&D$62&"'!C2:C1000")=$C5) ), 5, FALSE ) )} | E5: {=IF( VLOOKUP( $A5, _xlfn._xlws.FILTER( INDIRECT("'"&E$62&"'!A2:E1000"), (INDIRECT("'"&E$62&"'!B2:B1000")=$B5) * (INDIRECT("'"&E$62&"'!C2:C1000")=$C5) ), 5, FALSE )=0, "", VLOOKUP( $A5, _xlfn._xlws.FILTER( INDIRECT("'"&E$62&"'!A2:E1000"), (INDIRECT("'"&E$62&"'!B2:B1000")=$B5) * (INDIRECT("'"&E$62&"'!C2:C1000")=$C5) ), 5, FALSE ) )} | F5: {=IF( VLOOKUP( $A5, _xlfn._xlws.FILTER( INDIRECT("'"&F$62&"'!A2:E1000"), (INDIRECT("'"&F$62&"'!B2:B1000")=$B5) * (INDIRECT("'"&F$62&"'!C2:C1000")=$C5) ), 5, FALSE )=0, "", VLOOKUP( $A5, _xlfn._xlws.FILTER( INDIRECT("'"&F$62&"'!A2:E1000"), (INDIRECT("'"&F$62&"'!B2:B1000")=$B5) * (INDIRECT("'"&F$62&"'!C2:C1000")=$C5) ), 5, FALSE ) )} | G5: {=IF( VLOOKUP( $A5, _xlfn._xlws.FILTER( INDIRECT("'"&G$62&"'!A2:E1000"), (INDIRECT("'"&G$62&"'!B2:B1000")=$B5) * (INDIRECT("'"&G$62&"'!C2:C1000")=$C5) ), 5, FALSE )=0, "", VLOOKUP( $A5, _xlfn._xlws.FILTER( INDIRECT("'"&G$62&"'!A2:E1000"), (INDIRECT("'"&G$62&"'!B2:B1000")=$B5) * (INDIRECT("'"&G$62&"'!C2:C1000")=$C5) ), 5, FALSE ) )} | H5: {=IF( VLOOKUP( $A5, _xlfn._xlws.FILTER( INDIRECT("'"&H$62&"'!A2:E1000"), (INDIRECT("'"&H$62&"'!B2:B1000")=$B5) * (INDIRECT("'"&H$62&"'!C2:C1000")=$C5) ), 5, FALSE )=0, "", VLOOKUP( $A5, _xlfn._xlws.FILTER( INDIRECT("'"&H$62&"'!A2:E1000"), (INDIRECT("'"&H$62&"'!B2:B1000")=$B5) * (INDIRECT("'"&H$62&"'!C2:C1000")=$C5) ), 5, FALSE ) )} | I5: {=IF( VLOOKUP( $A5, _xlfn._xlws.FILTER( INDIRECT("'"&I$62&"'!A2:E1000"), (INDIRECT("'"&I$62&"'!B2:B1000")=$B5) * (INDIRECT("'"&I$62&"'!C2:C1000")=$C5) ), 5, FALSE )=0, "", VLOOKUP( $A5, _xlfn._xlws.FILTER( INDIRECT("'"&I$62&"'!A2:E1000"), (INDIRECT("'"&I$62&"'!B2:B1000")=$B5) * (INDIRECT("'"&I$62&"'!C2:C1000")=$C5) ), 5, FALSE ) )} | J5: {=IF( VLOOKUP( $A5, _xlfn._xlws.FILTER( INDIRECT("'"&J$62&"'!A2:E1000"), (INDIRECT("'"&J$62&"'!B2:B1000")=$B5) * (INDIRECT("'"&J$62&"'!C2:C1000")=$C5) ), 5, FALSE )=0, "", VLOOKUP( $A5, _xlfn._xlws.FILTER( INDIRECT("'"&J$62&"'!A2:E1000"), (INDIRECT("'"&J$62&"'!B2:B1000")=$B5) * (INDIRECT("'"&J$62&"'!C2:C1000")=$C5) ), 5, FALSE ) )} | K5: {=IF( VLOOKUP( $A5, _xlfn._xlws.FILTER( INDIRECT("'"&K$62&"'!A2:E1000"), (INDIRECT("'"&K$62&"'!B2:B1000")=$B5) * (INDIRECT("'"&K$62&"'!C2:C1000")=$C5) ), 5, FALSE )=0, "", VLOOKUP( $A5, _xlfn._xlws.FILTER( INDIRECT("'"&K$62&"'!A2:E1000"), (INDIRECT("'"&K$62&"'!B2:B1000")=$B5) * (INDIRECT("'"&K$62&"'!C2:C1000")=$C5) ), 5, FALSE ) )} | ... O5: {=IF( VLOOKUP( $A5, _xlfn._xlws.FILTER( INDIRECT("'"&O$62&"'!A2:E1000"), (INDIRECT("'"&O$62&"'!B2:B1000")=$B5) * (INDIRECT("'"&O$62&"'!C2:C1000")=$C5) ), 5, FALSE )=0, "", VLOOKUP( $A5, _xlfn._xlws.FILTER( INDIRECT("'"&O$62&"'!A2:E1000"), (INDIRECT("'"&O$62&"'!B2:B1000")=$B5) * (INDIRECT("'"&O$62&"'!C2:C1000")=$C5) ), 5, FALSE ) )}
A6: Curitiba | B6: Campo Largo | C6: 05 | D6: {=IF( VLOOKUP( $A6, _xlfn._xlws.FILTER( INDIRECT("'"&D$62&"'!A2:E1000"), (INDIRECT("'"&D$62&"'!B2:B1000")=$B6) * (INDIRECT("'"&D$62&"'!C2:C1000")=$C6) ), 5, FALSE )=0, "", VLOOKUP( $A6, _xlfn._xlws.FILTER( INDIRECT("'"&D$62&"'!A2:E1000"), (INDIRECT("'"&D$62&"'!B2:B1000")=$B6) * (INDIRECT("'"&D$62&"'!C2:C1000")=$C6) ), 5, FALSE ) )} | E6: {=IF( VLOOKUP( $A6, _xlfn._xlws.FILTER( INDIRECT("'"&E$62&"'!A2:E1000"), (INDIRECT("'"&E$62&"'!B2:B1000")=$B6) * (INDIRECT("'"&E$62&"'!C2:C1000")=$C6) ), 5, FALSE )=0, "", VLOOKUP( $A6, _xlfn._xlws.FILTER( INDIRECT("'"&E$62&"'!A2:E1000"), (INDIRECT("'"&E$62&"'!B2:B1000")=$B6) * (INDIRECT("'"&E$62&"'!C2:C1000")=$C6) ), 5, FALSE ) )} | F6: {=IF( VLOOKUP( $A6, _xlfn._xlws.FILTER( INDIRECT("'"&F$62&"'!A2:E1000"), (INDIRECT("'"&F$62&"'!B2:B1000")=$B6) * (INDIRECT("'"&F$62&"'!C2:C1000")=$C6) ), 5, FALSE )=0, "", VLOOKUP( $A6, _xlfn._xlws.FILTER( INDIRECT("'"&F$62&"'!A2:E1000"), (INDIRECT("'"&F$62&"'!B2:B1000")=$B6) * (INDIRECT("'"&F$62&"'!C2:C1000")=$C6) ), 5, FALSE ) )} | G6: {=IF( VLOOKUP( $A6, _xlfn._xlws.FILTER( INDIRECT("'"&G$62&"'!A2:E1000"), (INDIRECT("'"&G$62&"'!B2:B1000")=$B6) * (INDIRECT("'"&G$62&"'!C2:C1000")=$C6) ), 5, FALSE )=0, "", VLOOKUP( $A6, _xlfn._xlws.FILTER( INDIRECT("'"&G$62&"'!A2:E1000"), (INDIRECT("'"&G$62&"'!B2:B1000")=$B6) * (INDIRECT("'"&G$62&"'!C2:C1000")=$C6) ), 5, FALSE ) )} | H6: {=IF( VLOOKUP( $A6, _xlfn._xlws.FILTER( INDIRECT("'"&H$62&"'!A2:E1000"), (INDIRECT("'"&H$62&"'!B2:B1000")=$B6) * (INDIRECT("'"&H$62&"'!C2:C1000")=$C6) ), 5, FALSE )=0, "", VLOOKUP( $A6, _xlfn._xlws.FILTER( INDIRECT("'"&H$62&"'!A2:E1000"), (INDIRECT("'"&H$62&"'!B2:B1000")=$B6) * (INDIRECT("'"&H$62&"'!C2:C1000")=$C6) ), 5, FALSE ) )} | I6: {=IF( VLOOKUP( $A6, _xlfn._xlws.FILTER( INDIRECT("'"&I$62&"'!A2:E1000"), (INDIRECT("'"&I$62&"'!B2:B1000")=$B6) * (INDIRECT("'"&I$62&"'!C2:C1000")=$C6) ), 5, FALSE )=0, "", VLOOKUP( $A6, _xlfn._xlws.FILTER( INDIRECT("'"&I$62&"'!A2:E1000"), (INDIRECT("'"&I$62&"'!B2:B1000")=$B6) * (INDIRECT("'"&I$62&"'!C2:C1000")=$C6) ), 5, FALSE ) )} | J6: {=IF( VLOOKUP( $A6, _xlfn._xlws.FILTER( INDIRECT("'"&J$62&"'!A2:E1000"), (INDIRECT("'"&J$62&"'!B2:B1000")=$B6) * (INDIRECT("'"&J$62&"'!C2:C1000")=$C6) ), 5, FALSE )=0, "", VLOOKUP( $A6, _xlfn._xlws.FILTER( INDIRECT("'"&J$62&"'!A2:E1000"), (INDIRECT("'"&J$62&"'!B2:B1000")=$B6) * (INDIRECT("'"&J$62&"'!C2:C1000")=$C6) ), 5, FALSE ) )} | K6: {=IF( VLOOKUP( $A6, _xlfn._xlws.FILTER( INDIRECT("'"&K$62&"'!A2:E1000"), (INDIRECT("'"&K$62&"'!B2:B1000")=$B6) * (INDIRECT("'"&K$62&"'!C2:C1000")=$C6) ), 5, FALSE )=0, "", VLOOKUP( $A6, _xlfn._xlws.FILTER( INDIRECT("'"&K$62&"'!A2:E1000"), (INDIRECT("'"&K$62&"'!B2:B1000")=$B6) * (INDIRECT("'"&K$62&"'!C2:C1000")=$C6) ), 5, FALSE ) )} | ... O6: {=IF( VLOOKUP( $A6, _xlfn._xlws.FILTER( INDIRECT("'"&O$62&"'!A2:E1000"), (INDIRECT("'"&O$62&"'!B2:B1000")=$B6) * (INDIRECT("'"&O$62&"'!C2:C1000")=$C6) ), 5, FALSE )=0, "", VLOOKUP( $A6, _xlfn._xlws.FILTER( INDIRECT("'"&O$62&"'!A2:E1000"), (INDIRECT("'"&O$62&"'!B2:B1000")=$B6) * (INDIRECT("'"&O$62&"'!C2:C1000")=$C6) ), 5, FALSE ) )}
A7: Curitiba | B7: Campo Magro | C7: 01 | D7: {=IF( VLOOKUP( $A7, _xlfn._xlws.FILTER( INDIRECT("'"&D$62&"'!A2:E1000"), (INDIRECT("'"&D$62&"'!B2:B1000")=$B7) * (INDIRECT("'"&D$62&"'!C2:C1000")=$C7) ), 5, FALSE )=0, "", VLOOKUP( $A7, _xlfn._xlws.FILTER( INDIRECT("'"&D$62&"'!A2:E1000"), (INDIRECT("'"&D$62&"'!B2:B1000")=$B7) * (INDIRECT("'"&D$62&"'!C2:C1000")=$C7) ), 5, FALSE ) )} | E7: {=IF( VLOOKUP( $A7, _xlfn._xlws.FILTER( INDIRECT("'"&E$62&"'!A2:E1000"), (INDIRECT("'"&E$62&"'!B2:B1000")=$B7) * (INDIRECT("'"&E$62&"'!C2:C1000")=$C7) ), 5, FALSE )=0, "", VLOOKUP( $A7, _xlfn._xlws.FILTER( INDIRECT("'"&E$62&"'!A2:E1000"), (INDIRECT("'"&E$62&"'!B2:B1000")=$B7) * (INDIRECT("'"&E$62&"'!C2:C1000")=$C7) ), 5, FALSE ) )} | F7: {=IF( VLOOKUP( $A7, _xlfn._xlws.FILTER( INDIRECT("'"&F$62&"'!A2:E1000"), (INDIRECT("'"&F$62&"'!B2:B1000")=$B7) * (INDIRECT("'"&F$62&"'!C2:C1000")=$C7) ), 5, FALSE )=0, "", VLOOKUP( $A7, _xlfn._xlws.FILTER( INDIRECT("'"&F$62&"'!A2:E1000"), (INDIRECT("'"&F$62&"'!B2:B1000")=$B7) * (INDIRECT("'"&F$62&"'!C2:C1000")=$C7) ), 5, FALSE ) )} | G7: {=IF( VLOOKUP( $A7, _xlfn._xlws.FILTER( INDIRECT("'"&G$62&"'!A2:E1000"), (INDIRECT("'"&G$62&"'!B2:B1000")=$B7) * (INDIRECT("'"&G$62&"'!C2:C1000")=$C7) ), 5, FALSE )=0, "", VLOOKUP( $A7, _xlfn._xlws.FILTER( INDIRECT("'"&G$62&"'!A2:E1000"), (INDIRECT("'"&G$62&"'!B2:B1000")=$B7) * (INDIRECT("'"&G$62&"'!C2:C1000")=$C7) ), 5, FALSE ) )} | H7: {=IF( VLOOKUP( $A7, _xlfn._xlws.FILTER( INDIRECT("'"&H$62&"'!A2:E1000"), (INDIRECT("'"&H$62&"'!B2:B1000")=$B7) * (INDIRECT("'"&H$62&"'!C2:C1000")=$C7) ), 5, FALSE )=0, "", VLOOKUP( $A7, _xlfn._xlws.FILTER( INDIRECT("'"&H$62&"'!A2:E1000"), (INDIRECT("'"&H$62&"'!B2:B1000")=$B7) * (INDIRECT("'"&H$62&"'!C2:C1000")=$C7) ), 5, FALSE ) )} | I7: {=IF( VLOOKUP( $A7, _xlfn._xlws.FILTER( INDIRECT("'"&I$62&"'!A2:E1000"), (INDIRECT("'"&I$62&"'!B2:B1000")=$B7) * (INDIRECT("'"&I$62&"'!C2:C1000")=$C7) ), 5, FALSE )=0, "", VLOOKUP( $A7, _xlfn._xlws.FILTER( INDIRECT("'"&I$62&"'!A2:E1000"), (INDIRECT("'"&I$62&"'!B2:B1000")=$B7) * (INDIRECT("'"&I$62&"'!C2:C1000")=$C7) ), 5, FALSE ) )} | J7: {=IF( VLOOKUP( $A7, _xlfn._xlws.FILTER( INDIRECT("'"&J$62&"'!A2:E1000"), (INDIRECT("'"&J$62&"'!B2:B1000")=$B7) * (INDIRECT("'"&J$62&"'!C2:C1000")=$C7) ), 5, FALSE )=0, "", VLOOKUP( $A7, _xlfn._xlws.FILTER( INDIRECT("'"&J$62&"'!A2:E1000"), (INDIRECT("'"&J$62&"'!B2:B1000")=$B7) * (INDIRECT("'"&J$62&"'!C2:C1000")=$C7) ), 5, FALSE ) )} | K7: {=IF( VLOOKUP( $A7, _xlfn._xlws.FILTER( INDIRECT("'"&K$62&"'!A2:E1000"), (INDIRECT("'"&K$62&"'!B2:B1000")=$B7) * (INDIRECT("'"&K$62&"'!C2:C1000")=$C7) ), 5, FALSE )=0, "", VLOOKUP( $A7, _xlfn._xlws.FILTER( INDIRECT("'"&K$62&"'!A2:E1000"), (INDIRECT("'"&K$62&"'!B2:B1000")=$B7) * (INDIRECT("'"&K$62&"'!C2:C1000")=$C7) ), 5, FALSE ) )} | ... O7: {=IF( VLOOKUP( $A7, _xlfn._xlws.FILTER( INDIRECT("'"&O$62&"'!A2:E1000"), (INDIRECT("'"&O$62&"'!B2:B1000")=$B7) * (INDIRECT("'"&O$62&"'!C2:C1000")=$C7) ), 5, FALSE )=0, "", VLOOKUP( $A7, _xlfn._xlws.FILTER( INDIRECT("'"&O$62&"'!A2:E1000"), (INDIRECT("'"&O$62&"'!B2:B1000")=$B7) * (INDIRECT("'"&O$62&"'!C2:C1000")=$C7) ), 5, FALSE ) )}
A8: Curitiba | B8: Cerro Azul | C8: 01 | D8: {=IF( VLOOKUP( $A8, _xlfn._xlws.FILTER( INDIRECT("'"&D$62&"'!A2:E1000"), (INDIRECT("'"&D$62&"'!B2:B1000")=$B8) * (INDIRECT("'"&D$62&"'!C2:C1000")=$C8) ), 5, FALSE )=0, "", VLOOKUP( $A8, _xlfn._xlws.FILTER( INDIRECT("'"&D$62&"'!A2:E1000"), (INDIRECT("'"&D$62&"'!B2:B1000")=$B8) * (INDIRECT("'"&D$62&"'!C2:C1000")=$C8) ), 5, FALSE ) )} | E8: {=IF( VLOOKUP( $A8, _xlfn._xlws.FILTER( INDIRECT("'"&E$62&"'!A2:E1000"), (INDIRECT("'"&E$62&"'!B2:B1000")=$B8) * (INDIRECT("'"&E$62&"'!C2:C1000")=$C8) ), 5, FALSE )=0, "", VLOOKUP( $A8, _xlfn._xlws.FILTER( INDIRECT("'"&E$62&"'!A2:E1000"), (INDIRECT("'"&E$62&"'!B2:B1000")=$B8) * (INDIRECT("'"&E$62&"'!C2:C1000")=$C8) ), 5, FALSE ) )} | F8: {=IF( VLOOKUP( $A8, _xlfn._xlws.FILTER( INDIRECT("'"&F$62&"'!A2:E1000"), (INDIRECT("'"&F$62&"'!B2:B1000")=$B8) * (INDIRECT("'"&F$62&"'!C2:C1000")=$C8) ), 5, FALSE )=0, "", VLOOKUP( $A8, _xlfn._xlws.FILTER( INDIRECT("'"&F$62&"'!A2:E1000"), (INDIRECT("'"&F$62&"'!B2:B1000")=$B8) * (INDIRECT("'"&F$62&"'!C2:C1000")=$C8) ), 5, FALSE ) )} | G8: {=IF( VLOOKUP( $A8, _xlfn._xlws.FILTER( INDIRECT("'"&G$62&"'!A2:E1000"), (INDIRECT("'"&G$62&"'!B2:B1000")=$B8) * (INDIRECT("'"&G$62&"'!C2:C1000")=$C8) ), 5, FALSE )=0, "", VLOOKUP( $A8, _xlfn._xlws.FILTER( INDIRECT("'"&G$62&"'!A2:E1000"), (INDIRECT("'"&G$62&"'!B2:B1000")=$B8) * (INDIRECT("'"&G$62&"'!C2:C1000")=$C8) ), 5, FALSE ) )} | H8: {=IF( VLOOKUP( $A8, _xlfn._xlws.FILTER( INDIRECT("'"&H$62&"'!A2:E1000"), (INDIRECT("'"&H$62&"'!B2:B1000")=$B8) * (INDIRECT("'"&H$62&"'!C2:C1000")=$C8) ), 5, FALSE )=0, "", VLOOKUP( $A8, _xlfn._xlws.FILTER( INDIRECT("'"&H$62&"'!A2:E1000"), (INDIRECT("'"&H$62&"'!B2:B1000")=$B8) * (INDIRECT("'"&H$62&"'!C2:C1000")=$C8) ), 5, FALSE ) )} | I8: {=IF( VLOOKUP( $A8, _xlfn._xlws.FILTER( INDIRECT("'"&I$62&"'!A2:E1000"), (INDIRECT("'"&I$62&"'!B2:B1000")=$B8) * (INDIRECT("'"&I$62&"'!C2:C1000")=$C8) ), 5, FALSE )=0, "", VLOOKUP( $A8, _xlfn._xlws.FILTER( INDIRECT("'"&I$62&"'!A2:E1000"), (INDIRECT("'"&I$62&"'!B2:B1000")=$B8) * (INDIRECT("'"&I$62&"'!C2:C1000")=$C8) ), 5, FALSE ) )} | J8: {=IF( VLOOKUP( $A8, _xlfn._xlws.FILTER( INDIRECT("'"&J$62&"'!A2:E1000"), (INDIRECT("'"&J$62&"'!B2:B1000")=$B8) * (INDIRECT("'"&J$62&"'!C2:C1000")=$C8) ), 5, FALSE )=0, "", VLOOKUP( $A8, _xlfn._xlws.FILTER( INDIRECT("'"&J$62&"'!A2:E1000"), (INDIRECT("'"&J$62&"'!B2:B1000")=$B8) * (INDIRECT("'"&J$62&"'!C2:C1000")=$C8) ), 5, FALSE ) )} | K8: {=IF( VLOOKUP( $A8, _xlfn._xlws.FILTER( INDIRECT("'"&K$62&"'!A2:E1000"), (INDIRECT("'"&K$62&"'!B2:B1000")=$B8) * (INDIRECT("'"&K$62&"'!C2:C1000")=$C8) ), 5, FALSE )=0, "", VLOOKUP( $A8, _xlfn._xlws.FILTER( INDIRECT("'"&K$62&"'!A2:E1000"), (INDIRECT("'"&K$62&"'!B2:B1000")=$B8) * (INDIRECT("'"&K$62&"'!C2:C1000")=$C8) ), 5, FALSE ) )} | ... O8: {=IF( VLOOKUP( $A8, _xlfn._xlws.FILTER( INDIRECT("'"&O$62&"'!A2:E1000"), (INDIRECT("'"&O$62&"'!B2:B1000")=$B8) * (INDIRECT("'"&O$62&"'!C2:C1000")=$C8) ), 5, FALSE )=0, "", VLOOKUP( $A8, _xlfn._xlws.FILTER( INDIRECT("'"&O$62&"'!A2:E1000"), (INDIRECT("'"&O$62&"'!B2:B1000")=$B8) * (INDIRECT("'"&O$62&"'!C2:C1000")=$C8) ), 5, FALSE ) )}
A9: Curitiba | B9: Lapa | C9: 01 | D9: {=IF( VLOOKUP( $A9, _xlfn._xlws.FILTER( INDIRECT("'"&D$62&"'!A2:E1000"), (INDIRECT("'"&D$62&"'!B2:B1000")=$B9) * (INDIRECT("'"&D$62&"'!C2:C1000")=$C9) ), 5, FALSE )=0, "", VLOOKUP( $A9, _xlfn._xlws.FILTER( INDIRECT("'"&D$62&"'!A2:E1000"), (INDIRECT("'"&D$62&"'!B2:B1000")=$B9) * (INDIRECT("'"&D$62&"'!C2:C1000")=$C9) ), 5, FALSE ) )} | E9: {=IF( VLOOKUP( $A9, _xlfn._xlws.FILTER( INDIRECT("'"&E$62&"'!A2:E1000"), (INDIRECT("'"&E$62&"'!B2:B1000")=$B9) * (INDIRECT("'"&E$62&"'!C2:C1000")=$C9) ), 5, FALSE )=0, "", VLOOKUP( $A9, _xlfn._xlws.FILTER( INDIRECT("'"&E$62&"'!A2:E1000"), (INDIRECT("'"&E$62&"'!B2:B1000")=$B9) * (INDIRECT("'"&E$62&"'!C2:C1000")=$C9) ), 5, FALSE ) )} | F9: {=IF( VLOOKUP( $A9, _xlfn._xlws.FILTER( INDIRECT("'"&F$62&"'!A2:E1000"), (INDIRECT("'"&F$62&"'!B2:B1000")=$B9) * (INDIRECT("'"&F$62&"'!C2:C1000")=$C9) ), 5, FALSE )=0, "", VLOOKUP( $A9, _xlfn._xlws.FILTER( INDIRECT("'"&F$62&"'!A2:E1000"), (INDIRECT("'"&F$62&"'!B2:B1000")=$B9) * (INDIRECT("'"&F$62&"'!C2:C1000")=$C9) ), 5, FALSE ) )} | G9: {=IF( VLOOKUP( $A9, _xlfn._xlws.FILTER( INDIRECT("'"&G$62&"'!A2:E1000"), (INDIRECT("'"&G$62&"'!B2:B1000")=$B9) * (INDIRECT("'"&G$62&"'!C2:C1000")=$C9) ), 5, FALSE )=0, "", VLOOKUP( $A9, _xlfn._xlws.FILTER( INDIRECT("'"&G$62&"'!A2:E1000"), (INDIRECT("'"&G$62&"'!B2:B1000")=$B9) * (INDIRECT("'"&G$62&"'!C2:C1000")=$C9) ), 5, FALSE ) )} | H9: {=IF( VLOOKUP( $A9, _xlfn._xlws.FILTER( INDIRECT("'"&H$62&"'!A2:E1000"), (INDIRECT("'"&H$62&"'!B2:B1000")=$B9) * (INDIRECT("'"&H$62&"'!C2:C1000")=$C9) ), 5, FALSE )=0, "", VLOOKUP( $A9, _xlfn._xlws.FILTER( INDIRECT("'"&H$62&"'!A2:E1000"), (INDIRECT("'"&H$62&"'!B2:B1000")=$B9) * (INDIRECT("'"&H$62&"'!C2:C1000")=$C9) ), 5, FALSE ) )} | I9: {=IF( VLOOKUP( $A9, _xlfn._xlws.FILTER( INDIRECT("'"&I$62&"'!A2:E1000"), (INDIRECT("'"&I$62&"'!B2:B1000")=$B9) * (INDIRECT("'"&I$62&"'!C2:C1000")=$C9) ), 5, FALSE )=0, "", VLOOKUP( $A9, _xlfn._xlws.FILTER( INDIRECT("'"&I$62&"'!A2:E1000"), (INDIRECT("'"&I$62&"'!B2:B1000")=$B9) * (INDIRECT("'"&I$62&"'!C2:C1000")=$C9) ), 5, FALSE ) )} | J9: {=IF( VLOOKUP( $A9, _xlfn._xlws.FILTER( INDIRECT("'"&J$62&"'!A2:E1000"), (INDIRECT("'"&J$62&"'!B2:B1000")=$B9) * (INDIRECT("'"&J$62&"'!C2:C1000")=$C9) ), 5, FALSE )=0, "", VLOOKUP( $A9, _xlfn._xlws.FILTER( INDIRECT("'"&J$62&"'!A2:E1000"), (INDIRECT("'"&J$62&"'!B2:B1000")=$B9) * (INDIRECT("'"&J$62&"'!C2:C1000")=$C9) ), 5, FALSE ) )} | K9: {=IF( VLOOKUP( $A9, _xlfn._xlws.FILTER( INDIRECT("'"&K$62&"'!A2:E1000"), (INDIRECT("'"&K$62&"'!B2:B1000")=$B9) * (INDIRECT("'"&K$62&"'!C2:C1000")=$C9) ), 5, FALSE )=0, "", VLOOKUP( $A9, _xlfn._xlws.FILTER( INDIRECT("'"&K$62&"'!A2:E1000"), (INDIRECT("'"&K$62&"'!B2:B1000")=$B9) * (INDIRECT("'"&K$62&"'!C2:C1000")=$C9) ), 5, FALSE ) )} | ... O9: {=IF( VLOOKUP( $A9, _xlfn._xlws.FILTER( INDIRECT("'"&O$62&"'!A2:E1000"), (INDIRECT("'"&O$62&"'!B2:B1000")=$B9) * (INDIRECT("'"&O$62&"'!C2:C1000")=$C9) ), 5, FALSE )=0, "", VLOOKUP( $A9, _xlfn._xlws.FILTER( INDIRECT("'"&O$62&"'!A2:E1000"), (INDIRECT("'"&O$62&"'!B2:B1000")=$B9) * (INDIRECT("'"&O$62&"'!C2:C1000")=$C9) ), 5, FALSE ) )}
A10: Curitiba | B10: Rio Branco Do Sul | C10: 01 | D10: {=IF( VLOOKUP( $A10, _xlfn._xlws.FILTER( INDIRECT("'"&D$62&"'!A2:E1000"), (INDIRECT("'"&D$62&"'!B2:B1000")=$B10) * (INDIRECT("'"&D$62&"'!C2:C1000")=$C10) ), 5, FALSE )=0, "", VLOOKUP( $A10, _xlfn._xlws.FILTER( INDIRECT("'"&D$62&"'!A2:E1000"), (INDIRECT("'"&D$62&"'!B2:B1000")=$B10) * (INDIRECT("'"&D$62&"'!C2:C1000")=$C10) ), 5, FALSE ) )} | E10: {=IF( VLOOKUP( $A10, _xlfn._xlws.FILTER( INDIRECT("'"&E$62&"'!A2:E1000"), (INDIRECT("'"&E$62&"'!B2:B1000")=$B10) * (INDIRECT("'"&E$62&"'!C2:C1000")=$C10) ), 5, FALSE )=0, "", VLOOKUP( $A10, _xlfn._xlws.FILTER( INDIRECT("'"&E$62&"'!A2:E1000"), (INDIRECT("'"&E$62&"'!B2:B1000")=$B10) * (INDIRECT("'"&E$62&"'!C2:C1000")=$C10) ), 5, FALSE ) )} | F10: {=IF( VLOOKUP( $A10, _xlfn._xlws.FILTER( INDIRECT("'"&F$62&"'!A2:E1000"), (INDIRECT("'"&F$62&"'!B2:B1000")=$B10) * (INDIRECT("'"&F$62&"'!C2:C1000")=$C10) ), 5, FALSE )=0, "", VLOOKUP( $A10, _xlfn._xlws.FILTER( INDIRECT("'"&F$62&"'!A2:E1000"), (INDIRECT("'"&F$62&"'!B2:B1000")=$B10) * (INDIRECT("'"&F$62&"'!C2:C1000")=$C10) ), 5, FALSE ) )} | G10: {=IF( VLOOKUP( $A10, _xlfn._xlws.FILTER( INDIRECT("'"&G$62&"'!A2:E1000"), (INDIRECT("'"&G$62&"'!B2:B1000")=$B10) * (INDIRECT("'"&G$62&"'!C2:C1000")=$C10) ), 5, FALSE )=0, "", VLOOKUP( $A10, _xlfn._xlws.FILTER( INDIRECT("'"&G$62&"'!A2:E1000"), (INDIRECT("'"&G$62&"'!B2:B1000")=$B10) * (INDIRECT("'"&G$62&"'!C2:C1000")=$C10) ), 5, FALSE ) )} | H10: {=IF( VLOOKUP( $A10, _xlfn._xlws.FILTER( INDIRECT("'"&H$62&"'!A2:E1000"), (INDIRECT("'"&H$62&"'!B2:B1000")=$B10) * (INDIRECT("'"&H$62&"'!C2:C1000")=$C10) ), 5, FALSE )=0, "", VLOOKUP( $A10, _xlfn._xlws.FILTER( INDIRECT("'"&H$62&"'!A2:E1000"), (INDIRECT("'"&H$62&"'!B2:B1000")=$B10) * (INDIRECT("'"&H$62&"'!C2:C1000")=$C10) ), 5, FALSE ) )} | I10: {=IF( VLOOKUP( $A10, _xlfn._xlws.FILTER( INDIRECT("'"&I$62&"'!A2:E1000"), (INDIRECT("'"&I$62&"'!B2:B1000")=$B10) * (INDIRECT("'"&I$62&"'!C2:C1000")=$C10) ), 5, FALSE )=0, "", VLOOKUP( $A10, _xlfn._xlws.FILTER( INDIRECT("'"&I$62&"'!A2:E1000"), (INDIRECT("'"&I$62&"'!B2:B1000")=$B10) * (INDIRECT("'"&I$62&"'!C2:C1000")=$C10) ), 5, FALSE ) )} | J10: {=IF( VLOOKUP( $A10, _xlfn._xlws.FILTER( INDIRECT("'"&J$62&"'!A2:E1000"), (INDIRECT("'"&J$62&"'!B2:B1000")=$B10) * (INDIRECT("'"&J$62&"'!C2:C1000")=$C10) ), 5, FALSE )=0, "", VLOOKUP( $A10, _xlfn._xlws.FILTER( INDIRECT("'"&J$62&"'!A2:E1000"), (INDIRECT("'"&J$62&"'!B2:B1000")=$B10) * (INDIRECT("'"&J$62&"'!C2:C1000")=$C10) ), 5, FALSE ) )} | K10: {=IF( VLOOKUP( $A10, _xlfn._xlws.FILTER( INDIRECT("'"&K$62&"'!A2:E1000"), (INDIRECT("'"&K$62&"'!B2:B1000")=$B10) * (INDIRECT("'"&K$62&"'!C2:C1000")=$C10) ), 5, FALSE )=0, "", VLOOKUP( $A10, _xlfn._xlws.FILTER( INDIRECT("'"&K$62&"'!A2:E1000"), (INDIRECT("'"&K$62&"'!B2:B1000")=$B10) * (INDIRECT("'"&K$62&"'!C2:C1000")=$C10) ), 5, FALSE ) )} | ... O10: {=IF( VLOOKUP( $A10, _xlfn._xlws.FILTER( INDIRECT("'"&O$62&"'!A2:E1000"), (INDIRECT("'"&O$62&"'!B2:B1000")=$B10) * (INDIRECT("'"&O$62&"'!C2:C1000")=$C10) ), 5, FALSE )=0, "", VLOOKUP( $A10, _xlfn._xlws.FILTER( INDIRECT("'"&O$62&"'!A2:E1000"), (INDIRECT("'"&O$62&"'!B2:B1000")=$B10) * (INDIRECT("'"&O$62&"'!C2:C1000")=$C10) ), 5, FALSE ) )}
A11: Curitiba | B11: Rio Branco Do Sul | C11: 02 | D11: {=IF( VLOOKUP( $A11, _xlfn._xlws.FILTER( INDIRECT("'"&D$62&"'!A2:E1000"), (INDIRECT("'"&D$62&"'!B2:B1000")=$B11) * (INDIRECT("'"&D$62&"'!C2:C1000")=$C11) ), 5, FALSE )=0, "", VLOOKUP( $A11, _xlfn._xlws.FILTER( INDIRECT("'"&D$62&"'!A2:E1000"), (INDIRECT("'"&D$62&"'!B2:B1000")=$B11) * (INDIRECT("'"&D$62&"'!C2:C1000")=$C11) ), 5, FALSE ) )} | E11: {=IF( VLOOKUP( $A11, _xlfn._xlws.FILTER( INDIRECT("'"&E$62&"'!A2:E1000"), (INDIRECT("'"&E$62&"'!B2:B1000")=$B11) * (INDIRECT("'"&E$62&"'!C2:C1000")=$C11) ), 5, FALSE )=0, "", VLOOKUP( $A11, _xlfn._xlws.FILTER( INDIRECT("'"&E$62&"'!A2:E1000"), (INDIRECT("'"&E$62&"'!B2:B1000")=$B11) * (INDIRECT("'"&E$62&"'!C2:C1000")=$C11) ), 5, FALSE ) )} | F11: {=IF( VLOOKUP( $A11, _xlfn._xlws.FILTER( INDIRECT("'"&F$62&"'!A2:E1000"), (INDIRECT("'"&F$62&"'!B2:B1000")=$B11) * (INDIRECT("'"&F$62&"'!C2:C1000")=$C11) ), 5, FALSE )=0, "", VLOOKUP( $A11, _xlfn._xlws.FILTER( INDIRECT("'"&F$62&"'!A2:E1000"), (INDIRECT("'"&F$62&"'!B2:B1000")=$B11) * (INDIRECT("'"&F$62&"'!C2:C1000")=$C11) ), 5, FALSE ) )} | G11: {=IF( VLOOKUP( $A11, _xlfn._xlws.FILTER( INDIRECT("'"&G$62&"'!A2:E1000"), (INDIRECT("'"&G$62&"'!B2:B1000")=$B11) * (INDIRECT("'"&G$62&"'!C2:C1000")=$C11) ), 5, FALSE )=0, "", VLOOKUP( $A11, _xlfn._xlws.FILTER( INDIRECT("'"&G$62&"'!A2:E1000"), (INDIRECT("'"&G$62&"'!B2:B1000")=$B11) * (INDIRECT("'"&G$62&"'!C2:C1000")=$C11) ), 5, FALSE ) )} | H11: {=IF( VLOOKUP( $A11, _xlfn._xlws.FILTER( INDIRECT("'"&H$62&"'!A2:E1000"), (INDIRECT("'"&H$62&"'!B2:B1000")=$B11) * (INDIRECT("'"&H$62&"'!C2:C1000")=$C11) ), 5, FALSE )=0, "", VLOOKUP( $A11, _xlfn._xlws.FILTER( INDIRECT("'"&H$62&"'!A2:E1000"), (INDIRECT("'"&H$62&"'!B2:B1000")=$B11) * (INDIRECT("'"&H$62&"'!C2:C1000")=$C11) ), 5, FALSE ) )} | I11: {=IF( VLOOKUP( $A11, _xlfn._xlws.FILTER( INDIRECT("'"&I$62&"'!A2:E1000"), (INDIRECT("'"&I$62&"'!B2:B1000")=$B11) * (INDIRECT("'"&I$62&"'!C2:C1000")=$C11) ), 5, FALSE )=0, "", VLOOKUP( $A11, _xlfn._xlws.FILTER( INDIRECT("'"&I$62&"'!A2:E1000"), (INDIRECT("'"&I$62&"'!B2:B1000")=$B11) * (INDIRECT("'"&I$62&"'!C2:C1000")=$C11) ), 5, FALSE ) )} | J11: {=IF( VLOOKUP( $A11, _xlfn._xlws.FILTER( INDIRECT("'"&J$62&"'!A2:E1000"), (INDIRECT("'"&J$62&"'!B2:B1000")=$B11) * (INDIRECT("'"&J$62&"'!C2:C1000")=$C11) ), 5, FALSE )=0, "", VLOOKUP( $A11, _xlfn._xlws.FILTER( INDIRECT("'"&J$62&"'!A2:E1000"), (INDIRECT("'"&J$62&"'!B2:B1000")=$B11) * (INDIRECT("'"&J$62&"'!C2:C1000")=$C11) ), 5, FALSE ) )} | K11: {=IF( VLOOKUP( $A11, _xlfn._xlws.FILTER( INDIRECT("'"&K$62&"'!A2:E1000"), (INDIRECT("'"&K$62&"'!B2:B1000")=$B11) * (INDIRECT("'"&K$62&"'!C2:C1000")=$C11) ), 5, FALSE )=0, "", VLOOKUP( $A11, _xlfn._xlws.FILTER( INDIRECT("'"&K$62&"'!A2:E1000"), (INDIRECT("'"&K$62&"'!B2:B1000")=$B11) * (INDIRECT("'"&K$62&"'!C2:C1000")=$C11) ), 5, FALSE ) )} | ... O11: {=IF( VLOOKUP( $A11, _xlfn._xlws.FILTER( INDIRECT("'"&O$62&"'!A2:E1000"), (INDIRECT("'"&O$62&"'!B2:B1000")=$B11) * (INDIRECT("'"&O$62&"'!C2:C1000")=$C11) ), 5, FALSE )=0, "", VLOOKUP( $A11, _xlfn._xlws.FILTER( INDIRECT("'"&O$62&"'!A2:E1000"), (INDIRECT("'"&O$62&"'!B2:B1000")=$B11) * (INDIRECT("'"&O$62&"'!C2:C1000")=$C11) ), 5, FALSE ) )}
A12: Curitiba | B12: Rio Negro | C12: 01 | D12: {=IF( VLOOKUP( $A12, _xlfn._xlws.FILTER( INDIRECT("'"&D$62&"'!A2:E1000"), (INDIRECT("'"&D$62&"'!B2:B1000")=$B12) * (INDIRECT("'"&D$62&"'!C2:C1000")=$C12) ), 5, FALSE )=0, "", VLOOKUP( $A12, _xlfn._xlws.FILTER( INDIRECT("'"&D$62&"'!A2:E1000"), (INDIRECT("'"&D$62&"'!B2:B1000")=$B12) * (INDIRECT("'"&D$62&"'!C2:C1000")=$C12) ), 5, FALSE ) )} | E12: {=IF( VLOOKUP( $A12, _xlfn._xlws.FILTER( INDIRECT("'"&E$62&"'!A2:E1000"), (INDIRECT("'"&E$62&"'!B2:B1000")=$B12) * (INDIRECT("'"&E$62&"'!C2:C1000")=$C12) ), 5, FALSE )=0, "", VLOOKUP( $A12, _xlfn._xlws.FILTER( INDIRECT("'"&E$62&"'!A2:E1000"), (INDIRECT("'"&E$62&"'!B2:B1000")=$B12) * (INDIRECT("'"&E$62&"'!C2:C1000")=$C12) ), 5, FALSE ) )} | F12: {=IF( VLOOKUP( $A12, _xlfn._xlws.FILTER( INDIRECT("'"&F$62&"'!A2:E1000"), (INDIRECT("'"&F$62&"'!B2:B1000")=$B12) * (INDIRECT("'"&F$62&"'!C2:C1000")=$C12) ), 5, FALSE )=0, "", VLOOKUP( $A12, _xlfn._xlws.FILTER( INDIRECT("'"&F$62&"'!A2:E1000"), (INDIRECT("'"&F$62&"'!B2:B1000")=$B12) * (INDIRECT("'"&F$62&"'!C2:C1000")=$C12) ), 5, FALSE ) )} | G12: {=IF( VLOOKUP( $A12, _xlfn._xlws.FILTER( INDIRECT("'"&G$62&"'!A2:E1000"), (INDIRECT("'"&G$62&"'!B2:B1000")=$B12) * (INDIRECT("'"&G$62&"'!C2:C1000")=$C12) ), 5, FALSE )=0, "", VLOOKUP( $A12, _xlfn._xlws.FILTER( INDIRECT("'"&G$62&"'!A2:E1000"), (INDIRECT("'"&G$62&"'!B2:B1000")=$B12) * (INDIRECT("'"&G$62&"'!C2:C1000")=$C12) ), 5, FALSE ) )} | H12: {=IF( VLOOKUP( $A12, _xlfn._xlws.FILTER( INDIRECT("'"&H$62&"'!A2:E1000"), (INDIRECT("'"&H$62&"'!B2:B1000")=$B12) * (INDIRECT("'"&H$62&"'!C2:C1000")=$C12) ), 5, FALSE )=0, "", VLOOKUP( $A12, _xlfn._xlws.FILTER( INDIRECT("'"&H$62&"'!A2:E1000"), (INDIRECT("'"&H$62&"'!B2:B1000")=$B12) * (INDIRECT("'"&H$62&"'!C2:C1000")=$C12) ), 5, FALSE ) )} | I12: {=IF( VLOOKUP( $A12, _xlfn._xlws.FILTER( INDIRECT("'"&I$62&"'!A2:E1000"), (INDIRECT("'"&I$62&"'!B2:B1000")=$B12) * (INDIRECT("'"&I$62&"'!C2:C1000")=$C12) ), 5, FALSE )=0, "", VLOOKUP( $A12, _xlfn._xlws.FILTER( INDIRECT("'"&I$62&"'!A2:E1000"), (INDIRECT("'"&I$62&"'!B2:B1000")=$B12) * (INDIRECT("'"&I$62&"'!C2:C1000")=$C12) ), 5, FALSE ) )} | J12: {=IF( VLOOKUP( $A12, _xlfn._xlws.FILTER( INDIRECT("'"&J$62&"'!A2:E1000"), (INDIRECT("'"&J$62&"'!B2:B1000")=$B12) * (INDIRECT("'"&J$62&"'!C2:C1000")=$C12) ), 5, FALSE )=0, "", VLOOKUP( $A12, _xlfn._xlws.FILTER( INDIRECT("'"&J$62&"'!A2:E1000"), (INDIRECT("'"&J$62&"'!B2:B1000")=$B12) * (INDIRECT("'"&J$62&"'!C2:C1000")=$C12) ), 5, FALSE ) )} | K12: {=IF( VLOOKUP( $A12, _xlfn._xlws.FILTER( INDIRECT("'"&K$62&"'!A2:E1000"), (INDIRECT("'"&K$62&"'!B2:B1000")=$B12) * (INDIRECT("'"&K$62&"'!C2:C1000")=$C12) ), 5, FALSE )=0, "", VLOOKUP( $A12, _xlfn._xlws.FILTER( INDIRECT("'"&K$62&"'!A2:E1000"), (INDIRECT("'"&K$62&"'!B2:B1000")=$B12) * (INDIRECT("'"&K$62&"'!C2:C1000")=$C12) ), 5, FALSE ) )} | ... O12: {=IF( VLOOKUP( $A12, _xlfn._xlws.FILTER( INDIRECT("'"&O$62&"'!A2:E1000"), (INDIRECT("'"&O$62&"'!B2:B1000")=$B12) * (INDIRECT("'"&O$62&"'!C2:C1000")=$C12) ), 5, FALSE )=0, "", VLOOKUP( $A12, _xlfn._xlws.FILTER( INDIRECT("'"&O$62&"'!A2:E1000"), (INDIRECT("'"&O$62&"'!B2:B1000")=$B12) * (INDIRECT("'"&O$62&"'!C2:C1000")=$C12) ), 5, FALSE ) )}
A13: Curitiba | B13: São João Do Triunfo | C13: 01 | D13: {=IF( VLOOKUP( $A13, _xlfn._xlws.FILTER( INDIRECT("'"&D$62&"'!A2:E1000"), (INDIRECT("'"&D$62&"'!B2:B1000")=$B13) * (INDIRECT("'"&D$62&"'!C2:C1000")=$C13) ), 5, FALSE )=0, "", VLOOKUP( $A13, _xlfn._xlws.FILTER( INDIRECT("'"&D$62&"'!A2:E1000"), (INDIRECT("'"&D$62&"'!B2:B1000")=$B13) * (INDIRECT("'"&D$62&"'!C2:C1000")=$C13) ), 5, FALSE ) )} | E13: {=IF( VLOOKUP( $A13, _xlfn._xlws.FILTER( INDIRECT("'"&E$62&"'!A2:E1000"), (INDIRECT("'"&E$62&"'!B2:B1000")=$B13) * (INDIRECT("'"&E$62&"'!C2:C1000")=$C13) ), 5, FALSE )=0, "", VLOOKUP( $A13, _xlfn._xlws.FILTER( INDIRECT("'"&E$62&"'!A2:E1000"), (INDIRECT("'"&E$62&"'!B2:B1000")=$B13) * (INDIRECT("'"&E$62&"'!C2:C1000")=$C13) ), 5, FALSE ) )} | F13: {=IF( VLOOKUP( $A13, _xlfn._xlws.FILTER( INDIRECT("'"&F$62&"'!A2:E1000"), (INDIRECT("'"&F$62&"'!B2:B1000")=$B13) * (INDIRECT("'"&F$62&"'!C2:C1000")=$C13) ), 5, FALSE )=0, "", VLOOKUP( $A13, _xlfn._xlws.FILTER( INDIRECT("'"&F$62&"'!A2:E1000"), (INDIRECT("'"&F$62&"'!B2:B1000")=$B13) * (INDIRECT("'"&F$62&"'!C2:C1000")=$C13) ), 5, FALSE ) )} | G13: {=IF( VLOOKUP( $A13, _xlfn._xlws.FILTER( INDIRECT("'"&G$62&"'!A2:E1000"), (INDIRECT("'"&G$62&"'!B2:B1000")=$B13) * (INDIRECT("'"&G$62&"'!C2:C1000")=$C13) ), 5, FALSE )=0, "", VLOOKUP( $A13, _xlfn._xlws.FILTER( INDIRECT("'"&G$62&"'!A2:E1000"), (INDIRECT("'"&G$62&"'!B2:B1000")=$B13) * (INDIRECT("'"&G$62&"'!C2:C1000")=$C13) ), 5, FALSE ) )} | H13: {=IF( VLOOKUP( $A13, _xlfn._xlws.FILTER( INDIRECT("'"&H$62&"'!A2:E1000"), (INDIRECT("'"&H$62&"'!B2:B1000")=$B13) * (INDIRECT("'"&H$62&"'!C2:C1000")=$C13) ), 5, FALSE )=0, "", VLOOKUP( $A13, _xlfn._xlws.FILTER( INDIRECT("'"&H$62&"'!A2:E1000"), (INDIRECT("'"&H$62&"'!B2:B1000")=$B13) * (INDIRECT("'"&H$62&"'!C2:C1000")=$C13) ), 5, FALSE ) )} | I13: {=IF( VLOOKUP( $A13, _xlfn._xlws.FILTER( INDIRECT("'"&I$62&"'!A2:E1000"), (INDIRECT("'"&I$62&"'!B2:B1000")=$B13) * (INDIRECT("'"&I$62&"'!C2:C1000")=$C13) ), 5, FALSE )=0, "", VLOOKUP( $A13, _xlfn._xlws.FILTER( INDIRECT("'"&I$62&"'!A2:E1000"), (INDIRECT("'"&I$62&"'!B2:B1000")=$B13) * (INDIRECT("'"&I$62&"'!C2:C1000")=$C13) ), 5, FALSE ) )} | J13: {=IF( VLOOKUP( $A13, _xlfn._xlws.FILTER( INDIRECT("'"&J$62&"'!A2:E1000"), (INDIRECT("'"&J$62&"'!B2:B1000")=$B13) * (INDIRECT("'"&J$62&"'!C2:C1000")=$C13) ), 5, FALSE )=0, "", VLOOKUP( $A13, _xlfn._xlws.FILTER( INDIRECT("'"&J$62&"'!A2:E1000"), (INDIRECT("'"&J$62&"'!B2:B1000")=$B13) * (INDIRECT("'"&J$62&"'!C2:C1000")=$C13) ), 5, FALSE ) )} | K13: {=IF( VLOOKUP( $A13, _xlfn._xlws.FILTER( INDIRECT("'"&K$62&"'!A2:E1000"), (INDIRECT("'"&K$62&"'!B2:B1000")=$B13) * (INDIRECT("'"&K$62&"'!C2:C1000")=$C13) ), 5, FALSE )=0, "", VLOOKUP( $A13, _xlfn._xlws.FILTER( INDIRECT("'"&K$62&"'!A2:E1000"), (INDIRECT("'"&K$62&"'!B2:B1000")=$B13) * (INDIRECT("'"&K$62&"'!C2:C1000")=$C13) ), 5, FALSE ) )} | ... O13: {=IF( VLOOKUP( $A13, _xlfn._xlws.FILTER( INDIRECT("'"&O$62&"'!A2:E1000"), (INDIRECT("'"&O$62&"'!B2:B1000")=$B13) * (INDIRECT("'"&O$62&"'!C2:C1000")=$C13) ), 5, FALSE )=0, "", VLOOKUP( $A13, _xlfn._xlws.FILTER( INDIRECT("'"&O$62&"'!A2:E1000"), (INDIRECT("'"&O$62&"'!B2:B1000")=$B13) * (INDIRECT("'"&O$62&"'!C2:C1000")=$C13) ), 5, FALSE ) )}
A14: Curitiba | B14: Tijucas Do Sul | C14: 01 | D14: {=IF( VLOOKUP( $A14, _xlfn._xlws.FILTER( INDIRECT("'"&D$62&"'!A2:E1000"), (INDIRECT("'"&D$62&"'!B2:B1000")=$B14) * (INDIRECT("'"&D$62&"'!C2:C1000")=$C14) ), 5, FALSE )=0, "", VLOOKUP( $A14, _xlfn._xlws.FILTER( INDIRECT("'"&D$62&"'!A2:E1000"), (INDIRECT("'"&D$62&"'!B2:B1000")=$B14) * (INDIRECT("'"&D$62&"'!C2:C1000")=$C14) ), 5, FALSE ) )} | E14: {=IF( VLOOKUP( $A14, _xlfn._xlws.FILTER( INDIRECT("'"&E$62&"'!A2:E1000"), (INDIRECT("'"&E$62&"'!B2:B1000")=$B14) * (INDIRECT("'"&E$62&"'!C2:C1000")=$C14) ), 5, FALSE )=0, "", VLOOKUP( $A14, _xlfn._xlws.FILTER( INDIRECT("'"&E$62&"'!A2:E1000"), (INDIRECT("'"&E$62&"'!B2:B1000")=$B14) * (INDIRECT("'"&E$62&"'!C2:C1000")=$C14) ), 5, FALSE ) )} | F14: {=IF( VLOOKUP( $A14, _xlfn._xlws.FILTER( INDIRECT("'"&F$62&"'!A2:E1000"), (INDIRECT("'"&F$62&"'!B2:B1000")=$B14) * (INDIRECT("'"&F$62&"'!C2:C1000")=$C14) ), 5, FALSE )=0, "", VLOOKUP( $A14, _xlfn._xlws.FILTER( INDIRECT("'"&F$62&"'!A2:E1000"), (INDIRECT("'"&F$62&"'!B2:B1000")=$B14) * (INDIRECT("'"&F$62&"'!C2:C1000")=$C14) ), 5, FALSE ) )} | G14: {=IF( VLOOKUP( $A14, _xlfn._xlws.FILTER( INDIRECT("'"&G$62&"'!A2:E1000"), (INDIRECT("'"&G$62&"'!B2:B1000")=$B14) * (INDIRECT("'"&G$62&"'!C2:C1000")=$C14) ), 5, FALSE )=0, "", VLOOKUP( $A14, _xlfn._xlws.FILTER( INDIRECT("'"&G$62&"'!A2:E1000"), (INDIRECT("'"&G$62&"'!B2:B1000")=$B14) * (INDIRECT("'"&G$62&"'!C2:C1000")=$C14) ), 5, FALSE ) )} | H14: {=IF( VLOOKUP( $A14, _xlfn._xlws.FILTER( INDIRECT("'"&H$62&"'!A2:E1000"), (INDIRECT("'"&H$62&"'!B2:B1000")=$B14) * (INDIRECT("'"&H$62&"'!C2:C1000")=$C14) ), 5, FALSE )=0, "", VLOOKUP( $A14, _xlfn._xlws.FILTER( INDIRECT("'"&H$62&"'!A2:E1000"), (INDIRECT("'"&H$62&"'!B2:B1000")=$B14) * (INDIRECT("'"&H$62&"'!C2:C1000")=$C14) ), 5, FALSE ) )} | I14: {=IF( VLOOKUP( $A14, _xlfn._xlws.FILTER( INDIRECT("'"&I$62&"'!A2:E1000"), (INDIRECT("'"&I$62&"'!B2:B1000")=$B14) * (INDIRECT("'"&I$62&"'!C2:C1000")=$C14) ), 5, FALSE )=0, "", VLOOKUP( $A14, _xlfn._xlws.FILTER( INDIRECT("'"&I$62&"'!A2:E1000"), (INDIRECT("'"&I$62&"'!B2:B1000")=$B14) * (INDIRECT("'"&I$62&"'!C2:C1000")=$C14) ), 5, FALSE ) )} | J14: {=IF( VLOOKUP( $A14, _xlfn._xlws.FILTER( INDIRECT("'"&J$62&"'!A2:E1000"), (INDIRECT("'"&J$62&"'!B2:B1000")=$B14) * (INDIRECT("'"&J$62&"'!C2:C1000")=$C14) ), 5, FALSE )=0, "", VLOOKUP( $A14, _xlfn._xlws.FILTER( INDIRECT("'"&J$62&"'!A2:E1000"), (INDIRECT("'"&J$62&"'!B2:B1000")=$B14) * (INDIRECT("'"&J$62&"'!C2:C1000")=$C14) ), 5, FALSE ) )} | K14: {=IF( VLOOKUP( $A14, _xlfn._xlws.FILTER( INDIRECT("'"&K$62&"'!A2:E1000"), (INDIRECT("'"&K$62&"'!B2:B1000")=$B14) * (INDIRECT("'"&K$62&"'!C2:C1000")=$C14) ), 5, FALSE )=0, "", VLOOKUP( $A14, _xlfn._xlws.FILTER( INDIRECT("'"&K$62&"'!A2:E1000"), (INDIRECT("'"&K$62&"'!B2:B1000")=$B14) * (INDIRECT("'"&K$62&"'!C2:C1000")=$C14) ), 5, FALSE ) )} | ... O14: {=IF( VLOOKUP( $A14, _xlfn._xlws.FILTER( INDIRECT("'"&O$62&"'!A2:E1000"), (INDIRECT("'"&O$62&"'!B2:B1000")=$B14) * (INDIRECT("'"&O$62&"'!C2:C1000")=$C14) ), 5, FALSE )=0, "", VLOOKUP( $A14, _xlfn._xlws.FILTER( INDIRECT("'"&O$62&"'!A2:E1000"), (INDIRECT("'"&O$62&"'!B2:B1000")=$B14) * (INDIRECT("'"&O$62&"'!C2:C1000")=$C14) ), 5, FALSE ) )}
A16: Vanessa | B16: Municípios | C16: UVR | D16: 01.25 | E16: 02.25 | F16: 03.25 | G16: 04.25 | H16: 05.25 | I16: 06.25 | J16: 07.25 | K16: 08.25 | L16: 09.25 | M16: 10.25 | N16: 11.25 | O16: 12.25
A17: Francisco Beltrão | B17: Barracão | C17: 01 | D17: {=IF( VLOOKUP( $A17, _xlfn._xlws.FILTER( INDIRECT("'"&D$62&"'!A2:E1000"), (INDIRECT("'"&D$62&"'!B2:B1000")=$B17) * (INDIRECT("'"&D$62&"'!C2:C1000")=$C17) ), 5, FALSE )=0, "", VLOOKUP( $A17, _xlfn._xlws.FILTER( INDIRECT("'"&D$62&"'!A2:E1000"), (INDIRECT("'"&D$62&"'!B2:B1000")=$B17) * (INDIRECT("'"&D$62&"'!C2:C1000")=$C17) ), 5, FALSE ) )} | E17: {=IF( VLOOKUP( $A17, _xlfn._xlws.FILTER( INDIRECT("'"&E$62&"'!A2:E1000"), (INDIRECT("'"&E$62&"'!B2:B1000")=$B17) * (INDIRECT("'"&E$62&"'!C2:C1000")=$C17) ), 5, FALSE )=0, "", VLOOKUP( $A17, _xlfn._xlws.FILTER( INDIRECT("'"&E$62&"'!A2:E1000"), (INDIRECT("'"&E$62&"'!B2:B1000")=$B17) * (INDIRECT("'"&E$62&"'!C2:C1000")=$C17) ), 5, FALSE ) )} | F17: {=IF( VLOOKUP( $A17, _xlfn._xlws.FILTER( INDIRECT("'"&F$62&"'!A2:E1000"), (INDIRECT("'"&F$62&"'!B2:B1000")=$B17) * (INDIRECT("'"&F$62&"'!C2:C1000")=$C17) ), 5, FALSE )=0, "", VLOOKUP( $A17, _xlfn._xlws.FILTER( INDIRECT("'"&F$62&"'!A2:E1000"), (INDIRECT("'"&F$62&"'!B2:B1000")=$B17) * (INDIRECT("'"&F$62&"'!C2:C1000")=$C17) ), 5, FALSE ) )} | G17: {=IF( VLOOKUP( $A17, _xlfn._xlws.FILTER( INDIRECT("'"&G$62&"'!A2:E1000"), (INDIRECT("'"&G$62&"'!B2:B1000")=$B17) * (INDIRECT("'"&G$62&"'!C2:C1000")=$C17) ), 5, FALSE )=0, "", VLOOKUP( $A17, _xlfn._xlws.FILTER( INDIRECT("'"&G$62&"'!A2:E1000"), (INDIRECT("'"&G$62&"'!B2:B1000")=$B17) * (INDIRECT("'"&G$62&"'!C2:C1000")=$C17) ), 5, FALSE ) )} | H17: {=IF( VLOOKUP( $A17, _xlfn._xlws.FILTER( INDIRECT("'"&H$62&"'!A2:E1000"), (INDIRECT("'"&H$62&"'!B2:B1000")=$B17) * (INDIRECT("'"&H$62&"'!C2:C1000")=$C17) ), 5, FALSE )=0, "", VLOOKUP( $A17, _xlfn._xlws.FILTER( INDIRECT("'"&H$62&"'!A2:E1000"), (INDIRECT("'"&H$62&"'!B2:B1000")=$B17) * (INDIRECT("'"&H$62&"'!C2:C1000")=$C17) ), 5, FALSE ) )} | I17: {=IF( VLOOKUP( $A17, _xlfn._xlws.FILTER( INDIRECT("'"&I$62&"'!A2:E1000"), (INDIRECT("'"&I$62&"'!B2:B1000")=$B17) * (INDIRECT("'"&I$62&"'!C2:C1000")=$C17) ), 5, FALSE )=0, "", VLOOKUP( $A17, _xlfn._xlws.FILTER( INDIRECT("'"&I$62&"'!A2:E1000"), (INDIRECT("'"&I$62&"'!B2:B1000")=$B17) * (INDIRECT("'"&I$62&"'!C2:C1000")=$C17) ), 5, FALSE ) )} | J17: {=IF( VLOOKUP( $A17, _xlfn._xlws.FILTER( INDIRECT("'"&J$62&"'!A2:E1000"), (INDIRECT("'"&J$62&"'!B2:B1000")=$B17) * (INDIRECT("'"&J$62&"'!C2:C1000")=$C17) ), 5, FALSE )=0, "", VLOOKUP( $A17, _xlfn._xlws.FILTER( INDIRECT("'"&J$62&"'!A2:E1000"), (INDIRECT("'"&J$62&"'!B2:B1000")=$B17) * (INDIRECT("'"&J$62&"'!C2:C1000")=$C17) ), 5, FALSE ) )} | K17: {=IF( VLOOKUP( $A17, _xlfn._xlws.FILTER( INDIRECT("'"&K$62&"'!A2:E1000"), (INDIRECT("'"&K$62&"'!B2:B1000")=$B17) * (INDIRECT("'"&K$62&"'!C2:C1000")=$C17) ), 5, FALSE )=0, "", VLOOKUP( $A17, _xlfn._xlws.FILTER( INDIRECT("'"&K$62&"'!A2:E1000"), (INDIRECT("'"&K$62&"'!B2:B1000")=$B17) * (INDIRECT("'"&K$62&"'!C2:C1000")=$C17) ), 5, FALSE ) )} | ... O17: {=IF( VLOOKUP( $A17, _xlfn._xlws.FILTER( INDIRECT("'"&O$62&"'!A2:E1000"), (INDIRECT("'"&O$62&"'!B2:B1000")=$B17) * (INDIRECT("'"&O$62&"'!C2:C1000")=$C17) ), 5, FALSE )=0, "", VLOOKUP( $A17, _xlfn._xlws.FILTER( INDIRECT("'"&O$62&"'!A2:E1000"), (INDIRECT("'"&O$62&"'!B2:B1000")=$B17) * (INDIRECT("'"&O$62&"'!C2:C1000")=$C17) ), 5, FALSE ) )}
A18: Francisco Beltrão | B18: Capanema | C18: 01 | D18: {=IF( VLOOKUP( $A18, _xlfn._xlws.FILTER( INDIRECT("'"&D$62&"'!A2:E1000"), (INDIRECT("'"&D$62&"'!B2:B1000")=$B18) * (INDIRECT("'"&D$62&"'!C2:C1000")=$C18) ), 5, FALSE )=0, "", VLOOKUP( $A18, _xlfn._xlws.FILTER( INDIRECT("'"&D$62&"'!A2:E1000"), (INDIRECT("'"&D$62&"'!B2:B1000")=$B18) * (INDIRECT("'"&D$62&"'!C2:C1000")=$C18) ), 5, FALSE ) )} | E18: {=IF( VLOOKUP( $A18, _xlfn._xlws.FILTER( INDIRECT("'"&E$62&"'!A2:E1000"), (INDIRECT("'"&E$62&"'!B2:B1000")=$B18) * (INDIRECT("'"&E$62&"'!C2:C1000")=$C18) ), 5, FALSE )=0, "", VLOOKUP( $A18, _xlfn._xlws.FILTER( INDIRECT("'"&E$62&"'!A2:E1000"), (INDIRECT("'"&E$62&"'!B2:B1000")=$B18) * (INDIRECT("'"&E$62&"'!C2:C1000")=$C18) ), 5, FALSE ) )} | F18: {=IF( VLOOKUP( $A18, _xlfn._xlws.FILTER( INDIRECT("'"&F$62&"'!A2:E1000"), (INDIRECT("'"&F$62&"'!B2:B1000")=$B18) * (INDIRECT("'"&F$62&"'!C2:C1000")=$C18) ), 5, FALSE )=0, "", VLOOKUP( $A18, _xlfn._xlws.FILTER( INDIRECT("'"&F$62&"'!A2:E1000"), (INDIRECT("'"&F$62&"'!B2:B1000")=$B18) * (INDIRECT("'"&F$62&"'!C2:C1000")=$C18) ), 5, FALSE ) )} | G18: {=IF( VLOOKUP( $A18, _xlfn._xlws.FILTER( INDIRECT("'"&G$62&"'!A2:E1000"), (INDIRECT("'"&G$62&"'!B2:B1000")=$B18) * (INDIRECT("'"&G$62&"'!C2:C1000")=$C18) ), 5, FALSE )=0, "", VLOOKUP( $A18, _xlfn._xlws.FILTER( INDIRECT("'"&G$62&"'!A2:E1000"), (INDIRECT("'"&G$62&"'!B2:B1000")=$B18) * (INDIRECT("'"&G$62&"'!C2:C1000")=$C18) ), 5, FALSE ) )} | H18: {=IF( VLOOKUP( $A18, _xlfn._xlws.FILTER( INDIRECT("'"&H$62&"'!A2:E1000"), (INDIRECT("'"&H$62&"'!B2:B1000")=$B18) * (INDIRECT("'"&H$62&"'!C2:C1000")=$C18) ), 5, FALSE )=0, "", VLOOKUP( $A18, _xlfn._xlws.FILTER( INDIRECT("'"&H$62&"'!A2:E1000"), (INDIRECT("'"&H$62&"'!B2:B1000")=$B18) * (INDIRECT("'"&H$62&"'!C2:C1000")=$C18) ), 5, FALSE ) )} | I18: {=IF( VLOOKUP( $A18, _xlfn._xlws.FILTER( INDIRECT("'"&I$62&"'!A2:E1000"), (INDIRECT("'"&I$62&"'!B2:B1000")=$B18) * (INDIRECT("'"&I$62&"'!C2:C1000")=$C18) ), 5, FALSE )=0, "", VLOOKUP( $A18, _xlfn._xlws.FILTER( INDIRECT("'"&I$62&"'!A2:E1000"), (INDIRECT("'"&I$62&"'!B2:B1000")=$B18) * (INDIRECT("'"&I$62&"'!C2:C1000")=$C18) ), 5, FALSE ) )} | J18: {=IF( VLOOKUP( $A18, _xlfn._xlws.FILTER( INDIRECT("'"&J$62&"'!A2:E1000"), (INDIRECT("'"&J$62&"'!B2:B1000")=$B18) * (INDIRECT("'"&J$62&"'!C2:C1000")=$C18) ), 5, FALSE )=0, "", VLOOKUP( $A18, _xlfn._xlws.FILTER( INDIRECT("'"&J$62&"'!A2:E1000"), (INDIRECT("'"&J$62&"'!B2:B1000")=$B18) * (INDIRECT("'"&J$62&"'!C2:C1000")=$C18) ), 5, FALSE ) )} | K18: {=IF( VLOOKUP( $A18, _xlfn._xlws.FILTER( INDIRECT("'"&K$62&"'!A2:E1000"), (INDIRECT("'"&K$62&"'!B2:B1000")=$B18) * (INDIRECT("'"&K$62&"'!C2:C1000")=$C18) ), 5, FALSE )=0, "", VLOOKUP( $A18, _xlfn._xlws.FILTER( INDIRECT("'"&K$62&"'!A2:E1000"), (INDIRECT("'"&K$62&"'!B2:B1000")=$B18) * (INDIRECT("'"&K$62&"'!C2:C1000")=$C18) ), 5, FALSE ) )} | ... O18: {=IF( VLOOKUP( $A18, _xlfn._xlws.FILTER( INDIRECT("'"&O$62&"'!A2:E1000"), (INDIRECT("'"&O$62&"'!B2:B1000")=$B18) * (INDIRECT("'"&O$62&"'!C2:C1000")=$C18) ), 5, FALSE )=0, "", VLOOKUP( $A18, _xlfn._xlws.FILTER( INDIRECT("'"&O$62&"'!A2:E1000"), (INDIRECT("'"&O$62&"'!B2:B1000")=$B18) * (INDIRECT("'"&O$62&"'!C2:C1000")=$C18) ), 5, FALSE ) )}
A19: Francisco Beltrão | B19: Coronel Vivida | C19: 01 | D19: {=IF( VLOOKUP( $A19, _xlfn._xlws.FILTER( INDIRECT("'"&D$62&"'!A2:E1000"), (INDIRECT("'"&D$62&"'!B2:B1000")=$B19) * (INDIRECT("'"&D$62&"'!C2:C1000")=$C19) ), 5, FALSE )=0, "", VLOOKUP( $A19, _xlfn._xlws.FILTER( INDIRECT("'"&D$62&"'!A2:E1000"), (INDIRECT("'"&D$62&"'!B2:B1000")=$B19) * (INDIRECT("'"&D$62&"'!C2:C1000")=$C19) ), 5, FALSE ) )} | E19: {=IF( VLOOKUP( $A19, _xlfn._xlws.FILTER( INDIRECT("'"&E$62&"'!A2:E1000"), (INDIRECT("'"&E$62&"'!B2:B1000")=$B19) * (INDIRECT("'"&E$62&"'!C2:C1000")=$C19) ), 5, FALSE )=0, "", VLOOKUP( $A19, _xlfn._xlws.FILTER( INDIRECT("'"&E$62&"'!A2:E1000"), (INDIRECT("'"&E$62&"'!B2:B1000")=$B19) * (INDIRECT("'"&E$62&"'!C2:C1000")=$C19) ), 5, FALSE ) )} | F19: {=IF( VLOOKUP( $A19, _xlfn._xlws.FILTER( INDIRECT("'"&F$62&"'!A2:E1000"), (INDIRECT("'"&F$62&"'!B2:B1000")=$B19) * (INDIRECT("'"&F$62&"'!C2:C1000")=$C19) ), 5, FALSE )=0, "", VLOOKUP( $A19, _xlfn._xlws.FILTER( INDIRECT("'"&F$62&"'!A2:E1000"), (INDIRECT("'"&F$62&"'!B2:B1000")=$B19) * (INDIRECT("'"&F$62&"'!C2:C1000")=$C19) ), 5, FALSE ) )} | G19: {=IF( VLOOKUP( $A19, _xlfn._xlws.FILTER( INDIRECT("'"&G$62&"'!A2:E1000"), (INDIRECT("'"&G$62&"'!B2:B1000")=$B19) * (INDIRECT("'"&G$62&"'!C2:C1000")=$C19) ), 5, FALSE )=0, "", VLOOKUP( $A19, _xlfn._xlws.FILTER( INDIRECT("'"&G$62&"'!A2:E1000"), (INDIRECT("'"&G$62&"'!B2:B1000")=$B19) * (INDIRECT("'"&G$62&"'!C2:C1000")=$C19) ), 5, FALSE ) )} | H19: {=IF( VLOOKUP( $A19, _xlfn._xlws.FILTER( INDIRECT("'"&H$62&"'!A2:E1000"), (INDIRECT("'"&H$62&"'!B2:B1000")=$B19) * (INDIRECT("'"&H$62&"'!C2:C1000")=$C19) ), 5, FALSE )=0, "", VLOOKUP( $A19, _xlfn._xlws.FILTER( INDIRECT("'"&H$62&"'!A2:E1000"), (INDIRECT("'"&H$62&"'!B2:B1000")=$B19) * (INDIRECT("'"&H$62&"'!C2:C1000")=$C19) ), 5, FALSE ) )} | I19: {=IF( VLOOKUP( $A19, _xlfn._xlws.FILTER( INDIRECT("'"&I$62&"'!A2:E1000"), (INDIRECT("'"&I$62&"'!B2:B1000")=$B19) * (INDIRECT("'"&I$62&"'!C2:C1000")=$C19) ), 5, FALSE )=0, "", VLOOKUP( $A19, _xlfn._xlws.FILTER( INDIRECT("'"&I$62&"'!A2:E1000"), (INDIRECT("'"&I$62&"'!B2:B1000")=$B19) * (INDIRECT("'"&I$62&"'!C2:C1000")=$C19) ), 5, FALSE ) )} | J19: {=IF( VLOOKUP( $A19, _xlfn._xlws.FILTER( INDIRECT("'"&J$62&"'!A2:E1000"), (INDIRECT("'"&J$62&"'!B2:B1000")=$B19) * (INDIRECT("'"&J$62&"'!C2:C1000")=$C19) ), 5, FALSE )=0, "", VLOOKUP( $A19, _xlfn._xlws.FILTER( INDIRECT("'"&J$62&"'!A2:E1000"), (INDIRECT("'"&J$62&"'!B2:B1000")=$B19) * (INDIRECT("'"&J$62&"'!C2:C1000")=$C19) ), 5, FALSE ) )} | K19: {=IF( VLOOKUP( $A19, _xlfn._xlws.FILTER( INDIRECT("'"&K$62&"'!A2:E1000"), (INDIRECT("'"&K$62&"'!B2:B1000")=$B19) * (INDIRECT("'"&K$62&"'!C2:C1000")=$C19) ), 5, FALSE )=0, "", VLOOKUP( $A19, _xlfn._xlws.FILTER( INDIRECT("'"&K$62&"'!A2:E1000"), (INDIRECT("'"&K$62&"'!B2:B1000")=$B19) * (INDIRECT("'"&K$62&"'!C2:C1000")=$C19) ), 5, FALSE ) )} | ... O19: {=IF( VLOOKUP( $A19, _xlfn._xlws.FILTER( INDIRECT("'"&O$62&"'!A2:E1000"), (INDIRECT("'"&O$62&"'!B2:B1000")=$B19) * (INDIRECT("'"&O$62&"'!C2:C1000")=$C19) ), 5, FALSE )=0, "", VLOOKUP( $A19, _xlfn._xlws.FILTER( INDIRECT("'"&O$62&"'!A2:E1000"), (INDIRECT("'"&O$62&"'!B2:B1000")=$B19) * (INDIRECT("'"&O$62&"'!C2:C1000")=$C19) ), 5, FALSE ) )}
A20: Francisco Beltrão | B20: Enéas Marques | C20: 01 | D20: {=IF( VLOOKUP( $A20, _xlfn._xlws.FILTER( INDIRECT("'"&D$62&"'!A2:E1000"), (INDIRECT("'"&D$62&"'!B2:B1000")=$B20) * (INDIRECT("'"&D$62&"'!C2:C1000")=$C20) ), 5, FALSE )=0, "", VLOOKUP( $A20, _xlfn._xlws.FILTER( INDIRECT("'"&D$62&"'!A2:E1000"), (INDIRECT("'"&D$62&"'!B2:B1000")=$B20) * (INDIRECT("'"&D$62&"'!C2:C1000")=$C20) ), 5, FALSE ) )} | E20: {=IF( VLOOKUP( $A20, _xlfn._xlws.FILTER( INDIRECT("'"&E$62&"'!A2:E1000"), (INDIRECT("'"&E$62&"'!B2:B1000")=$B20) * (INDIRECT("'"&E$62&"'!C2:C1000")=$C20) ), 5, FALSE )=0, "", VLOOKUP( $A20, _xlfn._xlws.FILTER( INDIRECT("'"&E$62&"'!A2:E1000"), (INDIRECT("'"&E$62&"'!B2:B1000")=$B20) * (INDIRECT("'"&E$62&"'!C2:C1000")=$C20) ), 5, FALSE ) )} | F20: {=IF( VLOOKUP( $A20, _xlfn._xlws.FILTER( INDIRECT("'"&F$62&"'!A2:E1000"), (INDIRECT("'"&F$62&"'!B2:B1000")=$B20) * (INDIRECT("'"&F$62&"'!C2:C1000")=$C20) ), 5, FALSE )=0, "", VLOOKUP( $A20, _xlfn._xlws.FILTER( INDIRECT("'"&F$62&"'!A2:E1000"), (INDIRECT("'"&F$62&"'!B2:B1000")=$B20) * (INDIRECT("'"&F$62&"'!C2:C1000")=$C20) ), 5, FALSE ) )} | G20: {=IF( VLOOKUP( $A20, _xlfn._xlws.FILTER( INDIRECT("'"&G$62&"'!A2:E1000"), (INDIRECT("'"&G$62&"'!B2:B1000")=$B20) * (INDIRECT("'"&G$62&"'!C2:C1000")=$C20) ), 5, FALSE )=0, "", VLOOKUP( $A20, _xlfn._xlws.FILTER( INDIRECT("'"&G$62&"'!A2:E1000"), (INDIRECT("'"&G$62&"'!B2:B1000")=$B20) * (INDIRECT("'"&G$62&"'!C2:C1000")=$C20) ), 5, FALSE ) )} | H20: {=IF( VLOOKUP( $A20, _xlfn._xlws.FILTER( INDIRECT("'"&H$62&"'!A2:E1000"), (INDIRECT("'"&H$62&"'!B2:B1000")=$B20) * (INDIRECT("'"&H$62&"'!C2:C1000")=$C20) ), 5, FALSE )=0, "", VLOOKUP( $A20, _xlfn._xlws.FILTER( INDIRECT("'"&H$62&"'!A2:E1000"), (INDIRECT("'"&H$62&"'!B2:B1000")=$B20) * (INDIRECT("'"&H$62&"'!C2:C1000")=$C20) ), 5, FALSE ) )} | I20: {=IF( VLOOKUP( $A20, _xlfn._xlws.FILTER( INDIRECT("'"&I$62&"'!A2:E1000"), (INDIRECT("'"&I$62&"'!B2:B1000")=$B20) * (INDIRECT("'"&I$62&"'!C2:C1000")=$C20) ), 5, FALSE )=0, "", VLOOKUP( $A20, _xlfn._xlws.FILTER( INDIRECT("'"&I$62&"'!A2:E1000"), (INDIRECT("'"&I$62&"'!B2:B1000")=$B20) * (INDIRECT("'"&I$62&"'!C2:C1000")=$C20) ), 5, FALSE ) )} | J20: {=IF( VLOOKUP( $A20, _xlfn._xlws.FILTER( INDIRECT("'"&J$62&"'!A2:E1000"), (INDIRECT("'"&J$62&"'!B2:B1000")=$B20) * (INDIRECT("'"&J$62&"'!C2:C1000")=$C20) ), 5, FALSE )=0, "", VLOOKUP( $A20, _xlfn._xlws.FILTER( INDIRECT("'"&J$62&"'!A2:E1000"), (INDIRECT("'"&J$62&"'!B2:B1000")=$B20) * (INDIRECT("'"&J$62&"'!C2:C1000")=$C20) ), 5, FALSE ) )} | K20: {=IF( VLOOKUP( $A20, _xlfn._xlws.FILTER( INDIRECT("'"&K$62&"'!A2:E1000"), (INDIRECT("'"&K$62&"'!B2:B1000")=$B20) * (INDIRECT("'"&K$62&"'!C2:C1000")=$C20) ), 5, FALSE )=0, "", VLOOKUP( $A20, _xlfn._xlws.FILTER( INDIRECT("'"&K$62&"'!A2:E1000"), (INDIRECT("'"&K$62&"'!B2:B1000")=$B20) * (INDIRECT("'"&K$62&"'!C2:C1000")=$C20) ), 5, FALSE ) )} | ... O20: {=IF( VLOOKUP( $A20, _xlfn._xlws.FILTER( INDIRECT("'"&O$62&"'!A2:E1000"), (INDIRECT("'"&O$62&"'!B2:B1000")=$B20) * (INDIRECT("'"&O$62&"'!C2:C1000")=$C20) ), 5, FALSE )=0, "", VLOOKUP( $A20, _xlfn._xlws.FILTER( INDIRECT("'"&O$62&"'!A2:E1000"), (INDIRECT("'"&O$62&"'!B2:B1000")=$B20) * (INDIRECT("'"&O$62&"'!C2:C1000")=$C20) ), 5, FALSE ) )}
A21: Francisco Beltrão | B21: Francisco Beltrão | C21: 01 | D21: {=IF( VLOOKUP( $A21, _xlfn._xlws.FILTER( INDIRECT("'"&D$62&"'!A2:E1000"), (INDIRECT("'"&D$62&"'!B2:B1000")=$B21) * (INDIRECT("'"&D$62&"'!C2:C1000")=$C21) ), 5, FALSE )=0, "", VLOOKUP( $A21, _xlfn._xlws.FILTER( INDIRECT("'"&D$62&"'!A2:E1000"), (INDIRECT("'"&D$62&"'!B2:B1000")=$B21) * (INDIRECT("'"&D$62&"'!C2:C1000")=$C21) ), 5, FALSE ) )} | E21: {=IF( VLOOKUP( $A21, _xlfn._xlws.FILTER( INDIRECT("'"&E$62&"'!A2:E1000"), (INDIRECT("'"&E$62&"'!B2:B1000")=$B21) * (INDIRECT("'"&E$62&"'!C2:C1000")=$C21) ), 5, FALSE )=0, "", VLOOKUP( $A21, _xlfn._xlws.FILTER( INDIRECT("'"&E$62&"'!A2:E1000"), (INDIRECT("'"&E$62&"'!B2:B1000")=$B21) * (INDIRECT("'"&E$62&"'!C2:C1000")=$C21) ), 5, FALSE ) )} | F21: {=IF( VLOOKUP( $A21, _xlfn._xlws.FILTER( INDIRECT("'"&F$62&"'!A2:E1000"), (INDIRECT("'"&F$62&"'!B2:B1000")=$B21) * (INDIRECT("'"&F$62&"'!C2:C1000")=$C21) ), 5, FALSE )=0, "", VLOOKUP( $A21, _xlfn._xlws.FILTER( INDIRECT("'"&F$62&"'!A2:E1000"), (INDIRECT("'"&F$62&"'!B2:B1000")=$B21) * (INDIRECT("'"&F$62&"'!C2:C1000")=$C21) ), 5, FALSE ) )} | G21: {=IF( VLOOKUP( $A21, _xlfn._xlws.FILTER( INDIRECT("'"&G$62&"'!A2:E1000"), (INDIRECT("'"&G$62&"'!B2:B1000")=$B21) * (INDIRECT("'"&G$62&"'!C2:C1000")=$C21) ), 5, FALSE )=0, "", VLOOKUP( $A21, _xlfn._xlws.FILTER( INDIRECT("'"&G$62&"'!A2:E1000"), (INDIRECT("'"&G$62&"'!B2:B1000")=$B21) * (INDIRECT("'"&G$62&"'!C2:C1000")=$C21) ), 5, FALSE ) )} | H21: {=IF( VLOOKUP( $A21, _xlfn._xlws.FILTER( INDIRECT("'"&H$62&"'!A2:E1000"), (INDIRECT("'"&H$62&"'!B2:B1000")=$B21) * (INDIRECT("'"&H$62&"'!C2:C1000")=$C21) ), 5, FALSE )=0, "", VLOOKUP( $A21, _xlfn._xlws.FILTER( INDIRECT("'"&H$62&"'!A2:E1000"), (INDIRECT("'"&H$62&"'!B2:B1000")=$B21) * (INDIRECT("'"&H$62&"'!C2:C1000")=$C21) ), 5, FALSE ) )} | I21: {=IF( VLOOKUP( $A21, _xlfn._xlws.FILTER( INDIRECT("'"&I$62&"'!A2:E1000"), (INDIRECT("'"&I$62&"'!B2:B1000")=$B21) * (INDIRECT("'"&I$62&"'!C2:C1000")=$C21) ), 5, FALSE )=0, "", VLOOKUP( $A21, _xlfn._xlws.FILTER( INDIRECT("'"&I$62&"'!A2:E1000"), (INDIRECT("'"&I$62&"'!B2:B1000")=$B21) * (INDIRECT("'"&I$62&"'!C2:C1000")=$C21) ), 5, FALSE ) )} | J21: {=IF( VLOOKUP( $A21, _xlfn._xlws.FILTER( INDIRECT("'"&J$62&"'!A2:E1000"), (INDIRECT("'"&J$62&"'!B2:B1000")=$B21) * (INDIRECT("'"&J$62&"'!C2:C1000")=$C21) ), 5, FALSE )=0, "", VLOOKUP( $A21, _xlfn._xlws.FILTER( INDIRECT("'"&J$62&"'!A2:E1000"), (INDIRECT("'"&J$62&"'!B2:B1000")=$B21) * (INDIRECT("'"&J$62&"'!C2:C1000")=$C21) ), 5, FALSE ) )} | K21: {=IF( VLOOKUP( $A21, _xlfn._xlws.FILTER( INDIRECT("'"&K$62&"'!A2:E1000"), (INDIRECT("'"&K$62&"'!B2:B1000")=$B21) * (INDIRECT("'"&K$62&"'!C2:C1000")=$C21) ), 5, FALSE )=0, "", VLOOKUP( $A21, _xlfn._xlws.FILTER( INDIRECT("'"&K$62&"'!A2:E1000"), (INDIRECT("'"&K$62&"'!B2:B1000")=$B21) * (INDIRECT("'"&K$62&"'!C2:C1000")=$C21) ), 5, FALSE ) )} | ... O21: {=IF( VLOOKUP( $A21, _xlfn._xlws.FILTER( INDIRECT("'"&O$62&"'!A2:E1000"), (INDIRECT("'"&O$62&"'!B2:B1000")=$B21) * (INDIRECT("'"&O$62&"'!C2:C1000")=$C21) ), 5, FALSE )=0, "", VLOOKUP( $A21, _xlfn._xlws.FILTER( INDIRECT("'"&O$62&"'!A2:E1000"), (INDIRECT("'"&O$62&"'!B2:B1000")=$B21) * (INDIRECT("'"&O$62&"'!C2:C1000")=$C21) ), 5, FALSE ) )}
A22: Francisco Beltrão | B22: Francisco Beltrão | C22: 02 | D22: {=IF( VLOOKUP( $A22, _xlfn._xlws.FILTER( INDIRECT("'"&D$62&"'!A2:E1000"), (INDIRECT("'"&D$62&"'!B2:B1000")=$B22) * (INDIRECT("'"&D$62&"'!C2:C1000")=$C22) ), 5, FALSE )=0, "", VLOOKUP( $A22, _xlfn._xlws.FILTER( INDIRECT("'"&D$62&"'!A2:E1000"), (INDIRECT("'"&D$62&"'!B2:B1000")=$B22) * (INDIRECT("'"&D$62&"'!C2:C1000")=$C22) ), 5, FALSE ) )} | E22: {=IF( VLOOKUP( $A22, _xlfn._xlws.FILTER( INDIRECT("'"&E$62&"'!A2:E1000"), (INDIRECT("'"&E$62&"'!B2:B1000")=$B22) * (INDIRECT("'"&E$62&"'!C2:C1000")=$C22) ), 5, FALSE )=0, "", VLOOKUP( $A22, _xlfn._xlws.FILTER( INDIRECT("'"&E$62&"'!A2:E1000"), (INDIRECT("'"&E$62&"'!B2:B1000")=$B22) * (INDIRECT("'"&E$62&"'!C2:C1000")=$C22) ), 5, FALSE ) )} | F22: {=IF( VLOOKUP( $A22, _xlfn._xlws.FILTER( INDIRECT("'"&F$62&"'!A2:E1000"), (INDIRECT("'"&F$62&"'!B2:B1000")=$B22) * (INDIRECT("'"&F$62&"'!C2:C1000")=$C22) ), 5, FALSE )=0, "", VLOOKUP( $A22, _xlfn._xlws.FILTER( INDIRECT("'"&F$62&"'!A2:E1000"), (INDIRECT("'"&F$62&"'!B2:B1000")=$B22) * (INDIRECT("'"&F$62&"'!C2:C1000")=$C22) ), 5, FALSE ) )} | G22: {=IF( VLOOKUP( $A22, _xlfn._xlws.FILTER( INDIRECT("'"&G$62&"'!A2:E1000"), (INDIRECT("'"&G$62&"'!B2:B1000")=$B22) * (INDIRECT("'"&G$62&"'!C2:C1000")=$C22) ), 5, FALSE )=0, "", VLOOKUP( $A22, _xlfn._xlws.FILTER( INDIRECT("'"&G$62&"'!A2:E1000"), (INDIRECT("'"&G$62&"'!B2:B1000")=$B22) * (INDIRECT("'"&G$62&"'!C2:C1000")=$C22) ), 5, FALSE ) )} | H22: {=IF( VLOOKUP( $A22, _xlfn._xlws.FILTER( INDIRECT("'"&H$62&"'!A2:E1000"), (INDIRECT("'"&H$62&"'!B2:B1000")=$B22) * (INDIRECT("'"&H$62&"'!C2:C1000")=$C22) ), 5, FALSE )=0, "", VLOOKUP( $A22, _xlfn._xlws.FILTER( INDIRECT("'"&H$62&"'!A2:E1000"), (INDIRECT("'"&H$62&"'!B2:B1000")=$B22) * (INDIRECT("'"&H$62&"'!C2:C1000")=$C22) ), 5, FALSE ) )} | I22: {=IF( VLOOKUP( $A22, _xlfn._xlws.FILTER( INDIRECT("'"&I$62&"'!A2:E1000"), (INDIRECT("'"&I$62&"'!B2:B1000")=$B22) * (INDIRECT("'"&I$62&"'!C2:C1000")=$C22) ), 5, FALSE )=0, "", VLOOKUP( $A22, _xlfn._xlws.FILTER( INDIRECT("'"&I$62&"'!A2:E1000"), (INDIRECT("'"&I$62&"'!B2:B1000")=$B22) * (INDIRECT("'"&I$62&"'!C2:C1000")=$C22) ), 5, FALSE ) )} | J22: {=IF( VLOOKUP( $A22, _xlfn._xlws.FILTER( INDIRECT("'"&J$62&"'!A2:E1000"), (INDIRECT("'"&J$62&"'!B2:B1000")=$B22) * (INDIRECT("'"&J$62&"'!C2:C1000")=$C22) ), 5, FALSE )=0, "", VLOOKUP( $A22, _xlfn._xlws.FILTER( INDIRECT("'"&J$62&"'!A2:E1000"), (INDIRECT("'"&J$62&"'!B2:B1000")=$B22) * (INDIRECT("'"&J$62&"'!C2:C1000")=$C22) ), 5, FALSE ) )} | K22: {=IF( VLOOKUP( $A22, _xlfn._xlws.FILTER( INDIRECT("'"&K$62&"'!A2:E1000"), (INDIRECT("'"&K$62&"'!B2:B1000")=$B22) * (INDIRECT("'"&K$62&"'!C2:C1000")=$C22) ), 5, FALSE )=0, "", VLOOKUP( $A22, _xlfn._xlws.FILTER( INDIRECT("'"&K$62&"'!A2:E1000"), (INDIRECT("'"&K$62&"'!B2:B1000")=$B22) * (INDIRECT("'"&K$62&"'!C2:C1000")=$C22) ), 5, FALSE ) )} | ... O22: {=IF( VLOOKUP( $A22, _xlfn._xlws.FILTER( INDIRECT("'"&O$62&"'!A2:E1000"), (INDIRECT("'"&O$62&"'!B2:B1000")=$B22) * (INDIRECT("'"&O$62&"'!C2:C1000")=$C22) ), 5, FALSE )=0, "", VLOOKUP( $A22, _xlfn._xlws.FILTER( INDIRECT("'"&O$62&"'!A2:E1000"), (INDIRECT("'"&O$62&"'!B2:B1000")=$B22) * (INDIRECT("'"&O$62&"'!C2:C1000")=$C22) ), 5, FALSE ) )}
A23: Francisco Beltrão | B23: Francisco Beltrão | C23: 03 | D23: {=IF( VLOOKUP( $A23, _xlfn._xlws.FILTER( INDIRECT("'"&D$62&"'!A2:E1000"), (INDIRECT("'"&D$62&"'!B2:B1000")=$B23) * (INDIRECT("'"&D$62&"'!C2:C1000")=$C23) ), 5, FALSE )=0, "", VLOOKUP( $A23, _xlfn._xlws.FILTER( INDIRECT("'"&D$62&"'!A2:E1000"), (INDIRECT("'"&D$62&"'!B2:B1000")=$B23) * (INDIRECT("'"&D$62&"'!C2:C1000")=$C23) ), 5, FALSE ) )} | E23: {=IF( VLOOKUP( $A23, _xlfn._xlws.FILTER( INDIRECT("'"&E$62&"'!A2:E1000"), (INDIRECT("'"&E$62&"'!B2:B1000")=$B23) * (INDIRECT("'"&E$62&"'!C2:C1000")=$C23) ), 5, FALSE )=0, "", VLOOKUP( $A23, _xlfn._xlws.FILTER( INDIRECT("'"&E$62&"'!A2:E1000"), (INDIRECT("'"&E$62&"'!B2:B1000")=$B23) * (INDIRECT("'"&E$62&"'!C2:C1000")=$C23) ), 5, FALSE ) )} | F23: {=IF( VLOOKUP( $A23, _xlfn._xlws.FILTER( INDIRECT("'"&F$62&"'!A2:E1000"), (INDIRECT("'"&F$62&"'!B2:B1000")=$B23) * (INDIRECT("'"&F$62&"'!C2:C1000")=$C23) ), 5, FALSE )=0, "", VLOOKUP( $A23, _xlfn._xlws.FILTER( INDIRECT("'"&F$62&"'!A2:E1000"), (INDIRECT("'"&F$62&"'!B2:B1000")=$B23) * (INDIRECT("'"&F$62&"'!C2:C1000")=$C23) ), 5, FALSE ) )} | G23: {=IF( VLOOKUP( $A23, _xlfn._xlws.FILTER( INDIRECT("'"&G$62&"'!A2:E1000"), (INDIRECT("'"&G$62&"'!B2:B1000")=$B23) * (INDIRECT("'"&G$62&"'!C2:C1000")=$C23) ), 5, FALSE )=0, "", VLOOKUP( $A23, _xlfn._xlws.FILTER( INDIRECT("'"&G$62&"'!A2:E1000"), (INDIRECT("'"&G$62&"'!B2:B1000")=$B23) * (INDIRECT("'"&G$62&"'!C2:C1000")=$C23) ), 5, FALSE ) )} | H23: {=IF( VLOOKUP( $A23, _xlfn._xlws.FILTER( INDIRECT("'"&H$62&"'!A2:E1000"), (INDIRECT("'"&H$62&"'!B2:B1000")=$B23) * (INDIRECT("'"&H$62&"'!C2:C1000")=$C23) ), 5, FALSE )=0, "", VLOOKUP( $A23, _xlfn._xlws.FILTER( INDIRECT("'"&H$62&"'!A2:E1000"), (INDIRECT("'"&H$62&"'!B2:B1000")=$B23) * (INDIRECT("'"&H$62&"'!C2:C1000")=$C23) ), 5, FALSE ) )} | I23: {=IF( VLOOKUP( $A23, _xlfn._xlws.FILTER( INDIRECT("'"&I$62&"'!A2:E1000"), (INDIRECT("'"&I$62&"'!B2:B1000")=$B23) * (INDIRECT("'"&I$62&"'!C2:C1000")=$C23) ), 5, FALSE )=0, "", VLOOKUP( $A23, _xlfn._xlws.FILTER( INDIRECT("'"&I$62&"'!A2:E1000"), (INDIRECT("'"&I$62&"'!B2:B1000")=$B23) * (INDIRECT("'"&I$62&"'!C2:C1000")=$C23) ), 5, FALSE ) )} | J23: {=IF( VLOOKUP( $A23, _xlfn._xlws.FILTER( INDIRECT("'"&J$62&"'!A2:E1000"), (INDIRECT("'"&J$62&"'!B2:B1000")=$B23) * (INDIRECT("'"&J$62&"'!C2:C1000")=$C23) ), 5, FALSE )=0, "", VLOOKUP( $A23, _xlfn._xlws.FILTER( INDIRECT("'"&J$62&"'!A2:E1000"), (INDIRECT("'"&J$62&"'!B2:B1000")=$B23) * (INDIRECT("'"&J$62&"'!C2:C1000")=$C23) ), 5, FALSE ) )} | K23: {=IF( VLOOKUP( $A23, _xlfn._xlws.FILTER( INDIRECT("'"&K$62&"'!A2:E1000"), (INDIRECT("'"&K$62&"'!B2:B1000")=$B23) * (INDIRECT("'"&K$62&"'!C2:C1000")=$C23) ), 5, FALSE )=0, "", VLOOKUP( $A23, _xlfn._xlws.FILTER( INDIRECT("'"&K$62&"'!A2:E1000"), (INDIRECT("'"&K$62&"'!B2:B1000")=$B23) * (INDIRECT("'"&K$62&"'!C2:C1000")=$C23) ), 5, FALSE ) )} | ... O23: {=IF( VLOOKUP( $A23, _xlfn._xlws.FILTER( INDIRECT("'"&O$62&"'!A2:E1000"), (INDIRECT("'"&O$62&"'!B2:B1000")=$B23) * (INDIRECT("'"&O$62&"'!C2:C1000")=$C23) ), 5, FALSE )=0, "", VLOOKUP( $A23, _xlfn._xlws.FILTER( INDIRECT("'"&O$62&"'!A2:E1000"), (INDIRECT("'"&O$62&"'!B2:B1000")=$B23) * (INDIRECT("'"&O$62&"'!C2:C1000")=$C23) ), 5, FALSE ) )}
A24: Francisco Beltrão | B24: Marmeleiro | C24: 01 | D24: {=IF( VLOOKUP( $A24, _xlfn._xlws.FILTER( INDIRECT("'"&D$62&"'!A2:E1000"), (INDIRECT("'"&D$62&"'!B2:B1000")=$B24) * (INDIRECT("'"&D$62&"'!C2:C1000")=$C24) ), 5, FALSE )=0, "", VLOOKUP( $A24, _xlfn._xlws.FILTER( INDIRECT("'"&D$62&"'!A2:E1000"), (INDIRECT("'"&D$62&"'!B2:B1000")=$B24) * (INDIRECT("'"&D$62&"'!C2:C1000")=$C24) ), 5, FALSE ) )} | E24: {=IF( VLOOKUP( $A24, _xlfn._xlws.FILTER( INDIRECT("'"&E$62&"'!A2:E1000"), (INDIRECT("'"&E$62&"'!B2:B1000")=$B24) * (INDIRECT("'"&E$62&"'!C2:C1000")=$C24) ), 5, FALSE )=0, "", VLOOKUP( $A24, _xlfn._xlws.FILTER( INDIRECT("'"&E$62&"'!A2:E1000"), (INDIRECT("'"&E$62&"'!B2:B1000")=$B24) * (INDIRECT("'"&E$62&"'!C2:C1000")=$C24) ), 5, FALSE ) )} | F24: {=IF( VLOOKUP( $A24, _xlfn._xlws.FILTER( INDIRECT("'"&F$62&"'!A2:E1000"), (INDIRECT("'"&F$62&"'!B2:B1000")=$B24) * (INDIRECT("'"&F$62&"'!C2:C1000")=$C24) ), 5, FALSE )=0, "", VLOOKUP( $A24, _xlfn._xlws.FILTER( INDIRECT("'"&F$62&"'!A2:E1000"), (INDIRECT("'"&F$62&"'!B2:B1000")=$B24) * (INDIRECT("'"&F$62&"'!C2:C1000")=$C24) ), 5, FALSE ) )} | G24: {=IF( VLOOKUP( $A24, _xlfn._xlws.FILTER( INDIRECT("'"&G$62&"'!A2:E1000"), (INDIRECT("'"&G$62&"'!B2:B1000")=$B24) * (INDIRECT("'"&G$62&"'!C2:C1000")=$C24) ), 5, FALSE )=0, "", VLOOKUP( $A24, _xlfn._xlws.FILTER( INDIRECT("'"&G$62&"'!A2:E1000"), (INDIRECT("'"&G$62&"'!B2:B1000")=$B24) * (INDIRECT("'"&G$62&"'!C2:C1000")=$C24) ), 5, FALSE ) )} | H24: {=IF( VLOOKUP( $A24, _xlfn._xlws.FILTER( INDIRECT("'"&H$62&"'!A2:E1000"), (INDIRECT("'"&H$62&"'!B2:B1000")=$B24) * (INDIRECT("'"&H$62&"'!C2:C1000")=$C24) ), 5, FALSE )=0, "", VLOOKUP( $A24, _xlfn._xlws.FILTER( INDIRECT("'"&H$62&"'!A2:E1000"), (INDIRECT("'"&H$62&"'!B2:B1000")=$B24) * (INDIRECT("'"&H$62&"'!C2:C1000")=$C24) ), 5, FALSE ) )} | I24: {=IF( VLOOKUP( $A24, _xlfn._xlws.FILTER( INDIRECT("'"&I$62&"'!A2:E1000"), (INDIRECT("'"&I$62&"'!B2:B1000")=$B24) * (INDIRECT("'"&I$62&"'!C2:C1000")=$C24) ), 5, FALSE )=0, "", VLOOKUP( $A24, _xlfn._xlws.FILTER( INDIRECT("'"&I$62&"'!A2:E1000"), (INDIRECT("'"&I$62&"'!B2:B1000")=$B24) * (INDIRECT("'"&I$62&"'!C2:C1000")=$C24) ), 5, FALSE ) )} | J24: {=IF( VLOOKUP( $A24, _xlfn._xlws.FILTER( INDIRECT("'"&J$62&"'!A2:E1000"), (INDIRECT("'"&J$62&"'!B2:B1000")=$B24) * (INDIRECT("'"&J$62&"'!C2:C1000")=$C24) ), 5, FALSE )=0, "", VLOOKUP( $A24, _xlfn._xlws.FILTER( INDIRECT("'"&J$62&"'!A2:E1000"), (INDIRECT("'"&J$62&"'!B2:B1000")=$B24) * (INDIRECT("'"&J$62&"'!C2:C1000")=$C24) ), 5, FALSE ) )} | K24: {=IF( VLOOKUP( $A24, _xlfn._xlws.FILTER( INDIRECT("'"&K$62&"'!A2:E1000"), (INDIRECT("'"&K$62&"'!B2:B1000")=$B24) * (INDIRECT("'"&K$62&"'!C2:C1000")=$C24) ), 5, FALSE )=0, "", VLOOKUP( $A24, _xlfn._xlws.FILTER( INDIRECT("'"&K$62&"'!A2:E1000"), (INDIRECT("'"&K$62&"'!B2:B1000")=$B24) * (INDIRECT("'"&K$62&"'!C2:C1000")=$C24) ), 5, FALSE ) )} | ... O24: {=IF( VLOOKUP( $A24, _xlfn._xlws.FILTER( INDIRECT("'"&O$62&"'!A2:E1000"), (INDIRECT("'"&O$62&"'!B2:B1000")=$B24) * (INDIRECT("'"&O$62&"'!C2:C1000")=$C24) ), 5, FALSE )=0, "", VLOOKUP( $A24, _xlfn._xlws.FILTER( INDIRECT("'"&O$62&"'!A2:E1000"), (INDIRECT("'"&O$62&"'!B2:B1000")=$B24) * (INDIRECT("'"&O$62&"'!C2:C1000")=$C24) ), 5, FALSE ) )}
A25: Francisco Beltrão | B25: Realeza | C25: 01 | D25: {=IF( VLOOKUP( $A25, _xlfn._xlws.FILTER( INDIRECT("'"&D$62&"'!A2:E1000"), (INDIRECT("'"&D$62&"'!B2:B1000")=$B25) * (INDIRECT("'"&D$62&"'!C2:C1000")=$C25) ), 5, FALSE )=0, "", VLOOKUP( $A25, _xlfn._xlws.FILTER( INDIRECT("'"&D$62&"'!A2:E1000"), (INDIRECT("'"&D$62&"'!B2:B1000")=$B25) * (INDIRECT("'"&D$62&"'!C2:C1000")=$C25) ), 5, FALSE ) )} | E25: {=IF( VLOOKUP( $A25, _xlfn._xlws.FILTER( INDIRECT("'"&E$62&"'!A2:E1000"), (INDIRECT("'"&E$62&"'!B2:B1000")=$B25) * (INDIRECT("'"&E$62&"'!C2:C1000")=$C25) ), 5, FALSE )=0, "", VLOOKUP( $A25, _xlfn._xlws.FILTER( INDIRECT("'"&E$62&"'!A2:E1000"), (INDIRECT("'"&E$62&"'!B2:B1000")=$B25) * (INDIRECT("'"&E$62&"'!C2:C1000")=$C25) ), 5, FALSE ) )} | F25: {=IF( VLOOKUP( $A25, _xlfn._xlws.FILTER( INDIRECT("'"&F$62&"'!A2:E1000"), (INDIRECT("'"&F$62&"'!B2:B1000")=$B25) * (INDIRECT("'"&F$62&"'!C2:C1000")=$C25) ), 5, FALSE )=0, "", VLOOKUP( $A25, _xlfn._xlws.FILTER( INDIRECT("'"&F$62&"'!A2:E1000"), (INDIRECT("'"&F$62&"'!B2:B1000")=$B25) * (INDIRECT("'"&F$62&"'!C2:C1000")=$C25) ), 5, FALSE ) )} | G25: {=IF( VLOOKUP( $A25, _xlfn._xlws.FILTER( INDIRECT("'"&G$62&"'!A2:E1000"), (INDIRECT("'"&G$62&"'!B2:B1000")=$B25) * (INDIRECT("'"&G$62&"'!C2:C1000")=$C25) ), 5, FALSE )=0, "", VLOOKUP( $A25, _xlfn._xlws.FILTER( INDIRECT("'"&G$62&"'!A2:E1000"), (INDIRECT("'"&G$62&"'!B2:B1000")=$B25) * (INDIRECT("'"&G$62&"'!C2:C1000")=$C25) ), 5, FALSE ) )} | H25: {=IF( VLOOKUP( $A25, _xlfn._xlws.FILTER( INDIRECT("'"&H$62&"'!A2:E1000"), (INDIRECT("'"&H$62&"'!B2:B1000")=$B25) * (INDIRECT("'"&H$62&"'!C2:C1000")=$C25) ), 5, FALSE )=0, "", VLOOKUP( $A25, _xlfn._xlws.FILTER( INDIRECT("'"&H$62&"'!A2:E1000"), (INDIRECT("'"&H$62&"'!B2:B1000")=$B25) * (INDIRECT("'"&H$62&"'!C2:C1000")=$C25) ), 5, FALSE ) )} | I25: {=IF( VLOOKUP( $A25, _xlfn._xlws.FILTER( INDIRECT("'"&I$62&"'!A2:E1000"), (INDIRECT("'"&I$62&"'!B2:B1000")=$B25) * (INDIRECT("'"&I$62&"'!C2:C1000")=$C25) ), 5, FALSE )=0, "", VLOOKUP( $A25, _xlfn._xlws.FILTER( INDIRECT("'"&I$62&"'!A2:E1000"), (INDIRECT("'"&I$62&"'!B2:B1000")=$B25) * (INDIRECT("'"&I$62&"'!C2:C1000")=$C25) ), 5, FALSE ) )} | J25: {=IF( VLOOKUP( $A25, _xlfn._xlws.FILTER( INDIRECT("'"&J$62&"'!A2:E1000"), (INDIRECT("'"&J$62&"'!B2:B1000")=$B25) * (INDIRECT("'"&J$62&"'!C2:C1000")=$C25) ), 5, FALSE )=0, "", VLOOKUP( $A25, _xlfn._xlws.FILTER( INDIRECT("'"&J$62&"'!A2:E1000"), (INDIRECT("'"&J$62&"'!B2:B1000")=$B25) * (INDIRECT("'"&J$62&"'!C2:C1000")=$C25) ), 5, FALSE ) )} | K25: {=IF( VLOOKUP( $A25, _xlfn._xlws.FILTER( INDIRECT("'"&K$62&"'!A2:E1000"), (INDIRECT("'"&K$62&"'!B2:B1000")=$B25) * (INDIRECT("'"&K$62&"'!C2:C1000")=$C25) ), 5, FALSE )=0, "", VLOOKUP( $A25, _xlfn._xlws.FILTER( INDIRECT("'"&K$62&"'!A2:E1000"), (INDIRECT("'"&K$62&"'!B2:B1000")=$B25) * (INDIRECT("'"&K$62&"'!C2:C1000")=$C25) ), 5, FALSE ) )} | ... O25: {=IF( VLOOKUP( $A25, _xlfn._xlws.FILTER( INDIRECT("'"&O$62&"'!A2:E1000"), (INDIRECT("'"&O$62&"'!B2:B1000")=$B25) * (INDIRECT("'"&O$62&"'!C2:C1000")=$C25) ), 5, FALSE )=0, "", VLOOKUP( $A25, _xlfn._xlws.FILTER( INDIRECT("'"&O$62&"'!A2:E1000"), (INDIRECT("'"&O$62&"'!B2:B1000")=$B25) * (INDIRECT("'"&O$62&"'!C2:C1000")=$C25) ), 5, FALSE ) )}
A26: Francisco Beltrão | B26: Salgado Filho | C26: 01 | D26: {=IF( VLOOKUP( $A26, _xlfn._xlws.FILTER( INDIRECT("'"&D$62&"'!A2:E1000"), (INDIRECT("'"&D$62&"'!B2:B1000")=$B26) * (INDIRECT("'"&D$62&"'!C2:C1000")=$C26) ), 5, FALSE )=0, "", VLOOKUP( $A26, _xlfn._xlws.FILTER( INDIRECT("'"&D$62&"'!A2:E1000"), (INDIRECT("'"&D$62&"'!B2:B1000")=$B26) * (INDIRECT("'"&D$62&"'!C2:C1000")=$C26) ), 5, FALSE ) )} | E26: {=IF( VLOOKUP( $A26, _xlfn._xlws.FILTER( INDIRECT("'"&E$62&"'!A2:E1000"), (INDIRECT("'"&E$62&"'!B2:B1000")=$B26) * (INDIRECT("'"&E$62&"'!C2:C1000")=$C26) ), 5, FALSE )=0, "", VLOOKUP( $A26, _xlfn._xlws.FILTER( INDIRECT("'"&E$62&"'!A2:E1000"), (INDIRECT("'"&E$62&"'!B2:B1000")=$B26) * (INDIRECT("'"&E$62&"'!C2:C1000")=$C26) ), 5, FALSE ) )} | F26: {=IF( VLOOKUP( $A26, _xlfn._xlws.FILTER( INDIRECT("'"&F$62&"'!A2:E1000"), (INDIRECT("'"&F$62&"'!B2:B1000")=$B26) * (INDIRECT("'"&F$62&"'!C2:C1000")=$C26) ), 5, FALSE )=0, "", VLOOKUP( $A26, _xlfn._xlws.FILTER( INDIRECT("'"&F$62&"'!A2:E1000"), (INDIRECT("'"&F$62&"'!B2:B1000")=$B26) * (INDIRECT("'"&F$62&"'!C2:C1000")=$C26) ), 5, FALSE ) )} | G26: {=IF( VLOOKUP( $A26, _xlfn._xlws.FILTER( INDIRECT("'"&G$62&"'!A2:E1000"), (INDIRECT("'"&G$62&"'!B2:B1000")=$B26) * (INDIRECT("'"&G$62&"'!C2:C1000")=$C26) ), 5, FALSE )=0, "", VLOOKUP( $A26, _xlfn._xlws.FILTER( INDIRECT("'"&G$62&"'!A2:E1000"), (INDIRECT("'"&G$62&"'!B2:B1000")=$B26) * (INDIRECT("'"&G$62&"'!C2:C1000")=$C26) ), 5, FALSE ) )} | H26: {=IF( VLOOKUP( $A26, _xlfn._xlws.FILTER( INDIRECT("'"&H$62&"'!A2:E1000"), (INDIRECT("'"&H$62&"'!B2:B1000")=$B26) * (INDIRECT("'"&H$62&"'!C2:C1000")=$C26) ), 5, FALSE )=0, "", VLOOKUP( $A26, _xlfn._xlws.FILTER( INDIRECT("'"&H$62&"'!A2:E1000"), (INDIRECT("'"&H$62&"'!B2:B1000")=$B26) * (INDIRECT("'"&H$62&"'!C2:C1000")=$C26) ), 5, FALSE ) )} | I26: {=IF( VLOOKUP( $A26, _xlfn._xlws.FILTER( INDIRECT("'"&I$62&"'!A2:E1000"), (INDIRECT("'"&I$62&"'!B2:B1000")=$B26) * (INDIRECT("'"&I$62&"'!C2:C1000")=$C26) ), 5, FALSE )=0, "", VLOOKUP( $A26, _xlfn._xlws.FILTER( INDIRECT("'"&I$62&"'!A2:E1000"), (INDIRECT("'"&I$62&"'!B2:B1000")=$B26) * (INDIRECT("'"&I$62&"'!C2:C1000")=$C26) ), 5, FALSE ) )} | J26: {=IF( VLOOKUP( $A26, _xlfn._xlws.FILTER( INDIRECT("'"&J$62&"'!A2:E1000"), (INDIRECT("'"&J$62&"'!B2:B1000")=$B26) * (INDIRECT("'"&J$62&"'!C2:C1000")=$C26) ), 5, FALSE )=0, "", VLOOKUP( $A26, _xlfn._xlws.FILTER( INDIRECT("'"&J$62&"'!A2:E1000"), (INDIRECT("'"&J$62&"'!B2:B1000")=$B26) * (INDIRECT("'"&J$62&"'!C2:C1000")=$C26) ), 5, FALSE ) )} | K26: {=IF( VLOOKUP( $A26, _xlfn._xlws.FILTER( INDIRECT("'"&K$62&"'!A2:E1000"), (INDIRECT("'"&K$62&"'!B2:B1000")=$B26) * (INDIRECT("'"&K$62&"'!C2:C1000")=$C26) ), 5, FALSE )=0, "", VLOOKUP( $A26, _xlfn._xlws.FILTER( INDIRECT("'"&K$62&"'!A2:E1000"), (INDIRECT("'"&K$62&"'!B2:B1000")=$B26) * (INDIRECT("'"&K$62&"'!C2:C1000")=$C26) ), 5, FALSE ) )} | ... O26: {=IF( VLOOKUP( $A26, _xlfn._xlws.FILTER( INDIRECT("'"&O$62&"'!A2:E1000"), (INDIRECT("'"&O$62&"'!B2:B1000")=$B26) * (INDIRECT("'"&O$62&"'!C2:C1000")=$C26) ), 5, FALSE )=0, "", VLOOKUP( $A26, _xlfn._xlws.FILTER( INDIRECT("'"&O$62&"'!A2:E1000"), (INDIRECT("'"&O$62&"'!B2:B1000")=$B26) * (INDIRECT("'"&O$62&"'!C2:C1000")=$C26) ), 5, FALSE ) )}
A28: Juliane | B28: Municípios | C28: UVR | D28: 01.25 | E28: 02.25 | F28: 03.25 | G28: 04.25 | H28: 05.25 | I28: 06.25 | J28: 07.25 | K28: 08.25 | L28: 09.25 | M28: 10.25 | N28: 11.25 | O28: 12.25
A29: Guarapuava I | B29: General Carneiro | C29: 01 | D29: {=IF( VLOOKUP( $A29, _xlfn._xlws.FILTER( INDIRECT("'"&D$62&"'!A2:E1000"), (INDIRECT("'"&D$62&"'!B2:B1000")=$B29) * (INDIRECT("'"&D$62&"'!C2:C1000")=$C29) ), 5, FALSE )=0, "", VLOOKUP( $A29, _xlfn._xlws.FILTER( INDIRECT("'"&D$62&"'!A2:E1000"), (INDIRECT("'"&D$62&"'!B2:B1000")=$B29) * (INDIRECT("'"&D$62&"'!C2:C1000")=$C29) ), 5, FALSE ) )} | E29: {=IF( VLOOKUP( $A29, _xlfn._xlws.FILTER( INDIRECT("'"&E$62&"'!A2:E1000"), (INDIRECT("'"&E$62&"'!B2:B1000")=$B29) * (INDIRECT("'"&E$62&"'!C2:C1000")=$C29) ), 5, FALSE )=0, "", VLOOKUP( $A29, _xlfn._xlws.FILTER( INDIRECT("'"&E$62&"'!A2:E1000"), (INDIRECT("'"&E$62&"'!B2:B1000")=$B29) * (INDIRECT("'"&E$62&"'!C2:C1000")=$C29) ), 5, FALSE ) )} | F29: {=IF( VLOOKUP( $A29, _xlfn._xlws.FILTER( INDIRECT("'"&F$62&"'!A2:E1000"), (INDIRECT("'"&F$62&"'!B2:B1000")=$B29) * (INDIRECT("'"&F$62&"'!C2:C1000")=$C29) ), 5, FALSE )=0, "", VLOOKUP( $A29, _xlfn._xlws.FILTER( INDIRECT("'"&F$62&"'!A2:E1000"), (INDIRECT("'"&F$62&"'!B2:B1000")=$B29) * (INDIRECT("'"&F$62&"'!C2:C1000")=$C29) ), 5, FALSE ) )} | G29: {=IF( VLOOKUP( $A29, _xlfn._xlws.FILTER( INDIRECT("'"&G$62&"'!A2:E1000"), (INDIRECT("'"&G$62&"'!B2:B1000")=$B29) * (INDIRECT("'"&G$62&"'!C2:C1000")=$C29) ), 5, FALSE )=0, "", VLOOKUP( $A29, _xlfn._xlws.FILTER( INDIRECT("'"&G$62&"'!A2:E1000"), (INDIRECT("'"&G$62&"'!B2:B1000")=$B29) * (INDIRECT("'"&G$62&"'!C2:C1000")=$C29) ), 5, FALSE ) )} | H29: {=IF( VLOOKUP( $A29, _xlfn._xlws.FILTER( INDIRECT("'"&H$62&"'!A2:E1000"), (INDIRECT("'"&H$62&"'!B2:B1000")=$B29) * (INDIRECT("'"&H$62&"'!C2:C1000")=$C29) ), 5, FALSE )=0, "", VLOOKUP( $A29, _xlfn._xlws.FILTER( INDIRECT("'"&H$62&"'!A2:E1000"), (INDIRECT("'"&H$62&"'!B2:B1000")=$B29) * (INDIRECT("'"&H$62&"'!C2:C1000")=$C29) ), 5, FALSE ) )} | I29: {=IF( VLOOKUP( $A29, _xlfn._xlws.FILTER( INDIRECT("'"&I$62&"'!A2:E1000"), (INDIRECT("'"&I$62&"'!B2:B1000")=$B29) * (INDIRECT("'"&I$62&"'!C2:C1000")=$C29) ), 5, FALSE )=0, "", VLOOKUP( $A29, _xlfn._xlws.FILTER( INDIRECT("'"&I$62&"'!A2:E1000"), (INDIRECT("'"&I$62&"'!B2:B1000")=$B29) * (INDIRECT("'"&I$62&"'!C2:C1000")=$C29) ), 5, FALSE ) )} | J29: {=IF( VLOOKUP( $A29, _xlfn._xlws.FILTER( INDIRECT("'"&J$62&"'!A2:E1000"), (INDIRECT("'"&J$62&"'!B2:B1000")=$B29) * (INDIRECT("'"&J$62&"'!C2:C1000")=$C29) ), 5, FALSE )=0, "", VLOOKUP( $A29, _xlfn._xlws.FILTER( INDIRECT("'"&J$62&"'!A2:E1000"), (INDIRECT("'"&J$62&"'!B2:B1000")=$B29) * (INDIRECT("'"&J$62&"'!C2:C1000")=$C29) ), 5, FALSE ) )} | K29: {=IF( VLOOKUP( $A29, _xlfn._xlws.FILTER( INDIRECT("'"&K$62&"'!A2:E1000"), (INDIRECT("'"&K$62&"'!B2:B1000")=$B29) * (INDIRECT("'"&K$62&"'!C2:C1000")=$C29) ), 5, FALSE )=0, "", VLOOKUP( $A29, _xlfn._xlws.FILTER( INDIRECT("'"&K$62&"'!A2:E1000"), (INDIRECT("'"&K$62&"'!B2:B1000")=$B29) * (INDIRECT("'"&K$62&"'!C2:C1000")=$C29) ), 5, FALSE ) )} | ... O29: {=IF( VLOOKUP( $A29, _xlfn._xlws.FILTER( INDIRECT("'"&O$62&"'!A2:E1000"), (INDIRECT("'"&O$62&"'!B2:B1000")=$B29) * (INDIRECT("'"&O$62&"'!C2:C1000")=$C29) ), 5, FALSE )=0, "", VLOOKUP( $A29, _xlfn._xlws.FILTER( INDIRECT("'"&O$62&"'!A2:E1000"), (INDIRECT("'"&O$62&"'!B2:B1000")=$B29) * (INDIRECT("'"&O$62&"'!C2:C1000")=$C29) ), 5, FALSE ) )}
A30: Guarapuava I | B30: Reserva Do Iguaçu | C30: 01 | D30: {=IF( VLOOKUP( $A30, _xlfn._xlws.FILTER( INDIRECT("'"&D$62&"'!A2:E1000"), (INDIRECT("'"&D$62&"'!B2:B1000")=$B30) * (INDIRECT("'"&D$62&"'!C2:C1000")=$C30) ), 5, FALSE )=0, "", VLOOKUP( $A30, _xlfn._xlws.FILTER( INDIRECT("'"&D$62&"'!A2:E1000"), (INDIRECT("'"&D$62&"'!B2:B1000")=$B30) * (INDIRECT("'"&D$62&"'!C2:C1000")=$C30) ), 5, FALSE ) )} | E30: {=IF( VLOOKUP( $A30, _xlfn._xlws.FILTER( INDIRECT("'"&E$62&"'!A2:E1000"), (INDIRECT("'"&E$62&"'!B2:B1000")=$B30) * (INDIRECT("'"&E$62&"'!C2:C1000")=$C30) ), 5, FALSE )=0, "", VLOOKUP( $A30, _xlfn._xlws.FILTER( INDIRECT("'"&E$62&"'!A2:E1000"), (INDIRECT("'"&E$62&"'!B2:B1000")=$B30) * (INDIRECT("'"&E$62&"'!C2:C1000")=$C30) ), 5, FALSE ) )} | F30: {=IF( VLOOKUP( $A30, _xlfn._xlws.FILTER( INDIRECT("'"&F$62&"'!A2:E1000"), (INDIRECT("'"&F$62&"'!B2:B1000")=$B30) * (INDIRECT("'"&F$62&"'!C2:C1000")=$C30) ), 5, FALSE )=0, "", VLOOKUP( $A30, _xlfn._xlws.FILTER( INDIRECT("'"&F$62&"'!A2:E1000"), (INDIRECT("'"&F$62&"'!B2:B1000")=$B30) * (INDIRECT("'"&F$62&"'!C2:C1000")=$C30) ), 5, FALSE ) )} | G30: {=IF( VLOOKUP( $A30, _xlfn._xlws.FILTER( INDIRECT("'"&G$62&"'!A2:E1000"), (INDIRECT("'"&G$62&"'!B2:B1000")=$B30) * (INDIRECT("'"&G$62&"'!C2:C1000")=$C30) ), 5, FALSE )=0, "", VLOOKUP( $A30, _xlfn._xlws.FILTER( INDIRECT("'"&G$62&"'!A2:E1000"), (INDIRECT("'"&G$62&"'!B2:B1000")=$B30) * (INDIRECT("'"&G$62&"'!C2:C1000")=$C30) ), 5, FALSE ) )} | H30: {=IF( VLOOKUP( $A30, _xlfn._xlws.FILTER( INDIRECT("'"&H$62&"'!A2:E1000"), (INDIRECT("'"&H$62&"'!B2:B1000")=$B30) * (INDIRECT("'"&H$62&"'!C2:C1000")=$C30) ), 5, FALSE )=0, "", VLOOKUP( $A30, _xlfn._xlws.FILTER( INDIRECT("'"&H$62&"'!A2:E1000"), (INDIRECT("'"&H$62&"'!B2:B1000")=$B30) * (INDIRECT("'"&H$62&"'!C2:C1000")=$C30) ), 5, FALSE ) )} | I30: {=IF( VLOOKUP( $A30, _xlfn._xlws.FILTER( INDIRECT("'"&I$62&"'!A2:E1000"), (INDIRECT("'"&I$62&"'!B2:B1000")=$B30) * (INDIRECT("'"&I$62&"'!C2:C1000")=$C30) ), 5, FALSE )=0, "", VLOOKUP( $A30, _xlfn._xlws.FILTER( INDIRECT("'"&I$62&"'!A2:E1000"), (INDIRECT("'"&I$62&"'!B2:B1000")=$B30) * (INDIRECT("'"&I$62&"'!C2:C1000")=$C30) ), 5, FALSE ) )} | J30: {=IF( VLOOKUP( $A30, _xlfn._xlws.FILTER( INDIRECT("'"&J$62&"'!A2:E1000"), (INDIRECT("'"&J$62&"'!B2:B1000")=$B30) * (INDIRECT("'"&J$62&"'!C2:C1000")=$C30) ), 5, FALSE )=0, "", VLOOKUP( $A30, _xlfn._xlws.FILTER( INDIRECT("'"&J$62&"'!A2:E1000"), (INDIRECT("'"&J$62&"'!B2:B1000")=$B30) * (INDIRECT("'"&J$62&"'!C2:C1000")=$C30) ), 5, FALSE ) )} | K30: {=IF( VLOOKUP( $A30, _xlfn._xlws.FILTER( INDIRECT("'"&K$62&"'!A2:E1000"), (INDIRECT("'"&K$62&"'!B2:B1000")=$B30) * (INDIRECT("'"&K$62&"'!C2:C1000")=$C30) ), 5, FALSE )=0, "", VLOOKUP( $A30, _xlfn._xlws.FILTER( INDIRECT("'"&K$62&"'!A2:E1000"), (INDIRECT("'"&K$62&"'!B2:B1000")=$B30) * (INDIRECT("'"&K$62&"'!C2:C1000")=$C30) ), 5, FALSE ) )} | ... O30: {=IF( VLOOKUP( $A30, _xlfn._xlws.FILTER( INDIRECT("'"&O$62&"'!A2:E1000"), (INDIRECT("'"&O$62&"'!B2:B1000")=$B30) * (INDIRECT("'"&O$62&"'!C2:C1000")=$C30) ), 5, FALSE )=0, "", VLOOKUP( $A30, _xlfn._xlws.FILTER( INDIRECT("'"&O$62&"'!A2:E1000"), (INDIRECT("'"&O$62&"'!B2:B1000")=$B30) * (INDIRECT("'"&O$62&"'!C2:C1000")=$C30) ), 5, FALSE ) )}
A32: Aramis | B32: Municípios | C32: UVR | D32: 01.25 | E32: 02.25 | F32: 03.25 | G32: 04.25 | H32: 05.25 | I32: 06.25 | J32: 07.25 | K32: 08.25 | L32: 09.25 | M32: 10.25 | N32: 11.25 | O32: 12.25
A33: Guarapuava II | B33: Campina Da Lagoa | C33: 01 | D33: {=IF( VLOOKUP( $A33, _xlfn._xlws.FILTER( INDIRECT("'"&D$62&"'!A2:E1000"), (INDIRECT("'"&D$62&"'!B2:B1000")=$B33) * (INDIRECT("'"&D$62&"'!C2:C1000")=$C33) ), 5, FALSE )=0, "", VLOOKUP( $A33, _xlfn._xlws.FILTER( INDIRECT("'"&D$62&"'!A2:E1000"), (INDIRECT("'"&D$62&"'!B2:B1000")=$B33) * (INDIRECT("'"&D$62&"'!C2:C1000")=$C33) ), 5, FALSE ) )} | E33: {=IF( VLOOKUP( $A33, _xlfn._xlws.FILTER( INDIRECT("'"&E$62&"'!A2:E1000"), (INDIRECT("'"&E$62&"'!B2:B1000")=$B33) * (INDIRECT("'"&E$62&"'!C2:C1000")=$C33) ), 5, FALSE )=0, "", VLOOKUP( $A33, _xlfn._xlws.FILTER( INDIRECT("'"&E$62&"'!A2:E1000"), (INDIRECT("'"&E$62&"'!B2:B1000")=$B33) * (INDIRECT("'"&E$62&"'!C2:C1000")=$C33) ), 5, FALSE ) )} | F33: {=IF( VLOOKUP( $A33, _xlfn._xlws.FILTER( INDIRECT("'"&F$62&"'!A2:E1000"), (INDIRECT("'"&F$62&"'!B2:B1000")=$B33) * (INDIRECT("'"&F$62&"'!C2:C1000")=$C33) ), 5, FALSE )=0, "", VLOOKUP( $A33, _xlfn._xlws.FILTER( INDIRECT("'"&F$62&"'!A2:E1000"), (INDIRECT("'"&F$62&"'!B2:B1000")=$B33) * (INDIRECT("'"&F$62&"'!C2:C1000")=$C33) ), 5, FALSE ) )} | G33: {=IF( VLOOKUP( $A33, _xlfn._xlws.FILTER( INDIRECT("'"&G$62&"'!A2:E1000"), (INDIRECT("'"&G$62&"'!B2:B1000")=$B33) * (INDIRECT("'"&G$62&"'!C2:C1000")=$C33) ), 5, FALSE )=0, "", VLOOKUP( $A33, _xlfn._xlws.FILTER( INDIRECT("'"&G$62&"'!A2:E1000"), (INDIRECT("'"&G$62&"'!B2:B1000")=$B33) * (INDIRECT("'"&G$62&"'!C2:C1000")=$C33) ), 5, FALSE ) )} | H33: {=IF( VLOOKUP( $A33, _xlfn._xlws.FILTER( INDIRECT("'"&H$62&"'!A2:E1000"), (INDIRECT("'"&H$62&"'!B2:B1000")=$B33) * (INDIRECT("'"&H$62&"'!C2:C1000")=$C33) ), 5, FALSE )=0, "", VLOOKUP( $A33, _xlfn._xlws.FILTER( INDIRECT("'"&H$62&"'!A2:E1000"), (INDIRECT("'"&H$62&"'!B2:B1000")=$B33) * (INDIRECT("'"&H$62&"'!C2:C1000")=$C33) ), 5, FALSE ) )} | I33: {=IF( VLOOKUP( $A33, _xlfn._xlws.FILTER( INDIRECT("'"&I$62&"'!A2:E1000"), (INDIRECT("'"&I$62&"'!B2:B1000")=$B33) * (INDIRECT("'"&I$62&"'!C2:C1000")=$C33) ), 5, FALSE )=0, "", VLOOKUP( $A33, _xlfn._xlws.FILTER( INDIRECT("'"&I$62&"'!A2:E1000"), (INDIRECT("'"&I$62&"'!B2:B1000")=$B33) * (INDIRECT("'"&I$62&"'!C2:C1000")=$C33) ), 5, FALSE ) )} | J33: {=IF( VLOOKUP( $A33, _xlfn._xlws.FILTER( INDIRECT("'"&J$62&"'!A2:E1000"), (INDIRECT("'"&J$62&"'!B2:B1000")=$B33) * (INDIRECT("'"&J$62&"'!C2:C1000")=$C33) ), 5, FALSE )=0, "", VLOOKUP( $A33, _xlfn._xlws.FILTER( INDIRECT("'"&J$62&"'!A2:E1000"), (INDIRECT("'"&J$62&"'!B2:B1000")=$B33) * (INDIRECT("'"&J$62&"'!C2:C1000")=$C33) ), 5, FALSE ) )} | K33: {=IF( VLOOKUP( $A33, _xlfn._xlws.FILTER( INDIRECT("'"&K$62&"'!A2:E1000"), (INDIRECT("'"&K$62&"'!B2:B1000")=$B33) * (INDIRECT("'"&K$62&"'!C2:C1000")=$C33) ), 5, FALSE )=0, "", VLOOKUP( $A33, _xlfn._xlws.FILTER( INDIRECT("'"&K$62&"'!A2:E1000"), (INDIRECT("'"&K$62&"'!B2:B1000")=$B33) * (INDIRECT("'"&K$62&"'!C2:C1000")=$C33) ), 5, FALSE ) )} | ... O33: {=IF( VLOOKUP( $A33, _xlfn._xlws.FILTER( INDIRECT("'"&O$62&"'!A2:E1000"), (INDIRECT("'"&O$62&"'!B2:B1000")=$B33) * (INDIRECT("'"&O$62&"'!C2:C1000")=$C33) ), 5, FALSE )=0, "", VLOOKUP( $A33, _xlfn._xlws.FILTER( INDIRECT("'"&O$62&"'!A2:E1000"), (INDIRECT("'"&O$62&"'!B2:B1000")=$B33) * (INDIRECT("'"&O$62&"'!C2:C1000")=$C33) ), 5, FALSE ) )}
A34: Guarapuava II | B34: Laranjeiras Do Sul | C34: 01 | D34: {=IF( VLOOKUP( $A34, _xlfn._xlws.FILTER( INDIRECT("'"&D$62&"'!A2:E1000"), (INDIRECT("'"&D$62&"'!B2:B1000")=$B34) * (INDIRECT("'"&D$62&"'!C2:C1000")=$C34) ), 5, FALSE )=0, "", VLOOKUP( $A34, _xlfn._xlws.FILTER( INDIRECT("'"&D$62&"'!A2:E1000"), (INDIRECT("'"&D$62&"'!B2:B1000")=$B34) * (INDIRECT("'"&D$62&"'!C2:C1000")=$C34) ), 5, FALSE ) )} | E34: {=IF( VLOOKUP( $A34, _xlfn._xlws.FILTER( INDIRECT("'"&E$62&"'!A2:E1000"), (INDIRECT("'"&E$62&"'!B2:B1000")=$B34) * (INDIRECT("'"&E$62&"'!C2:C1000")=$C34) ), 5, FALSE )=0, "", VLOOKUP( $A34, _xlfn._xlws.FILTER( INDIRECT("'"&E$62&"'!A2:E1000"), (INDIRECT("'"&E$62&"'!B2:B1000")=$B34) * (INDIRECT("'"&E$62&"'!C2:C1000")=$C34) ), 5, FALSE ) )} | F34: {=IF( VLOOKUP( $A34, _xlfn._xlws.FILTER( INDIRECT("'"&F$62&"'!A2:E1000"), (INDIRECT("'"&F$62&"'!B2:B1000")=$B34) * (INDIRECT("'"&F$62&"'!C2:C1000")=$C34) ), 5, FALSE )=0, "", VLOOKUP( $A34, _xlfn._xlws.FILTER( INDIRECT("'"&F$62&"'!A2:E1000"), (INDIRECT("'"&F$62&"'!B2:B1000")=$B34) * (INDIRECT("'"&F$62&"'!C2:C1000")=$C34) ), 5, FALSE ) )} | G34: {=IF( VLOOKUP( $A34, _xlfn._xlws.FILTER( INDIRECT("'"&G$62&"'!A2:E1000"), (INDIRECT("'"&G$62&"'!B2:B1000")=$B34) * (INDIRECT("'"&G$62&"'!C2:C1000")=$C34) ), 5, FALSE )=0, "", VLOOKUP( $A34, _xlfn._xlws.FILTER( INDIRECT("'"&G$62&"'!A2:E1000"), (INDIRECT("'"&G$62&"'!B2:B1000")=$B34) * (INDIRECT("'"&G$62&"'!C2:C1000")=$C34) ), 5, FALSE ) )} | H34: {=IF( VLOOKUP( $A34, _xlfn._xlws.FILTER( INDIRECT("'"&H$62&"'!A2:E1000"), (INDIRECT("'"&H$62&"'!B2:B1000")=$B34) * (INDIRECT("'"&H$62&"'!C2:C1000")=$C34) ), 5, FALSE )=0, "", VLOOKUP( $A34, _xlfn._xlws.FILTER( INDIRECT("'"&H$62&"'!A2:E1000"), (INDIRECT("'"&H$62&"'!B2:B1000")=$B34) * (INDIRECT("'"&H$62&"'!C2:C1000")=$C34) ), 5, FALSE ) )} | I34: {=IF( VLOOKUP( $A34, _xlfn._xlws.FILTER( INDIRECT("'"&I$62&"'!A2:E1000"), (INDIRECT("'"&I$62&"'!B2:B1000")=$B34) * (INDIRECT("'"&I$62&"'!C2:C1000")=$C34) ), 5, FALSE )=0, "", VLOOKUP( $A34, _xlfn._xlws.FILTER( INDIRECT("'"&I$62&"'!A2:E1000"), (INDIRECT("'"&I$62&"'!B2:B1000")=$B34) * (INDIRECT("'"&I$62&"'!C2:C1000")=$C34) ), 5, FALSE ) )} | J34: {=IF( VLOOKUP( $A34, _xlfn._xlws.FILTER( INDIRECT("'"&J$62&"'!A2:E1000"), (INDIRECT("'"&J$62&"'!B2:B1000")=$B34) * (INDIRECT("'"&J$62&"'!C2:C1000")=$C34) ), 5, FALSE )=0, "", VLOOKUP( $A34, _xlfn._xlws.FILTER( INDIRECT("'"&J$62&"'!A2:E1000"), (INDIRECT("'"&J$62&"'!B2:B1000")=$B34) * (INDIRECT("'"&J$62&"'!C2:C1000")=$C34) ), 5, FALSE ) )} | K34: {=IF( VLOOKUP( $A34, _xlfn._xlws.FILTER( INDIRECT("'"&K$62&"'!A2:E1000"), (INDIRECT("'"&K$62&"'!B2:B1000")=$B34) * (INDIRECT("'"&K$62&"'!C2:C1000")=$C34) ), 5, FALSE )=0, "", VLOOKUP( $A34, _xlfn._xlws.FILTER( INDIRECT("'"&K$62&"'!A2:E1000"), (INDIRECT("'"&K$62&"'!B2:B1000")=$B34) * (INDIRECT("'"&K$62&"'!C2:C1000")=$C34) ), 5, FALSE ) )} | ... O34: {=IF( VLOOKUP( $A34, _xlfn._xlws.FILTER( INDIRECT("'"&O$62&"'!A2:E1000"), (INDIRECT("'"&O$62&"'!B2:B1000")=$B34) * (INDIRECT("'"&O$62&"'!C2:C1000")=$C34) ), 5, FALSE )=0, "", VLOOKUP( $A34, _xlfn._xlws.FILTER( INDIRECT("'"&O$62&"'!A2:E1000"), (INDIRECT("'"&O$62&"'!B2:B1000")=$B34) * (INDIRECT("'"&O$62&"'!C2:C1000")=$C34) ), 5, FALSE ) )}
A35: Guarapuava II | B35: Mato Rico | C35: 01 | D35: {=IF( VLOOKUP( $A35, _xlfn._xlws.FILTER( INDIRECT("'"&D$62&"'!A2:E1000"), (INDIRECT("'"&D$62&"'!B2:B1000")=$B35) * (INDIRECT("'"&D$62&"'!C2:C1000")=$C35) ), 5, FALSE )=0, "", VLOOKUP( $A35, _xlfn._xlws.FILTER( INDIRECT("'"&D$62&"'!A2:E1000"), (INDIRECT("'"&D$62&"'!B2:B1000")=$B35) * (INDIRECT("'"&D$62&"'!C2:C1000")=$C35) ), 5, FALSE ) )} | E35: {=IF( VLOOKUP( $A35, _xlfn._xlws.FILTER( INDIRECT("'"&E$62&"'!A2:E1000"), (INDIRECT("'"&E$62&"'!B2:B1000")=$B35) * (INDIRECT("'"&E$62&"'!C2:C1000")=$C35) ), 5, FALSE )=0, "", VLOOKUP( $A35, _xlfn._xlws.FILTER( INDIRECT("'"&E$62&"'!A2:E1000"), (INDIRECT("'"&E$62&"'!B2:B1000")=$B35) * (INDIRECT("'"&E$62&"'!C2:C1000")=$C35) ), 5, FALSE ) )} | F35: {=IF( VLOOKUP( $A35, _xlfn._xlws.FILTER( INDIRECT("'"&F$62&"'!A2:E1000"), (INDIRECT("'"&F$62&"'!B2:B1000")=$B35) * (INDIRECT("'"&F$62&"'!C2:C1000")=$C35) ), 5, FALSE )=0, "", VLOOKUP( $A35, _xlfn._xlws.FILTER( INDIRECT("'"&F$62&"'!A2:E1000"), (INDIRECT("'"&F$62&"'!B2:B1000")=$B35) * (INDIRECT("'"&F$62&"'!C2:C1000")=$C35) ), 5, FALSE ) )} | G35: {=IF( VLOOKUP( $A35, _xlfn._xlws.FILTER( INDIRECT("'"&G$62&"'!A2:E1000"), (INDIRECT("'"&G$62&"'!B2:B1000")=$B35) * (INDIRECT("'"&G$62&"'!C2:C1000")=$C35) ), 5, FALSE )=0, "", VLOOKUP( $A35, _xlfn._xlws.FILTER( INDIRECT("'"&G$62&"'!A2:E1000"), (INDIRECT("'"&G$62&"'!B2:B1000")=$B35) * (INDIRECT("'"&G$62&"'!C2:C1000")=$C35) ), 5, FALSE ) )} | H35: {=IF( VLOOKUP( $A35, _xlfn._xlws.FILTER( INDIRECT("'"&H$62&"'!A2:E1000"), (INDIRECT("'"&H$62&"'!B2:B1000")=$B35) * (INDIRECT("'"&H$62&"'!C2:C1000")=$C35) ), 5, FALSE )=0, "", VLOOKUP( $A35, _xlfn._xlws.FILTER( INDIRECT("'"&H$62&"'!A2:E1000"), (INDIRECT("'"&H$62&"'!B2:B1000")=$B35) * (INDIRECT("'"&H$62&"'!C2:C1000")=$C35) ), 5, FALSE ) )} | I35: {=IF( VLOOKUP( $A35, _xlfn._xlws.FILTER( INDIRECT("'"&I$62&"'!A2:E1000"), (INDIRECT("'"&I$62&"'!B2:B1000")=$B35) * (INDIRECT("'"&I$62&"'!C2:C1000")=$C35) ), 5, FALSE )=0, "", VLOOKUP( $A35, _xlfn._xlws.FILTER( INDIRECT("'"&I$62&"'!A2:E1000"), (INDIRECT("'"&I$62&"'!B2:B1000")=$B35) * (INDIRECT("'"&I$62&"'!C2:C1000")=$C35) ), 5, FALSE ) )} | J35: {=IF( VLOOKUP( $A35, _xlfn._xlws.FILTER( INDIRECT("'"&J$62&"'!A2:E1000"), (INDIRECT("'"&J$62&"'!B2:B1000")=$B35) * (INDIRECT("'"&J$62&"'!C2:C1000")=$C35) ), 5, FALSE )=0, "", VLOOKUP( $A35, _xlfn._xlws.FILTER( INDIRECT("'"&J$62&"'!A2:E1000"), (INDIRECT("'"&J$62&"'!B2:B1000")=$B35) * (INDIRECT("'"&J$62&"'!C2:C1000")=$C35) ), 5, FALSE ) )} | K35: {=IF( VLOOKUP( $A35, _xlfn._xlws.FILTER( INDIRECT("'"&K$62&"'!A2:E1000"), (INDIRECT("'"&K$62&"'!B2:B1000")=$B35) * (INDIRECT("'"&K$62&"'!C2:C1000")=$C35) ), 5, FALSE )=0, "", VLOOKUP( $A35, _xlfn._xlws.FILTER( INDIRECT("'"&K$62&"'!A2:E1000"), (INDIRECT("'"&K$62&"'!B2:B1000")=$B35) * (INDIRECT("'"&K$62&"'!C2:C1000")=$C35) ), 5, FALSE ) )} | ... O35: {=IF( VLOOKUP( $A35, _xlfn._xlws.FILTER( INDIRECT("'"&O$62&"'!A2:E1000"), (INDIRECT("'"&O$62&"'!B2:B1000")=$B35) * (INDIRECT("'"&O$62&"'!C2:C1000")=$C35) ), 5, FALSE )=0, "", VLOOKUP( $A35, _xlfn._xlws.FILTER( INDIRECT("'"&O$62&"'!A2:E1000"), (INDIRECT("'"&O$62&"'!B2:B1000")=$B35) * (INDIRECT("'"&O$62&"'!C2:C1000")=$C35) ), 5, FALSE ) )}
A36: Guarapuava II | B36: Palmital | C36: 01 | D36: {=IF( VLOOKUP( $A36, _xlfn._xlws.FILTER( INDIRECT("'"&D$62&"'!A2:E1000"), (INDIRECT("'"&D$62&"'!B2:B1000")=$B36) * (INDIRECT("'"&D$62&"'!C2:C1000")=$C36) ), 5, FALSE )=0, "", VLOOKUP( $A36, _xlfn._xlws.FILTER( INDIRECT("'"&D$62&"'!A2:E1000"), (INDIRECT("'"&D$62&"'!B2:B1000")=$B36) * (INDIRECT("'"&D$62&"'!C2:C1000")=$C36) ), 5, FALSE ) )} | E36: {=IF( VLOOKUP( $A36, _xlfn._xlws.FILTER( INDIRECT("'"&E$62&"'!A2:E1000"), (INDIRECT("'"&E$62&"'!B2:B1000")=$B36) * (INDIRECT("'"&E$62&"'!C2:C1000")=$C36) ), 5, FALSE )=0, "", VLOOKUP( $A36, _xlfn._xlws.FILTER( INDIRECT("'"&E$62&"'!A2:E1000"), (INDIRECT("'"&E$62&"'!B2:B1000")=$B36) * (INDIRECT("'"&E$62&"'!C2:C1000")=$C36) ), 5, FALSE ) )} | F36: {=IF( VLOOKUP( $A36, _xlfn._xlws.FILTER( INDIRECT("'"&F$62&"'!A2:E1000"), (INDIRECT("'"&F$62&"'!B2:B1000")=$B36) * (INDIRECT("'"&F$62&"'!C2:C1000")=$C36) ), 5, FALSE )=0, "", VLOOKUP( $A36, _xlfn._xlws.FILTER( INDIRECT("'"&F$62&"'!A2:E1000"), (INDIRECT("'"&F$62&"'!B2:B1000")=$B36) * (INDIRECT("'"&F$62&"'!C2:C1000")=$C36) ), 5, FALSE ) )} | G36: {=IF( VLOOKUP( $A36, _xlfn._xlws.FILTER( INDIRECT("'"&G$62&"'!A2:E1000"), (INDIRECT("'"&G$62&"'!B2:B1000")=$B36) * (INDIRECT("'"&G$62&"'!C2:C1000")=$C36) ), 5, FALSE )=0, "", VLOOKUP( $A36, _xlfn._xlws.FILTER( INDIRECT("'"&G$62&"'!A2:E1000"), (INDIRECT("'"&G$62&"'!B2:B1000")=$B36) * (INDIRECT("'"&G$62&"'!C2:C1000")=$C36) ), 5, FALSE ) )} | H36: {=IF( VLOOKUP( $A36, _xlfn._xlws.FILTER( INDIRECT("'"&H$62&"'!A2:E1000"), (INDIRECT("'"&H$62&"'!B2:B1000")=$B36) * (INDIRECT("'"&H$62&"'!C2:C1000")=$C36) ), 5, FALSE )=0, "", VLOOKUP( $A36, _xlfn._xlws.FILTER( INDIRECT("'"&H$62&"'!A2:E1000"), (INDIRECT("'"&H$62&"'!B2:B1000")=$B36) * (INDIRECT("'"&H$62&"'!C2:C1000")=$C36) ), 5, FALSE ) )} | I36: {=IF( VLOOKUP( $A36, _xlfn._xlws.FILTER( INDIRECT("'"&I$62&"'!A2:E1000"), (INDIRECT("'"&I$62&"'!B2:B1000")=$B36) * (INDIRECT("'"&I$62&"'!C2:C1000")=$C36) ), 5, FALSE )=0, "", VLOOKUP( $A36, _xlfn._xlws.FILTER( INDIRECT("'"&I$62&"'!A2:E1000"), (INDIRECT("'"&I$62&"'!B2:B1000")=$B36) * (INDIRECT("'"&I$62&"'!C2:C1000")=$C36) ), 5, FALSE ) )} | J36: {=IF( VLOOKUP( $A36, _xlfn._xlws.FILTER( INDIRECT("'"&J$62&"'!A2:E1000"), (INDIRECT("'"&J$62&"'!B2:B1000")=$B36) * (INDIRECT("'"&J$62&"'!C2:C1000")=$C36) ), 5, FALSE )=0, "", VLOOKUP( $A36, _xlfn._xlws.FILTER( INDIRECT("'"&J$62&"'!A2:E1000"), (INDIRECT("'"&J$62&"'!B2:B1000")=$B36) * (INDIRECT("'"&J$62&"'!C2:C1000")=$C36) ), 5, FALSE ) )} | K36: {=IF( VLOOKUP( $A36, _xlfn._xlws.FILTER( INDIRECT("'"&K$62&"'!A2:E1000"), (INDIRECT("'"&K$62&"'!B2:B1000")=$B36) * (INDIRECT("'"&K$62&"'!C2:C1000")=$C36) ), 5, FALSE )=0, "", VLOOKUP( $A36, _xlfn._xlws.FILTER( INDIRECT("'"&K$62&"'!A2:E1000"), (INDIRECT("'"&K$62&"'!B2:B1000")=$B36) * (INDIRECT("'"&K$62&"'!C2:C1000")=$C36) ), 5, FALSE ) )} | ... O36: {=IF( VLOOKUP( $A36, _xlfn._xlws.FILTER( INDIRECT("'"&O$62&"'!A2:E1000"), (INDIRECT("'"&O$62&"'!B2:B1000")=$B36) * (INDIRECT("'"&O$62&"'!C2:C1000")=$C36) ), 5, FALSE )=0, "", VLOOKUP( $A36, _xlfn._xlws.FILTER( INDIRECT("'"&O$62&"'!A2:E1000"), (INDIRECT("'"&O$62&"'!B2:B1000")=$B36) * (INDIRECT("'"&O$62&"'!C2:C1000")=$C36) ), 5, FALSE ) )}
A37: Guarapuava II | B37: Quedas Do Iguaçu | C37: 01 | D37: {=IF( VLOOKUP( $A37, _xlfn._xlws.FILTER( INDIRECT("'"&D$62&"'!A2:E1000"), (INDIRECT("'"&D$62&"'!B2:B1000")=$B37) * (INDIRECT("'"&D$62&"'!C2:C1000")=$C37) ), 5, FALSE )=0, "", VLOOKUP( $A37, _xlfn._xlws.FILTER( INDIRECT("'"&D$62&"'!A2:E1000"), (INDIRECT("'"&D$62&"'!B2:B1000")=$B37) * (INDIRECT("'"&D$62&"'!C2:C1000")=$C37) ), 5, FALSE ) )} | E37: {=IF( VLOOKUP( $A37, _xlfn._xlws.FILTER( INDIRECT("'"&E$62&"'!A2:E1000"), (INDIRECT("'"&E$62&"'!B2:B1000")=$B37) * (INDIRECT("'"&E$62&"'!C2:C1000")=$C37) ), 5, FALSE )=0, "", VLOOKUP( $A37, _xlfn._xlws.FILTER( INDIRECT("'"&E$62&"'!A2:E1000"), (INDIRECT("'"&E$62&"'!B2:B1000")=$B37) * (INDIRECT("'"&E$62&"'!C2:C1000")=$C37) ), 5, FALSE ) )} | F37: {=IF( VLOOKUP( $A37, _xlfn._xlws.FILTER( INDIRECT("'"&F$62&"'!A2:E1000"), (INDIRECT("'"&F$62&"'!B2:B1000")=$B37) * (INDIRECT("'"&F$62&"'!C2:C1000")=$C37) ), 5, FALSE )=0, "", VLOOKUP( $A37, _xlfn._xlws.FILTER( INDIRECT("'"&F$62&"'!A2:E1000"), (INDIRECT("'"&F$62&"'!B2:B1000")=$B37) * (INDIRECT("'"&F$62&"'!C2:C1000")=$C37) ), 5, FALSE ) )} | G37: {=IF( VLOOKUP( $A37, _xlfn._xlws.FILTER( INDIRECT("'"&G$62&"'!A2:E1000"), (INDIRECT("'"&G$62&"'!B2:B1000")=$B37) * (INDIRECT("'"&G$62&"'!C2:C1000")=$C37) ), 5, FALSE )=0, "", VLOOKUP( $A37, _xlfn._xlws.FILTER( INDIRECT("'"&G$62&"'!A2:E1000"), (INDIRECT("'"&G$62&"'!B2:B1000")=$B37) * (INDIRECT("'"&G$62&"'!C2:C1000")=$C37) ), 5, FALSE ) )} | H37: {=IF( VLOOKUP( $A37, _xlfn._xlws.FILTER( INDIRECT("'"&H$62&"'!A2:E1000"), (INDIRECT("'"&H$62&"'!B2:B1000")=$B37) * (INDIRECT("'"&H$62&"'!C2:C1000")=$C37) ), 5, FALSE )=0, "", VLOOKUP( $A37, _xlfn._xlws.FILTER( INDIRECT("'"&H$62&"'!A2:E1000"), (INDIRECT("'"&H$62&"'!B2:B1000")=$B37) * (INDIRECT("'"&H$62&"'!C2:C1000")=$C37) ), 5, FALSE ) )} | I37: {=IF( VLOOKUP( $A37, _xlfn._xlws.FILTER( INDIRECT("'"&I$62&"'!A2:E1000"), (INDIRECT("'"&I$62&"'!B2:B1000")=$B37) * (INDIRECT("'"&I$62&"'!C2:C1000")=$C37) ), 5, FALSE )=0, "", VLOOKUP( $A37, _xlfn._xlws.FILTER( INDIRECT("'"&I$62&"'!A2:E1000"), (INDIRECT("'"&I$62&"'!B2:B1000")=$B37) * (INDIRECT("'"&I$62&"'!C2:C1000")=$C37) ), 5, FALSE ) )} | J37: {=IF( VLOOKUP( $A37, _xlfn._xlws.FILTER( INDIRECT("'"&J$62&"'!A2:E1000"), (INDIRECT("'"&J$62&"'!B2:B1000")=$B37) * (INDIRECT("'"&J$62&"'!C2:C1000")=$C37) ), 5, FALSE )=0, "", VLOOKUP( $A37, _xlfn._xlws.FILTER( INDIRECT("'"&J$62&"'!A2:E1000"), (INDIRECT("'"&J$62&"'!B2:B1000")=$B37) * (INDIRECT("'"&J$62&"'!C2:C1000")=$C37) ), 5, FALSE ) )} | K37: {=IF( VLOOKUP( $A37, _xlfn._xlws.FILTER( INDIRECT("'"&K$62&"'!A2:E1000"), (INDIRECT("'"&K$62&"'!B2:B1000")=$B37) * (INDIRECT("'"&K$62&"'!C2:C1000")=$C37) ), 5, FALSE )=0, "", VLOOKUP( $A37, _xlfn._xlws.FILTER( INDIRECT("'"&K$62&"'!A2:E1000"), (INDIRECT("'"&K$62&"'!B2:B1000")=$B37) * (INDIRECT("'"&K$62&"'!C2:C1000")=$C37) ), 5, FALSE ) )} | ... O37: {=IF( VLOOKUP( $A37, _xlfn._xlws.FILTER( INDIRECT("'"&O$62&"'!A2:E1000"), (INDIRECT("'"&O$62&"'!B2:B1000")=$B37) * (INDIRECT("'"&O$62&"'!C2:C1000")=$C37) ), 5, FALSE )=0, "", VLOOKUP( $A37, _xlfn._xlws.FILTER( INDIRECT("'"&O$62&"'!A2:E1000"), (INDIRECT("'"&O$62&"'!B2:B1000")=$B37) * (INDIRECT("'"&O$62&"'!C2:C1000")=$C37) ), 5, FALSE ) )}
A38: Guarapuava II | B38: Santa Maria Do Oeste | C38: 01 | D38: {=IF( VLOOKUP( $A38, _xlfn._xlws.FILTER( INDIRECT("'"&D$62&"'!A2:E1000"), (INDIRECT("'"&D$62&"'!B2:B1000")=$B38) * (INDIRECT("'"&D$62&"'!C2:C1000")=$C38) ), 5, FALSE )=0, "", VLOOKUP( $A38, _xlfn._xlws.FILTER( INDIRECT("'"&D$62&"'!A2:E1000"), (INDIRECT("'"&D$62&"'!B2:B1000")=$B38) * (INDIRECT("'"&D$62&"'!C2:C1000")=$C38) ), 5, FALSE ) )} | E38: {=IF( VLOOKUP( $A38, _xlfn._xlws.FILTER( INDIRECT("'"&E$62&"'!A2:E1000"), (INDIRECT("'"&E$62&"'!B2:B1000")=$B38) * (INDIRECT("'"&E$62&"'!C2:C1000")=$C38) ), 5, FALSE )=0, "", VLOOKUP( $A38, _xlfn._xlws.FILTER( INDIRECT("'"&E$62&"'!A2:E1000"), (INDIRECT("'"&E$62&"'!B2:B1000")=$B38) * (INDIRECT("'"&E$62&"'!C2:C1000")=$C38) ), 5, FALSE ) )} | F38: {=IF( VLOOKUP( $A38, _xlfn._xlws.FILTER( INDIRECT("'"&F$62&"'!A2:E1000"), (INDIRECT("'"&F$62&"'!B2:B1000")=$B38) * (INDIRECT("'"&F$62&"'!C2:C1000")=$C38) ), 5, FALSE )=0, "", VLOOKUP( $A38, _xlfn._xlws.FILTER( INDIRECT("'"&F$62&"'!A2:E1000"), (INDIRECT("'"&F$62&"'!B2:B1000")=$B38) * (INDIRECT("'"&F$62&"'!C2:C1000")=$C38) ), 5, FALSE ) )} | G38: {=IF( VLOOKUP( $A38, _xlfn._xlws.FILTER( INDIRECT("'"&G$62&"'!A2:E1000"), (INDIRECT("'"&G$62&"'!B2:B1000")=$B38) * (INDIRECT("'"&G$62&"'!C2:C1000")=$C38) ), 5, FALSE )=0, "", VLOOKUP( $A38, _xlfn._xlws.FILTER( INDIRECT("'"&G$62&"'!A2:E1000"), (INDIRECT("'"&G$62&"'!B2:B1000")=$B38) * (INDIRECT("'"&G$62&"'!C2:C1000")=$C38) ), 5, FALSE ) )} | H38: {=IF( VLOOKUP( $A38, _xlfn._xlws.FILTER( INDIRECT("'"&H$62&"'!A2:E1000"), (INDIRECT("'"&H$62&"'!B2:B1000")=$B38) * (INDIRECT("'"&H$62&"'!C2:C1000")=$C38) ), 5, FALSE )=0, "", VLOOKUP( $A38, _xlfn._xlws.FILTER( INDIRECT("'"&H$62&"'!A2:E1000"), (INDIRECT("'"&H$62&"'!B2:B1000")=$B38) * (INDIRECT("'"&H$62&"'!C2:C1000")=$C38) ), 5, FALSE ) )} | I38: {=IF( VLOOKUP( $A38, _xlfn._xlws.FILTER( INDIRECT("'"&I$62&"'!A2:E1000"), (INDIRECT("'"&I$62&"'!B2:B1000")=$B38) * (INDIRECT("'"&I$62&"'!C2:C1000")=$C38) ), 5, FALSE )=0, "", VLOOKUP( $A38, _xlfn._xlws.FILTER( INDIRECT("'"&I$62&"'!A2:E1000"), (INDIRECT("'"&I$62&"'!B2:B1000")=$B38) * (INDIRECT("'"&I$62&"'!C2:C1000")=$C38) ), 5, FALSE ) )} | J38: {=IF( VLOOKUP( $A38, _xlfn._xlws.FILTER( INDIRECT("'"&J$62&"'!A2:E1000"), (INDIRECT("'"&J$62&"'!B2:B1000")=$B38) * (INDIRECT("'"&J$62&"'!C2:C1000")=$C38) ), 5, FALSE )=0, "", VLOOKUP( $A38, _xlfn._xlws.FILTER( INDIRECT("'"&J$62&"'!A2:E1000"), (INDIRECT("'"&J$62&"'!B2:B1000")=$B38) * (INDIRECT("'"&J$62&"'!C2:C1000")=$C38) ), 5, FALSE ) )} | K38: {=IF( VLOOKUP( $A38, _xlfn._xlws.FILTER( INDIRECT("'"&K$62&"'!A2:E1000"), (INDIRECT("'"&K$62&"'!B2:B1000")=$B38) * (INDIRECT("'"&K$62&"'!C2:C1000")=$C38) ), 5, FALSE )=0, "", VLOOKUP( $A38, _xlfn._xlws.FILTER( INDIRECT("'"&K$62&"'!A2:E1000"), (INDIRECT("'"&K$62&"'!B2:B1000")=$B38) * (INDIRECT("'"&K$62&"'!C2:C1000")=$C38) ), 5, FALSE ) )} | ... O38: {=IF( VLOOKUP( $A38, _xlfn._xlws.FILTER( INDIRECT("'"&O$62&"'!A2:E1000"), (INDIRECT("'"&O$62&"'!B2:B1000")=$B38) * (INDIRECT("'"&O$62&"'!C2:C1000")=$C38) ), 5, FALSE )=0, "", VLOOKUP( $A38, _xlfn._xlws.FILTER( INDIRECT("'"&O$62&"'!A2:E1000"), (INDIRECT("'"&O$62&"'!B2:B1000")=$B38) * (INDIRECT("'"&O$62&"'!C2:C1000")=$C38) ), 5, FALSE ) )}
A39: Guarapuava II | B39: São João | C39: 01 | D39: {=IF( VLOOKUP( $A39, _xlfn._xlws.FILTER( INDIRECT("'"&D$62&"'!A2:E1000"), (INDIRECT("'"&D$62&"'!B2:B1000")=$B39) * (INDIRECT("'"&D$62&"'!C2:C1000")=$C39) ), 5, FALSE )=0, "", VLOOKUP( $A39, _xlfn._xlws.FILTER( INDIRECT("'"&D$62&"'!A2:E1000"), (INDIRECT("'"&D$62&"'!B2:B1000")=$B39) * (INDIRECT("'"&D$62&"'!C2:C1000")=$C39) ), 5, FALSE ) )} | E39: {=IF( VLOOKUP( $A39, _xlfn._xlws.FILTER( INDIRECT("'"&E$62&"'!A2:E1000"), (INDIRECT("'"&E$62&"'!B2:B1000")=$B39) * (INDIRECT("'"&E$62&"'!C2:C1000")=$C39) ), 5, FALSE )=0, "", VLOOKUP( $A39, _xlfn._xlws.FILTER( INDIRECT("'"&E$62&"'!A2:E1000"), (INDIRECT("'"&E$62&"'!B2:B1000")=$B39) * (INDIRECT("'"&E$62&"'!C2:C1000")=$C39) ), 5, FALSE ) )} | F39: {=IF( VLOOKUP( $A39, _xlfn._xlws.FILTER( INDIRECT("'"&F$62&"'!A2:E1000"), (INDIRECT("'"&F$62&"'!B2:B1000")=$B39) * (INDIRECT("'"&F$62&"'!C2:C1000")=$C39) ), 5, FALSE )=0, "", VLOOKUP( $A39, _xlfn._xlws.FILTER( INDIRECT("'"&F$62&"'!A2:E1000"), (INDIRECT("'"&F$62&"'!B2:B1000")=$B39) * (INDIRECT("'"&F$62&"'!C2:C1000")=$C39) ), 5, FALSE ) )} | G39: {=IF( VLOOKUP( $A39, _xlfn._xlws.FILTER( INDIRECT("'"&G$62&"'!A2:E1000"), (INDIRECT("'"&G$62&"'!B2:B1000")=$B39) * (INDIRECT("'"&G$62&"'!C2:C1000")=$C39) ), 5, FALSE )=0, "", VLOOKUP( $A39, _xlfn._xlws.FILTER( INDIRECT("'"&G$62&"'!A2:E1000"), (INDIRECT("'"&G$62&"'!B2:B1000")=$B39) * (INDIRECT("'"&G$62&"'!C2:C1000")=$C39) ), 5, FALSE ) )} | H39: {=IF( VLOOKUP( $A39, _xlfn._xlws.FILTER( INDIRECT("'"&H$62&"'!A2:E1000"), (INDIRECT("'"&H$62&"'!B2:B1000")=$B39) * (INDIRECT("'"&H$62&"'!C2:C1000")=$C39) ), 5, FALSE )=0, "", VLOOKUP( $A39, _xlfn._xlws.FILTER( INDIRECT("'"&H$62&"'!A2:E1000"), (INDIRECT("'"&H$62&"'!B2:B1000")=$B39) * (INDIRECT("'"&H$62&"'!C2:C1000")=$C39) ), 5, FALSE ) )} | I39: {=IF( VLOOKUP( $A39, _xlfn._xlws.FILTER( INDIRECT("'"&I$62&"'!A2:E1000"), (INDIRECT("'"&I$62&"'!B2:B1000")=$B39) * (INDIRECT("'"&I$62&"'!C2:C1000")=$C39) ), 5, FALSE )=0, "", VLOOKUP( $A39, _xlfn._xlws.FILTER( INDIRECT("'"&I$62&"'!A2:E1000"), (INDIRECT("'"&I$62&"'!B2:B1000")=$B39) * (INDIRECT("'"&I$62&"'!C2:C1000")=$C39) ), 5, FALSE ) )} | J39: {=IF( VLOOKUP( $A39, _xlfn._xlws.FILTER( INDIRECT("'"&J$62&"'!A2:E1000"), (INDIRECT("'"&J$62&"'!B2:B1000")=$B39) * (INDIRECT("'"&J$62&"'!C2:C1000")=$C39) ), 5, FALSE )=0, "", VLOOKUP( $A39, _xlfn._xlws.FILTER( INDIRECT("'"&J$62&"'!A2:E1000"), (INDIRECT("'"&J$62&"'!B2:B1000")=$B39) * (INDIRECT("'"&J$62&"'!C2:C1000")=$C39) ), 5, FALSE ) )} | K39: {=IF( VLOOKUP( $A39, _xlfn._xlws.FILTER( INDIRECT("'"&K$62&"'!A2:E1000"), (INDIRECT("'"&K$62&"'!B2:B1000")=$B39) * (INDIRECT("'"&K$62&"'!C2:C1000")=$C39) ), 5, FALSE )=0, "", VLOOKUP( $A39, _xlfn._xlws.FILTER( INDIRECT("'"&K$62&"'!A2:E1000"), (INDIRECT("'"&K$62&"'!B2:B1000")=$B39) * (INDIRECT("'"&K$62&"'!C2:C1000")=$C39) ), 5, FALSE ) )} | ... O39: {=IF( VLOOKUP( $A39, _xlfn._xlws.FILTER( INDIRECT("'"&O$62&"'!A2:E1000"), (INDIRECT("'"&O$62&"'!B2:B1000")=$B39) * (INDIRECT("'"&O$62&"'!C2:C1000")=$C39) ), 5, FALSE )=0, "", VLOOKUP( $A39, _xlfn._xlws.FILTER( INDIRECT("'"&O$62&"'!A2:E1000"), (INDIRECT("'"&O$62&"'!B2:B1000")=$B39) * (INDIRECT("'"&O$62&"'!C2:C1000")=$C39) ), 5, FALSE ) )}
A41: Johvanny | B41: Municípios | C41: UVR | D41: 01.25 | E41: 02.25 | F41: 03.25 | G41: 04.25 | H41: 05.25 | I41: 06.25 | J41: 07.25 | K41: 08.25 | L41: 09.25 | M41: 10.25 | N41: 11.25 | O41: 12.25
A42: Londrina | B42: Cambará | C42: 01 | D42: {=IF( VLOOKUP( $A42, _xlfn._xlws.FILTER( INDIRECT("'"&D$62&"'!A2:E1000"), (INDIRECT("'"&D$62&"'!B2:B1000")=$B42) * (INDIRECT("'"&D$62&"'!C2:C1000")=$C42) ), 5, FALSE )=0, "", VLOOKUP( $A42, _xlfn._xlws.FILTER( INDIRECT("'"&D$62&"'!A2:E1000"), (INDIRECT("'"&D$62&"'!B2:B1000")=$B42) * (INDIRECT("'"&D$62&"'!C2:C1000")=$C42) ), 5, FALSE ) )} | E42: {=IF( VLOOKUP( $A42, _xlfn._xlws.FILTER( INDIRECT("'"&E$62&"'!A2:E1000"), (INDIRECT("'"&E$62&"'!B2:B1000")=$B42) * (INDIRECT("'"&E$62&"'!C2:C1000")=$C42) ), 5, FALSE )=0, "", VLOOKUP( $A42, _xlfn._xlws.FILTER( INDIRECT("'"&E$62&"'!A2:E1000"), (INDIRECT("'"&E$62&"'!B2:B1000")=$B42) * (INDIRECT("'"&E$62&"'!C2:C1000")=$C42) ), 5, FALSE ) )} | F42: {=IF( VLOOKUP( $A42, _xlfn._xlws.FILTER( INDIRECT("'"&F$62&"'!A2:E1000"), (INDIRECT("'"&F$62&"'!B2:B1000")=$B42) * (INDIRECT("'"&F$62&"'!C2:C1000")=$C42) ), 5, FALSE )=0, "", VLOOKUP( $A42, _xlfn._xlws.FILTER( INDIRECT("'"&F$62&"'!A2:E1000"), (INDIRECT("'"&F$62&"'!B2:B1000")=$B42) * (INDIRECT("'"&F$62&"'!C2:C1000")=$C42) ), 5, FALSE ) )} | G42: {=IF( VLOOKUP( $A42, _xlfn._xlws.FILTER( INDIRECT("'"&G$62&"'!A2:E1000"), (INDIRECT("'"&G$62&"'!B2:B1000")=$B42) * (INDIRECT("'"&G$62&"'!C2:C1000")=$C42) ), 5, FALSE )=0, "", VLOOKUP( $A42, _xlfn._xlws.FILTER( INDIRECT("'"&G$62&"'!A2:E1000"), (INDIRECT("'"&G$62&"'!B2:B1000")=$B42) * (INDIRECT("'"&G$62&"'!C2:C1000")=$C42) ), 5, FALSE ) )} | H42: {=IF( VLOOKUP( $A42, _xlfn._xlws.FILTER( INDIRECT("'"&H$62&"'!A2:E1000"), (INDIRECT("'"&H$62&"'!B2:B1000")=$B42) * (INDIRECT("'"&H$62&"'!C2:C1000")=$C42) ), 5, FALSE )=0, "", VLOOKUP( $A42, _xlfn._xlws.FILTER( INDIRECT("'"&H$62&"'!A2:E1000"), (INDIRECT("'"&H$62&"'!B2:B1000")=$B42) * (INDIRECT("'"&H$62&"'!C2:C1000")=$C42) ), 5, FALSE ) )} | I42: {=IF( VLOOKUP( $A42, _xlfn._xlws.FILTER( INDIRECT("'"&I$62&"'!A2:E1000"), (INDIRECT("'"&I$62&"'!B2:B1000")=$B42) * (INDIRECT("'"&I$62&"'!C2:C1000")=$C42) ), 5, FALSE )=0, "", VLOOKUP( $A42, _xlfn._xlws.FILTER( INDIRECT("'"&I$62&"'!A2:E1000"), (INDIRECT("'"&I$62&"'!B2:B1000")=$B42) * (INDIRECT("'"&I$62&"'!C2:C1000")=$C42) ), 5, FALSE ) )} | J42: {=IF( VLOOKUP( $A42, _xlfn._xlws.FILTER( INDIRECT("'"&J$62&"'!A2:E1000"), (INDIRECT("'"&J$62&"'!B2:B1000")=$B42) * (INDIRECT("'"&J$62&"'!C2:C1000")=$C42) ), 5, FALSE )=0, "", VLOOKUP( $A42, _xlfn._xlws.FILTER( INDIRECT("'"&J$62&"'!A2:E1000"), (INDIRECT("'"&J$62&"'!B2:B1000")=$B42) * (INDIRECT("'"&J$62&"'!C2:C1000")=$C42) ), 5, FALSE ) )} | K42: {=IF( VLOOKUP( $A42, _xlfn._xlws.FILTER( INDIRECT("'"&K$62&"'!A2:E1000"), (INDIRECT("'"&K$62&"'!B2:B1000")=$B42) * (INDIRECT("'"&K$62&"'!C2:C1000")=$C42) ), 5, FALSE )=0, "", VLOOKUP( $A42, _xlfn._xlws.FILTER( INDIRECT("'"&K$62&"'!A2:E1000"), (INDIRECT("'"&K$62&"'!B2:B1000")=$B42) * (INDIRECT("'"&K$62&"'!C2:C1000")=$C42) ), 5, FALSE ) )} | ... O42: {=IF( VLOOKUP( $A42, _xlfn._xlws.FILTER( INDIRECT("'"&O$62&"'!A2:E1000"), (INDIRECT("'"&O$62&"'!B2:B1000")=$B42) * (INDIRECT("'"&O$62&"'!C2:C1000")=$C42) ), 5, FALSE )=0, "", VLOOKUP( $A42, _xlfn._xlws.FILTER( INDIRECT("'"&O$62&"'!A2:E1000"), (INDIRECT("'"&O$62&"'!B2:B1000")=$B42) * (INDIRECT("'"&O$62&"'!C2:C1000")=$C42) ), 5, FALSE ) )}
A43: Londrina | B43: Ibaiti | C43: 01 | D43: {=IF( VLOOKUP( $A43, _xlfn._xlws.FILTER( INDIRECT("'"&D$62&"'!A2:E1000"), (INDIRECT("'"&D$62&"'!B2:B1000")=$B43) * (INDIRECT("'"&D$62&"'!C2:C1000")=$C43) ), 5, FALSE )=0, "", VLOOKUP( $A43, _xlfn._xlws.FILTER( INDIRECT("'"&D$62&"'!A2:E1000"), (INDIRECT("'"&D$62&"'!B2:B1000")=$B43) * (INDIRECT("'"&D$62&"'!C2:C1000")=$C43) ), 5, FALSE ) )} | E43: {=IF( VLOOKUP( $A43, _xlfn._xlws.FILTER( INDIRECT("'"&E$62&"'!A2:E1000"), (INDIRECT("'"&E$62&"'!B2:B1000")=$B43) * (INDIRECT("'"&E$62&"'!C2:C1000")=$C43) ), 5, FALSE )=0, "", VLOOKUP( $A43, _xlfn._xlws.FILTER( INDIRECT("'"&E$62&"'!A2:E1000"), (INDIRECT("'"&E$62&"'!B2:B1000")=$B43) * (INDIRECT("'"&E$62&"'!C2:C1000")=$C43) ), 5, FALSE ) )} | F43: {=IF( VLOOKUP( $A43, _xlfn._xlws.FILTER( INDIRECT("'"&F$62&"'!A2:E1000"), (INDIRECT("'"&F$62&"'!B2:B1000")=$B43) * (INDIRECT("'"&F$62&"'!C2:C1000")=$C43) ), 5, FALSE )=0, "", VLOOKUP( $A43, _xlfn._xlws.FILTER( INDIRECT("'"&F$62&"'!A2:E1000"), (INDIRECT("'"&F$62&"'!B2:B1000")=$B43) * (INDIRECT("'"&F$62&"'!C2:C1000")=$C43) ), 5, FALSE ) )} | G43: {=IF( VLOOKUP( $A43, _xlfn._xlws.FILTER( INDIRECT("'"&G$62&"'!A2:E1000"), (INDIRECT("'"&G$62&"'!B2:B1000")=$B43) * (INDIRECT("'"&G$62&"'!C2:C1000")=$C43) ), 5, FALSE )=0, "", VLOOKUP( $A43, _xlfn._xlws.FILTER( INDIRECT("'"&G$62&"'!A2:E1000"), (INDIRECT("'"&G$62&"'!B2:B1000")=$B43) * (INDIRECT("'"&G$62&"'!C2:C1000")=$C43) ), 5, FALSE ) )} | H43: {=IF( VLOOKUP( $A43, _xlfn._xlws.FILTER( INDIRECT("'"&H$62&"'!A2:E1000"), (INDIRECT("'"&H$62&"'!B2:B1000")=$B43) * (INDIRECT("'"&H$62&"'!C2:C1000")=$C43) ), 5, FALSE )=0, "", VLOOKUP( $A43, _xlfn._xlws.FILTER( INDIRECT("'"&H$62&"'!A2:E1000"), (INDIRECT("'"&H$62&"'!B2:B1000")=$B43) * (INDIRECT("'"&H$62&"'!C2:C1000")=$C43) ), 5, FALSE ) )} | I43: {=IF( VLOOKUP( $A43, _xlfn._xlws.FILTER( INDIRECT("'"&I$62&"'!A2:E1000"), (INDIRECT("'"&I$62&"'!B2:B1000")=$B43) * (INDIRECT("'"&I$62&"'!C2:C1000")=$C43) ), 5, FALSE )=0, "", VLOOKUP( $A43, _xlfn._xlws.FILTER( INDIRECT("'"&I$62&"'!A2:E1000"), (INDIRECT("'"&I$62&"'!B2:B1000")=$B43) * (INDIRECT("'"&I$62&"'!C2:C1000")=$C43) ), 5, FALSE ) )} | J43: {=IF( VLOOKUP( $A43, _xlfn._xlws.FILTER( INDIRECT("'"&J$62&"'!A2:E1000"), (INDIRECT("'"&J$62&"'!B2:B1000")=$B43) * (INDIRECT("'"&J$62&"'!C2:C1000")=$C43) ), 5, FALSE )=0, "", VLOOKUP( $A43, _xlfn._xlws.FILTER( INDIRECT("'"&J$62&"'!A2:E1000"), (INDIRECT("'"&J$62&"'!B2:B1000")=$B43) * (INDIRECT("'"&J$62&"'!C2:C1000")=$C43) ), 5, FALSE ) )} | K43: {=IF( VLOOKUP( $A43, _xlfn._xlws.FILTER( INDIRECT("'"&K$62&"'!A2:E1000"), (INDIRECT("'"&K$62&"'!B2:B1000")=$B43) * (INDIRECT("'"&K$62&"'!C2:C1000")=$C43) ), 5, FALSE )=0, "", VLOOKUP( $A43, _xlfn._xlws.FILTER( INDIRECT("'"&K$62&"'!A2:E1000"), (INDIRECT("'"&K$62&"'!B2:B1000")=$B43) * (INDIRECT("'"&K$62&"'!C2:C1000")=$C43) ), 5, FALSE ) )} | ... O43: {=IF( VLOOKUP( $A43, _xlfn._xlws.FILTER( INDIRECT("'"&O$62&"'!A2:E1000"), (INDIRECT("'"&O$62&"'!B2:B1000")=$B43) * (INDIRECT("'"&O$62&"'!C2:C1000")=$C43) ), 5, FALSE )=0, "", VLOOKUP( $A43, _xlfn._xlws.FILTER( INDIRECT("'"&O$62&"'!A2:E1000"), (INDIRECT("'"&O$62&"'!B2:B1000")=$B43) * (INDIRECT("'"&O$62&"'!C2:C1000")=$C43) ), 5, FALSE ) )}
A44: Londrina | B44: Jaguapitã | C44: 01 | D44: {=IF( VLOOKUP( $A44, _xlfn._xlws.FILTER( INDIRECT("'"&D$62&"'!A2:E1000"), (INDIRECT("'"&D$62&"'!B2:B1000")=$B44) * (INDIRECT("'"&D$62&"'!C2:C1000")=$C44) ), 5, FALSE )=0, "", VLOOKUP( $A44, _xlfn._xlws.FILTER( INDIRECT("'"&D$62&"'!A2:E1000"), (INDIRECT("'"&D$62&"'!B2:B1000")=$B44) * (INDIRECT("'"&D$62&"'!C2:C1000")=$C44) ), 5, FALSE ) )} | E44: {=IF( VLOOKUP( $A44, _xlfn._xlws.FILTER( INDIRECT("'"&E$62&"'!A2:E1000"), (INDIRECT("'"&E$62&"'!B2:B1000")=$B44) * (INDIRECT("'"&E$62&"'!C2:C1000")=$C44) ), 5, FALSE )=0, "", VLOOKUP( $A44, _xlfn._xlws.FILTER( INDIRECT("'"&E$62&"'!A2:E1000"), (INDIRECT("'"&E$62&"'!B2:B1000")=$B44) * (INDIRECT("'"&E$62&"'!C2:C1000")=$C44) ), 5, FALSE ) )} | F44: {=IF( VLOOKUP( $A44, _xlfn._xlws.FILTER( INDIRECT("'"&F$62&"'!A2:E1000"), (INDIRECT("'"&F$62&"'!B2:B1000")=$B44) * (INDIRECT("'"&F$62&"'!C2:C1000")=$C44) ), 5, FALSE )=0, "", VLOOKUP( $A44, _xlfn._xlws.FILTER( INDIRECT("'"&F$62&"'!A2:E1000"), (INDIRECT("'"&F$62&"'!B2:B1000")=$B44) * (INDIRECT("'"&F$62&"'!C2:C1000")=$C44) ), 5, FALSE ) )} | G44: {=IF( VLOOKUP( $A44, _xlfn._xlws.FILTER( INDIRECT("'"&G$62&"'!A2:E1000"), (INDIRECT("'"&G$62&"'!B2:B1000")=$B44) * (INDIRECT("'"&G$62&"'!C2:C1000")=$C44) ), 5, FALSE )=0, "", VLOOKUP( $A44, _xlfn._xlws.FILTER( INDIRECT("'"&G$62&"'!A2:E1000"), (INDIRECT("'"&G$62&"'!B2:B1000")=$B44) * (INDIRECT("'"&G$62&"'!C2:C1000")=$C44) ), 5, FALSE ) )} | H44: {=IF( VLOOKUP( $A44, _xlfn._xlws.FILTER( INDIRECT("'"&H$62&"'!A2:E1000"), (INDIRECT("'"&H$62&"'!B2:B1000")=$B44) * (INDIRECT("'"&H$62&"'!C2:C1000")=$C44) ), 5, FALSE )=0, "", VLOOKUP( $A44, _xlfn._xlws.FILTER( INDIRECT("'"&H$62&"'!A2:E1000"), (INDIRECT("'"&H$62&"'!B2:B1000")=$B44) * (INDIRECT("'"&H$62&"'!C2:C1000")=$C44) ), 5, FALSE ) )} | I44: {=IF( VLOOKUP( $A44, _xlfn._xlws.FILTER( INDIRECT("'"&I$62&"'!A2:E1000"), (INDIRECT("'"&I$62&"'!B2:B1000")=$B44) * (INDIRECT("'"&I$62&"'!C2:C1000")=$C44) ), 5, FALSE )=0, "", VLOOKUP( $A44, _xlfn._xlws.FILTER( INDIRECT("'"&I$62&"'!A2:E1000"), (INDIRECT("'"&I$62&"'!B2:B1000")=$B44) * (INDIRECT("'"&I$62&"'!C2:C1000")=$C44) ), 5, FALSE ) )} | J44: {=IF( VLOOKUP( $A44, _xlfn._xlws.FILTER( INDIRECT("'"&J$62&"'!A2:E1000"), (INDIRECT("'"&J$62&"'!B2:B1000")=$B44) * (INDIRECT("'"&J$62&"'!C2:C1000")=$C44) ), 5, FALSE )=0, "", VLOOKUP( $A44, _xlfn._xlws.FILTER( INDIRECT("'"&J$62&"'!A2:E1000"), (INDIRECT("'"&J$62&"'!B2:B1000")=$B44) * (INDIRECT("'"&J$62&"'!C2:C1000")=$C44) ), 5, FALSE ) )} | K44: {=IF( VLOOKUP( $A44, _xlfn._xlws.FILTER( INDIRECT("'"&K$62&"'!A2:E1000"), (INDIRECT("'"&K$62&"'!B2:B1000")=$B44) * (INDIRECT("'"&K$62&"'!C2:C1000")=$C44) ), 5, FALSE )=0, "", VLOOKUP( $A44, _xlfn._xlws.FILTER( INDIRECT("'"&K$62&"'!A2:E1000"), (INDIRECT("'"&K$62&"'!B2:B1000")=$B44) * (INDIRECT("'"&K$62&"'!C2:C1000")=$C44) ), 5, FALSE ) )} | ... O44: {=IF( VLOOKUP( $A44, _xlfn._xlws.FILTER( INDIRECT("'"&O$62&"'!A2:E1000"), (INDIRECT("'"&O$62&"'!B2:B1000")=$B44) * (INDIRECT("'"&O$62&"'!C2:C1000")=$C44) ), 5, FALSE )=0, "", VLOOKUP( $A44, _xlfn._xlws.FILTER( INDIRECT("'"&O$62&"'!A2:E1000"), (INDIRECT("'"&O$62&"'!B2:B1000")=$B44) * (INDIRECT("'"&O$62&"'!C2:C1000")=$C44) ), 5, FALSE ) )}
A45: Londrina | B45: Jaguariaíva | C45: 01 | D45: {=IF( VLOOKUP( $A45, _xlfn._xlws.FILTER( INDIRECT("'"&D$62&"'!A2:E1000"), (INDIRECT("'"&D$62&"'!B2:B1000")=$B45) * (INDIRECT("'"&D$62&"'!C2:C1000")=$C45) ), 5, FALSE )=0, "", VLOOKUP( $A45, _xlfn._xlws.FILTER( INDIRECT("'"&D$62&"'!A2:E1000"), (INDIRECT("'"&D$62&"'!B2:B1000")=$B45) * (INDIRECT("'"&D$62&"'!C2:C1000")=$C45) ), 5, FALSE ) )} | E45: {=IF( VLOOKUP( $A45, _xlfn._xlws.FILTER( INDIRECT("'"&E$62&"'!A2:E1000"), (INDIRECT("'"&E$62&"'!B2:B1000")=$B45) * (INDIRECT("'"&E$62&"'!C2:C1000")=$C45) ), 5, FALSE )=0, "", VLOOKUP( $A45, _xlfn._xlws.FILTER( INDIRECT("'"&E$62&"'!A2:E1000"), (INDIRECT("'"&E$62&"'!B2:B1000")=$B45) * (INDIRECT("'"&E$62&"'!C2:C1000")=$C45) ), 5, FALSE ) )} | F45: {=IF( VLOOKUP( $A45, _xlfn._xlws.FILTER( INDIRECT("'"&F$62&"'!A2:E1000"), (INDIRECT("'"&F$62&"'!B2:B1000")=$B45) * (INDIRECT("'"&F$62&"'!C2:C1000")=$C45) ), 5, FALSE )=0, "", VLOOKUP( $A45, _xlfn._xlws.FILTER( INDIRECT("'"&F$62&"'!A2:E1000"), (INDIRECT("'"&F$62&"'!B2:B1000")=$B45) * (INDIRECT("'"&F$62&"'!C2:C1000")=$C45) ), 5, FALSE ) )} | G45: {=IF( VLOOKUP( $A45, _xlfn._xlws.FILTER( INDIRECT("'"&G$62&"'!A2:E1000"), (INDIRECT("'"&G$62&"'!B2:B1000")=$B45) * (INDIRECT("'"&G$62&"'!C2:C1000")=$C45) ), 5, FALSE )=0, "", VLOOKUP( $A45, _xlfn._xlws.FILTER( INDIRECT("'"&G$62&"'!A2:E1000"), (INDIRECT("'"&G$62&"'!B2:B1000")=$B45) * (INDIRECT("'"&G$62&"'!C2:C1000")=$C45) ), 5, FALSE ) )} | H45: {=IF( VLOOKUP( $A45, _xlfn._xlws.FILTER( INDIRECT("'"&H$62&"'!A2:E1000"), (INDIRECT("'"&H$62&"'!B2:B1000")=$B45) * (INDIRECT("'"&H$62&"'!C2:C1000")=$C45) ), 5, FALSE )=0, "", VLOOKUP( $A45, _xlfn._xlws.FILTER( INDIRECT("'"&H$62&"'!A2:E1000"), (INDIRECT("'"&H$62&"'!B2:B1000")=$B45) * (INDIRECT("'"&H$62&"'!C2:C1000")=$C45) ), 5, FALSE ) )} | I45: {=IF( VLOOKUP( $A45, _xlfn._xlws.FILTER( INDIRECT("'"&I$62&"'!A2:E1000"), (INDIRECT("'"&I$62&"'!B2:B1000")=$B45) * (INDIRECT("'"&I$62&"'!C2:C1000")=$C45) ), 5, FALSE )=0, "", VLOOKUP( $A45, _xlfn._xlws.FILTER( INDIRECT("'"&I$62&"'!A2:E1000"), (INDIRECT("'"&I$62&"'!B2:B1000")=$B45) * (INDIRECT("'"&I$62&"'!C2:C1000")=$C45) ), 5, FALSE ) )} | J45: {=IF( VLOOKUP( $A45, _xlfn._xlws.FILTER( INDIRECT("'"&J$62&"'!A2:E1000"), (INDIRECT("'"&J$62&"'!B2:B1000")=$B45) * (INDIRECT("'"&J$62&"'!C2:C1000")=$C45) ), 5, FALSE )=0, "", VLOOKUP( $A45, _xlfn._xlws.FILTER( INDIRECT("'"&J$62&"'!A2:E1000"), (INDIRECT("'"&J$62&"'!B2:B1000")=$B45) * (INDIRECT("'"&J$62&"'!C2:C1000")=$C45) ), 5, FALSE ) )} | K45: {=IF( VLOOKUP( $A45, _xlfn._xlws.FILTER( INDIRECT("'"&K$62&"'!A2:E1000"), (INDIRECT("'"&K$62&"'!B2:B1000")=$B45) * (INDIRECT("'"&K$62&"'!C2:C1000")=$C45) ), 5, FALSE )=0, "", VLOOKUP( $A45, _xlfn._xlws.FILTER( INDIRECT("'"&K$62&"'!A2:E1000"), (INDIRECT("'"&K$62&"'!B2:B1000")=$B45) * (INDIRECT("'"&K$62&"'!C2:C1000")=$C45) ), 5, FALSE ) )} | ... O45: {=IF( VLOOKUP( $A45, _xlfn._xlws.FILTER( INDIRECT("'"&O$62&"'!A2:E1000"), (INDIRECT("'"&O$62&"'!B2:B1000")=$B45) * (INDIRECT("'"&O$62&"'!C2:C1000")=$C45) ), 5, FALSE )=0, "", VLOOKUP( $A45, _xlfn._xlws.FILTER( INDIRECT("'"&O$62&"'!A2:E1000"), (INDIRECT("'"&O$62&"'!B2:B1000")=$B45) * (INDIRECT("'"&O$62&"'!C2:C1000")=$C45) ), 5, FALSE ) )}
A46: Londrina | B46: Ortigueira | C46: 01 | D46: {=IF( VLOOKUP( $A46, _xlfn._xlws.FILTER( INDIRECT("'"&D$62&"'!A2:E1000"), (INDIRECT("'"&D$62&"'!B2:B1000")=$B46) * (INDIRECT("'"&D$62&"'!C2:C1000")=$C46) ), 5, FALSE )=0, "", VLOOKUP( $A46, _xlfn._xlws.FILTER( INDIRECT("'"&D$62&"'!A2:E1000"), (INDIRECT("'"&D$62&"'!B2:B1000")=$B46) * (INDIRECT("'"&D$62&"'!C2:C1000")=$C46) ), 5, FALSE ) )} | E46: {=IF( VLOOKUP( $A46, _xlfn._xlws.FILTER( INDIRECT("'"&E$62&"'!A2:E1000"), (INDIRECT("'"&E$62&"'!B2:B1000")=$B46) * (INDIRECT("'"&E$62&"'!C2:C1000")=$C46) ), 5, FALSE )=0, "", VLOOKUP( $A46, _xlfn._xlws.FILTER( INDIRECT("'"&E$62&"'!A2:E1000"), (INDIRECT("'"&E$62&"'!B2:B1000")=$B46) * (INDIRECT("'"&E$62&"'!C2:C1000")=$C46) ), 5, FALSE ) )} | F46: {=IF( VLOOKUP( $A46, _xlfn._xlws.FILTER( INDIRECT("'"&F$62&"'!A2:E1000"), (INDIRECT("'"&F$62&"'!B2:B1000")=$B46) * (INDIRECT("'"&F$62&"'!C2:C1000")=$C46) ), 5, FALSE )=0, "", VLOOKUP( $A46, _xlfn._xlws.FILTER( INDIRECT("'"&F$62&"'!A2:E1000"), (INDIRECT("'"&F$62&"'!B2:B1000")=$B46) * (INDIRECT("'"&F$62&"'!C2:C1000")=$C46) ), 5, FALSE ) )} | G46: {=IF( VLOOKUP( $A46, _xlfn._xlws.FILTER( INDIRECT("'"&G$62&"'!A2:E1000"), (INDIRECT("'"&G$62&"'!B2:B1000")=$B46) * (INDIRECT("'"&G$62&"'!C2:C1000")=$C46) ), 5, FALSE )=0, "", VLOOKUP( $A46, _xlfn._xlws.FILTER( INDIRECT("'"&G$62&"'!A2:E1000"), (INDIRECT("'"&G$62&"'!B2:B1000")=$B46) * (INDIRECT("'"&G$62&"'!C2:C1000")=$C46) ), 5, FALSE ) )} | H46: {=IF( VLOOKUP( $A46, _xlfn._xlws.FILTER( INDIRECT("'"&H$62&"'!A2:E1000"), (INDIRECT("'"&H$62&"'!B2:B1000")=$B46) * (INDIRECT("'"&H$62&"'!C2:C1000")=$C46) ), 5, FALSE )=0, "", VLOOKUP( $A46, _xlfn._xlws.FILTER( INDIRECT("'"&H$62&"'!A2:E1000"), (INDIRECT("'"&H$62&"'!B2:B1000")=$B46) * (INDIRECT("'"&H$62&"'!C2:C1000")=$C46) ), 5, FALSE ) )} | I46: {=IF( VLOOKUP( $A46, _xlfn._xlws.FILTER( INDIRECT("'"&I$62&"'!A2:E1000"), (INDIRECT("'"&I$62&"'!B2:B1000")=$B46) * (INDIRECT("'"&I$62&"'!C2:C1000")=$C46) ), 5, FALSE )=0, "", VLOOKUP( $A46, _xlfn._xlws.FILTER( INDIRECT("'"&I$62&"'!A2:E1000"), (INDIRECT("'"&I$62&"'!B2:B1000")=$B46) * (INDIRECT("'"&I$62&"'!C2:C1000")=$C46) ), 5, FALSE ) )} | J46: {=IF( VLOOKUP( $A46, _xlfn._xlws.FILTER( INDIRECT("'"&J$62&"'!A2:E1000"), (INDIRECT("'"&J$62&"'!B2:B1000")=$B46) * (INDIRECT("'"&J$62&"'!C2:C1000")=$C46) ), 5, FALSE )=0, "", VLOOKUP( $A46, _xlfn._xlws.FILTER( INDIRECT("'"&J$62&"'!A2:E1000"), (INDIRECT("'"&J$62&"'!B2:B1000")=$B46) * (INDIRECT("'"&J$62&"'!C2:C1000")=$C46) ), 5, FALSE ) )} | K46: {=IF( VLOOKUP( $A46, _xlfn._xlws.FILTER( INDIRECT("'"&K$62&"'!A2:E1000"), (INDIRECT("'"&K$62&"'!B2:B1000")=$B46) * (INDIRECT("'"&K$62&"'!C2:C1000")=$C46) ), 5, FALSE )=0, "", VLOOKUP( $A46, _xlfn._xlws.FILTER( INDIRECT("'"&K$62&"'!A2:E1000"), (INDIRECT("'"&K$62&"'!B2:B1000")=$B46) * (INDIRECT("'"&K$62&"'!C2:C1000")=$C46) ), 5, FALSE ) )} | ... O46: {=IF( VLOOKUP( $A46, _xlfn._xlws.FILTER( INDIRECT("'"&O$62&"'!A2:E1000"), (INDIRECT("'"&O$62&"'!B2:B1000")=$B46) * (INDIRECT("'"&O$62&"'!C2:C1000")=$C46) ), 5, FALSE )=0, "", VLOOKUP( $A46, _xlfn._xlws.FILTER( INDIRECT("'"&O$62&"'!A2:E1000"), (INDIRECT("'"&O$62&"'!B2:B1000")=$B46) * (INDIRECT("'"&O$62&"'!C2:C1000")=$C46) ), 5, FALSE ) )}
A47: Londrina | B47: Ribeirão Claro | C47: 01 | D47: {=IF( VLOOKUP( $A47, _xlfn._xlws.FILTER( INDIRECT("'"&D$62&"'!A2:E1000"), (INDIRECT("'"&D$62&"'!B2:B1000")=$B47) * (INDIRECT("'"&D$62&"'!C2:C1000")=$C47) ), 5, FALSE )=0, "", VLOOKUP( $A47, _xlfn._xlws.FILTER( INDIRECT("'"&D$62&"'!A2:E1000"), (INDIRECT("'"&D$62&"'!B2:B1000")=$B47) * (INDIRECT("'"&D$62&"'!C2:C1000")=$C47) ), 5, FALSE ) )} | E47: {=IF( VLOOKUP( $A47, _xlfn._xlws.FILTER( INDIRECT("'"&E$62&"'!A2:E1000"), (INDIRECT("'"&E$62&"'!B2:B1000")=$B47) * (INDIRECT("'"&E$62&"'!C2:C1000")=$C47) ), 5, FALSE )=0, "", VLOOKUP( $A47, _xlfn._xlws.FILTER( INDIRECT("'"&E$62&"'!A2:E1000"), (INDIRECT("'"&E$62&"'!B2:B1000")=$B47) * (INDIRECT("'"&E$62&"'!C2:C1000")=$C47) ), 5, FALSE ) )} | F47: {=IF( VLOOKUP( $A47, _xlfn._xlws.FILTER( INDIRECT("'"&F$62&"'!A2:E1000"), (INDIRECT("'"&F$62&"'!B2:B1000")=$B47) * (INDIRECT("'"&F$62&"'!C2:C1000")=$C47) ), 5, FALSE )=0, "", VLOOKUP( $A47, _xlfn._xlws.FILTER( INDIRECT("'"&F$62&"'!A2:E1000"), (INDIRECT("'"&F$62&"'!B2:B1000")=$B47) * (INDIRECT("'"&F$62&"'!C2:C1000")=$C47) ), 5, FALSE ) )} | G47: {=IF( VLOOKUP( $A47, _xlfn._xlws.FILTER( INDIRECT("'"&G$62&"'!A2:E1000"), (INDIRECT("'"&G$62&"'!B2:B1000")=$B47) * (INDIRECT("'"&G$62&"'!C2:C1000")=$C47) ), 5, FALSE )=0, "", VLOOKUP( $A47, _xlfn._xlws.FILTER( INDIRECT("'"&G$62&"'!A2:E1000"), (INDIRECT("'"&G$62&"'!B2:B1000")=$B47) * (INDIRECT("'"&G$62&"'!C2:C1000")=$C47) ), 5, FALSE ) )} | H47: {=IF( VLOOKUP( $A47, _xlfn._xlws.FILTER( INDIRECT("'"&H$62&"'!A2:E1000"), (INDIRECT("'"&H$62&"'!B2:B1000")=$B47) * (INDIRECT("'"&H$62&"'!C2:C1000")=$C47) ), 5, FALSE )=0, "", VLOOKUP( $A47, _xlfn._xlws.FILTER( INDIRECT("'"&H$62&"'!A2:E1000"), (INDIRECT("'"&H$62&"'!B2:B1000")=$B47) * (INDIRECT("'"&H$62&"'!C2:C1000")=$C47) ), 5, FALSE ) )} | I47: {=IF( VLOOKUP( $A47, _xlfn._xlws.FILTER( INDIRECT("'"&I$62&"'!A2:E1000"), (INDIRECT("'"&I$62&"'!B2:B1000")=$B47) * (INDIRECT("'"&I$62&"'!C2:C1000")=$C47) ), 5, FALSE )=0, "", VLOOKUP( $A47, _xlfn._xlws.FILTER( INDIRECT("'"&I$62&"'!A2:E1000"), (INDIRECT("'"&I$62&"'!B2:B1000")=$B47) * (INDIRECT("'"&I$62&"'!C2:C1000")=$C47) ), 5, FALSE ) )} | J47: {=IF( VLOOKUP( $A47, _xlfn._xlws.FILTER( INDIRECT("'"&J$62&"'!A2:E1000"), (INDIRECT("'"&J$62&"'!B2:B1000")=$B47) * (INDIRECT("'"&J$62&"'!C2:C1000")=$C47) ), 5, FALSE )=0, "", VLOOKUP( $A47, _xlfn._xlws.FILTER( INDIRECT("'"&J$62&"'!A2:E1000"), (INDIRECT("'"&J$62&"'!B2:B1000")=$B47) * (INDIRECT("'"&J$62&"'!C2:C1000")=$C47) ), 5, FALSE ) )} | K47: {=IF( VLOOKUP( $A47, _xlfn._xlws.FILTER( INDIRECT("'"&K$62&"'!A2:E1000"), (INDIRECT("'"&K$62&"'!B2:B1000")=$B47) * (INDIRECT("'"&K$62&"'!C2:C1000")=$C47) ), 5, FALSE )=0, "", VLOOKUP( $A47, _xlfn._xlws.FILTER( INDIRECT("'"&K$62&"'!A2:E1000"), (INDIRECT("'"&K$62&"'!B2:B1000")=$B47) * (INDIRECT("'"&K$62&"'!C2:C1000")=$C47) ), 5, FALSE ) )} | ... O47: {=IF( VLOOKUP( $A47, _xlfn._xlws.FILTER( INDIRECT("'"&O$62&"'!A2:E1000"), (INDIRECT("'"&O$62&"'!B2:B1000")=$B47) * (INDIRECT("'"&O$62&"'!C2:C1000")=$C47) ), 5, FALSE )=0, "", VLOOKUP( $A47, _xlfn._xlws.FILTER( INDIRECT("'"&O$62&"'!A2:E1000"), (INDIRECT("'"&O$62&"'!B2:B1000")=$B47) * (INDIRECT("'"&O$62&"'!C2:C1000")=$C47) ), 5, FALSE ) )}
A48: Londrina | B48: Santa Mariana | C48: 01 | D48: {=IF( VLOOKUP( $A48, _xlfn._xlws.FILTER( INDIRECT("'"&D$62&"'!A2:E1000"), (INDIRECT("'"&D$62&"'!B2:B1000")=$B48) * (INDIRECT("'"&D$62&"'!C2:C1000")=$C48) ), 5, FALSE )=0, "", VLOOKUP( $A48, _xlfn._xlws.FILTER( INDIRECT("'"&D$62&"'!A2:E1000"), (INDIRECT("'"&D$62&"'!B2:B1000")=$B48) * (INDIRECT("'"&D$62&"'!C2:C1000")=$C48) ), 5, FALSE ) )} | E48: {=IF( VLOOKUP( $A48, _xlfn._xlws.FILTER( INDIRECT("'"&E$62&"'!A2:E1000"), (INDIRECT("'"&E$62&"'!B2:B1000")=$B48) * (INDIRECT("'"&E$62&"'!C2:C1000")=$C48) ), 5, FALSE )=0, "", VLOOKUP( $A48, _xlfn._xlws.FILTER( INDIRECT("'"&E$62&"'!A2:E1000"), (INDIRECT("'"&E$62&"'!B2:B1000")=$B48) * (INDIRECT("'"&E$62&"'!C2:C1000")=$C48) ), 5, FALSE ) )} | F48: {=IF( VLOOKUP( $A48, _xlfn._xlws.FILTER( INDIRECT("'"&F$62&"'!A2:E1000"), (INDIRECT("'"&F$62&"'!B2:B1000")=$B48) * (INDIRECT("'"&F$62&"'!C2:C1000")=$C48) ), 5, FALSE )=0, "", VLOOKUP( $A48, _xlfn._xlws.FILTER( INDIRECT("'"&F$62&"'!A2:E1000"), (INDIRECT("'"&F$62&"'!B2:B1000")=$B48) * (INDIRECT("'"&F$62&"'!C2:C1000")=$C48) ), 5, FALSE ) )} | G48: {=IF( VLOOKUP( $A48, _xlfn._xlws.FILTER( INDIRECT("'"&G$62&"'!A2:E1000"), (INDIRECT("'"&G$62&"'!B2:B1000")=$B48) * (INDIRECT("'"&G$62&"'!C2:C1000")=$C48) ), 5, FALSE )=0, "", VLOOKUP( $A48, _xlfn._xlws.FILTER( INDIRECT("'"&G$62&"'!A2:E1000"), (INDIRECT("'"&G$62&"'!B2:B1000")=$B48) * (INDIRECT("'"&G$62&"'!C2:C1000")=$C48) ), 5, FALSE ) )} | H48: {=IF( VLOOKUP( $A48, _xlfn._xlws.FILTER( INDIRECT("'"&H$62&"'!A2:E1000"), (INDIRECT("'"&H$62&"'!B2:B1000")=$B48) * (INDIRECT("'"&H$62&"'!C2:C1000")=$C48) ), 5, FALSE )=0, "", VLOOKUP( $A48, _xlfn._xlws.FILTER( INDIRECT("'"&H$62&"'!A2:E1000"), (INDIRECT("'"&H$62&"'!B2:B1000")=$B48) * (INDIRECT("'"&H$62&"'!C2:C1000")=$C48) ), 5, FALSE ) )} | I48: {=IF( VLOOKUP( $A48, _xlfn._xlws.FILTER( INDIRECT("'"&I$62&"'!A2:E1000"), (INDIRECT("'"&I$62&"'!B2:B1000")=$B48) * (INDIRECT("'"&I$62&"'!C2:C1000")=$C48) ), 5, FALSE )=0, "", VLOOKUP( $A48, _xlfn._xlws.FILTER( INDIRECT("'"&I$62&"'!A2:E1000"), (INDIRECT("'"&I$62&"'!B2:B1000")=$B48) * (INDIRECT("'"&I$62&"'!C2:C1000")=$C48) ), 5, FALSE ) )} | J48: {=IF( VLOOKUP( $A48, _xlfn._xlws.FILTER( INDIRECT("'"&J$62&"'!A2:E1000"), (INDIRECT("'"&J$62&"'!B2:B1000")=$B48) * (INDIRECT("'"&J$62&"'!C2:C1000")=$C48) ), 5, FALSE )=0, "", VLOOKUP( $A48, _xlfn._xlws.FILTER( INDIRECT("'"&J$62&"'!A2:E1000"), (INDIRECT("'"&J$62&"'!B2:B1000")=$B48) * (INDIRECT("'"&J$62&"'!C2:C1000")=$C48) ), 5, FALSE ) )} | K48: {=IF( VLOOKUP( $A48, _xlfn._xlws.FILTER( INDIRECT("'"&K$62&"'!A2:E1000"), (INDIRECT("'"&K$62&"'!B2:B1000")=$B48) * (INDIRECT("'"&K$62&"'!C2:C1000")=$C48) ), 5, FALSE )=0, "", VLOOKUP( $A48, _xlfn._xlws.FILTER( INDIRECT("'"&K$62&"'!A2:E1000"), (INDIRECT("'"&K$62&"'!B2:B1000")=$B48) * (INDIRECT("'"&K$62&"'!C2:C1000")=$C48) ), 5, FALSE ) )} | ... O48: {=IF( VLOOKUP( $A48, _xlfn._xlws.FILTER( INDIRECT("'"&O$62&"'!A2:E1000"), (INDIRECT("'"&O$62&"'!B2:B1000")=$B48) * (INDIRECT("'"&O$62&"'!C2:C1000")=$C48) ), 5, FALSE )=0, "", VLOOKUP( $A48, _xlfn._xlws.FILTER( INDIRECT("'"&O$62&"'!A2:E1000"), (INDIRECT("'"&O$62&"'!B2:B1000")=$B48) * (INDIRECT("'"&O$62&"'!C2:C1000")=$C48) ), 5, FALSE ) )}
A49: Londrina | B49: Santana Do Itararé | C49: 01 | D49: {=IF( VLOOKUP( $A49, _xlfn._xlws.FILTER( INDIRECT("'"&D$62&"'!A2:E1000"), (INDIRECT("'"&D$62&"'!B2:B1000")=$B49) * (INDIRECT("'"&D$62&"'!C2:C1000")=$C49) ), 5, FALSE )=0, "", VLOOKUP( $A49, _xlfn._xlws.FILTER( INDIRECT("'"&D$62&"'!A2:E1000"), (INDIRECT("'"&D$62&"'!B2:B1000")=$B49) * (INDIRECT("'"&D$62&"'!C2:C1000")=$C49) ), 5, FALSE ) )} | E49: {=IF( VLOOKUP( $A49, _xlfn._xlws.FILTER( INDIRECT("'"&E$62&"'!A2:E1000"), (INDIRECT("'"&E$62&"'!B2:B1000")=$B49) * (INDIRECT("'"&E$62&"'!C2:C1000")=$C49) ), 5, FALSE )=0, "", VLOOKUP( $A49, _xlfn._xlws.FILTER( INDIRECT("'"&E$62&"'!A2:E1000"), (INDIRECT("'"&E$62&"'!B2:B1000")=$B49) * (INDIRECT("'"&E$62&"'!C2:C1000")=$C49) ), 5, FALSE ) )} | F49: {=IF( VLOOKUP( $A49, _xlfn._xlws.FILTER( INDIRECT("'"&F$62&"'!A2:E1000"), (INDIRECT("'"&F$62&"'!B2:B1000")=$B49) * (INDIRECT("'"&F$62&"'!C2:C1000")=$C49) ), 5, FALSE )=0, "", VLOOKUP( $A49, _xlfn._xlws.FILTER( INDIRECT("'"&F$62&"'!A2:E1000"), (INDIRECT("'"&F$62&"'!B2:B1000")=$B49) * (INDIRECT("'"&F$62&"'!C2:C1000")=$C49) ), 5, FALSE ) )} | G49: {=IF( VLOOKUP( $A49, _xlfn._xlws.FILTER( INDIRECT("'"&G$62&"'!A2:E1000"), (INDIRECT("'"&G$62&"'!B2:B1000")=$B49) * (INDIRECT("'"&G$62&"'!C2:C1000")=$C49) ), 5, FALSE )=0, "", VLOOKUP( $A49, _xlfn._xlws.FILTER( INDIRECT("'"&G$62&"'!A2:E1000"), (INDIRECT("'"&G$62&"'!B2:B1000")=$B49) * (INDIRECT("'"&G$62&"'!C2:C1000")=$C49) ), 5, FALSE ) )} | H49: {=IF( VLOOKUP( $A49, _xlfn._xlws.FILTER( INDIRECT("'"&H$62&"'!A2:E1000"), (INDIRECT("'"&H$62&"'!B2:B1000")=$B49) * (INDIRECT("'"&H$62&"'!C2:C1000")=$C49) ), 5, FALSE )=0, "", VLOOKUP( $A49, _xlfn._xlws.FILTER( INDIRECT("'"&H$62&"'!A2:E1000"), (INDIRECT("'"&H$62&"'!B2:B1000")=$B49) * (INDIRECT("'"&H$62&"'!C2:C1000")=$C49) ), 5, FALSE ) )} | I49: {=IF( VLOOKUP( $A49, _xlfn._xlws.FILTER( INDIRECT("'"&I$62&"'!A2:E1000"), (INDIRECT("'"&I$62&"'!B2:B1000")=$B49) * (INDIRECT("'"&I$62&"'!C2:C1000")=$C49) ), 5, FALSE )=0, "", VLOOKUP( $A49, _xlfn._xlws.FILTER( INDIRECT("'"&I$62&"'!A2:E1000"), (INDIRECT("'"&I$62&"'!B2:B1000")=$B49) * (INDIRECT("'"&I$62&"'!C2:C1000")=$C49) ), 5, FALSE ) )} | J49: {=IF( VLOOKUP( $A49, _xlfn._xlws.FILTER( INDIRECT("'"&J$62&"'!A2:E1000"), (INDIRECT("'"&J$62&"'!B2:B1000")=$B49) * (INDIRECT("'"&J$62&"'!C2:C1000")=$C49) ), 5, FALSE )=0, "", VLOOKUP( $A49, _xlfn._xlws.FILTER( INDIRECT("'"&J$62&"'!A2:E1000"), (INDIRECT("'"&J$62&"'!B2:B1000")=$B49) * (INDIRECT("'"&J$62&"'!C2:C1000")=$C49) ), 5, FALSE ) )} | K49: {=IF( VLOOKUP( $A49, _xlfn._xlws.FILTER( INDIRECT("'"&K$62&"'!A2:E1000"), (INDIRECT("'"&K$62&"'!B2:B1000")=$B49) * (INDIRECT("'"&K$62&"'!C2:C1000")=$C49) ), 5, FALSE )=0, "", VLOOKUP( $A49, _xlfn._xlws.FILTER( INDIRECT("'"&K$62&"'!A2:E1000"), (INDIRECT("'"&K$62&"'!B2:B1000")=$B49) * (INDIRECT("'"&K$62&"'!C2:C1000")=$C49) ), 5, FALSE ) )} | ... O49: {=IF( VLOOKUP( $A49, _xlfn._xlws.FILTER( INDIRECT("'"&O$62&"'!A2:E1000"), (INDIRECT("'"&O$62&"'!B2:B1000")=$B49) * (INDIRECT("'"&O$62&"'!C2:C1000")=$C49) ), 5, FALSE )=0, "", VLOOKUP( $A49, _xlfn._xlws.FILTER( INDIRECT("'"&O$62&"'!A2:E1000"), (INDIRECT("'"&O$62&"'!B2:B1000")=$B49) * (INDIRECT("'"&O$62&"'!C2:C1000")=$C49) ), 5, FALSE ) )}
A51: Diana | B51: Municípios | C51: UVR | D51: 01.25 | E51: 02.25 | F51: 03.25 | G51: 04.25 | H51: 05.25 | I51: 06.25 | J51: 07.25 | K51: 08.25 | L51: 09.25 | M51: 10.25 | N51: 11.25 | O51: 12.25
A52: Maringá | B52: Apucarana | C52: 01 | D52: {=IF( VLOOKUP( $A52, _xlfn._xlws.FILTER( INDIRECT("'"&D$62&"'!A2:E1000"), (INDIRECT("'"&D$62&"'!B2:B1000")=$B52) * (INDIRECT("'"&D$62&"'!C2:C1000")=$C52) ), 5, FALSE )=0, "", VLOOKUP( $A52, _xlfn._xlws.FILTER( INDIRECT("'"&D$62&"'!A2:E1000"), (INDIRECT("'"&D$62&"'!B2:B1000")=$B52) * (INDIRECT("'"&D$62&"'!C2:C1000")=$C52) ), 5, FALSE ) )} | E52: {=IF( VLOOKUP( $A52, _xlfn._xlws.FILTER( INDIRECT("'"&E$62&"'!A2:E1000"), (INDIRECT("'"&E$62&"'!B2:B1000")=$B52) * (INDIRECT("'"&E$62&"'!C2:C1000")=$C52) ), 5, FALSE )=0, "", VLOOKUP( $A52, _xlfn._xlws.FILTER( INDIRECT("'"&E$62&"'!A2:E1000"), (INDIRECT("'"&E$62&"'!B2:B1000")=$B52) * (INDIRECT("'"&E$62&"'!C2:C1000")=$C52) ), 5, FALSE ) )} | F52: {=IF( VLOOKUP( $A52, _xlfn._xlws.FILTER( INDIRECT("'"&F$62&"'!A2:E1000"), (INDIRECT("'"&F$62&"'!B2:B1000")=$B52) * (INDIRECT("'"&F$62&"'!C2:C1000")=$C52) ), 5, FALSE )=0, "", VLOOKUP( $A52, _xlfn._xlws.FILTER( INDIRECT("'"&F$62&"'!A2:E1000"), (INDIRECT("'"&F$62&"'!B2:B1000")=$B52) * (INDIRECT("'"&F$62&"'!C2:C1000")=$C52) ), 5, FALSE ) )} | G52: {=IF( VLOOKUP( $A52, _xlfn._xlws.FILTER( INDIRECT("'"&G$62&"'!A2:E1000"), (INDIRECT("'"&G$62&"'!B2:B1000")=$B52) * (INDIRECT("'"&G$62&"'!C2:C1000")=$C52) ), 5, FALSE )=0, "", VLOOKUP( $A52, _xlfn._xlws.FILTER( INDIRECT("'"&G$62&"'!A2:E1000"), (INDIRECT("'"&G$62&"'!B2:B1000")=$B52) * (INDIRECT("'"&G$62&"'!C2:C1000")=$C52) ), 5, FALSE ) )} | H52: {=IF( VLOOKUP( $A52, _xlfn._xlws.FILTER( INDIRECT("'"&H$62&"'!A2:E1000"), (INDIRECT("'"&H$62&"'!B2:B1000")=$B52) * (INDIRECT("'"&H$62&"'!C2:C1000")=$C52) ), 5, FALSE )=0, "", VLOOKUP( $A52, _xlfn._xlws.FILTER( INDIRECT("'"&H$62&"'!A2:E1000"), (INDIRECT("'"&H$62&"'!B2:B1000")=$B52) * (INDIRECT("'"&H$62&"'!C2:C1000")=$C52) ), 5, FALSE ) )} | I52: {=IF( VLOOKUP( $A52, _xlfn._xlws.FILTER( INDIRECT("'"&I$62&"'!A2:E1000"), (INDIRECT("'"&I$62&"'!B2:B1000")=$B52) * (INDIRECT("'"&I$62&"'!C2:C1000")=$C52) ), 5, FALSE )=0, "", VLOOKUP( $A52, _xlfn._xlws.FILTER( INDIRECT("'"&I$62&"'!A2:E1000"), (INDIRECT("'"&I$62&"'!B2:B1000")=$B52) * (INDIRECT("'"&I$62&"'!C2:C1000")=$C52) ), 5, FALSE ) )} | J52: {=IF( VLOOKUP( $A52, _xlfn._xlws.FILTER( INDIRECT("'"&J$62&"'!A2:E1000"), (INDIRECT("'"&J$62&"'!B2:B1000")=$B52) * (INDIRECT("'"&J$62&"'!C2:C1000")=$C52) ), 5, FALSE )=0, "", VLOOKUP( $A52, _xlfn._xlws.FILTER( INDIRECT("'"&J$62&"'!A2:E1000"), (INDIRECT("'"&J$62&"'!B2:B1000")=$B52) * (INDIRECT("'"&J$62&"'!C2:C1000")=$C52) ), 5, FALSE ) )} | K52: {=IF( VLOOKUP( $A52, _xlfn._xlws.FILTER( INDIRECT("'"&K$62&"'!A2:E1000"), (INDIRECT("'"&K$62&"'!B2:B1000")=$B52) * (INDIRECT("'"&K$62&"'!C2:C1000")=$C52) ), 5, FALSE )=0, "", VLOOKUP( $A52, _xlfn._xlws.FILTER( INDIRECT("'"&K$62&"'!A2:E1000"), (INDIRECT("'"&K$62&"'!B2:B1000")=$B52) * (INDIRECT("'"&K$62&"'!C2:C1000")=$C52) ), 5, FALSE ) )} | ... O52: {=IF( VLOOKUP( $A52, _xlfn._xlws.FILTER( INDIRECT("'"&O$62&"'!A2:E1000"), (INDIRECT("'"&O$62&"'!B2:B1000")=$B52) * (INDIRECT("'"&O$62&"'!C2:C1000")=$C52) ), 5, FALSE )=0, "", VLOOKUP( $A52, _xlfn._xlws.FILTER( INDIRECT("'"&O$62&"'!A2:E1000"), (INDIRECT("'"&O$62&"'!B2:B1000")=$B52) * (INDIRECT("'"&O$62&"'!C2:C1000")=$C52) ), 5, FALSE ) )}
A53: Maringá | B53: Atalaia | C53: 01 | D53: {=IF( VLOOKUP( $A53, _xlfn._xlws.FILTER( INDIRECT("'"&D$62&"'!A2:E1000"), (INDIRECT("'"&D$62&"'!B2:B1000")=$B53) * (INDIRECT("'"&D$62&"'!C2:C1000")=$C53) ), 5, FALSE )=0, "", VLOOKUP( $A53, _xlfn._xlws.FILTER( INDIRECT("'"&D$62&"'!A2:E1000"), (INDIRECT("'"&D$62&"'!B2:B1000")=$B53) * (INDIRECT("'"&D$62&"'!C2:C1000")=$C53) ), 5, FALSE ) )} | E53: {=IF( VLOOKUP( $A53, _xlfn._xlws.FILTER( INDIRECT("'"&E$62&"'!A2:E1000"), (INDIRECT("'"&E$62&"'!B2:B1000")=$B53) * (INDIRECT("'"&E$62&"'!C2:C1000")=$C53) ), 5, FALSE )=0, "", VLOOKUP( $A53, _xlfn._xlws.FILTER( INDIRECT("'"&E$62&"'!A2:E1000"), (INDIRECT("'"&E$62&"'!B2:B1000")=$B53) * (INDIRECT("'"&E$62&"'!C2:C1000")=$C53) ), 5, FALSE ) )} | F53: {=IF( VLOOKUP( $A53, _xlfn._xlws.FILTER( INDIRECT("'"&F$62&"'!A2:E1000"), (INDIRECT("'"&F$62&"'!B2:B1000")=$B53) * (INDIRECT("'"&F$62&"'!C2:C1000")=$C53) ), 5, FALSE )=0, "", VLOOKUP( $A53, _xlfn._xlws.FILTER( INDIRECT("'"&F$62&"'!A2:E1000"), (INDIRECT("'"&F$62&"'!B2:B1000")=$B53) * (INDIRECT("'"&F$62&"'!C2:C1000")=$C53) ), 5, FALSE ) )} | G53: {=IF( VLOOKUP( $A53, _xlfn._xlws.FILTER( INDIRECT("'"&G$62&"'!A2:E1000"), (INDIRECT("'"&G$62&"'!B2:B1000")=$B53) * (INDIRECT("'"&G$62&"'!C2:C1000")=$C53) ), 5, FALSE )=0, "", VLOOKUP( $A53, _xlfn._xlws.FILTER( INDIRECT("'"&G$62&"'!A2:E1000"), (INDIRECT("'"&G$62&"'!B2:B1000")=$B53) * (INDIRECT("'"&G$62&"'!C2:C1000")=$C53) ), 5, FALSE ) )} | H53: {=IF( VLOOKUP( $A53, _xlfn._xlws.FILTER( INDIRECT("'"&H$62&"'!A2:E1000"), (INDIRECT("'"&H$62&"'!B2:B1000")=$B53) * (INDIRECT("'"&H$62&"'!C2:C1000")=$C53) ), 5, FALSE )=0, "", VLOOKUP( $A53, _xlfn._xlws.FILTER( INDIRECT("'"&H$62&"'!A2:E1000"), (INDIRECT("'"&H$62&"'!B2:B1000")=$B53) * (INDIRECT("'"&H$62&"'!C2:C1000")=$C53) ), 5, FALSE ) )} | I53: {=IF( VLOOKUP( $A53, _xlfn._xlws.FILTER( INDIRECT("'"&I$62&"'!A2:E1000"), (INDIRECT("'"&I$62&"'!B2:B1000")=$B53) * (INDIRECT("'"&I$62&"'!C2:C1000")=$C53) ), 5, FALSE )=0, "", VLOOKUP( $A53, _xlfn._xlws.FILTER( INDIRECT("'"&I$62&"'!A2:E1000"), (INDIRECT("'"&I$62&"'!B2:B1000")=$B53) * (INDIRECT("'"&I$62&"'!C2:C1000")=$C53) ), 5, FALSE ) )} | J53: {=IF( VLOOKUP( $A53, _xlfn._xlws.FILTER( INDIRECT("'"&J$62&"'!A2:E1000"), (INDIRECT("'"&J$62&"'!B2:B1000")=$B53) * (INDIRECT("'"&J$62&"'!C2:C1000")=$C53) ), 5, FALSE )=0, "", VLOOKUP( $A53, _xlfn._xlws.FILTER( INDIRECT("'"&J$62&"'!A2:E1000"), (INDIRECT("'"&J$62&"'!B2:B1000")=$B53) * (INDIRECT("'"&J$62&"'!C2:C1000")=$C53) ), 5, FALSE ) )} | K53: {=IF( VLOOKUP( $A53, _xlfn._xlws.FILTER( INDIRECT("'"&K$62&"'!A2:E1000"), (INDIRECT("'"&K$62&"'!B2:B1000")=$B53) * (INDIRECT("'"&K$62&"'!C2:C1000")=$C53) ), 5, FALSE )=0, "", VLOOKUP( $A53, _xlfn._xlws.FILTER( INDIRECT("'"&K$62&"'!A2:E1000"), (INDIRECT("'"&K$62&"'!B2:B1000")=$B53) * (INDIRECT("'"&K$62&"'!C2:C1000")=$C53) ), 5, FALSE ) )} | ... O53: {=IF( VLOOKUP( $A53, _xlfn._xlws.FILTER( INDIRECT("'"&O$62&"'!A2:E1000"), (INDIRECT("'"&O$62&"'!B2:B1000")=$B53) * (INDIRECT("'"&O$62&"'!C2:C1000")=$C53) ), 5, FALSE )=0, "", VLOOKUP( $A53, _xlfn._xlws.FILTER( INDIRECT("'"&O$62&"'!A2:E1000"), (INDIRECT("'"&O$62&"'!B2:B1000")=$B53) * (INDIRECT("'"&O$62&"'!C2:C1000")=$C53) ), 5, FALSE ) )}
A54: Maringá | B54: Borrazópolis | C54: 01 | D54: {=IF( VLOOKUP( $A54, _xlfn._xlws.FILTER( INDIRECT("'"&D$62&"'!A2:E1000"), (INDIRECT("'"&D$62&"'!B2:B1000")=$B54) * (INDIRECT("'"&D$62&"'!C2:C1000")=$C54) ), 5, FALSE )=0, "", VLOOKUP( $A54, _xlfn._xlws.FILTER( INDIRECT("'"&D$62&"'!A2:E1000"), (INDIRECT("'"&D$62&"'!B2:B1000")=$B54) * (INDIRECT("'"&D$62&"'!C2:C1000")=$C54) ), 5, FALSE ) )} | E54: {=IF( VLOOKUP( $A54, _xlfn._xlws.FILTER( INDIRECT("'"&E$62&"'!A2:E1000"), (INDIRECT("'"&E$62&"'!B2:B1000")=$B54) * (INDIRECT("'"&E$62&"'!C2:C1000")=$C54) ), 5, FALSE )=0, "", VLOOKUP( $A54, _xlfn._xlws.FILTER( INDIRECT("'"&E$62&"'!A2:E1000"), (INDIRECT("'"&E$62&"'!B2:B1000")=$B54) * (INDIRECT("'"&E$62&"'!C2:C1000")=$C54) ), 5, FALSE ) )} | F54: {=IF( VLOOKUP( $A54, _xlfn._xlws.FILTER( INDIRECT("'"&F$62&"'!A2:E1000"), (INDIRECT("'"&F$62&"'!B2:B1000")=$B54) * (INDIRECT("'"&F$62&"'!C2:C1000")=$C54) ), 5, FALSE )=0, "", VLOOKUP( $A54, _xlfn._xlws.FILTER( INDIRECT("'"&F$62&"'!A2:E1000"), (INDIRECT("'"&F$62&"'!B2:B1000")=$B54) * (INDIRECT("'"&F$62&"'!C2:C1000")=$C54) ), 5, FALSE ) )} | G54: {=IF( VLOOKUP( $A54, _xlfn._xlws.FILTER( INDIRECT("'"&G$62&"'!A2:E1000"), (INDIRECT("'"&G$62&"'!B2:B1000")=$B54) * (INDIRECT("'"&G$62&"'!C2:C1000")=$C54) ), 5, FALSE )=0, "", VLOOKUP( $A54, _xlfn._xlws.FILTER( INDIRECT("'"&G$62&"'!A2:E1000"), (INDIRECT("'"&G$62&"'!B2:B1000")=$B54) * (INDIRECT("'"&G$62&"'!C2:C1000")=$C54) ), 5, FALSE ) )} | H54: {=IF( VLOOKUP( $A54, _xlfn._xlws.FILTER( INDIRECT("'"&H$62&"'!A2:E1000"), (INDIRECT("'"&H$62&"'!B2:B1000")=$B54) * (INDIRECT("'"&H$62&"'!C2:C1000")=$C54) ), 5, FALSE )=0, "", VLOOKUP( $A54, _xlfn._xlws.FILTER( INDIRECT("'"&H$62&"'!A2:E1000"), (INDIRECT("'"&H$62&"'!B2:B1000")=$B54) * (INDIRECT("'"&H$62&"'!C2:C1000")=$C54) ), 5, FALSE ) )} | I54: {=IF( VLOOKUP( $A54, _xlfn._xlws.FILTER( INDIRECT("'"&I$62&"'!A2:E1000"), (INDIRECT("'"&I$62&"'!B2:B1000")=$B54) * (INDIRECT("'"&I$62&"'!C2:C1000")=$C54) ), 5, FALSE )=0, "", VLOOKUP( $A54, _xlfn._xlws.FILTER( INDIRECT("'"&I$62&"'!A2:E1000"), (INDIRECT("'"&I$62&"'!B2:B1000")=$B54) * (INDIRECT("'"&I$62&"'!C2:C1000")=$C54) ), 5, FALSE ) )} | J54: {=IF( VLOOKUP( $A54, _xlfn._xlws.FILTER( INDIRECT("'"&J$62&"'!A2:E1000"), (INDIRECT("'"&J$62&"'!B2:B1000")=$B54) * (INDIRECT("'"&J$62&"'!C2:C1000")=$C54) ), 5, FALSE )=0, "", VLOOKUP( $A54, _xlfn._xlws.FILTER( INDIRECT("'"&J$62&"'!A2:E1000"), (INDIRECT("'"&J$62&"'!B2:B1000")=$B54) * (INDIRECT("'"&J$62&"'!C2:C1000")=$C54) ), 5, FALSE ) )} | K54: {=IF( VLOOKUP( $A54, _xlfn._xlws.FILTER( INDIRECT("'"&K$62&"'!A2:E1000"), (INDIRECT("'"&K$62&"'!B2:B1000")=$B54) * (INDIRECT("'"&K$62&"'!C2:C1000")=$C54) ), 5, FALSE )=0, "", VLOOKUP( $A54, _xlfn._xlws.FILTER( INDIRECT("'"&K$62&"'!A2:E1000"), (INDIRECT("'"&K$62&"'!B2:B1000")=$B54) * (INDIRECT("'"&K$62&"'!C2:C1000")=$C54) ), 5, FALSE ) )} | ... O54: {=IF( VLOOKUP( $A54, _xlfn._xlws.FILTER( INDIRECT("'"&O$62&"'!A2:E1000"), (INDIRECT("'"&O$62&"'!B2:B1000")=$B54) * (INDIRECT("'"&O$62&"'!C2:C1000")=$C54) ), 5, FALSE )=0, "", VLOOKUP( $A54, _xlfn._xlws.FILTER( INDIRECT("'"&O$62&"'!A2:E1000"), (INDIRECT("'"&O$62&"'!B2:B1000")=$B54) * (INDIRECT("'"&O$62&"'!C2:C1000")=$C54) ), 5, FALSE ) )}
A55: Maringá | B55: Jardim Alegre | C55: 01 | D55: {=IF( VLOOKUP( $A55, _xlfn._xlws.FILTER( INDIRECT("'"&D$62&"'!A2:E1000"), (INDIRECT("'"&D$62&"'!B2:B1000")=$B55) * (INDIRECT("'"&D$62&"'!C2:C1000")=$C55) ), 5, FALSE )=0, "", VLOOKUP( $A55, _xlfn._xlws.FILTER( INDIRECT("'"&D$62&"'!A2:E1000"), (INDIRECT("'"&D$62&"'!B2:B1000")=$B55) * (INDIRECT("'"&D$62&"'!C2:C1000")=$C55) ), 5, FALSE ) )} | E55: {=IF( VLOOKUP( $A55, _xlfn._xlws.FILTER( INDIRECT("'"&E$62&"'!A2:E1000"), (INDIRECT("'"&E$62&"'!B2:B1000")=$B55) * (INDIRECT("'"&E$62&"'!C2:C1000")=$C55) ), 5, FALSE )=0, "", VLOOKUP( $A55, _xlfn._xlws.FILTER( INDIRECT("'"&E$62&"'!A2:E1000"), (INDIRECT("'"&E$62&"'!B2:B1000")=$B55) * (INDIRECT("'"&E$62&"'!C2:C1000")=$C55) ), 5, FALSE ) )} | F55: {=IF( VLOOKUP( $A55, _xlfn._xlws.FILTER( INDIRECT("'"&F$62&"'!A2:E1000"), (INDIRECT("'"&F$62&"'!B2:B1000")=$B55) * (INDIRECT("'"&F$62&"'!C2:C1000")=$C55) ), 5, FALSE )=0, "", VLOOKUP( $A55, _xlfn._xlws.FILTER( INDIRECT("'"&F$62&"'!A2:E1000"), (INDIRECT("'"&F$62&"'!B2:B1000")=$B55) * (INDIRECT("'"&F$62&"'!C2:C1000")=$C55) ), 5, FALSE ) )} | G55: {=IF( VLOOKUP( $A55, _xlfn._xlws.FILTER( INDIRECT("'"&G$62&"'!A2:E1000"), (INDIRECT("'"&G$62&"'!B2:B1000")=$B55) * (INDIRECT("'"&G$62&"'!C2:C1000")=$C55) ), 5, FALSE )=0, "", VLOOKUP( $A55, _xlfn._xlws.FILTER( INDIRECT("'"&G$62&"'!A2:E1000"), (INDIRECT("'"&G$62&"'!B2:B1000")=$B55) * (INDIRECT("'"&G$62&"'!C2:C1000")=$C55) ), 5, FALSE ) )} | H55: {=IF( VLOOKUP( $A55, _xlfn._xlws.FILTER( INDIRECT("'"&H$62&"'!A2:E1000"), (INDIRECT("'"&H$62&"'!B2:B1000")=$B55) * (INDIRECT("'"&H$62&"'!C2:C1000")=$C55) ), 5, FALSE )=0, "", VLOOKUP( $A55, _xlfn._xlws.FILTER( INDIRECT("'"&H$62&"'!A2:E1000"), (INDIRECT("'"&H$62&"'!B2:B1000")=$B55) * (INDIRECT("'"&H$62&"'!C2:C1000")=$C55) ), 5, FALSE ) )} | I55: {=IF( VLOOKUP( $A55, _xlfn._xlws.FILTER( INDIRECT("'"&I$62&"'!A2:E1000"), (INDIRECT("'"&I$62&"'!B2:B1000")=$B55) * (INDIRECT("'"&I$62&"'!C2:C1000")=$C55) ), 5, FALSE )=0, "", VLOOKUP( $A55, _xlfn._xlws.FILTER( INDIRECT("'"&I$62&"'!A2:E1000"), (INDIRECT("'"&I$62&"'!B2:B1000")=$B55) * (INDIRECT("'"&I$62&"'!C2:C1000")=$C55) ), 5, FALSE ) )} | J55: {=IF( VLOOKUP( $A55, _xlfn._xlws.FILTER( INDIRECT("'"&J$62&"'!A2:E1000"), (INDIRECT("'"&J$62&"'!B2:B1000")=$B55) * (INDIRECT("'"&J$62&"'!C2:C1000")=$C55) ), 5, FALSE )=0, "", VLOOKUP( $A55, _xlfn._xlws.FILTER( INDIRECT("'"&J$62&"'!A2:E1000"), (INDIRECT("'"&J$62&"'!B2:B1000")=$B55) * (INDIRECT("'"&J$62&"'!C2:C1000")=$C55) ), 5, FALSE ) )} | K55: {=IF( VLOOKUP( $A55, _xlfn._xlws.FILTER( INDIRECT("'"&K$62&"'!A2:E1000"), (INDIRECT("'"&K$62&"'!B2:B1000")=$B55) * (INDIRECT("'"&K$62&"'!C2:C1000")=$C55) ), 5, FALSE )=0, "", VLOOKUP( $A55, _xlfn._xlws.FILTER( INDIRECT("'"&K$62&"'!A2:E1000"), (INDIRECT("'"&K$62&"'!B2:B1000")=$B55) * (INDIRECT("'"&K$62&"'!C2:C1000")=$C55) ), 5, FALSE ) )} | ... O55: {=IF( VLOOKUP( $A55, _xlfn._xlws.FILTER( INDIRECT("'"&O$62&"'!A2:E1000"), (INDIRECT("'"&O$62&"'!B2:B1000")=$B55) * (INDIRECT("'"&O$62&"'!C2:C1000")=$C55) ), 5, FALSE )=0, "", VLOOKUP( $A55, _xlfn._xlws.FILTER( INDIRECT("'"&O$62&"'!A2:E1000"), (INDIRECT("'"&O$62&"'!B2:B1000")=$B55) * (INDIRECT("'"&O$62&"'!C2:C1000")=$C55) ), 5, FALSE ) )}
A56: Maringá | B56: Kaloré | C56: 01 | D56: {=IF( VLOOKUP( $A56, _xlfn._xlws.FILTER( INDIRECT("'"&D$62&"'!A2:E1000"), (INDIRECT("'"&D$62&"'!B2:B1000")=$B56) * (INDIRECT("'"&D$62&"'!C2:C1000")=$C56) ), 5, FALSE )=0, "", VLOOKUP( $A56, _xlfn._xlws.FILTER( INDIRECT("'"&D$62&"'!A2:E1000"), (INDIRECT("'"&D$62&"'!B2:B1000")=$B56) * (INDIRECT("'"&D$62&"'!C2:C1000")=$C56) ), 5, FALSE ) )} | E56: {=IF( VLOOKUP( $A56, _xlfn._xlws.FILTER( INDIRECT("'"&E$62&"'!A2:E1000"), (INDIRECT("'"&E$62&"'!B2:B1000")=$B56) * (INDIRECT("'"&E$62&"'!C2:C1000")=$C56) ), 5, FALSE )=0, "", VLOOKUP( $A56, _xlfn._xlws.FILTER( INDIRECT("'"&E$62&"'!A2:E1000"), (INDIRECT("'"&E$62&"'!B2:B1000")=$B56) * (INDIRECT("'"&E$62&"'!C2:C1000")=$C56) ), 5, FALSE ) )} | F56: {=IF( VLOOKUP( $A56, _xlfn._xlws.FILTER( INDIRECT("'"&F$62&"'!A2:E1000"), (INDIRECT("'"&F$62&"'!B2:B1000")=$B56) * (INDIRECT("'"&F$62&"'!C2:C1000")=$C56) ), 5, FALSE )=0, "", VLOOKUP( $A56, _xlfn._xlws.FILTER( INDIRECT("'"&F$62&"'!A2:E1000"), (INDIRECT("'"&F$62&"'!B2:B1000")=$B56) * (INDIRECT("'"&F$62&"'!C2:C1000")=$C56) ), 5, FALSE ) )} | G56: {=IF( VLOOKUP( $A56, _xlfn._xlws.FILTER( INDIRECT("'"&G$62&"'!A2:E1000"), (INDIRECT("'"&G$62&"'!B2:B1000")=$B56) * (INDIRECT("'"&G$62&"'!C2:C1000")=$C56) ), 5, FALSE )=0, "", VLOOKUP( $A56, _xlfn._xlws.FILTER( INDIRECT("'"&G$62&"'!A2:E1000"), (INDIRECT("'"&G$62&"'!B2:B1000")=$B56) * (INDIRECT("'"&G$62&"'!C2:C1000")=$C56) ), 5, FALSE ) )} | H56: {=IF( VLOOKUP( $A56, _xlfn._xlws.FILTER( INDIRECT("'"&H$62&"'!A2:E1000"), (INDIRECT("'"&H$62&"'!B2:B1000")=$B56) * (INDIRECT("'"&H$62&"'!C2:C1000")=$C56) ), 5, FALSE )=0, "", VLOOKUP( $A56, _xlfn._xlws.FILTER( INDIRECT("'"&H$62&"'!A2:E1000"), (INDIRECT("'"&H$62&"'!B2:B1000")=$B56) * (INDIRECT("'"&H$62&"'!C2:C1000")=$C56) ), 5, FALSE ) )} | I56: {=IF( VLOOKUP( $A56, _xlfn._xlws.FILTER( INDIRECT("'"&I$62&"'!A2:E1000"), (INDIRECT("'"&I$62&"'!B2:B1000")=$B56) * (INDIRECT("'"&I$62&"'!C2:C1000")=$C56) ), 5, FALSE )=0, "", VLOOKUP( $A56, _xlfn._xlws.FILTER( INDIRECT("'"&I$62&"'!A2:E1000"), (INDIRECT("'"&I$62&"'!B2:B1000")=$B56) * (INDIRECT("'"&I$62&"'!C2:C1000")=$C56) ), 5, FALSE ) )} | J56: {=IF( VLOOKUP( $A56, _xlfn._xlws.FILTER( INDIRECT("'"&J$62&"'!A2:E1000"), (INDIRECT("'"&J$62&"'!B2:B1000")=$B56) * (INDIRECT("'"&J$62&"'!C2:C1000")=$C56) ), 5, FALSE )=0, "", VLOOKUP( $A56, _xlfn._xlws.FILTER( INDIRECT("'"&J$62&"'!A2:E1000"), (INDIRECT("'"&J$62&"'!B2:B1000")=$B56) * (INDIRECT("'"&J$62&"'!C2:C1000")=$C56) ), 5, FALSE ) )} | K56: {=IF( VLOOKUP( $A56, _xlfn._xlws.FILTER( INDIRECT("'"&K$62&"'!A2:E1000"), (INDIRECT("'"&K$62&"'!B2:B1000")=$B56) * (INDIRECT("'"&K$62&"'!C2:C1000")=$C56) ), 5, FALSE )=0, "", VLOOKUP( $A56, _xlfn._xlws.FILTER( INDIRECT("'"&K$62&"'!A2:E1000"), (INDIRECT("'"&K$62&"'!B2:B1000")=$B56) * (INDIRECT("'"&K$62&"'!C2:C1000")=$C56) ), 5, FALSE ) )} | ... O56: {=IF( VLOOKUP( $A56, _xlfn._xlws.FILTER( INDIRECT("'"&O$62&"'!A2:E1000"), (INDIRECT("'"&O$62&"'!B2:B1000")=$B56) * (INDIRECT("'"&O$62&"'!C2:C1000")=$C56) ), 5, FALSE )=0, "", VLOOKUP( $A56, _xlfn._xlws.FILTER( INDIRECT("'"&O$62&"'!A2:E1000"), (INDIRECT("'"&O$62&"'!B2:B1000")=$B56) * (INDIRECT("'"&O$62&"'!C2:C1000")=$C56) ), 5, FALSE ) )}
A57: Maringá | B57: Mandaguari | C57: 01 | D57: {=IF( VLOOKUP( $A57, _xlfn._xlws.FILTER( INDIRECT("'"&D$62&"'!A2:E1000"), (INDIRECT("'"&D$62&"'!B2:B1000")=$B57) * (INDIRECT("'"&D$62&"'!C2:C1000")=$C57) ), 5, FALSE )=0, "", VLOOKUP( $A57, _xlfn._xlws.FILTER( INDIRECT("'"&D$62&"'!A2:E1000"), (INDIRECT("'"&D$62&"'!B2:B1000")=$B57) * (INDIRECT("'"&D$62&"'!C2:C1000")=$C57) ), 5, FALSE ) )} | E57: {=IF( VLOOKUP( $A57, _xlfn._xlws.FILTER( INDIRECT("'"&E$62&"'!A2:E1000"), (INDIRECT("'"&E$62&"'!B2:B1000")=$B57) * (INDIRECT("'"&E$62&"'!C2:C1000")=$C57) ), 5, FALSE )=0, "", VLOOKUP( $A57, _xlfn._xlws.FILTER( INDIRECT("'"&E$62&"'!A2:E1000"), (INDIRECT("'"&E$62&"'!B2:B1000")=$B57) * (INDIRECT("'"&E$62&"'!C2:C1000")=$C57) ), 5, FALSE ) )} | F57: {=IF( VLOOKUP( $A57, _xlfn._xlws.FILTER( INDIRECT("'"&F$62&"'!A2:E1000"), (INDIRECT("'"&F$62&"'!B2:B1000")=$B57) * (INDIRECT("'"&F$62&"'!C2:C1000")=$C57) ), 5, FALSE )=0, "", VLOOKUP( $A57, _xlfn._xlws.FILTER( INDIRECT("'"&F$62&"'!A2:E1000"), (INDIRECT("'"&F$62&"'!B2:B1000")=$B57) * (INDIRECT("'"&F$62&"'!C2:C1000")=$C57) ), 5, FALSE ) )} | G57: {=IF( VLOOKUP( $A57, _xlfn._xlws.FILTER( INDIRECT("'"&G$62&"'!A2:E1000"), (INDIRECT("'"&G$62&"'!B2:B1000")=$B57) * (INDIRECT("'"&G$62&"'!C2:C1000")=$C57) ), 5, FALSE )=0, "", VLOOKUP( $A57, _xlfn._xlws.FILTER( INDIRECT("'"&G$62&"'!A2:E1000"), (INDIRECT("'"&G$62&"'!B2:B1000")=$B57) * (INDIRECT("'"&G$62&"'!C2:C1000")=$C57) ), 5, FALSE ) )} | H57: {=IF( VLOOKUP( $A57, _xlfn._xlws.FILTER( INDIRECT("'"&H$62&"'!A2:E1000"), (INDIRECT("'"&H$62&"'!B2:B1000")=$B57) * (INDIRECT("'"&H$62&"'!C2:C1000")=$C57) ), 5, FALSE )=0, "", VLOOKUP( $A57, _xlfn._xlws.FILTER( INDIRECT("'"&H$62&"'!A2:E1000"), (INDIRECT("'"&H$62&"'!B2:B1000")=$B57) * (INDIRECT("'"&H$62&"'!C2:C1000")=$C57) ), 5, FALSE ) )} | I57: {=IF( VLOOKUP( $A57, _xlfn._xlws.FILTER( INDIRECT("'"&I$62&"'!A2:E1000"), (INDIRECT("'"&I$62&"'!B2:B1000")=$B57) * (INDIRECT("'"&I$62&"'!C2:C1000")=$C57) ), 5, FALSE )=0, "", VLOOKUP( $A57, _xlfn._xlws.FILTER( INDIRECT("'"&I$62&"'!A2:E1000"), (INDIRECT("'"&I$62&"'!B2:B1000")=$B57) * (INDIRECT("'"&I$62&"'!C2:C1000")=$C57) ), 5, FALSE ) )} | J57: {=IF( VLOOKUP( $A57, _xlfn._xlws.FILTER( INDIRECT("'"&J$62&"'!A2:E1000"), (INDIRECT("'"&J$62&"'!B2:B1000")=$B57) * (INDIRECT("'"&J$62&"'!C2:C1000")=$C57) ), 5, FALSE )=0, "", VLOOKUP( $A57, _xlfn._xlws.FILTER( INDIRECT("'"&J$62&"'!A2:E1000"), (INDIRECT("'"&J$62&"'!B2:B1000")=$B57) * (INDIRECT("'"&J$62&"'!C2:C1000")=$C57) ), 5, FALSE ) )} | K57: {=IF( VLOOKUP( $A57, _xlfn._xlws.FILTER( INDIRECT("'"&K$62&"'!A2:E1000"), (INDIRECT("'"&K$62&"'!B2:B1000")=$B57) * (INDIRECT("'"&K$62&"'!C2:C1000")=$C57) ), 5, FALSE )=0, "", VLOOKUP( $A57, _xlfn._xlws.FILTER( INDIRECT("'"&K$62&"'!A2:E1000"), (INDIRECT("'"&K$62&"'!B2:B1000")=$B57) * (INDIRECT("'"&K$62&"'!C2:C1000")=$C57) ), 5, FALSE ) )} | ... O57: {=IF( VLOOKUP( $A57, _xlfn._xlws.FILTER( INDIRECT("'"&O$62&"'!A2:E1000"), (INDIRECT("'"&O$62&"'!B2:B1000")=$B57) * (INDIRECT("'"&O$62&"'!C2:C1000")=$C57) ), 5, FALSE )=0, "", VLOOKUP( $A57, _xlfn._xlws.FILTER( INDIRECT("'"&O$62&"'!A2:E1000"), (INDIRECT("'"&O$62&"'!B2:B1000")=$B57) * (INDIRECT("'"&O$62&"'!C2:C1000")=$C57) ), 5, FALSE ) )}
A58: Maringá | B58: Nova Tebas | C58: 01 | D58: {=IF( VLOOKUP( $A58, _xlfn._xlws.FILTER( INDIRECT("'"&D$62&"'!A2:E1000"), (INDIRECT("'"&D$62&"'!B2:B1000")=$B58) * (INDIRECT("'"&D$62&"'!C2:C1000")=$C58) ), 5, FALSE )=0, "", VLOOKUP( $A58, _xlfn._xlws.FILTER( INDIRECT("'"&D$62&"'!A2:E1000"), (INDIRECT("'"&D$62&"'!B2:B1000")=$B58) * (INDIRECT("'"&D$62&"'!C2:C1000")=$C58) ), 5, FALSE ) )} | E58: {=IF( VLOOKUP( $A58, _xlfn._xlws.FILTER( INDIRECT("'"&E$62&"'!A2:E1000"), (INDIRECT("'"&E$62&"'!B2:B1000")=$B58) * (INDIRECT("'"&E$62&"'!C2:C1000")=$C58) ), 5, FALSE )=0, "", VLOOKUP( $A58, _xlfn._xlws.FILTER( INDIRECT("'"&E$62&"'!A2:E1000"), (INDIRECT("'"&E$62&"'!B2:B1000")=$B58) * (INDIRECT("'"&E$62&"'!C2:C1000")=$C58) ), 5, FALSE ) )} | F58: {=IF( VLOOKUP( $A58, _xlfn._xlws.FILTER( INDIRECT("'"&F$62&"'!A2:E1000"), (INDIRECT("'"&F$62&"'!B2:B1000")=$B58) * (INDIRECT("'"&F$62&"'!C2:C1000")=$C58) ), 5, FALSE )=0, "", VLOOKUP( $A58, _xlfn._xlws.FILTER( INDIRECT("'"&F$62&"'!A2:E1000"), (INDIRECT("'"&F$62&"'!B2:B1000")=$B58) * (INDIRECT("'"&F$62&"'!C2:C1000")=$C58) ), 5, FALSE ) )} | G58: {=IF( VLOOKUP( $A58, _xlfn._xlws.FILTER( INDIRECT("'"&G$62&"'!A2:E1000"), (INDIRECT("'"&G$62&"'!B2:B1000")=$B58) * (INDIRECT("'"&G$62&"'!C2:C1000")=$C58) ), 5, FALSE )=0, "", VLOOKUP( $A58, _xlfn._xlws.FILTER( INDIRECT("'"&G$62&"'!A2:E1000"), (INDIRECT("'"&G$62&"'!B2:B1000")=$B58) * (INDIRECT("'"&G$62&"'!C2:C1000")=$C58) ), 5, FALSE ) )} | H58: {=IF( VLOOKUP( $A58, _xlfn._xlws.FILTER( INDIRECT("'"&H$62&"'!A2:E1000"), (INDIRECT("'"&H$62&"'!B2:B1000")=$B58) * (INDIRECT("'"&H$62&"'!C2:C1000")=$C58) ), 5, FALSE )=0, "", VLOOKUP( $A58, _xlfn._xlws.FILTER( INDIRECT("'"&H$62&"'!A2:E1000"), (INDIRECT("'"&H$62&"'!B2:B1000")=$B58) * (INDIRECT("'"&H$62&"'!C2:C1000")=$C58) ), 5, FALSE ) )} | I58: {=IF( VLOOKUP( $A58, _xlfn._xlws.FILTER( INDIRECT("'"&I$62&"'!A2:E1000"), (INDIRECT("'"&I$62&"'!B2:B1000")=$B58) * (INDIRECT("'"&I$62&"'!C2:C1000")=$C58) ), 5, FALSE )=0, "", VLOOKUP( $A58, _xlfn._xlws.FILTER( INDIRECT("'"&I$62&"'!A2:E1000"), (INDIRECT("'"&I$62&"'!B2:B1000")=$B58) * (INDIRECT("'"&I$62&"'!C2:C1000")=$C58) ), 5, FALSE ) )} | J58: {=IF( VLOOKUP( $A58, _xlfn._xlws.FILTER( INDIRECT("'"&J$62&"'!A2:E1000"), (INDIRECT("'"&J$62&"'!B2:B1000")=$B58) * (INDIRECT("'"&J$62&"'!C2:C1000")=$C58) ), 5, FALSE )=0, "", VLOOKUP( $A58, _xlfn._xlws.FILTER( INDIRECT("'"&J$62&"'!A2:E1000"), (INDIRECT("'"&J$62&"'!B2:B1000")=$B58) * (INDIRECT("'"&J$62&"'!C2:C1000")=$C58) ), 5, FALSE ) )} | K58: {=IF( VLOOKUP( $A58, _xlfn._xlws.FILTER( INDIRECT("'"&K$62&"'!A2:E1000"), (INDIRECT("'"&K$62&"'!B2:B1000")=$B58) * (INDIRECT("'"&K$62&"'!C2:C1000")=$C58) ), 5, FALSE )=0, "", VLOOKUP( $A58, _xlfn._xlws.FILTER( INDIRECT("'"&K$62&"'!A2:E1000"), (INDIRECT("'"&K$62&"'!B2:B1000")=$B58) * (INDIRECT("'"&K$62&"'!C2:C1000")=$C58) ), 5, FALSE ) )} | ... O58: {=IF( VLOOKUP( $A58, _xlfn._xlws.FILTER( INDIRECT("'"&O$62&"'!A2:E1000"), (INDIRECT("'"&O$62&"'!B2:B1000")=$B58) * (INDIRECT("'"&O$62&"'!C2:C1000")=$C58) ), 5, FALSE )=0, "", VLOOKUP( $A58, _xlfn._xlws.FILTER( INDIRECT("'"&O$62&"'!A2:E1000"), (INDIRECT("'"&O$62&"'!B2:B1000")=$B58) * (INDIRECT("'"&O$62&"'!C2:C1000")=$C58) ), 5, FALSE ) )}
A59: Maringá | B59: Presidente Castelo Branco | C59: 01 | D59: {=IF( VLOOKUP( $A59, _xlfn._xlws.FILTER( INDIRECT("'"&D$62&"'!A2:E1000"), (INDIRECT("'"&D$62&"'!B2:B1000")=$B59) * (INDIRECT("'"&D$62&"'!C2:C1000")=$C59) ), 5, FALSE )=0, "", VLOOKUP( $A59, _xlfn._xlws.FILTER( INDIRECT("'"&D$62&"'!A2:E1000"), (INDIRECT("'"&D$62&"'!B2:B1000")=$B59) * (INDIRECT("'"&D$62&"'!C2:C1000")=$C59) ), 5, FALSE ) )} | E59: {=IF( VLOOKUP( $A59, _xlfn._xlws.FILTER( INDIRECT("'"&E$62&"'!A2:E1000"), (INDIRECT("'"&E$62&"'!B2:B1000")=$B59) * (INDIRECT("'"&E$62&"'!C2:C1000")=$C59) ), 5, FALSE )=0, "", VLOOKUP( $A59, _xlfn._xlws.FILTER( INDIRECT("'"&E$62&"'!A2:E1000"), (INDIRECT("'"&E$62&"'!B2:B1000")=$B59) * (INDIRECT("'"&E$62&"'!C2:C1000")=$C59) ), 5, FALSE ) )} | F59: {=IF( VLOOKUP( $A59, _xlfn._xlws.FILTER( INDIRECT("'"&F$62&"'!A2:E1000"), (INDIRECT("'"&F$62&"'!B2:B1000")=$B59) * (INDIRECT("'"&F$62&"'!C2:C1000")=$C59) ), 5, FALSE )=0, "", VLOOKUP( $A59, _xlfn._xlws.FILTER( INDIRECT("'"&F$62&"'!A2:E1000"), (INDIRECT("'"&F$62&"'!B2:B1000")=$B59) * (INDIRECT("'"&F$62&"'!C2:C1000")=$C59) ), 5, FALSE ) )} | G59: {=IF( VLOOKUP( $A59, _xlfn._xlws.FILTER( INDIRECT("'"&G$62&"'!A2:E1000"), (INDIRECT("'"&G$62&"'!B2:B1000")=$B59) * (INDIRECT("'"&G$62&"'!C2:C1000")=$C59) ), 5, FALSE )=0, "", VLOOKUP( $A59, _xlfn._xlws.FILTER( INDIRECT("'"&G$62&"'!A2:E1000"), (INDIRECT("'"&G$62&"'!B2:B1000")=$B59) * (INDIRECT("'"&G$62&"'!C2:C1000")=$C59) ), 5, FALSE ) )} | H59: {=IF( VLOOKUP( $A59, _xlfn._xlws.FILTER( INDIRECT("'"&H$62&"'!A2:E1000"), (INDIRECT("'"&H$62&"'!B2:B1000")=$B59) * (INDIRECT("'"&H$62&"'!C2:C1000")=$C59) ), 5, FALSE )=0, "", VLOOKUP( $A59, _xlfn._xlws.FILTER( INDIRECT("'"&H$62&"'!A2:E1000"), (INDIRECT("'"&H$62&"'!B2:B1000")=$B59) * (INDIRECT("'"&H$62&"'!C2:C1000")=$C59) ), 5, FALSE ) )} | I59: {=IF( VLOOKUP( $A59, _xlfn._xlws.FILTER( INDIRECT("'"&I$62&"'!A2:E1000"), (INDIRECT("'"&I$62&"'!B2:B1000")=$B59) * (INDIRECT("'"&I$62&"'!C2:C1000")=$C59) ), 5, FALSE )=0, "", VLOOKUP( $A59, _xlfn._xlws.FILTER( INDIRECT("'"&I$62&"'!A2:E1000"), (INDIRECT("'"&I$62&"'!B2:B1000")=$B59) * (INDIRECT("'"&I$62&"'!C2:C1000")=$C59) ), 5, FALSE ) )} | J59: {=IF( VLOOKUP( $A59, _xlfn._xlws.FILTER( INDIRECT("'"&J$62&"'!A2:E1000"), (INDIRECT("'"&J$62&"'!B2:B1000")=$B59) * (INDIRECT("'"&J$62&"'!C2:C1000")=$C59) ), 5, FALSE )=0, "", VLOOKUP( $A59, _xlfn._xlws.FILTER( INDIRECT("'"&J$62&"'!A2:E1000"), (INDIRECT("'"&J$62&"'!B2:B1000")=$B59) * (INDIRECT("'"&J$62&"'!C2:C1000")=$C59) ), 5, FALSE ) )} | K59: {=IF( VLOOKUP( $A59, _xlfn._xlws.FILTER( INDIRECT("'"&K$62&"'!A2:E1000"), (INDIRECT("'"&K$62&"'!B2:B1000")=$B59) * (INDIRECT("'"&K$62&"'!C2:C1000")=$C59) ), 5, FALSE )=0, "", VLOOKUP( $A59, _xlfn._xlws.FILTER( INDIRECT("'"&K$62&"'!A2:E1000"), (INDIRECT("'"&K$62&"'!B2:B1000")=$B59) * (INDIRECT("'"&K$62&"'!C2:C1000")=$C59) ), 5, FALSE ) )} | ... O59: {=IF( VLOOKUP( $A59, _xlfn._xlws.FILTER( INDIRECT("'"&O$62&"'!A2:E1000"), (INDIRECT("'"&O$62&"'!B2:B1000")=$B59) * (INDIRECT("'"&O$62&"'!C2:C1000")=$C59) ), 5, FALSE )=0, "", VLOOKUP( $A59, _xlfn._xlws.FILTER( INDIRECT("'"&O$62&"'!A2:E1000"), (INDIRECT("'"&O$62&"'!B2:B1000")=$B59) * (INDIRECT("'"&O$62&"'!C2:C1000")=$C59) ), 5, FALSE ) )}
A60: Maringá | B60: São João Do Ivaí | C60: 01 | D60: {=IF( VLOOKUP( $A60, _xlfn._xlws.FILTER( INDIRECT("'"&D$62&"'!A2:E1000"), (INDIRECT("'"&D$62&"'!B2:B1000")=$B60) * (INDIRECT("'"&D$62&"'!C2:C1000")=$C60) ), 5, FALSE )=0, "", VLOOKUP( $A60, _xlfn._xlws.FILTER( INDIRECT("'"&D$62&"'!A2:E1000"), (INDIRECT("'"&D$62&"'!B2:B1000")=$B60) * (INDIRECT("'"&D$62&"'!C2:C1000")=$C60) ), 5, FALSE ) )} | E60: {=IF( VLOOKUP( $A60, _xlfn._xlws.FILTER( INDIRECT("'"&E$62&"'!A2:E1000"), (INDIRECT("'"&E$62&"'!B2:B1000")=$B60) * (INDIRECT("'"&E$62&"'!C2:C1000")=$C60) ), 5, FALSE )=0, "", VLOOKUP( $A60, _xlfn._xlws.FILTER( INDIRECT("'"&E$62&"'!A2:E1000"), (INDIRECT("'"&E$62&"'!B2:B1000")=$B60) * (INDIRECT("'"&E$62&"'!C2:C1000")=$C60) ), 5, FALSE ) )} | F60: {=IF( VLOOKUP( $A60, _xlfn._xlws.FILTER( INDIRECT("'"&F$62&"'!A2:E1000"), (INDIRECT("'"&F$62&"'!B2:B1000")=$B60) * (INDIRECT("'"&F$62&"'!C2:C1000")=$C60) ), 5, FALSE )=0, "", VLOOKUP( $A60, _xlfn._xlws.FILTER( INDIRECT("'"&F$62&"'!A2:E1000"), (INDIRECT("'"&F$62&"'!B2:B1000")=$B60) * (INDIRECT("'"&F$62&"'!C2:C1000")=$C60) ), 5, FALSE ) )} | G60: {=IF( VLOOKUP( $A60, _xlfn._xlws.FILTER( INDIRECT("'"&G$62&"'!A2:E1000"), (INDIRECT("'"&G$62&"'!B2:B1000")=$B60) * (INDIRECT("'"&G$62&"'!C2:C1000")=$C60) ), 5, FALSE )=0, "", VLOOKUP( $A60, _xlfn._xlws.FILTER( INDIRECT("'"&G$62&"'!A2:E1000"), (INDIRECT("'"&G$62&"'!B2:B1000")=$B60) * (INDIRECT("'"&G$62&"'!C2:C1000")=$C60) ), 5, FALSE ) )} | H60: {=IF( VLOOKUP( $A60, _xlfn._xlws.FILTER( INDIRECT("'"&H$62&"'!A2:E1000"), (INDIRECT("'"&H$62&"'!B2:B1000")=$B60) * (INDIRECT("'"&H$62&"'!C2:C1000")=$C60) ), 5, FALSE )=0, "", VLOOKUP( $A60, _xlfn._xlws.FILTER( INDIRECT("'"&H$62&"'!A2:E1000"), (INDIRECT("'"&H$62&"'!B2:B1000")=$B60) * (INDIRECT("'"&H$62&"'!C2:C1000")=$C60) ), 5, FALSE ) )} | I60: {=IF( VLOOKUP( $A60, _xlfn._xlws.FILTER( INDIRECT("'"&I$62&"'!A2:E1000"), (INDIRECT("'"&I$62&"'!B2:B1000")=$B60) * (INDIRECT("'"&I$62&"'!C2:C1000")=$C60) ), 5, FALSE )=0, "", VLOOKUP( $A60, _xlfn._xlws.FILTER( INDIRECT("'"&I$62&"'!A2:E1000"), (INDIRECT("'"&I$62&"'!B2:B1000")=$B60) * (INDIRECT("'"&I$62&"'!C2:C1000")=$C60) ), 5, FALSE ) )} | J60: {=IF( VLOOKUP( $A60, _xlfn._xlws.FILTER( INDIRECT("'"&J$62&"'!A2:E1000"), (INDIRECT("'"&J$62&"'!B2:B1000")=$B60) * (INDIRECT("'"&J$62&"'!C2:C1000")=$C60) ), 5, FALSE )=0, "", VLOOKUP( $A60, _xlfn._xlws.FILTER( INDIRECT("'"&J$62&"'!A2:E1000"), (INDIRECT("'"&J$62&"'!B2:B1000")=$B60) * (INDIRECT("'"&J$62&"'!C2:C1000")=$C60) ), 5, FALSE ) )} | K60: {=IF( VLOOKUP( $A60, _xlfn._xlws.FILTER( INDIRECT("'"&K$62&"'!A2:E1000"), (INDIRECT("'"&K$62&"'!B2:B1000")=$B60) * (INDIRECT("'"&K$62&"'!C2:C1000")=$C60) ), 5, FALSE )=0, "", VLOOKUP( $A60, _xlfn._xlws.FILTER( INDIRECT("'"&K$62&"'!A2:E1000"), (INDIRECT("'"&K$62&"'!B2:B1000")=$B60) * (INDIRECT("'"&K$62&"'!C2:C1000")=$C60) ), 5, FALSE ) )} | ... O60: {=IF( VLOOKUP( $A60, _xlfn._xlws.FILTER( INDIRECT("'"&O$62&"'!A2:E1000"), (INDIRECT("'"&O$62&"'!B2:B1000")=$B60) * (INDIRECT("'"&O$62&"'!C2:C1000")=$C60) ), 5, FALSE )=0, "", VLOOKUP( $A60, _xlfn._xlws.FILTER( INDIRECT("'"&O$62&"'!A2:E1000"), (INDIRECT("'"&O$62&"'!B2:B1000")=$B60) * (INDIRECT("'"&O$62&"'!C2:C1000")=$C60) ), 5, FALSE ) )}
A62: Mário | B62: Municípios | C62: UVR | D62: 01.25 | E62: 02.25 | F62: 03.25 | G62: 04.25 | H62: 05.25 | I62: 06.25 | J62: 07.25 | K62: 08.25 | L62: 09.25 | M62: 10.25 | N62: 11.25 | O62: 12.25
A63: Paranavaí | B63: Alto Paraná | C63: 01 | D63: {=IF( VLOOKUP( $A63, _xlfn._xlws.FILTER( INDIRECT("'"&D$62&"'!A2:E1000"), (INDIRECT("'"&D$62&"'!B2:B1000")=$B63) * (INDIRECT("'"&D$62&"'!C2:C1000")=$C63) ), 5, FALSE )=0, "", VLOOKUP( $A63, _xlfn._xlws.FILTER( INDIRECT("'"&D$62&"'!A2:E1000"), (INDIRECT("'"&D$62&"'!B2:B1000")=$B63) * (INDIRECT("'"&D$62&"'!C2:C1000")=$C63) ), 5, FALSE ) )} | E63: {=IF( VLOOKUP( $A63, _xlfn._xlws.FILTER( INDIRECT("'"&E$62&"'!A2:E1000"), (INDIRECT("'"&E$62&"'!B2:B1000")=$B63) * (INDIRECT("'"&E$62&"'!C2:C1000")=$C63) ), 5, FALSE )=0, "", VLOOKUP( $A63, _xlfn._xlws.FILTER( INDIRECT("'"&E$62&"'!A2:E1000"), (INDIRECT("'"&E$62&"'!B2:B1000")=$B63) * (INDIRECT("'"&E$62&"'!C2:C1000")=$C63) ), 5, FALSE ) )} | F63: {=IF( VLOOKUP( $A63, _xlfn._xlws.FILTER( INDIRECT("'"&F$62&"'!A2:E1000"), (INDIRECT("'"&F$62&"'!B2:B1000")=$B63) * (INDIRECT("'"&F$62&"'!C2:C1000")=$C63) ), 5, FALSE )=0, "", VLOOKUP( $A63, _xlfn._xlws.FILTER( INDIRECT("'"&F$62&"'!A2:E1000"), (INDIRECT("'"&F$62&"'!B2:B1000")=$B63) * (INDIRECT("'"&F$62&"'!C2:C1000")=$C63) ), 5, FALSE ) )} | G63: {=IF( VLOOKUP( $A63, _xlfn._xlws.FILTER( INDIRECT("'"&G$62&"'!A2:E1000"), (INDIRECT("'"&G$62&"'!B2:B1000")=$B63) * (INDIRECT("'"&G$62&"'!C2:C1000")=$C63) ), 5, FALSE )=0, "", VLOOKUP( $A63, _xlfn._xlws.FILTER( INDIRECT("'"&G$62&"'!A2:E1000"), (INDIRECT("'"&G$62&"'!B2:B1000")=$B63) * (INDIRECT("'"&G$62&"'!C2:C1000")=$C63) ), 5, FALSE ) )} | H63: {=IF( VLOOKUP( $A63, _xlfn._xlws.FILTER( INDIRECT("'"&H$62&"'!A2:E1000"), (INDIRECT("'"&H$62&"'!B2:B1000")=$B63) * (INDIRECT("'"&H$62&"'!C2:C1000")=$C63) ), 5, FALSE )=0, "", VLOOKUP( $A63, _xlfn._xlws.FILTER( INDIRECT("'"&H$62&"'!A2:E1000"), (INDIRECT("'"&H$62&"'!B2:B1000")=$B63) * (INDIRECT("'"&H$62&"'!C2:C1000")=$C63) ), 5, FALSE ) )} | I63: {=IF( VLOOKUP( $A63, _xlfn._xlws.FILTER( INDIRECT("'"&I$62&"'!A2:E1000"), (INDIRECT("'"&I$62&"'!B2:B1000")=$B63) * (INDIRECT("'"&I$62&"'!C2:C1000")=$C63) ), 5, FALSE )=0, "", VLOOKUP( $A63, _xlfn._xlws.FILTER( INDIRECT("'"&I$62&"'!A2:E1000"), (INDIRECT("'"&I$62&"'!B2:B1000")=$B63) * (INDIRECT("'"&I$62&"'!C2:C1000")=$C63) ), 5, FALSE ) )} | J63: {=IF( VLOOKUP( $A63, _xlfn._xlws.FILTER( INDIRECT("'"&J$62&"'!A2:E1000"), (INDIRECT("'"&J$62&"'!B2:B1000")=$B63) * (INDIRECT("'"&J$62&"'!C2:C1000")=$C63) ), 5, FALSE )=0, "", VLOOKUP( $A63, _xlfn._xlws.FILTER( INDIRECT("'"&J$62&"'!A2:E1000"), (INDIRECT("'"&J$62&"'!B2:B1000")=$B63) * (INDIRECT("'"&J$62&"'!C2:C1000")=$C63) ), 5, FALSE ) )} | K63: {=IF( VLOOKUP( $A63, _xlfn._xlws.FILTER( INDIRECT("'"&K$62&"'!A2:E1000"), (INDIRECT("'"&K$62&"'!B2:B1000")=$B63) * (INDIRECT("'"&K$62&"'!C2:C1000")=$C63) ), 5, FALSE )=0, "", VLOOKUP( $A63, _xlfn._xlws.FILTER( INDIRECT("'"&K$62&"'!A2:E1000"), (INDIRECT("'"&K$62&"'!B2:B1000")=$B63) * (INDIRECT("'"&K$62&"'!C2:C1000")=$C63) ), 5, FALSE ) )} | ... O63: {=IF( VLOOKUP( $A63, _xlfn._xlws.FILTER( INDIRECT("'"&O$62&"'!A2:E1000"), (INDIRECT("'"&O$62&"'!B2:B1000")=$B63) * (INDIRECT("'"&O$62&"'!C2:C1000")=$C63) ), 5, FALSE )=0, "", VLOOKUP( $A63, _xlfn._xlws.FILTER( INDIRECT("'"&O$62&"'!A2:E1000"), (INDIRECT("'"&O$62&"'!B2:B1000")=$B63) * (INDIRECT("'"&O$62&"'!C2:C1000")=$C63) ), 5, FALSE ) )} | R63: Paranavai | S63: Paranavaí
A64: Paranavaí | B64: Amaporã | C64: 01 | D64: {=IF( VLOOKUP( $A64, _xlfn._xlws.FILTER( INDIRECT("'"&D$62&"'!A2:E1000"), (INDIRECT("'"&D$62&"'!B2:B1000")=$B64) * (INDIRECT("'"&D$62&"'!C2:C1000")=$C64) ), 5, FALSE )=0, "", VLOOKUP( $A64, _xlfn._xlws.FILTER( INDIRECT("'"&D$62&"'!A2:E1000"), (INDIRECT("'"&D$62&"'!B2:B1000")=$B64) * (INDIRECT("'"&D$62&"'!C2:C1000")=$C64) ), 5, FALSE ) )} | E64: {=IF( VLOOKUP( $A64, _xlfn._xlws.FILTER( INDIRECT("'"&E$62&"'!A2:E1000"), (INDIRECT("'"&E$62&"'!B2:B1000")=$B64) * (INDIRECT("'"&E$62&"'!C2:C1000")=$C64) ), 5, FALSE )=0, "", VLOOKUP( $A64, _xlfn._xlws.FILTER( INDIRECT("'"&E$62&"'!A2:E1000"), (INDIRECT("'"&E$62&"'!B2:B1000")=$B64) * (INDIRECT("'"&E$62&"'!C2:C1000")=$C64) ), 5, FALSE ) )} | F64: {=IF( VLOOKUP( $A64, _xlfn._xlws.FILTER( INDIRECT("'"&F$62&"'!A2:E1000"), (INDIRECT("'"&F$62&"'!B2:B1000")=$B64) * (INDIRECT("'"&F$62&"'!C2:C1000")=$C64) ), 5, FALSE )=0, "", VLOOKUP( $A64, _xlfn._xlws.FILTER( INDIRECT("'"&F$62&"'!A2:E1000"), (INDIRECT("'"&F$62&"'!B2:B1000")=$B64) * (INDIRECT("'"&F$62&"'!C2:C1000")=$C64) ), 5, FALSE ) )} | G64: {=IF( VLOOKUP( $A64, _xlfn._xlws.FILTER( INDIRECT("'"&G$62&"'!A2:E1000"), (INDIRECT("'"&G$62&"'!B2:B1000")=$B64) * (INDIRECT("'"&G$62&"'!C2:C1000")=$C64) ), 5, FALSE )=0, "", VLOOKUP( $A64, _xlfn._xlws.FILTER( INDIRECT("'"&G$62&"'!A2:E1000"), (INDIRECT("'"&G$62&"'!B2:B1000")=$B64) * (INDIRECT("'"&G$62&"'!C2:C1000")=$C64) ), 5, FALSE ) )} | H64: {=IF( VLOOKUP( $A64, _xlfn._xlws.FILTER( INDIRECT("'"&H$62&"'!A2:E1000"), (INDIRECT("'"&H$62&"'!B2:B1000")=$B64) * (INDIRECT("'"&H$62&"'!C2:C1000")=$C64) ), 5, FALSE )=0, "", VLOOKUP( $A64, _xlfn._xlws.FILTER( INDIRECT("'"&H$62&"'!A2:E1000"), (INDIRECT("'"&H$62&"'!B2:B1000")=$B64) * (INDIRECT("'"&H$62&"'!C2:C1000")=$C64) ), 5, FALSE ) )} | I64: {=IF( VLOOKUP( $A64, _xlfn._xlws.FILTER( INDIRECT("'"&I$62&"'!A2:E1000"), (INDIRECT("'"&I$62&"'!B2:B1000")=$B64) * (INDIRECT("'"&I$62&"'!C2:C1000")=$C64) ), 5, FALSE )=0, "", VLOOKUP( $A64, _xlfn._xlws.FILTER( INDIRECT("'"&I$62&"'!A2:E1000"), (INDIRECT("'"&I$62&"'!B2:B1000")=$B64) * (INDIRECT("'"&I$62&"'!C2:C1000")=$C64) ), 5, FALSE ) )} | J64: {=IF( VLOOKUP( $A64, _xlfn._xlws.FILTER( INDIRECT("'"&J$62&"'!A2:E1000"), (INDIRECT("'"&J$62&"'!B2:B1000")=$B64) * (INDIRECT("'"&J$62&"'!C2:C1000")=$C64) ), 5, FALSE )=0, "", VLOOKUP( $A64, _xlfn._xlws.FILTER( INDIRECT("'"&J$62&"'!A2:E1000"), (INDIRECT("'"&J$62&"'!B2:B1000")=$B64) * (INDIRECT("'"&J$62&"'!C2:C1000")=$C64) ), 5, FALSE ) )} | K64: {=IF( VLOOKUP( $A64, _xlfn._xlws.FILTER( INDIRECT("'"&K$62&"'!A2:E1000"), (INDIRECT("'"&K$62&"'!B2:B1000")=$B64) * (INDIRECT("'"&K$62&"'!C2:C1000")=$C64) ), 5, FALSE )=0, "", VLOOKUP( $A64, _xlfn._xlws.FILTER( INDIRECT("'"&K$62&"'!A2:E1000"), (INDIRECT("'"&K$62&"'!B2:B1000")=$B64) * (INDIRECT("'"&K$62&"'!C2:C1000")=$C64) ), 5, FALSE ) )} | ... O64: {=IF( VLOOKUP( $A64, _xlfn._xlws.FILTER( INDIRECT("'"&O$62&"'!A2:E1000"), (INDIRECT("'"&O$62&"'!B2:B1000")=$B64) * (INDIRECT("'"&O$62&"'!C2:C1000")=$C64) ), 5, FALSE )=0, "", VLOOKUP( $A64, _xlfn._xlws.FILTER( INDIRECT("'"&O$62&"'!A2:E1000"), (INDIRECT("'"&O$62&"'!B2:B1000")=$B64) * (INDIRECT("'"&O$62&"'!C2:C1000")=$C64) ), 5, FALSE ) )} | R64: Curitiba | S64: Curitiba
A65: Paranavaí | B65: Colorado | C65: 01 | D65: {=IF( VLOOKUP( $A65, _xlfn._xlws.FILTER( INDIRECT("'"&D$62&"'!A2:E1000"), (INDIRECT("'"&D$62&"'!B2:B1000")=$B65) * (INDIRECT("'"&D$62&"'!C2:C1000")=$C65) ), 5, FALSE )=0, "", VLOOKUP( $A65, _xlfn._xlws.FILTER( INDIRECT("'"&D$62&"'!A2:E1000"), (INDIRECT("'"&D$62&"'!B2:B1000")=$B65) * (INDIRECT("'"&D$62&"'!C2:C1000")=$C65) ), 5, FALSE ) )} | E65: {=IF( VLOOKUP( $A65, _xlfn._xlws.FILTER( INDIRECT("'"&E$62&"'!A2:E1000"), (INDIRECT("'"&E$62&"'!B2:B1000")=$B65) * (INDIRECT("'"&E$62&"'!C2:C1000")=$C65) ), 5, FALSE )=0, "", VLOOKUP( $A65, _xlfn._xlws.FILTER( INDIRECT("'"&E$62&"'!A2:E1000"), (INDIRECT("'"&E$62&"'!B2:B1000")=$B65) * (INDIRECT("'"&E$62&"'!C2:C1000")=$C65) ), 5, FALSE ) )} | F65: {=IF( VLOOKUP( $A65, _xlfn._xlws.FILTER( INDIRECT("'"&F$62&"'!A2:E1000"), (INDIRECT("'"&F$62&"'!B2:B1000")=$B65) * (INDIRECT("'"&F$62&"'!C2:C1000")=$C65) ), 5, FALSE )=0, "", VLOOKUP( $A65, _xlfn._xlws.FILTER( INDIRECT("'"&F$62&"'!A2:E1000"), (INDIRECT("'"&F$62&"'!B2:B1000")=$B65) * (INDIRECT("'"&F$62&"'!C2:C1000")=$C65) ), 5, FALSE ) )} | G65: {=IF( VLOOKUP( $A65, _xlfn._xlws.FILTER( INDIRECT("'"&G$62&"'!A2:E1000"), (INDIRECT("'"&G$62&"'!B2:B1000")=$B65) * (INDIRECT("'"&G$62&"'!C2:C1000")=$C65) ), 5, FALSE )=0, "", VLOOKUP( $A65, _xlfn._xlws.FILTER( INDIRECT("'"&G$62&"'!A2:E1000"), (INDIRECT("'"&G$62&"'!B2:B1000")=$B65) * (INDIRECT("'"&G$62&"'!C2:C1000")=$C65) ), 5, FALSE ) )} | H65: {=IF( VLOOKUP( $A65, _xlfn._xlws.FILTER( INDIRECT("'"&H$62&"'!A2:E1000"), (INDIRECT("'"&H$62&"'!B2:B1000")=$B65) * (INDIRECT("'"&H$62&"'!C2:C1000")=$C65) ), 5, FALSE )=0, "", VLOOKUP( $A65, _xlfn._xlws.FILTER( INDIRECT("'"&H$62&"'!A2:E1000"), (INDIRECT("'"&H$62&"'!B2:B1000")=$B65) * (INDIRECT("'"&H$62&"'!C2:C1000")=$C65) ), 5, FALSE ) )} | I65: {=IF( VLOOKUP( $A65, _xlfn._xlws.FILTER( INDIRECT("'"&I$62&"'!A2:E1000"), (INDIRECT("'"&I$62&"'!B2:B1000")=$B65) * (INDIRECT("'"&I$62&"'!C2:C1000")=$C65) ), 5, FALSE )=0, "", VLOOKUP( $A65, _xlfn._xlws.FILTER( INDIRECT("'"&I$62&"'!A2:E1000"), (INDIRECT("'"&I$62&"'!B2:B1000")=$B65) * (INDIRECT("'"&I$62&"'!C2:C1000")=$C65) ), 5, FALSE ) )} | J65: {=IF( VLOOKUP( $A65, _xlfn._xlws.FILTER( INDIRECT("'"&J$62&"'!A2:E1000"), (INDIRECT("'"&J$62&"'!B2:B1000")=$B65) * (INDIRECT("'"&J$62&"'!C2:C1000")=$C65) ), 5, FALSE )=0, "", VLOOKUP( $A65, _xlfn._xlws.FILTER( INDIRECT("'"&J$62&"'!A2:E1000"), (INDIRECT("'"&J$62&"'!B2:B1000")=$B65) * (INDIRECT("'"&J$62&"'!C2:C1000")=$C65) ), 5, FALSE ) )} | K65: {=IF( VLOOKUP( $A65, _xlfn._xlws.FILTER( INDIRECT("'"&K$62&"'!A2:E1000"), (INDIRECT("'"&K$62&"'!B2:B1000")=$B65) * (INDIRECT("'"&K$62&"'!C2:C1000")=$C65) ), 5, FALSE )=0, "", VLOOKUP( $A65, _xlfn._xlws.FILTER( INDIRECT("'"&K$62&"'!A2:E1000"), (INDIRECT("'"&K$62&"'!B2:B1000")=$B65) * (INDIRECT("'"&K$62&"'!C2:C1000")=$C65) ), 5, FALSE ) )} | ... O65: {=IF( VLOOKUP( $A65, _xlfn._xlws.FILTER( INDIRECT("'"&O$62&"'!A2:E1000"), (INDIRECT("'"&O$62&"'!B2:B1000")=$B65) * (INDIRECT("'"&O$62&"'!C2:C1000")=$C65) ), 5, FALSE )=0, "", VLOOKUP( $A65, _xlfn._xlws.FILTER( INDIRECT("'"&O$62&"'!A2:E1000"), (INDIRECT("'"&O$62&"'!B2:B1000")=$B65) * (INDIRECT("'"&O$62&"'!C2:C1000")=$C65) ), 5, FALSE ) )} | R65: Francisco Beltrão | S65: Francisco Beltrão
A66: Paranavaí | B66: Cruzeiro Do Sul | C66: 01 | D66: {=IF( VLOOKUP( $A66, _xlfn._xlws.FILTER( INDIRECT("'"&D$62&"'!A2:E1000"), (INDIRECT("'"&D$62&"'!B2:B1000")=$B66) * (INDIRECT("'"&D$62&"'!C2:C1000")=$C66) ), 5, FALSE )=0, "", VLOOKUP( $A66, _xlfn._xlws.FILTER( INDIRECT("'"&D$62&"'!A2:E1000"), (INDIRECT("'"&D$62&"'!B2:B1000")=$B66) * (INDIRECT("'"&D$62&"'!C2:C1000")=$C66) ), 5, FALSE ) )} | E66: {=IF( VLOOKUP( $A66, _xlfn._xlws.FILTER( INDIRECT("'"&E$62&"'!A2:E1000"), (INDIRECT("'"&E$62&"'!B2:B1000")=$B66) * (INDIRECT("'"&E$62&"'!C2:C1000")=$C66) ), 5, FALSE )=0, "", VLOOKUP( $A66, _xlfn._xlws.FILTER( INDIRECT("'"&E$62&"'!A2:E1000"), (INDIRECT("'"&E$62&"'!B2:B1000")=$B66) * (INDIRECT("'"&E$62&"'!C2:C1000")=$C66) ), 5, FALSE ) )} | F66: {=IF( VLOOKUP( $A66, _xlfn._xlws.FILTER( INDIRECT("'"&F$62&"'!A2:E1000"), (INDIRECT("'"&F$62&"'!B2:B1000")=$B66) * (INDIRECT("'"&F$62&"'!C2:C1000")=$C66) ), 5, FALSE )=0, "", VLOOKUP( $A66, _xlfn._xlws.FILTER( INDIRECT("'"&F$62&"'!A2:E1000"), (INDIRECT("'"&F$62&"'!B2:B1000")=$B66) * (INDIRECT("'"&F$62&"'!C2:C1000")=$C66) ), 5, FALSE ) )} | G66: {=IF( VLOOKUP( $A66, _xlfn._xlws.FILTER( INDIRECT("'"&G$62&"'!A2:E1000"), (INDIRECT("'"&G$62&"'!B2:B1000")=$B66) * (INDIRECT("'"&G$62&"'!C2:C1000")=$C66) ), 5, FALSE )=0, "", VLOOKUP( $A66, _xlfn._xlws.FILTER( INDIRECT("'"&G$62&"'!A2:E1000"), (INDIRECT("'"&G$62&"'!B2:B1000")=$B66) * (INDIRECT("'"&G$62&"'!C2:C1000")=$C66) ), 5, FALSE ) )} | H66: {=IF( VLOOKUP( $A66, _xlfn._xlws.FILTER( INDIRECT("'"&H$62&"'!A2:E1000"), (INDIRECT("'"&H$62&"'!B2:B1000")=$B66) * (INDIRECT("'"&H$62&"'!C2:C1000")=$C66) ), 5, FALSE )=0, "", VLOOKUP( $A66, _xlfn._xlws.FILTER( INDIRECT("'"&H$62&"'!A2:E1000"), (INDIRECT("'"&H$62&"'!B2:B1000")=$B66) * (INDIRECT("'"&H$62&"'!C2:C1000")=$C66) ), 5, FALSE ) )} | I66: {=IF( VLOOKUP( $A66, _xlfn._xlws.FILTER( INDIRECT("'"&I$62&"'!A2:E1000"), (INDIRECT("'"&I$62&"'!B2:B1000")=$B66) * (INDIRECT("'"&I$62&"'!C2:C1000")=$C66) ), 5, FALSE )=0, "", VLOOKUP( $A66, _xlfn._xlws.FILTER( INDIRECT("'"&I$62&"'!A2:E1000"), (INDIRECT("'"&I$62&"'!B2:B1000")=$B66) * (INDIRECT("'"&I$62&"'!C2:C1000")=$C66) ), 5, FALSE ) )} | J66: {=IF( VLOOKUP( $A66, _xlfn._xlws.FILTER( INDIRECT("'"&J$62&"'!A2:E1000"), (INDIRECT("'"&J$62&"'!B2:B1000")=$B66) * (INDIRECT("'"&J$62&"'!C2:C1000")=$C66) ), 5, FALSE )=0, "", VLOOKUP( $A66, _xlfn._xlws.FILTER( INDIRECT("'"&J$62&"'!A2:E1000"), (INDIRECT("'"&J$62&"'!B2:B1000")=$B66) * (INDIRECT("'"&J$62&"'!C2:C1000")=$C66) ), 5, FALSE ) )} | K66: {=IF( VLOOKUP( $A66, _xlfn._xlws.FILTER( INDIRECT("'"&K$62&"'!A2:E1000"), (INDIRECT("'"&K$62&"'!B2:B1000")=$B66) * (INDIRECT("'"&K$62&"'!C2:C1000")=$C66) ), 5, FALSE )=0, "", VLOOKUP( $A66, _xlfn._xlws.FILTER( INDIRECT("'"&K$62&"'!A2:E1000"), (INDIRECT("'"&K$62&"'!B2:B1000")=$B66) * (INDIRECT("'"&K$62&"'!C2:C1000")=$C66) ), 5, FALSE ) )} | ... O66: {=IF( VLOOKUP( $A66, _xlfn._xlws.FILTER( INDIRECT("'"&O$62&"'!A2:E1000"), (INDIRECT("'"&O$62&"'!B2:B1000")=$B66) * (INDIRECT("'"&O$62&"'!C2:C1000")=$C66) ), 5, FALSE )=0, "", VLOOKUP( $A66, _xlfn._xlws.FILTER( INDIRECT("'"&O$62&"'!A2:E1000"), (INDIRECT("'"&O$62&"'!B2:B1000")=$B66) * (INDIRECT("'"&O$62&"'!C2:C1000")=$C66) ), 5, FALSE ) )} | R66: Guarapuava | S66: Guarapuava
A67: Paranavaí | B67: Mandaguaçu | C67: 01 | D67: {=IF( VLOOKUP( $A67, _xlfn._xlws.FILTER( INDIRECT("'"&D$62&"'!A2:E1000"), (INDIRECT("'"&D$62&"'!B2:B1000")=$B67) * (INDIRECT("'"&D$62&"'!C2:C1000")=$C67) ), 5, FALSE )=0, "", VLOOKUP( $A67, _xlfn._xlws.FILTER( INDIRECT("'"&D$62&"'!A2:E1000"), (INDIRECT("'"&D$62&"'!B2:B1000")=$B67) * (INDIRECT("'"&D$62&"'!C2:C1000")=$C67) ), 5, FALSE ) )} | E67: {=IF( VLOOKUP( $A67, _xlfn._xlws.FILTER( INDIRECT("'"&E$62&"'!A2:E1000"), (INDIRECT("'"&E$62&"'!B2:B1000")=$B67) * (INDIRECT("'"&E$62&"'!C2:C1000")=$C67) ), 5, FALSE )=0, "", VLOOKUP( $A67, _xlfn._xlws.FILTER( INDIRECT("'"&E$62&"'!A2:E1000"), (INDIRECT("'"&E$62&"'!B2:B1000")=$B67) * (INDIRECT("'"&E$62&"'!C2:C1000")=$C67) ), 5, FALSE ) )} | F67: {=IF( VLOOKUP( $A67, _xlfn._xlws.FILTER( INDIRECT("'"&F$62&"'!A2:E1000"), (INDIRECT("'"&F$62&"'!B2:B1000")=$B67) * (INDIRECT("'"&F$62&"'!C2:C1000")=$C67) ), 5, FALSE )=0, "", VLOOKUP( $A67, _xlfn._xlws.FILTER( INDIRECT("'"&F$62&"'!A2:E1000"), (INDIRECT("'"&F$62&"'!B2:B1000")=$B67) * (INDIRECT("'"&F$62&"'!C2:C1000")=$C67) ), 5, FALSE ) )} | G67: {=IF( VLOOKUP( $A67, _xlfn._xlws.FILTER( INDIRECT("'"&G$62&"'!A2:E1000"), (INDIRECT("'"&G$62&"'!B2:B1000")=$B67) * (INDIRECT("'"&G$62&"'!C2:C1000")=$C67) ), 5, FALSE )=0, "", VLOOKUP( $A67, _xlfn._xlws.FILTER( INDIRECT("'"&G$62&"'!A2:E1000"), (INDIRECT("'"&G$62&"'!B2:B1000")=$B67) * (INDIRECT("'"&G$62&"'!C2:C1000")=$C67) ), 5, FALSE ) )} | H67: {=IF( VLOOKUP( $A67, _xlfn._xlws.FILTER( INDIRECT("'"&H$62&"'!A2:E1000"), (INDIRECT("'"&H$62&"'!B2:B1000")=$B67) * (INDIRECT("'"&H$62&"'!C2:C1000")=$C67) ), 5, FALSE )=0, "", VLOOKUP( $A67, _xlfn._xlws.FILTER( INDIRECT("'"&H$62&"'!A2:E1000"), (INDIRECT("'"&H$62&"'!B2:B1000")=$B67) * (INDIRECT("'"&H$62&"'!C2:C1000")=$C67) ), 5, FALSE ) )} | I67: {=IF( VLOOKUP( $A67, _xlfn._xlws.FILTER( INDIRECT("'"&I$62&"'!A2:E1000"), (INDIRECT("'"&I$62&"'!B2:B1000")=$B67) * (INDIRECT("'"&I$62&"'!C2:C1000")=$C67) ), 5, FALSE )=0, "", VLOOKUP( $A67, _xlfn._xlws.FILTER( INDIRECT("'"&I$62&"'!A2:E1000"), (INDIRECT("'"&I$62&"'!B2:B1000")=$B67) * (INDIRECT("'"&I$62&"'!C2:C1000")=$C67) ), 5, FALSE ) )} | J67: {=IF( VLOOKUP( $A67, _xlfn._xlws.FILTER( INDIRECT("'"&J$62&"'!A2:E1000"), (INDIRECT("'"&J$62&"'!B2:B1000")=$B67) * (INDIRECT("'"&J$62&"'!C2:C1000")=$C67) ), 5, FALSE )=0, "", VLOOKUP( $A67, _xlfn._xlws.FILTER( INDIRECT("'"&J$62&"'!A2:E1000"), (INDIRECT("'"&J$62&"'!B2:B1000")=$B67) * (INDIRECT("'"&J$62&"'!C2:C1000")=$C67) ), 5, FALSE ) )} | K67: {=IF( VLOOKUP( $A67, _xlfn._xlws.FILTER( INDIRECT("'"&K$62&"'!A2:E1000"), (INDIRECT("'"&K$62&"'!B2:B1000")=$B67) * (INDIRECT("'"&K$62&"'!C2:C1000")=$C67) ), 5, FALSE )=0, "", VLOOKUP( $A67, _xlfn._xlws.FILTER( INDIRECT("'"&K$62&"'!A2:E1000"), (INDIRECT("'"&K$62&"'!B2:B1000")=$B67) * (INDIRECT("'"&K$62&"'!C2:C1000")=$C67) ), 5, FALSE ) )} | ... O67: {=IF( VLOOKUP( $A67, _xlfn._xlws.FILTER( INDIRECT("'"&O$62&"'!A2:E1000"), (INDIRECT("'"&O$62&"'!B2:B1000")=$B67) * (INDIRECT("'"&O$62&"'!C2:C1000")=$C67) ), 5, FALSE )=0, "", VLOOKUP( $A67, _xlfn._xlws.FILTER( INDIRECT("'"&O$62&"'!A2:E1000"), (INDIRECT("'"&O$62&"'!B2:B1000")=$B67) * (INDIRECT("'"&O$62&"'!C2:C1000")=$C67) ), 5, FALSE ) )} | R67: Londrina | S67: Londrina
A68: Paranavaí | B68: Paraíso Do Norte | C68: 01 | D68: {=IF( VLOOKUP( $A68, _xlfn._xlws.FILTER( INDIRECT("'"&D$62&"'!A2:E1000"), (INDIRECT("'"&D$62&"'!B2:B1000")=$B68) * (INDIRECT("'"&D$62&"'!C2:C1000")=$C68) ), 5, FALSE )=0, "", VLOOKUP( $A68, _xlfn._xlws.FILTER( INDIRECT("'"&D$62&"'!A2:E1000"), (INDIRECT("'"&D$62&"'!B2:B1000")=$B68) * (INDIRECT("'"&D$62&"'!C2:C1000")=$C68) ), 5, FALSE ) )} | E68: {=IF( VLOOKUP( $A68, _xlfn._xlws.FILTER( INDIRECT("'"&E$62&"'!A2:E1000"), (INDIRECT("'"&E$62&"'!B2:B1000")=$B68) * (INDIRECT("'"&E$62&"'!C2:C1000")=$C68) ), 5, FALSE )=0, "", VLOOKUP( $A68, _xlfn._xlws.FILTER( INDIRECT("'"&E$62&"'!A2:E1000"), (INDIRECT("'"&E$62&"'!B2:B1000")=$B68) * (INDIRECT("'"&E$62&"'!C2:C1000")=$C68) ), 5, FALSE ) )} | F68: {=IF( VLOOKUP( $A68, _xlfn._xlws.FILTER( INDIRECT("'"&F$62&"'!A2:E1000"), (INDIRECT("'"&F$62&"'!B2:B1000")=$B68) * (INDIRECT("'"&F$62&"'!C2:C1000")=$C68) ), 5, FALSE )=0, "", VLOOKUP( $A68, _xlfn._xlws.FILTER( INDIRECT("'"&F$62&"'!A2:E1000"), (INDIRECT("'"&F$62&"'!B2:B1000")=$B68) * (INDIRECT("'"&F$62&"'!C2:C1000")=$C68) ), 5, FALSE ) )} | G68: {=IF( VLOOKUP( $A68, _xlfn._xlws.FILTER( INDIRECT("'"&G$62&"'!A2:E1000"), (INDIRECT("'"&G$62&"'!B2:B1000")=$B68) * (INDIRECT("'"&G$62&"'!C2:C1000")=$C68) ), 5, FALSE )=0, "", VLOOKUP( $A68, _xlfn._xlws.FILTER( INDIRECT("'"&G$62&"'!A2:E1000"), (INDIRECT("'"&G$62&"'!B2:B1000")=$B68) * (INDIRECT("'"&G$62&"'!C2:C1000")=$C68) ), 5, FALSE ) )} | H68: {=IF( VLOOKUP( $A68, _xlfn._xlws.FILTER( INDIRECT("'"&H$62&"'!A2:E1000"), (INDIRECT("'"&H$62&"'!B2:B1000")=$B68) * (INDIRECT("'"&H$62&"'!C2:C1000")=$C68) ), 5, FALSE )=0, "", VLOOKUP( $A68, _xlfn._xlws.FILTER( INDIRECT("'"&H$62&"'!A2:E1000"), (INDIRECT("'"&H$62&"'!B2:B1000")=$B68) * (INDIRECT("'"&H$62&"'!C2:C1000")=$C68) ), 5, FALSE ) )} | I68: {=IF( VLOOKUP( $A68, _xlfn._xlws.FILTER( INDIRECT("'"&I$62&"'!A2:E1000"), (INDIRECT("'"&I$62&"'!B2:B1000")=$B68) * (INDIRECT("'"&I$62&"'!C2:C1000")=$C68) ), 5, FALSE )=0, "", VLOOKUP( $A68, _xlfn._xlws.FILTER( INDIRECT("'"&I$62&"'!A2:E1000"), (INDIRECT("'"&I$62&"'!B2:B1000")=$B68) * (INDIRECT("'"&I$62&"'!C2:C1000")=$C68) ), 5, FALSE ) )} | J68: {=IF( VLOOKUP( $A68, _xlfn._xlws.FILTER( INDIRECT("'"&J$62&"'!A2:E1000"), (INDIRECT("'"&J$62&"'!B2:B1000")=$B68) * (INDIRECT("'"&J$62&"'!C2:C1000")=$C68) ), 5, FALSE )=0, "", VLOOKUP( $A68, _xlfn._xlws.FILTER( INDIRECT("'"&J$62&"'!A2:E1000"), (INDIRECT("'"&J$62&"'!B2:B1000")=$B68) * (INDIRECT("'"&J$62&"'!C2:C1000")=$C68) ), 5, FALSE ) )} | K68: {=IF( VLOOKUP( $A68, _xlfn._xlws.FILTER( INDIRECT("'"&K$62&"'!A2:E1000"), (INDIRECT("'"&K$62&"'!B2:B1000")=$B68) * (INDIRECT("'"&K$62&"'!C2:C1000")=$C68) ), 5, FALSE )=0, "", VLOOKUP( $A68, _xlfn._xlws.FILTER( INDIRECT("'"&K$62&"'!A2:E1000"), (INDIRECT("'"&K$62&"'!B2:B1000")=$B68) * (INDIRECT("'"&K$62&"'!C2:C1000")=$C68) ), 5, FALSE ) )} | ... O68: {=IF( VLOOKUP( $A68, _xlfn._xlws.FILTER( INDIRECT("'"&O$62&"'!A2:E1000"), (INDIRECT("'"&O$62&"'!B2:B1000")=$B68) * (INDIRECT("'"&O$62&"'!C2:C1000")=$C68) ), 5, FALSE )=0, "", VLOOKUP( $A68, _xlfn._xlws.FILTER( INDIRECT("'"&O$62&"'!A2:E1000"), (INDIRECT("'"&O$62&"'!B2:B1000")=$B68) * (INDIRECT("'"&O$62&"'!C2:C1000")=$C68) ), 5, FALSE ) )} | R68: Maringá | S68: Maringá
A69: Paranavaí | B69: Santa Mônica | C69: 01 | D69: {=IF( VLOOKUP( $A69, _xlfn._xlws.FILTER( INDIRECT("'"&D$62&"'!A2:E1000"), (INDIRECT("'"&D$62&"'!B2:B1000")=$B69) * (INDIRECT("'"&D$62&"'!C2:C1000")=$C69) ), 5, FALSE )=0, "", VLOOKUP( $A69, _xlfn._xlws.FILTER( INDIRECT("'"&D$62&"'!A2:E1000"), (INDIRECT("'"&D$62&"'!B2:B1000")=$B69) * (INDIRECT("'"&D$62&"'!C2:C1000")=$C69) ), 5, FALSE ) )} | E69: {=IF( VLOOKUP( $A69, _xlfn._xlws.FILTER( INDIRECT("'"&E$62&"'!A2:E1000"), (INDIRECT("'"&E$62&"'!B2:B1000")=$B69) * (INDIRECT("'"&E$62&"'!C2:C1000")=$C69) ), 5, FALSE )=0, "", VLOOKUP( $A69, _xlfn._xlws.FILTER( INDIRECT("'"&E$62&"'!A2:E1000"), (INDIRECT("'"&E$62&"'!B2:B1000")=$B69) * (INDIRECT("'"&E$62&"'!C2:C1000")=$C69) ), 5, FALSE ) )} | F69: {=IF( VLOOKUP( $A69, _xlfn._xlws.FILTER( INDIRECT("'"&F$62&"'!A2:E1000"), (INDIRECT("'"&F$62&"'!B2:B1000")=$B69) * (INDIRECT("'"&F$62&"'!C2:C1000")=$C69) ), 5, FALSE )=0, "", VLOOKUP( $A69, _xlfn._xlws.FILTER( INDIRECT("'"&F$62&"'!A2:E1000"), (INDIRECT("'"&F$62&"'!B2:B1000")=$B69) * (INDIRECT("'"&F$62&"'!C2:C1000")=$C69) ), 5, FALSE ) )} | G69: {=IF( VLOOKUP( $A69, _xlfn._xlws.FILTER( INDIRECT("'"&G$62&"'!A2:E1000"), (INDIRECT("'"&G$62&"'!B2:B1000")=$B69) * (INDIRECT("'"&G$62&"'!C2:C1000")=$C69) ), 5, FALSE )=0, "", VLOOKUP( $A69, _xlfn._xlws.FILTER( INDIRECT("'"&G$62&"'!A2:E1000"), (INDIRECT("'"&G$62&"'!B2:B1000")=$B69) * (INDIRECT("'"&G$62&"'!C2:C1000")=$C69) ), 5, FALSE ) )} | H69: {=IF( VLOOKUP( $A69, _xlfn._xlws.FILTER( INDIRECT("'"&H$62&"'!A2:E1000"), (INDIRECT("'"&H$62&"'!B2:B1000")=$B69) * (INDIRECT("'"&H$62&"'!C2:C1000")=$C69) ), 5, FALSE )=0, "", VLOOKUP( $A69, _xlfn._xlws.FILTER( INDIRECT("'"&H$62&"'!A2:E1000"), (INDIRECT("'"&H$62&"'!B2:B1000")=$B69) * (INDIRECT("'"&H$62&"'!C2:C1000")=$C69) ), 5, FALSE ) )} | I69: {=IF( VLOOKUP( $A69, _xlfn._xlws.FILTER( INDIRECT("'"&I$62&"'!A2:E1000"), (INDIRECT("'"&I$62&"'!B2:B1000")=$B69) * (INDIRECT("'"&I$62&"'!C2:C1000")=$C69) ), 5, FALSE )=0, "", VLOOKUP( $A69, _xlfn._xlws.FILTER( INDIRECT("'"&I$62&"'!A2:E1000"), (INDIRECT("'"&I$62&"'!B2:B1000")=$B69) * (INDIRECT("'"&I$62&"'!C2:C1000")=$C69) ), 5, FALSE ) )} | J69: {=IF( VLOOKUP( $A69, _xlfn._xlws.FILTER( INDIRECT("'"&J$62&"'!A2:E1000"), (INDIRECT("'"&J$62&"'!B2:B1000")=$B69) * (INDIRECT("'"&J$62&"'!C2:C1000")=$C69) ), 5, FALSE )=0, "", VLOOKUP( $A69, _xlfn._xlws.FILTER( INDIRECT("'"&J$62&"'!A2:E1000"), (INDIRECT("'"&J$62&"'!B2:B1000")=$B69) * (INDIRECT("'"&J$62&"'!C2:C1000")=$C69) ), 5, FALSE ) )} | K69: {=IF( VLOOKUP( $A69, _xlfn._xlws.FILTER( INDIRECT("'"&K$62&"'!A2:E1000"), (INDIRECT("'"&K$62&"'!B2:B1000")=$B69) * (INDIRECT("'"&K$62&"'!C2:C1000")=$C69) ), 5, FALSE )=0, "", VLOOKUP( $A69, _xlfn._xlws.FILTER( INDIRECT("'"&K$62&"'!A2:E1000"), (INDIRECT("'"&K$62&"'!B2:B1000")=$B69) * (INDIRECT("'"&K$62&"'!C2:C1000")=$C69) ), 5, FALSE ) )} | ... O69: {=IF( VLOOKUP( $A69, _xlfn._xlws.FILTER( INDIRECT("'"&O$62&"'!A2:E1000"), (INDIRECT("'"&O$62&"'!B2:B1000")=$B69) * (INDIRECT("'"&O$62&"'!C2:C1000")=$C69) ), 5, FALSE )=0, "", VLOOKUP( $A69, _xlfn._xlws.FILTER( INDIRECT("'"&O$62&"'!A2:E1000"), (INDIRECT("'"&O$62&"'!B2:B1000")=$B69) * (INDIRECT("'"&O$62&"'!C2:C1000")=$C69) ), 5, FALSE ) )} | R69: Laranjeiras do Sul | S69: Laranjeiras do Sul
