Workbook

Sheet Resumo
A1: Categoria | B1: 11.24 | C1: 12.24 | D1: 01.25 | E1: 02.25 | F1: 03.25 | G1: 04.25 | H1: 05.25 | I1: 06.25 | J1: 07.25 | K1: 08.25 | L1: 09.25 | M1: 10.25 | N1: 11.25 | O1: 12.25 | P1: Total
A2: Enviado | B2: =COUNTIF(INDIRECT(B$1&"!E2:E1000"),$A2) | C2: =COUNTIF(INDIRECT(C$1&"!E2:E1000"),$A2) | D2: =COUNTIF(INDIRECT(D$1&"!E2:E1000"),$A2) | E2: =COUNTIF(INDIRECT(E$1&"!E2:E1000"),$A2) | F2: =COUNTIF(INDIRECT(F$1&"!E2:E1000"),$A2) | G2: =COUNTIF(INDIRECT(G$1&"!E2:E1000"),$A2) | H2: =COUNTIF(INDIRECT(H$1&"!E2:E1000"),$A2) | I2: =COUNTIF(INDIRECT(I$1&"!E2:E1000"),$A2) | ... O2: =COUNTIF(INDIRECT(O$1&"!E2:E1000"),$A2) | P2: =SUM(B2:O2)
A3: Atrasado | B3: =COUNTIF(INDIRECT("11.24!E2:E1000"),$A3) | C3: =COUNTIF(INDIRECT(C$1&"!E2:E1000"),$A3) | D3: =COUNTIF(INDIRECT(D$1&"!E2:E1000"),$A3) | E3: =COUNTIF(INDIRECT(E$1&"!E2:E1000"),$A3) | F3: =COUNTIF(INDIRECT(F$1&"!E2:E1000"),$A3) | G3: =COUNTIF(INDIRECT(G$1&"!E2:E1000"),$A3) | H3: =COUNTIF(INDIRECT(H$1&"!E2:E1000"),$A3) | I3: =COUNTIF(INDIRECT(I$1&"!E2:E1000"),$A3) | J3: =COUNTIF(INDIRECT(J$1&"!E2:E1000"),$A3) | ... O3: =COUNTIF(INDIRECT(O$1&"!E2:E1000"),$A3) | P3: =SUM(B3:O3)
A4: Atrasado >= 2 | B4: =COUNTIF(INDIRECT("11.24!E2:E1000"),$A4) | C4: =COUNTIF(INDIRECT(C$1&"!E2:E1000"),$A4) | D4: =COUNTIF(INDIRECT(D$1&"!E2:E1000"),$A4) | E4: =COUNTIF(INDIRECT(E$1&"!E2:E1000"),$A4) | F4: =COUNTIF(INDIRECT(F$1&"!E2:E1000"),$A4) | G4: =COUNTIF(INDIRECT(G$1&"!E2:E1000"),$A4) | H4: =COUNTIF(INDIRECT(H$1&"!E2:E1000"),$A4) | I4: =COUNTIF(INDIRECT(I$1&"!E2:E1000"),$A4) | J4: =COUNTIF(INDIRECT(J$1&"!E2:E1000"),$A4) | ... O4: =COUNTIF(INDIRECT(O$1&"!E2:E1000"),$A4) | P4: =SUM(B4:O4)
A5: Duplicado | B5: =COUNTIF(INDIRECT("11.24!E2:E1000"),$A5) | C5: =COUNTIF(INDIRECT(C$1&"!E2:E1000"),$A5) | D5: =COUNTIF(INDIRECT(D$1&"!E2:E1000"),$A5) | E5: =COUNTIF(INDIRECT(E$1&"!E2:E1000"),$A5) | F5: =COUNTIF(INDIRECT(F$1&"!E2:E1000"),$A5) | G5: =COUNTIF(INDIRECT(G$1&"!E2:E1000"),$A5) | H5: =COUNTIF(INDIRECT(H$1&"!E2:E1000"),$A5) | I5: =COUNTIF(INDIRECT(I$1&"!E2:E1000"),$A5) | J5: =COUNTIF(INDIRECT(J$1&"!E2:E1000"),$A5) | ... O5: =COUNTIF(INDIRECT(O$1&"!E2:E1000"),$A5) | P5: =SUM(B5:O5)
A6: Outras Ocorrências | B6: =COUNTIF(INDIRECT("11.24!E2:E1000"),$A6) | C6: =COUNTIF(INDIRECT(C$1&"!E2:E1000"),$A6) | D6: =COUNTIF(INDIRECT(D$1&"!E2:E1000"),$A6) | E6: =COUNTIF(INDIRECT(E$1&"!E2:E1000"),$A6) | F6: =COUNTIF(INDIRECT(F$1&"!E2:E1000"),$A6) | G6: =COUNTIF(INDIRECT(G$1&"!E2:E1000"),$A6) | H6: =COUNTIF(INDIRECT(H$1&"!E2:E1000"),$A6) | I6: =COUNTIF(INDIRECT(I$1&"!E2:E1000"),$A6) | J6: =COUNTIF(INDIRECT(J$1&"!E2:E1000"),$A6) | ... O6: =COUNTIF(INDIRECT(O$1&"!E2:E1000"),$A6) | P6: =SUM(B6:O6)
A7: Sem Técnico | B7: =COUNTIF(INDIRECT("11.24!E2:E1000"),$A7) | C7: =COUNTIF(INDIRECT(C$1&"!E2:E1000"),$A7) | D7: =COUNTIF(INDIRECT(D$1&"!E2:E1000"),$A7) | E7: =COUNTIF(INDIRECT(E$1&"!E2:E1000"),$A7) | F7: =COUNTIF(INDIRECT(F$1&"!E2:E1000"),$A7) | G7: =COUNTIF(INDIRECT(G$1&"!E2:E1000"),$A7) | H7: =COUNTIF(INDIRECT(H$1&"!E2:E1000"),$A7) | I7: =COUNTIF(INDIRECT(I$1&"!E2:E1000"),$A7) | J7: =COUNTIF(INDIRECT(J$1&"!E2:E1000"),$A7) | ... O7: =COUNTIF(INDIRECT(O$1&"!E2:E1000"),$A7) | P7: =SUM(B7:O7)
A8: Total | B8: =SUM(B2:B7) | C8: =SUM(C2:C7) | D8: =SUM(D2:D7) | E8: =SUM(E2:E7) | F8: =SUM(F2:F7) | G8: =SUM(G2:G7) | H8: =SUM(H2:H7) | I8: =SUM(I2:I7) | ... O8: =SUM(O2:O7) | P8: =SUM(B8:O8)
A11: Digite o Mês de Referência | C11: Mês de Referência | K11: Acumulado (Total) | R11: Resumo por Regional
A12: 10.25 | C12: Monitoramento (Envios) | K12: Monitoramento (Envios) | R12: Regional | T12: Valquiria
C13: Regional | D13: Envi. | E13: Atra. | F13: Atra. >= 2 | G13: Dup. | H13: Out. Ocor. | I13: Sem Tec. | K13: Envi. | L13: Atra. | M13: Atra. >= 2 | N13: Dup. | O13: Out. Ocor. | P13: Sem Tec. | R13: =_xlfn.CONCAT("Envios - Mês de Referência - ", A12)
C14: Bianca | D14: {=IFERROR(ROWS(_xlfn._xlws.FILTER(INDIRECT($A$12&"!A2:E100"),(INDIRECT($A$12&"!A2:A100")=$C14)*(INDIRECT($A$12&"!E2:E100")="Enviado"))), 0)} | E14: {=IFERROR(ROWS(_xlfn._xlws.FILTER(INDIRECT($A$12&"!A2:E100"),(INDIRECT($A$12&"!A2:A100")=$C14)*(INDIRECT($A$12&"!E2:E100")="Atrasado"))), 0)} | F14: {=IFERROR(ROWS(_xlfn._xlws.FILTER(INDIRECT($A$12&"!A2:E100"),(INDIRECT($A$12&"!A2:A100")=$C14)*(INDIRECT($A$12&"!E2:E100")="Atrasado >= 2"))), 0)} | G14: {=IFERROR(ROWS(_xlfn._xlws.FILTER(INDIRECT($A$12&"!A2:E100"),(INDIRECT($A$12&"!A2:A100")=$C14)*(INDIRECT($A$12&"!E2:E100")="Duplicado"))), 0)} | H14: {=IFERROR(ROWS(_xlfn._xlws.FILTER(INDIRECT($A$12&"!A2:E100"),(INDIRECT($A$12&"!A2:A100")=$C14)*(INDIRECT($A$12&"!E2:E100")="Outras Ocorrências"))), 0)} | I14: {=IFERROR(ROWS(_xlfn._xlws.FILTER(INDIRECT($A$12&"!A2:E100"),(INDIRECT($A$12&"!A2:A100")=$C14)*(INDIRECT($A$12&"!E2:E100")="Sem Técnico"))), 0)} | K14: =COUNTIF(INDIRECT("Monitoramento!$D$2:$Q$12"), "Enviado") | L14: =COUNTIF(INDIRECT("Monitoramento!$D$2:$Q$12"), "Atrasado") | M14: =COUNTIF(INDIRECT("Monitoramento!$D$2:$Q$12"), "Atrasado >= 2") | N14: =COUNTIF(INDIRECT("Monitoramento!$D$2:$Q$12"), "Duplicado") | O14: =COUNTIF(INDIRECT("Monitoramento!$D$2:$Q$12"), "Outras Ocorrências") | P14: =COUNTIF(INDIRECT("Monitoramento!$D$2:$Q$12"), "Sem Técnico") | R14: Enviados | S14: =VLOOKUP($T$12,$C$14:$I$19,2, FALSE) | T14: =S14/SUM($S$14:$S$19)
C15: Gabriel | D15: {=IFERROR(ROWS(_xlfn._xlws.FILTER(INDIRECT($A$12&"!A2:E100"),(INDIRECT($A$12&"!A2:A100")=$C15)*(INDIRECT($A$12&"!E2:E100")="Enviado"))), 0)} | E15: {=IFERROR(ROWS(_xlfn._xlws.FILTER(INDIRECT($A$12&"!A2:E100"),(INDIRECT($A$12&"!A2:A100")=$C15)*(INDIRECT($A$12&"!E2:E100")="Atrasado"))), 0)} | F15: {=IFERROR(ROWS(_xlfn._xlws.FILTER(INDIRECT($A$12&"!A2:E100"),(INDIRECT($A$12&"!A2:A100")=$C15)*(INDIRECT($A$12&"!E2:E100")="Atrasado >= 2"))), 0)} | G15: {=IFERROR(ROWS(_xlfn._xlws.FILTER(INDIRECT($A$12&"!A2:E100"),(INDIRECT($A$12&"!A2:A100")=$C15)*(INDIRECT($A$12&"!E2:E100")="Duplicado"))), 0)} | H15: {=IFERROR(ROWS(_xlfn._xlws.FILTER(INDIRECT($A$12&"!A2:E100"),(INDIRECT($A$12&"!A2:A100")=$C15)*(INDIRECT($A$12&"!E2:E100")="Outras Ocorrências"))), 0)} | I15: {=IFERROR(ROWS(_xlfn._xlws.FILTER(INDIRECT($A$12&"!A2:E100"),(INDIRECT($A$12&"!A2:A100")=$C15)*(INDIRECT($A$12&"!E2:E100")="Sem Técnico"))), 0)} | K15: =COUNTIF(INDIRECT("Monitoramento!$D$15:$Q$25"), "Enviado") | L15: =COUNTIF(INDIRECT("Monitoramento!$D$15:$Q$25"), "Atrasado") | M15: =COUNTIF(INDIRECT("Monitoramento!$D$15:$Q$25"), "Atrasado >= 2") | N15: =COUNTIF(INDIRECT("Monitoramento!$D$15:$Q$25"), "Duplicado") | O15: =COUNTIF(INDIRECT("Monitoramento!$D$15:$Q$25"), "Outras Ocorrências") | P15: =COUNTIF(INDIRECT("Monitoramento!$D$15:$Q$25"), "Sem Técnico") | R15: Atrasados | S15: =VLOOKUP($T$12,$C$14:$I$19,3,FALSE) | T15: =S15/SUM($S$14:$S$19)
C16: Gustavo | D16: {=IFERROR(ROWS(_xlfn._xlws.FILTER(INDIRECT($A$12&"!A2:E100"),(INDIRECT($A$12&"!A2:A100")=$C16)*(INDIRECT($A$12&"!E2:E100")="Enviado"))), 0)} | E16: {=IFERROR(ROWS(_xlfn._xlws.FILTER(INDIRECT($A$12&"!A2:E100"),(INDIRECT($A$12&"!A2:A100")=$C16)*(INDIRECT($A$12&"!E2:E100")="Atrasado"))), 0)} | F16: {=IFERROR(ROWS(_xlfn._xlws.FILTER(INDIRECT($A$12&"!A2:E100"),(INDIRECT($A$12&"!A2:A100")=$C16)*(INDIRECT($A$12&"!E2:E100")="Atrasado >= 2"))), 0)} | G16: {=IFERROR(ROWS(_xlfn._xlws.FILTER(INDIRECT($A$12&"!A2:E100"),(INDIRECT($A$12&"!A2:A100")=$C16)*(INDIRECT($A$12&"!E2:E100")="Duplicado"))), 0)} | H16: {=IFERROR(ROWS(_xlfn._xlws.FILTER(INDIRECT($A$12&"!A2:E100"),(INDIRECT($A$12&"!A2:A100")=$C16)*(INDIRECT($A$12&"!E2:E100")="Outras Ocorrências"))), 0)} | I16: {=IFERROR(ROWS(_xlfn._xlws.FILTER(INDIRECT($A$12&"!A2:E100"),(INDIRECT($A$12&"!A2:A100")=$C16)*(INDIRECT($A$12&"!E2:E100")="Sem Técnico"))), 0)} | K16: =COUNTIF(INDIRECT("Monitoramento!$D$28:$Q$38"), "Enviado") | L16: =COUNTIF(INDIRECT("Monitoramento!$D$28:$Q$38"), "Atrasado") | M16: =COUNTIF(INDIRECT("Monitoramento!$D$28:$Q$38"), "Atrasado >= 2") | N16: =COUNTIF(INDIRECT("Monitoramento!$D$28:$Q$38"), "Duplicado") | O16: =COUNTIF(INDIRECT("Monitoramento!$D$28:$Q$38"), "Outras Ocorrências") | P16: =COUNTIF(INDIRECT("Monitoramento!$D$28:$Q$38"), "Sem Técnico") | R16: Atrasados >= 2 | S16: =VLOOKUP($T$12,$C$14:$I$19,4,FALSE) | T16: =S16/SUM($S$14:$S$19)
C17: Larissa | D17: {=IFERROR(ROWS(_xlfn._xlws.FILTER(INDIRECT($A$12&"!A2:E100"),(INDIRECT($A$12&"!A2:A100")=$C17)*(INDIRECT($A$12&"!E2:E100")="Enviado"))), 0)} | E17: {=IFERROR(ROWS(_xlfn._xlws.FILTER(INDIRECT($A$12&"!A2:E100"),(INDIRECT($A$12&"!A2:A100")=$C17)*(INDIRECT($A$12&"!E2:E100")="Atrasado"))), 0)} | F17: {=IFERROR(ROWS(_xlfn._xlws.FILTER(INDIRECT($A$12&"!A2:E100"),(INDIRECT($A$12&"!A2:A100")=$C17)*(INDIRECT($A$12&"!E2:E100")="Atrasado >= 2"))), 0)} | G17: {=IFERROR(ROWS(_xlfn._xlws.FILTER(INDIRECT($A$12&"!A2:E100"),(INDIRECT($A$12&"!A2:A100")=$C17)*(INDIRECT($A$12&"!E2:E100")="Duplicado"))), 0)} | H17: {=IFERROR(ROWS(_xlfn._xlws.FILTER(INDIRECT($A$12&"!A2:E100"),(INDIRECT($A$12&"!A2:A100")=$C17)*(INDIRECT($A$12&"!E2:E100")="Outras Ocorrências"))), 0)} | I17: {=IFERROR(ROWS(_xlfn._xlws.FILTER(INDIRECT($A$12&"!A2:E100"),(INDIRECT($A$12&"!A2:A100")=$C17)*(INDIRECT($A$12&"!E2:E100")="Sem Técnico"))), 0)} | K17: =COUNTIF(INDIRECT("Monitoramento!$D$41:$Q$53"), "Enviado") | L17: =COUNTIF(INDIRECT("Monitoramento!$D$41:$Q$53"), "Atrasado") | M17: =COUNTIF(INDIRECT("Monitoramento!$D$41:$Q$53"), "Atrasado >= 2") | N17: =COUNTIF(INDIRECT("Monitoramento!$D$41:$Q$53"), "Duplicado") | O17: =COUNTIF(INDIRECT("Monitoramento!$D$41:$Q$53"), "Outras Ocorrências") | P17: =COUNTIF(INDIRECT("Monitoramento!$D$41:$Q$53"), "Sem Técnico") | R17: Duplicados | S17: =VLOOKUP($T$12,$C$14:$I$19,5,FALSE) | T17: =S17/SUM($S$14:$S$19)
C18: Luana | D18: {=IFERROR(ROWS(_xlfn._xlws.FILTER(INDIRECT($A$12&"!A2:E100"),(INDIRECT($A$12&"!A2:A100")=$C18)*(INDIRECT($A$12&"!E2:E100")="Enviado"))), 0)} | E18: {=IFERROR(ROWS(_xlfn._xlws.FILTER(INDIRECT($A$12&"!A2:E100"),(INDIRECT($A$12&"!A2:A100")=$C18)*(INDIRECT($A$12&"!E2:E100")="Atrasado"))), 0)} | F18: {=IFERROR(ROWS(_xlfn._xlws.FILTER(INDIRECT($A$12&"!A2:E100"),(INDIRECT($A$12&"!A2:A100")=$C18)*(INDIRECT($A$12&"!E2:E100")="Atrasado >= 2"))), 0)} | G18: {=IFERROR(ROWS(_xlfn._xlws.FILTER(INDIRECT($A$12&"!A2:E100"),(INDIRECT($A$12&"!A2:A100")=$C18)*(INDIRECT($A$12&"!E2:E100")="Duplicado"))), 0)} | H18: {=IFERROR(ROWS(_xlfn._xlws.FILTER(INDIRECT($A$12&"!A2:E100"),(INDIRECT($A$12&"!A2:A100")=$C18)*(INDIRECT($A$12&"!E2:E100")="Outras Ocorrências"))), 0)} | I18: {=IFERROR(ROWS(_xlfn._xlws.FILTER(INDIRECT($A$12&"!A2:E100"),(INDIRECT($A$12&"!A2:A100")=$C18)*(INDIRECT($A$12&"!E2:E100")="Sem Técnico"))), 0)} | K18: =COUNTIF(INDIRECT("Monitoramento!$D$56:$Q$67"), "Enviado") | L18: =COUNTIF(INDIRECT("Monitoramento!$D$56:$Q$67"), "Atrasado") | M18: =COUNTIF(INDIRECT("Monitoramento!$D$56:$Q$67"), "Atrasado >= 2") | N18: =COUNTIF(INDIRECT("Monitoramento!$D$56:$Q$67"), "Duplicado") | O18: =COUNTIF(INDIRECT("Monitoramento!$D$56:$Q$67"), "Outras Ocorrências") | P18: =COUNTIF(INDIRECT("Monitoramento!$D$56:$Q$67"), "Sem Técnico") | R18: Outras Ocorrências | S18: =VLOOKUP($T$12,$C$14:$I$19,6,FALSE) | T18: =S18/SUM($S$14:$S$19)
C19: Valquiria | D19: {=IFERROR(ROWS(_xlfn._xlws.FILTER(INDIRECT($A$12&"!A2:E100"),(INDIRECT($A$12&"!A2:A100")=$C19)*(INDIRECT($A$12&"!E2:E100")="Enviado"))), 0)} | E19: {=IFERROR(ROWS(_xlfn._xlws.FILTER(INDIRECT($A$12&"!A2:E100"),(INDIRECT($A$12&"!A2:A100")=$C19)*(INDIRECT($A$12&"!E2:E100")="Atrasado"))), 0)} | F19: {=IFERROR(ROWS(_xlfn._xlws.FILTER(INDIRECT($A$12&"!A2:E100"),(INDIRECT($A$12&"!A2:A100")=$C19)*(INDIRECT($A$12&"!E2:E100")="Atrasado >= 2"))), 0)} | G19: {=IFERROR(ROWS(_xlfn._xlws.FILTER(INDIRECT($A$12&"!A2:E100"),(INDIRECT($A$12&"!A2:A100")=$C19)*(INDIRECT($A$12&"!E2:E100")="Duplicado"))), 0)} | H19: {=IFERROR(ROWS(_xlfn._xlws.FILTER(INDIRECT($A$12&"!A2:E100"),(INDIRECT($A$12&"!A2:A100")=$C19)*(INDIRECT($A$12&"!E2:E100")="Outras Ocorrências"))), 0)} | I19: {=IFERROR(ROWS(_xlfn._xlws.FILTER(INDIRECT($A$12&"!A2:E100"),(INDIRECT($A$12&"!A2:A100")=$C19)*(INDIRECT($A$12&"!E2:E100")="Sem Técnico"))), 0)} | K19: =COUNTIF(INDIRECT("Monitoramento!$D$70:$Q$80"), "Enviado") | L19: =COUNTIF(INDIRECT("Monitoramento!$D$70:$Q$80"), "Atrasado") | M19: =COUNTIF(INDIRECT("Monitoramento!$D$70:$Q$80"), "Atrasado >= 2") | N19: =COUNTIF(INDIRECT("Monitoramento!$D$70:$Q$80"), "Duplicado") | O19: =COUNTIF(INDIRECT("Monitoramento!$D$70:$Q$80"), "Outras Ocorrências") | P19: =COUNTIF(INDIRECT("Monitoramento!$D$70:$Q$80"), "Sem Técnico") | R19: Sem Técnico | S19: =VLOOKUP($T$12,$C$14:$I$19,7,FALSE) | T19: =S19/SUM($S$14:$S$19)
C20: Regionais (Validações) | K20: Regionais (Validações) | R20: % Validação | S20: =VLOOKUP($T$12,$C$22:$I$27,7,FALSE)
C21: Regional | E21: Validados | G21: Não Validados | I21: % Val. | K21: Validados | M21: Não Validados | O21: % Validados | R21: Envios - Acumulado (Total)
C22: Bianca | E22: {=IFERROR(ROWS(_xlfn._xlws.FILTER(INDIRECT($A$12&"!A2:E100"),(INDIRECT($A$12&"!A2:A100")=$C22)*(INDIRECT($A$12&"!G2:G100")="Sim"))), 0)} | G22: {=IFERROR(ROWS(_xlfn._xlws.FILTER(INDIRECT($A$12&"!A2:E100"),(INDIRECT($A$12&"!A2:A100")=$C22)*(INDIRECT($A$12&"!G2:G100")="Não")))-E14, 0)} | I22: =IFERROR(E22/SUM(E22:H22),0) | K22: =COUNTIF(INDIRECT("Regionais!$D$2:$Q$12"), "Sim") | M22: =COUNTIF(INDIRECT("Regionais!$D$2:$Q$12"), "Não")-SUM(L14:M14) | O22: =IFERROR(K22/SUM(K22:N22), 0) | R22: Enviados | S22: =VLOOKUP($T$12,$C$13:$P$19,9,FALSE) | T22: =S22/SUM($S$22:$S$27)
C23: Gabriel | E23: {=IFERROR(ROWS(_xlfn._xlws.FILTER(INDIRECT($A$12&"!A2:E100"),(INDIRECT($A$12&"!A2:A100")=$C23)*(INDIRECT($A$12&"!G2:G100")="Sim"))), 0)} | G23: {=IFERROR(ROWS(_xlfn._xlws.FILTER(INDIRECT($A$12&"!A2:E100"),(INDIRECT($A$12&"!A2:A100")=$C23)*(INDIRECT($A$12&"!G2:G100")="Não")))-E15, 0)} | I23: =IFERROR(E23/SUM(E23:H23),0) | K23: =COUNTIF(INDIRECT("Regionais!$D$15:$Q$25"), "Sim") | M23: =COUNTIF(INDIRECT("Regionais!$D$15:$Q$25"), "Não")-SUM(L15:M15) | O23: =IFERROR(K23/SUM(K23:N23), 0) | R23: Atrasados | S23: =VLOOKUP($T$12,$C$13:$P$19,10,FALSE) | T23: =S23/SUM($S$22:$S$27)
C24: Gustavo | E24: {=IFERROR(ROWS(_xlfn._xlws.FILTER(INDIRECT($A$12&"!A2:E100"),(INDIRECT($A$12&"!A2:A100")=$C24)*(INDIRECT($A$12&"!G2:G100")="Sim"))), 0)} | G24: {=IFERROR(ROWS(_xlfn._xlws.FILTER(INDIRECT($A$12&"!A2:E100"),(INDIRECT($A$12&"!A2:A100")=$C24)*(INDIRECT($A$12&"!G2:G100")="Não")))-E16, 0)} | I24: =IFERROR(E24/SUM(E24:H24),0) | K24: =COUNTIF(INDIRECT("Regionais!$D$28:$Q$38"), "Sim") | M24: =COUNTIF(INDIRECT("Regionais!$D$28:$Q$38"), "Não")-SUM(L16:M16) | O24: =IFERROR(K24/SUM(K24:N24), 0) | R24: Atrasados >= 2 | S24: =VLOOKUP($T$12,$C$13:$P$19,11,FALSE) | T24: =S24/SUM($S$22:$S$27)
C25: Larissa | E25: {=IFERROR(ROWS(_xlfn._xlws.FILTER(INDIRECT($A$12&"!A2:E100"),(INDIRECT($A$12&"!A2:A100")=$C25)*(INDIRECT($A$12&"!G2:G100")="Sim"))), 0)} | G25: {=IFERROR(ROWS(_xlfn._xlws.FILTER(INDIRECT($A$12&"!A2:E100"),(INDIRECT($A$12&"!A2:A100")=$C25)*(INDIRECT($A$12&"!G2:G100")="Não")))-E17, 0)} | I25: =IFERROR(E25/SUM(E25:H25),0) | K25: =COUNTIF(INDIRECT("Regionais!$D$41:$Q$53"), "Sim") | M25: =COUNTIF(INDIRECT("Regionais!$D$41:$Q$53"), "Não")-SUM(L17:M17) | O25: =IFERROR(K25/SUM(K25:N25), 0) | R25: Duplicados | S25: =VLOOKUP($T$12,$C$13:$P$19,12,FALSE) | T25: =S25/SUM($S$22:$S$27)
C26: Luana | E26: {=IFERROR(ROWS(_xlfn._xlws.FILTER(INDIRECT($A$12&"!A2:E100"),(INDIRECT($A$12&"!A2:A100")=$C26)*(INDIRECT($A$12&"!G2:G100")="Sim"))), 0)} | G26: {=IFERROR(ROWS(_xlfn._xlws.FILTER(INDIRECT($A$12&"!A2:E100"),(INDIRECT($A$12&"!A2:A100")=$C26)*(INDIRECT($A$12&"!G2:G100")="Não")))-E18, 0)} | I26: =IFERROR(E26/SUM(E26:H26),0) | K26: =COUNTIF(INDIRECT("Regionais!$D$56:$Q$67"), "Sim") | M26: =COUNTIF(INDIRECT("Regionais!$D$56:$Q$67"), "Não")-SUM(L18:M18) | O26: =IFERROR(K26/SUM(K26:N26), 0) | R26: Outras Ocorrências | S26: =VLOOKUP($T$12,$C$13:$P$19,13,FALSE) | T26: =S26/SUM($S$22:$S$27)
C27: Valquiria | E27: {=IFERROR(ROWS(_xlfn._xlws.FILTER(INDIRECT($A$12&"!A2:E100"),(INDIRECT($A$12&"!A2:A100")=$C27)*(INDIRECT($A$12&"!G2:G100")="Sim"))), 0)} | G27: {=IFERROR(ROWS(_xlfn._xlws.FILTER(INDIRECT($A$12&"!A2:E100"),(INDIRECT($A$12&"!A2:A100")=$C27)*(INDIRECT($A$12&"!G2:G100")="Não")))-E19, 0)} | I27: =IFERROR(E27/SUM(E27:H27),0) | K27: =COUNTIF(INDIRECT("Regionais!$D$70:$Q$80"), "Sim") | M27: =COUNTIF(INDIRECT("Regionais!$D$70:$Q$80"), "Não")-SUM(L19:M19) | O27: =IFERROR(K27/SUM(K27:N27), 0) | R27: Sem Técnico | S27: =VLOOKUP($T$12,$C$13:$P$19,14,FALSE) | T27: =S27/SUM($S$22:$S$27)
R28: % Validação | S28: =VLOOKUP($T$12,$C$21:$P$27,13,FALSE)
C34: Formulários | E34: Enviado | F34: Atrasado | G34: Sem Téc | H34: Outras | I34: Total
C35: 4 - Receitas (11/24) | E35: =B$2+B$5 | F35: =B$3+B$4 | G35: =B$7 | H35: =B$6 | I35: =SUM(E35:H35)
C36: 4 - Receitas (12/24) | E36: =C$2+C$5 | F36: =C$3+C$4 | G36: =C$7 | H36: =C$6 | I36: =SUM(E36:H36)
C37: 4 - Receitas (01/25) | E37: =D$2+D$5 | F37: =D$3+D$4 | G37: =D$7 | H37: =D$6 | I37: =SUM(E37:H37)
C38: 4 - Receitas (02/25) | E38: =E$2+E$5 | F38: =E$3+E$4 | G38: =E$7 | H38: =E$6 | I38: =SUM(E38:H38)
C39: 4 - Receitas (03/25) | E39: =F$2+F$5 | F39: =F$3+F$4 | G39: =F$7 | H39: =F$6 | I39: =SUM(E39:H39)
C40: 4 - Receitas (04/25) | E40: =G$2+G$5 | F40: =G$3+G$4 | G40: =G$7 | H40: =G$6 | I40: =SUM(E40:H40)
C41: 4 - Receitas (05/25) | E41: =H$2+H$5 | F41: =H$3+H$4 | G41: =H$7 | H41: =H$6 | I41: =SUM(E41:H41)
C42: 4 - Receitas (06/25) | E42: =I$2+I$5 | F42: =I$3+I$4 | G42: =I$7 | H42: =I$6 | I42: =SUM(E42:H42)
C43: 4 - Receitas (07/25) | E43: =J$2+J$5 | F43: =J$3+J$4 | G43: =J$7 | H43: =J$6 | I43: =SUM(E43:H43)
C44: 4 - Receitas (08/25) | E44: =K$2+K$5 | F44: =K$3+K$4 | G44: =K$7 | H44: =K$6 | I44: =SUM(E44:H44)
C45: 4 - Receitas (09/25) | E45: =L$2+L$5 | F45: =L$3+L$4 | G45: =L$7 | H45: =L$6 | I45: =SUM(E45:H45)
C46: 4 - Receitas (10/25) | E46: =M$2+M$5 | F46: =M$3+M$4 | G46: =M$7 | H46: =M$6 | I46: =SUM(E46:H46)
C47: 4 - Receitas (11/25) | E47: =N$2+N$5 | F47: =N$3+N$4 | G47: =N$7 | H47: =N$6 | I47: =SUM(E47:H47)
C48: 4 - Receitas (12/25) | E48: =O$2+O$5 | F48: =O$3+O$4 | G48: =O$7 | H48: =O$6 | I48: =SUM(E48:H48)
B50: Regional | C50: Município | E50: UVR | F50: Lacuna | G50: V1 | H50: Status (06-11)
B51: Valquiria | C51: Formosa do Oeste | E51: 1 | F51: 11.24 | G51: 45611 | H51: Atrasado >= 2
B52: Gabriel | C52: Maripa | E52: 1 | F52: 11.24 | G52: 45611 | H52: Enviado
B53: Gabriel | C53: Mundo Novo | E53: 1 | F53: 11.24 | G53: 45611 | H53: Atrasado >= 2
B54: Gabriel | C54: Assis Chateaubriand | E54: 1 | F54: 12.24 | G54: 45641 | H54: Enviado
B55: Valquiria | C55: Cafelândia | E55: 1 | F55: 12.24 | G55: 45641 | H55: Atrasado >= 2
B56: Valquiria | C56: Formosa do Oeste | E56: 1 | F56: 12.24 | G56: 45641 | H56: Atrasado >= 2
B57: Larissa | C57: Foz do Iguaçu | E57: 6 | F57: 12.24 | G57: 45641 | H57: Atrasado >= 2
B58: Valquiria | C58: Jesuítas | E58: 1 | F58: 12.24 | G58: 45641 | H58: Atrasado >= 2
B59: Luana | C59: Marechal Candido Rondon | E59: 1 | F59: 12.24 | G59: 45641 | H59: Atrasado >= 2
B60: Luana | C60: Marechal Candido Rondon | E60: 2 | F60: 12.24 | G60: 45641 | H60: Atrasado >= 2
B61: Gabriel | C61: Maripa | E61: 1 | F61: 12.24 | G61: 45641 | H61: Enviado
B62: Gabriel | C62: Palotina | E62: 1 | F62: 12.24 | G62: 45641 | H62: Atrasado >= 2
... B72: Bianca | C72: Tres Barras do Parana | E72: 1 | F72: 01.25 | G72: 45672 | H72: Atrasado >= 2

Sheet Monitoramento
A1: Regional | B1: Municípios | C1: UVR | D1: 11.24 | E1: 12.24 | F1: 01.25 | G1: 02.25 | H1: 03.25 | I1: 04.25 | J1: 05.25 | K1: 06.25 | L1: 07.25 | M1: 08.25 | N1: 09.25 | O1: 10.25 | P1: 11.25 | Q1: 12.25
A2: Bianca | B2: Anahy | C2: 1 | D2: {=IF( VLOOKUP( $A2, _xlfn._xlws.FILTER( INDIRECT("'"&D$14&"'!A2:E1000"), (INDIRECT("'"&D$14&"'!B2:B1000")=$B2) * (INDIRECT("'"&D$14&"'!C2:C1000")=$C2) ), 5, FALSE )=0, "", VLOOKUP( $A2, _xlfn._xlws.FILTER( INDIRECT("'"&D$14&"'!A2:E1000"), (INDIRECT("'"&D$14&"'!B2:B1000")=$B2) * (INDIRECT("'"&D$14&"'!C2:C1000")=$C2) ), 5, FALSE ) )} | E2: {=IF( VLOOKUP( $A2, _xlfn._xlws.FILTER( INDIRECT("'"&E$14&"'!A2:E1000"), (INDIRECT("'"&E$14&"'!B2:B1000")=$B2) * (INDIRECT("'"&E$14&"'!C2:C1000")=$C2) ), 5, FALSE )=0, "", VLOOKUP( $A2, _xlfn._xlws.FILTER( INDIRECT("'"&E$14&"'!A2:E1000"), (INDIRECT("'"&E$14&"'!B2:B1000")=$B2) * (INDIRECT("'"&E$14&"'!C2:C1000")=$C2) ), 5, FALSE ) )} | F2: {=IF( VLOOKUP( $A2, _xlfn._xlws.FILTER( INDIRECT("'"&F$14&"'!A2:E1000"), (INDIRECT("'"&F$14&"'!B2:B1000")=$B2) * (INDIRECT("'"&F$14&"'!C2:C1000")=$C2) ), 5, FALSE )=0, "", VLOOKUP( $A2, _xlfn._xlws.FILTER( INDIRECT("'"&F$14&"'!A2:E1000"), (INDIRECT("'"&F$14&"'!B2:B1000")=$B2) * (INDIRECT("'"&F$14&"'!C2:C1000")=$C2) ), 5, FALSE ) )} | G2: {=IF( VLOOKUP( $A2, _xlfn._xlws.FILTER( INDIRECT("'"&G$14&"'!A2:E1000"), (INDIRECT("'"&G$14&"'!B2:B1000")=$B2) * (INDIRECT("'"&G$14&"'!C2:C1000")=$C2) ), 5, FALSE )=0, "", VLOOKUP( $A2, _xlfn._xlws.FILTER( INDIRECT("'"&G$14&"'!A2:E1000"), (INDIRECT("'"&G$14&"'!B2:B1000")=$B2) * (INDIRECT("'"&G$14&"'!C2:C1000")=$C2) ), 5, FALSE ) )} | H2: {=IF( VLOOKUP( $A2, _xlfn._xlws.FILTER( INDIRECT("'"&H$14&"'!A2:E1000"), (INDIRECT("'"&H$14&"'!B2:B1000")=$B2) * (INDIRECT("'"&H$14&"'!C2:C1000")=$C2) ), 5, FALSE )=0, "", VLOOKUP( $A2, _xlfn._xlws.FILTER( INDIRECT("'"&H$14&"'!A2:E1000"), (INDIRECT("'"&H$14&"'!B2:B1000")=$B2) * (INDIRECT("'"&H$14&"'!C2:C1000")=$C2) ), 5, FALSE ) )} | I2: {=IF( VLOOKUP( $A2, _xlfn._xlws.FILTER( INDIRECT("'"&I$14&"'!A2:E1000"), (INDIRECT("'"&I$14&"'!B2:B1000")=$B2) * (INDIRECT("'"&I$14&"'!C2:C1000")=$C2) ), 5, FALSE )=0, "", VLOOKUP( $A2, _xlfn._xlws.FILTER( INDIRECT("'"&I$14&"'!A2:E1000"), (INDIRECT("'"&I$14&"'!B2:B1000")=$B2) * (INDIRECT("'"&I$14&"'!C2:C1000")=$C2) ), 5, FALSE ) )} | J2: {=IF( VLOOKUP( $A2, _xlfn._xlws.FILTER( INDIRECT("'"&J$14&"'!A2:E1000"), (INDIRECT("'"&J$14&"'!B2:B1000")=$B2) * (INDIRECT("'"&J$14&"'!C2:C1000")=$C2) ), 5, FALSE )=0, "", VLOOKUP( $A2, _xlfn._xlws.FILTER( INDIRECT("'"&J$14&"'!A2:E1000"), (INDIRECT("'"&J$14&"'!B2:B1000")=$B2) * (INDIRECT("'"&J$14&"'!C2:C1000")=$C2) ), 5, FALSE ) )} | K2: {=IF( VLOOKUP( $A2, _xlfn._xlws.FILTER( INDIRECT("'"&K$14&"'!A2:E1000"), (INDIRECT("'"&K$14&"'!B2:B1000")=$B2) * (INDIRECT("'"&K$14&"'!C2:C1000")=$C2) ), 5, FALSE )=0, "", VLOOKUP( $A2, _xlfn._xlws.FILTER( INDIRECT("'"&K$14&"'!A2:E1000"), (INDIRECT("'"&K$14&"'!B2:B1000")=$B2) * (INDIRECT("'"&K$14&"'!C2:C1000")=$C2) ), 5, FALSE ) )} | ... Q2: {=IF( VLOOKUP( $A2, _xlfn._xlws.FILTER( INDIRECT("'"&Q$14&"'!A2:E1000"), (INDIRECT("'"&Q$14&"'!B2:B1000")=$B2) * (INDIRECT("'"&Q$14&"'!C2:C1000")=$C2) ), 5, FALSE )=0, "", VLOOKUP( $A2, _xlfn._xlws.FILTER( INDIRECT("'"&Q$14&"'!A2:E1000"), (INDIRECT("'"&Q$14&"'!B2:B1000")=$B2) * (INDIRECT("'"&Q$14&"'!C2:C1000")=$C2) ), 5, FALSE ) )}
A3: Bianca | B3: Boa Vista da Aparecida | C3: 1 | D3: {=IF( VLOOKUP( $A3, _xlfn._xlws.FILTER( INDIRECT("'"&D$14&"'!A2:E1000"), (INDIRECT("'"&D$14&"'!B2:B1000")=$B3) * (INDIRECT("'"&D$14&"'!C2:C1000")=$C3) ), 5, FALSE )=0, "", VLOOKUP( $A3, _xlfn._xlws.FILTER( INDIRECT("'"&D$14&"'!A2:E1000"), (INDIRECT("'"&D$14&"'!B2:B1000")=$B3) * (INDIRECT("'"&D$14&"'!C2:C1000")=$C3) ), 5, FALSE ) )} | E3: {=IF( VLOOKUP( $A3, _xlfn._xlws.FILTER( INDIRECT("'"&E$14&"'!A2:E1000"), (INDIRECT("'"&E$14&"'!B2:B1000")=$B3) * (INDIRECT("'"&E$14&"'!C2:C1000")=$C3) ), 5, FALSE )=0, "", VLOOKUP( $A3, _xlfn._xlws.FILTER( INDIRECT("'"&E$14&"'!A2:E1000"), (INDIRECT("'"&E$14&"'!B2:B1000")=$B3) * (INDIRECT("'"&E$14&"'!C2:C1000")=$C3) ), 5, FALSE ) )} | F3: {=IF( VLOOKUP( $A3, _xlfn._xlws.FILTER( INDIRECT("'"&F$14&"'!A2:E1000"), (INDIRECT("'"&F$14&"'!B2:B1000")=$B3) * (INDIRECT("'"&F$14&"'!C2:C1000")=$C3) ), 5, FALSE )=0, "", VLOOKUP( $A3, _xlfn._xlws.FILTER( INDIRECT("'"&F$14&"'!A2:E1000"), (INDIRECT("'"&F$14&"'!B2:B1000")=$B3) * (INDIRECT("'"&F$14&"'!C2:C1000")=$C3) ), 5, FALSE ) )} | G3: {=IF( VLOOKUP( $A3, _xlfn._xlws.FILTER( INDIRECT("'"&G$14&"'!A2:E1000"), (INDIRECT("'"&G$14&"'!B2:B1000")=$B3) * (INDIRECT("'"&G$14&"'!C2:C1000")=$C3) ), 5, FALSE )=0, "", VLOOKUP( $A3, _xlfn._xlws.FILTER( INDIRECT("'"&G$14&"'!A2:E1000"), (INDIRECT("'"&G$14&"'!B2:B1000")=$B3) * (INDIRECT("'"&G$14&"'!C2:C1000")=$C3) ), 5, FALSE ) )} | H3: {=IF( VLOOKUP( $A3, _xlfn._xlws.FILTER( INDIRECT("'"&H$14&"'!A2:E1000"), (INDIRECT("'"&H$14&"'!B2:B1000")=$B3) * (INDIRECT("'"&H$14&"'!C2:C1000")=$C3) ), 5, FALSE )=0, "", VLOOKUP( $A3, _xlfn._xlws.FILTER( INDIRECT("'"&H$14&"'!A2:E1000"), (INDIRECT("'"&H$14&"'!B2:B1000")=$B3) * (INDIRECT("'"&H$14&"'!C2:C1000")=$C3) ), 5, FALSE ) )} | I3: {=IF( VLOOKUP( $A3, _xlfn._xlws.FILTER( INDIRECT("'"&I$14&"'!A2:E1000"), (INDIRECT("'"&I$14&"'!B2:B1000")=$B3) * (INDIRECT("'"&I$14&"'!C2:C1000")=$C3) ), 5, FALSE )=0, "", VLOOKUP( $A3, _xlfn._xlws.FILTER( INDIRECT("'"&I$14&"'!A2:E1000"), (INDIRECT("'"&I$14&"'!B2:B1000")=$B3) * (INDIRECT("'"&I$14&"'!C2:C1000")=$C3) ), 5, FALSE ) )} | J3: {=IF( VLOOKUP( $A3, _xlfn._xlws.FILTER( INDIRECT("'"&J$14&"'!A2:E1000"), (INDIRECT("'"&J$14&"'!B2:B1000")=$B3) * (INDIRECT("'"&J$14&"'!C2:C1000")=$C3) ), 5, FALSE )=0, "", VLOOKUP( $A3, _xlfn._xlws.FILTER( INDIRECT("'"&J$14&"'!A2:E1000"), (INDIRECT("'"&J$14&"'!B2:B1000")=$B3) * (INDIRECT("'"&J$14&"'!C2:C1000")=$C3) ), 5, FALSE ) )} | K3: {=IF( VLOOKUP( $A3, _xlfn._xlws.FILTER( INDIRECT("'"&K$14&"'!A2:E1000"), (INDIRECT("'"&K$14&"'!B2:B1000")=$B3) * (INDIRECT("'"&K$14&"'!C2:C1000")=$C3) ), 5, FALSE )=0, "", VLOOKUP( $A3, _xlfn._xlws.FILTER( INDIRECT("'"&K$14&"'!A2:E1000"), (INDIRECT("'"&K$14&"'!B2:B1000")=$B3) * (INDIRECT("'"&K$14&"'!C2:C1000")=$C3) ), 5, FALSE ) )} | ... Q3: {=IF( VLOOKUP( $A3, _xlfn._xlws.FILTER( INDIRECT("'"&Q$14&"'!A2:E1000"), (INDIRECT("'"&Q$14&"'!B2:B1000")=$B3) * (INDIRECT("'"&Q$14&"'!C2:C1000")=$C3) ), 5, FALSE )=0, "", VLOOKUP( $A3, _xlfn._xlws.FILTER( INDIRECT("'"&Q$14&"'!A2:E1000"), (INDIRECT("'"&Q$14&"'!B2:B1000")=$B3) * (INDIRECT("'"&Q$14&"'!C2:C1000")=$C3) ), 5, FALSE ) )}
A4: Bianca | B4: Braganey | C4: 1 | D4: {=IF( VLOOKUP( $A4, _xlfn._xlws.FILTER( INDIRECT("'"&D$14&"'!A2:E1000"), (INDIRECT("'"&D$14&"'!B2:B1000")=$B4) * (INDIRECT("'"&D$14&"'!C2:C1000")=$C4) ), 5, FALSE )=0, "", VLOOKUP( $A4, _xlfn._xlws.FILTER( INDIRECT("'"&D$14&"'!A2:E1000"), (INDIRECT("'"&D$14&"'!B2:B1000")=$B4) * (INDIRECT("'"&D$14&"'!C2:C1000")=$C4) ), 5, FALSE ) )} | E4: {=IF( VLOOKUP( $A4, _xlfn._xlws.FILTER( INDIRECT("'"&E$14&"'!A2:E1000"), (INDIRECT("'"&E$14&"'!B2:B1000")=$B4) * (INDIRECT("'"&E$14&"'!C2:C1000")=$C4) ), 5, FALSE )=0, "", VLOOKUP( $A4, _xlfn._xlws.FILTER( INDIRECT("'"&E$14&"'!A2:E1000"), (INDIRECT("'"&E$14&"'!B2:B1000")=$B4) * (INDIRECT("'"&E$14&"'!C2:C1000")=$C4) ), 5, FALSE ) )} | F4: {=IF( VLOOKUP( $A4, _xlfn._xlws.FILTER( INDIRECT("'"&F$14&"'!A2:E1000"), (INDIRECT("'"&F$14&"'!B2:B1000")=$B4) * (INDIRECT("'"&F$14&"'!C2:C1000")=$C4) ), 5, FALSE )=0, "", VLOOKUP( $A4, _xlfn._xlws.FILTER( INDIRECT("'"&F$14&"'!A2:E1000"), (INDIRECT("'"&F$14&"'!B2:B1000")=$B4) * (INDIRECT("'"&F$14&"'!C2:C1000")=$C4) ), 5, FALSE ) )} | G4: {=IF( VLOOKUP( $A4, _xlfn._xlws.FILTER( INDIRECT("'"&G$14&"'!A2:E1000"), (INDIRECT("'"&G$14&"'!B2:B1000")=$B4) * (INDIRECT("'"&G$14&"'!C2:C1000")=$C4) ), 5, FALSE )=0, "", VLOOKUP( $A4, _xlfn._xlws.FILTER( INDIRECT("'"&G$14&"'!A2:E1000"), (INDIRECT("'"&G$14&"'!B2:B1000")=$B4) * (INDIRECT("'"&G$14&"'!C2:C1000")=$C4) ), 5, FALSE ) )} | H4: {=IF( VLOOKUP( $A4, _xlfn._xlws.FILTER( INDIRECT("'"&H$14&"'!A2:E1000"), (INDIRECT("'"&H$14&"'!B2:B1000")=$B4) * (INDIRECT("'"&H$14&"'!C2:C1000")=$C4) ), 5, FALSE )=0, "", VLOOKUP( $A4, _xlfn._xlws.FILTER( INDIRECT("'"&H$14&"'!A2:E1000"), (INDIRECT("'"&H$14&"'!B2:B1000")=$B4) * (INDIRECT("'"&H$14&"'!C2:C1000")=$C4) ), 5, FALSE ) )} | I4: {=IF( VLOOKUP( $A4, _xlfn._xlws.FILTER( INDIRECT("'"&I$14&"'!A2:E1000"), (INDIRECT("'"&I$14&"'!B2:B1000")=$B4) * (INDIRECT("'"&I$14&"'!C2:C1000")=$C4) ), 5, FALSE )=0, "", VLOOKUP( $A4, _xlfn._xlws.FILTER( INDIRECT("'"&I$14&"'!A2:E1000"), (INDIRECT("'"&I$14&"'!B2:B1000")=$B4) * (INDIRECT("'"&I$14&"'!C2:C1000")=$C4) ), 5, FALSE ) )} | J4: {=IF( VLOOKUP( $A4, _xlfn._xlws.FILTER( INDIRECT("'"&J$14&"'!A2:E1000"), (INDIRECT("'"&J$14&"'!B2:B1000")=$B4) * (INDIRECT("'"&J$14&"'!C2:C1000")=$C4) ), 5, FALSE )=0, "", VLOOKUP( $A4, _xlfn._xlws.FILTER( INDIRECT("'"&J$14&"'!A2:E1000"), (INDIRECT("'"&J$14&"'!B2:B1000")=$B4) * (INDIRECT("'"&J$14&"'!C2:C1000")=$C4) ), 5, FALSE ) )} | K4: {=IF( VLOOKUP( $A4, _xlfn._xlws.FILTER( INDIRECT("'"&K$14&"'!A2:E1000"), (INDIRECT("'"&K$14&"'!B2:B1000")=$B4) * (INDIRECT("'"&K$14&"'!C2:C1000")=$C4) ), 5, FALSE )=0, "", VLOOKUP( $A4, _xlfn._xlws.FILTER( INDIRECT("'"&K$14&"'!A2:E1000"), (INDIRECT("'"&K$14&"'!B2:B1000")=$B4) * (INDIRECT("'"&K$14&"'!C2:C1000")=$C4) ), 5, FALSE ) )} | ... Q4: {=IF( VLOOKUP( $A4, _xlfn._xlws.FILTER( INDIRECT("'"&Q$14&"'!A2:E1000"), (INDIRECT("'"&Q$14&"'!B2:B1000")=$B4) * (INDIRECT("'"&Q$14&"'!C2:C1000")=$C4) ), 5, FALSE )=0, "", VLOOKUP( $A4, _xlfn._xlws.FILTER( INDIRECT("'"&Q$14&"'!A2:E1000"), (INDIRECT("'"&Q$14&"'!B2:B1000")=$B4) * (INDIRECT("'"&Q$14&"'!C2:C1000")=$C4) ), 5, FALSE ) )}
A5: Bianca | B5: Campo Bonito | C5: 1 | D5: {=IF( VLOOKUP( $A5, _xlfn._xlws.FILTER( INDIRECT("'"&D$14&"'!A2:E1000"), (INDIRECT("'"&D$14&"'!B2:B1000")=$B5) * (INDIRECT("'"&D$14&"'!C2:C1000")=$C5) ), 5, FALSE )=0, "", VLOOKUP( $A5, _xlfn._xlws.FILTER( INDIRECT("'"&D$14&"'!A2:E1000"), (INDIRECT("'"&D$14&"'!B2:B1000")=$B5) * (INDIRECT("'"&D$14&"'!C2:C1000")=$C5) ), 5, FALSE ) )} | E5: {=IF( VLOOKUP( $A5, _xlfn._xlws.FILTER( INDIRECT("'"&E$14&"'!A2:E1000"), (INDIRECT("'"&E$14&"'!B2:B1000")=$B5) * (INDIRECT("'"&E$14&"'!C2:C1000")=$C5) ), 5, FALSE )=0, "", VLOOKUP( $A5, _xlfn._xlws.FILTER( INDIRECT("'"&E$14&"'!A2:E1000"), (INDIRECT("'"&E$14&"'!B2:B1000")=$B5) * (INDIRECT("'"&E$14&"'!C2:C1000")=$C5) ), 5, FALSE ) )} | F5: {=IF( VLOOKUP( $A5, _xlfn._xlws.FILTER( INDIRECT("'"&F$14&"'!A2:E1000"), (INDIRECT("'"&F$14&"'!B2:B1000")=$B5) * (INDIRECT("'"&F$14&"'!C2:C1000")=$C5) ), 5, FALSE )=0, "", VLOOKUP( $A5, _xlfn._xlws.FILTER( INDIRECT("'"&F$14&"'!A2:E1000"), (INDIRECT("'"&F$14&"'!B2:B1000")=$B5) * (INDIRECT("'"&F$14&"'!C2:C1000")=$C5) ), 5, FALSE ) )} | G5: {=IF( VLOOKUP( $A5, _xlfn._xlws.FILTER( INDIRECT("'"&G$14&"'!A2:E1000"), (INDIRECT("'"&G$14&"'!B2:B1000")=$B5) * (INDIRECT("'"&G$14&"'!C2:C1000")=$C5) ), 5, FALSE )=0, "", VLOOKUP( $A5, _xlfn._xlws.FILTER( INDIRECT("'"&G$14&"'!A2:E1000"), (INDIRECT("'"&G$14&"'!B2:B1000")=$B5) * (INDIRECT("'"&G$14&"'!C2:C1000")=$C5) ), 5, FALSE ) )} | H5: {=IF( VLOOKUP( $A5, _xlfn._xlws.FILTER( INDIRECT("'"&H$14&"'!A2:E1000"), (INDIRECT("'"&H$14&"'!B2:B1000")=$B5) * (INDIRECT("'"&H$14&"'!C2:C1000")=$C5) ), 5, FALSE )=0, "", VLOOKUP( $A5, _xlfn._xlws.FILTER( INDIRECT("'"&H$14&"'!A2:E1000"), (INDIRECT("'"&H$14&"'!B2:B1000")=$B5) * (INDIRECT("'"&H$14&"'!C2:C1000")=$C5) ), 5, FALSE ) )} | I5: {=IF( VLOOKUP( $A5, _xlfn._xlws.FILTER( INDIRECT("'"&I$14&"'!A2:E1000"), (INDIRECT("'"&I$14&"'!B2:B1000")=$B5) * (INDIRECT("'"&I$14&"'!C2:C1000")=$C5) ), 5, FALSE )=0, "", VLOOKUP( $A5, _xlfn._xlws.FILTER( INDIRECT("'"&I$14&"'!A2:E1000"), (INDIRECT("'"&I$14&"'!B2:B1000")=$B5) * (INDIRECT("'"&I$14&"'!C2:C1000")=$C5) ), 5, FALSE ) )} | J5: {=IF( VLOOKUP( $A5, _xlfn._xlws.FILTER( INDIRECT("'"&J$14&"'!A2:E1000"), (INDIRECT("'"&J$14&"'!B2:B1000")=$B5) * (INDIRECT("'"&J$14&"'!C2:C1000")=$C5) ), 5, FALSE )=0, "", VLOOKUP( $A5, _xlfn._xlws.FILTER( INDIRECT("'"&J$14&"'!A2:E1000"), (INDIRECT("'"&J$14&"'!B2:B1000")=$B5) * (INDIRECT("'"&J$14&"'!C2:C1000")=$C5) ), 5, FALSE ) )} | K5: {=IF( VLOOKUP( $A5, _xlfn._xlws.FILTER( INDIRECT("'"&K$14&"'!A2:E1000"), (INDIRECT("'"&K$14&"'!B2:B1000")=$B5) * (INDIRECT("'"&K$14&"'!C2:C1000")=$C5) ), 5, FALSE )=0, "", VLOOKUP( $A5, _xlfn._xlws.FILTER( INDIRECT("'"&K$14&"'!A2:E1000"), (INDIRECT("'"&K$14&"'!B2:B1000")=$B5) * (INDIRECT("'"&K$14&"'!C2:C1000")=$C5) ), 5, FALSE ) )} | ... Q5: {=IF( VLOOKUP( $A5, _xlfn._xlws.FILTER( INDIRECT("'"&Q$14&"'!A2:E1000"), (INDIRECT("'"&Q$14&"'!B2:B1000")=$B5) * (INDIRECT("'"&Q$14&"'!C2:C1000")=$C5) ), 5, FALSE )=0, "", VLOOKUP( $A5, _xlfn._xlws.FILTER( INDIRECT("'"&Q$14&"'!A2:E1000"), (INDIRECT("'"&Q$14&"'!B2:B1000")=$B5) * (INDIRECT("'"&Q$14&"'!C2:C1000")=$C5) ), 5, FALSE ) )}
A6: Bianca | B6: Catanduvas | C6: 1 | D6: {=IF( VLOOKUP( $A6, _xlfn._xlws.FILTER( INDIRECT("'"&D$14&"'!A2:E1000"), (INDIRECT("'"&D$14&"'!B2:B1000")=$B6) * (INDIRECT("'"&D$14&"'!C2:C1000")=$C6) ), 5, FALSE )=0, "", VLOOKUP( $A6, _xlfn._xlws.FILTER( INDIRECT("'"&D$14&"'!A2:E1000"), (INDIRECT("'"&D$14&"'!B2:B1000")=$B6) * (INDIRECT("'"&D$14&"'!C2:C1000")=$C6) ), 5, FALSE ) )} | E6: {=IF( VLOOKUP( $A6, _xlfn._xlws.FILTER( INDIRECT("'"&E$14&"'!A2:E1000"), (INDIRECT("'"&E$14&"'!B2:B1000")=$B6) * (INDIRECT("'"&E$14&"'!C2:C1000")=$C6) ), 5, FALSE )=0, "", VLOOKUP( $A6, _xlfn._xlws.FILTER( INDIRECT("'"&E$14&"'!A2:E1000"), (INDIRECT("'"&E$14&"'!B2:B1000")=$B6) * (INDIRECT("'"&E$14&"'!C2:C1000")=$C6) ), 5, FALSE ) )} | F6: {=IF( VLOOKUP( $A6, _xlfn._xlws.FILTER( INDIRECT("'"&F$14&"'!A2:E1000"), (INDIRECT("'"&F$14&"'!B2:B1000")=$B6) * (INDIRECT("'"&F$14&"'!C2:C1000")=$C6) ), 5, FALSE )=0, "", VLOOKUP( $A6, _xlfn._xlws.FILTER( INDIRECT("'"&F$14&"'!A2:E1000"), (INDIRECT("'"&F$14&"'!B2:B1000")=$B6) * (INDIRECT("'"&F$14&"'!C2:C1000")=$C6) ), 5, FALSE ) )} | G6: {=IF( VLOOKUP( $A6, _xlfn._xlws.FILTER( INDIRECT("'"&G$14&"'!A2:E1000"), (INDIRECT("'"&G$14&"'!B2:B1000")=$B6) * (INDIRECT("'"&G$14&"'!C2:C1000")=$C6) ), 5, FALSE )=0, "", VLOOKUP( $A6, _xlfn._xlws.FILTER( INDIRECT("'"&G$14&"'!A2:E1000"), (INDIRECT("'"&G$14&"'!B2:B1000")=$B6) * (INDIRECT("'"&G$14&"'!C2:C1000")=$C6) ), 5, FALSE ) )} | H6: {=IF( VLOOKUP( $A6, _xlfn._xlws.FILTER( INDIRECT("'"&H$14&"'!A2:E1000"), (INDIRECT("'"&H$14&"'!B2:B1000")=$B6) * (INDIRECT("'"&H$14&"'!C2:C1000")=$C6) ), 5, FALSE )=0, "", VLOOKUP( $A6, _xlfn._xlws.FILTER( INDIRECT("'"&H$14&"'!A2:E1000"), (INDIRECT("'"&H$14&"'!B2:B1000")=$B6) * (INDIRECT("'"&H$14&"'!C2:C1000")=$C6) ), 5, FALSE ) )} | I6: {=IF( VLOOKUP( $A6, _xlfn._xlws.FILTER( INDIRECT("'"&I$14&"'!A2:E1000"), (INDIRECT("'"&I$14&"'!B2:B1000")=$B6) * (INDIRECT("'"&I$14&"'!C2:C1000")=$C6) ), 5, FALSE )=0, "", VLOOKUP( $A6, _xlfn._xlws.FILTER( INDIRECT("'"&I$14&"'!A2:E1000"), (INDIRECT("'"&I$14&"'!B2:B1000")=$B6) * (INDIRECT("'"&I$14&"'!C2:C1000")=$C6) ), 5, FALSE ) )} | J6: {=IF( VLOOKUP( $A6, _xlfn._xlws.FILTER( INDIRECT("'"&J$14&"'!A2:E1000"), (INDIRECT("'"&J$14&"'!B2:B1000")=$B6) * (INDIRECT("'"&J$14&"'!C2:C1000")=$C6) ), 5, FALSE )=0, "", VLOOKUP( $A6, _xlfn._xlws.FILTER( INDIRECT("'"&J$14&"'!A2:E1000"), (INDIRECT("'"&J$14&"'!B2:B1000")=$B6) * (INDIRECT("'"&J$14&"'!C2:C1000")=$C6) ), 5, FALSE ) )} | K6: {=IF( VLOOKUP( $A6, _xlfn._xlws.FILTER( INDIRECT("'"&K$14&"'!A2:E1000"), (INDIRECT("'"&K$14&"'!B2:B1000")=$B6) * (INDIRECT("'"&K$14&"'!C2:C1000")=$C6) ), 5, FALSE )=0, "", VLOOKUP( $A6, _xlfn._xlws.FILTER( INDIRECT("'"&K$14&"'!A2:E1000"), (INDIRECT("'"&K$14&"'!B2:B1000")=$B6) * (INDIRECT("'"&K$14&"'!C2:C1000")=$C6) ), 5, FALSE ) )} | ... Q6: {=IF( VLOOKUP( $A6, _xlfn._xlws.FILTER( INDIRECT("'"&Q$14&"'!A2:E1000"), (INDIRECT("'"&Q$14&"'!B2:B1000")=$B6) * (INDIRECT("'"&Q$14&"'!C2:C1000")=$C6) ), 5, FALSE )=0, "", VLOOKUP( $A6, _xlfn._xlws.FILTER( INDIRECT("'"&Q$14&"'!A2:E1000"), (INDIRECT("'"&Q$14&"'!B2:B1000")=$B6) * (INDIRECT("'"&Q$14&"'!C2:C1000")=$C6) ), 5, FALSE ) )}
A7: Bianca | B7: Corbélia | C7: 1 | D7: {=IF( VLOOKUP( $A7, _xlfn._xlws.FILTER( INDIRECT("'"&D$14&"'!A2:E1000"), (INDIRECT("'"&D$14&"'!B2:B1000")=$B7) * (INDIRECT("'"&D$14&"'!C2:C1000")=$C7) ), 5, FALSE )=0, "", VLOOKUP( $A7, _xlfn._xlws.FILTER( INDIRECT("'"&D$14&"'!A2:E1000"), (INDIRECT("'"&D$14&"'!B2:B1000")=$B7) * (INDIRECT("'"&D$14&"'!C2:C1000")=$C7) ), 5, FALSE ) )} | E7: {=IF( VLOOKUP( $A7, _xlfn._xlws.FILTER( INDIRECT("'"&E$14&"'!A2:E1000"), (INDIRECT("'"&E$14&"'!B2:B1000")=$B7) * (INDIRECT("'"&E$14&"'!C2:C1000")=$C7) ), 5, FALSE )=0, "", VLOOKUP( $A7, _xlfn._xlws.FILTER( INDIRECT("'"&E$14&"'!A2:E1000"), (INDIRECT("'"&E$14&"'!B2:B1000")=$B7) * (INDIRECT("'"&E$14&"'!C2:C1000")=$C7) ), 5, FALSE ) )} | F7: {=IF( VLOOKUP( $A7, _xlfn._xlws.FILTER( INDIRECT("'"&F$14&"'!A2:E1000"), (INDIRECT("'"&F$14&"'!B2:B1000")=$B7) * (INDIRECT("'"&F$14&"'!C2:C1000")=$C7) ), 5, FALSE )=0, "", VLOOKUP( $A7, _xlfn._xlws.FILTER( INDIRECT("'"&F$14&"'!A2:E1000"), (INDIRECT("'"&F$14&"'!B2:B1000")=$B7) * (INDIRECT("'"&F$14&"'!C2:C1000")=$C7) ), 5, FALSE ) )} | G7: {=IF( VLOOKUP( $A7, _xlfn._xlws.FILTER( INDIRECT("'"&G$14&"'!A2:E1000"), (INDIRECT("'"&G$14&"'!B2:B1000")=$B7) * (INDIRECT("'"&G$14&"'!C2:C1000")=$C7) ), 5, FALSE )=0, "", VLOOKUP( $A7, _xlfn._xlws.FILTER( INDIRECT("'"&G$14&"'!A2:E1000"), (INDIRECT("'"&G$14&"'!B2:B1000")=$B7) * (INDIRECT("'"&G$14&"'!C2:C1000")=$C7) ), 5, FALSE ) )} | H7: {=IF( VLOOKUP( $A7, _xlfn._xlws.FILTER( INDIRECT("'"&H$14&"'!A2:E1000"), (INDIRECT("'"&H$14&"'!B2:B1000")=$B7) * (INDIRECT("'"&H$14&"'!C2:C1000")=$C7) ), 5, FALSE )=0, "", VLOOKUP( $A7, _xlfn._xlws.FILTER( INDIRECT("'"&H$14&"'!A2:E1000"), (INDIRECT("'"&H$14&"'!B2:B1000")=$B7) * (INDIRECT("'"&H$14&"'!C2:C1000")=$C7) ), 5, FALSE ) )} | I7: {=IF( VLOOKUP( $A7, _xlfn._xlws.FILTER( INDIRECT("'"&I$14&"'!A2:E1000"), (INDIRECT("'"&I$14&"'!B2:B1000")=$B7) * (INDIRECT("'"&I$14&"'!C2:C1000")=$C7) ), 5, FALSE )=0, "", VLOOKUP( $A7, _xlfn._xlws.FILTER( INDIRECT("'"&I$14&"'!A2:E1000"), (INDIRECT("'"&I$14&"'!B2:B1000")=$B7) * (INDIRECT("'"&I$14&"'!C2:C1000")=$C7) ), 5, FALSE ) )} | J7: {=IF( VLOOKUP( $A7, _xlfn._xlws.FILTER( INDIRECT("'"&J$14&"'!A2:E1000"), (INDIRECT("'"&J$14&"'!B2:B1000")=$B7) * (INDIRECT("'"&J$14&"'!C2:C1000")=$C7) ), 5, FALSE )=0, "", VLOOKUP( $A7, _xlfn._xlws.FILTER( INDIRECT("'"&J$14&"'!A2:E1000"), (INDIRECT("'"&J$14&"'!B2:B1000")=$B7) * (INDIRECT("'"&J$14&"'!C2:C1000")=$C7) ), 5, FALSE ) )} | K7: {=IF( VLOOKUP( $A7, _xlfn._xlws.FILTER( INDIRECT("'"&K$14&"'!A2:E1000"), (INDIRECT("'"&K$14&"'!B2:B1000")=$B7) * (INDIRECT("'"&K$14&"'!C2:C1000")=$C7) ), 5, FALSE )=0, "", VLOOKUP( $A7, _xlfn._xlws.FILTER( INDIRECT("'"&K$14&"'!A2:E1000"), (INDIRECT("'"&K$14&"'!B2:B1000")=$B7) * (INDIRECT("'"&K$14&"'!C2:C1000")=$C7) ), 5, FALSE ) )} | ... Q7: {=IF( VLOOKUP( $A7, _xlfn._xlws.FILTER( INDIRECT("'"&Q$14&"'!A2:E1000"), (INDIRECT("'"&Q$14&"'!B2:B1000")=$B7) * (INDIRECT("'"&Q$14&"'!C2:C1000")=$C7) ), 5, FALSE )=0, "", VLOOKUP( $A7, _xlfn._xlws.FILTER( INDIRECT("'"&Q$14&"'!A2:E1000"), (INDIRECT("'"&Q$14&"'!B2:B1000")=$B7) * (INDIRECT("'"&Q$14&"'!C2:C1000")=$C7) ), 5, FALSE ) )}
A8: Bianca | B8: Diamante do Sul | C8: 1 | D8: {=IF( VLOOKUP( $A8, _xlfn._xlws.FILTER( INDIRECT("'"&D$14&"'!A2:E1000"), (INDIRECT("'"&D$14&"'!B2:B1000")=$B8) * (INDIRECT("'"&D$14&"'!C2:C1000")=$C8) ), 5, FALSE )=0, "", VLOOKUP( $A8, _xlfn._xlws.FILTER( INDIRECT("'"&D$14&"'!A2:E1000"), (INDIRECT("'"&D$14&"'!B2:B1000")=$B8) * (INDIRECT("'"&D$14&"'!C2:C1000")=$C8) ), 5, FALSE ) )} | E8: {=IF( VLOOKUP( $A8, _xlfn._xlws.FILTER( INDIRECT("'"&E$14&"'!A2:E1000"), (INDIRECT("'"&E$14&"'!B2:B1000")=$B8) * (INDIRECT("'"&E$14&"'!C2:C1000")=$C8) ), 5, FALSE )=0, "", VLOOKUP( $A8, _xlfn._xlws.FILTER( INDIRECT("'"&E$14&"'!A2:E1000"), (INDIRECT("'"&E$14&"'!B2:B1000")=$B8) * (INDIRECT("'"&E$14&"'!C2:C1000")=$C8) ), 5, FALSE ) )} | F8: {=IF( VLOOKUP( $A8, _xlfn._xlws.FILTER( INDIRECT("'"&F$14&"'!A2:E1000"), (INDIRECT("'"&F$14&"'!B2:B1000")=$B8) * (INDIRECT("'"&F$14&"'!C2:C1000")=$C8) ), 5, FALSE )=0, "", VLOOKUP( $A8, _xlfn._xlws.FILTER( INDIRECT("'"&F$14&"'!A2:E1000"), (INDIRECT("'"&F$14&"'!B2:B1000")=$B8) * (INDIRECT("'"&F$14&"'!C2:C1000")=$C8) ), 5, FALSE ) )} | G8: {=IF( VLOOKUP( $A8, _xlfn._xlws.FILTER( INDIRECT("'"&G$14&"'!A2:E1000"), (INDIRECT("'"&G$14&"'!B2:B1000")=$B8) * (INDIRECT("'"&G$14&"'!C2:C1000")=$C8) ), 5, FALSE )=0, "", VLOOKUP( $A8, _xlfn._xlws.FILTER( INDIRECT("'"&G$14&"'!A2:E1000"), (INDIRECT("'"&G$14&"'!B2:B1000")=$B8) * (INDIRECT("'"&G$14&"'!C2:C1000")=$C8) ), 5, FALSE ) )} | H8: {=IF( VLOOKUP( $A8, _xlfn._xlws.FILTER( INDIRECT("'"&H$14&"'!A2:E1000"), (INDIRECT("'"&H$14&"'!B2:B1000")=$B8) * (INDIRECT("'"&H$14&"'!C2:C1000")=$C8) ), 5, FALSE )=0, "", VLOOKUP( $A8, _xlfn._xlws.FILTER( INDIRECT("'"&H$14&"'!A2:E1000"), (INDIRECT("'"&H$14&"'!B2:B1000")=$B8) * (INDIRECT("'"&H$14&"'!C2:C1000")=$C8) ), 5, FALSE ) )} | I8: {=IF( VLOOKUP( $A8, _xlfn._xlws.FILTER( INDIRECT("'"&I$14&"'!A2:E1000"), (INDIRECT("'"&I$14&"'!B2:B1000")=$B8) * (INDIRECT("'"&I$14&"'!C2:C1000")=$C8) ), 5, FALSE )=0, "", VLOOKUP( $A8, _xlfn._xlws.FILTER( INDIRECT("'"&I$14&"'!A2:E1000"), (INDIRECT("'"&I$14&"'!B2:B1000")=$B8) * (INDIRECT("'"&I$14&"'!C2:C1000")=$C8) ), 5, FALSE ) )} | J8: {=IF( VLOOKUP( $A8, _xlfn._xlws.FILTER( INDIRECT("'"&J$14&"'!A2:E1000"), (INDIRECT("'"&J$14&"'!B2:B1000")=$B8) * (INDIRECT("'"&J$14&"'!C2:C1000")=$C8) ), 5, FALSE )=0, "", VLOOKUP( $A8, _xlfn._xlws.FILTER( INDIRECT("'"&J$14&"'!A2:E1000"), (INDIRECT("'"&J$14&"'!B2:B1000")=$B8) * (INDIRECT("'"&J$14&"'!C2:C1000")=$C8) ), 5, FALSE ) )} | K8: {=IF( VLOOKUP( $A8, _xlfn._xlws.FILTER( INDIRECT("'"&K$14&"'!A2:E1000"), (INDIRECT("'"&K$14&"'!B2:B1000")=$B8) * (INDIRECT("'"&K$14&"'!C2:C1000")=$C8) ), 5, FALSE )=0, "", VLOOKUP( $A8, _xlfn._xlws.FILTER( INDIRECT("'"&K$14&"'!A2:E1000"), (INDIRECT("'"&K$14&"'!B2:B1000")=$B8) * (INDIRECT("'"&K$14&"'!C2:C1000")=$C8) ), 5, FALSE ) )} | ... Q8: {=IF( VLOOKUP( $A8, _xlfn._xlws.FILTER( INDIRECT("'"&Q$14&"'!A2:E1000"), (INDIRECT("'"&Q$14&"'!B2:B1000")=$B8) * (INDIRECT("'"&Q$14&"'!C2:C1000")=$C8) ), 5, FALSE )=0, "", VLOOKUP( $A8, _xlfn._xlws.FILTER( INDIRECT("'"&Q$14&"'!A2:E1000"), (INDIRECT("'"&Q$14&"'!B2:B1000")=$B8) * (INDIRECT("'"&Q$14&"'!C2:C1000")=$C8) ), 5, FALSE ) )}
A9: Bianca | B9: Guaraniacu | C9: 1 | D9: {=IF( VLOOKUP( $A9, _xlfn._xlws.FILTER( INDIRECT("'"&D$14&"'!A2:E1000"), (INDIRECT("'"&D$14&"'!B2:B1000")=$B9) * (INDIRECT("'"&D$14&"'!C2:C1000")=$C9) ), 5, FALSE )=0, "", VLOOKUP( $A9, _xlfn._xlws.FILTER( INDIRECT("'"&D$14&"'!A2:E1000"), (INDIRECT("'"&D$14&"'!B2:B1000")=$B9) * (INDIRECT("'"&D$14&"'!C2:C1000")=$C9) ), 5, FALSE ) )} | E9: {=IF( VLOOKUP( $A9, _xlfn._xlws.FILTER( INDIRECT("'"&E$14&"'!A2:E1000"), (INDIRECT("'"&E$14&"'!B2:B1000")=$B9) * (INDIRECT("'"&E$14&"'!C2:C1000")=$C9) ), 5, FALSE )=0, "", VLOOKUP( $A9, _xlfn._xlws.FILTER( INDIRECT("'"&E$14&"'!A2:E1000"), (INDIRECT("'"&E$14&"'!B2:B1000")=$B9) * (INDIRECT("'"&E$14&"'!C2:C1000")=$C9) ), 5, FALSE ) )} | F9: {=IF( VLOOKUP( $A9, _xlfn._xlws.FILTER( INDIRECT("'"&F$14&"'!A2:E1000"), (INDIRECT("'"&F$14&"'!B2:B1000")=$B9) * (INDIRECT("'"&F$14&"'!C2:C1000")=$C9) ), 5, FALSE )=0, "", VLOOKUP( $A9, _xlfn._xlws.FILTER( INDIRECT("'"&F$14&"'!A2:E1000"), (INDIRECT("'"&F$14&"'!B2:B1000")=$B9) * (INDIRECT("'"&F$14&"'!C2:C1000")=$C9) ), 5, FALSE ) )} | G9: {=IF( VLOOKUP( $A9, _xlfn._xlws.FILTER( INDIRECT("'"&G$14&"'!A2:E1000"), (INDIRECT("'"&G$14&"'!B2:B1000")=$B9) * (INDIRECT("'"&G$14&"'!C2:C1000")=$C9) ), 5, FALSE )=0, "", VLOOKUP( $A9, _xlfn._xlws.FILTER( INDIRECT("'"&G$14&"'!A2:E1000"), (INDIRECT("'"&G$14&"'!B2:B1000")=$B9) * (INDIRECT("'"&G$14&"'!C2:C1000")=$C9) ), 5, FALSE ) )} | H9: {=IF( VLOOKUP( $A9, _xlfn._xlws.FILTER( INDIRECT("'"&H$14&"'!A2:E1000"), (INDIRECT("'"&H$14&"'!B2:B1000")=$B9) * (INDIRECT("'"&H$14&"'!C2:C1000")=$C9) ), 5, FALSE )=0, "", VLOOKUP( $A9, _xlfn._xlws.FILTER( INDIRECT("'"&H$14&"'!A2:E1000"), (INDIRECT("'"&H$14&"'!B2:B1000")=$B9) * (INDIRECT("'"&H$14&"'!C2:C1000")=$C9) ), 5, FALSE ) )} | I9: {=IF( VLOOKUP( $A9, _xlfn._xlws.FILTER( INDIRECT("'"&I$14&"'!A2:E1000"), (INDIRECT("'"&I$14&"'!B2:B1000")=$B9) * (INDIRECT("'"&I$14&"'!C2:C1000")=$C9) ), 5, FALSE )=0, "", VLOOKUP( $A9, _xlfn._xlws.FILTER( INDIRECT("'"&I$14&"'!A2:E1000"), (INDIRECT("'"&I$14&"'!B2:B1000")=$B9) * (INDIRECT("'"&I$14&"'!C2:C1000")=$C9) ), 5, FALSE ) )} | J9: {=IF( VLOOKUP( $A9, _xlfn._xlws.FILTER( INDIRECT("'"&J$14&"'!A2:E1000"), (INDIRECT("'"&J$14&"'!B2:B1000")=$B9) * (INDIRECT("'"&J$14&"'!C2:C1000")=$C9) ), 5, FALSE )=0, "", VLOOKUP( $A9, _xlfn._xlws.FILTER( INDIRECT("'"&J$14&"'!A2:E1000"), (INDIRECT("'"&J$14&"'!B2:B1000")=$B9) * (INDIRECT("'"&J$14&"'!C2:C1000")=$C9) ), 5, FALSE ) )} | K9: {=IF( VLOOKUP( $A9, _xlfn._xlws.FILTER( INDIRECT("'"&K$14&"'!A2:E1000"), (INDIRECT("'"&K$14&"'!B2:B1000")=$B9) * (INDIRECT("'"&K$14&"'!C2:C1000")=$C9) ), 5, FALSE )=0, "", VLOOKUP( $A9, _xlfn._xlws.FILTER( INDIRECT("'"&K$14&"'!A2:E1000"), (INDIRECT("'"&K$14&"'!B2:B1000")=$B9) * (INDIRECT("'"&K$14&"'!C2:C1000")=$C9) ), 5, FALSE ) )} | ... Q9: {=IF( VLOOKUP( $A9, _xlfn._xlws.FILTER( INDIRECT("'"&Q$14&"'!A2:E1000"), (INDIRECT("'"&Q$14&"'!B2:B1000")=$B9) * (INDIRECT("'"&Q$14&"'!C2:C1000")=$C9) ), 5, FALSE )=0, "", VLOOKUP( $A9, _xlfn._xlws.FILTER( INDIRECT("'"&Q$14&"'!A2:E1000"), (INDIRECT("'"&Q$14&"'!B2:B1000")=$B9) * (INDIRECT("'"&Q$14&"'!C2:C1000")=$C9) ), 5, FALSE ) )}
A10: Bianca | B10: Ibema | C10: 1 | D10: {=IF( VLOOKUP( $A10, _xlfn._xlws.FILTER( INDIRECT("'"&D$14&"'!A2:E1000"), (INDIRECT("'"&D$14&"'!B2:B1000")=$B10) * (INDIRECT("'"&D$14&"'!C2:C1000")=$C10) ), 5, FALSE )=0, "", VLOOKUP( $A10, _xlfn._xlws.FILTER( INDIRECT("'"&D$14&"'!A2:E1000"), (INDIRECT("'"&D$14&"'!B2:B1000")=$B10) * (INDIRECT("'"&D$14&"'!C2:C1000")=$C10) ), 5, FALSE ) )} | E10: {=IF( VLOOKUP( $A10, _xlfn._xlws.FILTER( INDIRECT("'"&E$14&"'!A2:E1000"), (INDIRECT("'"&E$14&"'!B2:B1000")=$B10) * (INDIRECT("'"&E$14&"'!C2:C1000")=$C10) ), 5, FALSE )=0, "", VLOOKUP( $A10, _xlfn._xlws.FILTER( INDIRECT("'"&E$14&"'!A2:E1000"), (INDIRECT("'"&E$14&"'!B2:B1000")=$B10) * (INDIRECT("'"&E$14&"'!C2:C1000")=$C10) ), 5, FALSE ) )} | F10: {=IF( VLOOKUP( $A10, _xlfn._xlws.FILTER( INDIRECT("'"&F$14&"'!A2:E1000"), (INDIRECT("'"&F$14&"'!B2:B1000")=$B10) * (INDIRECT("'"&F$14&"'!C2:C1000")=$C10) ), 5, FALSE )=0, "", VLOOKUP( $A10, _xlfn._xlws.FILTER( INDIRECT("'"&F$14&"'!A2:E1000"), (INDIRECT("'"&F$14&"'!B2:B1000")=$B10) * (INDIRECT("'"&F$14&"'!C2:C1000")=$C10) ), 5, FALSE ) )} | G10: {=IF( VLOOKUP( $A10, _xlfn._xlws.FILTER( INDIRECT("'"&G$14&"'!A2:E1000"), (INDIRECT("'"&G$14&"'!B2:B1000")=$B10) * (INDIRECT("'"&G$14&"'!C2:C1000")=$C10) ), 5, FALSE )=0, "", VLOOKUP( $A10, _xlfn._xlws.FILTER( INDIRECT("'"&G$14&"'!A2:E1000"), (INDIRECT("'"&G$14&"'!B2:B1000")=$B10) * (INDIRECT("'"&G$14&"'!C2:C1000")=$C10) ), 5, FALSE ) )} | H10: {=IF( VLOOKUP( $A10, _xlfn._xlws.FILTER( INDIRECT("'"&H$14&"'!A2:E1000"), (INDIRECT("'"&H$14&"'!B2:B1000")=$B10) * (INDIRECT("'"&H$14&"'!C2:C1000")=$C10) ), 5, FALSE )=0, "", VLOOKUP( $A10, _xlfn._xlws.FILTER( INDIRECT("'"&H$14&"'!A2:E1000"), (INDIRECT("'"&H$14&"'!B2:B1000")=$B10) * (INDIRECT("'"&H$14&"'!C2:C1000")=$C10) ), 5, FALSE ) )} | I10: {=IF( VLOOKUP( $A10, _xlfn._xlws.FILTER( INDIRECT("'"&I$14&"'!A2:E1000"), (INDIRECT("'"&I$14&"'!B2:B1000")=$B10) * (INDIRECT("'"&I$14&"'!C2:C1000")=$C10) ), 5, FALSE )=0, "", VLOOKUP( $A10, _xlfn._xlws.FILTER( INDIRECT("'"&I$14&"'!A2:E1000"), (INDIRECT("'"&I$14&"'!B2:B1000")=$B10) * (INDIRECT("'"&I$14&"'!C2:C1000")=$C10) ), 5, FALSE ) )} | J10: {=IF( VLOOKUP( $A10, _xlfn._xlws.FILTER( INDIRECT("'"&J$14&"'!A2:E1000"), (INDIRECT("'"&J$14&"'!B2:B1000")=$B10) * (INDIRECT("'"&J$14&"'!C2:C1000")=$C10) ), 5, FALSE )=0, "", VLOOKUP( $A10, _xlfn._xlws.FILTER( INDIRECT("'"&J$14&"'!A2:E1000"), (INDIRECT("'"&J$14&"'!B2:B1000")=$B10) * (INDIRECT("'"&J$14&"'!C2:C1000")=$C10) ), 5, FALSE ) )} | K10: {=IF( VLOOKUP( $A10, _xlfn._xlws.FILTER( INDIRECT("'"&K$14&"'!A2:E1000"), (INDIRECT("'"&K$14&"'!B2:B1000")=$B10) * (INDIRECT("'"&K$14&"'!C2:C1000")=$C10) ), 5, FALSE )=0, "", VLOOKUP( $A10, _xlfn._xlws.FILTER( INDIRECT("'"&K$14&"'!A2:E1000"), (INDIRECT("'"&K$14&"'!B2:B1000")=$B10) * (INDIRECT("'"&K$14&"'!C2:C1000")=$C10) ), 5, FALSE ) )} | ... Q10: {=IF( VLOOKUP( $A10, _xlfn._xlws.FILTER( INDIRECT("'"&Q$14&"'!A2:E1000"), (INDIRECT("'"&Q$14&"'!B2:B1000")=$B10) * (INDIRECT("'"&Q$14&"'!C2:C1000")=$C10) ), 5, FALSE )=0, "", VLOOKUP( $A10, _xlfn._xlws.FILTER( INDIRECT("'"&Q$14&"'!A2:E1000"), (INDIRECT("'"&Q$14&"'!B2:B1000")=$B10) * (INDIRECT("'"&Q$14&"'!C2:C1000")=$C10) ), 5, FALSE ) )}
A11: Bianca | B11: Iguatu | C11: 1 | D11: {=IF( VLOOKUP( $A11, _xlfn._xlws.FILTER( INDIRECT("'"&D$14&"'!A2:E1000"), (INDIRECT("'"&D$14&"'!B2:B1000")=$B11) * (INDIRECT("'"&D$14&"'!C2:C1000")=$C11) ), 5, FALSE )=0, "", VLOOKUP( $A11, _xlfn._xlws.FILTER( INDIRECT("'"&D$14&"'!A2:E1000"), (INDIRECT("'"&D$14&"'!B2:B1000")=$B11) * (INDIRECT("'"&D$14&"'!C2:C1000")=$C11) ), 5, FALSE ) )} | E11: {=IF( VLOOKUP( $A11, _xlfn._xlws.FILTER( INDIRECT("'"&E$14&"'!A2:E1000"), (INDIRECT("'"&E$14&"'!B2:B1000")=$B11) * (INDIRECT("'"&E$14&"'!C2:C1000")=$C11) ), 5, FALSE )=0, "", VLOOKUP( $A11, _xlfn._xlws.FILTER( INDIRECT("'"&E$14&"'!A2:E1000"), (INDIRECT("'"&E$14&"'!B2:B1000")=$B11) * (INDIRECT("'"&E$14&"'!C2:C1000")=$C11) ), 5, FALSE ) )} | F11: {=IF( VLOOKUP( $A11, _xlfn._xlws.FILTER( INDIRECT("'"&F$14&"'!A2:E1000"), (INDIRECT("'"&F$14&"'!B2:B1000")=$B11) * (INDIRECT("'"&F$14&"'!C2:C1000")=$C11) ), 5, FALSE )=0, "", VLOOKUP( $A11, _xlfn._xlws.FILTER( INDIRECT("'"&F$14&"'!A2:E1000"), (INDIRECT("'"&F$14&"'!B2:B1000")=$B11) * (INDIRECT("'"&F$14&"'!C2:C1000")=$C11) ), 5, FALSE ) )} | G11: {=IF( VLOOKUP( $A11, _xlfn._xlws.FILTER( INDIRECT("'"&G$14&"'!A2:E1000"), (INDIRECT("'"&G$14&"'!B2:B1000")=$B11) * (INDIRECT("'"&G$14&"'!C2:C1000")=$C11) ), 5, FALSE )=0, "", VLOOKUP( $A11, _xlfn._xlws.FILTER( INDIRECT("'"&G$14&"'!A2:E1000"), (INDIRECT("'"&G$14&"'!B2:B1000")=$B11) * (INDIRECT("'"&G$14&"'!C2:C1000")=$C11) ), 5, FALSE ) )} | H11: {=IF( VLOOKUP( $A11, _xlfn._xlws.FILTER( INDIRECT("'"&H$14&"'!A2:E1000"), (INDIRECT("'"&H$14&"'!B2:B1000")=$B11) * (INDIRECT("'"&H$14&"'!C2:C1000")=$C11) ), 5, FALSE )=0, "", VLOOKUP( $A11, _xlfn._xlws.FILTER( INDIRECT("'"&H$14&"'!A2:E1000"), (INDIRECT("'"&H$14&"'!B2:B1000")=$B11) * (INDIRECT("'"&H$14&"'!C2:C1000")=$C11) ), 5, FALSE ) )} | I11: {=IF( VLOOKUP( $A11, _xlfn._xlws.FILTER( INDIRECT("'"&I$14&"'!A2:E1000"), (INDIRECT("'"&I$14&"'!B2:B1000")=$B11) * (INDIRECT("'"&I$14&"'!C2:C1000")=$C11) ), 5, FALSE )=0, "", VLOOKUP( $A11, _xlfn._xlws.FILTER( INDIRECT("'"&I$14&"'!A2:E1000"), (INDIRECT("'"&I$14&"'!B2:B1000")=$B11) * (INDIRECT("'"&I$14&"'!C2:C1000")=$C11) ), 5, FALSE ) )} | J11: {=IF( VLOOKUP( $A11, _xlfn._xlws.FILTER( INDIRECT("'"&J$14&"'!A2:E1000"), (INDIRECT("'"&J$14&"'!B2:B1000")=$B11) * (INDIRECT("'"&J$14&"'!C2:C1000")=$C11) ), 5, FALSE )=0, "", VLOOKUP( $A11, _xlfn._xlws.FILTER( INDIRECT("'"&J$14&"'!A2:E1000"), (INDIRECT("'"&J$14&"'!B2:B1000")=$B11) * (INDIRECT("'"&J$14&"'!C2:C1000")=$C11) ), 5, FALSE ) )} | K11: {=IF( VLOOKUP( $A11, _xlfn._xlws.FILTER( INDIRECT("'"&K$14&"'!A2:E1000"), (INDIRECT("'"&K$14&"'!B2:B1000")=$B11) * (INDIRECT("'"&K$14&"'!C2:C1000")=$C11) ), 5, FALSE )=0, "", VLOOKUP( $A11, _xlfn._xlws.FILTER( INDIRECT("'"&K$14&"'!A2:E1000"), (INDIRECT("'"&K$14&"'!B2:B1000")=$B11) * (INDIRECT("'"&K$14&"'!C2:C1000")=$C11) ), 5, FALSE ) )} | ... Q11: {=IF( VLOOKUP( $A11, _xlfn._xlws.FILTER( INDIRECT("'"&Q$14&"'!A2:E1000"), (INDIRECT("'"&Q$14&"'!B2:B1000")=$B11) * (INDIRECT("'"&Q$14&"'!C2:C1000")=$C11) ), 5, FALSE )=0, "", VLOOKUP( $A11, _xlfn._xlws.FILTER( INDIRECT("'"&Q$14&"'!A2:E1000"), (INDIRECT("'"&Q$14&"'!B2:B1000")=$B11) * (INDIRECT("'"&Q$14&"'!C2:C1000")=$C11) ), 5, FALSE ) )}
A12: Bianca | B12: Tres Barras do Parana | C12: 1 | D12: {=IF( VLOOKUP( $A12, _xlfn._xlws.FILTER( INDIRECT("'"&D$14&"'!A2:E1000"), (INDIRECT("'"&D$14&"'!B2:B1000")=$B12) * (INDIRECT("'"&D$14&"'!C2:C1000")=$C12) ), 5, FALSE )=0, "", VLOOKUP( $A12, _xlfn._xlws.FILTER( INDIRECT("'"&D$14&"'!A2:E1000"), (INDIRECT("'"&D$14&"'!B2:B1000")=$B12) * (INDIRECT("'"&D$14&"'!C2:C1000")=$C12) ), 5, FALSE ) )} | E12: {=IF( VLOOKUP( $A12, _xlfn._xlws.FILTER( INDIRECT("'"&E$14&"'!A2:E1000"), (INDIRECT("'"&E$14&"'!B2:B1000")=$B12) * (INDIRECT("'"&E$14&"'!C2:C1000")=$C12) ), 5, FALSE )=0, "", VLOOKUP( $A12, _xlfn._xlws.FILTER( INDIRECT("'"&E$14&"'!A2:E1000"), (INDIRECT("'"&E$14&"'!B2:B1000")=$B12) * (INDIRECT("'"&E$14&"'!C2:C1000")=$C12) ), 5, FALSE ) )} | F12: {=IF( VLOOKUP( $A12, _xlfn._xlws.FILTER( INDIRECT("'"&F$14&"'!A2:E1000"), (INDIRECT("'"&F$14&"'!B2:B1000")=$B12) * (INDIRECT("'"&F$14&"'!C2:C1000")=$C12) ), 5, FALSE )=0, "", VLOOKUP( $A12, _xlfn._xlws.FILTER( INDIRECT("'"&F$14&"'!A2:E1000"), (INDIRECT("'"&F$14&"'!B2:B1000")=$B12) * (INDIRECT("'"&F$14&"'!C2:C1000")=$C12) ), 5, FALSE ) )} | G12: {=IF( VLOOKUP( $A12, _xlfn._xlws.FILTER( INDIRECT("'"&G$14&"'!A2:E1000"), (INDIRECT("'"&G$14&"'!B2:B1000")=$B12) * (INDIRECT("'"&G$14&"'!C2:C1000")=$C12) ), 5, FALSE )=0, "", VLOOKUP( $A12, _xlfn._xlws.FILTER( INDIRECT("'"&G$14&"'!A2:E1000"), (INDIRECT("'"&G$14&"'!B2:B1000")=$B12) * (INDIRECT("'"&G$14&"'!C2:C1000")=$C12) ), 5, FALSE ) )} | H12: {=IF( VLOOKUP( $A12, _xlfn._xlws.FILTER( INDIRECT("'"&H$14&"'!A2:E1000"), (INDIRECT("'"&H$14&"'!B2:B1000")=$B12) * (INDIRECT("'"&H$14&"'!C2:C1000")=$C12) ), 5, FALSE )=0, "", VLOOKUP( $A12, _xlfn._xlws.FILTER( INDIRECT("'"&H$14&"'!A2:E1000"), (INDIRECT("'"&H$14&"'!B2:B1000")=$B12) * (INDIRECT("'"&H$14&"'!C2:C1000")=$C12) ), 5, FALSE ) )} | I12: {=IF( VLOOKUP( $A12, _xlfn._xlws.FILTER( INDIRECT("'"&I$14&"'!A2:E1000"), (INDIRECT("'"&I$14&"'!B2:B1000")=$B12) * (INDIRECT("'"&I$14&"'!C2:C1000")=$C12) ), 5, FALSE )=0, "", VLOOKUP( $A12, _xlfn._xlws.FILTER( INDIRECT("'"&I$14&"'!A2:E1000"), (INDIRECT("'"&I$14&"'!B2:B1000")=$B12) * (INDIRECT("'"&I$14&"'!C2:C1000")=$C12) ), 5, FALSE ) )} | J12: {=IF( VLOOKUP( $A12, _xlfn._xlws.FILTER( INDIRECT("'"&J$14&"'!A2:E1000"), (INDIRECT("'"&J$14&"'!B2:B1000")=$B12) * (INDIRECT("'"&J$14&"'!C2:C1000")=$C12) ), 5, FALSE )=0, "", VLOOKUP( $A12, _xlfn._xlws.FILTER( INDIRECT("'"&J$14&"'!A2:E1000"), (INDIRECT("'"&J$14&"'!B2:B1000")=$B12) * (INDIRECT("'"&J$14&"'!C2:C1000")=$C12) ), 5, FALSE ) )} | K12: {=IF( VLOOKUP( $A12, _xlfn._xlws.FILTER( INDIRECT("'"&K$14&"'!A2:E1000"), (INDIRECT("'"&K$14&"'!B2:B1000")=$B12) * (INDIRECT("'"&K$14&"'!C2:C1000")=$C12) ), 5, FALSE )=0, "", VLOOKUP( $A12, _xlfn._xlws.FILTER( INDIRECT("'"&K$14&"'!A2:E1000"), (INDIRECT("'"&K$14&"'!B2:B1000")=$B12) * (INDIRECT("'"&K$14&"'!C2:C1000")=$C12) ), 5, FALSE ) )} | ... Q12: {=IF( VLOOKUP( $A12, _xlfn._xlws.FILTER( INDIRECT("'"&Q$14&"'!A2:E1000"), (INDIRECT("'"&Q$14&"'!B2:B1000")=$B12) * (INDIRECT("'"&Q$14&"'!C2:C1000")=$C12) ), 5, FALSE )=0, "", VLOOKUP( $A12, _xlfn._xlws.FILTER( INDIRECT("'"&Q$14&"'!A2:E1000"), (INDIRECT("'"&Q$14&"'!B2:B1000")=$B12) * (INDIRECT("'"&Q$14&"'!C2:C1000")=$C12) ), 5, FALSE ) )}
A14: Regional | B14: Municípios | C14: UVR | D14: 11.24 | E14: 12.24 | F14: 01.25 | G14: 02.25 | H14: 03.25 | I14: 04.25 | J14: 05.25 | K14: 06.25 | L14: 07.25 | M14: 08.25 | N14: 09.25 | O14: 10.25 | P14: 11.25 | Q14: 12.25
A15: Gabriel | B15: Altônia | C15: 1 | D15: {=IF( VLOOKUP( $A15, _xlfn._xlws.FILTER( INDIRECT("'"&D$14&"'!A2:E1000"), (INDIRECT("'"&D$14&"'!B2:B1000")=$B15) * (INDIRECT("'"&D$14&"'!C2:C1000")=$C15) ), 5, FALSE )=0, "", VLOOKUP( $A15, _xlfn._xlws.FILTER( INDIRECT("'"&D$14&"'!A2:E1000"), (INDIRECT("'"&D$14&"'!B2:B1000")=$B15) * (INDIRECT("'"&D$14&"'!C2:C1000")=$C15) ), 5, FALSE ) )} | E15: {=IF( VLOOKUP( $A15, _xlfn._xlws.FILTER( INDIRECT("'"&E$14&"'!A2:E1000"), (INDIRECT("'"&E$14&"'!B2:B1000")=$B15) * (INDIRECT("'"&E$14&"'!C2:C1000")=$C15) ), 5, FALSE )=0, "", VLOOKUP( $A15, _xlfn._xlws.FILTER( INDIRECT("'"&E$14&"'!A2:E1000"), (INDIRECT("'"&E$14&"'!B2:B1000")=$B15) * (INDIRECT("'"&E$14&"'!C2:C1000")=$C15) ), 5, FALSE ) )} | F15: {=IF( VLOOKUP( $A15, _xlfn._xlws.FILTER( INDIRECT("'"&F$14&"'!A2:E1000"), (INDIRECT("'"&F$14&"'!B2:B1000")=$B15) * (INDIRECT("'"&F$14&"'!C2:C1000")=$C15) ), 5, FALSE )=0, "", VLOOKUP( $A15, _xlfn._xlws.FILTER( INDIRECT("'"&F$14&"'!A2:E1000"), (INDIRECT("'"&F$14&"'!B2:B1000")=$B15) * (INDIRECT("'"&F$14&"'!C2:C1000")=$C15) ), 5, FALSE ) )} | G15: {=IF( VLOOKUP( $A15, _xlfn._xlws.FILTER( INDIRECT("'"&G$14&"'!A2:E1000"), (INDIRECT("'"&G$14&"'!B2:B1000")=$B15) * (INDIRECT("'"&G$14&"'!C2:C1000")=$C15) ), 5, FALSE )=0, "", VLOOKUP( $A15, _xlfn._xlws.FILTER( INDIRECT("'"&G$14&"'!A2:E1000"), (INDIRECT("'"&G$14&"'!B2:B1000")=$B15) * (INDIRECT("'"&G$14&"'!C2:C1000")=$C15) ), 5, FALSE ) )} | H15: {=IF( VLOOKUP( $A15, _xlfn._xlws.FILTER( INDIRECT("'"&H$14&"'!A2:E1000"), (INDIRECT("'"&H$14&"'!B2:B1000")=$B15) * (INDIRECT("'"&H$14&"'!C2:C1000")=$C15) ), 5, FALSE )=0, "", VLOOKUP( $A15, _xlfn._xlws.FILTER( INDIRECT("'"&H$14&"'!A2:E1000"), (INDIRECT("'"&H$14&"'!B2:B1000")=$B15) * (INDIRECT("'"&H$14&"'!C2:C1000")=$C15) ), 5, FALSE ) )} | I15: {=IF( VLOOKUP( $A15, _xlfn._xlws.FILTER( INDIRECT("'"&I$14&"'!A2:E1000"), (INDIRECT("'"&I$14&"'!B2:B1000")=$B15) * (INDIRECT("'"&I$14&"'!C2:C1000")=$C15) ), 5, FALSE )=0, "", VLOOKUP( $A15, _xlfn._xlws.FILTER( INDIRECT("'"&I$14&"'!A2:E1000"), (INDIRECT("'"&I$14&"'!B2:B1000")=$B15) * (INDIRECT("'"&I$14&"'!C2:C1000")=$C15) ), 5, FALSE ) )} | J15: {=IF( VLOOKUP( $A15, _xlfn._xlws.FILTER( INDIRECT("'"&J$14&"'!A2:E1000"), (INDIRECT("'"&J$14&"'!B2:B1000")=$B15) * (INDIRECT("'"&J$14&"'!C2:C1000")=$C15) ), 5, FALSE )=0, "", VLOOKUP( $A15, _xlfn._xlws.FILTER( INDIRECT("'"&J$14&"'!A2:E1000"), (INDIRECT("'"&J$14&"'!B2:B1000")=$B15) * (INDIRECT("'"&J$14&"'!C2:C1000")=$C15) ), 5, FALSE ) )} | K15: {=IF( VLOOKUP( $A15, _xlfn._xlws.FILTER( INDIRECT("'"&K$14&"'!A2:E1000"), (INDIRECT("'"&K$14&"'!B2:B1000")=$B15) * (INDIRECT("'"&K$14&"'!C2:C1000")=$C15) ), 5, FALSE )=0, "", VLOOKUP( $A15, _xlfn._xlws.FILTER( INDIRECT("'"&K$14&"'!A2:E1000"), (INDIRECT("'"&K$14&"'!B2:B1000")=$B15) * (INDIRECT("'"&K$14&"'!C2:C1000")=$C15) ), 5, FALSE ) )} | ... Q15: {=IF( VLOOKUP( $A15, _xlfn._xlws.FILTER( INDIRECT("'"&Q$14&"'!A2:E1000"), (INDIRECT("'"&Q$14&"'!B2:B1000")=$B15) * (INDIRECT("'"&Q$14&"'!C2:C1000")=$C15) ), 5, FALSE )=0, "", VLOOKUP( $A15, _xlfn._xlws.FILTER( INDIRECT("'"&Q$14&"'!A2:E1000"), (INDIRECT("'"&Q$14&"'!B2:B1000")=$B15) * (INDIRECT("'"&Q$14&"'!C2:C1000")=$C15) ), 5, FALSE ) )}
A16: Gabriel | B16: Francisco Alves | C16: 1 | D16: {=IF( VLOOKUP( $A16, _xlfn._xlws.FILTER( INDIRECT("'"&D$14&"'!A2:E1000"), (INDIRECT("'"&D$14&"'!B2:B1000")=$B16) * (INDIRECT("'"&D$14&"'!C2:C1000")=$C16) ), 5, FALSE )=0, "", VLOOKUP( $A16, _xlfn._xlws.FILTER( INDIRECT("'"&D$14&"'!A2:E1000"), (INDIRECT("'"&D$14&"'!B2:B1000")=$B16) * (INDIRECT("'"&D$14&"'!C2:C1000")=$C16) ), 5, FALSE ) )} | E16: {=IF( VLOOKUP( $A16, _xlfn._xlws.FILTER( INDIRECT("'"&E$14&"'!A2:E1000"), (INDIRECT("'"&E$14&"'!B2:B1000")=$B16) * (INDIRECT("'"&E$14&"'!C2:C1000")=$C16) ), 5, FALSE )=0, "", VLOOKUP( $A16, _xlfn._xlws.FILTER( INDIRECT("'"&E$14&"'!A2:E1000"), (INDIRECT("'"&E$14&"'!B2:B1000")=$B16) * (INDIRECT("'"&E$14&"'!C2:C1000")=$C16) ), 5, FALSE ) )} | F16: {=IF( VLOOKUP( $A16, _xlfn._xlws.FILTER( INDIRECT("'"&F$14&"'!A2:E1000"), (INDIRECT("'"&F$14&"'!B2:B1000")=$B16) * (INDIRECT("'"&F$14&"'!C2:C1000")=$C16) ), 5, FALSE )=0, "", VLOOKUP( $A16, _xlfn._xlws.FILTER( INDIRECT("'"&F$14&"'!A2:E1000"), (INDIRECT("'"&F$14&"'!B2:B1000")=$B16) * (INDIRECT("'"&F$14&"'!C2:C1000")=$C16) ), 5, FALSE ) )} | G16: {=IF( VLOOKUP( $A16, _xlfn._xlws.FILTER( INDIRECT("'"&G$14&"'!A2:E1000"), (INDIRECT("'"&G$14&"'!B2:B1000")=$B16) * (INDIRECT("'"&G$14&"'!C2:C1000")=$C16) ), 5, FALSE )=0, "", VLOOKUP( $A16, _xlfn._xlws.FILTER( INDIRECT("'"&G$14&"'!A2:E1000"), (INDIRECT("'"&G$14&"'!B2:B1000")=$B16) * (INDIRECT("'"&G$14&"'!C2:C1000")=$C16) ), 5, FALSE ) )} | H16: {=IF( VLOOKUP( $A16, _xlfn._xlws.FILTER( INDIRECT("'"&H$14&"'!A2:E1000"), (INDIRECT("'"&H$14&"'!B2:B1000")=$B16) * (INDIRECT("'"&H$14&"'!C2:C1000")=$C16) ), 5, FALSE )=0, "", VLOOKUP( $A16, _xlfn._xlws.FILTER( INDIRECT("'"&H$14&"'!A2:E1000"), (INDIRECT("'"&H$14&"'!B2:B1000")=$B16) * (INDIRECT("'"&H$14&"'!C2:C1000")=$C16) ), 5, FALSE ) )} | I16: {=IF( VLOOKUP( $A16, _xlfn._xlws.FILTER( INDIRECT("'"&I$14&"'!A2:E1000"), (INDIRECT("'"&I$14&"'!B2:B1000")=$B16) * (INDIRECT("'"&I$14&"'!C2:C1000")=$C16) ), 5, FALSE )=0, "", VLOOKUP( $A16, _xlfn._xlws.FILTER( INDIRECT("'"&I$14&"'!A2:E1000"), (INDIRECT("'"&I$14&"'!B2:B1000")=$B16) * (INDIRECT("'"&I$14&"'!C2:C1000")=$C16) ), 5, FALSE ) )} | J16: {=IF( VLOOKUP( $A16, _xlfn._xlws.FILTER( INDIRECT("'"&J$14&"'!A2:E1000"), (INDIRECT("'"&J$14&"'!B2:B1000")=$B16) * (INDIRECT("'"&J$14&"'!C2:C1000")=$C16) ), 5, FALSE )=0, "", VLOOKUP( $A16, _xlfn._xlws.FILTER( INDIRECT("'"&J$14&"'!A2:E1000"), (INDIRECT("'"&J$14&"'!B2:B1000")=$B16) * (INDIRECT("'"&J$14&"'!C2:C1000")=$C16) ), 5, FALSE ) )} | K16: {=IF( VLOOKUP( $A16, _xlfn._xlws.FILTER( INDIRECT("'"&K$14&"'!A2:E1000"), (INDIRECT("'"&K$14&"'!B2:B1000")=$B16) * (INDIRECT("'"&K$14&"'!C2:C1000")=$C16) ), 5, FALSE )=0, "", VLOOKUP( $A16, _xlfn._xlws.FILTER( INDIRECT("'"&K$14&"'!A2:E1000"), (INDIRECT("'"&K$14&"'!B2:B1000")=$B16) * (INDIRECT("'"&K$14&"'!C2:C1000")=$C16) ), 5, FALSE ) )} | ... Q16: {=IF( VLOOKUP( $A16, _xlfn._xlws.FILTER( INDIRECT("'"&Q$14&"'!A2:E1000"), (INDIRECT("'"&Q$14&"'!B2:B1000")=$B16) * (INDIRECT("'"&Q$14&"'!C2:C1000")=$C16) ), 5, FALSE )=0, "", VLOOKUP( $A16, _xlfn._xlws.FILTER( INDIRECT("'"&Q$14&"'!A2:E1000"), (INDIRECT("'"&Q$14&"'!B2:B1000")=$B16) * (INDIRECT("'"&Q$14&"'!C2:C1000")=$C16) ), 5, FALSE ) )}
A17: Gabriel | B17: Guaira | C17: 1 | D17: {=IF( VLOOKUP( $A17, _xlfn._xlws.FILTER( INDIRECT("'"&D$14&"'!A2:E1000"), (INDIRECT("'"&D$14&"'!B2:B1000")=$B17) * (INDIRECT("'"&D$14&"'!C2:C1000")=$C17) ), 5, FALSE )=0, "", VLOOKUP( $A17, _xlfn._xlws.FILTER( INDIRECT("'"&D$14&"'!A2:E1000"), (INDIRECT("'"&D$14&"'!B2:B1000")=$B17) * (INDIRECT("'"&D$14&"'!C2:C1000")=$C17) ), 5, FALSE ) )} | E17: {=IF( VLOOKUP( $A17, _xlfn._xlws.FILTER( INDIRECT("'"&E$14&"'!A2:E1000"), (INDIRECT("'"&E$14&"'!B2:B1000")=$B17) * (INDIRECT("'"&E$14&"'!C2:C1000")=$C17) ), 5, FALSE )=0, "", VLOOKUP( $A17, _xlfn._xlws.FILTER( INDIRECT("'"&E$14&"'!A2:E1000"), (INDIRECT("'"&E$14&"'!B2:B1000")=$B17) * (INDIRECT("'"&E$14&"'!C2:C1000")=$C17) ), 5, FALSE ) )} | F17: {=IF( VLOOKUP( $A17, _xlfn._xlws.FILTER( INDIRECT("'"&F$14&"'!A2:E1000"), (INDIRECT("'"&F$14&"'!B2:B1000")=$B17) * (INDIRECT("'"&F$14&"'!C2:C1000")=$C17) ), 5, FALSE )=0, "", VLOOKUP( $A17, _xlfn._xlws.FILTER( INDIRECT("'"&F$14&"'!A2:E1000"), (INDIRECT("'"&F$14&"'!B2:B1000")=$B17) * (INDIRECT("'"&F$14&"'!C2:C1000")=$C17) ), 5, FALSE ) )} | G17: {=IF( VLOOKUP( $A17, _xlfn._xlws.FILTER( INDIRECT("'"&G$14&"'!A2:E1000"), (INDIRECT("'"&G$14&"'!B2:B1000")=$B17) * (INDIRECT("'"&G$14&"'!C2:C1000")=$C17) ), 5, FALSE )=0, "", VLOOKUP( $A17, _xlfn._xlws.FILTER( INDIRECT("'"&G$14&"'!A2:E1000"), (INDIRECT("'"&G$14&"'!B2:B1000")=$B17) * (INDIRECT("'"&G$14&"'!C2:C1000")=$C17) ), 5, FALSE ) )} | H17: {=IF( VLOOKUP( $A17, _xlfn._xlws.FILTER( INDIRECT("'"&H$14&"'!A2:E1000"), (INDIRECT("'"&H$14&"'!B2:B1000")=$B17) * (INDIRECT("'"&H$14&"'!C2:C1000")=$C17) ), 5, FALSE )=0, "", VLOOKUP( $A17, _xlfn._xlws.FILTER( INDIRECT("'"&H$14&"'!A2:E1000"), (INDIRECT("'"&H$14&"'!B2:B1000")=$B17) * (INDIRECT("'"&H$14&"'!C2:C1000")=$C17) ), 5, FALSE ) )} | I17: {=IF( VLOOKUP( $A17, _xlfn._xlws.FILTER( INDIRECT("'"&I$14&"'!A2:E1000"), (INDIRECT("'"&I$14&"'!B2:B1000")=$B17) * (INDIRECT("'"&I$14&"'!C2:C1000")=$C17) ), 5, FALSE )=0, "", VLOOKUP( $A17, _xlfn._xlws.FILTER( INDIRECT("'"&I$14&"'!A2:E1000"), (INDIRECT("'"&I$14&"'!B2:B1000")=$B17) * (INDIRECT("'"&I$14&"'!C2:C1000")=$C17) ), 5, FALSE ) )} | J17: {=IF( VLOOKUP( $A17, _xlfn._xlws.FILTER( INDIRECT("'"&J$14&"'!A2:E1000"), (INDIRECT("'"&J$14&"'!B2:B1000")=$B17) * (INDIRECT("'"&J$14&"'!C2:C1000")=$C17) ), 5, FALSE )=0, "", VLOOKUP( $A17, _xlfn._xlws.FILTER( INDIRECT("'"&J$14&"'!A2:E1000"), (INDIRECT("'"&J$14&"'!B2:B1000")=$B17) * (INDIRECT("'"&J$14&"'!C2:C1000")=$C17) ), 5, FALSE ) )} | K17: {=IF( VLOOKUP( $A17, _xlfn._xlws.FILTER( INDIRECT("'"&K$14&"'!A2:E1000"), (INDIRECT("'"&K$14&"'!B2:B1000")=$B17) * (INDIRECT("'"&K$14&"'!C2:C1000")=$C17) ), 5, FALSE )=0, "", VLOOKUP( $A17, _xlfn._xlws.FILTER( INDIRECT("'"&K$14&"'!A2:E1000"), (INDIRECT("'"&K$14&"'!B2:B1000")=$B17) * (INDIRECT("'"&K$14&"'!C2:C1000")=$C17) ), 5, FALSE ) )} | ... Q17: {=IF( VLOOKUP( $A17, _xlfn._xlws.FILTER( INDIRECT("'"&Q$14&"'!A2:E1000"), (INDIRECT("'"&Q$14&"'!B2:B1000")=$B17) * (INDIRECT("'"&Q$14&"'!C2:C1000")=$C17) ), 5, FALSE )=0, "", VLOOKUP( $A17, _xlfn._xlws.FILTER( INDIRECT("'"&Q$14&"'!A2:E1000"), (INDIRECT("'"&Q$14&"'!B2:B1000")=$B17) * (INDIRECT("'"&Q$14&"'!C2:C1000")=$C17) ), 5, FALSE ) )}
A18: Gabriel | B18: Mercedes | C18: 1 | D18: {=IF( VLOOKUP( $A18, _xlfn._xlws.FILTER( INDIRECT("'"&D$14&"'!A2:E1000"), (INDIRECT("'"&D$14&"'!B2:B1000")=$B18) * (INDIRECT("'"&D$14&"'!C2:C1000")=$C18) ), 5, FALSE )=0, "", VLOOKUP( $A18, _xlfn._xlws.FILTER( INDIRECT("'"&D$14&"'!A2:E1000"), (INDIRECT("'"&D$14&"'!B2:B1000")=$B18) * (INDIRECT("'"&D$14&"'!C2:C1000")=$C18) ), 5, FALSE ) )} | E18: {=IF( VLOOKUP( $A18, _xlfn._xlws.FILTER( INDIRECT("'"&E$14&"'!A2:E1000"), (INDIRECT("'"&E$14&"'!B2:B1000")=$B18) * (INDIRECT("'"&E$14&"'!C2:C1000")=$C18) ), 5, FALSE )=0, "", VLOOKUP( $A18, _xlfn._xlws.FILTER( INDIRECT("'"&E$14&"'!A2:E1000"), (INDIRECT("'"&E$14&"'!B2:B1000")=$B18) * (INDIRECT("'"&E$14&"'!C2:C1000")=$C18) ), 5, FALSE ) )} | F18: {=IF( VLOOKUP( $A18, _xlfn._xlws.FILTER( INDIRECT("'"&F$14&"'!A2:E1000"), (INDIRECT("'"&F$14&"'!B2:B1000")=$B18) * (INDIRECT("'"&F$14&"'!C2:C1000")=$C18) ), 5, FALSE )=0, "", VLOOKUP( $A18, _xlfn._xlws.FILTER( INDIRECT("'"&F$14&"'!A2:E1000"), (INDIRECT("'"&F$14&"'!B2:B1000")=$B18) * (INDIRECT("'"&F$14&"'!C2:C1000")=$C18) ), 5, FALSE ) )} | G18: {=IF( VLOOKUP( $A18, _xlfn._xlws.FILTER( INDIRECT("'"&G$14&"'!A2:E1000"), (INDIRECT("'"&G$14&"'!B2:B1000")=$B18) * (INDIRECT("'"&G$14&"'!C2:C1000")=$C18) ), 5, FALSE )=0, "", VLOOKUP( $A18, _xlfn._xlws.FILTER( INDIRECT("'"&G$14&"'!A2:E1000"), (INDIRECT("'"&G$14&"'!B2:B1000")=$B18) * (INDIRECT("'"&G$14&"'!C2:C1000")=$C18) ), 5, FALSE ) )} | H18: {=IF( VLOOKUP( $A18, _xlfn._xlws.FILTER( INDIRECT("'"&H$14&"'!A2:E1000"), (INDIRECT("'"&H$14&"'!B2:B1000")=$B18) * (INDIRECT("'"&H$14&"'!C2:C1000")=$C18) ), 5, FALSE )=0, "", VLOOKUP( $A18, _xlfn._xlws.FILTER( INDIRECT("'"&H$14&"'!A2:E1000"), (INDIRECT("'"&H$14&"'!B2:B1000")=$B18) * (INDIRECT("'"&H$14&"'!C2:C1000")=$C18) ), 5, FALSE ) )} | I18: {=IF( VLOOKUP( $A18, _xlfn._xlws.FILTER( INDIRECT("'"&I$14&"'!A2:E1000"), (INDIRECT("'"&I$14&"'!B2:B1000")=$B18) * (INDIRECT("'"&I$14&"'!C2:C1000")=$C18) ), 5, FALSE )=0, "", VLOOKUP( $A18, _xlfn._xlws.FILTER( INDIRECT("'"&I$14&"'!A2:E1000"), (INDIRECT("'"&I$14&"'!B2:B1000")=$B18) * (INDIRECT("'"&I$14&"'!C2:C1000")=$C18) ), 5, FALSE ) )} | J18: {=IF( VLOOKUP( $A18, _xlfn._xlws.FILTER( INDIRECT("'"&J$14&"'!A2:E1000"), (INDIRECT("'"&J$14&"'!B2:B1000")=$B18) * (INDIRECT("'"&J$14&"'!C2:C1000")=$C18) ), 5, FALSE )=0, "", VLOOKUP( $A18, _xlfn._xlws.FILTER( INDIRECT("'"&J$14&"'!A2:E1000"), (INDIRECT("'"&J$14&"'!B2:B1000")=$B18) * (INDIRECT("'"&J$14&"'!C2:C1000")=$C18) ), 5, FALSE ) )} | K18: {=IF( VLOOKUP( $A18, _xlfn._xlws.FILTER( INDIRECT("'"&K$14&"'!A2:E1000"), (INDIRECT("'"&K$14&"'!B2:B1000")=$B18) * (INDIRECT("'"&K$14&"'!C2:C1000")=$C18) ), 5, FALSE )=0, "", VLOOKUP( $A18, _xlfn._xlws.FILTER( INDIRECT("'"&K$14&"'!A2:E1000"), (INDIRECT("'"&K$14&"'!B2:B1000")=$B18) * (INDIRECT("'"&K$14&"'!C2:C1000")=$C18) ), 5, FALSE ) )} | ... Q18: {=IF( VLOOKUP( $A18, _xlfn._xlws.FILTER( INDIRECT("'"&Q$14&"'!A2:E1000"), (INDIRECT("'"&Q$14&"'!B2:B1000")=$B18) * (INDIRECT("'"&Q$14&"'!C2:C1000")=$C18) ), 5, FALSE )=0, "", VLOOKUP( $A18, _xlfn._xlws.FILTER( INDIRECT("'"&Q$14&"'!A2:E1000"), (INDIRECT("'"&Q$14&"'!B2:B1000")=$B18) * (INDIRECT("'"&Q$14&"'!C2:C1000")=$C18) ), 5, FALSE ) )}
A19: Gabriel | B19: Mundo Novo | C19: 1 | D19: {=IF( VLOOKUP( $A19, _xlfn._xlws.FILTER( INDIRECT("'"&D$14&"'!A2:E1000"), (INDIRECT("'"&D$14&"'!B2:B1000")=$B19) * (INDIRECT("'"&D$14&"'!C2:C1000")=$C19) ), 5, FALSE )=0, "", VLOOKUP( $A19, _xlfn._xlws.FILTER( INDIRECT("'"&D$14&"'!A2:E1000"), (INDIRECT("'"&D$14&"'!B2:B1000")=$B19) * (INDIRECT("'"&D$14&"'!C2:C1000")=$C19) ), 5, FALSE ) )} | E19: {=IF( VLOOKUP( $A19, _xlfn._xlws.FILTER( INDIRECT("'"&E$14&"'!A2:E1000"), (INDIRECT("'"&E$14&"'!B2:B1000")=$B19) * (INDIRECT("'"&E$14&"'!C2:C1000")=$C19) ), 5, FALSE )=0, "", VLOOKUP( $A19, _xlfn._xlws.FILTER( INDIRECT("'"&E$14&"'!A2:E1000"), (INDIRECT("'"&E$14&"'!B2:B1000")=$B19) * (INDIRECT("'"&E$14&"'!C2:C1000")=$C19) ), 5, FALSE ) )} | F19: {=IF( VLOOKUP( $A19, _xlfn._xlws.FILTER( INDIRECT("'"&F$14&"'!A2:E1000"), (INDIRECT("'"&F$14&"'!B2:B1000")=$B19) * (INDIRECT("'"&F$14&"'!C2:C1000")=$C19) ), 5, FALSE )=0, "", VLOOKUP( $A19, _xlfn._xlws.FILTER( INDIRECT("'"&F$14&"'!A2:E1000"), (INDIRECT("'"&F$14&"'!B2:B1000")=$B19) * (INDIRECT("'"&F$14&"'!C2:C1000")=$C19) ), 5, FALSE ) )} | G19: {=IF( VLOOKUP( $A19, _xlfn._xlws.FILTER( INDIRECT("'"&G$14&"'!A2:E1000"), (INDIRECT("'"&G$14&"'!B2:B1000")=$B19) * (INDIRECT("'"&G$14&"'!C2:C1000")=$C19) ), 5, FALSE )=0, "", VLOOKUP( $A19, _xlfn._xlws.FILTER( INDIRECT("'"&G$14&"'!A2:E1000"), (INDIRECT("'"&G$14&"'!B2:B1000")=$B19) * (INDIRECT("'"&G$14&"'!C2:C1000")=$C19) ), 5, FALSE ) )} | H19: {=IF( VLOOKUP( $A19, _xlfn._xlws.FILTER( INDIRECT("'"&H$14&"'!A2:E1000"), (INDIRECT("'"&H$14&"'!B2:B1000")=$B19) * (INDIRECT("'"&H$14&"'!C2:C1000")=$C19) ), 5, FALSE )=0, "", VLOOKUP( $A19, _xlfn._xlws.FILTER( INDIRECT("'"&H$14&"'!A2:E1000"), (INDIRECT("'"&H$14&"'!B2:B1000")=$B19) * (INDIRECT("'"&H$14&"'!C2:C1000")=$C19) ), 5, FALSE ) )} | I19: {=IF( VLOOKUP( $A19, _xlfn._xlws.FILTER( INDIRECT("'"&I$14&"'!A2:E1000"), (INDIRECT("'"&I$14&"'!B2:B1000")=$B19) * (INDIRECT("'"&I$14&"'!C2:C1000")=$C19) ), 5, FALSE )=0, "", VLOOKUP( $A19, _xlfn._xlws.FILTER( INDIRECT("'"&I$14&"'!A2:E1000"), (INDIRECT("'"&I$14&"'!B2:B1000")=$B19) * (INDIRECT("'"&I$14&"'!C2:C1000")=$C19) ), 5, FALSE ) )} | J19: {=IF( VLOOKUP( $A19, _xlfn._xlws.FILTER( INDIRECT("'"&J$14&"'!A2:E1000"), (INDIRECT("'"&J$14&"'!B2:B1000")=$B19) * (INDIRECT("'"&J$14&"'!C2:C1000")=$C19) ), 5, FALSE )=0, "", VLOOKUP( $A19, _xlfn._xlws.FILTER( INDIRECT("'"&J$14&"'!A2:E1000"), (INDIRECT("'"&J$14&"'!B2:B1000")=$B19) * (INDIRECT("'"&J$14&"'!C2:C1000")=$C19) ), 5, FALSE ) )} | K19: {=IF( VLOOKUP( $A19, _xlfn._xlws.FILTER( INDIRECT("'"&K$14&"'!A2:E1000"), (INDIRECT("'"&K$14&"'!B2:B1000")=$B19) * (INDIRECT("'"&K$14&"'!C2:C1000")=$C19) ), 5, FALSE )=0, "", VLOOKUP( $A19, _xlfn._xlws.FILTER( INDIRECT("'"&K$14&"'!A2:E1000"), (INDIRECT("'"&K$14&"'!B2:B1000")=$B19) * (INDIRECT("'"&K$14&"'!C2:C1000")=$C19) ), 5, FALSE ) )} | ... Q19: {=IF( VLOOKUP( $A19, _xlfn._xlws.FILTER( INDIRECT("'"&Q$14&"'!A2:E1000"), (INDIRECT("'"&Q$14&"'!B2:B1000")=$B19) * (INDIRECT("'"&Q$14&"'!C2:C1000")=$C19) ), 5, FALSE )=0, "", VLOOKUP( $A19, _xlfn._xlws.FILTER( INDIRECT("'"&Q$14&"'!A2:E1000"), (INDIRECT("'"&Q$14&"'!B2:B1000")=$B19) * (INDIRECT("'"&Q$14&"'!C2:C1000")=$C19) ), 5, FALSE ) )}
A20: Gabriel | B20: Nova Santa Rosa | C20: 1 | D20: {=IF( VLOOKUP( $A20, _xlfn._xlws.FILTER( INDIRECT("'"&D$14&"'!A2:E1000"), (INDIRECT("'"&D$14&"'!B2:B1000")=$B20) * (INDIRECT("'"&D$14&"'!C2:C1000")=$C20) ), 5, FALSE )=0, "", VLOOKUP( $A20, _xlfn._xlws.FILTER( INDIRECT("'"&D$14&"'!A2:E1000"), (INDIRECT("'"&D$14&"'!B2:B1000")=$B20) * (INDIRECT("'"&D$14&"'!C2:C1000")=$C20) ), 5, FALSE ) )} | E20: {=IF( VLOOKUP( $A20, _xlfn._xlws.FILTER( INDIRECT("'"&E$14&"'!A2:E1000"), (INDIRECT("'"&E$14&"'!B2:B1000")=$B20) * (INDIRECT("'"&E$14&"'!C2:C1000")=$C20) ), 5, FALSE )=0, "", VLOOKUP( $A20, _xlfn._xlws.FILTER( INDIRECT("'"&E$14&"'!A2:E1000"), (INDIRECT("'"&E$14&"'!B2:B1000")=$B20) * (INDIRECT("'"&E$14&"'!C2:C1000")=$C20) ), 5, FALSE ) )} | F20: {=IF( VLOOKUP( $A20, _xlfn._xlws.FILTER( INDIRECT("'"&F$14&"'!A2:E1000"), (INDIRECT("'"&F$14&"'!B2:B1000")=$B20) * (INDIRECT("'"&F$14&"'!C2:C1000")=$C20) ), 5, FALSE )=0, "", VLOOKUP( $A20, _xlfn._xlws.FILTER( INDIRECT("'"&F$14&"'!A2:E1000"), (INDIRECT("'"&F$14&"'!B2:B1000")=$B20) * (INDIRECT("'"&F$14&"'!C2:C1000")=$C20) ), 5, FALSE ) )} | G20: {=IF( VLOOKUP( $A20, _xlfn._xlws.FILTER( INDIRECT("'"&G$14&"'!A2:E1000"), (INDIRECT("'"&G$14&"'!B2:B1000")=$B20) * (INDIRECT("'"&G$14&"'!C2:C1000")=$C20) ), 5, FALSE )=0, "", VLOOKUP( $A20, _xlfn._xlws.FILTER( INDIRECT("'"&G$14&"'!A2:E1000"), (INDIRECT("'"&G$14&"'!B2:B1000")=$B20) * (INDIRECT("'"&G$14&"'!C2:C1000")=$C20) ), 5, FALSE ) )} | H20: {=IF( VLOOKUP( $A20, _xlfn._xlws.FILTER( INDIRECT("'"&H$14&"'!A2:E1000"), (INDIRECT("'"&H$14&"'!B2:B1000")=$B20) * (INDIRECT("'"&H$14&"'!C2:C1000")=$C20) ), 5, FALSE )=0, "", VLOOKUP( $A20, _xlfn._xlws.FILTER( INDIRECT("'"&H$14&"'!A2:E1000"), (INDIRECT("'"&H$14&"'!B2:B1000")=$B20) * (INDIRECT("'"&H$14&"'!C2:C1000")=$C20) ), 5, FALSE ) )} | I20: {=IF( VLOOKUP( $A20, _xlfn._xlws.FILTER( INDIRECT("'"&I$14&"'!A2:E1000"), (INDIRECT("'"&I$14&"'!B2:B1000")=$B20) * (INDIRECT("'"&I$14&"'!C2:C1000")=$C20) ), 5, FALSE )=0, "", VLOOKUP( $A20, _xlfn._xlws.FILTER( INDIRECT("'"&I$14&"'!A2:E1000"), (INDIRECT("'"&I$14&"'!B2:B1000")=$B20) * (INDIRECT("'"&I$14&"'!C2:C1000")=$C20) ), 5, FALSE ) )} | J20: {=IF( VLOOKUP( $A20, _xlfn._xlws.FILTER( INDIRECT("'"&J$14&"'!A2:E1000"), (INDIRECT("'"&J$14&"'!B2:B1000")=$B20) * (INDIRECT("'"&J$14&"'!C2:C1000")=$C20) ), 5, FALSE )=0, "", VLOOKUP( $A20, _xlfn._xlws.FILTER( INDIRECT("'"&J$14&"'!A2:E1000"), (INDIRECT("'"&J$14&"'!B2:B1000")=$B20) * (INDIRECT("'"&J$14&"'!C2:C1000")=$C20) ), 5, FALSE ) )} | K20: {=IF( VLOOKUP( $A20, _xlfn._xlws.FILTER( INDIRECT("'"&K$14&"'!A2:E1000"), (INDIRECT("'"&K$14&"'!B2:B1000")=$B20) * (INDIRECT("'"&K$14&"'!C2:C1000")=$C20) ), 5, FALSE )=0, "", VLOOKUP( $A20, _xlfn._xlws.FILTER( INDIRECT("'"&K$14&"'!A2:E1000"), (INDIRECT("'"&K$14&"'!B2:B1000")=$B20) * (INDIRECT("'"&K$14&"'!C2:C1000")=$C20) ), 5, FALSE ) )} | ... Q20: {=IF( VLOOKUP( $A20, _xlfn._xlws.FILTER( INDIRECT("'"&Q$14&"'!A2:E1000"), (INDIRECT("'"&Q$14&"'!B2:B1000")=$B20) * (INDIRECT("'"&Q$14&"'!C2:C1000")=$C20) ), 5, FALSE )=0, "", VLOOKUP( $A20, _xlfn._xlws.FILTER( INDIRECT("'"&Q$14&"'!A2:E1000"), (INDIRECT("'"&Q$14&"'!B2:B1000")=$B20) * (INDIRECT("'"&Q$14&"'!C2:C1000")=$C20) ), 5, FALSE ) )}
A21: Gabriel | B21: Ouro Verde do Oeste | C21: 1 | D21: {=IF( VLOOKUP( $A21, _xlfn._xlws.FILTER( INDIRECT("'"&D$14&"'!A2:E1000"), (INDIRECT("'"&D$14&"'!B2:B1000")=$B21) * (INDIRECT("'"&D$14&"'!C2:C1000")=$C21) ), 5, FALSE )=0, "", VLOOKUP( $A21, _xlfn._xlws.FILTER( INDIRECT("'"&D$14&"'!A2:E1000"), (INDIRECT("'"&D$14&"'!B2:B1000")=$B21) * (INDIRECT("'"&D$14&"'!C2:C1000")=$C21) ), 5, FALSE ) )} | E21: {=IF( VLOOKUP( $A21, _xlfn._xlws.FILTER( INDIRECT("'"&E$14&"'!A2:E1000"), (INDIRECT("'"&E$14&"'!B2:B1000")=$B21) * (INDIRECT("'"&E$14&"'!C2:C1000")=$C21) ), 5, FALSE )=0, "", VLOOKUP( $A21, _xlfn._xlws.FILTER( INDIRECT("'"&E$14&"'!A2:E1000"), (INDIRECT("'"&E$14&"'!B2:B1000")=$B21) * (INDIRECT("'"&E$14&"'!C2:C1000")=$C21) ), 5, FALSE ) )} | F21: {=IF( VLOOKUP( $A21, _xlfn._xlws.FILTER( INDIRECT("'"&F$14&"'!A2:E1000"), (INDIRECT("'"&F$14&"'!B2:B1000")=$B21) * (INDIRECT("'"&F$14&"'!C2:C1000")=$C21) ), 5, FALSE )=0, "", VLOOKUP( $A21, _xlfn._xlws.FILTER( INDIRECT("'"&F$14&"'!A2:E1000"), (INDIRECT("'"&F$14&"'!B2:B1000")=$B21) * (INDIRECT("'"&F$14&"'!C2:C1000")=$C21) ), 5, FALSE ) )} | G21: {=IF( VLOOKUP( $A21, _xlfn._xlws.FILTER( INDIRECT("'"&G$14&"'!A2:E1000"), (INDIRECT("'"&G$14&"'!B2:B1000")=$B21) * (INDIRECT("'"&G$14&"'!C2:C1000")=$C21) ), 5, FALSE )=0, "", VLOOKUP( $A21, _xlfn._xlws.FILTER( INDIRECT("'"&G$14&"'!A2:E1000"), (INDIRECT("'"&G$14&"'!B2:B1000")=$B21) * (INDIRECT("'"&G$14&"'!C2:C1000")=$C21) ), 5, FALSE ) )} | H21: {=IF( VLOOKUP( $A21, _xlfn._xlws.FILTER( INDIRECT("'"&H$14&"'!A2:E1000"), (INDIRECT("'"&H$14&"'!B2:B1000")=$B21) * (INDIRECT("'"&H$14&"'!C2:C1000")=$C21) ), 5, FALSE )=0, "", VLOOKUP( $A21, _xlfn._xlws.FILTER( INDIRECT("'"&H$14&"'!A2:E1000"), (INDIRECT("'"&H$14&"'!B2:B1000")=$B21) * (INDIRECT("'"&H$14&"'!C2:C1000")=$C21) ), 5, FALSE ) )} | I21: {=IF( VLOOKUP( $A21, _xlfn._xlws.FILTER( INDIRECT("'"&I$14&"'!A2:E1000"), (INDIRECT("'"&I$14&"'!B2:B1000")=$B21) * (INDIRECT("'"&I$14&"'!C2:C1000")=$C21) ), 5, FALSE )=0, "", VLOOKUP( $A21, _xlfn._xlws.FILTER( INDIRECT("'"&I$14&"'!A2:E1000"), (INDIRECT("'"&I$14&"'!B2:B1000")=$B21) * (INDIRECT("'"&I$14&"'!C2:C1000")=$C21) ), 5, FALSE ) )} | J21: {=IF( VLOOKUP( $A21, _xlfn._xlws.FILTER( INDIRECT("'"&J$14&"'!A2:E1000"), (INDIRECT("'"&J$14&"'!B2:B1000")=$B21) * (INDIRECT("'"&J$14&"'!C2:C1000")=$C21) ), 5, FALSE )=0, "", VLOOKUP( $A21, _xlfn._xlws.FILTER( INDIRECT("'"&J$14&"'!A2:E1000"), (INDIRECT("'"&J$14&"'!B2:B1000")=$B21) * (INDIRECT("'"&J$14&"'!C2:C1000")=$C21) ), 5, FALSE ) )} | K21: {=IF( VLOOKUP( $A21, _xlfn._xlws.FILTER( INDIRECT("'"&K$14&"'!A2:E1000"), (INDIRECT("'"&K$14&"'!B2:B1000")=$B21) * (INDIRECT("'"&K$14&"'!C2:C1000")=$C21) ), 5, FALSE )=0, "", VLOOKUP( $A21, _xlfn._xlws.FILTER( INDIRECT("'"&K$14&"'!A2:E1000"), (INDIRECT("'"&K$14&"'!B2:B1000")=$B21) * (INDIRECT("'"&K$14&"'!C2:C1000")=$C21) ), 5, FALSE ) )} | ... Q21: {=IF( VLOOKUP( $A21, _xlfn._xlws.FILTER( INDIRECT("'"&Q$14&"'!A2:E1000"), (INDIRECT("'"&Q$14&"'!B2:B1000")=$B21) * (INDIRECT("'"&Q$14&"'!C2:C1000")=$C21) ), 5, FALSE )=0, "", VLOOKUP( $A21, _xlfn._xlws.FILTER( INDIRECT("'"&Q$14&"'!A2:E1000"), (INDIRECT("'"&Q$14&"'!B2:B1000")=$B21) * (INDIRECT("'"&Q$14&"'!C2:C1000")=$C21) ), 5, FALSE ) )}
A22: Gabriel | B22: Quatro Pontes | C22: 1 | D22: {=IF( VLOOKUP( $A22, _xlfn._xlws.FILTER( INDIRECT("'"&D$14&"'!A2:E1000"), (INDIRECT("'"&D$14&"'!B2:B1000")=$B22) * (INDIRECT("'"&D$14&"'!C2:C1000")=$C22) ), 5, FALSE )=0, "", VLOOKUP( $A22, _xlfn._xlws.FILTER( INDIRECT("'"&D$14&"'!A2:E1000"), (INDIRECT("'"&D$14&"'!B2:B1000")=$B22) * (INDIRECT("'"&D$14&"'!C2:C1000")=$C22) ), 5, FALSE ) )} | E22: {=IF( VLOOKUP( $A22, _xlfn._xlws.FILTER( INDIRECT("'"&E$14&"'!A2:E1000"), (INDIRECT("'"&E$14&"'!B2:B1000")=$B22) * (INDIRECT("'"&E$14&"'!C2:C1000")=$C22) ), 5, FALSE )=0, "", VLOOKUP( $A22, _xlfn._xlws.FILTER( INDIRECT("'"&E$14&"'!A2:E1000"), (INDIRECT("'"&E$14&"'!B2:B1000")=$B22) * (INDIRECT("'"&E$14&"'!C2:C1000")=$C22) ), 5, FALSE ) )} | F22: {=IF( VLOOKUP( $A22, _xlfn._xlws.FILTER( INDIRECT("'"&F$14&"'!A2:E1000"), (INDIRECT("'"&F$14&"'!B2:B1000")=$B22) * (INDIRECT("'"&F$14&"'!C2:C1000")=$C22) ), 5, FALSE )=0, "", VLOOKUP( $A22, _xlfn._xlws.FILTER( INDIRECT("'"&F$14&"'!A2:E1000"), (INDIRECT("'"&F$14&"'!B2:B1000")=$B22) * (INDIRECT("'"&F$14&"'!C2:C1000")=$C22) ), 5, FALSE ) )} | G22: {=IF( VLOOKUP( $A22, _xlfn._xlws.FILTER( INDIRECT("'"&G$14&"'!A2:E1000"), (INDIRECT("'"&G$14&"'!B2:B1000")=$B22) * (INDIRECT("'"&G$14&"'!C2:C1000")=$C22) ), 5, FALSE )=0, "", VLOOKUP( $A22, _xlfn._xlws.FILTER( INDIRECT("'"&G$14&"'!A2:E1000"), (INDIRECT("'"&G$14&"'!B2:B1000")=$B22) * (INDIRECT("'"&G$14&"'!C2:C1000")=$C22) ), 5, FALSE ) )} | H22: {=IF( VLOOKUP( $A22, _xlfn._xlws.FILTER( INDIRECT("'"&H$14&"'!A2:E1000"), (INDIRECT("'"&H$14&"'!B2:B1000")=$B22) * (INDIRECT("'"&H$14&"'!C2:C1000")=$C22) ), 5, FALSE )=0, "", VLOOKUP( $A22, _xlfn._xlws.FILTER( INDIRECT("'"&H$14&"'!A2:E1000"), (INDIRECT("'"&H$14&"'!B2:B1000")=$B22) * (INDIRECT("'"&H$14&"'!C2:C1000")=$C22) ), 5, FALSE ) )} | I22: {=IF( VLOOKUP( $A22, _xlfn._xlws.FILTER( INDIRECT("'"&I$14&"'!A2:E1000"), (INDIRECT("'"&I$14&"'!B2:B1000")=$B22) * (INDIRECT("'"&I$14&"'!C2:C1000")=$C22) ), 5, FALSE )=0, "", VLOOKUP( $A22, _xlfn._xlws.FILTER( INDIRECT("'"&I$14&"'!A2:E1000"), (INDIRECT("'"&I$14&"'!B2:B1000")=$B22) * (INDIRECT("'"&I$14&"'!C2:C1000")=$C22) ), 5, FALSE ) )} | J22: {=IF( VLOOKUP( $A22, _xlfn._xlws.FILTER( INDIRECT("'"&J$14&"'!A2:E1000"), (INDIRECT("'"&J$14&"'!B2:B1000")=$B22) * (INDIRECT("'"&J$14&"'!C2:C1000")=$C22) ), 5, FALSE )=0, "", VLOOKUP( $A22, _xlfn._xlws.FILTER( INDIRECT("'"&J$14&"'!A2:E1000"), (INDIRECT("'"&J$14&"'!B2:B1000")=$B22) * (INDIRECT("'"&J$14&"'!C2:C1000")=$C22) ), 5, FALSE ) )} | K22: {=IF( VLOOKUP( $A22, _xlfn._xlws.FILTER( INDIRECT("'"&K$14&"'!A2:E1000"), (INDIRECT("'"&K$14&"'!B2:B1000")=$B22) * (INDIRECT("'"&K$14&"'!C2:C1000")=$C22) ), 5, FALSE )=0, "", VLOOKUP( $A22, _xlfn._xlws.FILTER( INDIRECT("'"&K$14&"'!A2:E1000"), (INDIRECT("'"&K$14&"'!B2:B1000")=$B22) * (INDIRECT("'"&K$14&"'!C2:C1000")=$C22) ), 5, FALSE ) )} | ... Q22: {=IF( VLOOKUP( $A22, _xlfn._xlws.FILTER( INDIRECT("'"&Q$14&"'!A2:E1000"), (INDIRECT("'"&Q$14&"'!B2:B1000")=$B22) * (INDIRECT("'"&Q$14&"'!C2:C1000")=$C22) ), 5, FALSE )=0, "", VLOOKUP( $A22, _xlfn._xlws.FILTER( INDIRECT("'"&Q$14&"'!A2:E1000"), (INDIRECT("'"&Q$14&"'!B2:B1000")=$B22) * (INDIRECT("'"&Q$14&"'!C2:C1000")=$C22) ), 5, FALSE ) )}
A23: Gabriel | B23: São Jose das Palmeiras | C23: 1 | D23: {=IF( VLOOKUP( $A23, _xlfn._xlws.FILTER( INDIRECT("'"&D$14&"'!A2:E1000"), (INDIRECT("'"&D$14&"'!B2:B1000")=$B23) * (INDIRECT("'"&D$14&"'!C2:C1000")=$C23) ), 5, FALSE )=0, "", VLOOKUP( $A23, _xlfn._xlws.FILTER( INDIRECT("'"&D$14&"'!A2:E1000"), (INDIRECT("'"&D$14&"'!B2:B1000")=$B23) * (INDIRECT("'"&D$14&"'!C2:C1000")=$C23) ), 5, FALSE ) )} | E23: {=IF( VLOOKUP( $A23, _xlfn._xlws.FILTER( INDIRECT("'"&E$14&"'!A2:E1000"), (INDIRECT("'"&E$14&"'!B2:B1000")=$B23) * (INDIRECT("'"&E$14&"'!C2:C1000")=$C23) ), 5, FALSE )=0, "", VLOOKUP( $A23, _xlfn._xlws.FILTER( INDIRECT("'"&E$14&"'!A2:E1000"), (INDIRECT("'"&E$14&"'!B2:B1000")=$B23) * (INDIRECT("'"&E$14&"'!C2:C1000")=$C23) ), 5, FALSE ) )} | F23: {=IF( VLOOKUP( $A23, _xlfn._xlws.FILTER( INDIRECT("'"&F$14&"'!A2:E1000"), (INDIRECT("'"&F$14&"'!B2:B1000")=$B23) * (INDIRECT("'"&F$14&"'!C2:C1000")=$C23) ), 5, FALSE )=0, "", VLOOKUP( $A23, _xlfn._xlws.FILTER( INDIRECT("'"&F$14&"'!A2:E1000"), (INDIRECT("'"&F$14&"'!B2:B1000")=$B23) * (INDIRECT("'"&F$14&"'!C2:C1000")=$C23) ), 5, FALSE ) )} | G23: {=IF( VLOOKUP( $A23, _xlfn._xlws.FILTER( INDIRECT("'"&G$14&"'!A2:E1000"), (INDIRECT("'"&G$14&"'!B2:B1000")=$B23) * (INDIRECT("'"&G$14&"'!C2:C1000")=$C23) ), 5, FALSE )=0, "", VLOOKUP( $A23, _xlfn._xlws.FILTER( INDIRECT("'"&G$14&"'!A2:E1000"), (INDIRECT("'"&G$14&"'!B2:B1000")=$B23) * (INDIRECT("'"&G$14&"'!C2:C1000")=$C23) ), 5, FALSE ) )} | H23: {=IF( VLOOKUP( $A23, _xlfn._xlws.FILTER( INDIRECT("'"&H$14&"'!A2:E1000"), (INDIRECT("'"&H$14&"'!B2:B1000")=$B23) * (INDIRECT("'"&H$14&"'!C2:C1000")=$C23) ), 5, FALSE )=0, "", VLOOKUP( $A23, _xlfn._xlws.FILTER( INDIRECT("'"&H$14&"'!A2:E1000"), (INDIRECT("'"&H$14&"'!B2:B1000")=$B23) * (INDIRECT("'"&H$14&"'!C2:C1000")=$C23) ), 5, FALSE ) )} | I23: {=IF( VLOOKUP( $A23, _xlfn._xlws.FILTER( INDIRECT("'"&I$14&"'!A2:E1000"), (INDIRECT("'"&I$14&"'!B2:B1000")=$B23) * (INDIRECT("'"&I$14&"'!C2:C1000")=$C23) ), 5, FALSE )=0, "", VLOOKUP( $A23, _xlfn._xlws.FILTER( INDIRECT("'"&I$14&"'!A2:E1000"), (INDIRECT("'"&I$14&"'!B2:B1000")=$B23) * (INDIRECT("'"&I$14&"'!C2:C1000")=$C23) ), 5, FALSE ) )} | J23: {=IF( VLOOKUP( $A23, _xlfn._xlws.FILTER( INDIRECT("'"&J$14&"'!A2:E1000"), (INDIRECT("'"&J$14&"'!B2:B1000")=$B23) * (INDIRECT("'"&J$14&"'!C2:C1000")=$C23) ), 5, FALSE )=0, "", VLOOKUP( $A23, _xlfn._xlws.FILTER( INDIRECT("'"&J$14&"'!A2:E1000"), (INDIRECT("'"&J$14&"'!B2:B1000")=$B23) * (INDIRECT("'"&J$14&"'!C2:C1000")=$C23) ), 5, FALSE ) )} | K23: {=IF( VLOOKUP( $A23, _xlfn._xlws.FILTER( INDIRECT("'"&K$14&"'!A2:E1000"), (INDIRECT("'"&K$14&"'!B2:B1000")=$B23) * (INDIRECT("'"&K$14&"'!C2:C1000")=$C23) ), 5, FALSE )=0, "", VLOOKUP( $A23, _xlfn._xlws.FILTER( INDIRECT("'"&K$14&"'!A2:E1000"), (INDIRECT("'"&K$14&"'!B2:B1000")=$B23) * (INDIRECT("'"&K$14&"'!C2:C1000")=$C23) ), 5, FALSE ) )} | ... Q23: {=IF( VLOOKUP( $A23, _xlfn._xlws.FILTER( INDIRECT("'"&Q$14&"'!A2:E1000"), (INDIRECT("'"&Q$14&"'!B2:B1000")=$B23) * (INDIRECT("'"&Q$14&"'!C2:C1000")=$C23) ), 5, FALSE )=0, "", VLOOKUP( $A23, _xlfn._xlws.FILTER( INDIRECT("'"&Q$14&"'!A2:E1000"), (INDIRECT("'"&Q$14&"'!B2:B1000")=$B23) * (INDIRECT("'"&Q$14&"'!C2:C1000")=$C23) ), 5, FALSE ) )}
A24: Gabriel | B24: Terra Roxa | C24: 1 | D24: {=IF( VLOOKUP( $A24, _xlfn._xlws.FILTER( INDIRECT("'"&D$14&"'!A2:E1000"), (INDIRECT("'"&D$14&"'!B2:B1000")=$B24) * (INDIRECT("'"&D$14&"'!C2:C1000")=$C24) ), 5, FALSE )=0, "", VLOOKUP( $A24, _xlfn._xlws.FILTER( INDIRECT("'"&D$14&"'!A2:E1000"), (INDIRECT("'"&D$14&"'!B2:B1000")=$B24) * (INDIRECT("'"&D$14&"'!C2:C1000")=$C24) ), 5, FALSE ) )} | E24: {=IF( VLOOKUP( $A24, _xlfn._xlws.FILTER( INDIRECT("'"&E$14&"'!A2:E1000"), (INDIRECT("'"&E$14&"'!B2:B1000")=$B24) * (INDIRECT("'"&E$14&"'!C2:C1000")=$C24) ), 5, FALSE )=0, "", VLOOKUP( $A24, _xlfn._xlws.FILTER( INDIRECT("'"&E$14&"'!A2:E1000"), (INDIRECT("'"&E$14&"'!B2:B1000")=$B24) * (INDIRECT("'"&E$14&"'!C2:C1000")=$C24) ), 5, FALSE ) )} | F24: {=IF( VLOOKUP( $A24, _xlfn._xlws.FILTER( INDIRECT("'"&F$14&"'!A2:E1000"), (INDIRECT("'"&F$14&"'!B2:B1000")=$B24) * (INDIRECT("'"&F$14&"'!C2:C1000")=$C24) ), 5, FALSE )=0, "", VLOOKUP( $A24, _xlfn._xlws.FILTER( INDIRECT("'"&F$14&"'!A2:E1000"), (INDIRECT("'"&F$14&"'!B2:B1000")=$B24) * (INDIRECT("'"&F$14&"'!C2:C1000")=$C24) ), 5, FALSE ) )} | G24: {=IF( VLOOKUP( $A24, _xlfn._xlws.FILTER( INDIRECT("'"&G$14&"'!A2:E1000"), (INDIRECT("'"&G$14&"'!B2:B1000")=$B24) * (INDIRECT("'"&G$14&"'!C2:C1000")=$C24) ), 5, FALSE )=0, "", VLOOKUP( $A24, _xlfn._xlws.FILTER( INDIRECT("'"&G$14&"'!A2:E1000"), (INDIRECT("'"&G$14&"'!B2:B1000")=$B24) * (INDIRECT("'"&G$14&"'!C2:C1000")=$C24) ), 5, FALSE ) )} | H24: {=IF( VLOOKUP( $A24, _xlfn._xlws.FILTER( INDIRECT("'"&H$14&"'!A2:E1000"), (INDIRECT("'"&H$14&"'!B2:B1000")=$B24) * (INDIRECT("'"&H$14&"'!C2:C1000")=$C24) ), 5, FALSE )=0, "", VLOOKUP( $A24, _xlfn._xlws.FILTER( INDIRECT("'"&H$14&"'!A2:E1000"), (INDIRECT("'"&H$14&"'!B2:B1000")=$B24) * (INDIRECT("'"&H$14&"'!C2:C1000")=$C24) ), 5, FALSE ) )} | I24: {=IF( VLOOKUP( $A24, _xlfn._xlws.FILTER( INDIRECT("'"&I$14&"'!A2:E1000"), (INDIRECT("'"&I$14&"'!B2:B1000")=$B24) * (INDIRECT("'"&I$14&"'!C2:C1000")=$C24) ), 5, FALSE )=0, "", VLOOKUP( $A24, _xlfn._xlws.FILTER( INDIRECT("'"&I$14&"'!A2:E1000"), (INDIRECT("'"&I$14&"'!B2:B1000")=$B24) * (INDIRECT("'"&I$14&"'!C2:C1000")=$C24) ), 5, FALSE ) )} | J24: {=IF( VLOOKUP( $A24, _xlfn._xlws.FILTER( INDIRECT("'"&J$14&"'!A2:E1000"), (INDIRECT("'"&J$14&"'!B2:B1000")=$B24) * (INDIRECT("'"&J$14&"'!C2:C1000")=$C24) ), 5, FALSE )=0, "", VLOOKUP( $A24, _xlfn._xlws.FILTER( INDIRECT("'"&J$14&"'!A2:E1000"), (INDIRECT("'"&J$14&"'!B2:B1000")=$B24) * (INDIRECT("'"&J$14&"'!C2:C1000")=$C24) ), 5, FALSE ) )} | K24: {=IF( VLOOKUP( $A24, _xlfn._xlws.FILTER( INDIRECT("'"&K$14&"'!A2:E1000"), (INDIRECT("'"&K$14&"'!B2:B1000")=$B24) * (INDIRECT("'"&K$14&"'!C2:C1000")=$C24) ), 5, FALSE )=0, "", VLOOKUP( $A24, _xlfn._xlws.FILTER( INDIRECT("'"&K$14&"'!A2:E1000"), (INDIRECT("'"&K$14&"'!B2:B1000")=$B24) * (INDIRECT("'"&K$14&"'!C2:C1000")=$C24) ), 5, FALSE ) )} | ... Q24: {=IF( VLOOKUP( $A24, _xlfn._xlws.FILTER( INDIRECT("'"&Q$14&"'!A2:E1000"), (INDIRECT("'"&Q$14&"'!B2:B1000")=$B24) * (INDIRECT("'"&Q$14&"'!C2:C1000")=$C24) ), 5, FALSE )=0, "", VLOOKUP( $A24, _xlfn._xlws.FILTER( INDIRECT("'"&Q$14&"'!A2:E1000"), (INDIRECT("'"&Q$14&"'!B2:B1000")=$B24) * (INDIRECT("'"&Q$14&"'!C2:C1000")=$C24) ), 5, FALSE ) )}
A25: Gabriel | B25: Toledo | C25: 1 | D25: {=IF( VLOOKUP( $A25, _xlfn._xlws.FILTER( INDIRECT("'"&D$14&"'!A2:E1000"), (INDIRECT("'"&D$14&"'!B2:B1000")=$B25) * (INDIRECT("'"&D$14&"'!C2:C1000")=$C25) ), 5, FALSE )=0, "", VLOOKUP( $A25, _xlfn._xlws.FILTER( INDIRECT("'"&D$14&"'!A2:E1000"), (INDIRECT("'"&D$14&"'!B2:B1000")=$B25) * (INDIRECT("'"&D$14&"'!C2:C1000")=$C25) ), 5, FALSE ) )} | E25: {=IF( VLOOKUP( $A25, _xlfn._xlws.FILTER( INDIRECT("'"&E$14&"'!A2:E1000"), (INDIRECT("'"&E$14&"'!B2:B1000")=$B25) * (INDIRECT("'"&E$14&"'!C2:C1000")=$C25) ), 5, FALSE )=0, "", VLOOKUP( $A25, _xlfn._xlws.FILTER( INDIRECT("'"&E$14&"'!A2:E1000"), (INDIRECT("'"&E$14&"'!B2:B1000")=$B25) * (INDIRECT("'"&E$14&"'!C2:C1000")=$C25) ), 5, FALSE ) )} | F25: {=IF( VLOOKUP( $A25, _xlfn._xlws.FILTER( INDIRECT("'"&F$14&"'!A2:E1000"), (INDIRECT("'"&F$14&"'!B2:B1000")=$B25) * (INDIRECT("'"&F$14&"'!C2:C1000")=$C25) ), 5, FALSE )=0, "", VLOOKUP( $A25, _xlfn._xlws.FILTER( INDIRECT("'"&F$14&"'!A2:E1000"), (INDIRECT("'"&F$14&"'!B2:B1000")=$B25) * (INDIRECT("'"&F$14&"'!C2:C1000")=$C25) ), 5, FALSE ) )} | G25: {=IF( VLOOKUP( $A25, _xlfn._xlws.FILTER( INDIRECT("'"&G$14&"'!A2:E1000"), (INDIRECT("'"&G$14&"'!B2:B1000")=$B25) * (INDIRECT("'"&G$14&"'!C2:C1000")=$C25) ), 5, FALSE )=0, "", VLOOKUP( $A25, _xlfn._xlws.FILTER( INDIRECT("'"&G$14&"'!A2:E1000"), (INDIRECT("'"&G$14&"'!B2:B1000")=$B25) * (INDIRECT("'"&G$14&"'!C2:C1000")=$C25) ), 5, FALSE ) )} | H25: {=IF( VLOOKUP( $A25, _xlfn._xlws.FILTER( INDIRECT("'"&H$14&"'!A2:E1000"), (INDIRECT("'"&H$14&"'!B2:B1000")=$B25) * (INDIRECT("'"&H$14&"'!C2:C1000")=$C25) ), 5, FALSE )=0, "", VLOOKUP( $A25, _xlfn._xlws.FILTER( INDIRECT("'"&H$14&"'!A2:E1000"), (INDIRECT("'"&H$14&"'!B2:B1000")=$B25) * (INDIRECT("'"&H$14&"'!C2:C1000")=$C25) ), 5, FALSE ) )} | I25: {=IF( VLOOKUP( $A25, _xlfn._xlws.FILTER( INDIRECT("'"&I$14&"'!A2:E1000"), (INDIRECT("'"&I$14&"'!B2:B1000")=$B25) * (INDIRECT("'"&I$14&"'!C2:C1000")=$C25) ), 5, FALSE )=0, "", VLOOKUP( $A25, _xlfn._xlws.FILTER( INDIRECT("'"&I$14&"'!A2:E1000"), (INDIRECT("'"&I$14&"'!B2:B1000")=$B25) * (INDIRECT("'"&I$14&"'!C2:C1000")=$C25) ), 5, FALSE ) )} | J25: {=IF( VLOOKUP( $A25, _xlfn._xlws.FILTER( INDIRECT("'"&J$14&"'!A2:E1000"), (INDIRECT("'"&J$14&"'!B2:B1000")=$B25) * (INDIRECT("'"&J$14&"'!C2:C1000")=$C25) ), 5, FALSE )=0, "", VLOOKUP( $A25, _xlfn._xlws.FILTER( INDIRECT("'"&J$14&"'!A2:E1000"), (INDIRECT("'"&J$14&"'!B2:B1000")=$B25) * (INDIRECT("'"&J$14&"'!C2:C1000")=$C25) ), 5, FALSE ) )} | K25: {=IF( VLOOKUP( $A25, _xlfn._xlws.FILTER( INDIRECT("'"&K$14&"'!A2:E1000"), (INDIRECT("'"&K$14&"'!B2:B1000")=$B25) * (INDIRECT("'"&K$14&"'!C2:C1000")=$C25) ), 5, FALSE )=0, "", VLOOKUP( $A25, _xlfn._xlws.FILTER( INDIRECT("'"&K$14&"'!A2:E1000"), (INDIRECT("'"&K$14&"'!B2:B1000")=$B25) * (INDIRECT("'"&K$14&"'!C2:C1000")=$C25) ), 5, FALSE ) )} | ... Q25: {=IF( VLOOKUP( $A25, _xlfn._xlws.FILTER( INDIRECT("'"&Q$14&"'!A2:E1000"), (INDIRECT("'"&Q$14&"'!B2:B1000")=$B25) * (INDIRECT("'"&Q$14&"'!C2:C1000")=$C25) ), 5, FALSE )=0, "", VLOOKUP( $A25, _xlfn._xlws.FILTER( INDIRECT("'"&Q$14&"'!A2:E1000"), (INDIRECT("'"&Q$14&"'!B2:B1000")=$B25) * (INDIRECT("'"&Q$14&"'!C2:C1000")=$C25) ), 5, FALSE ) )}
A27: Regional | B27: Municípios | C27: UVR | D27: 11.24 | E27: 12.24 | F27: 01.25 | G27: 02.25 | H27: 03.25 | I27: 04.25 | J27: 05.25 | K27: 06.25 | L27: 07.25 | M27: 08.25 | N27: 09.25 | O27: 10.25 | P27: 11.25 | Q27: 12.25
A28: Gustavo | B28: Assis Chateaubriand | C28: 1 | D28: {=IF( VLOOKUP( $A28, _xlfn._xlws.FILTER( INDIRECT("'"&D$14&"'!A2:E1000"), (INDIRECT("'"&D$14&"'!B2:B1000")=$B28) * (INDIRECT("'"&D$14&"'!C2:C1000")=$C28) ), 5, FALSE )=0, "", VLOOKUP( $A28, _xlfn._xlws.FILTER( INDIRECT("'"&D$14&"'!A2:E1000"), (INDIRECT("'"&D$14&"'!B2:B1000")=$B28) * (INDIRECT("'"&D$14&"'!C2:C1000")=$C28) ), 5, FALSE ) )} | E28: {=IF( VLOOKUP( $A28, _xlfn._xlws.FILTER( INDIRECT("'"&E$14&"'!A2:E1000"), (INDIRECT("'"&E$14&"'!B2:B1000")=$B28) * (INDIRECT("'"&E$14&"'!C2:C1000")=$C28) ), 5, FALSE )=0, "", VLOOKUP( $A28, _xlfn._xlws.FILTER( INDIRECT("'"&E$14&"'!A2:E1000"), (INDIRECT("'"&E$14&"'!B2:B1000")=$B28) * (INDIRECT("'"&E$14&"'!C2:C1000")=$C28) ), 5, FALSE ) )} | F28: {=IF( VLOOKUP( $A28, _xlfn._xlws.FILTER( INDIRECT("'"&F$14&"'!A2:E1000"), (INDIRECT("'"&F$14&"'!B2:B1000")=$B28) * (INDIRECT("'"&F$14&"'!C2:C1000")=$C28) ), 5, FALSE )=0, "", VLOOKUP( $A28, _xlfn._xlws.FILTER( INDIRECT("'"&F$14&"'!A2:E1000"), (INDIRECT("'"&F$14&"'!B2:B1000")=$B28) * (INDIRECT("'"&F$14&"'!C2:C1000")=$C28) ), 5, FALSE ) )} | G28: {=IF( VLOOKUP( $A28, _xlfn._xlws.FILTER( INDIRECT("'"&G$14&"'!A2:E1000"), (INDIRECT("'"&G$14&"'!B2:B1000")=$B28) * (INDIRECT("'"&G$14&"'!C2:C1000")=$C28) ), 5, FALSE )=0, "", VLOOKUP( $A28, _xlfn._xlws.FILTER( INDIRECT("'"&G$14&"'!A2:E1000"), (INDIRECT("'"&G$14&"'!B2:B1000")=$B28) * (INDIRECT("'"&G$14&"'!C2:C1000")=$C28) ), 5, FALSE ) )} | H28: {=IF( VLOOKUP( $A28, _xlfn._xlws.FILTER( INDIRECT("'"&H$14&"'!A2:E1000"), (INDIRECT("'"&H$14&"'!B2:B1000")=$B28) * (INDIRECT("'"&H$14&"'!C2:C1000")=$C28) ), 5, FALSE )=0, "", VLOOKUP( $A28, _xlfn._xlws.FILTER( INDIRECT("'"&H$14&"'!A2:E1000"), (INDIRECT("'"&H$14&"'!B2:B1000")=$B28) * (INDIRECT("'"&H$14&"'!C2:C1000")=$C28) ), 5, FALSE ) )} | I28: {=IF( VLOOKUP( $A28, _xlfn._xlws.FILTER( INDIRECT("'"&I$14&"'!A2:E1000"), (INDIRECT("'"&I$14&"'!B2:B1000")=$B28) * (INDIRECT("'"&I$14&"'!C2:C1000")=$C28) ), 5, FALSE )=0, "", VLOOKUP( $A28, _xlfn._xlws.FILTER( INDIRECT("'"&I$14&"'!A2:E1000"), (INDIRECT("'"&I$14&"'!B2:B1000")=$B28) * (INDIRECT("'"&I$14&"'!C2:C1000")=$C28) ), 5, FALSE ) )} | J28: {=IF( VLOOKUP( $A28, _xlfn._xlws.FILTER( INDIRECT("'"&J$14&"'!A2:E1000"), (INDIRECT("'"&J$14&"'!B2:B1000")=$B28) * (INDIRECT("'"&J$14&"'!C2:C1000")=$C28) ), 5, FALSE )=0, "", VLOOKUP( $A28, _xlfn._xlws.FILTER( INDIRECT("'"&J$14&"'!A2:E1000"), (INDIRECT("'"&J$14&"'!B2:B1000")=$B28) * (INDIRECT("'"&J$14&"'!C2:C1000")=$C28) ), 5, FALSE ) )} | K28: {=IF( VLOOKUP( $A28, _xlfn._xlws.FILTER( INDIRECT("'"&K$14&"'!A2:E1000"), (INDIRECT("'"&K$14&"'!B2:B1000")=$B28) * (INDIRECT("'"&K$14&"'!C2:C1000")=$C28) ), 5, FALSE )=0, "", VLOOKUP( $A28, _xlfn._xlws.FILTER( INDIRECT("'"&K$14&"'!A2:E1000"), (INDIRECT("'"&K$14&"'!B2:B1000")=$B28) * (INDIRECT("'"&K$14&"'!C2:C1000")=$C28) ), 5, FALSE ) )} | ... Q28: {=IF( VLOOKUP( $A28, _xlfn._xlws.FILTER( INDIRECT("'"&Q$14&"'!A2:E1000"), (INDIRECT("'"&Q$14&"'!B2:B1000")=$B28) * (INDIRECT("'"&Q$14&"'!C2:C1000")=$C28) ), 5, FALSE )=0, "", VLOOKUP( $A28, _xlfn._xlws.FILTER( INDIRECT("'"&Q$14&"'!A2:E1000"), (INDIRECT("'"&Q$14&"'!B2:B1000")=$B28) * (INDIRECT("'"&Q$14&"'!C2:C1000")=$C28) ), 5, FALSE ) )}
A29: Gustavo | B29: Brasilândia do Sul | C29: 1 | D29: {=IF( VLOOKUP( $A29, _xlfn._xlws.FILTER( INDIRECT("'"&D$14&"'!A2:E1000"), (INDIRECT("'"&D$14&"'!B2:B1000")=$B29) * (INDIRECT("'"&D$14&"'!C2:C1000")=$C29) ), 5, FALSE )=0, "", VLOOKUP( $A29, _xlfn._xlws.FILTER( INDIRECT("'"&D$14&"'!A2:E1000"), (INDIRECT("'"&D$14&"'!B2:B1000")=$B29) * (INDIRECT("'"&D$14&"'!C2:C1000")=$C29) ), 5, FALSE ) )} | E29: {=IF( VLOOKUP( $A29, _xlfn._xlws.FILTER( INDIRECT("'"&E$14&"'!A2:E1000"), (INDIRECT("'"&E$14&"'!B2:B1000")=$B29) * (INDIRECT("'"&E$14&"'!C2:C1000")=$C29) ), 5, FALSE )=0, "", VLOOKUP( $A29, _xlfn._xlws.FILTER( INDIRECT("'"&E$14&"'!A2:E1000"), (INDIRECT("'"&E$14&"'!B2:B1000")=$B29) * (INDIRECT("'"&E$14&"'!C2:C1000")=$C29) ), 5, FALSE ) )} | F29: {=IF( VLOOKUP( $A29, _xlfn._xlws.FILTER( INDIRECT("'"&F$14&"'!A2:E1000"), (INDIRECT("'"&F$14&"'!B2:B1000")=$B29) * (INDIRECT("'"&F$14&"'!C2:C1000")=$C29) ), 5, FALSE )=0, "", VLOOKUP( $A29, _xlfn._xlws.FILTER( INDIRECT("'"&F$14&"'!A2:E1000"), (INDIRECT("'"&F$14&"'!B2:B1000")=$B29) * (INDIRECT("'"&F$14&"'!C2:C1000")=$C29) ), 5, FALSE ) )} | G29: {=IF( VLOOKUP( $A29, _xlfn._xlws.FILTER( INDIRECT("'"&G$14&"'!A2:E1000"), (INDIRECT("'"&G$14&"'!B2:B1000")=$B29) * (INDIRECT("'"&G$14&"'!C2:C1000")=$C29) ), 5, FALSE )=0, "", VLOOKUP( $A29, _xlfn._xlws.FILTER( INDIRECT("'"&G$14&"'!A2:E1000"), (INDIRECT("'"&G$14&"'!B2:B1000")=$B29) * (INDIRECT("'"&G$14&"'!C2:C1000")=$C29) ), 5, FALSE ) )} | H29: {=IF( VLOOKUP( $A29, _xlfn._xlws.FILTER( INDIRECT("'"&H$14&"'!A2:E1000"), (INDIRECT("'"&H$14&"'!B2:B1000")=$B29) * (INDIRECT("'"&H$14&"'!C2:C1000")=$C29) ), 5, FALSE )=0, "", VLOOKUP( $A29, _xlfn._xlws.FILTER( INDIRECT("'"&H$14&"'!A2:E1000"), (INDIRECT("'"&H$14&"'!B2:B1000")=$B29) * (INDIRECT("'"&H$14&"'!C2:C1000")=$C29) ), 5, FALSE ) )} | I29: {=IF( VLOOKUP( $A29, _xlfn._xlws.FILTER( INDIRECT("'"&I$14&"'!A2:E1000"), (INDIRECT("'"&I$14&"'!B2:B1000")=$B29) * (INDIRECT("'"&I$14&"'!C2:C1000")=$C29) ), 5, FALSE )=0, "", VLOOKUP( $A29, _xlfn._xlws.FILTER( INDIRECT("'"&I$14&"'!A2:E1000"), (INDIRECT("'"&I$14&"'!B2:B1000")=$B29) * (INDIRECT("'"&I$14&"'!C2:C1000")=$C29) ), 5, FALSE ) )} | J29: {=IF( VLOOKUP( $A29, _xlfn._xlws.FILTER( INDIRECT("'"&J$14&"'!A2:E1000"), (INDIRECT("'"&J$14&"'!B2:B1000")=$B29) * (INDIRECT("'"&J$14&"'!C2:C1000")=$C29) ), 5, FALSE )=0, "", VLOOKUP( $A29, _xlfn._xlws.FILTER( INDIRECT("'"&J$14&"'!A2:E1000"), (INDIRECT("'"&J$14&"'!B2:B1000")=$B29) * (INDIRECT("'"&J$14&"'!C2:C1000")=$C29) ), 5, FALSE ) )} | K29: {=IF( VLOOKUP( $A29, _xlfn._xlws.FILTER( INDIRECT("'"&K$14&"'!A2:E1000"), (INDIRECT("'"&K$14&"'!B2:B1000")=$B29) * (INDIRECT("'"&K$14&"'!C2:C1000")=$C29) ), 5, FALSE )=0, "", VLOOKUP( $A29, _xlfn._xlws.FILTER( INDIRECT("'"&K$14&"'!A2:E1000"), (INDIRECT("'"&K$14&"'!B2:B1000")=$B29) * (INDIRECT("'"&K$14&"'!C2:C1000")=$C29) ), 5, FALSE ) )} | ... Q29: {=IF( VLOOKUP( $A29, _xlfn._xlws.FILTER( INDIRECT("'"&Q$14&"'!A2:E1000"), (INDIRECT("'"&Q$14&"'!B2:B1000")=$B29) * (INDIRECT("'"&Q$14&"'!C2:C1000")=$C29) ), 5, FALSE )=0, "", VLOOKUP( $A29, _xlfn._xlws.FILTER( INDIRECT("'"&Q$14&"'!A2:E1000"), (INDIRECT("'"&Q$14&"'!B2:B1000")=$B29) * (INDIRECT("'"&Q$14&"'!C2:C1000")=$C29) ), 5, FALSE ) )}
A30: Gustavo | B30: Cafelândia | C30: 1 | D30: {=IF( VLOOKUP( $A30, _xlfn._xlws.FILTER( INDIRECT("'"&D$14&"'!A2:E1000"), (INDIRECT("'"&D$14&"'!B2:B1000")=$B30) * (INDIRECT("'"&D$14&"'!C2:C1000")=$C30) ), 5, FALSE )=0, "", VLOOKUP( $A30, _xlfn._xlws.FILTER( INDIRECT("'"&D$14&"'!A2:E1000"), (INDIRECT("'"&D$14&"'!B2:B1000")=$B30) * (INDIRECT("'"&D$14&"'!C2:C1000")=$C30) ), 5, FALSE ) )} | E30: {=IF( VLOOKUP( $A30, _xlfn._xlws.FILTER( INDIRECT("'"&E$14&"'!A2:E1000"), (INDIRECT("'"&E$14&"'!B2:B1000")=$B30) * (INDIRECT("'"&E$14&"'!C2:C1000")=$C30) ), 5, FALSE )=0, "", VLOOKUP( $A30, _xlfn._xlws.FILTER( INDIRECT("'"&E$14&"'!A2:E1000"), (INDIRECT("'"&E$14&"'!B2:B1000")=$B30) * (INDIRECT("'"&E$14&"'!C2:C1000")=$C30) ), 5, FALSE ) )} | F30: {=IF( VLOOKUP( $A30, _xlfn._xlws.FILTER( INDIRECT("'"&F$14&"'!A2:E1000"), (INDIRECT("'"&F$14&"'!B2:B1000")=$B30) * (INDIRECT("'"&F$14&"'!C2:C1000")=$C30) ), 5, FALSE )=0, "", VLOOKUP( $A30, _xlfn._xlws.FILTER( INDIRECT("'"&F$14&"'!A2:E1000"), (INDIRECT("'"&F$14&"'!B2:B1000")=$B30) * (INDIRECT("'"&F$14&"'!C2:C1000")=$C30) ), 5, FALSE ) )} | G30: {=IF( VLOOKUP( $A30, _xlfn._xlws.FILTER( INDIRECT("'"&G$14&"'!A2:E1000"), (INDIRECT("'"&G$14&"'!B2:B1000")=$B30) * (INDIRECT("'"&G$14&"'!C2:C1000")=$C30) ), 5, FALSE )=0, "", VLOOKUP( $A30, _xlfn._xlws.FILTER( INDIRECT("'"&G$14&"'!A2:E1000"), (INDIRECT("'"&G$14&"'!B2:B1000")=$B30) * (INDIRECT("'"&G$14&"'!C2:C1000")=$C30) ), 5, FALSE ) )} | H30: {=IF( VLOOKUP( $A30, _xlfn._xlws.FILTER( INDIRECT("'"&H$14&"'!A2:E1000"), (INDIRECT("'"&H$14&"'!B2:B1000")=$B30) * (INDIRECT("'"&H$14&"'!C2:C1000")=$C30) ), 5, FALSE )=0, "", VLOOKUP( $A30, _xlfn._xlws.FILTER( INDIRECT("'"&H$14&"'!A2:E1000"), (INDIRECT("'"&H$14&"'!B2:B1000")=$B30) * (INDIRECT("'"&H$14&"'!C2:C1000")=$C30) ), 5, FALSE ) )} | I30: {=IF( VLOOKUP( $A30, _xlfn._xlws.FILTER( INDIRECT("'"&I$14&"'!A2:E1000"), (INDIRECT("'"&I$14&"'!B2:B1000")=$B30) * (INDIRECT("'"&I$14&"'!C2:C1000")=$C30) ), 5, FALSE )=0, "", VLOOKUP( $A30, _xlfn._xlws.FILTER( INDIRECT("'"&I$14&"'!A2:E1000"), (INDIRECT("'"&I$14&"'!B2:B1000")=$B30) * (INDIRECT("'"&I$14&"'!C2:C1000")=$C30) ), 5, FALSE ) )} | J30: {=IF( VLOOKUP( $A30, _xlfn._xlws.FILTER( INDIRECT("'"&J$14&"'!A2:E1000"), (INDIRECT("'"&J$14&"'!B2:B1000")=$B30) * (INDIRECT("'"&J$14&"'!C2:C1000")=$C30) ), 5, FALSE )=0, "", VLOOKUP( $A30, _xlfn._xlws.FILTER( INDIRECT("'"&J$14&"'!A2:E1000"), (INDIRECT("'"&J$14&"'!B2:B1000")=$B30) * (INDIRECT("'"&J$14&"'!C2:C1000")=$C30) ), 5, FALSE ) )} | K30: {=IF( VLOOKUP( $A30, _xlfn._xlws.FILTER( INDIRECT("'"&K$14&"'!A2:E1000"), (INDIRECT("'"&K$14&"'!B2:B1000")=$B30) * (INDIRECT("'"&K$14&"'!C2:C1000")=$C30) ), 5, FALSE )=0, "", VLOOKUP( $A30, _xlfn._xlws.FILTER( INDIRECT("'"&K$14&"'!A2:E1000"), (INDIRECT("'"&K$14&"'!B2:B1000")=$B30) * (INDIRECT("'"&K$14&"'!C2:C1000")=$C30) ), 5, FALSE ) )} | ... Q30: {=IF( VLOOKUP( $A30, _xlfn._xlws.FILTER( INDIRECT("'"&Q$14&"'!A2:E1000"), (INDIRECT("'"&Q$14&"'!B2:B1000")=$B30) * (INDIRECT("'"&Q$14&"'!C2:C1000")=$C30) ), 5, FALSE )=0, "", VLOOKUP( $A30, _xlfn._xlws.FILTER( INDIRECT("'"&Q$14&"'!A2:E1000"), (INDIRECT("'"&Q$14&"'!B2:B1000")=$B30) * (INDIRECT("'"&Q$14&"'!C2:C1000")=$C30) ), 5, FALSE ) )}
A31: Gustavo | B31: Formosa do Oeste | C31: 1 | D31: {=IF( VLOOKUP( $A31, _xlfn._xlws.FILTER( INDIRECT("'"&D$14&"'!A2:E1000"), (INDIRECT("'"&D$14&"'!B2:B1000")=$B31) * (INDIRECT("'"&D$14&"'!C2:C1000")=$C31) ), 5, FALSE )=0, "", VLOOKUP( $A31, _xlfn._xlws.FILTER( INDIRECT("'"&D$14&"'!A2:E1000"), (INDIRECT("'"&D$14&"'!B2:B1000")=$B31) * (INDIRECT("'"&D$14&"'!C2:C1000")=$C31) ), 5, FALSE ) )} | E31: {=IF( VLOOKUP( $A31, _xlfn._xlws.FILTER( INDIRECT("'"&E$14&"'!A2:E1000"), (INDIRECT("'"&E$14&"'!B2:B1000")=$B31) * (INDIRECT("'"&E$14&"'!C2:C1000")=$C31) ), 5, FALSE )=0, "", VLOOKUP( $A31, _xlfn._xlws.FILTER( INDIRECT("'"&E$14&"'!A2:E1000"), (INDIRECT("'"&E$14&"'!B2:B1000")=$B31) * (INDIRECT("'"&E$14&"'!C2:C1000")=$C31) ), 5, FALSE ) )} | F31: {=IF( VLOOKUP( $A31, _xlfn._xlws.FILTER( INDIRECT("'"&F$14&"'!A2:E1000"), (INDIRECT("'"&F$14&"'!B2:B1000")=$B31) * (INDIRECT("'"&F$14&"'!C2:C1000")=$C31) ), 5, FALSE )=0, "", VLOOKUP( $A31, _xlfn._xlws.FILTER( INDIRECT("'"&F$14&"'!A2:E1000"), (INDIRECT("'"&F$14&"'!B2:B1000")=$B31) * (INDIRECT("'"&F$14&"'!C2:C1000")=$C31) ), 5, FALSE ) )} | G31: {=IF( VLOOKUP( $A31, _xlfn._xlws.FILTER( INDIRECT("'"&G$14&"'!A2:E1000"), (INDIRECT("'"&G$14&"'!B2:B1000")=$B31) * (INDIRECT("'"&G$14&"'!C2:C1000")=$C31) ), 5, FALSE )=0, "", VLOOKUP( $A31, _xlfn._xlws.FILTER( INDIRECT("'"&G$14&"'!A2:E1000"), (INDIRECT("'"&G$14&"'!B2:B1000")=$B31) * (INDIRECT("'"&G$14&"'!C2:C1000")=$C31) ), 5, FALSE ) )} | H31: {=IF( VLOOKUP( $A31, _xlfn._xlws.FILTER( INDIRECT("'"&H$14&"'!A2:E1000"), (INDIRECT("'"&H$14&"'!B2:B1000")=$B31) * (INDIRECT("'"&H$14&"'!C2:C1000")=$C31) ), 5, FALSE )=0, "", VLOOKUP( $A31, _xlfn._xlws.FILTER( INDIRECT("'"&H$14&"'!A2:E1000"), (INDIRECT("'"&H$14&"'!B2:B1000")=$B31) * (INDIRECT("'"&H$14&"'!C2:C1000")=$C31) ), 5, FALSE ) )} | I31: {=IF( VLOOKUP( $A31, _xlfn._xlws.FILTER( INDIRECT("'"&I$14&"'!A2:E1000"), (INDIRECT("'"&I$14&"'!B2:B1000")=$B31) * (INDIRECT("'"&I$14&"'!C2:C1000")=$C31) ), 5, FALSE )=0, "", VLOOKUP( $A31, _xlfn._xlws.FILTER( INDIRECT("'"&I$14&"'!A2:E1000"), (INDIRECT("'"&I$14&"'!B2:B1000")=$B31) * (INDIRECT("'"&I$14&"'!C2:C1000")=$C31) ), 5, FALSE ) )} | J31: {=IF( VLOOKUP( $A31, _xlfn._xlws.FILTER( INDIRECT("'"&J$14&"'!A2:E1000"), (INDIRECT("'"&J$14&"'!B2:B1000")=$B31) * (INDIRECT("'"&J$14&"'!C2:C1000")=$C31) ), 5, FALSE )=0, "", VLOOKUP( $A31, _xlfn._xlws.FILTER( INDIRECT("'"&J$14&"'!A2:E1000"), (INDIRECT("'"&J$14&"'!B2:B1000")=$B31) * (INDIRECT("'"&J$14&"'!C2:C1000")=$C31) ), 5, FALSE ) )} | K31: {=IF( VLOOKUP( $A31, _xlfn._xlws.FILTER( INDIRECT("'"&K$14&"'!A2:E1000"), (INDIRECT("'"&K$14&"'!B2:B1000")=$B31) * (INDIRECT("'"&K$14&"'!C2:C1000")=$C31) ), 5, FALSE )=0, "", VLOOKUP( $A31, _xlfn._xlws.FILTER( INDIRECT("'"&K$14&"'!A2:E1000"), (INDIRECT("'"&K$14&"'!B2:B1000")=$B31) * (INDIRECT("'"&K$14&"'!C2:C1000")=$C31) ), 5, FALSE ) )} | ... Q31: {=IF( VLOOKUP( $A31, _xlfn._xlws.FILTER( INDIRECT("'"&Q$14&"'!A2:E1000"), (INDIRECT("'"&Q$14&"'!B2:B1000")=$B31) * (INDIRECT("'"&Q$14&"'!C2:C1000")=$C31) ), 5, FALSE )=0, "", VLOOKUP( $A31, _xlfn._xlws.FILTER( INDIRECT("'"&Q$14&"'!A2:E1000"), (INDIRECT("'"&Q$14&"'!B2:B1000")=$B31) * (INDIRECT("'"&Q$14&"'!C2:C1000")=$C31) ), 5, FALSE ) )}
A32: Gustavo | B32: Iracema do Oeste | C32: 1 | D32: {=IF( VLOOKUP( $A32, _xlfn._xlws.FILTER( INDIRECT("'"&D$14&"'!A2:E1000"), (INDIRECT("'"&D$14&"'!B2:B1000")=$B32) * (INDIRECT("'"&D$14&"'!C2:C1000")=$C32) ), 5, FALSE )=0, "", VLOOKUP( $A32, _xlfn._xlws.FILTER( INDIRECT("'"&D$14&"'!A2:E1000"), (INDIRECT("'"&D$14&"'!B2:B1000")=$B32) * (INDIRECT("'"&D$14&"'!C2:C1000")=$C32) ), 5, FALSE ) )} | E32: {=IF( VLOOKUP( $A32, _xlfn._xlws.FILTER( INDIRECT("'"&E$14&"'!A2:E1000"), (INDIRECT("'"&E$14&"'!B2:B1000")=$B32) * (INDIRECT("'"&E$14&"'!C2:C1000")=$C32) ), 5, FALSE )=0, "", VLOOKUP( $A32, _xlfn._xlws.FILTER( INDIRECT("'"&E$14&"'!A2:E1000"), (INDIRECT("'"&E$14&"'!B2:B1000")=$B32) * (INDIRECT("'"&E$14&"'!C2:C1000")=$C32) ), 5, FALSE ) )} | F32: {=IF( VLOOKUP( $A32, _xlfn._xlws.FILTER( INDIRECT("'"&F$14&"'!A2:E1000"), (INDIRECT("'"&F$14&"'!B2:B1000")=$B32) * (INDIRECT("'"&F$14&"'!C2:C1000")=$C32) ), 5, FALSE )=0, "", VLOOKUP( $A32, _xlfn._xlws.FILTER( INDIRECT("'"&F$14&"'!A2:E1000"), (INDIRECT("'"&F$14&"'!B2:B1000")=$B32) * (INDIRECT("'"&F$14&"'!C2:C1000")=$C32) ), 5, FALSE ) )} | G32: {=IF( VLOOKUP( $A32, _xlfn._xlws.FILTER( INDIRECT("'"&G$14&"'!A2:E1000"), (INDIRECT("'"&G$14&"'!B2:B1000")=$B32) * (INDIRECT("'"&G$14&"'!C2:C1000")=$C32) ), 5, FALSE )=0, "", VLOOKUP( $A32, _xlfn._xlws.FILTER( INDIRECT("'"&G$14&"'!A2:E1000"), (INDIRECT("'"&G$14&"'!B2:B1000")=$B32) * (INDIRECT("'"&G$14&"'!C2:C1000")=$C32) ), 5, FALSE ) )} | H32: {=IF( VLOOKUP( $A32, _xlfn._xlws.FILTER( INDIRECT("'"&H$14&"'!A2:E1000"), (INDIRECT("'"&H$14&"'!B2:B1000")=$B32) * (INDIRECT("'"&H$14&"'!C2:C1000")=$C32) ), 5, FALSE )=0, "", VLOOKUP( $A32, _xlfn._xlws.FILTER( INDIRECT("'"&H$14&"'!A2:E1000"), (INDIRECT("'"&H$14&"'!B2:B1000")=$B32) * (INDIRECT("'"&H$14&"'!C2:C1000")=$C32) ), 5, FALSE ) )} | I32: {=IF( VLOOKUP( $A32, _xlfn._xlws.FILTER( INDIRECT("'"&I$14&"'!A2:E1000"), (INDIRECT("'"&I$14&"'!B2:B1000")=$B32) * (INDIRECT("'"&I$14&"'!C2:C1000")=$C32) ), 5, FALSE )=0, "", VLOOKUP( $A32, _xlfn._xlws.FILTER( INDIRECT("'"&I$14&"'!A2:E1000"), (INDIRECT("'"&I$14&"'!B2:B1000")=$B32) * (INDIRECT("'"&I$14&"'!C2:C1000")=$C32) ), 5, FALSE ) )} | J32: {=IF( VLOOKUP( $A32, _xlfn._xlws.FILTER( INDIRECT("'"&J$14&"'!A2:E1000"), (INDIRECT("'"&J$14&"'!B2:B1000")=$B32) * (INDIRECT("'"&J$14&"'!C2:C1000")=$C32) ), 5, FALSE )=0, "", VLOOKUP( $A32, _xlfn._xlws.FILTER( INDIRECT("'"&J$14&"'!A2:E1000"), (INDIRECT("'"&J$14&"'!B2:B1000")=$B32) * (INDIRECT("'"&J$14&"'!C2:C1000")=$C32) ), 5, FALSE ) )} | K32: {=IF( VLOOKUP( $A32, _xlfn._xlws.FILTER( INDIRECT("'"&K$14&"'!A2:E1000"), (INDIRECT("'"&K$14&"'!B2:B1000")=$B32) * (INDIRECT("'"&K$14&"'!C2:C1000")=$C32) ), 5, FALSE )=0, "", VLOOKUP( $A32, _xlfn._xlws.FILTER( INDIRECT("'"&K$14&"'!A2:E1000"), (INDIRECT("'"&K$14&"'!B2:B1000")=$B32) * (INDIRECT("'"&K$14&"'!C2:C1000")=$C32) ), 5, FALSE ) )} | ... Q32: {=IF( VLOOKUP( $A32, _xlfn._xlws.FILTER( INDIRECT("'"&Q$14&"'!A2:E1000"), (INDIRECT("'"&Q$14&"'!B2:B1000")=$B32) * (INDIRECT("'"&Q$14&"'!C2:C1000")=$C32) ), 5, FALSE )=0, "", VLOOKUP( $A32, _xlfn._xlws.FILTER( INDIRECT("'"&Q$14&"'!A2:E1000"), (INDIRECT("'"&Q$14&"'!B2:B1000")=$B32) * (INDIRECT("'"&Q$14&"'!C2:C1000")=$C32) ), 5, FALSE ) )}
A33: Gustavo | B33: Jesuítas | C33: 1 | D33: {=IF( VLOOKUP( $A33, _xlfn._xlws.FILTER( INDIRECT("'"&D$14&"'!A2:E1000"), (INDIRECT("'"&D$14&"'!B2:B1000")=$B33) * (INDIRECT("'"&D$14&"'!C2:C1000")=$C33) ), 5, FALSE )=0, "", VLOOKUP( $A33, _xlfn._xlws.FILTER( INDIRECT("'"&D$14&"'!A2:E1000"), (INDIRECT("'"&D$14&"'!B2:B1000")=$B33) * (INDIRECT("'"&D$14&"'!C2:C1000")=$C33) ), 5, FALSE ) )} | E33: {=IF( VLOOKUP( $A33, _xlfn._xlws.FILTER( INDIRECT("'"&E$14&"'!A2:E1000"), (INDIRECT("'"&E$14&"'!B2:B1000")=$B33) * (INDIRECT("'"&E$14&"'!C2:C1000")=$C33) ), 5, FALSE )=0, "", VLOOKUP( $A33, _xlfn._xlws.FILTER( INDIRECT("'"&E$14&"'!A2:E1000"), (INDIRECT("'"&E$14&"'!B2:B1000")=$B33) * (INDIRECT("'"&E$14&"'!C2:C1000")=$C33) ), 5, FALSE ) )} | F33: {=IF( VLOOKUP( $A33, _xlfn._xlws.FILTER( INDIRECT("'"&F$14&"'!A2:E1000"), (INDIRECT("'"&F$14&"'!B2:B1000")=$B33) * (INDIRECT("'"&F$14&"'!C2:C1000")=$C33) ), 5, FALSE )=0, "", VLOOKUP( $A33, _xlfn._xlws.FILTER( INDIRECT("'"&F$14&"'!A2:E1000"), (INDIRECT("'"&F$14&"'!B2:B1000")=$B33) * (INDIRECT("'"&F$14&"'!C2:C1000")=$C33) ), 5, FALSE ) )} | G33: {=IF( VLOOKUP( $A33, _xlfn._xlws.FILTER( INDIRECT("'"&G$14&"'!A2:E1000"), (INDIRECT("'"&G$14&"'!B2:B1000")=$B33) * (INDIRECT("'"&G$14&"'!C2:C1000")=$C33) ), 5, FALSE )=0, "", VLOOKUP( $A33, _xlfn._xlws.FILTER( INDIRECT("'"&G$14&"'!A2:E1000"), (INDIRECT("'"&G$14&"'!B2:B1000")=$B33) * (INDIRECT("'"&G$14&"'!C2:C1000")=$C33) ), 5, FALSE ) )} | H33: {=IF( VLOOKUP( $A33, _xlfn._xlws.FILTER( INDIRECT("'"&H$14&"'!A2:E1000"), (INDIRECT("'"&H$14&"'!B2:B1000")=$B33) * (INDIRECT("'"&H$14&"'!C2:C1000")=$C33) ), 5, FALSE )=0, "", VLOOKUP( $A33, _xlfn._xlws.FILTER( INDIRECT("'"&H$14&"'!A2:E1000"), (INDIRECT("'"&H$14&"'!B2:B1000")=$B33) * (INDIRECT("'"&H$14&"'!C2:C1000")=$C33) ), 5, FALSE ) )} | I33: {=IF( VLOOKUP( $A33, _xlfn._xlws.FILTER( INDIRECT("'"&I$14&"'!A2:E1000"), (INDIRECT("'"&I$14&"'!B2:B1000")=$B33) * (INDIRECT("'"&I$14&"'!C2:C1000")=$C33) ), 5, FALSE )=0, "", VLOOKUP( $A33, _xlfn._xlws.FILTER( INDIRECT("'"&I$14&"'!A2:E1000"), (INDIRECT("'"&I$14&"'!B2:B1000")=$B33) * (INDIRECT("'"&I$14&"'!C2:C1000")=$C33) ), 5, FALSE ) )} | J33: {=IF( VLOOKUP( $A33, _xlfn._xlws.FILTER( INDIRECT("'"&J$14&"'!A2:E1000"), (INDIRECT("'"&J$14&"'!B2:B1000")=$B33) * (INDIRECT("'"&J$14&"'!C2:C1000")=$C33) ), 5, FALSE )=0, "", VLOOKUP( $A33, _xlfn._xlws.FILTER( INDIRECT("'"&J$14&"'!A2:E1000"), (INDIRECT("'"&J$14&"'!B2:B1000")=$B33) * (INDIRECT("'"&J$14&"'!C2:C1000")=$C33) ), 5, FALSE ) )} | K33: {=IF( VLOOKUP( $A33, _xlfn._xlws.FILTER( INDIRECT("'"&K$14&"'!A2:E1000"), (INDIRECT("'"&K$14&"'!B2:B1000")=$B33) * (INDIRECT("'"&K$14&"'!C2:C1000")=$C33) ), 5, FALSE )=0, "", VLOOKUP( $A33, _xlfn._xlws.FILTER( INDIRECT("'"&K$14&"'!A2:E1000"), (INDIRECT("'"&K$14&"'!B2:B1000")=$B33) * (INDIRECT("'"&K$14&"'!C2:C1000")=$C33) ), 5, FALSE ) )} | ... Q33: {=IF( VLOOKUP( $A33, _xlfn._xlws.FILTER( INDIRECT("'"&Q$14&"'!A2:E1000"), (INDIRECT("'"&Q$14&"'!B2:B1000")=$B33) * (INDIRECT("'"&Q$14&"'!C2:C1000")=$C33) ), 5, FALSE )=0, "", VLOOKUP( $A33, _xlfn._xlws.FILTER( INDIRECT("'"&Q$14&"'!A2:E1000"), (INDIRECT("'"&Q$14&"'!B2:B1000")=$B33) * (INDIRECT("'"&Q$14&"'!C2:C1000")=$C33) ), 5, FALSE ) )}
A34: Gustavo | B34: Maripa | C34: 1 | D34: {=IF( VLOOKUP( $A34, _xlfn._xlws.FILTER( INDIRECT("'"&D$14&"'!A2:E1000"), (INDIRECT("'"&D$14&"'!B2:B1000")=$B34) * (INDIRECT("'"&D$14&"'!C2:C1000")=$C34) ), 5, FALSE )=0, "", VLOOKUP( $A34, _xlfn._xlws.FILTER( INDIRECT("'"&D$14&"'!A2:E1000"), (INDIRECT("'"&D$14&"'!B2:B1000")=$B34) * (INDIRECT("'"&D$14&"'!C2:C1000")=$C34) ), 5, FALSE ) )} | E34: {=IF( VLOOKUP( $A34, _xlfn._xlws.FILTER( INDIRECT("'"&E$14&"'!A2:E1000"), (INDIRECT("'"&E$14&"'!B2:B1000")=$B34) * (INDIRECT("'"&E$14&"'!C2:C1000")=$C34) ), 5, FALSE )=0, "", VLOOKUP( $A34, _xlfn._xlws.FILTER( INDIRECT("'"&E$14&"'!A2:E1000"), (INDIRECT("'"&E$14&"'!B2:B1000")=$B34) * (INDIRECT("'"&E$14&"'!C2:C1000")=$C34) ), 5, FALSE ) )} | F34: {=IF( VLOOKUP( $A34, _xlfn._xlws.FILTER( INDIRECT("'"&F$14&"'!A2:E1000"), (INDIRECT("'"&F$14&"'!B2:B1000")=$B34) * (INDIRECT("'"&F$14&"'!C2:C1000")=$C34) ), 5, FALSE )=0, "", VLOOKUP( $A34, _xlfn._xlws.FILTER( INDIRECT("'"&F$14&"'!A2:E1000"), (INDIRECT("'"&F$14&"'!B2:B1000")=$B34) * (INDIRECT("'"&F$14&"'!C2:C1000")=$C34) ), 5, FALSE ) )} | G34: {=IF( VLOOKUP( $A34, _xlfn._xlws.FILTER( INDIRECT("'"&G$14&"'!A2:E1000"), (INDIRECT("'"&G$14&"'!B2:B1000")=$B34) * (INDIRECT("'"&G$14&"'!C2:C1000")=$C34) ), 5, FALSE )=0, "", VLOOKUP( $A34, _xlfn._xlws.FILTER( INDIRECT("'"&G$14&"'!A2:E1000"), (INDIRECT("'"&G$14&"'!B2:B1000")=$B34) * (INDIRECT("'"&G$14&"'!C2:C1000")=$C34) ), 5, FALSE ) )} | H34: {=IF( VLOOKUP( $A34, _xlfn._xlws.FILTER( INDIRECT("'"&H$14&"'!A2:E1000"), (INDIRECT("'"&H$14&"'!B2:B1000")=$B34) * (INDIRECT("'"&H$14&"'!C2:C1000")=$C34) ), 5, FALSE )=0, "", VLOOKUP( $A34, _xlfn._xlws.FILTER( INDIRECT("'"&H$14&"'!A2:E1000"), (INDIRECT("'"&H$14&"'!B2:B1000")=$B34) * (INDIRECT("'"&H$14&"'!C2:C1000")=$C34) ), 5, FALSE ) )} | I34: {=IF( VLOOKUP( $A34, _xlfn._xlws.FILTER( INDIRECT("'"&I$14&"'!A2:E1000"), (INDIRECT("'"&I$14&"'!B2:B1000")=$B34) * (INDIRECT("'"&I$14&"'!C2:C1000")=$C34) ), 5, FALSE )=0, "", VLOOKUP( $A34, _xlfn._xlws.FILTER( INDIRECT("'"&I$14&"'!A2:E1000"), (INDIRECT("'"&I$14&"'!B2:B1000")=$B34) * (INDIRECT("'"&I$14&"'!C2:C1000")=$C34) ), 5, FALSE ) )} | J34: {=IF( VLOOKUP( $A34, _xlfn._xlws.FILTER( INDIRECT("'"&J$14&"'!A2:E1000"), (INDIRECT("'"&J$14&"'!B2:B1000")=$B34) * (INDIRECT("'"&J$14&"'!C2:C1000")=$C34) ), 5, FALSE )=0, "", VLOOKUP( $A34, _xlfn._xlws.FILTER( INDIRECT("'"&J$14&"'!A2:E1000"), (INDIRECT("'"&J$14&"'!B2:B1000")=$B34) * (INDIRECT("'"&J$14&"'!C2:C1000")=$C34) ), 5, FALSE ) )} | K34: {=IF( VLOOKUP( $A34, _xlfn._xlws.FILTER( INDIRECT("'"&K$14&"'!A2:E1000"), (INDIRECT("'"&K$14&"'!B2:B1000")=$B34) * (INDIRECT("'"&K$14&"'!C2:C1000")=$C34) ), 5, FALSE )=0, "", VLOOKUP( $A34, _xlfn._xlws.FILTER( INDIRECT("'"&K$14&"'!A2:E1000"), (INDIRECT("'"&K$14&"'!B2:B1000")=$B34) * (INDIRECT("'"&K$14&"'!C2:C1000")=$C34) ), 5, FALSE ) )} | ... Q34: {=IF( VLOOKUP( $A34, _xlfn._xlws.FILTER( INDIRECT("'"&Q$14&"'!A2:E1000"), (INDIRECT("'"&Q$14&"'!B2:B1000")=$B34) * (INDIRECT("'"&Q$14&"'!C2:C1000")=$C34) ), 5, FALSE )=0, "", VLOOKUP( $A34, _xlfn._xlws.FILTER( INDIRECT("'"&Q$14&"'!A2:E1000"), (INDIRECT("'"&Q$14&"'!B2:B1000")=$B34) * (INDIRECT("'"&Q$14&"'!C2:C1000")=$C34) ), 5, FALSE ) )}
A35: Gustavo | B35: Nova Aurora | C35: 1 | D35: {=IF( VLOOKUP( $A35, _xlfn._xlws.FILTER( INDIRECT("'"&D$14&"'!A2:E1000"), (INDIRECT("'"&D$14&"'!B2:B1000")=$B35) * (INDIRECT("'"&D$14&"'!C2:C1000")=$C35) ), 5, FALSE )=0, "", VLOOKUP( $A35, _xlfn._xlws.FILTER( INDIRECT("'"&D$14&"'!A2:E1000"), (INDIRECT("'"&D$14&"'!B2:B1000")=$B35) * (INDIRECT("'"&D$14&"'!C2:C1000")=$C35) ), 5, FALSE ) )} | E35: {=IF( VLOOKUP( $A35, _xlfn._xlws.FILTER( INDIRECT("'"&E$14&"'!A2:E1000"), (INDIRECT("'"&E$14&"'!B2:B1000")=$B35) * (INDIRECT("'"&E$14&"'!C2:C1000")=$C35) ), 5, FALSE )=0, "", VLOOKUP( $A35, _xlfn._xlws.FILTER( INDIRECT("'"&E$14&"'!A2:E1000"), (INDIRECT("'"&E$14&"'!B2:B1000")=$B35) * (INDIRECT("'"&E$14&"'!C2:C1000")=$C35) ), 5, FALSE ) )} | F35: {=IF( VLOOKUP( $A35, _xlfn._xlws.FILTER( INDIRECT("'"&F$14&"'!A2:E1000"), (INDIRECT("'"&F$14&"'!B2:B1000")=$B35) * (INDIRECT("'"&F$14&"'!C2:C1000")=$C35) ), 5, FALSE )=0, "", VLOOKUP( $A35, _xlfn._xlws.FILTER( INDIRECT("'"&F$14&"'!A2:E1000"), (INDIRECT("'"&F$14&"'!B2:B1000")=$B35) * (INDIRECT("'"&F$14&"'!C2:C1000")=$C35) ), 5, FALSE ) )} | G35: {=IF( VLOOKUP( $A35, _xlfn._xlws.FILTER( INDIRECT("'"&G$14&"'!A2:E1000"), (INDIRECT("'"&G$14&"'!B2:B1000")=$B35) * (INDIRECT("'"&G$14&"'!C2:C1000")=$C35) ), 5, FALSE )=0, "", VLOOKUP( $A35, _xlfn._xlws.FILTER( INDIRECT("'"&G$14&"'!A2:E1000"), (INDIRECT("'"&G$14&"'!B2:B1000")=$B35) * (INDIRECT("'"&G$14&"'!C2:C1000")=$C35) ), 5, FALSE ) )} | H35: {=IF( VLOOKUP( $A35, _xlfn._xlws.FILTER( INDIRECT("'"&H$14&"'!A2:E1000"), (INDIRECT("'"&H$14&"'!B2:B1000")=$B35) * (INDIRECT("'"&H$14&"'!C2:C1000")=$C35) ), 5, FALSE )=0, "", VLOOKUP( $A35, _xlfn._xlws.FILTER( INDIRECT("'"&H$14&"'!A2:E1000"), (INDIRECT("'"&H$14&"'!B2:B1000")=$B35) * (INDIRECT("'"&H$14&"'!C2:C1000")=$C35) ), 5, FALSE ) )} | I35: {=IF( VLOOKUP( $A35, _xlfn._xlws.FILTER( INDIRECT("'"&I$14&"'!A2:E1000"), (INDIRECT("'"&I$14&"'!B2:B1000")=$B35) * (INDIRECT("'"&I$14&"'!C2:C1000")=$C35) ), 5, FALSE )=0, "", VLOOKUP( $A35, _xlfn._xlws.FILTER( INDIRECT("'"&I$14&"'!A2:E1000"), (INDIRECT("'"&I$14&"'!B2:B1000")=$B35) * (INDIRECT("'"&I$14&"'!C2:C1000")=$C35) ), 5, FALSE ) )} | J35: {=IF( VLOOKUP( $A35, _xlfn._xlws.FILTER( INDIRECT("'"&J$14&"'!A2:E1000"), (INDIRECT("'"&J$14&"'!B2:B1000")=$B35) * (INDIRECT("'"&J$14&"'!C2:C1000")=$C35) ), 5, FALSE )=0, "", VLOOKUP( $A35, _xlfn._xlws.FILTER( INDIRECT("'"&J$14&"'!A2:E1000"), (INDIRECT("'"&J$14&"'!B2:B1000")=$B35) * (INDIRECT("'"&J$14&"'!C2:C1000")=$C35) ), 5, FALSE ) )} | K35: {=IF( VLOOKUP( $A35, _xlfn._xlws.FILTER( INDIRECT("'"&K$14&"'!A2:E1000"), (INDIRECT("'"&K$14&"'!B2:B1000")=$B35) * (INDIRECT("'"&K$14&"'!C2:C1000")=$C35) ), 5, FALSE )=0, "", VLOOKUP( $A35, _xlfn._xlws.FILTER( INDIRECT("'"&K$14&"'!A2:E1000"), (INDIRECT("'"&K$14&"'!B2:B1000")=$B35) * (INDIRECT("'"&K$14&"'!C2:C1000")=$C35) ), 5, FALSE ) )} | ... Q35: {=IF( VLOOKUP( $A35, _xlfn._xlws.FILTER( INDIRECT("'"&Q$14&"'!A2:E1000"), (INDIRECT("'"&Q$14&"'!B2:B1000")=$B35) * (INDIRECT("'"&Q$14&"'!C2:C1000")=$C35) ), 5, FALSE )=0, "", VLOOKUP( $A35, _xlfn._xlws.FILTER( INDIRECT("'"&Q$14&"'!A2:E1000"), (INDIRECT("'"&Q$14&"'!B2:B1000")=$B35) * (INDIRECT("'"&Q$14&"'!C2:C1000")=$C35) ), 5, FALSE ) )}
A36: Gustavo | B36: Palotina | C36: 1 | D36: {=IF( VLOOKUP( $A36, _xlfn._xlws.FILTER( INDIRECT("'"&D$14&"'!A2:E1000"), (INDIRECT("'"&D$14&"'!B2:B1000")=$B36) * (INDIRECT("'"&D$14&"'!C2:C1000")=$C36) ), 5, FALSE )=0, "", VLOOKUP( $A36, _xlfn._xlws.FILTER( INDIRECT("'"&D$14&"'!A2:E1000"), (INDIRECT("'"&D$14&"'!B2:B1000")=$B36) * (INDIRECT("'"&D$14&"'!C2:C1000")=$C36) ), 5, FALSE ) )} | E36: {=IF( VLOOKUP( $A36, _xlfn._xlws.FILTER( INDIRECT("'"&E$14&"'!A2:E1000"), (INDIRECT("'"&E$14&"'!B2:B1000")=$B36) * (INDIRECT("'"&E$14&"'!C2:C1000")=$C36) ), 5, FALSE )=0, "", VLOOKUP( $A36, _xlfn._xlws.FILTER( INDIRECT("'"&E$14&"'!A2:E1000"), (INDIRECT("'"&E$14&"'!B2:B1000")=$B36) * (INDIRECT("'"&E$14&"'!C2:C1000")=$C36) ), 5, FALSE ) )} | F36: {=IF( VLOOKUP( $A36, _xlfn._xlws.FILTER( INDIRECT("'"&F$14&"'!A2:E1000"), (INDIRECT("'"&F$14&"'!B2:B1000")=$B36) * (INDIRECT("'"&F$14&"'!C2:C1000")=$C36) ), 5, FALSE )=0, "", VLOOKUP( $A36, _xlfn._xlws.FILTER( INDIRECT("'"&F$14&"'!A2:E1000"), (INDIRECT("'"&F$14&"'!B2:B1000")=$B36) * (INDIRECT("'"&F$14&"'!C2:C1000")=$C36) ), 5, FALSE ) )} | G36: {=IF( VLOOKUP( $A36, _xlfn._xlws.FILTER( INDIRECT("'"&G$14&"'!A2:E1000"), (INDIRECT("'"&G$14&"'!B2:B1000")=$B36) * (INDIRECT("'"&G$14&"'!C2:C1000")=$C36) ), 5, FALSE )=0, "", VLOOKUP( $A36, _xlfn._xlws.FILTER( INDIRECT("'"&G$14&"'!A2:E1000"), (INDIRECT("'"&G$14&"'!B2:B1000")=$B36) * (INDIRECT("'"&G$14&"'!C2:C1000")=$C36) ), 5, FALSE ) )} | H36: {=IF( VLOOKUP( $A36, _xlfn._xlws.FILTER( INDIRECT("'"&H$14&"'!A2:E1000"), (INDIRECT("'"&H$14&"'!B2:B1000")=$B36) * (INDIRECT("'"&H$14&"'!C2:C1000")=$C36) ), 5, FALSE )=0, "", VLOOKUP( $A36, _xlfn._xlws.FILTER( INDIRECT("'"&H$14&"'!A2:E1000"), (INDIRECT("'"&H$14&"'!B2:B1000")=$B36) * (INDIRECT("'"&H$14&"'!C2:C1000")=$C36) ), 5, FALSE ) )} | I36: {=IF( VLOOKUP( $A36, _xlfn._xlws.FILTER( INDIRECT("'"&I$14&"'!A2:E1000"), (INDIRECT("'"&I$14&"'!B2:B1000")=$B36) * (INDIRECT("'"&I$14&"'!C2:C1000")=$C36) ), 5, FALSE )=0, "", VLOOKUP( $A36, _xlfn._xlws.FILTER( INDIRECT("'"&I$14&"'!A2:E1000"), (INDIRECT("'"&I$14&"'!B2:B1000")=$B36) * (INDIRECT("'"&I$14&"'!C2:C1000")=$C36) ), 5, FALSE ) )} | J36: {=IF( VLOOKUP( $A36, _xlfn._xlws.FILTER( INDIRECT("'"&J$14&"'!A2:E1000"), (INDIRECT("'"&J$14&"'!B2:B1000")=$B36) * (INDIRECT("'"&J$14&"'!C2:C1000")=$C36) ), 5, FALSE )=0, "", VLOOKUP( $A36, _xlfn._xlws.FILTER( INDIRECT("'"&J$14&"'!A2:E1000"), (INDIRECT("'"&J$14&"'!B2:B1000")=$B36) * (INDIRECT("'"&J$14&"'!C2:C1000")=$C36) ), 5, FALSE ) )} | K36: {=IF( VLOOKUP( $A36, _xlfn._xlws.FILTER( INDIRECT("'"&K$14&"'!A2:E1000"), (INDIRECT("'"&K$14&"'!B2:B1000")=$B36) * (INDIRECT("'"&K$14&"'!C2:C1000")=$C36) ), 5, FALSE )=0, "", VLOOKUP( $A36, _xlfn._xlws.FILTER( INDIRECT("'"&K$14&"'!A2:E1000"), (INDIRECT("'"&K$14&"'!B2:B1000")=$B36) * (INDIRECT("'"&K$14&"'!C2:C1000")=$C36) ), 5, FALSE ) )} | ... Q36: {=IF( VLOOKUP( $A36, _xlfn._xlws.FILTER( INDIRECT("'"&Q$14&"'!A2:E1000"), (INDIRECT("'"&Q$14&"'!B2:B1000")=$B36) * (INDIRECT("'"&Q$14&"'!C2:C1000")=$C36) ), 5, FALSE )=0, "", VLOOKUP( $A36, _xlfn._xlws.FILTER( INDIRECT("'"&Q$14&"'!A2:E1000"), (INDIRECT("'"&Q$14&"'!B2:B1000")=$B36) * (INDIRECT("'"&Q$14&"'!C2:C1000")=$C36) ), 5, FALSE ) )}
A37: Gustavo | B37: Tupassi | C37: 1 | D37: {=IF( VLOOKUP( $A37, _xlfn._xlws.FILTER( INDIRECT("'"&D$14&"'!A2:E1000"), (INDIRECT("'"&D$14&"'!B2:B1000")=$B37) * (INDIRECT("'"&D$14&"'!C2:C1000")=$C37) ), 5, FALSE )=0, "", VLOOKUP( $A37, _xlfn._xlws.FILTER( INDIRECT("'"&D$14&"'!A2:E1000"), (INDIRECT("'"&D$14&"'!B2:B1000")=$B37) * (INDIRECT("'"&D$14&"'!C2:C1000")=$C37) ), 5, FALSE ) )} | E37: {=IF( VLOOKUP( $A37, _xlfn._xlws.FILTER( INDIRECT("'"&E$14&"'!A2:E1000"), (INDIRECT("'"&E$14&"'!B2:B1000")=$B37) * (INDIRECT("'"&E$14&"'!C2:C1000")=$C37) ), 5, FALSE )=0, "", VLOOKUP( $A37, _xlfn._xlws.FILTER( INDIRECT("'"&E$14&"'!A2:E1000"), (INDIRECT("'"&E$14&"'!B2:B1000")=$B37) * (INDIRECT("'"&E$14&"'!C2:C1000")=$C37) ), 5, FALSE ) )} | F37: {=IF( VLOOKUP( $A37, _xlfn._xlws.FILTER( INDIRECT("'"&F$14&"'!A2:E1000"), (INDIRECT("'"&F$14&"'!B2:B1000")=$B37) * (INDIRECT("'"&F$14&"'!C2:C1000")=$C37) ), 5, FALSE )=0, "", VLOOKUP( $A37, _xlfn._xlws.FILTER( INDIRECT("'"&F$14&"'!A2:E1000"), (INDIRECT("'"&F$14&"'!B2:B1000")=$B37) * (INDIRECT("'"&F$14&"'!C2:C1000")=$C37) ), 5, FALSE ) )} | G37: {=IF( VLOOKUP( $A37, _xlfn._xlws.FILTER( INDIRECT("'"&G$14&"'!A2:E1000"), (INDIRECT("'"&G$14&"'!B2:B1000")=$B37) * (INDIRECT("'"&G$14&"'!C2:C1000")=$C37) ), 5, FALSE )=0, "", VLOOKUP( $A37, _xlfn._xlws.FILTER( INDIRECT("'"&G$14&"'!A2:E1000"), (INDIRECT("'"&G$14&"'!B2:B1000")=$B37) * (INDIRECT("'"&G$14&"'!C2:C1000")=$C37) ), 5, FALSE ) )} | H37: {=IF( VLOOKUP( $A37, _xlfn._xlws.FILTER( INDIRECT("'"&H$14&"'!A2:E1000"), (INDIRECT("'"&H$14&"'!B2:B1000")=$B37) * (INDIRECT("'"&H$14&"'!C2:C1000")=$C37) ), 5, FALSE )=0, "", VLOOKUP( $A37, _xlfn._xlws.FILTER( INDIRECT("'"&H$14&"'!A2:E1000"), (INDIRECT("'"&H$14&"'!B2:B1000")=$B37) * (INDIRECT("'"&H$14&"'!C2:C1000")=$C37) ), 5, FALSE ) )} | I37: {=IF( VLOOKUP( $A37, _xlfn._xlws.FILTER( INDIRECT("'"&I$14&"'!A2:E1000"), (INDIRECT("'"&I$14&"'!B2:B1000")=$B37) * (INDIRECT("'"&I$14&"'!C2:C1000")=$C37) ), 5, FALSE )=0, "", VLOOKUP( $A37, _xlfn._xlws.FILTER( INDIRECT("'"&I$14&"'!A2:E1000"), (INDIRECT("'"&I$14&"'!B2:B1000")=$B37) * (INDIRECT("'"&I$14&"'!C2:C1000")=$C37) ), 5, FALSE ) )} | J37: {=IF( VLOOKUP( $A37, _xlfn._xlws.FILTER( INDIRECT("'"&J$14&"'!A2:E1000"), (INDIRECT("'"&J$14&"'!B2:B1000")=$B37) * (INDIRECT("'"&J$14&"'!C2:C1000")=$C37) ), 5, FALSE )=0, "", VLOOKUP( $A37, _xlfn._xlws.FILTER( INDIRECT("'"&J$14&"'!A2:E1000"), (INDIRECT("'"&J$14&"'!B2:B1000")=$B37) * (INDIRECT("'"&J$14&"'!C2:C1000")=$C37) ), 5, FALSE ) )} | K37: {=IF( VLOOKUP( $A37, _xlfn._xlws.FILTER( INDIRECT("'"&K$14&"'!A2:E1000"), (INDIRECT("'"&K$14&"'!B2:B1000")=$B37) * (INDIRECT("'"&K$14&"'!C2:C1000")=$C37) ), 5, FALSE )=0, "", VLOOKUP( $A37, _xlfn._xlws.FILTER( INDIRECT("'"&K$14&"'!A2:E1000"), (INDIRECT("'"&K$14&"'!B2:B1000")=$B37) * (INDIRECT("'"&K$14&"'!C2:C1000")=$C37) ), 5, FALSE ) )} | ... Q37: {=IF( VLOOKUP( $A37, _xlfn._xlws.FILTER( INDIRECT("'"&Q$14&"'!A2:E1000"), (INDIRECT("'"&Q$14&"'!B2:B1000")=$B37) * (INDIRECT("'"&Q$14&"'!C2:C1000")=$C37) ), 5, FALSE )=0, "", VLOOKUP( $A37, _xlfn._xlws.FILTER( INDIRECT("'"&Q$14&"'!A2:E1000"), (INDIRECT("'"&Q$14&"'!B2:B1000")=$B37) * (INDIRECT("'"&Q$14&"'!C2:C1000")=$C37) ), 5, FALSE ) )}
A38: Gustavo | B38: Ubirata | C38: 1 | D38: {=IF( VLOOKUP( $A38, _xlfn._xlws.FILTER( INDIRECT("'"&D$14&"'!A2:E1000"), (INDIRECT("'"&D$14&"'!B2:B1000")=$B38) * (INDIRECT("'"&D$14&"'!C2:C1000")=$C38) ), 5, FALSE )=0, "", VLOOKUP( $A38, _xlfn._xlws.FILTER( INDIRECT("'"&D$14&"'!A2:E1000"), (INDIRECT("'"&D$14&"'!B2:B1000")=$B38) * (INDIRECT("'"&D$14&"'!C2:C1000")=$C38) ), 5, FALSE ) )} | E38: {=IF( VLOOKUP( $A38, _xlfn._xlws.FILTER( INDIRECT("'"&E$14&"'!A2:E1000"), (INDIRECT("'"&E$14&"'!B2:B1000")=$B38) * (INDIRECT("'"&E$14&"'!C2:C1000")=$C38) ), 5, FALSE )=0, "", VLOOKUP( $A38, _xlfn._xlws.FILTER( INDIRECT("'"&E$14&"'!A2:E1000"), (INDIRECT("'"&E$14&"'!B2:B1000")=$B38) * (INDIRECT("'"&E$14&"'!C2:C1000")=$C38) ), 5, FALSE ) )} | F38: {=IF( VLOOKUP( $A38, _xlfn._xlws.FILTER( INDIRECT("'"&F$14&"'!A2:E1000"), (INDIRECT("'"&F$14&"'!B2:B1000")=$B38) * (INDIRECT("'"&F$14&"'!C2:C1000")=$C38) ), 5, FALSE )=0, "", VLOOKUP( $A38, _xlfn._xlws.FILTER( INDIRECT("'"&F$14&"'!A2:E1000"), (INDIRECT("'"&F$14&"'!B2:B1000")=$B38) * (INDIRECT("'"&F$14&"'!C2:C1000")=$C38) ), 5, FALSE ) )} | G38: {=IF( VLOOKUP( $A38, _xlfn._xlws.FILTER( INDIRECT("'"&G$14&"'!A2:E1000"), (INDIRECT("'"&G$14&"'!B2:B1000")=$B38) * (INDIRECT("'"&G$14&"'!C2:C1000")=$C38) ), 5, FALSE )=0, "", VLOOKUP( $A38, _xlfn._xlws.FILTER( INDIRECT("'"&G$14&"'!A2:E1000"), (INDIRECT("'"&G$14&"'!B2:B1000")=$B38) * (INDIRECT("'"&G$14&"'!C2:C1000")=$C38) ), 5, FALSE ) )} | H38: {=IF( VLOOKUP( $A38, _xlfn._xlws.FILTER( INDIRECT("'"&H$14&"'!A2:E1000"), (INDIRECT("'"&H$14&"'!B2:B1000")=$B38) * (INDIRECT("'"&H$14&"'!C2:C1000")=$C38) ), 5, FALSE )=0, "", VLOOKUP( $A38, _xlfn._xlws.FILTER( INDIRECT("'"&H$14&"'!A2:E1000"), (INDIRECT("'"&H$14&"'!B2:B1000")=$B38) * (INDIRECT("'"&H$14&"'!C2:C1000")=$C38) ), 5, FALSE ) )} | I38: {=IF( VLOOKUP( $A38, _xlfn._xlws.FILTER( INDIRECT("'"&I$14&"'!A2:E1000"), (INDIRECT("'"&I$14&"'!B2:B1000")=$B38) * (INDIRECT("'"&I$14&"'!C2:C1000")=$C38) ), 5, FALSE )=0, "", VLOOKUP( $A38, _xlfn._xlws.FILTER( INDIRECT("'"&I$14&"'!A2:E1000"), (INDIRECT("'"&I$14&"'!B2:B1000")=$B38) * (INDIRECT("'"&I$14&"'!C2:C1000")=$C38) ), 5, FALSE ) )} | J38: {=IF( VLOOKUP( $A38, _xlfn._xlws.FILTER( INDIRECT("'"&J$14&"'!A2:E1000"), (INDIRECT("'"&J$14&"'!B2:B1000")=$B38) * (INDIRECT("'"&J$14&"'!C2:C1000")=$C38) ), 5, FALSE )=0, "", VLOOKUP( $A38, _xlfn._xlws.FILTER( INDIRECT("'"&J$14&"'!A2:E1000"), (INDIRECT("'"&J$14&"'!B2:B1000")=$B38) * (INDIRECT("'"&J$14&"'!C2:C1000")=$C38) ), 5, FALSE ) )} | K38: {=IF( VLOOKUP( $A38, _xlfn._xlws.FILTER( INDIRECT("'"&K$14&"'!A2:E1000"), (INDIRECT("'"&K$14&"'!B2:B1000")=$B38) * (INDIRECT("'"&K$14&"'!C2:C1000")=$C38) ), 5, FALSE )=0, "", VLOOKUP( $A38, _xlfn._xlws.FILTER( INDIRECT("'"&K$14&"'!A2:E1000"), (INDIRECT("'"&K$14&"'!B2:B1000")=$B38) * (INDIRECT("'"&K$14&"'!C2:C1000")=$C38) ), 5, FALSE ) )} | ... Q38: {=IF( VLOOKUP( $A38, _xlfn._xlws.FILTER( INDIRECT("'"&Q$14&"'!A2:E1000"), (INDIRECT("'"&Q$14&"'!B2:B1000")=$B38) * (INDIRECT("'"&Q$14&"'!C2:C1000")=$C38) ), 5, FALSE )=0, "", VLOOKUP( $A38, _xlfn._xlws.FILTER( INDIRECT("'"&Q$14&"'!A2:E1000"), (INDIRECT("'"&Q$14&"'!B2:B1000")=$B38) * (INDIRECT("'"&Q$14&"'!C2:C1000")=$C38) ), 5, FALSE ) )}
A40: Regional | B40: Municípios | C40: UVR | D40: 11.24 | E40: 12.24 | F40: 01.25 | G40: 02.25 | H40: 03.25 | I40: 04.25 | J40: 05.25 | K40: 06.25 | L40: 07.25 | M40: 08.25 | N40: 09.25 | O40: 10.25 | P40: 11.25 | Q40: 12.25
A41: Larissa | B41: Foz do Iguaçu | C41: 1 | D41: {=IF( VLOOKUP( $A41, _xlfn._xlws.FILTER( INDIRECT("'"&D$14&"'!A2:E1000"), (INDIRECT("'"&D$14&"'!B2:B1000")=$B41) * (INDIRECT("'"&D$14&"'!C2:C1000")=$C41) ), 5, FALSE )=0, "", VLOOKUP( $A41, _xlfn._xlws.FILTER( INDIRECT("'"&D$14&"'!A2:E1000"), (INDIRECT("'"&D$14&"'!B2:B1000")=$B41) * (INDIRECT("'"&D$14&"'!C2:C1000")=$C41) ), 5, FALSE ) )} | E41: {=IF( VLOOKUP( $A41, _xlfn._xlws.FILTER( INDIRECT("'"&E$14&"'!A2:E1000"), (INDIRECT("'"&E$14&"'!B2:B1000")=$B41) * (INDIRECT("'"&E$14&"'!C2:C1000")=$C41) ), 5, FALSE )=0, "", VLOOKUP( $A41, _xlfn._xlws.FILTER( INDIRECT("'"&E$14&"'!A2:E1000"), (INDIRECT("'"&E$14&"'!B2:B1000")=$B41) * (INDIRECT("'"&E$14&"'!C2:C1000")=$C41) ), 5, FALSE ) )} | F41: {=IF( VLOOKUP( $A41, _xlfn._xlws.FILTER( INDIRECT("'"&F$14&"'!A2:E1000"), (INDIRECT("'"&F$14&"'!B2:B1000")=$B41) * (INDIRECT("'"&F$14&"'!C2:C1000")=$C41) ), 5, FALSE )=0, "", VLOOKUP( $A41, _xlfn._xlws.FILTER( INDIRECT("'"&F$14&"'!A2:E1000"), (INDIRECT("'"&F$14&"'!B2:B1000")=$B41) * (INDIRECT("'"&F$14&"'!C2:C1000")=$C41) ), 5, FALSE ) )} | G41: {=IF( VLOOKUP( $A41, _xlfn._xlws.FILTER( INDIRECT("'"&G$14&"'!A2:E1000"), (INDIRECT("'"&G$14&"'!B2:B1000")=$B41) * (INDIRECT("'"&G$14&"'!C2:C1000")=$C41) ), 5, FALSE )=0, "", VLOOKUP( $A41, _xlfn._xlws.FILTER( INDIRECT("'"&G$14&"'!A2:E1000"), (INDIRECT("'"&G$14&"'!B2:B1000")=$B41) * (INDIRECT("'"&G$14&"'!C2:C1000")=$C41) ), 5, FALSE ) )} | H41: {=IF( VLOOKUP( $A41, _xlfn._xlws.FILTER( INDIRECT("'"&H$14&"'!A2:E1000"), (INDIRECT("'"&H$14&"'!B2:B1000")=$B41) * (INDIRECT("'"&H$14&"'!C2:C1000")=$C41) ), 5, FALSE )=0, "", VLOOKUP( $A41, _xlfn._xlws.FILTER( INDIRECT("'"&H$14&"'!A2:E1000"), (INDIRECT("'"&H$14&"'!B2:B1000")=$B41) * (INDIRECT("'"&H$14&"'!C2:C1000")=$C41) ), 5, FALSE ) )} | I41: {=IF( VLOOKUP( $A41, _xlfn._xlws.FILTER( INDIRECT("'"&I$14&"'!A2:E1000"), (INDIRECT("'"&I$14&"'!B2:B1000")=$B41) * (INDIRECT("'"&I$14&"'!C2:C1000")=$C41) ), 5, FALSE )=0, "", VLOOKUP( $A41, _xlfn._xlws.FILTER( INDIRECT("'"&I$14&"'!A2:E1000"), (INDIRECT("'"&I$14&"'!B2:B1000")=$B41) * (INDIRECT("'"&I$14&"'!C2:C1000")=$C41) ), 5, FALSE ) )} | J41: {=IF( VLOOKUP( $A41, _xlfn._xlws.FILTER( INDIRECT("'"&J$14&"'!A2:E1000"), (INDIRECT("'"&J$14&"'!B2:B1000")=$B41) * (INDIRECT("'"&J$14&"'!C2:C1000")=$C41) ), 5, FALSE )=0, "", VLOOKUP( $A41, _xlfn._xlws.FILTER( INDIRECT("'"&J$14&"'!A2:E1000"), (INDIRECT("'"&J$14&"'!B2:B1000")=$B41) * (INDIRECT("'"&J$14&"'!C2:C1000")=$C41) ), 5, FALSE ) )} | K41: {=IF( VLOOKUP( $A41, _xlfn._xlws.FILTER( INDIRECT("'"&K$14&"'!A2:E1000"), (INDIRECT("'"&K$14&"'!B2:B1000")=$B41) * (INDIRECT("'"&K$14&"'!C2:C1000")=$C41) ), 5, FALSE )=0, "", VLOOKUP( $A41, _xlfn._xlws.FILTER( INDIRECT("'"&K$14&"'!A2:E1000"), (INDIRECT("'"&K$14&"'!B2:B1000")=$B41) * (INDIRECT("'"&K$14&"'!C2:C1000")=$C41) ), 5, FALSE ) )} | ... Q41: {=IF( VLOOKUP( $A41, _xlfn._xlws.FILTER( INDIRECT("'"&Q$14&"'!A2:E1000"), (INDIRECT("'"&Q$14&"'!B2:B1000")=$B41) * (INDIRECT("'"&Q$14&"'!C2:C1000")=$C41) ), 5, FALSE )=0, "", VLOOKUP( $A41, _xlfn._xlws.FILTER( INDIRECT("'"&Q$14&"'!A2:E1000"), (INDIRECT("'"&Q$14&"'!B2:B1000")=$B41) * (INDIRECT("'"&Q$14&"'!C2:C1000")=$C41) ), 5, FALSE ) )}
A42: Larissa | B42: Foz do Iguaçu | C42: 2 | D42: {=IF( VLOOKUP( $A42, _xlfn._xlws.FILTER( INDIRECT("'"&D$14&"'!A2:E1000"), (INDIRECT("'"&D$14&"'!B2:B1000")=$B42) * (INDIRECT("'"&D$14&"'!C2:C1000")=$C42) ), 5, FALSE )=0, "", VLOOKUP( $A42, _xlfn._xlws.FILTER( INDIRECT("'"&D$14&"'!A2:E1000"), (INDIRECT("'"&D$14&"'!B2:B1000")=$B42) * (INDIRECT("'"&D$14&"'!C2:C1000")=$C42) ), 5, FALSE ) )} | E42: {=IF( VLOOKUP( $A42, _xlfn._xlws.FILTER( INDIRECT("'"&E$14&"'!A2:E1000"), (INDIRECT("'"&E$14&"'!B2:B1000")=$B42) * (INDIRECT("'"&E$14&"'!C2:C1000")=$C42) ), 5, FALSE )=0, "", VLOOKUP( $A42, _xlfn._xlws.FILTER( INDIRECT("'"&E$14&"'!A2:E1000"), (INDIRECT("'"&E$14&"'!B2:B1000")=$B42) * (INDIRECT("'"&E$14&"'!C2:C1000")=$C42) ), 5, FALSE ) )} | F42: {=IF( VLOOKUP( $A42, _xlfn._xlws.FILTER( INDIRECT("'"&F$14&"'!A2:E1000"), (INDIRECT("'"&F$14&"'!B2:B1000")=$B42) * (INDIRECT("'"&F$14&"'!C2:C1000")=$C42) ), 5, FALSE )=0, "", VLOOKUP( $A42, _xlfn._xlws.FILTER( INDIRECT("'"&F$14&"'!A2:E1000"), (INDIRECT("'"&F$14&"'!B2:B1000")=$B42) * (INDIRECT("'"&F$14&"'!C2:C1000")=$C42) ), 5, FALSE ) )} | G42: {=IF( VLOOKUP( $A42, _xlfn._xlws.FILTER( INDIRECT("'"&G$14&"'!A2:E1000"), (INDIRECT("'"&G$14&"'!B2:B1000")=$B42) * (INDIRECT("'"&G$14&"'!C2:C1000")=$C42) ), 5, FALSE )=0, "", VLOOKUP( $A42, _xlfn._xlws.FILTER( INDIRECT("'"&G$14&"'!A2:E1000"), (INDIRECT("'"&G$14&"'!B2:B1000")=$B42) * (INDIRECT("'"&G$14&"'!C2:C1000")=$C42) ), 5, FALSE ) )} | H42: {=IF( VLOOKUP( $A42, _xlfn._xlws.FILTER( INDIRECT("'"&H$14&"'!A2:E1000"), (INDIRECT("'"&H$14&"'!B2:B1000")=$B42) * (INDIRECT("'"&H$14&"'!C2:C1000")=$C42) ), 5, FALSE )=0, "", VLOOKUP( $A42, _xlfn._xlws.FILTER( INDIRECT("'"&H$14&"'!A2:E1000"), (INDIRECT("'"&H$14&"'!B2:B1000")=$B42) * (INDIRECT("'"&H$14&"'!C2:C1000")=$C42) ), 5, FALSE ) )} | I42: {=IF( VLOOKUP( $A42, _xlfn._xlws.FILTER( INDIRECT("'"&I$14&"'!A2:E1000"), (INDIRECT("'"&I$14&"'!B2:B1000")=$B42) * (INDIRECT("'"&I$14&"'!C2:C1000")=$C42) ), 5, FALSE )=0, "", VLOOKUP( $A42, _xlfn._xlws.FILTER( INDIRECT("'"&I$14&"'!A2:E1000"), (INDIRECT("'"&I$14&"'!B2:B1000")=$B42) * (INDIRECT("'"&I$14&"'!C2:C1000")=$C42) ), 5, FALSE ) )} | J42: {=IF( VLOOKUP( $A42, _xlfn._xlws.FILTER( INDIRECT("'"&J$14&"'!A2:E1000"), (INDIRECT("'"&J$14&"'!B2:B1000")=$B42) * (INDIRECT("'"&J$14&"'!C2:C1000")=$C42) ), 5, FALSE )=0, "", VLOOKUP( $A42, _xlfn._xlws.FILTER( INDIRECT("'"&J$14&"'!A2:E1000"), (INDIRECT("'"&J$14&"'!B2:B1000")=$B42) * (INDIRECT("'"&J$14&"'!C2:C1000")=$C42) ), 5, FALSE ) )} | K42: {=IF( VLOOKUP( $A42, _xlfn._xlws.FILTER( INDIRECT("'"&K$14&"'!A2:E1000"), (INDIRECT("'"&K$14&"'!B2:B1000")=$B42) * (INDIRECT("'"&K$14&"'!C2:C1000")=$C42) ), 5, FALSE )=0, "", VLOOKUP( $A42, _xlfn._xlws.FILTER( INDIRECT("'"&K$14&"'!A2:E1000"), (INDIRECT("'"&K$14&"'!B2:B1000")=$B42) * (INDIRECT("'"&K$14&"'!C2:C1000")=$C42) ), 5, FALSE ) )} | ... Q42: {=IF( VLOOKUP( $A42, _xlfn._xlws.FILTER( INDIRECT("'"&Q$14&"'!A2:E1000"), (INDIRECT("'"&Q$14&"'!B2:B1000")=$B42) * (INDIRECT("'"&Q$14&"'!C2:C1000")=$C42) ), 5, FALSE )=0, "", VLOOKUP( $A42, _xlfn._xlws.FILTER( INDIRECT("'"&Q$14&"'!A2:E1000"), (INDIRECT("'"&Q$14&"'!B2:B1000")=$B42) * (INDIRECT("'"&Q$14&"'!C2:C1000")=$C42) ), 5, FALSE ) )}
A43: Larissa | B43: Foz do Iguaçu | C43: 3 | D43: {=IF( VLOOKUP( $A43, _xlfn._xlws.FILTER( INDIRECT("'"&D$14&"'!A2:E1000"), (INDIRECT("'"&D$14&"'!B2:B1000")=$B43) * (INDIRECT("'"&D$14&"'!C2:C1000")=$C43) ), 5, FALSE )=0, "", VLOOKUP( $A43, _xlfn._xlws.FILTER( INDIRECT("'"&D$14&"'!A2:E1000"), (INDIRECT("'"&D$14&"'!B2:B1000")=$B43) * (INDIRECT("'"&D$14&"'!C2:C1000")=$C43) ), 5, FALSE ) )} | E43: {=IF( VLOOKUP( $A43, _xlfn._xlws.FILTER( INDIRECT("'"&E$14&"'!A2:E1000"), (INDIRECT("'"&E$14&"'!B2:B1000")=$B43) * (INDIRECT("'"&E$14&"'!C2:C1000")=$C43) ), 5, FALSE )=0, "", VLOOKUP( $A43, _xlfn._xlws.FILTER( INDIRECT("'"&E$14&"'!A2:E1000"), (INDIRECT("'"&E$14&"'!B2:B1000")=$B43) * (INDIRECT("'"&E$14&"'!C2:C1000")=$C43) ), 5, FALSE ) )} | F43: {=IF( VLOOKUP( $A43, _xlfn._xlws.FILTER( INDIRECT("'"&F$14&"'!A2:E1000"), (INDIRECT("'"&F$14&"'!B2:B1000")=$B43) * (INDIRECT("'"&F$14&"'!C2:C1000")=$C43) ), 5, FALSE )=0, "", VLOOKUP( $A43, _xlfn._xlws.FILTER( INDIRECT("'"&F$14&"'!A2:E1000"), (INDIRECT("'"&F$14&"'!B2:B1000")=$B43) * (INDIRECT("'"&F$14&"'!C2:C1000")=$C43) ), 5, FALSE ) )} | G43: {=IF( VLOOKUP( $A43, _xlfn._xlws.FILTER( INDIRECT("'"&G$14&"'!A2:E1000"), (INDIRECT("'"&G$14&"'!B2:B1000")=$B43) * (INDIRECT("'"&G$14&"'!C2:C1000")=$C43) ), 5, FALSE )=0, "", VLOOKUP( $A43, _xlfn._xlws.FILTER( INDIRECT("'"&G$14&"'!A2:E1000"), (INDIRECT("'"&G$14&"'!B2:B1000")=$B43) * (INDIRECT("'"&G$14&"'!C2:C1000")=$C43) ), 5, FALSE ) )} | H43: {=IF( VLOOKUP( $A43, _xlfn._xlws.FILTER( INDIRECT("'"&H$14&"'!A2:E1000"), (INDIRECT("'"&H$14&"'!B2:B1000")=$B43) * (INDIRECT("'"&H$14&"'!C2:C1000")=$C43) ), 5, FALSE )=0, "", VLOOKUP( $A43, _xlfn._xlws.FILTER( INDIRECT("'"&H$14&"'!A2:E1000"), (INDIRECT("'"&H$14&"'!B2:B1000")=$B43) * (INDIRECT("'"&H$14&"'!C2:C1000")=$C43) ), 5, FALSE ) )} | I43: {=IF( VLOOKUP( $A43, _xlfn._xlws.FILTER( INDIRECT("'"&I$14&"'!A2:E1000"), (INDIRECT("'"&I$14&"'!B2:B1000")=$B43) * (INDIRECT("'"&I$14&"'!C2:C1000")=$C43) ), 5, FALSE )=0, "", VLOOKUP( $A43, _xlfn._xlws.FILTER( INDIRECT("'"&I$14&"'!A2:E1000"), (INDIRECT("'"&I$14&"'!B2:B1000")=$B43) * (INDIRECT("'"&I$14&"'!C2:C1000")=$C43) ), 5, FALSE ) )} | J43: {=IF( VLOOKUP( $A43, _xlfn._xlws.FILTER( INDIRECT("'"&J$14&"'!A2:E1000"), (INDIRECT("'"&J$14&"'!B2:B1000")=$B43) * (INDIRECT("'"&J$14&"'!C2:C1000")=$C43) ), 5, FALSE )=0, "", VLOOKUP( $A43, _xlfn._xlws.FILTER( INDIRECT("'"&J$14&"'!A2:E1000"), (INDIRECT("'"&J$14&"'!B2:B1000")=$B43) * (INDIRECT("'"&J$14&"'!C2:C1000")=$C43) ), 5, FALSE ) )} | K43: {=IF( VLOOKUP( $A43, _xlfn._xlws.FILTER( INDIRECT("'"&K$14&"'!A2:E1000"), (INDIRECT("'"&K$14&"'!B2:B1000")=$B43) * (INDIRECT("'"&K$14&"'!C2:C1000")=$C43) ), 5, FALSE )=0, "", VLOOKUP( $A43, _xlfn._xlws.FILTER( INDIRECT("'"&K$14&"'!A2:E1000"), (INDIRECT("'"&K$14&"'!B2:B1000")=$B43) * (INDIRECT("'"&K$14&"'!C2:C1000")=$C43) ), 5, FALSE ) )} | ... Q43: {=IF( VLOOKUP( $A43, _xlfn._xlws.FILTER( INDIRECT("'"&Q$14&"'!A2:E1000"), (INDIRECT("'"&Q$14&"'!B2:B1000")=$B43) * (INDIRECT("'"&Q$14&"'!C2:C1000")=$C43) ), 5, FALSE )=0, "", VLOOKUP( $A43, _xlfn._xlws.FILTER( INDIRECT("'"&Q$14&"'!A2:E1000"), (INDIRECT("'"&Q$14&"'!B2:B1000")=$B43) * (INDIRECT("'"&Q$14&"'!C2:C1000")=$C43) ), 5, FALSE ) )}
A44: Larissa | B44: Foz do Iguaçu | C44: 4 | D44: {=IF( VLOOKUP( $A44, _xlfn._xlws.FILTER( INDIRECT("'"&D$14&"'!A2:E1000"), (INDIRECT("'"&D$14&"'!B2:B1000")=$B44) * (INDIRECT("'"&D$14&"'!C2:C1000")=$C44) ), 5, FALSE )=0, "", VLOOKUP( $A44, _xlfn._xlws.FILTER( INDIRECT("'"&D$14&"'!A2:E1000"), (INDIRECT("'"&D$14&"'!B2:B1000")=$B44) * (INDIRECT("'"&D$14&"'!C2:C1000")=$C44) ), 5, FALSE ) )} | E44: {=IF( VLOOKUP( $A44, _xlfn._xlws.FILTER( INDIRECT("'"&E$14&"'!A2:E1000"), (INDIRECT("'"&E$14&"'!B2:B1000")=$B44) * (INDIRECT("'"&E$14&"'!C2:C1000")=$C44) ), 5, FALSE )=0, "", VLOOKUP( $A44, _xlfn._xlws.FILTER( INDIRECT("'"&E$14&"'!A2:E1000"), (INDIRECT("'"&E$14&"'!B2:B1000")=$B44) * (INDIRECT("'"&E$14&"'!C2:C1000")=$C44) ), 5, FALSE ) )} | F44: {=IF( VLOOKUP( $A44, _xlfn._xlws.FILTER( INDIRECT("'"&F$14&"'!A2:E1000"), (INDIRECT("'"&F$14&"'!B2:B1000")=$B44) * (INDIRECT("'"&F$14&"'!C2:C1000")=$C44) ), 5, FALSE )=0, "", VLOOKUP( $A44, _xlfn._xlws.FILTER( INDIRECT("'"&F$14&"'!A2:E1000"), (INDIRECT("'"&F$14&"'!B2:B1000")=$B44) * (INDIRECT("'"&F$14&"'!C2:C1000")=$C44) ), 5, FALSE ) )} | G44: {=IF( VLOOKUP( $A44, _xlfn._xlws.FILTER( INDIRECT("'"&G$14&"'!A2:E1000"), (INDIRECT("'"&G$14&"'!B2:B1000")=$B44) * (INDIRECT("'"&G$14&"'!C2:C1000")=$C44) ), 5, FALSE )=0, "", VLOOKUP( $A44, _xlfn._xlws.FILTER( INDIRECT("'"&G$14&"'!A2:E1000"), (INDIRECT("'"&G$14&"'!B2:B1000")=$B44) * (INDIRECT("'"&G$14&"'!C2:C1000")=$C44) ), 5, FALSE ) )} | H44: {=IF( VLOOKUP( $A44, _xlfn._xlws.FILTER( INDIRECT("'"&H$14&"'!A2:E1000"), (INDIRECT("'"&H$14&"'!B2:B1000")=$B44) * (INDIRECT("'"&H$14&"'!C2:C1000")=$C44) ), 5, FALSE )=0, "", VLOOKUP( $A44, _xlfn._xlws.FILTER( INDIRECT("'"&H$14&"'!A2:E1000"), (INDIRECT("'"&H$14&"'!B2:B1000")=$B44) * (INDIRECT("'"&H$14&"'!C2:C1000")=$C44) ), 5, FALSE ) )} | I44: {=IF( VLOOKUP( $A44, _xlfn._xlws.FILTER( INDIRECT("'"&I$14&"'!A2:E1000"), (INDIRECT("'"&I$14&"'!B2:B1000")=$B44) * (INDIRECT("'"&I$14&"'!C2:C1000")=$C44) ), 5, FALSE )=0, "", VLOOKUP( $A44, _xlfn._xlws.FILTER( INDIRECT("'"&I$14&"'!A2:E1000"), (INDIRECT("'"&I$14&"'!B2:B1000")=$B44) * (INDIRECT("'"&I$14&"'!C2:C1000")=$C44) ), 5, FALSE ) )} | J44: {=IF( VLOOKUP( $A44, _xlfn._xlws.FILTER( INDIRECT("'"&J$14&"'!A2:E1000"), (INDIRECT("'"&J$14&"'!B2:B1000")=$B44) * (INDIRECT("'"&J$14&"'!C2:C1000")=$C44) ), 5, FALSE )=0, "", VLOOKUP( $A44, _xlfn._xlws.FILTER( INDIRECT("'"&J$14&"'!A2:E1000"), (INDIRECT("'"&J$14&"'!B2:B1000")=$B44) * (INDIRECT("'"&J$14&"'!C2:C1000")=$C44) ), 5, FALSE ) )} | K44: {=IF( VLOOKUP( $A44, _xlfn._xlws.FILTER( INDIRECT("'"&K$14&"'!A2:E1000"), (INDIRECT("'"&K$14&"'!B2:B1000")=$B44) * (INDIRECT("'"&K$14&"'!C2:C1000")=$C44) ), 5, FALSE )=0, "", VLOOKUP( $A44, _xlfn._xlws.FILTER( INDIRECT("'"&K$14&"'!A2:E1000"), (INDIRECT("'"&K$14&"'!B2:B1000")=$B44) * (INDIRECT("'"&K$14&"'!C2:C1000")=$C44) ), 5, FALSE ) )} | ... Q44: {=IF( VLOOKUP( $A44, _xlfn._xlws.FILTER( INDIRECT("'"&Q$14&"'!A2:E1000"), (INDIRECT("'"&Q$14&"'!B2:B1000")=$B44) * (INDIRECT("'"&Q$14&"'!C2:C1000")=$C44) ), 5, FALSE )=0, "", VLOOKUP( $A44, _xlfn._xlws.FILTER( INDIRECT("'"&Q$14&"'!A2:E1000"), (INDIRECT("'"&Q$14&"'!B2:B1000")=$B44) * (INDIRECT("'"&Q$14&"'!C2:C1000")=$C44) ), 5, FALSE ) )}
A45: Larissa | B45: Foz do Iguaçu | C45: 5 | D45: {=IF( VLOOKUP( $A45, _xlfn._xlws.FILTER( INDIRECT("'"&D$14&"'!A2:E1000"), (INDIRECT("'"&D$14&"'!B2:B1000")=$B45) * (INDIRECT("'"&D$14&"'!C2:C1000")=$C45) ), 5, FALSE )=0, "", VLOOKUP( $A45, _xlfn._xlws.FILTER( INDIRECT("'"&D$14&"'!A2:E1000"), (INDIRECT("'"&D$14&"'!B2:B1000")=$B45) * (INDIRECT("'"&D$14&"'!C2:C1000")=$C45) ), 5, FALSE ) )} | E45: {=IF( VLOOKUP( $A45, _xlfn._xlws.FILTER( INDIRECT("'"&E$14&"'!A2:E1000"), (INDIRECT("'"&E$14&"'!B2:B1000")=$B45) * (INDIRECT("'"&E$14&"'!C2:C1000")=$C45) ), 5, FALSE )=0, "", VLOOKUP( $A45, _xlfn._xlws.FILTER( INDIRECT("'"&E$14&"'!A2:E1000"), (INDIRECT("'"&E$14&"'!B2:B1000")=$B45) * (INDIRECT("'"&E$14&"'!C2:C1000")=$C45) ), 5, FALSE ) )} | F45: {=IF( VLOOKUP( $A45, _xlfn._xlws.FILTER( INDIRECT("'"&F$14&"'!A2:E1000"), (INDIRECT("'"&F$14&"'!B2:B1000")=$B45) * (INDIRECT("'"&F$14&"'!C2:C1000")=$C45) ), 5, FALSE )=0, "", VLOOKUP( $A45, _xlfn._xlws.FILTER( INDIRECT("'"&F$14&"'!A2:E1000"), (INDIRECT("'"&F$14&"'!B2:B1000")=$B45) * (INDIRECT("'"&F$14&"'!C2:C1000")=$C45) ), 5, FALSE ) )} | G45: {=IF( VLOOKUP( $A45, _xlfn._xlws.FILTER( INDIRECT("'"&G$14&"'!A2:E1000"), (INDIRECT("'"&G$14&"'!B2:B1000")=$B45) * (INDIRECT("'"&G$14&"'!C2:C1000")=$C45) ), 5, FALSE )=0, "", VLOOKUP( $A45, _xlfn._xlws.FILTER( INDIRECT("'"&G$14&"'!A2:E1000"), (INDIRECT("'"&G$14&"'!B2:B1000")=$B45) * (INDIRECT("'"&G$14&"'!C2:C1000")=$C45) ), 5, FALSE ) )} | H45: {=IF( VLOOKUP( $A45, _xlfn._xlws.FILTER( INDIRECT("'"&H$14&"'!A2:E1000"), (INDIRECT("'"&H$14&"'!B2:B1000")=$B45) * (INDIRECT("'"&H$14&"'!C2:C1000")=$C45) ), 5, FALSE )=0, "", VLOOKUP( $A45, _xlfn._xlws.FILTER( INDIRECT("'"&H$14&"'!A2:E1000"), (INDIRECT("'"&H$14&"'!B2:B1000")=$B45) * (INDIRECT("'"&H$14&"'!C2:C1000")=$C45) ), 5, FALSE ) )} | I45: {=IF( VLOOKUP( $A45, _xlfn._xlws.FILTER( INDIRECT("'"&I$14&"'!A2:E1000"), (INDIRECT("'"&I$14&"'!B2:B1000")=$B45) * (INDIRECT("'"&I$14&"'!C2:C1000")=$C45) ), 5, FALSE )=0, "", VLOOKUP( $A45, _xlfn._xlws.FILTER( INDIRECT("'"&I$14&"'!A2:E1000"), (INDIRECT("'"&I$14&"'!B2:B1000")=$B45) * (INDIRECT("'"&I$14&"'!C2:C1000")=$C45) ), 5, FALSE ) )} | J45: {=IF( VLOOKUP( $A45, _xlfn._xlws.FILTER( INDIRECT("'"&J$14&"'!A2:E1000"), (INDIRECT("'"&J$14&"'!B2:B1000")=$B45) * (INDIRECT("'"&J$14&"'!C2:C1000")=$C45) ), 5, FALSE )=0, "", VLOOKUP( $A45, _xlfn._xlws.FILTER( INDIRECT("'"&J$14&"'!A2:E1000"), (INDIRECT("'"&J$14&"'!B2:B1000")=$B45) * (INDIRECT("'"&J$14&"'!C2:C1000")=$C45) ), 5, FALSE ) )} | K45: {=IF( VLOOKUP( $A45, _xlfn._xlws.FILTER( INDIRECT("'"&K$14&"'!A2:E1000"), (INDIRECT("'"&K$14&"'!B2:B1000")=$B45) * (INDIRECT("'"&K$14&"'!C2:C1000")=$C45) ), 5, FALSE )=0, "", VLOOKUP( $A45, _xlfn._xlws.FILTER( INDIRECT("'"&K$14&"'!A2:E1000"), (INDIRECT("'"&K$14&"'!B2:B1000")=$B45) * (INDIRECT("'"&K$14&"'!C2:C1000")=$C45) ), 5, FALSE ) )} | ... Q45: {=IF( VLOOKUP( $A45, _xlfn._xlws.FILTER( INDIRECT("'"&Q$14&"'!A2:E1000"), (INDIRECT("'"&Q$14&"'!B2:B1000")=$B45) * (INDIRECT("'"&Q$14&"'!C2:C1000")=$C45) ), 5, FALSE )=0, "", VLOOKUP( $A45, _xlfn._xlws.FILTER( INDIRECT("'"&Q$14&"'!A2:E1000"), (INDIRECT("'"&Q$14&"'!B2:B1000")=$B45) * (INDIRECT("'"&Q$14&"'!C2:C1000")=$C45) ), 5, FALSE ) )}
A46: Larissa | B46: Foz do Iguaçu | C46: 6 | D46: {=IF( VLOOKUP( $A46, _xlfn._xlws.FILTER( INDIRECT("'"&D$14&"'!A2:E1000"), (INDIRECT("'"&D$14&"'!B2:B1000")=$B46) * (INDIRECT("'"&D$14&"'!C2:C1000")=$C46) ), 5, FALSE )=0, "", VLOOKUP( $A46, _xlfn._xlws.FILTER( INDIRECT("'"&D$14&"'!A2:E1000"), (INDIRECT("'"&D$14&"'!B2:B1000")=$B46) * (INDIRECT("'"&D$14&"'!C2:C1000")=$C46) ), 5, FALSE ) )} | E46: {=IF( VLOOKUP( $A46, _xlfn._xlws.FILTER( INDIRECT("'"&E$14&"'!A2:E1000"), (INDIRECT("'"&E$14&"'!B2:B1000")=$B46) * (INDIRECT("'"&E$14&"'!C2:C1000")=$C46) ), 5, FALSE )=0, "", VLOOKUP( $A46, _xlfn._xlws.FILTER( INDIRECT("'"&E$14&"'!A2:E1000"), (INDIRECT("'"&E$14&"'!B2:B1000")=$B46) * (INDIRECT("'"&E$14&"'!C2:C1000")=$C46) ), 5, FALSE ) )} | F46: {=IF( VLOOKUP( $A46, _xlfn._xlws.FILTER( INDIRECT("'"&F$14&"'!A2:E1000"), (INDIRECT("'"&F$14&"'!B2:B1000")=$B46) * (INDIRECT("'"&F$14&"'!C2:C1000")=$C46) ), 5, FALSE )=0, "", VLOOKUP( $A46, _xlfn._xlws.FILTER( INDIRECT("'"&F$14&"'!A2:E1000"), (INDIRECT("'"&F$14&"'!B2:B1000")=$B46) * (INDIRECT("'"&F$14&"'!C2:C1000")=$C46) ), 5, FALSE ) )} | G46: {=IF( VLOOKUP( $A46, _xlfn._xlws.FILTER( INDIRECT("'"&G$14&"'!A2:E1000"), (INDIRECT("'"&G$14&"'!B2:B1000")=$B46) * (INDIRECT("'"&G$14&"'!C2:C1000")=$C46) ), 5, FALSE )=0, "", VLOOKUP( $A46, _xlfn._xlws.FILTER( INDIRECT("'"&G$14&"'!A2:E1000"), (INDIRECT("'"&G$14&"'!B2:B1000")=$B46) * (INDIRECT("'"&G$14&"'!C2:C1000")=$C46) ), 5, FALSE ) )} | H46: {=IF( VLOOKUP( $A46, _xlfn._xlws.FILTER( INDIRECT("'"&H$14&"'!A2:E1000"), (INDIRECT("'"&H$14&"'!B2:B1000")=$B46) * (INDIRECT("'"&H$14&"'!C2:C1000")=$C46) ), 5, FALSE )=0, "", VLOOKUP( $A46, _xlfn._xlws.FILTER( INDIRECT("'"&H$14&"'!A2:E1000"), (INDIRECT("'"&H$14&"'!B2:B1000")=$B46) * (INDIRECT("'"&H$14&"'!C2:C1000")=$C46) ), 5, FALSE ) )} | I46: {=IF( VLOOKUP( $A46, _xlfn._xlws.FILTER( INDIRECT("'"&I$14&"'!A2:E1000"), (INDIRECT("'"&I$14&"'!B2:B1000")=$B46) * (INDIRECT("'"&I$14&"'!C2:C1000")=$C46) ), 5, FALSE )=0, "", VLOOKUP( $A46, _xlfn._xlws.FILTER( INDIRECT("'"&I$14&"'!A2:E1000"), (INDIRECT("'"&I$14&"'!B2:B1000")=$B46) * (INDIRECT("'"&I$14&"'!C2:C1000")=$C46) ), 5, FALSE ) )} | J46: {=IF( VLOOKUP( $A46, _xlfn._xlws.FILTER( INDIRECT("'"&J$14&"'!A2:E1000"), (INDIRECT("'"&J$14&"'!B2:B1000")=$B46) * (INDIRECT("'"&J$14&"'!C2:C1000")=$C46) ), 5, FALSE )=0, "", VLOOKUP( $A46, _xlfn._xlws.FILTER( INDIRECT("'"&J$14&"'!A2:E1000"), (INDIRECT("'"&J$14&"'!B2:B1000")=$B46) * (INDIRECT("'"&J$14&"'!C2:C1000")=$C46) ), 5, FALSE ) )} | K46: {=IF( VLOOKUP( $A46, _xlfn._xlws.FILTER( INDIRECT("'"&K$14&"'!A2:E1000"), (INDIRECT("'"&K$14&"'!B2:B1000")=$B46) * (INDIRECT("'"&K$14&"'!C2:C1000")=$C46) ), 5, FALSE )=0, "", VLOOKUP( $A46, _xlfn._xlws.FILTER( INDIRECT("'"&K$14&"'!A2:E1000"), (INDIRECT("'"&K$14&"'!B2:B1000")=$B46) * (INDIRECT("'"&K$14&"'!C2:C1000")=$C46) ), 5, FALSE ) )} | ... Q46: {=IF( VLOOKUP( $A46, _xlfn._xlws.FILTER( INDIRECT("'"&Q$14&"'!A2:E1000"), (INDIRECT("'"&Q$14&"'!B2:B1000")=$B46) * (INDIRECT("'"&Q$14&"'!C2:C1000")=$C46) ), 5, FALSE )=0, "", VLOOKUP( $A46, _xlfn._xlws.FILTER( INDIRECT("'"&Q$14&"'!A2:E1000"), (INDIRECT("'"&Q$14&"'!B2:B1000")=$B46) * (INDIRECT("'"&Q$14&"'!C2:C1000")=$C46) ), 5, FALSE ) )}
A47: Larissa | B47: Foz do Iguaçu | C47: 7 | D47: {=IF( VLOOKUP( $A47, _xlfn._xlws.FILTER( INDIRECT("'"&D$14&"'!A2:E1000"), (INDIRECT("'"&D$14&"'!B2:B1000")=$B47) * (INDIRECT("'"&D$14&"'!C2:C1000")=$C47) ), 5, FALSE )=0, "", VLOOKUP( $A47, _xlfn._xlws.FILTER( INDIRECT("'"&D$14&"'!A2:E1000"), (INDIRECT("'"&D$14&"'!B2:B1000")=$B47) * (INDIRECT("'"&D$14&"'!C2:C1000")=$C47) ), 5, FALSE ) )} | E47: {=IF( VLOOKUP( $A47, _xlfn._xlws.FILTER( INDIRECT("'"&E$14&"'!A2:E1000"), (INDIRECT("'"&E$14&"'!B2:B1000")=$B47) * (INDIRECT("'"&E$14&"'!C2:C1000")=$C47) ), 5, FALSE )=0, "", VLOOKUP( $A47, _xlfn._xlws.FILTER( INDIRECT("'"&E$14&"'!A2:E1000"), (INDIRECT("'"&E$14&"'!B2:B1000")=$B47) * (INDIRECT("'"&E$14&"'!C2:C1000")=$C47) ), 5, FALSE ) )} | F47: {=IF( VLOOKUP( $A47, _xlfn._xlws.FILTER( INDIRECT("'"&F$14&"'!A2:E1000"), (INDIRECT("'"&F$14&"'!B2:B1000")=$B47) * (INDIRECT("'"&F$14&"'!C2:C1000")=$C47) ), 5, FALSE )=0, "", VLOOKUP( $A47, _xlfn._xlws.FILTER( INDIRECT("'"&F$14&"'!A2:E1000"), (INDIRECT("'"&F$14&"'!B2:B1000")=$B47) * (INDIRECT("'"&F$14&"'!C2:C1000")=$C47) ), 5, FALSE ) )} | G47: {=IF( VLOOKUP( $A47, _xlfn._xlws.FILTER( INDIRECT("'"&G$14&"'!A2:E1000"), (INDIRECT("'"&G$14&"'!B2:B1000")=$B47) * (INDIRECT("'"&G$14&"'!C2:C1000")=$C47) ), 5, FALSE )=0, "", VLOOKUP( $A47, _xlfn._xlws.FILTER( INDIRECT("'"&G$14&"'!A2:E1000"), (INDIRECT("'"&G$14&"'!B2:B1000")=$B47) * (INDIRECT("'"&G$14&"'!C2:C1000")=$C47) ), 5, FALSE ) )} | H47: {=IF( VLOOKUP( $A47, _xlfn._xlws.FILTER( INDIRECT("'"&H$14&"'!A2:E1000"), (INDIRECT("'"&H$14&"'!B2:B1000")=$B47) * (INDIRECT("'"&H$14&"'!C2:C1000")=$C47) ), 5, FALSE )=0, "", VLOOKUP( $A47, _xlfn._xlws.FILTER( INDIRECT("'"&H$14&"'!A2:E1000"), (INDIRECT("'"&H$14&"'!B2:B1000")=$B47) * (INDIRECT("'"&H$14&"'!C2:C1000")=$C47) ), 5, FALSE ) )} | I47: {=IF( VLOOKUP( $A47, _xlfn._xlws.FILTER( INDIRECT("'"&I$14&"'!A2:E1000"), (INDIRECT("'"&I$14&"'!B2:B1000")=$B47) * (INDIRECT("'"&I$14&"'!C2:C1000")=$C47) ), 5, FALSE )=0, "", VLOOKUP( $A47, _xlfn._xlws.FILTER( INDIRECT("'"&I$14&"'!A2:E1000"), (INDIRECT("'"&I$14&"'!B2:B1000")=$B47) * (INDIRECT("'"&I$14&"'!C2:C1000")=$C47) ), 5, FALSE ) )} | J47: {=IF( VLOOKUP( $A47, _xlfn._xlws.FILTER( INDIRECT("'"&J$14&"'!A2:E1000"), (INDIRECT("'"&J$14&"'!B2:B1000")=$B47) * (INDIRECT("'"&J$14&"'!C2:C1000")=$C47) ), 5, FALSE )=0, "", VLOOKUP( $A47, _xlfn._xlws.FILTER( INDIRECT("'"&J$14&"'!A2:E1000"), (INDIRECT("'"&J$14&"'!B2:B1000")=$B47) * (INDIRECT("'"&J$14&"'!C2:C1000")=$C47) ), 5, FALSE ) )} | K47: {=IF( VLOOKUP( $A47, _xlfn._xlws.FILTER( INDIRECT("'"&K$14&"'!A2:E1000"), (INDIRECT("'"&K$14&"'!B2:B1000")=$B47) * (INDIRECT("'"&K$14&"'!C2:C1000")=$C47) ), 5, FALSE )=0, "", VLOOKUP( $A47, _xlfn._xlws.FILTER( INDIRECT("'"&K$14&"'!A2:E1000"), (INDIRECT("'"&K$14&"'!B2:B1000")=$B47) * (INDIRECT("'"&K$14&"'!C2:C1000")=$C47) ), 5, FALSE ) )} | ... Q47: {=IF( VLOOKUP( $A47, _xlfn._xlws.FILTER( INDIRECT("'"&Q$14&"'!A2:E1000"), (INDIRECT("'"&Q$14&"'!B2:B1000")=$B47) * (INDIRECT("'"&Q$14&"'!C2:C1000")=$C47) ), 5, FALSE )=0, "", VLOOKUP( $A47, _xlfn._xlws.FILTER( INDIRECT("'"&Q$14&"'!A2:E1000"), (INDIRECT("'"&Q$14&"'!B2:B1000")=$B47) * (INDIRECT("'"&Q$14&"'!C2:C1000")=$C47) ), 5, FALSE ) )}
A48: Larissa | B48: Foz do Iguaçu | C48: 8 | D48: {=IF( VLOOKUP( $A48, _xlfn._xlws.FILTER( INDIRECT("'"&D$14&"'!A2:E1000"), (INDIRECT("'"&D$14&"'!B2:B1000")=$B48) * (INDIRECT("'"&D$14&"'!C2:C1000")=$C48) ), 5, FALSE )=0, "", VLOOKUP( $A48, _xlfn._xlws.FILTER( INDIRECT("'"&D$14&"'!A2:E1000"), (INDIRECT("'"&D$14&"'!B2:B1000")=$B48) * (INDIRECT("'"&D$14&"'!C2:C1000")=$C48) ), 5, FALSE ) )} | E48: {=IF( VLOOKUP( $A48, _xlfn._xlws.FILTER( INDIRECT("'"&E$14&"'!A2:E1000"), (INDIRECT("'"&E$14&"'!B2:B1000")=$B48) * (INDIRECT("'"&E$14&"'!C2:C1000")=$C48) ), 5, FALSE )=0, "", VLOOKUP( $A48, _xlfn._xlws.FILTER( INDIRECT("'"&E$14&"'!A2:E1000"), (INDIRECT("'"&E$14&"'!B2:B1000")=$B48) * (INDIRECT("'"&E$14&"'!C2:C1000")=$C48) ), 5, FALSE ) )} | F48: {=IF( VLOOKUP( $A48, _xlfn._xlws.FILTER( INDIRECT("'"&F$14&"'!A2:E1000"), (INDIRECT("'"&F$14&"'!B2:B1000")=$B48) * (INDIRECT("'"&F$14&"'!C2:C1000")=$C48) ), 5, FALSE )=0, "", VLOOKUP( $A48, _xlfn._xlws.FILTER( INDIRECT("'"&F$14&"'!A2:E1000"), (INDIRECT("'"&F$14&"'!B2:B1000")=$B48) * (INDIRECT("'"&F$14&"'!C2:C1000")=$C48) ), 5, FALSE ) )} | G48: {=IF( VLOOKUP( $A48, _xlfn._xlws.FILTER( INDIRECT("'"&G$14&"'!A2:E1000"), (INDIRECT("'"&G$14&"'!B2:B1000")=$B48) * (INDIRECT("'"&G$14&"'!C2:C1000")=$C48) ), 5, FALSE )=0, "", VLOOKUP( $A48, _xlfn._xlws.FILTER( INDIRECT("'"&G$14&"'!A2:E1000"), (INDIRECT("'"&G$14&"'!B2:B1000")=$B48) * (INDIRECT("'"&G$14&"'!C2:C1000")=$C48) ), 5, FALSE ) )} | H48: {=IF( VLOOKUP( $A48, _xlfn._xlws.FILTER( INDIRECT("'"&H$14&"'!A2:E1000"), (INDIRECT("'"&H$14&"'!B2:B1000")=$B48) * (INDIRECT("'"&H$14&"'!C2:C1000")=$C48) ), 5, FALSE )=0, "", VLOOKUP( $A48, _xlfn._xlws.FILTER( INDIRECT("'"&H$14&"'!A2:E1000"), (INDIRECT("'"&H$14&"'!B2:B1000")=$B48) * (INDIRECT("'"&H$14&"'!C2:C1000")=$C48) ), 5, FALSE ) )} | I48: {=IF( VLOOKUP( $A48, _xlfn._xlws.FILTER( INDIRECT("'"&I$14&"'!A2:E1000"), (INDIRECT("'"&I$14&"'!B2:B1000")=$B48) * (INDIRECT("'"&I$14&"'!C2:C1000")=$C48) ), 5, FALSE )=0, "", VLOOKUP( $A48, _xlfn._xlws.FILTER( INDIRECT("'"&I$14&"'!A2:E1000"), (INDIRECT("'"&I$14&"'!B2:B1000")=$B48) * (INDIRECT("'"&I$14&"'!C2:C1000")=$C48) ), 5, FALSE ) )} | J48: {=IF( VLOOKUP( $A48, _xlfn._xlws.FILTER( INDIRECT("'"&J$14&"'!A2:E1000"), (INDIRECT("'"&J$14&"'!B2:B1000")=$B48) * (INDIRECT("'"&J$14&"'!C2:C1000")=$C48) ), 5, FALSE )=0, "", VLOOKUP( $A48, _xlfn._xlws.FILTER( INDIRECT("'"&J$14&"'!A2:E1000"), (INDIRECT("'"&J$14&"'!B2:B1000")=$B48) * (INDIRECT("'"&J$14&"'!C2:C1000")=$C48) ), 5, FALSE ) )} | K48: {=IF( VLOOKUP( $A48, _xlfn._xlws.FILTER( INDIRECT("'"&K$14&"'!A2:E1000"), (INDIRECT("'"&K$14&"'!B2:B1000")=$B48) * (INDIRECT("'"&K$14&"'!C2:C1000")=$C48) ), 5, FALSE )=0, "", VLOOKUP( $A48, _xlfn._xlws.FILTER( INDIRECT("'"&K$14&"'!A2:E1000"), (INDIRECT("'"&K$14&"'!B2:B1000")=$B48) * (INDIRECT("'"&K$14&"'!C2:C1000")=$C48) ), 5, FALSE ) )} | ... Q48: {=IF( VLOOKUP( $A48, _xlfn._xlws.FILTER( INDIRECT("'"&Q$14&"'!A2:E1000"), (INDIRECT("'"&Q$14&"'!B2:B1000")=$B48) * (INDIRECT("'"&Q$14&"'!C2:C1000")=$C48) ), 5, FALSE )=0, "", VLOOKUP( $A48, _xlfn._xlws.FILTER( INDIRECT("'"&Q$14&"'!A2:E1000"), (INDIRECT("'"&Q$14&"'!B2:B1000")=$B48) * (INDIRECT("'"&Q$14&"'!C2:C1000")=$C48) ), 5, FALSE ) )}
A49: Larissa | B49: Foz do Iguaçu | C49: 9 | D49: {=IF( VLOOKUP( $A49, _xlfn._xlws.FILTER( INDIRECT("'"&D$14&"'!A2:E1000"), (INDIRECT("'"&D$14&"'!B2:B1000")=$B49) * (INDIRECT("'"&D$14&"'!C2:C1000")=$C49) ), 5, FALSE )=0, "", VLOOKUP( $A49, _xlfn._xlws.FILTER( INDIRECT("'"&D$14&"'!A2:E1000"), (INDIRECT("'"&D$14&"'!B2:B1000")=$B49) * (INDIRECT("'"&D$14&"'!C2:C1000")=$C49) ), 5, FALSE ) )} | E49: {=IF( VLOOKUP( $A49, _xlfn._xlws.FILTER( INDIRECT("'"&E$14&"'!A2:E1000"), (INDIRECT("'"&E$14&"'!B2:B1000")=$B49) * (INDIRECT("'"&E$14&"'!C2:C1000")=$C49) ), 5, FALSE )=0, "", VLOOKUP( $A49, _xlfn._xlws.FILTER( INDIRECT("'"&E$14&"'!A2:E1000"), (INDIRECT("'"&E$14&"'!B2:B1000")=$B49) * (INDIRECT("'"&E$14&"'!C2:C1000")=$C49) ), 5, FALSE ) )} | F49: {=IF( VLOOKUP( $A49, _xlfn._xlws.FILTER( INDIRECT("'"&F$14&"'!A2:E1000"), (INDIRECT("'"&F$14&"'!B2:B1000")=$B49) * (INDIRECT("'"&F$14&"'!C2:C1000")=$C49) ), 5, FALSE )=0, "", VLOOKUP( $A49, _xlfn._xlws.FILTER( INDIRECT("'"&F$14&"'!A2:E1000"), (INDIRECT("'"&F$14&"'!B2:B1000")=$B49) * (INDIRECT("'"&F$14&"'!C2:C1000")=$C49) ), 5, FALSE ) )} | G49: {=IF( VLOOKUP( $A49, _xlfn._xlws.FILTER( INDIRECT("'"&G$14&"'!A2:E1000"), (INDIRECT("'"&G$14&"'!B2:B1000")=$B49) * (INDIRECT("'"&G$14&"'!C2:C1000")=$C49) ), 5, FALSE )=0, "", VLOOKUP( $A49, _xlfn._xlws.FILTER( INDIRECT("'"&G$14&"'!A2:E1000"), (INDIRECT("'"&G$14&"'!B2:B1000")=$B49) * (INDIRECT("'"&G$14&"'!C2:C1000")=$C49) ), 5, FALSE ) )} | H49: {=IF( VLOOKUP( $A49, _xlfn._xlws.FILTER( INDIRECT("'"&H$14&"'!A2:E1000"), (INDIRECT("'"&H$14&"'!B2:B1000")=$B49) * (INDIRECT("'"&H$14&"'!C2:C1000")=$C49) ), 5, FALSE )=0, "", VLOOKUP( $A49, _xlfn._xlws.FILTER( INDIRECT("'"&H$14&"'!A2:E1000"), (INDIRECT("'"&H$14&"'!B2:B1000")=$B49) * (INDIRECT("'"&H$14&"'!C2:C1000")=$C49) ), 5, FALSE ) )} | I49: {=IF( VLOOKUP( $A49, _xlfn._xlws.FILTER( INDIRECT("'"&I$14&"'!A2:E1000"), (INDIRECT("'"&I$14&"'!B2:B1000")=$B49) * (INDIRECT("'"&I$14&"'!C2:C1000")=$C49) ), 5, FALSE )=0, "", VLOOKUP( $A49, _xlfn._xlws.FILTER( INDIRECT("'"&I$14&"'!A2:E1000"), (INDIRECT("'"&I$14&"'!B2:B1000")=$B49) * (INDIRECT("'"&I$14&"'!C2:C1000")=$C49) ), 5, FALSE ) )} | J49: {=IF( VLOOKUP( $A49, _xlfn._xlws.FILTER( INDIRECT("'"&J$14&"'!A2:E1000"), (INDIRECT("'"&J$14&"'!B2:B1000")=$B49) * (INDIRECT("'"&J$14&"'!C2:C1000")=$C49) ), 5, FALSE )=0, "", VLOOKUP( $A49, _xlfn._xlws.FILTER( INDIRECT("'"&J$14&"'!A2:E1000"), (INDIRECT("'"&J$14&"'!B2:B1000")=$B49) * (INDIRECT("'"&J$14&"'!C2:C1000")=$C49) ), 5, FALSE ) )} | K49: {=IF( VLOOKUP( $A49, _xlfn._xlws.FILTER( INDIRECT("'"&K$14&"'!A2:E1000"), (INDIRECT("'"&K$14&"'!B2:B1000")=$B49) * (INDIRECT("'"&K$14&"'!C2:C1000")=$C49) ), 5, FALSE )=0, "", VLOOKUP( $A49, _xlfn._xlws.FILTER( INDIRECT("'"&K$14&"'!A2:E1000"), (INDIRECT("'"&K$14&"'!B2:B1000")=$B49) * (INDIRECT("'"&K$14&"'!C2:C1000")=$C49) ), 5, FALSE ) )} | ... Q49: {=IF( VLOOKUP( $A49, _xlfn._xlws.FILTER( INDIRECT("'"&Q$14&"'!A2:E1000"), (INDIRECT("'"&Q$14&"'!B2:B1000")=$B49) * (INDIRECT("'"&Q$14&"'!C2:C1000")=$C49) ), 5, FALSE )=0, "", VLOOKUP( $A49, _xlfn._xlws.FILTER( INDIRECT("'"&Q$14&"'!A2:E1000"), (INDIRECT("'"&Q$14&"'!B2:B1000")=$B49) * (INDIRECT("'"&Q$14&"'!C2:C1000")=$C49) ), 5, FALSE ) )}
A50: Larissa | B50: Medianeira | C50: 1 | D50: {=IF( VLOOKUP( $A50, _xlfn._xlws.FILTER( INDIRECT("'"&D$14&"'!A2:E1000"), (INDIRECT("'"&D$14&"'!B2:B1000")=$B50) * (INDIRECT("'"&D$14&"'!C2:C1000")=$C50) ), 5, FALSE )=0, "", VLOOKUP( $A50, _xlfn._xlws.FILTER( INDIRECT("'"&D$14&"'!A2:E1000"), (INDIRECT("'"&D$14&"'!B2:B1000")=$B50) * (INDIRECT("'"&D$14&"'!C2:C1000")=$C50) ), 5, FALSE ) )} | E50: {=IF( VLOOKUP( $A50, _xlfn._xlws.FILTER( INDIRECT("'"&E$14&"'!A2:E1000"), (INDIRECT("'"&E$14&"'!B2:B1000")=$B50) * (INDIRECT("'"&E$14&"'!C2:C1000")=$C50) ), 5, FALSE )=0, "", VLOOKUP( $A50, _xlfn._xlws.FILTER( INDIRECT("'"&E$14&"'!A2:E1000"), (INDIRECT("'"&E$14&"'!B2:B1000")=$B50) * (INDIRECT("'"&E$14&"'!C2:C1000")=$C50) ), 5, FALSE ) )} | F50: {=IF( VLOOKUP( $A50, _xlfn._xlws.FILTER( INDIRECT("'"&F$14&"'!A2:E1000"), (INDIRECT("'"&F$14&"'!B2:B1000")=$B50) * (INDIRECT("'"&F$14&"'!C2:C1000")=$C50) ), 5, FALSE )=0, "", VLOOKUP( $A50, _xlfn._xlws.FILTER( INDIRECT("'"&F$14&"'!A2:E1000"), (INDIRECT("'"&F$14&"'!B2:B1000")=$B50) * (INDIRECT("'"&F$14&"'!C2:C1000")=$C50) ), 5, FALSE ) )} | G50: {=IF( VLOOKUP( $A50, _xlfn._xlws.FILTER( INDIRECT("'"&G$14&"'!A2:E1000"), (INDIRECT("'"&G$14&"'!B2:B1000")=$B50) * (INDIRECT("'"&G$14&"'!C2:C1000")=$C50) ), 5, FALSE )=0, "", VLOOKUP( $A50, _xlfn._xlws.FILTER( INDIRECT("'"&G$14&"'!A2:E1000"), (INDIRECT("'"&G$14&"'!B2:B1000")=$B50) * (INDIRECT("'"&G$14&"'!C2:C1000")=$C50) ), 5, FALSE ) )} | H50: {=IF( VLOOKUP( $A50, _xlfn._xlws.FILTER( INDIRECT("'"&H$14&"'!A2:E1000"), (INDIRECT("'"&H$14&"'!B2:B1000")=$B50) * (INDIRECT("'"&H$14&"'!C2:C1000")=$C50) ), 5, FALSE )=0, "", VLOOKUP( $A50, _xlfn._xlws.FILTER( INDIRECT("'"&H$14&"'!A2:E1000"), (INDIRECT("'"&H$14&"'!B2:B1000")=$B50) * (INDIRECT("'"&H$14&"'!C2:C1000")=$C50) ), 5, FALSE ) )} | I50: {=IF( VLOOKUP( $A50, _xlfn._xlws.FILTER( INDIRECT("'"&I$14&"'!A2:E1000"), (INDIRECT("'"&I$14&"'!B2:B1000")=$B50) * (INDIRECT("'"&I$14&"'!C2:C1000")=$C50) ), 5, FALSE )=0, "", VLOOKUP( $A50, _xlfn._xlws.FILTER( INDIRECT("'"&I$14&"'!A2:E1000"), (INDIRECT("'"&I$14&"'!B2:B1000")=$B50) * (INDIRECT("'"&I$14&"'!C2:C1000")=$C50) ), 5, FALSE ) )} | J50: {=IF( VLOOKUP( $A50, _xlfn._xlws.FILTER( INDIRECT("'"&J$14&"'!A2:E1000"), (INDIRECT("'"&J$14&"'!B2:B1000")=$B50) * (INDIRECT("'"&J$14&"'!C2:C1000")=$C50) ), 5, FALSE )=0, "", VLOOKUP( $A50, _xlfn._xlws.FILTER( INDIRECT("'"&J$14&"'!A2:E1000"), (INDIRECT("'"&J$14&"'!B2:B1000")=$B50) * (INDIRECT("'"&J$14&"'!C2:C1000")=$C50) ), 5, FALSE ) )} | K50: {=IF( VLOOKUP( $A50, _xlfn._xlws.FILTER( INDIRECT("'"&K$14&"'!A2:E1000"), (INDIRECT("'"&K$14&"'!B2:B1000")=$B50) * (INDIRECT("'"&K$14&"'!C2:C1000")=$C50) ), 5, FALSE )=0, "", VLOOKUP( $A50, _xlfn._xlws.FILTER( INDIRECT("'"&K$14&"'!A2:E1000"), (INDIRECT("'"&K$14&"'!B2:B1000")=$B50) * (INDIRECT("'"&K$14&"'!C2:C1000")=$C50) ), 5, FALSE ) )} | ... Q50: {=IF( VLOOKUP( $A50, _xlfn._xlws.FILTER( INDIRECT("'"&Q$14&"'!A2:E1000"), (INDIRECT("'"&Q$14&"'!B2:B1000")=$B50) * (INDIRECT("'"&Q$14&"'!C2:C1000")=$C50) ), 5, FALSE )=0, "", VLOOKUP( $A50, _xlfn._xlws.FILTER( INDIRECT("'"&Q$14&"'!A2:E1000"), (INDIRECT("'"&Q$14&"'!B2:B1000")=$B50) * (INDIRECT("'"&Q$14&"'!C2:C1000")=$C50) ), 5, FALSE ) )}
A51: Larissa | B51: Santa Terezinha de Itaipu | C51: 1 | D51: {=IF( VLOOKUP( $A51, _xlfn._xlws.FILTER( INDIRECT("'"&D$14&"'!A2:E1000"), (INDIRECT("'"&D$14&"'!B2:B1000")=$B51) * (INDIRECT("'"&D$14&"'!C2:C1000")=$C51) ), 5, FALSE )=0, "", VLOOKUP( $A51, _xlfn._xlws.FILTER( INDIRECT("'"&D$14&"'!A2:E1000"), (INDIRECT("'"&D$14&"'!B2:B1000")=$B51) * (INDIRECT("'"&D$14&"'!C2:C1000")=$C51) ), 5, FALSE ) )} | E51: {=IF( VLOOKUP( $A51, _xlfn._xlws.FILTER( INDIRECT("'"&E$14&"'!A2:E1000"), (INDIRECT("'"&E$14&"'!B2:B1000")=$B51) * (INDIRECT("'"&E$14&"'!C2:C1000")=$C51) ), 5, FALSE )=0, "", VLOOKUP( $A51, _xlfn._xlws.FILTER( INDIRECT("'"&E$14&"'!A2:E1000"), (INDIRECT("'"&E$14&"'!B2:B1000")=$B51) * (INDIRECT("'"&E$14&"'!C2:C1000")=$C51) ), 5, FALSE ) )} | F51: {=IF( VLOOKUP( $A51, _xlfn._xlws.FILTER( INDIRECT("'"&F$14&"'!A2:E1000"), (INDIRECT("'"&F$14&"'!B2:B1000")=$B51) * (INDIRECT("'"&F$14&"'!C2:C1000")=$C51) ), 5, FALSE )=0, "", VLOOKUP( $A51, _xlfn._xlws.FILTER( INDIRECT("'"&F$14&"'!A2:E1000"), (INDIRECT("'"&F$14&"'!B2:B1000")=$B51) * (INDIRECT("'"&F$14&"'!C2:C1000")=$C51) ), 5, FALSE ) )} | G51: {=IF( VLOOKUP( $A51, _xlfn._xlws.FILTER( INDIRECT("'"&G$14&"'!A2:E1000"), (INDIRECT("'"&G$14&"'!B2:B1000")=$B51) * (INDIRECT("'"&G$14&"'!C2:C1000")=$C51) ), 5, FALSE )=0, "", VLOOKUP( $A51, _xlfn._xlws.FILTER( INDIRECT("'"&G$14&"'!A2:E1000"), (INDIRECT("'"&G$14&"'!B2:B1000")=$B51) * (INDIRECT("'"&G$14&"'!C2:C1000")=$C51) ), 5, FALSE ) )} | H51: {=IF( VLOOKUP( $A51, _xlfn._xlws.FILTER( INDIRECT("'"&H$14&"'!A2:E1000"), (INDIRECT("'"&H$14&"'!B2:B1000")=$B51) * (INDIRECT("'"&H$14&"'!C2:C1000")=$C51) ), 5, FALSE )=0, "", VLOOKUP( $A51, _xlfn._xlws.FILTER( INDIRECT("'"&H$14&"'!A2:E1000"), (INDIRECT("'"&H$14&"'!B2:B1000")=$B51) * (INDIRECT("'"&H$14&"'!C2:C1000")=$C51) ), 5, FALSE ) )} | I51: {=IF( VLOOKUP( $A51, _xlfn._xlws.FILTER( INDIRECT("'"&I$14&"'!A2:E1000"), (INDIRECT("'"&I$14&"'!B2:B1000")=$B51) * (INDIRECT("'"&I$14&"'!C2:C1000")=$C51) ), 5, FALSE )=0, "", VLOOKUP( $A51, _xlfn._xlws.FILTER( INDIRECT("'"&I$14&"'!A2:E1000"), (INDIRECT("'"&I$14&"'!B2:B1000")=$B51) * (INDIRECT("'"&I$14&"'!C2:C1000")=$C51) ), 5, FALSE ) )} | J51: {=IF( VLOOKUP( $A51, _xlfn._xlws.FILTER( INDIRECT("'"&J$14&"'!A2:E1000"), (INDIRECT("'"&J$14&"'!B2:B1000")=$B51) * (INDIRECT("'"&J$14&"'!C2:C1000")=$C51) ), 5, FALSE )=0, "", VLOOKUP( $A51, _xlfn._xlws.FILTER( INDIRECT("'"&J$14&"'!A2:E1000"), (INDIRECT("'"&J$14&"'!B2:B1000")=$B51) * (INDIRECT("'"&J$14&"'!C2:C1000")=$C51) ), 5, FALSE ) )} | K51: {=IF( VLOOKUP( $A51, _xlfn._xlws.FILTER( INDIRECT("'"&K$14&"'!A2:E1000"), (INDIRECT("'"&K$14&"'!B2:B1000")=$B51) * (INDIRECT("'"&K$14&"'!C2:C1000")=$C51) ), 5, FALSE )=0, "", VLOOKUP( $A51, _xlfn._xlws.FILTER( INDIRECT("'"&K$14&"'!A2:E1000"), (INDIRECT("'"&K$14&"'!B2:B1000")=$B51) * (INDIRECT("'"&K$14&"'!C2:C1000")=$C51) ), 5, FALSE ) )} | ... Q51: {=IF( VLOOKUP( $A51, _xlfn._xlws.FILTER( INDIRECT("'"&Q$14&"'!A2:E1000"), (INDIRECT("'"&Q$14&"'!B2:B1000")=$B51) * (INDIRECT("'"&Q$14&"'!C2:C1000")=$C51) ), 5, FALSE )=0, "", VLOOKUP( $A51, _xlfn._xlws.FILTER( INDIRECT("'"&Q$14&"'!A2:E1000"), (INDIRECT("'"&Q$14&"'!B2:B1000")=$B51) * (INDIRECT("'"&Q$14&"'!C2:C1000")=$C51) ), 5, FALSE ) )}
A52: Larissa | B52: São Miguel do Iguaçu | C52: 1 | D52: {=IF( VLOOKUP( $A52, _xlfn._xlws.FILTER( INDIRECT("'"&D$14&"'!A2:E1000"), (INDIRECT("'"&D$14&"'!B2:B1000")=$B52) * (INDIRECT("'"&D$14&"'!C2:C1000")=$C52) ), 5, FALSE )=0, "", VLOOKUP( $A52, _xlfn._xlws.FILTER( INDIRECT("'"&D$14&"'!A2:E1000"), (INDIRECT("'"&D$14&"'!B2:B1000")=$B52) * (INDIRECT("'"&D$14&"'!C2:C1000")=$C52) ), 5, FALSE ) )} | E52: {=IF( VLOOKUP( $A52, _xlfn._xlws.FILTER( INDIRECT("'"&E$14&"'!A2:E1000"), (INDIRECT("'"&E$14&"'!B2:B1000")=$B52) * (INDIRECT("'"&E$14&"'!C2:C1000")=$C52) ), 5, FALSE )=0, "", VLOOKUP( $A52, _xlfn._xlws.FILTER( INDIRECT("'"&E$14&"'!A2:E1000"), (INDIRECT("'"&E$14&"'!B2:B1000")=$B52) * (INDIRECT("'"&E$14&"'!C2:C1000")=$C52) ), 5, FALSE ) )} | F52: {=IF( VLOOKUP( $A52, _xlfn._xlws.FILTER( INDIRECT("'"&F$14&"'!A2:E1000"), (INDIRECT("'"&F$14&"'!B2:B1000")=$B52) * (INDIRECT("'"&F$14&"'!C2:C1000")=$C52) ), 5, FALSE )=0, "", VLOOKUP( $A52, _xlfn._xlws.FILTER( INDIRECT("'"&F$14&"'!A2:E1000"), (INDIRECT("'"&F$14&"'!B2:B1000")=$B52) * (INDIRECT("'"&F$14&"'!C2:C1000")=$C52) ), 5, FALSE ) )} | G52: {=IF( VLOOKUP( $A52, _xlfn._xlws.FILTER( INDIRECT("'"&G$14&"'!A2:E1000"), (INDIRECT("'"&G$14&"'!B2:B1000")=$B52) * (INDIRECT("'"&G$14&"'!C2:C1000")=$C52) ), 5, FALSE )=0, "", VLOOKUP( $A52, _xlfn._xlws.FILTER( INDIRECT("'"&G$14&"'!A2:E1000"), (INDIRECT("'"&G$14&"'!B2:B1000")=$B52) * (INDIRECT("'"&G$14&"'!C2:C1000")=$C52) ), 5, FALSE ) )} | H52: {=IF( VLOOKUP( $A52, _xlfn._xlws.FILTER( INDIRECT("'"&H$14&"'!A2:E1000"), (INDIRECT("'"&H$14&"'!B2:B1000")=$B52) * (INDIRECT("'"&H$14&"'!C2:C1000")=$C52) ), 5, FALSE )=0, "", VLOOKUP( $A52, _xlfn._xlws.FILTER( INDIRECT("'"&H$14&"'!A2:E1000"), (INDIRECT("'"&H$14&"'!B2:B1000")=$B52) * (INDIRECT("'"&H$14&"'!C2:C1000")=$C52) ), 5, FALSE ) )} | I52: {=IF( VLOOKUP( $A52, _xlfn._xlws.FILTER( INDIRECT("'"&I$14&"'!A2:E1000"), (INDIRECT("'"&I$14&"'!B2:B1000")=$B52) * (INDIRECT("'"&I$14&"'!C2:C1000")=$C52) ), 5, FALSE )=0, "", VLOOKUP( $A52, _xlfn._xlws.FILTER( INDIRECT("'"&I$14&"'!A2:E1000"), (INDIRECT("'"&I$14&"'!B2:B1000")=$B52) * (INDIRECT("'"&I$14&"'!C2:C1000")=$C52) ), 5, FALSE ) )} | J52: {=IF( VLOOKUP( $A52, _xlfn._xlws.FILTER( INDIRECT("'"&J$14&"'!A2:E1000"), (INDIRECT("'"&J$14&"'!B2:B1000")=$B52) * (INDIRECT("'"&J$14&"'!C2:C1000")=$C52) ), 5, FALSE )=0, "", VLOOKUP( $A52, _xlfn._xlws.FILTER( INDIRECT("'"&J$14&"'!A2:E1000"), (INDIRECT("'"&J$14&"'!B2:B1000")=$B52) * (INDIRECT("'"&J$14&"'!C2:C1000")=$C52) ), 5, FALSE ) )} | K52: {=IF( VLOOKUP( $A52, _xlfn._xlws.FILTER( INDIRECT("'"&K$14&"'!A2:E1000"), (INDIRECT("'"&K$14&"'!B2:B1000")=$B52) * (INDIRECT("'"&K$14&"'!C2:C1000")=$C52) ), 5, FALSE )=0, "", VLOOKUP( $A52, _xlfn._xlws.FILTER( INDIRECT("'"&K$14&"'!A2:E1000"), (INDIRECT("'"&K$14&"'!B2:B1000")=$B52) * (INDIRECT("'"&K$14&"'!C2:C1000")=$C52) ), 5, FALSE ) )} | ... Q52: {=IF( VLOOKUP( $A52, _xlfn._xlws.FILTER( INDIRECT("'"&Q$14&"'!A2:E1000"), (INDIRECT("'"&Q$14&"'!B2:B1000")=$B52) * (INDIRECT("'"&Q$14&"'!C2:C1000")=$C52) ), 5, FALSE )=0, "", VLOOKUP( $A52, _xlfn._xlws.FILTER( INDIRECT("'"&Q$14&"'!A2:E1000"), (INDIRECT("'"&Q$14&"'!B2:B1000")=$B52) * (INDIRECT("'"&Q$14&"'!C2:C1000")=$C52) ), 5, FALSE ) )}
A53: Larissa | B53: Serranopolis do Iguaçu | C53: 1 | D53: {=IF( VLOOKUP( $A53, _xlfn._xlws.FILTER( INDIRECT("'"&D$14&"'!A2:E1000"), (INDIRECT("'"&D$14&"'!B2:B1000")=$B53) * (INDIRECT("'"&D$14&"'!C2:C1000")=$C53) ), 5, FALSE )=0, "", VLOOKUP( $A53, _xlfn._xlws.FILTER( INDIRECT("'"&D$14&"'!A2:E1000"), (INDIRECT("'"&D$14&"'!B2:B1000")=$B53) * (INDIRECT("'"&D$14&"'!C2:C1000")=$C53) ), 5, FALSE ) )} | E53: {=IF( VLOOKUP( $A53, _xlfn._xlws.FILTER( INDIRECT("'"&E$14&"'!A2:E1000"), (INDIRECT("'"&E$14&"'!B2:B1000")=$B53) * (INDIRECT("'"&E$14&"'!C2:C1000")=$C53) ), 5, FALSE )=0, "", VLOOKUP( $A53, _xlfn._xlws.FILTER( INDIRECT("'"&E$14&"'!A2:E1000"), (INDIRECT("'"&E$14&"'!B2:B1000")=$B53) * (INDIRECT("'"&E$14&"'!C2:C1000")=$C53) ), 5, FALSE ) )} | F53: {=IF( VLOOKUP( $A53, _xlfn._xlws.FILTER( INDIRECT("'"&F$14&"'!A2:E1000"), (INDIRECT("'"&F$14&"'!B2:B1000")=$B53) * (INDIRECT("'"&F$14&"'!C2:C1000")=$C53) ), 5, FALSE )=0, "", VLOOKUP( $A53, _xlfn._xlws.FILTER( INDIRECT("'"&F$14&"'!A2:E1000"), (INDIRECT("'"&F$14&"'!B2:B1000")=$B53) * (INDIRECT("'"&F$14&"'!C2:C1000")=$C53) ), 5, FALSE ) )} | G53: {=IF( VLOOKUP( $A53, _xlfn._xlws.FILTER( INDIRECT("'"&G$14&"'!A2:E1000"), (INDIRECT("'"&G$14&"'!B2:B1000")=$B53) * (INDIRECT("'"&G$14&"'!C2:C1000")=$C53) ), 5, FALSE )=0, "", VLOOKUP( $A53, _xlfn._xlws.FILTER( INDIRECT("'"&G$14&"'!A2:E1000"), (INDIRECT("'"&G$14&"'!B2:B1000")=$B53) * (INDIRECT("'"&G$14&"'!C2:C1000")=$C53) ), 5, FALSE ) )} | H53: {=IF( VLOOKUP( $A53, _xlfn._xlws.FILTER( INDIRECT("'"&H$14&"'!A2:E1000"), (INDIRECT("'"&H$14&"'!B2:B1000")=$B53) * (INDIRECT("'"&H$14&"'!C2:C1000")=$C53) ), 5, FALSE )=0, "", VLOOKUP( $A53, _xlfn._xlws.FILTER( INDIRECT("'"&H$14&"'!A2:E1000"), (INDIRECT("'"&H$14&"'!B2:B1000")=$B53) * (INDIRECT("'"&H$14&"'!C2:C1000")=$C53) ), 5, FALSE ) )} | I53: {=IF( VLOOKUP( $A53, _xlfn._xlws.FILTER( INDIRECT("'"&I$14&"'!A2:E1000"), (INDIRECT("'"&I$14&"'!B2:B1000")=$B53) * (INDIRECT("'"&I$14&"'!C2:C1000")=$C53) ), 5, FALSE )=0, "", VLOOKUP( $A53, _xlfn._xlws.FILTER( INDIRECT("'"&I$14&"'!A2:E1000"), (INDIRECT("'"&I$14&"'!B2:B1000")=$B53) * (INDIRECT("'"&I$14&"'!C2:C1000")=$C53) ), 5, FALSE ) )} | J53: {=IF( VLOOKUP( $A53, _xlfn._xlws.FILTER( INDIRECT("'"&J$14&"'!A2:E1000"), (INDIRECT("'"&J$14&"'!B2:B1000")=$B53) * (INDIRECT("'"&J$14&"'!C2:C1000")=$C53) ), 5, FALSE )=0, "", VLOOKUP( $A53, _xlfn._xlws.FILTER( INDIRECT("'"&J$14&"'!A2:E1000"), (INDIRECT("'"&J$14&"'!B2:B1000")=$B53) * (INDIRECT("'"&J$14&"'!C2:C1000")=$C53) ), 5, FALSE ) )} | K53: {=IF( VLOOKUP( $A53, _xlfn._xlws.FILTER( INDIRECT("'"&K$14&"'!A2:E1000"), (INDIRECT("'"&K$14&"'!B2:B1000")=$B53) * (INDIRECT("'"&K$14&"'!C2:C1000")=$C53) ), 5, FALSE )=0, "", VLOOKUP( $A53, _xlfn._xlws.FILTER( INDIRECT("'"&K$14&"'!A2:E1000"), (INDIRECT("'"&K$14&"'!B2:B1000")=$B53) * (INDIRECT("'"&K$14&"'!C2:C1000")=$C53) ), 5, FALSE ) )} | ... Q53: {=IF( VLOOKUP( $A53, _xlfn._xlws.FILTER( INDIRECT("'"&Q$14&"'!A2:E1000"), (INDIRECT("'"&Q$14&"'!B2:B1000")=$B53) * (INDIRECT("'"&Q$14&"'!C2:C1000")=$C53) ), 5, FALSE )=0, "", VLOOKUP( $A53, _xlfn._xlws.FILTER( INDIRECT("'"&Q$14&"'!A2:E1000"), (INDIRECT("'"&Q$14&"'!B2:B1000")=$B53) * (INDIRECT("'"&Q$14&"'!C2:C1000")=$C53) ), 5, FALSE ) )}
A55: Regional | B55: Municípios | C55: UVR | D55: 11.24 | E55: 12.24 | F55: 01.25 | G55: 02.25 | H55: 03.25 | I55: 04.25 | J55: 05.25 | K55: 06.25 | L55: 07.25 | M55: 08.25 | N55: 09.25 | O55: 10.25 | P55: 11.25 | Q55: 12.25
A56: Luana | B56: Diamante d'Oeste | C56: 1 | D56: {=IF( VLOOKUP( $A56, _xlfn._xlws.FILTER( INDIRECT("'"&D$14&"'!A2:E1000"), (INDIRECT("'"&D$14&"'!B2:B1000")=$B56) * (INDIRECT("'"&D$14&"'!C2:C1000")=$C56) ), 5, FALSE )=0, "", VLOOKUP( $A56, _xlfn._xlws.FILTER( INDIRECT("'"&D$14&"'!A2:E1000"), (INDIRECT("'"&D$14&"'!B2:B1000")=$B56) * (INDIRECT("'"&D$14&"'!C2:C1000")=$C56) ), 5, FALSE ) )} | E56: {=IF( VLOOKUP( $A56, _xlfn._xlws.FILTER( INDIRECT("'"&E$14&"'!A2:E1000"), (INDIRECT("'"&E$14&"'!B2:B1000")=$B56) * (INDIRECT("'"&E$14&"'!C2:C1000")=$C56) ), 5, FALSE )=0, "", VLOOKUP( $A56, _xlfn._xlws.FILTER( INDIRECT("'"&E$14&"'!A2:E1000"), (INDIRECT("'"&E$14&"'!B2:B1000")=$B56) * (INDIRECT("'"&E$14&"'!C2:C1000")=$C56) ), 5, FALSE ) )} | F56: {=IF( VLOOKUP( $A56, _xlfn._xlws.FILTER( INDIRECT("'"&F$14&"'!A2:E1000"), (INDIRECT("'"&F$14&"'!B2:B1000")=$B56) * (INDIRECT("'"&F$14&"'!C2:C1000")=$C56) ), 5, FALSE )=0, "", VLOOKUP( $A56, _xlfn._xlws.FILTER( INDIRECT("'"&F$14&"'!A2:E1000"), (INDIRECT("'"&F$14&"'!B2:B1000")=$B56) * (INDIRECT("'"&F$14&"'!C2:C1000")=$C56) ), 5, FALSE ) )} | G56: {=IF( VLOOKUP( $A56, _xlfn._xlws.FILTER( INDIRECT("'"&G$14&"'!A2:E1000"), (INDIRECT("'"&G$14&"'!B2:B1000")=$B56) * (INDIRECT("'"&G$14&"'!C2:C1000")=$C56) ), 5, FALSE )=0, "", VLOOKUP( $A56, _xlfn._xlws.FILTER( INDIRECT("'"&G$14&"'!A2:E1000"), (INDIRECT("'"&G$14&"'!B2:B1000")=$B56) * (INDIRECT("'"&G$14&"'!C2:C1000")=$C56) ), 5, FALSE ) )} | H56: {=IF( VLOOKUP( $A56, _xlfn._xlws.FILTER( INDIRECT("'"&H$14&"'!A2:E1000"), (INDIRECT("'"&H$14&"'!B2:B1000")=$B56) * (INDIRECT("'"&H$14&"'!C2:C1000")=$C56) ), 5, FALSE )=0, "", VLOOKUP( $A56, _xlfn._xlws.FILTER( INDIRECT("'"&H$14&"'!A2:E1000"), (INDIRECT("'"&H$14&"'!B2:B1000")=$B56) * (INDIRECT("'"&H$14&"'!C2:C1000")=$C56) ), 5, FALSE ) )} | I56: {=IF( VLOOKUP( $A56, _xlfn._xlws.FILTER( INDIRECT("'"&I$14&"'!A2:E1000"), (INDIRECT("'"&I$14&"'!B2:B1000")=$B56) * (INDIRECT("'"&I$14&"'!C2:C1000")=$C56) ), 5, FALSE )=0, "", VLOOKUP( $A56, _xlfn._xlws.FILTER( INDIRECT("'"&I$14&"'!A2:E1000"), (INDIRECT("'"&I$14&"'!B2:B1000")=$B56) * (INDIRECT("'"&I$14&"'!C2:C1000")=$C56) ), 5, FALSE ) )} | J56: {=IF( VLOOKUP( $A56, _xlfn._xlws.FILTER( INDIRECT("'"&J$14&"'!A2:E1000"), (INDIRECT("'"&J$14&"'!B2:B1000")=$B56) * (INDIRECT("'"&J$14&"'!C2:C1000")=$C56) ), 5, FALSE )=0, "", VLOOKUP( $A56, _xlfn._xlws.FILTER( INDIRECT("'"&J$14&"'!A2:E1000"), (INDIRECT("'"&J$14&"'!B2:B1000")=$B56) * (INDIRECT("'"&J$14&"'!C2:C1000")=$C56) ), 5, FALSE ) )} | K56: {=IF( VLOOKUP( $A56, _xlfn._xlws.FILTER( INDIRECT("'"&K$14&"'!A2:E1000"), (INDIRECT("'"&K$14&"'!B2:B1000")=$B56) * (INDIRECT("'"&K$14&"'!C2:C1000")=$C56) ), 5, FALSE )=0, "", VLOOKUP( $A56, _xlfn._xlws.FILTER( INDIRECT("'"&K$14&"'!A2:E1000"), (INDIRECT("'"&K$14&"'!B2:B1000")=$B56) * (INDIRECT("'"&K$14&"'!C2:C1000")=$C56) ), 5, FALSE ) )} | ... Q56: {=IF( VLOOKUP( $A56, _xlfn._xlws.FILTER( INDIRECT("'"&Q$14&"'!A2:E1000"), (INDIRECT("'"&Q$14&"'!B2:B1000")=$B56) * (INDIRECT("'"&Q$14&"'!C2:C1000")=$C56) ), 5, FALSE )=0, "", VLOOKUP( $A56, _xlfn._xlws.FILTER( INDIRECT("'"&Q$14&"'!A2:E1000"), (INDIRECT("'"&Q$14&"'!B2:B1000")=$B56) * (INDIRECT("'"&Q$14&"'!C2:C1000")=$C56) ), 5, FALSE ) )}
A57: Luana | B57: Entre Rios do Oeste | C57: 1 | D57: {=IF( VLOOKUP( $A57, _xlfn._xlws.FILTER( INDIRECT("'"&D$14&"'!A2:E1000"), (INDIRECT("'"&D$14&"'!B2:B1000")=$B57) * (INDIRECT("'"&D$14&"'!C2:C1000")=$C57) ), 5, FALSE )=0, "", VLOOKUP( $A57, _xlfn._xlws.FILTER( INDIRECT("'"&D$14&"'!A2:E1000"), (INDIRECT("'"&D$14&"'!B2:B1000")=$B57) * (INDIRECT("'"&D$14&"'!C2:C1000")=$C57) ), 5, FALSE ) )} | E57: {=IF( VLOOKUP( $A57, _xlfn._xlws.FILTER( INDIRECT("'"&E$14&"'!A2:E1000"), (INDIRECT("'"&E$14&"'!B2:B1000")=$B57) * (INDIRECT("'"&E$14&"'!C2:C1000")=$C57) ), 5, FALSE )=0, "", VLOOKUP( $A57, _xlfn._xlws.FILTER( INDIRECT("'"&E$14&"'!A2:E1000"), (INDIRECT("'"&E$14&"'!B2:B1000")=$B57) * (INDIRECT("'"&E$14&"'!C2:C1000")=$C57) ), 5, FALSE ) )} | F57: {=IF( VLOOKUP( $A57, _xlfn._xlws.FILTER( INDIRECT("'"&F$14&"'!A2:E1000"), (INDIRECT("'"&F$14&"'!B2:B1000")=$B57) * (INDIRECT("'"&F$14&"'!C2:C1000")=$C57) ), 5, FALSE )=0, "", VLOOKUP( $A57, _xlfn._xlws.FILTER( INDIRECT("'"&F$14&"'!A2:E1000"), (INDIRECT("'"&F$14&"'!B2:B1000")=$B57) * (INDIRECT("'"&F$14&"'!C2:C1000")=$C57) ), 5, FALSE ) )} | G57: {=IF( VLOOKUP( $A57, _xlfn._xlws.FILTER( INDIRECT("'"&G$14&"'!A2:E1000"), (INDIRECT("'"&G$14&"'!B2:B1000")=$B57) * (INDIRECT("'"&G$14&"'!C2:C1000")=$C57) ), 5, FALSE )=0, "", VLOOKUP( $A57, _xlfn._xlws.FILTER( INDIRECT("'"&G$14&"'!A2:E1000"), (INDIRECT("'"&G$14&"'!B2:B1000")=$B57) * (INDIRECT("'"&G$14&"'!C2:C1000")=$C57) ), 5, FALSE ) )} | H57: {=IF( VLOOKUP( $A57, _xlfn._xlws.FILTER( INDIRECT("'"&H$14&"'!A2:E1000"), (INDIRECT("'"&H$14&"'!B2:B1000")=$B57) * (INDIRECT("'"&H$14&"'!C2:C1000")=$C57) ), 5, FALSE )=0, "", VLOOKUP( $A57, _xlfn._xlws.FILTER( INDIRECT("'"&H$14&"'!A2:E1000"), (INDIRECT("'"&H$14&"'!B2:B1000")=$B57) * (INDIRECT("'"&H$14&"'!C2:C1000")=$C57) ), 5, FALSE ) )} | I57: {=IF( VLOOKUP( $A57, _xlfn._xlws.FILTER( INDIRECT("'"&I$14&"'!A2:E1000"), (INDIRECT("'"&I$14&"'!B2:B1000")=$B57) * (INDIRECT("'"&I$14&"'!C2:C1000")=$C57) ), 5, FALSE )=0, "", VLOOKUP( $A57, _xlfn._xlws.FILTER( INDIRECT("'"&I$14&"'!A2:E1000"), (INDIRECT("'"&I$14&"'!B2:B1000")=$B57) * (INDIRECT("'"&I$14&"'!C2:C1000")=$C57) ), 5, FALSE ) )} | J57: {=IF( VLOOKUP( $A57, _xlfn._xlws.FILTER( INDIRECT("'"&J$14&"'!A2:E1000"), (INDIRECT("'"&J$14&"'!B2:B1000")=$B57) * (INDIRECT("'"&J$14&"'!C2:C1000")=$C57) ), 5, FALSE )=0, "", VLOOKUP( $A57, _xlfn._xlws.FILTER( INDIRECT("'"&J$14&"'!A2:E1000"), (INDIRECT("'"&J$14&"'!B2:B1000")=$B57) * (INDIRECT("'"&J$14&"'!C2:C1000")=$C57) ), 5, FALSE ) )} | K57: {=IF( VLOOKUP( $A57, _xlfn._xlws.FILTER( INDIRECT("'"&K$14&"'!A2:E1000"), (INDIRECT("'"&K$14&"'!B2:B1000")=$B57) * (INDIRECT("'"&K$14&"'!C2:C1000")=$C57) ), 5, FALSE )=0, "", VLOOKUP( $A57, _xlfn._xlws.FILTER( INDIRECT("'"&K$14&"'!A2:E1000"), (INDIRECT("'"&K$14&"'!B2:B1000")=$B57) * (INDIRECT("'"&K$14&"'!C2:C1000")=$C57) ), 5, FALSE ) )} | ... Q57: {=IF( VLOOKUP( $A57, _xlfn._xlws.FILTER( INDIRECT("'"&Q$14&"'!A2:E1000"), (INDIRECT("'"&Q$14&"'!B2:B1000")=$B57) * (INDIRECT("'"&Q$14&"'!C2:C1000")=$C57) ), 5, FALSE )=0, "", VLOOKUP( $A57, _xlfn._xlws.FILTER( INDIRECT("'"&Q$14&"'!A2:E1000"), (INDIRECT("'"&Q$14&"'!B2:B1000")=$B57) * (INDIRECT("'"&Q$14&"'!C2:C1000")=$C57) ), 5, FALSE ) )}
A58: Luana | B58: Itaipulândia | C58: 1 | D58: {=IF( VLOOKUP( $A58, _xlfn._xlws.FILTER( INDIRECT("'"&D$14&"'!A2:E1000"), (INDIRECT("'"&D$14&"'!B2:B1000")=$B58) * (INDIRECT("'"&D$14&"'!C2:C1000")=$C58) ), 5, FALSE )=0, "", VLOOKUP( $A58, _xlfn._xlws.FILTER( INDIRECT("'"&D$14&"'!A2:E1000"), (INDIRECT("'"&D$14&"'!B2:B1000")=$B58) * (INDIRECT("'"&D$14&"'!C2:C1000")=$C58) ), 5, FALSE ) )} | E58: {=IF( VLOOKUP( $A58, _xlfn._xlws.FILTER( INDIRECT("'"&E$14&"'!A2:E1000"), (INDIRECT("'"&E$14&"'!B2:B1000")=$B58) * (INDIRECT("'"&E$14&"'!C2:C1000")=$C58) ), 5, FALSE )=0, "", VLOOKUP( $A58, _xlfn._xlws.FILTER( INDIRECT("'"&E$14&"'!A2:E1000"), (INDIRECT("'"&E$14&"'!B2:B1000")=$B58) * (INDIRECT("'"&E$14&"'!C2:C1000")=$C58) ), 5, FALSE ) )} | F58: {=IF( VLOOKUP( $A58, _xlfn._xlws.FILTER( INDIRECT("'"&F$14&"'!A2:E1000"), (INDIRECT("'"&F$14&"'!B2:B1000")=$B58) * (INDIRECT("'"&F$14&"'!C2:C1000")=$C58) ), 5, FALSE )=0, "", VLOOKUP( $A58, _xlfn._xlws.FILTER( INDIRECT("'"&F$14&"'!A2:E1000"), (INDIRECT("'"&F$14&"'!B2:B1000")=$B58) * (INDIRECT("'"&F$14&"'!C2:C1000")=$C58) ), 5, FALSE ) )} | G58: {=IF( VLOOKUP( $A58, _xlfn._xlws.FILTER( INDIRECT("'"&G$14&"'!A2:E1000"), (INDIRECT("'"&G$14&"'!B2:B1000")=$B58) * (INDIRECT("'"&G$14&"'!C2:C1000")=$C58) ), 5, FALSE )=0, "", VLOOKUP( $A58, _xlfn._xlws.FILTER( INDIRECT("'"&G$14&"'!A2:E1000"), (INDIRECT("'"&G$14&"'!B2:B1000")=$B58) * (INDIRECT("'"&G$14&"'!C2:C1000")=$C58) ), 5, FALSE ) )} | H58: {=IF( VLOOKUP( $A58, _xlfn._xlws.FILTER( INDIRECT("'"&H$14&"'!A2:E1000"), (INDIRECT("'"&H$14&"'!B2:B1000")=$B58) * (INDIRECT("'"&H$14&"'!C2:C1000")=$C58) ), 5, FALSE )=0, "", VLOOKUP( $A58, _xlfn._xlws.FILTER( INDIRECT("'"&H$14&"'!A2:E1000"), (INDIRECT("'"&H$14&"'!B2:B1000")=$B58) * (INDIRECT("'"&H$14&"'!C2:C1000")=$C58) ), 5, FALSE ) )} | I58: {=IF( VLOOKUP( $A58, _xlfn._xlws.FILTER( INDIRECT("'"&I$14&"'!A2:E1000"), (INDIRECT("'"&I$14&"'!B2:B1000")=$B58) * (INDIRECT("'"&I$14&"'!C2:C1000")=$C58) ), 5, FALSE )=0, "", VLOOKUP( $A58, _xlfn._xlws.FILTER( INDIRECT("'"&I$14&"'!A2:E1000"), (INDIRECT("'"&I$14&"'!B2:B1000")=$B58) * (INDIRECT("'"&I$14&"'!C2:C1000")=$C58) ), 5, FALSE ) )} | J58: {=IF( VLOOKUP( $A58, _xlfn._xlws.FILTER( INDIRECT("'"&J$14&"'!A2:E1000"), (INDIRECT("'"&J$14&"'!B2:B1000")=$B58) * (INDIRECT("'"&J$14&"'!C2:C1000")=$C58) ), 5, FALSE )=0, "", VLOOKUP( $A58, _xlfn._xlws.FILTER( INDIRECT("'"&J$14&"'!A2:E1000"), (INDIRECT("'"&J$14&"'!B2:B1000")=$B58) * (INDIRECT("'"&J$14&"'!C2:C1000")=$C58) ), 5, FALSE ) )} | K58: {=IF( VLOOKUP( $A58, _xlfn._xlws.FILTER( INDIRECT("'"&K$14&"'!A2:E1000"), (INDIRECT("'"&K$14&"'!B2:B1000")=$B58) * (INDIRECT("'"&K$14&"'!C2:C1000")=$C58) ), 5, FALSE )=0, "", VLOOKUP( $A58, _xlfn._xlws.FILTER( INDIRECT("'"&K$14&"'!A2:E1000"), (INDIRECT("'"&K$14&"'!B2:B1000")=$B58) * (INDIRECT("'"&K$14&"'!C2:C1000")=$C58) ), 5, FALSE ) )} | ... Q58: {=IF( VLOOKUP( $A58, _xlfn._xlws.FILTER( INDIRECT("'"&Q$14&"'!A2:E1000"), (INDIRECT("'"&Q$14&"'!B2:B1000")=$B58) * (INDIRECT("'"&Q$14&"'!C2:C1000")=$C58) ), 5, FALSE )=0, "", VLOOKUP( $A58, _xlfn._xlws.FILTER( INDIRECT("'"&Q$14&"'!A2:E1000"), (INDIRECT("'"&Q$14&"'!B2:B1000")=$B58) * (INDIRECT("'"&Q$14&"'!C2:C1000")=$C58) ), 5, FALSE ) )}
A59: Luana | B59: Marechal Candido Rondon | C59: 1 | D59: {=IF( VLOOKUP( $A59, _xlfn._xlws.FILTER( INDIRECT("'"&D$14&"'!A2:E1000"), (INDIRECT("'"&D$14&"'!B2:B1000")=$B59) * (INDIRECT("'"&D$14&"'!C2:C1000")=$C59) ), 5, FALSE )=0, "", VLOOKUP( $A59, _xlfn._xlws.FILTER( INDIRECT("'"&D$14&"'!A2:E1000"), (INDIRECT("'"&D$14&"'!B2:B1000")=$B59) * (INDIRECT("'"&D$14&"'!C2:C1000")=$C59) ), 5, FALSE ) )} | E59: {=IF( VLOOKUP( $A59, _xlfn._xlws.FILTER( INDIRECT("'"&E$14&"'!A2:E1000"), (INDIRECT("'"&E$14&"'!B2:B1000")=$B59) * (INDIRECT("'"&E$14&"'!C2:C1000")=$C59) ), 5, FALSE )=0, "", VLOOKUP( $A59, _xlfn._xlws.FILTER( INDIRECT("'"&E$14&"'!A2:E1000"), (INDIRECT("'"&E$14&"'!B2:B1000")=$B59) * (INDIRECT("'"&E$14&"'!C2:C1000")=$C59) ), 5, FALSE ) )} | F59: {=IF( VLOOKUP( $A59, _xlfn._xlws.FILTER( INDIRECT("'"&F$14&"'!A2:E1000"), (INDIRECT("'"&F$14&"'!B2:B1000")=$B59) * (INDIRECT("'"&F$14&"'!C2:C1000")=$C59) ), 5, FALSE )=0, "", VLOOKUP( $A59, _xlfn._xlws.FILTER( INDIRECT("'"&F$14&"'!A2:E1000"), (INDIRECT("'"&F$14&"'!B2:B1000")=$B59) * (INDIRECT("'"&F$14&"'!C2:C1000")=$C59) ), 5, FALSE ) )} | G59: {=IF( VLOOKUP( $A59, _xlfn._xlws.FILTER( INDIRECT("'"&G$14&"'!A2:E1000"), (INDIRECT("'"&G$14&"'!B2:B1000")=$B59) * (INDIRECT("'"&G$14&"'!C2:C1000")=$C59) ), 5, FALSE )=0, "", VLOOKUP( $A59, _xlfn._xlws.FILTER( INDIRECT("'"&G$14&"'!A2:E1000"), (INDIRECT("'"&G$14&"'!B2:B1000")=$B59) * (INDIRECT("'"&G$14&"'!C2:C1000")=$C59) ), 5, FALSE ) )} | H59: {=IF( VLOOKUP( $A59, _xlfn._xlws.FILTER( INDIRECT("'"&H$14&"'!A2:E1000"), (INDIRECT("'"&H$14&"'!B2:B1000")=$B59) * (INDIRECT("'"&H$14&"'!C2:C1000")=$C59) ), 5, FALSE )=0, "", VLOOKUP( $A59, _xlfn._xlws.FILTER( INDIRECT("'"&H$14&"'!A2:E1000"), (INDIRECT("'"&H$14&"'!B2:B1000")=$B59) * (INDIRECT("'"&H$14&"'!C2:C1000")=$C59) ), 5, FALSE ) )} | I59: {=IF( VLOOKUP( $A59, _xlfn._xlws.FILTER( INDIRECT("'"&I$14&"'!A2:E1000"), (INDIRECT("'"&I$14&"'!B2:B1000")=$B59) * (INDIRECT("'"&I$14&"'!C2:C1000")=$C59) ), 5, FALSE )=0, "", VLOOKUP( $A59, _xlfn._xlws.FILTER( INDIRECT("'"&I$14&"'!A2:E1000"), (INDIRECT("'"&I$14&"'!B2:B1000")=$B59) * (INDIRECT("'"&I$14&"'!C2:C1000")=$C59) ), 5, FALSE ) )} | J59: {=IF( VLOOKUP( $A59, _xlfn._xlws.FILTER( INDIRECT("'"&J$14&"'!A2:E1000"), (INDIRECT("'"&J$14&"'!B2:B1000")=$B59) * (INDIRECT("'"&J$14&"'!C2:C1000")=$C59) ), 5, FALSE )=0, "", VLOOKUP( $A59, _xlfn._xlws.FILTER( INDIRECT("'"&J$14&"'!A2:E1000"), (INDIRECT("'"&J$14&"'!B2:B1000")=$B59) * (INDIRECT("'"&J$14&"'!C2:C1000")=$C59) ), 5, FALSE ) )} | K59: {=IF( VLOOKUP( $A59, _xlfn._xlws.FILTER( INDIRECT("'"&K$14&"'!A2:E1000"), (INDIRECT("'"&K$14&"'!B2:B1000")=$B59) * (INDIRECT("'"&K$14&"'!C2:C1000")=$C59) ), 5, FALSE )=0, "", VLOOKUP( $A59, _xlfn._xlws.FILTER( INDIRECT("'"&K$14&"'!A2:E1000"), (INDIRECT("'"&K$14&"'!B2:B1000")=$B59) * (INDIRECT("'"&K$14&"'!C2:C1000")=$C59) ), 5, FALSE ) )} | ... Q59: {=IF( VLOOKUP( $A59, _xlfn._xlws.FILTER( INDIRECT("'"&Q$14&"'!A2:E1000"), (INDIRECT("'"&Q$14&"'!B2:B1000")=$B59) * (INDIRECT("'"&Q$14&"'!C2:C1000")=$C59) ), 5, FALSE )=0, "", VLOOKUP( $A59, _xlfn._xlws.FILTER( INDIRECT("'"&Q$14&"'!A2:E1000"), (INDIRECT("'"&Q$14&"'!B2:B1000")=$B59) * (INDIRECT("'"&Q$14&"'!C2:C1000")=$C59) ), 5, FALSE ) )}
A60: Luana | B60: Marechal Candido Rondon | C60: 2 | D60: {=IF( VLOOKUP( $A60, _xlfn._xlws.FILTER( INDIRECT("'"&D$14&"'!A2:E1000"), (INDIRECT("'"&D$14&"'!B2:B1000")=$B60) * (INDIRECT("'"&D$14&"'!C2:C1000")=$C60) ), 5, FALSE )=0, "", VLOOKUP( $A60, _xlfn._xlws.FILTER( INDIRECT("'"&D$14&"'!A2:E1000"), (INDIRECT("'"&D$14&"'!B2:B1000")=$B60) * (INDIRECT("'"&D$14&"'!C2:C1000")=$C60) ), 5, FALSE ) )} | E60: {=IF( VLOOKUP( $A60, _xlfn._xlws.FILTER( INDIRECT("'"&E$14&"'!A2:E1000"), (INDIRECT("'"&E$14&"'!B2:B1000")=$B60) * (INDIRECT("'"&E$14&"'!C2:C1000")=$C60) ), 5, FALSE )=0, "", VLOOKUP( $A60, _xlfn._xlws.FILTER( INDIRECT("'"&E$14&"'!A2:E1000"), (INDIRECT("'"&E$14&"'!B2:B1000")=$B60) * (INDIRECT("'"&E$14&"'!C2:C1000")=$C60) ), 5, FALSE ) )} | F60: {=IF( VLOOKUP( $A60, _xlfn._xlws.FILTER( INDIRECT("'"&F$14&"'!A2:E1000"), (INDIRECT("'"&F$14&"'!B2:B1000")=$B60) * (INDIRECT("'"&F$14&"'!C2:C1000")=$C60) ), 5, FALSE )=0, "", VLOOKUP( $A60, _xlfn._xlws.FILTER( INDIRECT("'"&F$14&"'!A2:E1000"), (INDIRECT("'"&F$14&"'!B2:B1000")=$B60) * (INDIRECT("'"&F$14&"'!C2:C1000")=$C60) ), 5, FALSE ) )} | G60: {=IF( VLOOKUP( $A60, _xlfn._xlws.FILTER( INDIRECT("'"&G$14&"'!A2:E1000"), (INDIRECT("'"&G$14&"'!B2:B1000")=$B60) * (INDIRECT("'"&G$14&"'!C2:C1000")=$C60) ), 5, FALSE )=0, "", VLOOKUP( $A60, _xlfn._xlws.FILTER( INDIRECT("'"&G$14&"'!A2:E1000"), (INDIRECT("'"&G$14&"'!B2:B1000")=$B60) * (INDIRECT("'"&G$14&"'!C2:C1000")=$C60) ), 5, FALSE ) )} | H60: {=IF( VLOOKUP( $A60, _xlfn._xlws.FILTER( INDIRECT("'"&H$14&"'!A2:E1000"), (INDIRECT("'"&H$14&"'!B2:B1000")=$B60) * (INDIRECT("'"&H$14&"'!C2:C1000")=$C60) ), 5, FALSE )=0, "", VLOOKUP( $A60, _xlfn._xlws.FILTER( INDIRECT("'"&H$14&"'!A2:E1000"), (INDIRECT("'"&H$14&"'!B2:B1000")=$B60) * (INDIRECT("'"&H$14&"'!C2:C1000")=$C60) ), 5, FALSE ) )} | I60: {=IF( VLOOKUP( $A60, _xlfn._xlws.FILTER( INDIRECT("'"&I$14&"'!A2:E1000"), (INDIRECT("'"&I$14&"'!B2:B1000")=$B60) * (INDIRECT("'"&I$14&"'!C2:C1000")=$C60) ), 5, FALSE )=0, "", VLOOKUP( $A60, _xlfn._xlws.FILTER( INDIRECT("'"&I$14&"'!A2:E1000"), (INDIRECT("'"&I$14&"'!B2:B1000")=$B60) * (INDIRECT("'"&I$14&"'!C2:C1000")=$C60) ), 5, FALSE ) )} | J60: {=IF( VLOOKUP( $A60, _xlfn._xlws.FILTER( INDIRECT("'"&J$14&"'!A2:E1000"), (INDIRECT("'"&J$14&"'!B2:B1000")=$B60) * (INDIRECT("'"&J$14&"'!C2:C1000")=$C60) ), 5, FALSE )=0, "", VLOOKUP( $A60, _xlfn._xlws.FILTER( INDIRECT("'"&J$14&"'!A2:E1000"), (INDIRECT("'"&J$14&"'!B2:B1000")=$B60) * (INDIRECT("'"&J$14&"'!C2:C1000")=$C60) ), 5, FALSE ) )} | K60: {=IF( VLOOKUP( $A60, _xlfn._xlws.FILTER( INDIRECT("'"&K$14&"'!A2:E1000"), (INDIRECT("'"&K$14&"'!B2:B1000")=$B60) * (INDIRECT("'"&K$14&"'!C2:C1000")=$C60) ), 5, FALSE )=0, "", VLOOKUP( $A60, _xlfn._xlws.FILTER( INDIRECT("'"&K$14&"'!A2:E1000"), (INDIRECT("'"&K$14&"'!B2:B1000")=$B60) * (INDIRECT("'"&K$14&"'!C2:C1000")=$C60) ), 5, FALSE ) )} | ... Q60: {=IF( VLOOKUP( $A60, _xlfn._xlws.FILTER( INDIRECT("'"&Q$14&"'!A2:E1000"), (INDIRECT("'"&Q$14&"'!B2:B1000")=$B60) * (INDIRECT("'"&Q$14&"'!C2:C1000")=$C60) ), 5, FALSE )=0, "", VLOOKUP( $A60, _xlfn._xlws.FILTER( INDIRECT("'"&Q$14&"'!A2:E1000"), (INDIRECT("'"&Q$14&"'!B2:B1000")=$B60) * (INDIRECT("'"&Q$14&"'!C2:C1000")=$C60) ), 5, FALSE ) )}
A61: Luana | B61: Matelândia | C61: 1 | D61: {=IF( VLOOKUP( $A61, _xlfn._xlws.FILTER( INDIRECT("'"&D$14&"'!A2:E1000"), (INDIRECT("'"&D$14&"'!B2:B1000")=$B61) * (INDIRECT("'"&D$14&"'!C2:C1000")=$C61) ), 5, FALSE )=0, "", VLOOKUP( $A61, _xlfn._xlws.FILTER( INDIRECT("'"&D$14&"'!A2:E1000"), (INDIRECT("'"&D$14&"'!B2:B1000")=$B61) * (INDIRECT("'"&D$14&"'!C2:C1000")=$C61) ), 5, FALSE ) )} | E61: {=IF( VLOOKUP( $A61, _xlfn._xlws.FILTER( INDIRECT("'"&E$14&"'!A2:E1000"), (INDIRECT("'"&E$14&"'!B2:B1000")=$B61) * (INDIRECT("'"&E$14&"'!C2:C1000")=$C61) ), 5, FALSE )=0, "", VLOOKUP( $A61, _xlfn._xlws.FILTER( INDIRECT("'"&E$14&"'!A2:E1000"), (INDIRECT("'"&E$14&"'!B2:B1000")=$B61) * (INDIRECT("'"&E$14&"'!C2:C1000")=$C61) ), 5, FALSE ) )} | F61: {=IF( VLOOKUP( $A61, _xlfn._xlws.FILTER( INDIRECT("'"&F$14&"'!A2:E1000"), (INDIRECT("'"&F$14&"'!B2:B1000")=$B61) * (INDIRECT("'"&F$14&"'!C2:C1000")=$C61) ), 5, FALSE )=0, "", VLOOKUP( $A61, _xlfn._xlws.FILTER( INDIRECT("'"&F$14&"'!A2:E1000"), (INDIRECT("'"&F$14&"'!B2:B1000")=$B61) * (INDIRECT("'"&F$14&"'!C2:C1000")=$C61) ), 5, FALSE ) )} | G61: {=IF( VLOOKUP( $A61, _xlfn._xlws.FILTER( INDIRECT("'"&G$14&"'!A2:E1000"), (INDIRECT("'"&G$14&"'!B2:B1000")=$B61) * (INDIRECT("'"&G$14&"'!C2:C1000")=$C61) ), 5, FALSE )=0, "", VLOOKUP( $A61, _xlfn._xlws.FILTER( INDIRECT("'"&G$14&"'!A2:E1000"), (INDIRECT("'"&G$14&"'!B2:B1000")=$B61) * (INDIRECT("'"&G$14&"'!C2:C1000")=$C61) ), 5, FALSE ) )} | H61: {=IF( VLOOKUP( $A61, _xlfn._xlws.FILTER( INDIRECT("'"&H$14&"'!A2:E1000"), (INDIRECT("'"&H$14&"'!B2:B1000")=$B61) * (INDIRECT("'"&H$14&"'!C2:C1000")=$C61) ), 5, FALSE )=0, "", VLOOKUP( $A61, _xlfn._xlws.FILTER( INDIRECT("'"&H$14&"'!A2:E1000"), (INDIRECT("'"&H$14&"'!B2:B1000")=$B61) * (INDIRECT("'"&H$14&"'!C2:C1000")=$C61) ), 5, FALSE ) )} | I61: {=IF( VLOOKUP( $A61, _xlfn._xlws.FILTER( INDIRECT("'"&I$14&"'!A2:E1000"), (INDIRECT("'"&I$14&"'!B2:B1000")=$B61) * (INDIRECT("'"&I$14&"'!C2:C1000")=$C61) ), 5, FALSE )=0, "", VLOOKUP( $A61, _xlfn._xlws.FILTER( INDIRECT("'"&I$14&"'!A2:E1000"), (INDIRECT("'"&I$14&"'!B2:B1000")=$B61) * (INDIRECT("'"&I$14&"'!C2:C1000")=$C61) ), 5, FALSE ) )} | J61: {=IF( VLOOKUP( $A61, _xlfn._xlws.FILTER( INDIRECT("'"&J$14&"'!A2:E1000"), (INDIRECT("'"&J$14&"'!B2:B1000")=$B61) * (INDIRECT("'"&J$14&"'!C2:C1000")=$C61) ), 5, FALSE )=0, "", VLOOKUP( $A61, _xlfn._xlws.FILTER( INDIRECT("'"&J$14&"'!A2:E1000"), (INDIRECT("'"&J$14&"'!B2:B1000")=$B61) * (INDIRECT("'"&J$14&"'!C2:C1000")=$C61) ), 5, FALSE ) )} | K61: {=IF( VLOOKUP( $A61, _xlfn._xlws.FILTER( INDIRECT("'"&K$14&"'!A2:E1000"), (INDIRECT("'"&K$14&"'!B2:B1000")=$B61) * (INDIRECT("'"&K$14&"'!C2:C1000")=$C61) ), 5, FALSE )=0, "", VLOOKUP( $A61, _xlfn._xlws.FILTER( INDIRECT("'"&K$14&"'!A2:E1000"), (INDIRECT("'"&K$14&"'!B2:B1000")=$B61) * (INDIRECT("'"&K$14&"'!C2:C1000")=$C61) ), 5, FALSE ) )} | ... Q61: {=IF( VLOOKUP( $A61, _xlfn._xlws.FILTER( INDIRECT("'"&Q$14&"'!A2:E1000"), (INDIRECT("'"&Q$14&"'!B2:B1000")=$B61) * (INDIRECT("'"&Q$14&"'!C2:C1000")=$C61) ), 5, FALSE )=0, "", VLOOKUP( $A61, _xlfn._xlws.FILTER( INDIRECT("'"&Q$14&"'!A2:E1000"), (INDIRECT("'"&Q$14&"'!B2:B1000")=$B61) * (INDIRECT("'"&Q$14&"'!C2:C1000")=$C61) ), 5, FALSE ) )}
A62: Luana | B62: Missal | C62: 1 | D62: {=IF( VLOOKUP( $A62, _xlfn._xlws.FILTER( INDIRECT("'"&D$14&"'!A2:E1000"), (INDIRECT("'"&D$14&"'!B2:B1000")=$B62) * (INDIRECT("'"&D$14&"'!C2:C1000")=$C62) ), 5, FALSE )=0, "", VLOOKUP( $A62, _xlfn._xlws.FILTER( INDIRECT("'"&D$14&"'!A2:E1000"), (INDIRECT("'"&D$14&"'!B2:B1000")=$B62) * (INDIRECT("'"&D$14&"'!C2:C1000")=$C62) ), 5, FALSE ) )} | E62: {=IF( VLOOKUP( $A62, _xlfn._xlws.FILTER( INDIRECT("'"&E$14&"'!A2:E1000"), (INDIRECT("'"&E$14&"'!B2:B1000")=$B62) * (INDIRECT("'"&E$14&"'!C2:C1000")=$C62) ), 5, FALSE )=0, "", VLOOKUP( $A62, _xlfn._xlws.FILTER( INDIRECT("'"&E$14&"'!A2:E1000"), (INDIRECT("'"&E$14&"'!B2:B1000")=$B62) * (INDIRECT("'"&E$14&"'!C2:C1000")=$C62) ), 5, FALSE ) )} | F62: {=IF( VLOOKUP( $A62, _xlfn._xlws.FILTER( INDIRECT("'"&F$14&"'!A2:E1000"), (INDIRECT("'"&F$14&"'!B2:B1000")=$B62) * (INDIRECT("'"&F$14&"'!C2:C1000")=$C62) ), 5, FALSE )=0, "", VLOOKUP( $A62, _xlfn._xlws.FILTER( INDIRECT("'"&F$14&"'!A2:E1000"), (INDIRECT("'"&F$14&"'!B2:B1000")=$B62) * (INDIRECT("'"&F$14&"'!C2:C1000")=$C62) ), 5, FALSE ) )} | G62: {=IF( VLOOKUP( $A62, _xlfn._xlws.FILTER( INDIRECT("'"&G$14&"'!A2:E1000"), (INDIRECT("'"&G$14&"'!B2:B1000")=$B62) * (INDIRECT("'"&G$14&"'!C2:C1000")=$C62) ), 5, FALSE )=0, "", VLOOKUP( $A62, _xlfn._xlws.FILTER( INDIRECT("'"&G$14&"'!A2:E1000"), (INDIRECT("'"&G$14&"'!B2:B1000")=$B62) * (INDIRECT("'"&G$14&"'!C2:C1000")=$C62) ), 5, FALSE ) )} | H62: {=IF( VLOOKUP( $A62, _xlfn._xlws.FILTER( INDIRECT("'"&H$14&"'!A2:E1000"), (INDIRECT("'"&H$14&"'!B2:B1000")=$B62) * (INDIRECT("'"&H$14&"'!C2:C1000")=$C62) ), 5, FALSE )=0, "", VLOOKUP( $A62, _xlfn._xlws.FILTER( INDIRECT("'"&H$14&"'!A2:E1000"), (INDIRECT("'"&H$14&"'!B2:B1000")=$B62) * (INDIRECT("'"&H$14&"'!C2:C1000")=$C62) ), 5, FALSE ) )} | I62: {=IF( VLOOKUP( $A62, _xlfn._xlws.FILTER( INDIRECT("'"&I$14&"'!A2:E1000"), (INDIRECT("'"&I$14&"'!B2:B1000")=$B62) * (INDIRECT("'"&I$14&"'!C2:C1000")=$C62) ), 5, FALSE )=0, "", VLOOKUP( $A62, _xlfn._xlws.FILTER( INDIRECT("'"&I$14&"'!A2:E1000"), (INDIRECT("'"&I$14&"'!B2:B1000")=$B62) * (INDIRECT("'"&I$14&"'!C2:C1000")=$C62) ), 5, FALSE ) )} | J62: {=IF( VLOOKUP( $A62, _xlfn._xlws.FILTER( INDIRECT("'"&J$14&"'!A2:E1000"), (INDIRECT("'"&J$14&"'!B2:B1000")=$B62) * (INDIRECT("'"&J$14&"'!C2:C1000")=$C62) ), 5, FALSE )=0, "", VLOOKUP( $A62, _xlfn._xlws.FILTER( INDIRECT("'"&J$14&"'!A2:E1000"), (INDIRECT("'"&J$14&"'!B2:B1000")=$B62) * (INDIRECT("'"&J$14&"'!C2:C1000")=$C62) ), 5, FALSE ) )} | K62: {=IF( VLOOKUP( $A62, _xlfn._xlws.FILTER( INDIRECT("'"&K$14&"'!A2:E1000"), (INDIRECT("'"&K$14&"'!B2:B1000")=$B62) * (INDIRECT("'"&K$14&"'!C2:C1000")=$C62) ), 5, FALSE )=0, "", VLOOKUP( $A62, _xlfn._xlws.FILTER( INDIRECT("'"&K$14&"'!A2:E1000"), (INDIRECT("'"&K$14&"'!B2:B1000")=$B62) * (INDIRECT("'"&K$14&"'!C2:C1000")=$C62) ), 5, FALSE ) )} | ... Q62: {=IF( VLOOKUP( $A62, _xlfn._xlws.FILTER( INDIRECT("'"&Q$14&"'!A2:E1000"), (INDIRECT("'"&Q$14&"'!B2:B1000")=$B62) * (INDIRECT("'"&Q$14&"'!C2:C1000")=$C62) ), 5, FALSE )=0, "", VLOOKUP( $A62, _xlfn._xlws.FILTER( INDIRECT("'"&Q$14&"'!A2:E1000"), (INDIRECT("'"&Q$14&"'!B2:B1000")=$B62) * (INDIRECT("'"&Q$14&"'!C2:C1000")=$C62) ), 5, FALSE ) )}
A63: Luana | B63: Pato Bragado | C63: 1 | D63: {=IF( VLOOKUP( $A63, _xlfn._xlws.FILTER( INDIRECT("'"&D$14&"'!A2:E1000"), (INDIRECT("'"&D$14&"'!B2:B1000")=$B63) * (INDIRECT("'"&D$14&"'!C2:C1000")=$C63) ), 5, FALSE )=0, "", VLOOKUP( $A63, _xlfn._xlws.FILTER( INDIRECT("'"&D$14&"'!A2:E1000"), (INDIRECT("'"&D$14&"'!B2:B1000")=$B63) * (INDIRECT("'"&D$14&"'!C2:C1000")=$C63) ), 5, FALSE ) )} | E63: {=IF( VLOOKUP( $A63, _xlfn._xlws.FILTER( INDIRECT("'"&E$14&"'!A2:E1000"), (INDIRECT("'"&E$14&"'!B2:B1000")=$B63) * (INDIRECT("'"&E$14&"'!C2:C1000")=$C63) ), 5, FALSE )=0, "", VLOOKUP( $A63, _xlfn._xlws.FILTER( INDIRECT("'"&E$14&"'!A2:E1000"), (INDIRECT("'"&E$14&"'!B2:B1000")=$B63) * (INDIRECT("'"&E$14&"'!C2:C1000")=$C63) ), 5, FALSE ) )} | F63: {=IF( VLOOKUP( $A63, _xlfn._xlws.FILTER( INDIRECT("'"&F$14&"'!A2:E1000"), (INDIRECT("'"&F$14&"'!B2:B1000")=$B63) * (INDIRECT("'"&F$14&"'!C2:C1000")=$C63) ), 5, FALSE )=0, "", VLOOKUP( $A63, _xlfn._xlws.FILTER( INDIRECT("'"&F$14&"'!A2:E1000"), (INDIRECT("'"&F$14&"'!B2:B1000")=$B63) * (INDIRECT("'"&F$14&"'!C2:C1000")=$C63) ), 5, FALSE ) )} | G63: {=IF( VLOOKUP( $A63, _xlfn._xlws.FILTER( INDIRECT("'"&G$14&"'!A2:E1000"), (INDIRECT("'"&G$14&"'!B2:B1000")=$B63) * (INDIRECT("'"&G$14&"'!C2:C1000")=$C63) ), 5, FALSE )=0, "", VLOOKUP( $A63, _xlfn._xlws.FILTER( INDIRECT("'"&G$14&"'!A2:E1000"), (INDIRECT("'"&G$14&"'!B2:B1000")=$B63) * (INDIRECT("'"&G$14&"'!C2:C1000")=$C63) ), 5, FALSE ) )} | H63: {=IF( VLOOKUP( $A63, _xlfn._xlws.FILTER( INDIRECT("'"&H$14&"'!A2:E1000"), (INDIRECT("'"&H$14&"'!B2:B1000")=$B63) * (INDIRECT("'"&H$14&"'!C2:C1000")=$C63) ), 5, FALSE )=0, "", VLOOKUP( $A63, _xlfn._xlws.FILTER( INDIRECT("'"&H$14&"'!A2:E1000"), (INDIRECT("'"&H$14&"'!B2:B1000")=$B63) * (INDIRECT("'"&H$14&"'!C2:C1000")=$C63) ), 5, FALSE ) )} | I63: {=IF( VLOOKUP( $A63, _xlfn._xlws.FILTER( INDIRECT("'"&I$14&"'!A2:E1000"), (INDIRECT("'"&I$14&"'!B2:B1000")=$B63) * (INDIRECT("'"&I$14&"'!C2:C1000")=$C63) ), 5, FALSE )=0, "", VLOOKUP( $A63, _xlfn._xlws.FILTER( INDIRECT("'"&I$14&"'!A2:E1000"), (INDIRECT("'"&I$14&"'!B2:B1000")=$B63) * (INDIRECT("'"&I$14&"'!C2:C1000")=$C63) ), 5, FALSE ) )} | J63: {=IF( VLOOKUP( $A63, _xlfn._xlws.FILTER( INDIRECT("'"&J$14&"'!A2:E1000"), (INDIRECT("'"&J$14&"'!B2:B1000")=$B63) * (INDIRECT("'"&J$14&"'!C2:C1000")=$C63) ), 5, FALSE )=0, "", VLOOKUP( $A63, _xlfn._xlws.FILTER( INDIRECT("'"&J$14&"'!A2:E1000"), (INDIRECT("'"&J$14&"'!B2:B1000")=$B63) * (INDIRECT("'"&J$14&"'!C2:C1000")=$C63) ), 5, FALSE ) )} | K63: {=IF( VLOOKUP( $A63, _xlfn._xlws.FILTER( INDIRECT("'"&K$14&"'!A2:E1000"), (INDIRECT("'"&K$14&"'!B2:B1000")=$B63) * (INDIRECT("'"&K$14&"'!C2:C1000")=$C63) ), 5, FALSE )=0, "", VLOOKUP( $A63, _xlfn._xlws.FILTER( INDIRECT("'"&K$14&"'!A2:E1000"), (INDIRECT("'"&K$14&"'!B2:B1000")=$B63) * (INDIRECT("'"&K$14&"'!C2:C1000")=$C63) ), 5, FALSE ) )} | ... Q63: {=IF( VLOOKUP( $A63, _xlfn._xlws.FILTER( INDIRECT("'"&Q$14&"'!A2:E1000"), (INDIRECT("'"&Q$14&"'!B2:B1000")=$B63) * (INDIRECT("'"&Q$14&"'!C2:C1000")=$C63) ), 5, FALSE )=0, "", VLOOKUP( $A63, _xlfn._xlws.FILTER( INDIRECT("'"&Q$14&"'!A2:E1000"), (INDIRECT("'"&Q$14&"'!B2:B1000")=$B63) * (INDIRECT("'"&Q$14&"'!C2:C1000")=$C63) ), 5, FALSE ) )}
A64: Luana | B64: Ramilândia | C64: 1 | D64: {=IF( VLOOKUP( $A64, _xlfn._xlws.FILTER( INDIRECT("'"&D$14&"'!A2:E1000"), (INDIRECT("'"&D$14&"'!B2:B1000")=$B64) * (INDIRECT("'"&D$14&"'!C2:C1000")=$C64) ), 5, FALSE )=0, "", VLOOKUP( $A64, _xlfn._xlws.FILTER( INDIRECT("'"&D$14&"'!A2:E1000"), (INDIRECT("'"&D$14&"'!B2:B1000")=$B64) * (INDIRECT("'"&D$14&"'!C2:C1000")=$C64) ), 5, FALSE ) )} | E64: {=IF( VLOOKUP( $A64, _xlfn._xlws.FILTER( INDIRECT("'"&E$14&"'!A2:E1000"), (INDIRECT("'"&E$14&"'!B2:B1000")=$B64) * (INDIRECT("'"&E$14&"'!C2:C1000")=$C64) ), 5, FALSE )=0, "", VLOOKUP( $A64, _xlfn._xlws.FILTER( INDIRECT("'"&E$14&"'!A2:E1000"), (INDIRECT("'"&E$14&"'!B2:B1000")=$B64) * (INDIRECT("'"&E$14&"'!C2:C1000")=$C64) ), 5, FALSE ) )} | F64: {=IF( VLOOKUP( $A64, _xlfn._xlws.FILTER( INDIRECT("'"&F$14&"'!A2:E1000"), (INDIRECT("'"&F$14&"'!B2:B1000")=$B64) * (INDIRECT("'"&F$14&"'!C2:C1000")=$C64) ), 5, FALSE )=0, "", VLOOKUP( $A64, _xlfn._xlws.FILTER( INDIRECT("'"&F$14&"'!A2:E1000"), (INDIRECT("'"&F$14&"'!B2:B1000")=$B64) * (INDIRECT("'"&F$14&"'!C2:C1000")=$C64) ), 5, FALSE ) )} | G64: {=IF( VLOOKUP( $A64, _xlfn._xlws.FILTER( INDIRECT("'"&G$14&"'!A2:E1000"), (INDIRECT("'"&G$14&"'!B2:B1000")=$B64) * (INDIRECT("'"&G$14&"'!C2:C1000")=$C64) ), 5, FALSE )=0, "", VLOOKUP( $A64, _xlfn._xlws.FILTER( INDIRECT("'"&G$14&"'!A2:E1000"), (INDIRECT("'"&G$14&"'!B2:B1000")=$B64) * (INDIRECT("'"&G$14&"'!C2:C1000")=$C64) ), 5, FALSE ) )} | H64: {=IF( VLOOKUP( $A64, _xlfn._xlws.FILTER( INDIRECT("'"&H$14&"'!A2:E1000"), (INDIRECT("'"&H$14&"'!B2:B1000")=$B64) * (INDIRECT("'"&H$14&"'!C2:C1000")=$C64) ), 5, FALSE )=0, "", VLOOKUP( $A64, _xlfn._xlws.FILTER( INDIRECT("'"&H$14&"'!A2:E1000"), (INDIRECT("'"&H$14&"'!B2:B1000")=$B64) * (INDIRECT("'"&H$14&"'!C2:C1000")=$C64) ), 5, FALSE ) )} | I64: {=IF( VLOOKUP( $A64, _xlfn._xlws.FILTER( INDIRECT("'"&I$14&"'!A2:E1000"), (INDIRECT("'"&I$14&"'!B2:B1000")=$B64) * (INDIRECT("'"&I$14&"'!C2:C1000")=$C64) ), 5, FALSE )=0, "", VLOOKUP( $A64, _xlfn._xlws.FILTER( INDIRECT("'"&I$14&"'!A2:E1000"), (INDIRECT("'"&I$14&"'!B2:B1000")=$B64) * (INDIRECT("'"&I$14&"'!C2:C1000")=$C64) ), 5, FALSE ) )} | J64: {=IF( VLOOKUP( $A64, _xlfn._xlws.FILTER( INDIRECT("'"&J$14&"'!A2:E1000"), (INDIRECT("'"&J$14&"'!B2:B1000")=$B64) * (INDIRECT("'"&J$14&"'!C2:C1000")=$C64) ), 5, FALSE )=0, "", VLOOKUP( $A64, _xlfn._xlws.FILTER( INDIRECT("'"&J$14&"'!A2:E1000"), (INDIRECT("'"&J$14&"'!B2:B1000")=$B64) * (INDIRECT("'"&J$14&"'!C2:C1000")=$C64) ), 5, FALSE ) )} | K64: {=IF( VLOOKUP( $A64, _xlfn._xlws.FILTER( INDIRECT("'"&K$14&"'!A2:E1000"), (INDIRECT("'"&K$14&"'!B2:B1000")=$B64) * (INDIRECT("'"&K$14&"'!C2:C1000")=$C64) ), 5, FALSE )=0, "", VLOOKUP( $A64, _xlfn._xlws.FILTER( INDIRECT("'"&K$14&"'!A2:E1000"), (INDIRECT("'"&K$14&"'!B2:B1000")=$B64) * (INDIRECT("'"&K$14&"'!C2:C1000")=$C64) ), 5, FALSE ) )} | ... Q64: {=IF( VLOOKUP( $A64, _xlfn._xlws.FILTER( INDIRECT("'"&Q$14&"'!A2:E1000"), (INDIRECT("'"&Q$14&"'!B2:B1000")=$B64) * (INDIRECT("'"&Q$14&"'!C2:C1000")=$C64) ), 5, FALSE )=0, "", VLOOKUP( $A64, _xlfn._xlws.FILTER( INDIRECT("'"&Q$14&"'!A2:E1000"), (INDIRECT("'"&Q$14&"'!B2:B1000")=$B64) * (INDIRECT("'"&Q$14&"'!C2:C1000")=$C64) ), 5, FALSE ) )}
A65: Luana | B65: Santa Helena | C65: 1 | D65: {=IF( VLOOKUP( $A65, _xlfn._xlws.FILTER( INDIRECT("'"&D$14&"'!A2:E1000"), (INDIRECT("'"&D$14&"'!B2:B1000")=$B65) * (INDIRECT("'"&D$14&"'!C2:C1000")=$C65) ), 5, FALSE )=0, "", VLOOKUP( $A65, _xlfn._xlws.FILTER( INDIRECT("'"&D$14&"'!A2:E1000"), (INDIRECT("'"&D$14&"'!B2:B1000")=$B65) * (INDIRECT("'"&D$14&"'!C2:C1000")=$C65) ), 5, FALSE ) )} | E65: {=IF( VLOOKUP( $A65, _xlfn._xlws.FILTER( INDIRECT("'"&E$14&"'!A2:E1000"), (INDIRECT("'"&E$14&"'!B2:B1000")=$B65) * (INDIRECT("'"&E$14&"'!C2:C1000")=$C65) ), 5, FALSE )=0, "", VLOOKUP( $A65, _xlfn._xlws.FILTER( INDIRECT("'"&E$14&"'!A2:E1000"), (INDIRECT("'"&E$14&"'!B2:B1000")=$B65) * (INDIRECT("'"&E$14&"'!C2:C1000")=$C65) ), 5, FALSE ) )} | F65: {=IF( VLOOKUP( $A65, _xlfn._xlws.FILTER( INDIRECT("'"&F$14&"'!A2:E1000"), (INDIRECT("'"&F$14&"'!B2:B1000")=$B65) * (INDIRECT("'"&F$14&"'!C2:C1000")=$C65) ), 5, FALSE )=0, "", VLOOKUP( $A65, _xlfn._xlws.FILTER( INDIRECT("'"&F$14&"'!A2:E1000"), (INDIRECT("'"&F$14&"'!B2:B1000")=$B65) * (INDIRECT("'"&F$14&"'!C2:C1000")=$C65) ), 5, FALSE ) )} | G65: {=IF( VLOOKUP( $A65, _xlfn._xlws.FILTER( INDIRECT("'"&G$14&"'!A2:E1000"), (INDIRECT("'"&G$14&"'!B2:B1000")=$B65) * (INDIRECT("'"&G$14&"'!C2:C1000")=$C65) ), 5, FALSE )=0, "", VLOOKUP( $A65, _xlfn._xlws.FILTER( INDIRECT("'"&G$14&"'!A2:E1000"), (INDIRECT("'"&G$14&"'!B2:B1000")=$B65) * (INDIRECT("'"&G$14&"'!C2:C1000")=$C65) ), 5, FALSE ) )} | H65: {=IF( VLOOKUP( $A65, _xlfn._xlws.FILTER( INDIRECT("'"&H$14&"'!A2:E1000"), (INDIRECT("'"&H$14&"'!B2:B1000")=$B65) * (INDIRECT("'"&H$14&"'!C2:C1000")=$C65) ), 5, FALSE )=0, "", VLOOKUP( $A65, _xlfn._xlws.FILTER( INDIRECT("'"&H$14&"'!A2:E1000"), (INDIRECT("'"&H$14&"'!B2:B1000")=$B65) * (INDIRECT("'"&H$14&"'!C2:C1000")=$C65) ), 5, FALSE ) )} | I65: {=IF( VLOOKUP( $A65, _xlfn._xlws.FILTER( INDIRECT("'"&I$14&"'!A2:E1000"), (INDIRECT("'"&I$14&"'!B2:B1000")=$B65) * (INDIRECT("'"&I$14&"'!C2:C1000")=$C65) ), 5, FALSE )=0, "", VLOOKUP( $A65, _xlfn._xlws.FILTER( INDIRECT("'"&I$14&"'!A2:E1000"), (INDIRECT("'"&I$14&"'!B2:B1000")=$B65) * (INDIRECT("'"&I$14&"'!C2:C1000")=$C65) ), 5, FALSE ) )} | J65: {=IF( VLOOKUP( $A65, _xlfn._xlws.FILTER( INDIRECT("'"&J$14&"'!A2:E1000"), (INDIRECT("'"&J$14&"'!B2:B1000")=$B65) * (INDIRECT("'"&J$14&"'!C2:C1000")=$C65) ), 5, FALSE )=0, "", VLOOKUP( $A65, _xlfn._xlws.FILTER( INDIRECT("'"&J$14&"'!A2:E1000"), (INDIRECT("'"&J$14&"'!B2:B1000")=$B65) * (INDIRECT("'"&J$14&"'!C2:C1000")=$C65) ), 5, FALSE ) )} | K65: {=IF( VLOOKUP( $A65, _xlfn._xlws.FILTER( INDIRECT("'"&K$14&"'!A2:E1000"), (INDIRECT("'"&K$14&"'!B2:B1000")=$B65) * (INDIRECT("'"&K$14&"'!C2:C1000")=$C65) ), 5, FALSE )=0, "", VLOOKUP( $A65, _xlfn._xlws.FILTER( INDIRECT("'"&K$14&"'!A2:E1000"), (INDIRECT("'"&K$14&"'!B2:B1000")=$B65) * (INDIRECT("'"&K$14&"'!C2:C1000")=$C65) ), 5, FALSE ) )} | ... Q65: {=IF( VLOOKUP( $A65, _xlfn._xlws.FILTER( INDIRECT("'"&Q$14&"'!A2:E1000"), (INDIRECT("'"&Q$14&"'!B2:B1000")=$B65) * (INDIRECT("'"&Q$14&"'!C2:C1000")=$C65) ), 5, FALSE )=0, "", VLOOKUP( $A65, _xlfn._xlws.FILTER( INDIRECT("'"&Q$14&"'!A2:E1000"), (INDIRECT("'"&Q$14&"'!B2:B1000")=$B65) * (INDIRECT("'"&Q$14&"'!C2:C1000")=$C65) ), 5, FALSE ) )}
