Workbook

Sheet Lacunas
A1: Regional | B1: Município | C1: UVR | D1: Mês da Lacuna | E1: Data de Referência CSV | F1: Data de Referência CSV - Trocado
A2: Valquiria | B2: Formosa do Oeste | C2: 01 | D2: 11.24 | E2: 15/11/2024 | F2: =""&RIGHT(LEFT(E2,5),2)&"/"&LEFT(E2,2)&"/"&RIGHT(E2,4) -> 11/15/2024
A3: Gabriel | B3: Maripa | C3: 01 | D3: 11.24 | E3: 15/11/2024 | F3: =""&RIGHT(LEFT(E3,5),2)&"/"&LEFT(E3,2)&"/"&RIGHT(E3,4) -> 11/15/2024
A4: Gabriel | B4: Mundo Novo | C4: 01 | D4: 11.24 | E4: 15/11/2024 | F4: =""&RIGHT(LEFT(E4,5),2)&"/"&LEFT(E4,2)&"/"&RIGHT(E4,4) -> 11/15/2024
A5: Gabriel | B5: Assis Chateaubriand | C5: 01 | D5: 12.24 | E5: 15/12/2024 | F5: =""&RIGHT(LEFT(E5,5),2)&"/"&LEFT(E5,2)&"/"&RIGHT(E5,4) -> 12/15/2024
A6: Valquiria | B6: Cafelândia | C6: 01 | D6: 12.24 | E6: 15/12/2024 | F6: =""&RIGHT(LEFT(E6,5),2)&"/"&LEFT(E6,2)&"/"&RIGHT(E6,4) -> 12/15/2024
A7: Valquiria | B7: Formosa do Oeste | C7: 01 | D7: 12.24 | E7: 15/12/2024 | F7: =""&RIGHT(LEFT(E7,5),2)&"/"&LEFT(E7,2)&"/"&RIGHT(E7,4) -> 12/15/2024
A8: Larissa | B8: Foz do Iguaçu | C8: 06 | D8: 12.24 | E8: 15/12/2024 | F8: =""&RIGHT(LEFT(E8,5),2)&"/"&LEFT(E8,2)&"/"&RIGHT(E8,4) -> 12/15/2024
A9: Valquiria | B9: Jesuítas | C9: 01 | D9: 12.24 | E9: 15/12/2024 | F9: =""&RIGHT(LEFT(E9,5),2)&"/"&LEFT(E9,2)&"/"&RIGHT(E9,4) -> 12/15/2024
A10: Luana | B10: Marechal Candido Rondon | C10: 01 | D10: 12.24 | E10: 15/12/2024 | F10: =""&RIGHT(LEFT(E10,5),2)&"/"&LEFT(E10,2)&"/"&RIGHT(E10,4) -> 12/15/2024
A11: Luana | B11: Marechal Candido Rondon | C11: 02 | D11: 12.24 | E11: 15/12/2024 | F11: =""&RIGHT(LEFT(E11,5),2)&"/"&LEFT(E11,2)&"/"&RIGHT(E11,4) -> 12/15/2024
A12: Gabriel | B12: Maripa | C12: 01 | D12: 12.24 | E12: 15/12/2024 | F12: =""&RIGHT(LEFT(E12,5),2)&"/"&LEFT(E12,2)&"/"&RIGHT(E12,4) -> 12/15/2024
A13: Gabriel | B13: Palotina | C13: 01 | D13: 12.24 | E13: 15/12/2024 | F13: =""&RIGHT(LEFT(E13,5),2)&"/"&LEFT(E13,2)&"/"&RIGHT(E13,4) -> 12/15/2024
A14: Gabriel | B14: Assis Chateaubriand | C14: 01 | D14: 01.25 | E14: 15/1/2025 | F14: =""&RIGHT(LEFT(E14,5),2)&""&LEFT(E14,2)&"/"&RIGHT(E14,4) -> 1/15/2025
A15: Gabriel | B15: Brasilândia do Sul | C15: 01 | D15: 01.25 | E15: 15/1/2025 | F15: =""&RIGHT(LEFT(E15,5),2)&""&LEFT(E15,2)&"/"&RIGHT(E15,4) -> 1/15/2025
A16: Valquiria | B16: Cafelândia | C16: 01 | D16: 01.25 | E16: 15/1/2025 | F16: =""&RIGHT(LEFT(E16,5),2)&""&LEFT(E16,2)&"/"&RIGHT(E16,4) -> 1/15/2025
A17: Larissa | B17: Foz do Iguaçu | C17: 06 | D17: 01.25 | E17: 15/1/2025 | F17: =""&RIGHT(LEFT(E17,5),2)&""&LEFT(E17,2)&"/"&RIGHT(E17,4) -> 1/15/2025
A18: Valquiria | B18: Jesuítas | C18: 01 | D18: 01.25 | E18: 15/1/2025 | F18: =""&RIGHT(LEFT(E18,5),2)&""&LEFT(E18,2)&"/"&RIGHT(E18,4) -> 1/15/2025
A19: Luana | B19: Marechal Candido Rondon | C19: 01 | D19: 01.25 | E19: 15/1/2025 | F19: =""&RIGHT(LEFT(E19,5),2)&""&LEFT(E19,2)&"/"&RIGHT(E19,4) -> 1/15/2025
A20: Luana | B20: Marechal Candido Rondon | C20: 02 | D20: 01.25 | E20: 15/1/2025 | F20: =""&RIGHT(LEFT(E20,5),2)&""&LEFT(E20,2)&"/"&RIGHT(E20,4) -> 1/15/2025
A21: Gabriel | B21: Palotina | C21: 01 | D21: 01.25 | E21: 15/1/2025 | F21: =""&RIGHT(LEFT(E21,5),2)&""&LEFT(E21,2)&"/"&RIGHT(E21,4) -> 1/15/2025
A22: Gabriel | B22: Palotina | C22: 01 | D22: 01.25 | E22: 15/1/2025 | F22: =""&RIGHT(LEFT(E22,5),2)&""&LEFT(E22,2)&"/"&RIGHT(E22,4) -> 1/15/2025
A23: Bianca | B23: Tres Barras do Parana | C23: 01 | D23: 01.25 | E23: 15/1/2025 | F23: =""&RIGHT(LEFT(E23,5),2)&""&LEFT(E23,2)&"/"&RIGHT(E23,4) -> 1/15/2025

Sheet Macro Dados - Todos
A1: Município | B1: UVR Município + Número | C1: UVR Número | D1: Data de referência | E1: Número de catadores na UVR no mês da data de referência | F1: Observações | G1: Receita venda recicláveis | H1: Receita prestação serviços | I1: Despesas | J1: Quantidade de recicláveis vendidos (kg) | K1: Rejeito (kg) | L1: Renda média catadores
A2: Boa Vista da Aparecida | B2: UVR 01 - Boa Vista da Aparecida | C2: 01 | D2: 15/11/2024 | E2: 9 | G2: 19071.16 | H2: 0 | I2: 0 | J2: 16471.4 | K2: 0 | L2: 1200
A3: Matelândia | B3: UVR 01 - Matelândia | C3: 01 | D3: 15/11/2024 | E3: 19 | F3: Essa valor corresponde a divisão entre os 19 associados. Entretanto, cabe ressaltar que a divisão é realizado por um associado a mais, com escopo de promover o diferencial dos coletores. Destarte, isso, há na somatória as sobras de um associado, 17 dias. | G3: 67793.31 | H3: 26176.5 | I3: 7256.65 | J3: 59380.3 | K3: 22672 | L3: 4478.52
A4: Terra Roxa | B4: UVR 01 - Terra Roxa | C4: 01 | D4: 15/11/2024 | E4: 15 | G4: 25610.16 | H4: 25610.16 | I4: 477.25 | J4: 33396.6 | K4: 13697.9 | L4: 2176.34
A5: Palotina | B5: UVR 01 - Palotina | C5: 01 | D5: 15/11/2024 | E5: 20 | F5: O total de Associados que trabalharam todos os dias( não tiveram faltas) foram 2 dois) | G5: 60299.1 | H5: 0 | I5: 12857.6 | J5: 94134 | K5: 59280 | L5: 3489.6
A6: Foz do Iguaçu | B6: UVR 04 - Foz do Iguaçu | C6: 04 | D6: 15/11/2024 | E6: 21 | F6: Os valores acima se referem ao mês de Novembro. | G6: 48942.46 | H6: 35639.19 | I6: 35639.19 | J6: 41305.4 | K6: 6100 | L6: 2933.21
A7: Capitão Leonidas Marques | B7: UVR 01 - Capitão Leonidas Marques | C7: 01 | D7: 15/11/2024 | E7: 17 | G7: 63618.97 | H7: 22223.11 | I7: 31891.02 | J7: 61224.5 | K7: 8825 | L7: 3156.12
A8: Foz do Iguaçu | B8: UVR 08 - Foz do Iguaçu | C8: 08 | D8: 15/11/2024 | E8: 19 | G8: 17530.5 | H8: 29212.43 | I8: 22694.42 | J8: 22318 | K8: 3347.7 | L8: 1368
A9: Missal | B9: UVR 01 - Missal | C9: 01 | D9: 15/11/2024 | E9: 20 | G9: 66332.61 | H9: 77678.97 | I9: 8627.96 | J9: 64840.18 | K9: 11.87 | L9: 3848.61
A10: Cascavel | B10: UVR 06 - Cascavel | C10: 06 | D10: 15/11/2024 | E10: 16 | G10: 23098.7 | H10: 1123.68 | I10: 9730.39 | J10: 24649.8 | K10: 4340.3 | L10: 1015.01
A11: Foz do Iguaçu | B11: UVR 03 - Foz do Iguaçu | C11: 03 | D11: 15/11/2024 | E11: 20 | G11: 30408.25 | H11: 39123.23 | I11: 24093.5 | J11: 43674.5 | K11: 6551 | L11: 2700
A12: Diamante do Sul | B12: UVR 01 - Diamante do Sul | C12: 01 | D12: 15/11/2024 | E12: 1 | G12: 6282.8 | H12: 0 | I12: 2200 | J12: 5570 | K12: 0 | L12: 4083.5
A13: Cascavel | B13: UVR 03 - Cascavel | C13: 03 | D13: 15/11/2024 | E13: 21 | G13: 44923.39 | H13: 19122.44 | I13: 23286.2 | J13: 66740 | K13: 14198.7 | L13: 1240.06
A14: São Pedro do Iguaçu | B14: UVR 01 - São Pedro do Iguaçu | C14: 01 | D14: 15/11/2024 | E14: 14 | G14: 17061.9 | H14: 9000 | I14: 0 | J14: 17656 | K14: 1600 | L14: 1981.6
A15: Serranopolis do Iguaçu | B15: UVR 01 - Serranopolis do Iguaçu | C15: 01 | D15: 15/11/2024 | E15: 10 | G15: 21807.74 | H15: 12249 | I15: 5460.57 | J15: 21585.5 | K15: 5639 | L15: 2860.51
A16: Itaipulândia | B16: UVR 01 - Itaipulândia | C16: 01 | D16: 15/11/2024 | E16: 60 | F16: 1 se encontra em auxilio reclusão | G16: 93880.62 | H16: 92350.38 | I16: 32721.62 | J16: 85412.81 | K16: 16950 | L16: 2601.5
A17: Foz do Iguaçu | B17: UVR 05 - Foz do Iguaçu | C17: 05 | D17: 15/11/2024 | E17: 14 | F17: Valores referente ao mês de novembro | G17: 29531.08 | H17: 39123.24 | I17: 39123.24 | J17: 43525.2 | K17: 6525 | L17: 2280.39
A18: Campo Bonito | B18: UVR 01 - Campo Bonito | C18: 01 | D18: 15/11/2024 | E18: 8 | G18: 13672.84 | H18: 19500 | I18: 7735.18 | J18: 11611.6 | K18: 4800 | L18: 2936.5
A19: Mundo Novo | B19: UVR 01 - Mundo Novo | C19: 01 | D19: 15/11/2024 | E19: 15 | G19: 35681.9 | H19: 0 | I19: 628.32 | J19: 51259.5 | K19: 5469 | L19: 2334.2
A20: Santa Helena | B20: UVR 01 - Santa Helena | C20: 01 | D20: 15/11/2024 | E20: 69 | G20: 93013.12 | H20: 0 | I20: 28451.22 | J20: 113235.1 | K20: 15000 | L20: 2104.83
A21: Vera Cruz do Oeste | B21: UVR 01 - Vera Cruz do Oeste | C21: 01 | D21: 15/11/2024 | E21: 16 | G21: 17881.93 | H21: 6660.28 | I21: 7837.81 | J21: 19418 | K21: 8780 | L21: 1500
A22: Jesuítas | B22: UVR 01 - Jesuítas | C22: 01 | D22: 15/11/2024 | E22: 9 | G22: 31383.45 | H22: 0 | I22: 0 | J22: 34526 | K22: 0 | L22: 3487
A23: Assis Chateaubriand | B23: UVR 01 - Assis Chateaubriand | C23: 01 | D23: 15/11/2024 | E23: 35 | F23: 1 à 18/11/2024. O término do mês foi antecipado, devido ao encerramento do contrato com o município. | G23: 50302.61 | H23: 15245.65 | I23: 870.37 | J23: 43559 | K23: 20650 | L23: 1936.56
A24: Iguatu | B24: UVR 01 - Iguatu | C24: 01 | D24: 15/11/2024 | E24: 5 | G24: 5806.27 | H24: 2653 | I24: 1100 | J24: 7580 | K24: 915 | L24: 1800
A25: Anahy | B25: UVR 01 - Anahy | C25: 01 | D25: 15/11/2024 | E25: 5 | G25: 8731.05 | H25: 0 | I25: 0 | J25: 10080 | K25: 0 | L25: 3129.24
A26: Pato Bragado | B26: UVR 01 - Pato Bragado | C26: 01 | D26: 15/11/2024 | E26: 11 | G26: 25017.69 | H26: 20059.85 | I26: 15663.72 | J26: 25560.89 | K26: 3072.09 | L26: 1889.8
A27: São Miguel do Iguaçu | B27: UVR 01 - São Miguel do Iguaçu | C27: 01 | D27: 15/11/2024 | E27: 41 | F27: renda com prestação de serviço | G27: 70493.19 | H27: 32570 | I27: 12341.4 | J27: 77242.2 | K27: 42550 | L27: 3000
A28: Medianeira | B28: UVR 01 - Medianeira | C28: 01 | D28: 15/11/2024 | E28: 50 | G28: 65077.51 | H28: 35250 | I28: 11112.5 | J28: 66201.5 | K28: 2750 | L28: 2064.27
A29: São Jose das Palmeiras | B29: UVR 01 - São Jose das Palmeiras | C29: 01 | D29: 15/11/2024 | E29: 6 | G29: 12943.5 | H29: 10220.59 | I29: 1197.79 | J29: 10725.3 | K29: 1121 | L29: 3660.8
A30: Catanduvas | B30: UVR 01 - Catanduvas | C30: 01 | D30: 15/11/2024 | E30: 10 | G30: 29839.84 | H30: 10036.15 | I30: 790.81 | J30: 24389 | K30: 4719 | L30: 3550
A31: Cafelândia | B31: UVR 01 - Cafelândia | C31: 01 | D31: 15/11/2024 | E31: 54 | G31: 53998.08 | H31: 0 | I31: 18963.58 | J31: 60590 | K31: 0 | L31: 2210
A32: Cascavel | B32: UVR 02 - Cascavel | C32: 02 | D32: 15/11/2024 | E32: 24 | G32: 68057.39 | H32: 59808.36 | I32: 28912.5 | J32: 99914.5 | K32: 9557.13 | L32: 1958.59
A33: Nova Santa Rosa | B33: UVR 01 - Nova Santa Rosa | C33: 01 | D33: 15/11/2024 | E33: 9 | G33: 25895.9 | H33: 6090.29 | I33: 1982.59 | J33: 33698.5 | K33: 3580 | L33: 3628.57
A34: Tupassi | B34: UVR 01 - Tupassi | C34: 01 | D34: 15/11/2024 | E34: 3 | G34: 8253.88 | H34: 0 | I34: 293 | J34: 10204 | K34: 2500 | L34: 2751
A35: Altônia | B35: UVR 01 - Altônia | C35: 01 | D35: 15/11/2024 | E35: 15 | G35: 34460.29 | H35: 0 | I35: 2630.77 | J35: 39412.5 | K35: 4474 | L35: 2500
A36: Cascavel | B36: UVR 04 - Cascavel | C36: 04 | D36: 15/11/2024 | E36: 22 | G36: 34172.1 | H36: 550 | I36: 17072.86 | J36: 27595.2 | K36: 10907 | L36: 1500
A37: Iracema do Oeste | B37: UVR 01 - Iracema do Oeste | C37: 01 | D37: 15/11/2024 | E37: 7 | G37: 11556.5 | H37: 16512 | I37: 1087.24 | J37: 14886.5 | K37: 1402 | L37: 2732.74
A38: Ubirata | B38: UVR 01 - Ubirata | C38: 01 | D38: 15/11/2024 | E38: 16 | G38: 32144.62 | H38: 5074.23 | I38: 3883.5 | J38: 30060 | K38: 10000 | L38: 2328.15
A39: Tres Barras do Parana | B39: UVR 01 - Tres Barras do Parana | C39: 01 | D39: 15/11/2024 | E39: 10 | G39: 24170.2 | H39: 1300 | I39: 0 | J39: 42170 | K39: 0 | L39: 2800
A40: Toledo | B40: UVR 01 - Toledo | C40: 01 | D40: 15/11/2024 | E40: 60 | G40: 109016.76 | H40: 40158 | I40: 112000 | J40: 200740 | K40: 134770 | L40: 2200
A41: Braganey | B41: UVR 01 - Braganey | C41: 01 | D41: 15/11/2024 | E41: 10 | F41: o valor em kg processado é de 24.048,00, mas sendo emitido na Nfe ,e de 17,048,00,(vlr total do teto em kg no contrato)tendo sabra de 7.000kg, para o próximo mês | G41: 16906.6 | H41: 8524 | I41: 3070 | J41: 17048 | K41: 0 | L41: 2177.8
A42: Cascavel | B42: UVR 05 - Cascavel | C42: 05 | D42: 15/11/2024 | E42: 22 | F42: 1560,00 reais referente ao rateio de novembro, mais a soma da renda média de rateio do valor de repasse municipal de 668,74 por catador. | G42: 32158.99 | H42: 4810.13 | I42: 9793.9 | J42: 34291 | K42: 6875 | L42: 2228.74
A43: Quatro Pontes | B43: UVR 01 - Quatro Pontes | C43: 01 | D43: 15/11/2024 | E43: 5 | F43: essa renda não representa o ideal, pois o rateio não é por diária | G43: 19470.47 | H43: 13562.2 | I43: 660 | J43: 21524.3 | K43: 6392 | L43: 3774.09
A44: Lindoeste | B44: UVR 01 - Lindoeste | C44: 01 | D44: 15/11/2024 | E44: 4 | G44: 7825.9 | H44: 4710.62 | I44: 1642.15 | J44: 6901.1 | K44: 0 | L44: 2723.56
A45: Santa Lúcia | B45: UVR 01 - Santa Lúcia | C45: 01 | D45: 15/11/2024 | E45: 10 | G45: 12219.62 | H45: 5225 | I45: 609.76 | J45: 8677.8 | K45: 2250 | L45: 2425.36
A46: Cascavel | B46: UVR 01 - Cascavel | C46: 01 | D46: 15/11/2024 | E46: 20 | G46: 62703.05 | H46: 24612.5 | I46: 40752.12 | J46: 121043.6 | K46: 12060 | L46: 2307.19
A47: Brasilândia do Sul | B47: UVR 01 - Brasilândia do Sul | C47: 01 | D47: 15/11/2024 | E47: 6 | G47: 5616.15 | H47: 3932.5 | I47: 0 | J47: 7012 | K47: 1725 | L47: 1655
A48: Ramilândia | B48: UVR 01 - Ramilândia | C48: 01 | D48: 15/11/2024 | E48: 10 | F48: Foi realizado o carregamento da carga referente ao mês de NOVEMBRO no dia 11/12/2024 | G48: 20307.67 | H48: 16657.9 | I48: 1700 | J48: 24036.65 | K48: 3240 | L48: 3487
A49: Céu Azul | B49: UVR 01 - Céu Azul | C49: 01 | D49: 15/11/2024 | E49: 15 | G49: 85456.9 | H49: 7259 | I49: 57370 | J49: 65260 | K49: 7580 | L49: 1873
A50: Maripa | B50: UVR 01 - Maripa | C50: 01 | D50: 15/11/2024 | E50: 5 | F50: A Recima é uma empresa tercerizada contratada pelo Município e o pagamento é realizado pela empresa | G50: 24858.1 | H50: 29503.37 | I50: 0 | J50: 28540 | K50: 0 | L50: 2500
A51: Diamante d'Oeste | B51: UVR 01 - Diamante d'Oeste | C51: 01 | D51: 15/11/2024 | E51: 13 | G51: 14945.49 | H51: 11956.57 | I51: 4409.63 | J51: 19870.8 | K51: 4702 | L51: 1856.72
A52: Francisco Alves | B52: UVR 01 - Francisco Alves | C52: 01 | D52: 15/11/2024 | E52: 13 | G52: 23858.49 | H52: 6000 | I52: 1440.62 | J52: 20769.6 | K52: 8156 | L52: 2244
A53: Ibema | B53: UVR 01 - Ibema | C53: 01 | D53: 15/11/2024 | E53: 9 | F53: bonificacao + valor da carga mensal | G53: 14417.75 | H53: 8388 | I53: 1538 | J53: 12526 | K53: 3189 | L53: 2533.88
A54: Foz do Iguaçu | B54: UVR 02 - Foz do Iguaçu | C54: 02 | D54: 15/11/2024 | E54: 18 | F54: Valores referentes ao mês de novembro/2024. | G54: 23062.85 | H54: 38862.3 | I54: 38862.3 | J54: 42980.8 | K54: 6400 | L54: 1352.45
A55: Nova Aurora | B55: UVR 01 - Nova Aurora | C55: 01 | D55: 15/11/2024 | E55: 11 | G55: 33992.9 | H55: 11963 | I55: 1754.09 | J55: 31719.18 | K55: 9800 | L55: 2997
A56: Mercedes | B56: UVR 01 - Mercedes | C56: 01 | D56: 15/11/2024 | E56: 11 | G56: 26678.65 | H56: 24178.55 | I56: 4419.24 | J56: 36000.3 | K56: 12400 | L56: 4950.9
A57: Ouro Verde do Oeste | B57: UVR 01 - Ouro Verde do Oeste | C57: 01 | D57: 15/11/2024 | E57: 10 | G57: 12058.23 | H57: 0 | I57: 0 | J57: 10500 | K57: 84000 | L57: 1229.47
A58: Corbélia | B58: UVR 01 - Corbélia | C58: 01 | D58: 15/11/2024 | E58: 38 | G58: 48137.37 | H58: 46057.56 | I58: 10305.11 | J58: 61263 | K58: 15680 | L58: 2600
A59: Santa Tereza do Oeste | B59: UVR 01 - Santa Tereza do Oeste | C59: 01 | D59: 15/11/2024 | E59: 3 | G59: 12308.7 | H59: 0 | I59: 1595.44 | J59: 12521.7 | K59: 0 | L59: 3000
A60: Santa Terezinha de Itaipu | B60: UVR 01 - Santa Terezinha de Itaipu | C60: 01 | D60: 15/11/2024 | E60: 43 | G60: 136193.52 | H60: 66227.5 | I60: 7374.85 | J60: 130969.3 | K60: 34375.4 | L60: 4595.63
A61: Guaira | B61: UVR 01 - Guaira | C61: 01 | D61: 15/11/2024 | E61: 16 | G61: 29710.85 | H61: 4000 | I61: 2840 | J61: 33806.75 | K61: 10000 | L61: 1800
A62: Terra Roxa | B62: UVR 01 - Terra Roxa | C62: 01 | D62: 15/12/2024 | E62: 15 | G62: 12404.15 | H62: 12404.15 | I62: 260 | J62: 15420 | K62: 14302.4 | L62: 2000
A63: Vera Cruz do Oeste | B63: UVR 01 - Vera Cruz do Oeste | C63: 01 | D63: 15/12/2024 | E63: 15 | G63: 27206.17 | H63: 10320.51 | I63: 6352.99 | J63: 24318.5 | K63: 8980 | L63: 2600
A64: Palotina | B64: UVR 01 - Palotina | C64: 01 | D64: 15/12/2024 | E64: 20 | F64: O total de Associados que trabalharam todos os dias( não tiveram faltas) foram 3 três) | G64: 65586.5 | H64: 0 | I64: 18985.51 | J64: 102194 | K64: 48200 | L64: 6642.2
A65: Santa Lúcia | B65: UVR 01 - Santa Lúcia | C65: 01 | D65: 15/12/2024 | E65: 10 | G65: 4361.2 | H65: 5225 | I65: 218 | J65: 4530 | K65: 1750 | L65: 1560
A66: Foz do Iguaçu | B66: UVR 07 - Foz do Iguaçu | C66: 07 | D66: 15/11/2024 | E66: 18 | G66: 31439.35 | H66: 35978.31 | I66: 19948.16 | J66: 35121 | K66: 4715.94 | L66: 2846.33
A67: Foz do Iguaçu | B67: UVR 07 - Foz do Iguaçu | C67: 07 | D67: 15/12/2024 | E67: 18 | G67: 23121.75 | H67: 34389.49 | I67: 21172.62 | J67: 29678.8 | K67: 4451.82 | L67: 2527
A68: Brasilândia do Sul | B68: UVR 01 - Brasilândia do Sul | C68: 01 | D68: 15/12/2024 | E68: 5 | G68: 5980.3 | H68: 3955.6 | I68: 0 | J68: 7192 | K68: 1729 | L68: 1800
A69: Missal | B69: UVR 01 - Missal | C69: 01 | D69: 15/12/2024 | E69: 20 | F69: vendas realizadas até o dia 20 de dezembro 2024, não recebendo o contrato da prefeitura esse mês, só em fevereiro | G69: 50047.45 | H69: 0 | I69: 4196 | J69: 51867.8 | K69: 11.07 | L69: 3166.76
A70: Foz do Iguaçu | B70: UVR 04 - Foz do Iguaçu | C70: 04 | D70: 15/12/2024 | E70: 23 | F70: Os valores acima se referem ao mês de Dezembro. | G70: 42987.78 | H70: 37127.85 | I70: 37127.85 | J70: 45968.4 | K70: 6800 | L70: 2066.7
A71: Marechal Candido Rondon | B71: UVR 02 - Marechal Candido Rondon | C71: 02 | D71: 15/11/2024 | E71: 35 | G71: 154283.51 | H71: 76402.67 | I71: 0 | J71: 152861 | K71: 39150 | L71: 2900
A72: Marechal Candido Rondon | B72: UVR 01 - Marechal Candido Rondon | C72: 01 | D72: 15/11/2024 | E72: 35 | G72: 142817.56 | H72: 76402.32 | I72: 0 | J72: 150118.5 | K72: 44580 | L72: 2700
A73: Pato Bragado | B73: UVR 01 - Pato Bragado | C73: 01 | D73: 15/12/2024 | E73: 10 | G73: 20833.91 | H73: 18578.67 | I73: 14440.33 | J73: 22270 | K73: 4500 | L73: 1431.47
A74: Capitão Leonidas Marques | B74: UVR 01 - Capitão Leonidas Marques | C74: 01 | D74: 15/12/2024 | E74: 19 | G74: 66413.18 | H74: 22516.69 | I74: 32538.72 | J74: 62028.3 | K74: 9300 | L74: 2937.95
A75: Cascavel | B75: UVR 02 - Cascavel | C75: 02 | D75: 15/12/2024 | E75: 30 | G75: 87187.37 | H75: 8885.97 | I75: 31197.67 | J75: 108988.52 | K75: 29750.1 | L75: 2837.6
A76: Cafelândia | B76: UVR 01 - Cafelândia | C76: 01 | D76: 15/12/2024 | E76: 54 | F76: valor da diaria mês de Dezembro R$113,71 | G76: 64350.62 | H76: 20918.32 | I76: 16068.48 | J76: 70264 | K76: 18290 | L76: 2103.63
A77: Campo Bonito | B77: UVR 01 - Campo Bonito | C77: 01 | D77: 15/12/2024 | E77: 8 | G77: 14315.1 | H77: 20414.61 | I77: 6288.2 | J77: 10619.6 | K77: 4700 | L77: 3183
A78: São Jose das Palmeiras | B78: UVR 01 - São Jose das Palmeiras | C78: 01 | D78: 15/12/2024 | E78: 6 | G78: 15901.09 | H78: 11028.61 | I78: 1197.79 | J78: 11687.87 | K78: 1437.8 | L78: 4290.97
A79: Tres Barras do Parana | B79: UVR 01 - Tres Barras do Parana | C79: 01 | D79: 15/12/2024 | E79: 12 | G79: 18874.58 | H79: 0 | I79: 0 | J79: 30019 | K79: 4000 | L79: 2300
A80: Medianeira | B80: UVR 01 - Medianeira | C80: 01 | D80: 15/12/2024 | E80: 48 | G80: 66589.87 | H80: 39750 | I80: 13806.06 | J80: 62073.5 | K80: 26340 | L80: 2404.33
A81: Foz do Iguaçu | B81: UVR 08 - Foz do Iguaçu | C81: 08 | D81: 15/12/2024 | E81: 19 | G81: 18116.35 | H81: 26614.29 | I81: 22701.65 | J81: 20565.5 | K81: 3084.82 | L81: 1834.63
A82: Iguatu | B82: UVR 01 - Iguatu | C82: 01 | D82: 15/12/2024 | E82: 3 | G82: 7399.43 | H82: 29670.87 | I82: 1841.4 | J82: 8702.5 | K82: 1030 | L82: 3040
A83: Matelândia | B83: UVR 01 - Matelândia | C83: 01 | D83: 15/12/2024 | E83: 19 | F83: Valores mensais record dese janeiro de 2019 :) Ano record desde 2019 , 685 toneladas comercializadas em 2024 | G83: 76208.54 | H83: 30474 | I83: 8747.05 | J83: 67726.2 | K83: 26736 | L83: 5171.77
A84: Jesuítas | B84: UVR 01 - Jesuítas | C84: 01 | D84: 15/12/2024 | E84: 10 | G84: 32954.2 | H84: 0 | I84: 0 | J84: 30594 | K84: 0 | L84: 3295.42
A85: Tupassi | B85: UVR 01 - Tupassi | C85: 01 | D85: 15/12/2024 | E85: 4 | G85: 6099.64 | H85: 1932.66 | I85: 128 | J85: 7158 | K85: 3500 | L85: 1524.96
A86: Marechal Candido Rondon | B86: UVR 01 - Marechal Candido Rondon | C86: 01 | D86: 15/12/2024 | E86: 30 | G86: 81830.64 | H86: 76402.32 | I86: 0 | J86: 150054.1 | K86: 29740 | L86: 2900
A87: Anahy | B87: UVR 01 - Anahy | C87: 01 | D87: 15/12/2024 | E87: 5 | G87: 10081.88 | H87: 0 | I87: 0 | J87: 9780 | K87: 0 | L87: 2910.82
A88: Marechal Candido Rondon | B88: UVR 02 - Marechal Candido Rondon | C88: 02 | D88: 15/12/2024 | E88: 29 | G88: 139018.76 | H88: 76402.67 | I88: 0 | J88: 154296.2 | K88: 25980 | L88: 3000
A89: Catanduvas | B89: UVR 01 - Catanduvas | C89: 01 | D89: 15/12/2024 | E89: 10 | G89: 27909.55 | H89: 13148 | I89: 1253.52 | J89: 33280 | K89: 4032 | L89: 4180
A90: Foz do Iguaçu | B90: UVR 03 - Foz do Iguaçu | C90: 03 | D90: 15/12/2024 | E90: 20 | G90: 27498.25 | H90: 39448.17 | I90: 26209.08 | J90: 58248 | K90: 6773 | L90: 2700
A91: Foz do Iguaçu | B91: UVR 05 - Foz do Iguaçu | C91: 05 | D91: 15/12/2024 | E91: 14 | F91: Valores referente ao mês de dezembro | G91: 31988.88 | H91: 39748.63 | I91: 39748.63 | J91: 44180 | K91: 5820 | L91: 2355.77
A92: São Pedro do Iguaçu | B92: UVR 01 - São Pedro do Iguaçu | C92: 01 | D92: 15/12/2024 | E92: 14 | G92: 12360.25 | H92: 0 | I92: 0 | J92: 16412 | K92: 1300 | L92: 1855.6
A93: Mundo Novo | B93: UVR 01 - Mundo Novo | C93: 01 | D93: 15/12/2024 | E93: 14 | G93: 38396.95 | H93: 0 | I93: 715.36 | J93: 38938 | K93: 7612 | L93: 2691.4
A94: Foz do Iguaçu | B94: UVR 02 - Foz do Iguaçu | C94: 02 | D94: 15/12/2024 | E94: 18 | F94: Valores referentes ao mês de dezembro/2024. | G94: 29668.23 | H94: 39639.87 | I94: 39639.87 | J94: 43571 | K94: 6500 | L94: 1692.78
A95: Foz do Iguaçu | B95: UVR 06 - Foz do Iguaçu | C95: 06 | D95: 15/11/2024 | E95: 19 | G95: 38908.29 | H95: 0 | I95: 13585.77 | J95: 50660.23 | K95: 7600 | L95: 2557.2
A96: Iracema do Oeste | B96: UVR 01 - Iracema do Oeste | C96: 01 | D96: 15/12/2024 | E96: 7 | G96: 8281.87 | H96: 16512 | I96: 1796.04 | J96: 7737 | K96: 1333 | L96: 2634
A97: São Miguel do Iguaçu | B97: UVR 01 - São Miguel do Iguaçu | C97: 01 | D97: 15/12/2024 | E97: 40 | F97: Renda com prestação de serviço | G97: 75043.54 | H97: 32570 | I97: 11966.07 | J97: 86275.8 | K97: 44000 | L97: 2900
A98: Ibema | B98: UVR 01 - Ibema | C98: 01 | D98: 15/12/2024 | E98: 10 | F98: venda de reciclaveis+contratos=renda mensal | G98: 14437.36 | H98: 6157.77 | I98: 2174 | J98: 14726.8 | K98: 5400 | L98: 2059.51
A99: Assis Chateaubriand | B99: UVR 01 - Assis Chateaubriand | C99: 01 | D99: 15/12/2024 | E99: 34 | F99: 01/12 à 23/12/2024 | G99: 69057.61 | H99: 30460.27 | I99: 8744 | J99: 87028.86 | K99: 15606 | L99: 3185
A100: Itaipulândia | B100: UVR 01 - Itaipulândia | C100: 01 | D100: 15/12/2024 | E100: 58 | G100: 83744.41 | H100: 174810.51 | I100: 18554.67 | J100: 83030.6 | K100: 20010 | L100: 2724.41
...

Sheet Macro Dados - Filtrados
A1: Regional | B1: Município | C1: UVR Município + Número | D1: UVR Número | E1: Data de referência | F1: Número de catadores na UVR no mês da data de referência | G1: Observações | H1: Receita venda recicláveis | I1: Receita prestação serviços | J1: Despesas | K1: Quantidade de recicláveis vendidos (kg) | L1: Rejeito (kg) | M1: Renda média catadores
A2: Valquiria | B2: {=_xlfn._xlws.FILTER( 'Macro Dados - Todos'!$A$2:$L$20000, ('Macro Dados - Todos'!$A$2:$A$20000=Lacunas!B2) * ('Macro Dados - Todos'!$C$2:$C$20000=Lacunas!C2) * ('Macro Dados - Todos'!$D$2:$D$20000=Lacunas!E2) )} -> Formosa do Oeste | C2: UVR 01 - Formosa do Oeste | D2: 01 | E2: 15/11/2024 | F2: 7 | G2: 0 | H2: 9598.75 | I2: 0 | J2: 0 | K2: 7363 | L2: 3620 | M2: 1371.25
A3: Gabriel | B3: {=_xlfn._xlws.FILTER( 'Macro Dados - Todos'!$A$2:$L$20000, ('Macro Dados - Todos'!$A$2:$A$20000=Lacunas!B3) * ('Macro Dados - Todos'!$C$2:$C$20000=Lacunas!C3) * ('Macro Dados - Todos'!$D$2:$D$20000=Lacunas!E3) )} -> Maripa | C3: UVR 01 - Maripa | D3: 01 | E3: 15/11/2024 | F3: 5 | G3: A Recima é uma empresa tercerizada contratada pelo Município e o pagamento é realizado pela empresa | H3: 24858.1 | I3: 29503.37 | J3: 0 | K3: 28540 | L3: 0 | M3: 2500
A4: Gabriel | B4: {=_xlfn._xlws.FILTER( 'Macro Dados - Todos'!$A$2:$L$20000, ('Macro Dados - Todos'!$A$2:$A$20000=Lacunas!B4) * ('Macro Dados - Todos'!$C$2:$C$20000=Lacunas!C4) * ('Macro Dados - Todos'!$D$2:$D$20000=Lacunas!E4) )} -> Mundo Novo | C4: UVR 01 - Mundo Novo | D4: 01 | E4: 15/11/2024 | F4: 15 | G4: 0 | H4: 35681.9 | I4: 0 | J4: 628.32 | K4: 51259.5 | L4: 5469 | M4: 2334.2
A5: Gabriel | B5: {=_xlfn._xlws.FILTER( 'Macro Dados - Todos'!$A$2:$L$20000, ('Macro Dados - Todos'!$A$2:$A$20000=Lacunas!B5) * ('Macro Dados - Todos'!$C$2:$C$20000=Lacunas!C5) * ('Macro Dados - Todos'!$D$2:$D$20000=Lacunas!E5) )} -> Assis Chateaubriand | C5: UVR 01 - Assis Chateaubriand | D5: 01 | E5: 15/12/2024 | F5: 34 | G5: 01/12 à 23/12/2024 | H5: 69057.61 | I5: 30460.27 | J5: 8744 | K5: 87028.86 | L5: 15606 | M5: 3185
A6: Valquiria | B6: {=_xlfn._xlws.FILTER( 'Macro Dados - Todos'!$A$2:$L$20000, ('Macro Dados - Todos'!$A$2:$A$20000=Lacunas!B6) * ('Macro Dados - Todos'!$C$2:$C$20000=Lacunas!C6) * ('Macro Dados - Todos'!$D$2:$D$20000=Lacunas!E6) )} -> Cafelândia | C6: UVR 01 - Cafelândia | D6: 01 | E6: 15/12/2024 | F6: 54 | G6: valor da diaria mês de Dezembro R$113,71 | H6: 64350.62 | I6: 20918.32 | J6: 16068.48 | K6: 70264 | L6: 18290 | M6: 2103.63
A7: Valquiria | B7: {=_xlfn._xlws.FILTER( 'Macro Dados - Todos'!$A$2:$L$20000, ('Macro Dados - Todos'!$A$2:$A$20000=Lacunas!B7) * ('Macro Dados - Todos'!$C$2:$C$20000=Lacunas!C7) * ('Macro Dados - Todos'!$D$2:$D$20000=Lacunas!E7) )} -> Formosa do Oeste | C7: UVR 01 - Formosa do Oeste | D7: 01 | E7: 15/12/2024 | F7: 7 | G7: 0 | H7: 11863.9 | I7: 0 | J7: 0 | K7: 9235 | L7: 4030 | M7: 1694.84
A8: Larissa | B8: {=_xlfn._xlws.FILTER( 'Macro Dados - Todos'!$A$2:$L$20000, ('Macro Dados - Todos'!$A$2:$A$20000=Lacunas!B8) * ('Macro Dados - Todos'!$C$2:$C$20000=Lacunas!C8) * ('Macro Dados - Todos'!$D$2:$D$20000=Lacunas!E8) )} -> Foz do Iguaçu | C8: UVR 06 - Foz do Iguaçu | D8: 06 | E8: 15/12/2024 | F8: 19 | G8: 0 | H8: 24687.4 | I8: 44852.27 | J8: 20769.16 | K8: 20980 | L8: 4210 | M8: 1596.64
A9: Valquiria | B9: {=_xlfn._xlws.FILTER( 'Macro Dados - Todos'!$A$2:$L$20000, ('Macro Dados - Todos'!$A$2:$A$20000=Lacunas!B9) * ('Macro Dados - Todos'!$C$2:$C$20000=Lacunas!C9) * ('Macro Dados - Todos'!$D$2:$D$20000=Lacunas!E9) )} -> Jesuítas | C9: UVR 01 - Jesuítas | D9: 01 | E9: 15/12/2024 | F9: 10 | G9: 0 | H9: 32954.2 | I9: 0 | J9: 0 | K9: 30594 | L9: 0 | M9: 3295.42
A10: Luana | B10: {=_xlfn._xlws.FILTER( 'Macro Dados - Todos'!$A$2:$L$20000, ('Macro Dados - Todos'!$A$2:$A$20000=Lacunas!B10) * ('Macro Dados - Todos'!$C$2:$C$20000=Lacunas!C10) * ('Macro Dados - Todos'!$D$2:$D$20000=Lacunas!E10) )} -> Marechal Candido Rondon | C10: UVR 01 - Marechal Candido Rondon | D10: 01 | E10: 15/12/2024 | F10: 30 | G10: 0 | H10: 81830.64 | I10: 76402.32 | J10: 0 | K10: 150054.1 | L10: 29740 | M10: 2900
A11: Luana | B11: {=_xlfn._xlws.FILTER( 'Macro Dados - Todos'!$A$2:$L$20000, ('Macro Dados - Todos'!$A$2:$A$20000=Lacunas!B11) * ('Macro Dados - Todos'!$C$2:$C$20000=Lacunas!C11) * ('Macro Dados - Todos'!$D$2:$D$20000=Lacunas!E11) )} -> Marechal Candido Rondon | C11: UVR 02 - Marechal Candido Rondon | D11: 02 | E11: 15/12/2024 | F11: 29 | G11: 0 | H11: 139018.76 | I11: 76402.67 | J11: 0 | K11: 154296.2 | L11: 25980 | M11: 3000
A12: Gabriel | B12: {=_xlfn._xlws.FILTER( 'Macro Dados - Todos'!$A$2:$L$20000, ('Macro Dados - Todos'!$A$2:$A$20000=Lacunas!B12) * ('Macro Dados - Todos'!$C$2:$C$20000=Lacunas!C12) * ('Macro Dados - Todos'!$D$2:$D$20000=Lacunas!E12) )} -> Maripa | C12: UVR 01 - Maripa | D12: 01 | E12: 15/12/2024 | F12: 5 | G12: A Recima é uma empresa tercerizada contratada pelo Município e o pagamento é realizado pela empresa | H12: 22822 | I12: 29503.37 | J12: 0 | K12: 20398 | L12: 0 | M12: 2500
A13: Gabriel | B13: {=_xlfn._xlws.FILTER( 'Macro Dados - Todos'!$A$2:$L$20000, ('Macro Dados - Todos'!$A$2:$A$20000=Lacunas!B13) * ('Macro Dados - Todos'!$C$2:$C$20000=Lacunas!C13) * ('Macro Dados - Todos'!$D$2:$D$20000=Lacunas!E13) )} -> Palotina | C13: UVR 01 - Palotina | D13: 01 | E13: 15/12/2024 | F13: 20 | G13: O total de Associados que trabalharam todos os dias( não tiveram faltas) foram 3 três) | H13: 65586.5 | I13: 0 | J13: 18985.51 | K13: 102194 | L13: 48200 | M13: 6642.2
A14: Gabriel | B14: {=_xlfn._xlws.FILTER( 'Macro Dados - Todos'!$A$2:$L$20000, ('Macro Dados - Todos'!$A$2:$A$20000=Lacunas!B14) * ('Macro Dados - Todos'!$C$2:$C$20000=Lacunas!C14) * ('Macro Dados - Todos'!$D$2:$D$20000=Lacunas!E14) )} -> Assis Chateaubriand | C14: UVR 01 - Assis Chateaubriand | D14: 01 | E14: 15/1/2025 | F14: 35 | G14: 0 | H14: 60635.57 | I14: 20852.5 | J14: 6862.97 | K14: 59542 | L14: 26447 | M14: 2800
A15: Gabriel | B15: {=_xlfn._xlws.FILTER( 'Macro Dados - Todos'!$A$2:$L$20000, ('Macro Dados - Todos'!$A$2:$A$20000=Lacunas!B15) * ('Macro Dados - Todos'!$C$2:$C$20000=Lacunas!C15) * ('Macro Dados - Todos'!$D$2:$D$20000=Lacunas!E15) )} -> Brasilândia do Sul | C15: UVR 01 - Brasilândia do Sul | D15: 01 | E15: 15/1/2025 | F15: 5 | G15: 0 | H15: 7861.9 | I15: 7700 | J15: 0 | K15: 15260 | L15: 1815 | M15: 2957.84
A16: Valquiria | B16: {=_xlfn._xlws.FILTER( 'Macro Dados - Todos'!$A$2:$L$20000, ('Macro Dados - Todos'!$A$2:$A$20000=Lacunas!B16) * ('Macro Dados - Todos'!$C$2:$C$20000=Lacunas!C16) * ('Macro Dados - Todos'!$D$2:$D$20000=Lacunas!E16) )} -> Cafelândia | C16: UVR 01 - Cafelândia | D16: 01 | E16: 15/1/2025 | F16: 48 | G16: Valor da diaria dos associados foi de R$122,90 | H16: 64957.32 | I16: 77184.72 | J16: 18645.48 | K16: 74791 | L16: 27340 | M16: 2235.03
A17: Larissa | B17: {=_xlfn._xlws.FILTER( 'Macro Dados - Todos'!$A$2:$L$20000, ('Macro Dados - Todos'!$A$2:$A$20000=Lacunas!B17) * ('Macro Dados - Todos'!$C$2:$C$20000=Lacunas!C17) * ('Macro Dados - Todos'!$D$2:$D$20000=Lacunas!E17) )} -> Foz do Iguaçu | C17: UVR 06 - Foz do Iguaçu | D17: 06 | E17: 15/1/2025 | F17: 19 | G17: 1943,48 | H17: 50035 | I17: 40307.67 | J17: 18148.15 | K17: 54742 | L17: 8450 | M17: 1943.48
A18: Valquiria | B18: {=_xlfn._xlws.FILTER( 'Macro Dados - Todos'!$A$2:$L$20000, ('Macro Dados - Todos'!$A$2:$A$20000=Lacunas!B18) * ('Macro Dados - Todos'!$C$2:$C$20000=Lacunas!C18) * ('Macro Dados - Todos'!$D$2:$D$20000=Lacunas!E18) )} -> Jesuítas | C18: UVR 01 - Jesuítas | D18: 01 | E18: 15/1/2025 | F18: 10 | G18: 0 | H18: 35453.7 | I18: 0 | J18: 0 | K18: 36695 | L18: 0 | M18: 3545.37
A19: Luana | B19: {=_xlfn._xlws.FILTER( 'Macro Dados - Todos'!$A$2:$L$20000, ('Macro Dados - Todos'!$A$2:$A$20000=Lacunas!B19) * ('Macro Dados - Todos'!$C$2:$C$20000=Lacunas!C19) * ('Macro Dados - Todos'!$D$2:$D$20000=Lacunas!E19) )} -> Marechal Candido Rondon | C19: UVR 01 - Marechal Candido Rondon | D19: 01 | E19: 15/1/2025 | F19: 30 | G19: 0 | H19: 115584.26 | I19: 76402.32 | J19: 0 | K19: 149335 | L19: 75790 | M19: 2900
A20: Luana | B20: {=_xlfn._xlws.FILTER( 'Macro Dados - Todos'!$A$2:$L$20000, ('Macro Dados - Todos'!$A$2:$A$20000=Lacunas!B20) * ('Macro Dados - Todos'!$C$2:$C$20000=Lacunas!C20) * ('Macro Dados - Todos'!$D$2:$D$20000=Lacunas!E20) )} -> Marechal Candido Rondon | C20: UVR 02 - Marechal Candido Rondon | D20: 02 | E20: 15/1/2025 | F20: 29 | G20: 0 | H20: 141072.9 | I20: 76402.67 | J20: 0 | K20: 150768 | L20: 45450 | M20: 3000
A21: Gabriel | B21: {=_xlfn._xlws.FILTER( 'Macro Dados - Todos'!$A$2:$L$20000, ('Macro Dados - Todos'!$A$2:$A$20000=Lacunas!B21) * ('Macro Dados - Todos'!$C$2:$C$20000=Lacunas!C21) * ('Macro Dados - Todos'!$D$2:$D$20000=Lacunas!E21) )} -> Palotina | C21: UVR 01 - Palotina | D21: 01 | E21: 15/1/2025 | F21: 20 | G21: O total de Associados que trabalharam todos os dias( não tiveram faltas) foram 2 (dois) | H21: 65797.05 | I21: 0 | J21: 13146.12 | K21: 101551 | L21: 46340 | M21: 3776.6
A22: Gabriel | B22: Palotina | C22: UVR 01 - Palotina | D22: 01 | E22: 15/1/2025 | F22: 22 | G22: O total de Associados que trabalharam todos os dias( não tiveram faltas) foram 03 (três) | H22: 74420.42 | I22: 0 | J22: 0 | K22: 86706 | L22: 48560 | M22: 4181.9
A23: Bianca | B23: {=_xlfn._xlws.FILTER( 'Macro Dados - Todos'!$A$2:$L$20000, ('Macro Dados - Todos'!$A$2:$A$20000=Lacunas!B23) * ('Macro Dados - Todos'!$C$2:$C$20000=Lacunas!C23) * ('Macro Dados - Todos'!$D$2:$D$20000=Lacunas!E23) )} -> Tres Barras do Parana | C23: UVR 01 - Tres Barras do Parana | D23: 01 | E23: 15/1/2025 | F23: 12 | G23: 0 | H23: 13698.85 | I23: 0 | J23: 0 | K23: 24207 | L23: 0 | M23: 1325

Sheet Micro Dados - Todos
A1: UVR Município + Número | B1: UVR Número | C1: Município | D1: Data de referência | E1: Tipo do registro | F1: Subtipo do registro | G1: Material | H1: Qual outro material? | I1: Quantidade | J1: Valor Absoluto (R$) | K1: Preço Médio | L1: Subtipo do Registro - Outro | M1: Data de referência
A2: UVR 01 - Tres Barras do Parana | B2: 01 | C2: Tres Barras do Parana | D2: =LEFT(M2,10) -> 12/15/2024 | E2: Receita da venda de recicláveis | F2: Metal | G2: Alumínio Latinha | I2: 87.5 | J2: 437.5 | K2: 5 | M2: 12/15/2024, 12:00 PM
A3: UVR 01 - Tres Barras do Parana | B3: 01 | C3: Tres Barras do Parana | D3: =LEFT(M3,10) -> 12/15/2024 | E3: Receita da venda de recicláveis | F3: Metal | G3: Inox | I3: 12.9 | J3: 32.25 | K3: 2.5 | M3: 12/15/2024, 12:00 PM
A4: UVR 01 - Tres Barras do Parana | B4: 01 | C4: Tres Barras do Parana | D4: =LEFT(M4,10) -> 12/15/2024 | E4: Receita da venda de recicláveis | F4: Metal | G4: Alumínio Bloco | I4: 12.4 | J4: 50.4 | K4: 4.06 | M4: 12/15/2024, 12:00 PM
A5: UVR 01 - Tres Barras do Parana | B5: 01 | C5: Tres Barras do Parana | D5: =LEFT(M5,10) -> 12/15/2024 | E5: Receita da venda de recicláveis | F5: Metal | G5: Alumínio Panela | I5: 28 | J5: 196 | K5: 7 | M5: 12/15/2024, 12:00 PM
A6: UVR 01 - Tres Barras do Parana | B6: 01 | C6: Tres Barras do Parana | D6: =LEFT(M6,10) -> 12/15/2024 | E6: Receita da venda de recicláveis | F6: Elétrico ou Eletrônicos | G6: Bateria | I6: 2 | J6: 5 | K6: 2.5 | M6: 12/15/2024, 12:00 PM
A7: UVR 01 - Tres Barras do Parana | B7: 01 | C7: Tres Barras do Parana | D7: =LEFT(M7,10) -> 12/15/2024 | E7: Receita da venda de recicláveis | F7: Elétrico ou Eletrônicos | G7: Informática | I7: 3 | J7: 60 | K7: 20 | M7: 12/15/2024, 12:00 PM
A8: UVR 01 - Tres Barras do Parana | B8: 01 | C8: Tres Barras do Parana | D8: =LEFT(M8,10) -> 12/15/2024 | E8: Receita da venda de recicláveis | F8: Elétrico ou Eletrônicos | G8: Informática | I8: 4 | J8: 80 | K8: 20 | M8: 12/15/2024, 12:00 PM
A9: UVR 01 - Tres Barras do Parana | B9: 01 | C9: Tres Barras do Parana | D9: =LEFT(M9,10) -> 12/15/2024 | E9: Receita da venda de recicláveis | F9: Elétrico ou Eletrônicos | G9: placa | I9: 15 | J9: 82.5 | K9: 5.5 | M9: 12/15/2024, 12:00 PM
A10: UVR 01 - Tres Barras do Parana | B10: 01 | C10: Tres Barras do Parana | D10: =LEFT(M10,10) -> 12/15/2024 | E10: Receita da venda de recicláveis | F10: Elétrico ou Eletrônicos | G10: Memória | I10: 2 | J10: 9.6 | K10: 4.8 | M10: 12/15/2024, 12:00 PM
A11: UVR 01 - Tres Barras do Parana | B11: 01 | C11: Tres Barras do Parana | D11: =LEFT(M11,10) -> 12/15/2024 | E11: Receita da venda de recicláveis | F11: Elétrico ou Eletrônicos | G11: Informática | I11: 467 | J11: 280.2 | K11: 0.6 | M11: 12/15/2024, 12:00 PM
A12: UVR 01 - Tres Barras do Parana | B12: 01 | C12: Tres Barras do Parana | D12: =LEFT(M12,10) -> 12/15/2024 | E12: Receita da venda de recicláveis | F12: Elétrico ou Eletrônicos | G12: Sucata Eletrônica | I12: 200 | J12: 180 | K12: 0.9 | M12: 12/15/2024, 12:00 PM
A13: UVR 01 - Tres Barras do Parana | B13: 01 | C13: Tres Barras do Parana | D13: =LEFT(M13,10) -> 12/15/2024 | E13: Receita da venda de recicláveis | F13: Elétrico ou Eletrônicos | G13: Sucata Eletrônica | I13: 136 | J13: 68 | K13: 0.5 | M13: 12/15/2024, 12:00 PM
... A27: UVR 01 - Tres Barras do Parana | B27: 01 | C27: Tres Barras do Parana | D27: =LEFT(M27,10) -> 12/15/2024 | E27: Receita da venda de recicláveis | F27: Papéis | G27: Papelão | I27: 8800 | J27: 3520 | K27: 0.4 | M27: 12/15/2024, 12:00 PM
A28: UVR 01 - Tres Barras do Parana | B28: 01 | C28: Tres Barras do Parana | D28: =LEFT(M28,10) -> 12/15/2024 | E28: Receita da prestação de serviços | F28: Serviço de Logística Reversa | I28: 0 | J28: 823 | M28: 12/15/2024, 12:00 PM
A29: UVR 01 - Tres Barras do Parana | B29: 01 | C29: Tres Barras do Parana | D29: =LEFT(M29,10) -> 12/15/2024 | E29: Despesa | F29: Impostos/taxas | I29: 0 | J29: 1200 | M29: 12/15/2024, 12:00 PM
A30: UVR 01 - Tres Barras do Parana | B30: 01 | C30: Tres Barras do Parana | D30: =LEFT(M30,10) -> 12/15/2024 | E30: Rejeito | F30: Rejeito | I30: 0 | M30: 12/15/2024, 12:00 PM
A31: UVR 01 - Tres Barras do Parana | B31: 01 | C31: Tres Barras do Parana | D31: =LEFT(M31,10) -> 12/15/2024 | E31: Receita da venda de recicláveis | F31: Metal | G31: Chaparia | I31: 23 | J31: 18 | K31: 0.78 | M31: 12/15/2024, 12:00 PM
A32: UVR 01 - Matelândia | B32: 01 | C32: Matelândia | D32: =LEFT(M32,10) -> 12/15/2024 | E32: Receita da venda de recicláveis | F32: Metal | G32: Sucatas | I32: 1086.5 | J32: 6667.3 | K32: 6.14 | M32: 12/15/2024, 12:00 PM
A33: UVR 01 - Matelândia | B33: 01 | C33: Matelândia | D33: =LEFT(M33,10) -> 12/15/2024 | E33: Receita da venda de recicláveis | F33: Metal | G33: Sucatas | I33: 4180 | J33: 1881 | K33: 0.45 | M33: 12/15/2024, 12:00 PM
A34: UVR 01 - Matelândia | B34: 01 | C34: Matelândia | D34: =LEFT(M34,10) -> 12/15/2024 | E34: Receita da venda de recicláveis | F34: Papéis | G34: Papelão | I34: 8130 | J34: 3252 | K34: 0.4 | M34: 12/15/2024, 12:00 PM
A35: UVR 01 - Matelândia | B35: 01 | C35: Matelândia | D35: =LEFT(M35,10) -> 12/15/2024 | E35: Receita da venda de recicláveis | F35: Papéis | G35: Papel Branco | I35: 1210 | J35: 726 | K35: 0.6 | M35: 12/15/2024, 12:00 PM
A36: UVR 01 - Matelândia | B36: 01 | C36: Matelândia | D36: =LEFT(M36,10) -> 12/15/2024 | E36: Receita da venda de recicláveis | F36: Papéis | G36: Papel Cimento | I36: 860 | J36: 129 | K36: 0.15 | M36: 12/15/2024, 12:00 PM
A37: UVR 01 - Matelândia | B37: 01 | C37: Matelândia | D37: =LEFT(M37,10) -> 12/15/2024 | E37: Receita da venda de recicláveis | F37: Papéis | G37: Papel Misto | I37: 6280 | J37: 942 | K37: 0.15 | M37: 12/15/2024, 12:00 PM
A38: UVR 01 - Matelândia | B38: 01 | C38: Matelândia | D38: =LEFT(M38,10) -> 12/15/2024 | E38: Receita da venda de recicláveis | F38: Papéis | G38: Papelão | I38: 9020 | J38: 3608 | K38: 0.4 | M38: 12/15/2024, 12:00 PM
A39: UVR 01 - Matelândia | B39: 01 | C39: Matelândia | D39: =LEFT(M39,10) -> 12/15/2024 | E39: Receita da venda de recicláveis | F39: Papéis | G39: Papel Branco | I39: 1120 | J39: 672 | K39: 0.6 | M39: 12/15/2024, 12:00 PM
A40: UVR 01 - Matelândia | B40: 01 | C40: Matelândia | D40: =LEFT(M40,10) -> 12/15/2024 | E40: Receita da venda de recicláveis | F40: Papéis | G40: Papel Cimento | I40: 320 | J40: 48 | K40: 0.15 | M40: 12/15/2024, 12:00 PM
A41: UVR 01 - Matelândia | B41: 01 | C41: Matelândia | D41: =LEFT(M41,10) -> 12/15/2024 | E41: Receita da venda de recicláveis | F41: Papéis | G41: Papel Misto | I41: 7150 | J41: 1072.5 | K41: 0.15 | M41: 12/15/2024, 12:00 PM
A42: UVR 01 - Matelândia | B42: 01 | C42: Matelândia | D42: =LEFT(M42,10) -> 12/15/2024 | E42: Receita da venda de recicláveis | F42: Plástico | G42: PS Expansível (Isopor) | I42: 250 | J42: 50 | K42: 0.2 | M42: 12/15/2024, 12:00 PM
... A50: UVR 01 - Matelândia | B50: 01 | C50: Matelândia | D50: =LEFT(M50,10) -> 12/15/2024 | E50: Receita da venda de recicláveis | F50: Plástico | G50: PEAD (Embalagens de produtos de limpeza) | I50: 544 | J50: 1196.8 | K50: 2.2 | M50: 12/15/2024, 12:00 PM
A51: UVR 01 - Matelândia | B51: 01 | C51: Matelândia | D51: =LEFT(M51,10) -> 12/15/2024 | E51: Receita da venda de recicláveis | F51: Plástico | G51: Outro tipo de plástico | H51: Fita arquemento ( PET ) | I51: 103 | J51: 51.5 | K51: 0.5 | M51: 12/15/2024, 12:00 PM
A52: UVR 01 - Matelândia | B52: 01 | C52: Matelândia | D52: =LEFT(M52,10) -> 12/15/2024 | E52: Receita da venda de recicláveis | F52: Plástico | G52: PP Rígido (Balde, bacia, potes de sorvetes, margarina, entre outros) | I52: 112 | J52: 156.8 | K52: 1.4 | M52: 12/15/2024, 12:00 PM
A53: UVR 01 - Matelândia | B53: 01 | C53: Matelândia | D53: =LEFT(M53,10) -> 12/15/2024 | E53: Receita da venda de recicláveis | F53: Plástico | G53: PS (Copos descartáveis) | I53: 317 | J53: 253.6 | K53: 0.8 | M53: 12/15/2024, 12:00 PM
A54: UVR 01 - Matelândia | B54: 01 | C54: Matelândia | D54: =LEFT(M54,10) -> 12/15/2024 | E54: Receita da venda de recicláveis | F54: Plástico | G54: PEBD Filme (Sacolinha, Sacos de lixo, Lona Preta) | I54: 504 | J54: 252 | K54: 0.5 | M54: 12/15/2024, 12:00 PM
A55: UVR 01 - Matelândia | B55: 01 | C55: Matelândia | D55: =LEFT(M55,10) -> 12/15/2024 | E55: Receita da venda de recicláveis | F55: Plástico | G55: PEBD Filme (Sacolinha, Sacos de lixo, Lona Preta) | I55: 1502 | J55: 1051.4 | K55: 0.7 | M55: 12/15/2024, 12:00 PM
A56: UVR 01 - Matelândia | B56: 01 | C56: Matelândia | D56: =LEFT(M56,10) -> 12/15/2024 | E56: Receita da venda de recicláveis | F56: Plástico | G56: PEAD Filme (Cristal) | I56: 1038 | J56: 1349.4 | K56: 1.3 | M56: 12/15/2024, 12:00 PM
A57: UVR 01 - Matelândia | B57: 01 | C57: Matelândia | D57: =LEFT(M57,10) -> 12/15/2024 | E57: Receita da venda de recicláveis | F57: Plástico | G57: PS Rígido (Forro de geladeiras) | I57: 113 | J57: 22.6 | K57: 0.2 | M57: 12/15/2024, 12:00 PM
A58: UVR 01 - Matelândia | B58: 01 | C58: Matelândia | D58: =LEFT(M58,10) -> 12/15/2024 | E58: Receita da venda de recicláveis | F58: Plástico | G58: PP Ráfia (Sacaria) | I58: 352 | J58: 176 | K58: 0.5 | M58: 12/15/2024, 12:00 PM
A59: UVR 01 - Matelândia | B59: 01 | C59: Matelândia | D59: =LEFT(M59,10) -> 12/15/2024 | E59: Receita da venda de recicláveis | F59: Plástico | G59: PET Cristal (Embalagens de refrigerante transparente) | I59: 1669 | J59: 3504.9 | K59: 2.1 | M59: 12/15/2024, 12:00 PM
A60: UVR 01 - Matelândia | B60: 01 | C60: Matelândia | D60: =LEFT(M60,10) -> 12/15/2024 | E60: Receita da venda de recicláveis | F60: Plástico | G60: Outro tipo de plástico | H60: Tampinha de Garrafas ( PP ) 2 Bags | I60: 243 | J60: 243 | K60: 1 | M60: 12/15/2024, 12:00 PM
A61: UVR 01 - Matelândia | B61: 01 | C61: Matelândia | D61: =LEFT(M61,10) -> 12/15/2024 | E61: Receita da venda de recicláveis | F61: Plástico | G61: PEAD (Embalagens de produtos de limpeza) | I61: 254 | J61: 558.8 | K61: 2.2 | M61: 12/15/2024, 12:00 PM
A62: UVR 01 - Matelândia | B62: 01 | C62: Matelândia | D62: =LEFT(M62,10) -> 12/15/2024 | E62: Receita da venda de recicláveis | F62: Plástico | G62: PEAD (Embalagens de produtos de limpeza) | I62: 64 | J62: 140.8 | K62: 2.2 | M62: 12/15/2024, 12:00 PM
A63: UVR 01 - Matelândia | B63: 01 | C63: Matelândia | D63: =LEFT(M63,10) -> 12/15/2024 | E63: Receita da venda de recicláveis | F63: Plástico | G63: PET Verde (Embalagens de refrigerante verde) | I63: 230 | J63: 437 | K63: 1.9 | M63: 12/15/2024, 12:00 PM
A64: UVR 01 - Matelândia | B64: 01 | C64: Matelândia | D64: =LEFT(M64,10) -> 12/15/2024 | E64: Receita da venda de recicláveis | F64: Plástico | G64: PS Expansível (Isopor) | I64: 260 | J64: 52 | K64: 0.2 | M64: 12/15/2024, 12:00 PM
A65: UVR 01 - Matelândia | B65: 01 | C65: Matelândia | D65: =LEFT(M65,10) -> 12/15/2024 | E65: Receita da venda de recicláveis | F65: Plástico | G65: PP Rígido (Balde, bacia, potes de sorvetes, margarina, entre outros) | I65: 854 | J65: 854 | K65: 1 | M65: 12/15/2024, 12:00 PM
A66: UVR 01 - Matelândia | B66: 01 | C66: Matelândia | D66: =LEFT(M66,10) -> 12/15/2024 | E66: Receita da venda de recicláveis | F66: Plástico | G66: PEAD (Embalagens de produtos de limpeza) | I66: 680 | J66: 1496 | K66: 2.2 | M66: 12/15/2024, 12:00 PM
A67: UVR 01 - Matelândia | B67: 01 | C67: Matelândia | D67: =LEFT(M67,10) -> 12/15/2024 | E67: Receita da venda de recicláveis | F67: Plástico | G67: PEAD (Embalagens de produtos de limpeza) | I67: 310 | J67: 682 | K67: 2.2 | M67: 12/15/2024, 12:00 PM
A68: UVR 01 - Matelândia | B68: 01 | C68: Matelândia | D68: =LEFT(M68,10) -> 12/15/2024 | E68: Receita da venda de recicláveis | F68: Plástico | G68: PEAD Injeção (Caixaria) | I68: 113 | J68: 452 | K68: 4 | M68: 12/15/2024, 12:00 PM
A69: UVR 01 - Matelândia | B69: 01 | C69: Matelândia | D69: =LEFT(M69,10) -> 12/15/2024 | E69: Receita da venda de recicláveis | F69: Plástico | G69: PEAD Filme (Cristal) | I69: 1580 | J69: 2054 | K69: 1.3 | M69: 12/15/2024, 12:00 PM
A70: UVR 01 - Matelândia | B70: 01 | C70: Matelândia | D70: =LEFT(M70,10) -> 12/15/2024 | E70: Receita da venda de recicláveis | F70: Plástico | G70: PP Rígido (Balde, bacia, potes de sorvetes, margarina, entre outros) | I70: 486 | J70: 680.4 | K70: 1.4 | M70: 12/15/2024, 12:00 PM
A71: UVR 01 - Matelândia | B71: 01 | C71: Matelândia | D71: =LEFT(M71,10) -> 12/15/2024 | E71: Receita da venda de recicláveis | F71: Plástico | G71: PVC (Cano, Forro, Tubulação de cano) | I71: 268 | J71: 134 | K71: 0.5 | M71: 12/15/2024, 12:00 PM
A72: UVR 01 - Matelândia | B72: 01 | C72: Matelândia | D72: =LEFT(M72,10) -> 12/15/2024 | E72: Receita da venda de recicláveis | F72: Plástico | G72: PET Óleo (Embalagens de óleo de cozinha) | I72: 78 | J72: 70.2 | K72: 0.9 | M72: 12/15/2024, 12:00 PM
... A76: UVR 01 - Matelândia | B76: 01 | C76: Matelândia | D76: =LEFT(M76,10) -> 12/15/2024 | E76: Receita da venda de recicláveis | F76: Plástico | G76: PS (Copos descartáveis) | I76: 102 | J76: 81.6 | K76: 0.8 | M76: 12/15/2024, 12:00 PM
A77: UVR 01 - Matelândia | B77: 01 | C77: Matelândia | D77: =LEFT(M77,10) -> 12/15/2024 | E77: Receita da prestação de serviços | F77: Contratos | G77: null | I77: 0 | J77: 14467.5 | M77: 12/15/2024, 12:00 PM
A78: UVR 01 - Matelândia | B78: 01 | C78: Matelândia | D78: =LEFT(M78,10) -> 12/15/2024 | E78: Despesa | F78: Impostos/taxas | G78: null | I78: 0 | J78: 2025.45 | M78: 12/15/2024, 12:00 PM
A79: UVR 01 - Matelândia | B79: 01 | C79: Matelândia | D79: =LEFT(M79,10) -> 12/15/2024 | E79: Despesa | F79: Combustível | G79: null | I79: 0 | J79: 180 | M79: 12/15/2024, 12:00 PM
A80: UVR 01 - Matelândia | B80: 01 | C80: Matelândia | D80: =LEFT(M80,10) -> 12/15/2024 | E80: Despesa | F80: Conserto e manutenção de equipamentos/veículo | G80: null | I80: 0 | J80: 130 | M80: 12/15/2024, 12:00 PM
A81: UVR 01 - Matelândia | B81: 01 | C81: Matelândia | D81: =LEFT(M81,10) -> 12/15/2024 | E81: Rejeito | F81: Rejeito | G81: null | I81: 20910 | M81: 12/15/2024, 12:00 PM
A82: UVR 01 - Diamante d'Oeste | B82: 01 | C82: Diamante d'Oeste | D82: =LEFT(M82,10) -> 12/15/2024 | E82: Receita da venda de recicláveis | F82: Papéis | G82: Papel Branco | I82: 246.6 | J82: 147.96 | K82: 0.6 | M82: 12/15/2024, 12:00 PM
A83: UVR 01 - Diamante d'Oeste | B83: 01 | C83: Diamante d'Oeste | D83: =LEFT(M83,10) -> 12/15/2024 | E83: Receita da venda de recicláveis | F83: Papéis | G83: Papel Misto | I83: 2184 | J83: 262.08 | K83: 0.12 | M83: 12/15/2024, 12:00 PM
A84: UVR 01 - Diamante d'Oeste | B84: 01 | C84: Diamante d'Oeste | D84: =LEFT(M84,10) -> 12/15/2024 | E84: Receita da venda de recicláveis | F84: Papéis | G84: Papelão | I84: 3052.6 | J84: 1312.61 | K84: 0.43 | M84: 12/15/2024, 12:00 PM
A85: UVR 01 - Diamante d'Oeste | B85: 01 | C85: Diamante d'Oeste | D85: =LEFT(M85,10) -> 12/15/2024 | E85: Receita da venda de recicláveis | F85: Papéis | G85: Tetra Pack | I85: 264.8 | J85: 34.42 | K85: 0.13 | M85: 12/15/2024, 12:00 PM
A86: UVR 01 - Diamante d'Oeste | B86: 01 | C86: Diamante d'Oeste | D86: =LEFT(M86,10) -> 12/15/2024 | E86: Receita da venda de recicláveis | F86: Plástico | G86: PVC (Cano, Forro, Tubulação de cano) | I86: 55.2 | J86: 33.12 | K86: 0.6 | M86: 12/15/2024, 12:00 PM
A87: UVR 01 - Diamante d'Oeste | B87: 01 | C87: Diamante d'Oeste | D87: =LEFT(M87,10) -> 12/15/2024 | E87: Receita da venda de recicláveis | F87: Plástico | G87: PEAD (Embalagens de produtos de limpeza) | I87: 80.8 | J87: 177.76 | K87: 2.2 | M87: 12/15/2024, 12:00 PM
A88: UVR 01 - Diamante d'Oeste | B88: 01 | C88: Diamante d'Oeste | D88: =LEFT(M88,10) -> 12/15/2024 | E88: Receita da venda de recicláveis | F88: Plástico | G88: PEAD (Embalagens de produtos de limpeza) | I88: 184 | J88: 441.6 | K88: 2.4 | M88: 12/15/2024, 12:00 PM
A89: UVR 01 - Diamante d'Oeste | B89: 01 | C89: Diamante d'Oeste | D89: =LEFT(M89,10) -> 12/15/2024 | E89: Receita da venda de recicláveis | F89: Plástico | G89: PEBD Filme (Sacolinha, Sacos de lixo, Lona Preta) | I89: 591.2 | J89: 354.72 | K89: 0.6 | M89: 12/15/2024, 12:00 PM
A90: UVR 01 - Diamante d'Oeste | B90: 01 | C90: Diamante d'Oeste | D90: =LEFT(M90,10) -> 12/15/2024 | E90: Receita da venda de recicláveis | F90: Plástico | G90: PEBD Filme (Sacolinha, Sacos de lixo, Lona Preta) | I90: 161 | J90: 96.6 | K90: 0.6 | M90: 12/15/2024, 12:00 PM
A91: UVR 01 - Diamante d'Oeste | B91: 01 | C91: Diamante d'Oeste | D91: =LEFT(M91,10) -> 12/15/2024 | E91: Receita da venda de recicláveis | F91: Plástico | G91: PEAD Filme (Cristal) | I91: 579.8 | J91: 869.7 | K91: 1.5 | M91: 12/15/2024, 12:00 PM
A92: UVR 01 - Diamante d'Oeste | B92: 01 | C92: Diamante d'Oeste | D92: =LEFT(M92,10) -> 12/15/2024 | E92: Receita da venda de recicláveis | F92: Plástico | G92: PET Cristal (Embalagens de refrigerante transparente) | I92: 358 | J92: 787.6 | K92: 2.2 | M92: 12/15/2024, 12:00 PM
A93: UVR 01 - Diamante d'Oeste | B93: 01 | C93: Diamante d'Oeste | D93: =LEFT(M93,10) -> 12/15/2024 | E93: Receita da venda de recicláveis | F93: Plástico | G93: PET Óleo (Embalagens de óleo de cozinha) | I93: 56.6 | J93: 39.62 | K93: 0.7 | M93: 12/15/2024, 12:00 PM
... A100: UVR 01 - Diamante d'Oeste | B100: 01 | C100: Diamante d'Oeste | D100: =LEFT(M100,10) -> 12/15/2024 | E100: Receita da venda de recicláveis | F100: Vidro | G100: Caco | I100: 2724 | J100: 408.6 | K100: 0.15 | M100: 12/15/2024, 12:00 PM
A101: UVR 01 - Diamante d'Oeste | B101: 01 | C101: Diamante d'Oeste | D101: =LEFT(M101,10) -> 12/15/2024 | E101: Receita da prestação de serviços | F101: Contratos | I101: 0 | J101: 9237.49 | M101: 12/15/2024, 12:00 PM
A102: UVR 01 - Diamante d'Oeste | B102: 01 | C102: Diamante d'Oeste | D102: =LEFT(M102,10) -> 12/15/2024 | E102: Despesa | F102: Fundo de caixa | I102: 0 | J102: 955.31 | M102: 12/15/2024, 12:00 PM
A103: UVR 01 - Diamante d'Oeste | B103: 01 | C103: Diamante d'Oeste | D103: =LEFT(M103,10) -> 12/15/2024 | E103: Despesa | F103: Impostos/taxas | I103: 0 | J103: 1306.8 | M103: 12/15/2024, 12:00 PM
A104: UVR 01 - Diamante d'Oeste | B104: 01 | C104: Diamante d'Oeste | D104: =LEFT(M104,10) -> 12/15/2024 | E104: Despesa | F104: Outra Despesa | I104: 0 | J104: 89.9 | L104: internet | M104: 12/15/2024, 12:00 PM
A105: UVR 01 - Diamante d'Oeste | B105: 01 | C105: Diamante d'Oeste | D105: =LEFT(M105,10) -> 12/15/2024 | E105: Despesa | F105: Outra Despesa | I105: 0 | J105: 71 | L105: sistema de nfe | M105: 12/15/2024, 12:00 PM
A106: UVR 01 - Diamante d'Oeste | B106: 01 | C106: Diamante d'Oeste | D106: =LEFT(M106,10) -> 12/15/2024 | E106: Despesa | F106: Impostos/taxas | I106: 0 | J106: 532.14 | M106: 12/15/2024, 12:00 PM
A107: UVR 01 - Diamante d'Oeste | B107: 01 | C107: Diamante d'Oeste | D107: =LEFT(M107,10) -> 12/15/2024 | E107: Despesa | F107: Outra Despesa | I107: 0 | J107: 650 | L107: valor fornecido para viagem de associados | M107: 12/15/2024, 12:00 PM
A108: UVR 01 - Ouro Verde do Oeste | B108: 01 | C108: Ouro Verde do Oeste | D108: =LEFT(M108,10) -> 12/15/2024 | E108: Rejeito | F108: Rejeito | G108: null | I108: 1300 | M108: 12/15/2024, 12:00 PM
A109: UVR 01 - Ouro Verde do Oeste | B109: 01 | C109: Ouro Verde do Oeste | D109: =LEFT(M109,10) -> 12/15/2024 | E109: Receita da venda de recicláveis | F109: Papéis | G109: Papelão | I109: 3511 | J109: 1404.52 | K109: 0.4 | M109: 12/15/2024, 12:00 PM
A110: UVR 01 - Ouro Verde do Oeste | B110: 01 | C110: Ouro Verde do Oeste | D110: =LEFT(M110,10) -> 12/15/2024 | E110: Receita da venda de recicláveis | F110: Papéis | G110: Papel Branco | I110: 295 | J110: 177 | K110: 0.6 | M110: 12/15/2024, 12:00 PM
A111: UVR 01 - Ouro Verde do Oeste | B111: 01 | C111: Ouro Verde do Oeste | D111: =LEFT(M111,10) -> 12/15/2024 | E111: Receita da venda de recicláveis | F111: Papéis | G111: Papel Misto | I111: 622.5 | J111: 68.48 | K111: 0.11 | M111: 12/15/2024, 12:00 PM
A112: UVR 01 - Ouro Verde do Oeste | B112: 01 | C112: Ouro Verde do Oeste | D112: =LEFT(M112,10) -> 12/15/2024 | E112: Receita da venda de recicláveis | F112: Papéis | G112: Tetra Pack | I112: 118 | J112: 12.98 | K112: 0.11 | M112: 12/15/2024, 12:00 PM
A113: UVR 01 - Ouro Verde do Oeste | B113: 01 | C113: Ouro Verde do Oeste | D113: =LEFT(M113,10) -> 12/15/2024 | E113: Receita da venda de recicláveis | F113: Plástico | G113: PEAD Filme (Cristal) | I113: 172 | J113: 249.4 | K113: 1.45 | M113: 12/15/2024, 12:00 PM
A114: UVR 01 - Ouro Verde do Oeste | B114: 01 | C114: Ouro Verde do Oeste | D114: =LEFT(M114,10) -> 12/15/2024 | E114: Receita da venda de recicláveis | F114: Plástico | G114: PET Cristal (Embalagens de refrigerante transparente) | I114: 218.5 | J114: 393.3 | K114: 1.8 | M114: 12/15/2024, 12:00 PM
A115: UVR 01 - Ouro Verde do Oeste | B115: 01 | C115: Ouro Verde do Oeste | D115: =LEFT(M115,10) -> 12/15/2024 | E115: Receita da venda de recicláveis | F115: Plástico | G115: PET Verde (Embalagens de refrigerante verde) | I115: 49.5 | J115: 89.1 | K115: 1.8 | M115: 12/15/2024, 12:00 PM
A116: UVR 01 - Ouro Verde do Oeste | B116: 01 | C116: Ouro Verde do Oeste | D116: =LEFT(M116,10) -> 12/15/2024 | E116: Receita da venda de recicláveis | F116: Plástico | G116: PET Colorido (Embalagens de PET colorido, PET bagunça) | I116: 79 | J116: 3.95 | K116: 0.05 | M116: 12/15/2024, 12:00 PM
A117: UVR 01 - Ouro Verde do Oeste | B117: 01 | C117: Ouro Verde do Oeste | D117: =LEFT(M117,10) -> 12/15/2024 | E117: Receita da venda de recicláveis | F117: Plástico | G117: PET Óleo (Embalagens de óleo de cozinha) | I117: 59.5 | J117: 35.7 | K117: 0.6 | M117: 12/15/2024, 12:00 PM
A118: UVR 01 - Ouro Verde do Oeste | B118: 01 | C118: Ouro Verde do Oeste | D118: =LEFT(M118,10) -> 12/15/2024 | E118: Receita da venda de recicláveis | F118: Plástico | G118: PEAD (Embalagens de produtos de limpeza) | I118: 70.5 | J118: 165.68 | K118: 2.35 | M118: 12/15/2024, 12:00 PM
A119: UVR 01 - Ouro Verde do Oeste | B119: 01 | C119: Ouro Verde do Oeste | D119: =LEFT(M119,10) -> 12/15/2024 | E119: Receita da venda de recicláveis | F119: Plástico | G119: PET Colorido (Embalagens de PET colorido, PET bagunça) | I119: 81.5 | J119: 69.28 | K119: 0.85 | M119: 12/15/2024, 12:00 PM
A120: UVR 01 - Ouro Verde do Oeste | B120: 01 | C120: Ouro Verde do Oeste | D120: =LEFT(M120,10) -> 12/15/2024 | E120: Receita da venda de recicláveis | F120: Plástico | G120: PP Rígido (Balde, bacia, potes de sorvetes, margarina, entre outros) | I120: 90.5 | J120: 135.75 | K120: 1.05 | M120: 12/15/2024, 12:00 PM
... A162: UVR 07 - Foz do Iguaçu | B162: 07 | C162: Foz do Iguaçu | D162: =LEFT(M162,10) -> 12/15/2024 | E162: Receita da venda de recicláveis | F162: Plástico | G162: PS Expansível (Isopor) | I162: 275 | J162: 165 | K162: 0.6 | M162: 12/15/2024, 12:00 PM
A163: UVR 07 - Foz do Iguaçu | B163: 07 | C163: Foz do Iguaçu | D163: =LEFT(M163,10) -> 12/15/2024 | E163: Despesa | F163: Funcionário/Apoio Técnico | I163: 0 | J163: 4293.07 | M163: 12/15/2024, 12:00 PM
A164: UVR 07 - Foz do Iguaçu | B164: 07 | C164: Foz do Iguaçu | D164: =LEFT(M164,10) -> 12/15/2024 | E164: Despesa | F164: Outra Despesa | I164: 0 | J164: 4785.23 | L164: motorista | M164: 12/15/2024, 12:00 PM
A165: UVR 07 - Foz do Iguaçu | B165: 07 | C165: Foz do Iguaçu | D165: =LEFT(M165,10) -> 12/15/2024 | E165: Despesa | F165: Outra Despesa | I165: 0 | J165: 765 | L165: Contabilidade | M165: 12/15/2024, 12:00 PM
A166: UVR 07 - Foz do Iguaçu | B166: 07 | C166: Foz do Iguaçu | D166: =LEFT(M166,10) -> 12/15/2024 | E166: Receita da prestação de serviços | F166: Contratos | I166: 0 | J166: 9223 | M166: 12/15/2024, 12:00 PM
A167: UVR 07 - Foz do Iguaçu | B167: 07 | C167: Foz do Iguaçu | D167: =LEFT(M167,10) -> 12/15/2024 | E167: Receita da prestação de serviços | F167: Contratos | I167: 0 | J167: 12849.87 | M167: 12/15/2024, 12:00 PM
A168: UVR 07 - Foz do Iguaçu | B168: 07 | C168: Foz do Iguaçu | D168: =LEFT(M168,10) -> 12/15/2024 | E168: Rejeito | F168: Rejeito | I168: 4752 | M168: 12/15/2024, 12:00 PM
A169: UVR 01 - Toledo | B169: 01 | C169: Toledo | D169: =LEFT(M169,10) -> 12/15/2024 | E169: Receita da venda de recicláveis | F169: Vidro | G169: Caco | I169: 32420 | J169: 1621 | K169: 0.05 | M169: 12/15/2024, 12:00 PM
A170: UVR 01 - Toledo | B170: 01 | C170: Toledo | D170: =LEFT(M170,10) -> 12/15/2024 | E170: Receita da venda de recicláveis | F170: Papéis | G170: Papel Misto | I170: 2833 | J170: 283.3 | K170: 0.1 | M170: 12/15/2024, 12:00 PM
...

Sheet Micro Dados - Filtrados
A1: Regional | B1: UVR Município + Número | C1: UVR Número | D1: Município | E1: Data de referência | F1: Tipo do registro | G1: Subtipo do registro | H1: Material | I1: Qual outro material? | J1: Quantidade | K1: Valor Absoluto (R$) | L1: Preço Médio | M1: Subtipo do Registro - Outro
A2: Valquiria | B2: {=_xlfn._xlws.FILTER( 'Micro Dados - Todos'!$A$2:$L$20000, ('Micro Dados - Todos'!$C$2:$C$20000=Lacunas!B2) * ('Micro Dados - Todos'!$B$2:$B$20000=Lacunas!C2) * ('Micro Dados - Todos'!$D$2:$D$20000=Lacunas!F2) )} -> UVR 01 - Formosa do Oeste | C2: 01 | D2: Formosa do Oeste | E2: 11/15/2024 | F2: Receita da venda de recicláveis | G2: Plástico | H2: PET Cristal (Embalagens de refrigerante transparente) | I2: 0 | J2: 830 | K2: 3486 | L2: 4.2 | M2: 0
A3: Valquiria | B3: UVR 01 - Formosa do Oeste | C3: 01 | D3: Formosa do Oeste | E3: 11/15/2024 | F3: Receita da venda de recicláveis | G3: Plástico | H3: PP Rígido (Balde, bacia, potes de sorvetes, margarina, entre outros) | I3: 0 | J3: 185 | K3: 259 | L3: 1.4 | M3: 0
A4: Valquiria | B4: UVR 01 - Formosa do Oeste | C4: 01 | D4: Formosa do Oeste | E4: 11/15/2024 | F4: Receita da venda de recicláveis | G4: Plástico | H4: PP Rígido (Balde, bacia, potes de sorvetes, margarina, entre outros) | I4: 0 | J4: 150 | K4: 270 | L4: 1.8 | M4: 0
A5: Valquiria | B5: UVR 01 - Formosa do Oeste | C5: 01 | D5: Formosa do Oeste | E5: 11/15/2024 | F5: Receita da venda de recicláveis | G5: Plástico | H5: PP Mineral (Copinho de água mineral) | I5: 0 | J5: 40 | K5: 40 | L5: 1 | M5: 0
A6: Valquiria | B6: UVR 01 - Formosa do Oeste | C6: 01 | D6: Formosa do Oeste | E6: 11/15/2024 | F6: Receita da venda de recicláveis | G6: Papéis | H6: Tetra Pack | I6: 0 | J6: 250 | K6: 62.5 | L6: 0.25 | M6: 0
A7: Valquiria | B7: UVR 01 - Formosa do Oeste | C7: 01 | D7: Formosa do Oeste | E7: 11/15/2024 | F7: Receita da venda de recicláveis | G7: Plástico | H7: PEBD Filme (Sacolinha, Sacos de lixo, Lona Preta) | I7: 0 | J7: 280 | K7: 196 | L7: 0.7 | M7: 0
A8: Valquiria | B8: UVR 01 - Formosa do Oeste | C8: 01 | D8: Formosa do Oeste | E8: 11/15/2024 | F8: Receita da venda de recicláveis | G8: Plástico | H8: PP Ráfia (Sacaria) | I8: 0 | J8: 110 | K8: 38.5 | L8: 0.35 | M8: 0
A9: Valquiria | B9: UVR 01 - Formosa do Oeste | C9: 01 | D9: Formosa do Oeste | E9: 11/15/2024 | F9: Receita da venda de recicláveis | G9: Plástico | H9: PP Rígido (Balde, bacia, potes de sorvetes, margarina, entre outros) | I9: 0 | J9: 75 | K9: 112.5 | L9: 1.5 | M9: 0
A10: Valquiria | B10: UVR 01 - Formosa do Oeste | C10: 01 | D10: Formosa do Oeste | E10: 11/15/2024 | F10: Receita da venda de recicláveis | G10: Plástico | H10: PEAD (Embalagens de produtos de limpeza) | I10: 0 | J10: 338 | K10: 760.5 | L10: 2.25 | M10: 0
A11: Valquiria | B11: UVR 01 - Formosa do Oeste | C11: 01 | D11: Formosa do Oeste | E11: 11/15/2024 | F11: Receita da venda de recicláveis | G11: Plástico | H11: PET Óleo (Embalagens de óleo de cozinha) | I11: 0 | J11: 75 | K11: 135 | L11: 1.8 | M11: 0
A12: Valquiria | B12: UVR 01 - Formosa do Oeste | C12: 01 | D12: Formosa do Oeste | E12: 11/15/2024 | F12: Receita da venda de recicláveis | G12: Plástico | H12: PP Rígido (Balde, bacia, potes de sorvetes, margarina, entre outros) | I12: 0 | J12: 50 | K12: 65 | L12: 1.3 | M12: 0
A13: Valquiria | B13: UVR 01 - Formosa do Oeste | C13: 01 | D13: Formosa do Oeste | E13: 11/15/2024 | F13: Receita da venda de recicláveis | G13: Plástico | H13: PET Colorido (Embalagens de PET colorido, PET bagunça) | I13: 0 | J13: 150 | K13: 30 | L13: 0.2 | M13: 0
A14: Valquiria | B14: UVR 01 - Formosa do Oeste | C14: 01 | D14: Formosa do Oeste | E14: 11/15/2024 | F14: Receita da venda de recicláveis | G14: Plástico | H14: PEBD Filme (Sacolinha, Sacos de lixo, Lona Preta) | I14: 0 | J14: 50 | K14: 30 | L14: 0.6 | M14: 0
... A25: Valquiria | B25: UVR 01 - Formosa do Oeste | C25: 01 | D25: Formosa do Oeste | E25: 11/15/2024 | F25: Rejeito | G25: Rejeito | H25: null | I25: 0 | J25: 3620 | K25: 0 | L25: 0 | M25: 0
A26: Gabriel | B26: {=_xlfn._xlws.FILTER( 'Micro Dados - Todos'!$A$2:$L$20000, ('Micro Dados - Todos'!$C$2:$C$20000=Lacunas!B3) * ('Micro Dados - Todos'!$B$2:$B$20000=Lacunas!C3) * ('Micro Dados - Todos'!$D$2:$D$20000=Lacunas!F3) )} -> UVR 01 - Maripa | C26: 01 | D26: Maripa | E26: 11/15/2024 | F26: Receita da venda de recicláveis | G26: Papéis | H26: Papel Branco | I26: 0 | J26: 800 | K26: 560 | L26: 0.7 | M26: 0
A27: Gabriel | B27: UVR 01 - Maripa | C27: 01 | D27: Maripa | E27: 11/15/2024 | F27: Receita da venda de recicláveis | G27: Papéis | H27: Papel Misto | I27: 0 | J27: 1300 | K27: 325 | L27: 0.25 | M27: 0
A28: Gabriel | B28: UVR 01 - Maripa | C28: 01 | D28: Maripa | E28: 11/15/2024 | F28: Receita da venda de recicláveis | G28: Papéis | H28: Papelão | I28: 0 | J28: 8500 | K28: 5950 | L28: 0.7 | M28: 0
A29: Gabriel | B29: UVR 01 - Maripa | C29: 01 | D29: Maripa | E29: 11/15/2024 | F29: Receita da venda de recicláveis | G29: Papéis | H29: Tetra Pack | I29: 0 | J29: 500 | K29: 150 | L29: 0.3 | M29: 0
A30: Gabriel | B30: UVR 01 - Maripa | C30: 01 | D30: Maripa | E30: 11/15/2024 | F30: Receita da venda de recicláveis | G30: Plástico | H30: PVC (Cano, Forro, Tubulação de cano) | I30: 0 | J30: 100 | K30: 80 | L30: 0.8 | M30: 0
A31: Gabriel | B31: UVR 01 - Maripa | C31: 01 | D31: Maripa | E31: 11/15/2024 | F31: Receita da venda de recicláveis | G31: Plástico | H31: PEAD (Embalagens de produtos de limpeza) | I31: 0 | J31: 1050 | K31: 2310 | L31: 2.2 | M31: 0
A32: Gabriel | B32: UVR 01 - Maripa | C32: 01 | D32: Maripa | E32: 11/15/2024 | F32: Receita da venda de recicláveis | G32: Plástico | H32: PEAD Filme (Cristal) | I32: 0 | J32: 1500 | K32: 1950 | L32: 1.3 | M32: 0
A33: Gabriel | B33: UVR 01 - Maripa | C33: 01 | D33: Maripa | E33: 11/15/2024 | F33: Receita da venda de recicláveis | G33: Plástico | H33: PEBD Filme (Sacolinha, Sacos de lixo, Lona Preta) | I33: 0 | J33: 2000 | K33: 1500 | L33: 0.75 | M33: 0
A34: Gabriel | B34: UVR 01 - Maripa | C34: 01 | D34: Maripa | E34: 11/15/2024 | F34: Receita da venda de recicláveis | G34: Plástico | H34: PET Verde (Embalagens de refrigerante verde) | I34: 0 | J34: 450 | K34: 1800 | L34: 4 | M34: 0
A35: Gabriel | B35: UVR 01 - Maripa | C35: 01 | D35: Maripa | E35: 11/15/2024 | F35: Receita da venda de recicláveis | G35: Plástico | H35: PET Cristal (Embalagens de refrigerante transparente) | I35: 0 | J35: 450 | K35: 1800 | L35: 4 | M35: 0
A36: Gabriel | B36: UVR 01 - Maripa | C36: 01 | D36: Maripa | E36: 11/15/2024 | F36: Receita da venda de recicláveis | G36: Plástico | H36: PET Óleo (Embalagens de óleo de cozinha) | I36: 0 | J36: 150 | K36: 195 | L36: 1.3 | M36: 0
A37: Gabriel | B37: UVR 01 - Maripa | C37: 01 | D37: Maripa | E37: 11/15/2024 | F37: Receita da venda de recicláveis | G37: Plástico | H37: PET Colorido (Embalagens de PET colorido, PET bagunça) | I37: 0 | J37: 100 | K37: 5 | L37: 0.05 | M37: 0
A38: Gabriel | B38: UVR 01 - Maripa | C38: 01 | D38: Maripa | E38: 11/15/2024 | F38: Receita da venda de recicláveis | G38: Plástico | H38: PS (Copos descartáveis) | I38: 0 | J38: 160 | K38: 160 | L38: 1 | M38: 0
... A48: Gabriel | B48: UVR 01 - Maripa | C48: 01 | D48: Maripa | E48: 11/15/2024 | F48: Receita da venda de recicláveis | G48: Elétrico ou Eletrônicos | H48: Bateria | I48: 0 | J48: 21 | K48: 54.6 | L48: 2.6 | M48: 0
A49: Gabriel | B49: UVR 01 - Maripa | C49: 01 | D49: Maripa | E49: 11/15/2024 | F49: Receita da prestação de serviços | G49: Contratos | H49: 0 | I49: 0 | J49: 0 | K49: 29503.37 | L49: 0 | M49: 0
A50: Gabriel | B50: {=_xlfn._xlws.FILTER( 'Micro Dados - Todos'!$A$2:$L$20000, ('Micro Dados - Todos'!$C$2:$C$20000=Lacunas!B4) * ('Micro Dados - Todos'!$B$2:$B$20000=Lacunas!C4) * ('Micro Dados - Todos'!$D$2:$D$20000=Lacunas!F4) )} -> UVR 01 - Mundo Novo | C50: 01 | D50: Mundo Novo | E50: 11/15/2024 | F50: Receita da venda de recicláveis | G50: Vidro | H50: Caco | I50: 0 | J50: 19340 | K50: 1934 | L50: 0.1 | M50: 0
A51: Gabriel | B51: UVR 01 - Mundo Novo | C51: 01 | D51: Mundo Novo | E51: 11/15/2024 | F51: Receita da venda de recicláveis | G51: Papéis | H51: Papelão | I51: 0 | J51: 21036 | K51: 16868.8 | L51: 0.8 | M51: 0
A52: Gabriel | B52: UVR 01 - Mundo Novo | C52: 01 | D52: Mundo Novo | E52: 11/15/2024 | F52: Receita da venda de recicláveis | G52: Papéis | H52: Papel Misto | I52: 0 | J52: 871 | K52: 348.8 | L52: 0.4 | M52: 0
A53: Gabriel | B53: UVR 01 - Mundo Novo | C53: 01 | D53: Mundo Novo | E53: 11/15/2024 | F53: Receita da venda de recicláveis | G53: Papéis | H53: Papel Branco | I53: 0 | J53: 778 | K53: 466.8 | L53: 0.6 | M53: 0
A54: Gabriel | B54: UVR 01 - Mundo Novo | C54: 01 | D54: Mundo Novo | E54: 11/15/2024 | F54: Receita da venda de recicláveis | G54: Papéis | H54: Tetra Pack | I54: 0 | J54: 251 | K54: 87.85 | L54: 0.35 | M54: 0
A55: Gabriel | B55: UVR 01 - Mundo Novo | C55: 01 | D55: Mundo Novo | E55: 11/15/2024 | F55: Receita da venda de recicláveis | G55: Papéis | H55: Papel Cimento | I55: 0 | J55: 366 | K55: 146.4 | L55: 0.4 | M55: 0
A56: Gabriel | B56: UVR 01 - Mundo Novo | C56: 01 | D56: Mundo Novo | E56: 11/15/2024 | F56: Receita da venda de recicláveis | G56: Papéis | H56: Papel Branco | I56: 0 | J56: 412 | K56: 247.2 | L56: 0.6 | M56: 0
A57: Gabriel | B57: UVR 01 - Mundo Novo | C57: 01 | D57: Mundo Novo | E57: 11/15/2024 | F57: Receita da venda de recicláveis | G57: Plástico | H57: PET Cristal (Embalagens de refrigerante transparente) | I57: 0 | J57: 1157 | K57: 5206.5 | L57: 4.5 | M57: 0
A58: Gabriel | B58: UVR 01 - Mundo Novo | C58: 01 | D58: Mundo Novo | E58: 11/15/2024 | F58: Receita da venda de recicláveis | G58: Plástico | H58: PEAD (Embalagens de produtos de limpeza) | I58: 0 | J58: 583 | K58: 1311.75 | L58: 2.25 | M58: 0
A59: Gabriel | B59: UVR 01 - Mundo Novo | C59: 01 | D59: Mundo Novo | E59: 11/15/2024 | F59: Receita da venda de recicláveis | G59: Plástico | H59: PEAD Filme (Cristal) | I59: 0 | J59: 1106 | K59: 1548.4 | L59: 1.4 | M59: 0
A60: Gabriel | B60: UVR 01 - Mundo Novo | C60: 01 | D60: Mundo Novo | E60: 11/15/2024 | F60: Receita da venda de recicláveis | G60: Plástico | H60: PEBD Filme (Sacolinha, Sacos de lixo, Lona Preta) | I60: 0 | J60: 1033 | K60: 826.4 | L60: 0.8 | M60: 0
A61: Gabriel | B61: UVR 01 - Mundo Novo | C61: 01 | D61: Mundo Novo | E61: 11/15/2024 | F61: Receita da venda de recicláveis | G61: Plástico | H61: PEBD Filme (Sacolinha, Sacos de lixo, Lona Preta) | I61: 0 | J61: 506 | K61: 303.6 | L61: 0.6 | M61: 0
A62: Gabriel | B62: UVR 01 - Mundo Novo | C62: 01 | D62: Mundo Novo | E62: 11/15/2024 | F62: Receita da venda de recicláveis | G62: Plástico | H62: PP Rígido (Balde, bacia, potes de sorvetes, margarina, entre outros) | I62: 0 | J62: 471 | K62: 706.5 | L62: 1.5 | M62: 0
A63: Gabriel | B63: UVR 01 - Mundo Novo | C63: 01 | D63: Mundo Novo | E63: 11/15/2024 | F63: Receita da venda de recicláveis | G63: Plástico | H63: PP Rígido (Balde, bacia, potes de sorvetes, margarina, entre outros) | I63: 0 | J63: 416 | K63: 416 | L63: 1 | M63: 0
A64: Gabriel | B64: UVR 01 - Mundo Novo | C64: 01 | D64: Mundo Novo | E64: 11/15/2024 | F64: Receita da venda de recicláveis | G64: Plástico | H64: Outro tipo de plástico | I64: parachoque | J64: 72 | K64: 28.8 | L64: 0.4 | M64: 0
A65: Gabriel | B65: UVR 01 - Mundo Novo | C65: 01 | D65: Mundo Novo | E65: 11/15/2024 | F65: Receita da venda de recicláveis | G65: Plástico | H65: PET Colorido (Embalagens de PET colorido, PET bagunça) | I65: 0 | J65: 107 | K65: 5.35 | L65: 0.05 | M65: 0
A66: Gabriel | B66: UVR 01 - Mundo Novo | C66: 01 | D66: Mundo Novo | E66: 11/15/2024 | F66: Receita da venda de recicláveis | G66: Plástico | H66: PP Ráfia (Sacaria) | I66: 0 | J66: 201 | K66: 40.2 | L66: 0.2 | M66: 0
A67: Gabriel | B67: UVR 01 - Mundo Novo | C67: 01 | D67: Mundo Novo | E67: 11/15/2024 | F67: Receita da venda de recicláveis | G67: Plástico | H67: PVC (Cano, Forro, Tubulação de cano) | I67: 0 | J67: 97 | K67: 97 | L67: 1 | M67: 0
A68: Gabriel | B68: UVR 01 - Mundo Novo | C68: 01 | D68: Mundo Novo | E68: 11/15/2024 | F68: Receita da venda de recicláveis | G68: Plástico | H68: PS (Copos descartáveis) | I68: 0 | J68: 291 | K68: 14.55 | L68: 0.05 | M68: 0
A69: Gabriel | B69: UVR 01 - Mundo Novo | C69: 01 | D69: Mundo Novo | E69: 11/15/2024 | F69: Receita da venda de recicláveis | G69: Metal | H69: Alumínio Latinha | I69: 0 | J69: 285 | K69: 2166 | L69: 7.6 | M69: 0
A70: Gabriel | B70: UVR 01 - Mundo Novo | C70: 01 | D70: Mundo Novo | E70: 11/15/2024 | F70: Receita da venda de recicláveis | G70: Metal | H70: Alumínio Bloco | I70: 0 | J70: 33 | K70: 264 | L70: 8 | M70: 0
A71: Gabriel | B71: UVR 01 - Mundo Novo | C71: 01 | D71: Mundo Novo | E71: 11/15/2024 | F71: Receita da venda de recicláveis | G71: Metal | H71: Cobre Limpo | I71: 0 | J71: 41.5 | K71: 1577 | L71: 38 | M71: 0
A72: Gabriel | B72: UVR 01 - Mundo Novo | C72: 01 | D72: Mundo Novo | E72: 11/15/2024 | F72: Receita da venda de recicláveis | G72: Metal | H72: Chaparia | I72: 0 | J72: 72 | K72: 288 | L72: 4 | M72: 0
A73: Gabriel | B73: UVR 01 - Mundo Novo | C73: 01 | D73: Mundo Novo | E73: 11/15/2024 | F73: Receita da venda de recicláveis | G73: Metal | H73: Outros Metais | I73: 0 | J73: 34 | K73: 102 | L73: 3 | M73: 0
A74: Gabriel | B74: UVR 01 - Mundo Novo | C74: 01 | D74: Mundo Novo | E74: 11/15/2024 | F74: Receita da venda de recicláveis | G74: Metal | H74: Sucatas | I74: 0 | J74: 1700 | K74: 680 | L74: 0.4 | M74: 0
A75: Gabriel | B75: UVR 01 - Mundo Novo | C75: 01 | D75: Mundo Novo | E75: 11/15/2024 | F75: Rejeito | G75: Rejeito | H75: 0 | I75: 0 | J75: 5469 | K75: 0 | L75: 0 | M75: 0
A76: Gabriel | B76: UVR 01 - Mundo Novo | C76: 01 | D76: Mundo Novo | E76: 11/15/2024 | F76: Despesa | G76: Fita de arqueamento para fardos | H76: 0 | I76: 0 | J76: 0 | K76: 628.32 | L76: 0 | M76: 0
A77: Gabriel | B77: {=_xlfn._xlws.FILTER( 'Micro Dados - Todos'!$A$2:$L$20000, ('Micro Dados - Todos'!$C$2:$C$20000=Lacunas!B5) * ('Micro Dados - Todos'!$B$2:$B$20000=Lacunas!C5) * ('Micro Dados - Todos'!$D$2:$D$20000=Lacunas!F5) )} -> UVR 01 - Assis Chateaubriand | C77: 01 | D77: Assis Chateaubriand | E77: 12/15/2024 | F77: Despesa | G77: Outra Despesa | H77: null | I77: 0 | J77: 0 | K77: 500 | L77: 0 | M77: Consultoria jurídica
A78: Gabriel | B78: UVR 01 - Assis Chateaubriand | C78: 01 | D78: Assis Chateaubriand | E78: 12/15/2024 | F78: Despesa | G78: Outra Despesa | H78: null | I78: 0 | J78: 0 | K78: 1000 | L78: 0 | M78: Contabilidade
A79: Gabriel | B79: UVR 01 - Assis Chateaubriand | C79: 01 | D79: Assis Chateaubriand | E79: 12/15/2024 | F79: Despesa | G79: Conserto e manutenção de equipamentos/veículo | H79: null | I79: 0 | J79: 0 | K79: 3417 | L79: 0 | M79: 0
A80: Gabriel | B80: UVR 01 - Assis Chateaubriand | C80: 01 | D80: Assis Chateaubriand | E80: 12/15/2024 | F80: Despesa | G80: Equipamentos de Proteção Individual | H80: null | I80: 0 | J80: 0 | K80: 11 | L80: 0 | M80: 0
A81: Gabriel | B81: UVR 01 - Assis Chateaubriand | C81: 01 | D81: Assis Chateaubriand | E81: 12/15/2024 | F81: Despesa | G81: Materiais de limpeza | H81: null | I81: 0 | J81: 0 | K81: 537 | L81: 0 | M81: 0
A82: Gabriel | B82: UVR 01 - Assis Chateaubriand | C82: 01 | D82: Assis Chateaubriand | E82: 12/15/2024 | F82: Despesa | G82: Outra Despesa | H82: null | I82: 0 | J82: 0 | K82: 281 | L82: 0 | M82: Seguro
A83: Gabriel | B83: UVR 01 - Assis Chateaubriand | C83: 01 | D83: Assis Chateaubriand | E83: 12/15/2024 | F83: Despesa | G83: Outra Despesa | H83: null | I83: 0 | J83: 0 | K83: 46 | L83: 0 | M83: Cesta de relacionamento
A84: Gabriel | B84: UVR 01 - Assis Chateaubriand | C84: 01 | D84: Assis Chateaubriand | E84: 12/15/2024 | F84: Despesa | G84: Fita de arqueamento para fardos | H84: null | I84: 0 | J84: 0 | K84: 1278 | L84: 0 | M84: 0
A85: Gabriel | B85: UVR 01 - Assis Chateaubriand | C85: 01 | D85: Assis Chateaubriand | E85: 12/15/2024 | F85: Despesa | G85: Alimentação | H85: null | I85: 0 | J85: 0 | K85: 251 | L85: 0 | M85: 0
A86: Gabriel | B86: UVR 01 - Assis Chateaubriand | C86: 01 | D86: Assis Chateaubriand | E86: 12/15/2024 | F86: Despesa | G86: Equipamentos de Proteção Individual | H86: null | I86: 0 | J86: 0 | K86: 150 | L86: 0 | M86: 0
A87: Gabriel | B87: UVR 01 - Assis Chateaubriand | C87: 01 | D87: Assis Chateaubriand | E87: 12/15/2024 | F87: Despesa | G87: Outra Despesa | H87: null | I87: 0 | J87: 0 | K87: 153 | L87: 0 | M87: Internet
A88: Gabriel | B88: UVR 01 - Assis Chateaubriand | C88: 01 | D88: Assis Chateaubriand | E88: 12/15/2024 | F88: Despesa | G88: Outra Despesa | H88: null | I88: 0 | J88: 0 | K88: 1000 | L88: 0 | M88: Contabilidade
A89: Gabriel | B89: UVR 01 - Assis Chateaubriand | C89: 01 | D89: Assis Chateaubriand | E89: 12/15/2024 | F89: Despesa | G89: Equipamentos de Proteção Individual | H89: null | I89: 0 | J89: 0 | K89: 120 | L89: 0 | M89: 0
A90: Gabriel | B90: UVR 01 - Assis Chateaubriand | C90: 01 | D90: Assis Chateaubriand | E90: 12/15/2024 | F90: Rejeito | G90: Rejeito | H90: null | I90: 0 | J90: 15606 | K90: 0 | L90: 0 | M90: 0
A91: Gabriel | B91: UVR 01 - Assis Chateaubriand | C91: 01 | D91: Assis Chateaubriand | E91: 12/15/2024 | F91: Receita da prestação de serviços | G91: Contratos | H91: null | I91: 0 | J91: 0 | K91: 30460.27 | L91: 0 | M91: 0
A92: Gabriel | B92: UVR 01 - Assis Chateaubriand | C92: 01 | D92: Assis Chateaubriand | E92: 12/15/2024 | F92: Receita da venda de recicláveis | G92: Vidro | H92: Caco | I92: 0 | J92: 17470 | K92: 2795.2 | L92: 0.16 | M92: 0
A93: Gabriel | B93: UVR 01 - Assis Chateaubriand | C93: 01 | D93: Assis Chateaubriand | E93: 12/15/2024 | F93: Receita da venda de recicláveis | G93: Papéis | H93: Papel Cimento | I93: 0 | J93: 3361 | K93: 1344.4 | L93: 0.4 | M93: 0
A94: Gabriel | B94: UVR 01 - Assis Chateaubriand | C94: 01 | D94: Assis Chateaubriand | E94: 12/15/2024 | F94: Receita da venda de recicláveis | G94: Papéis | H94: Papelão | I94: 0 | J94: 23315 | K94: 17486.25 | L94: 0.75 | M94: 0
A95: Gabriel | B95: UVR 01 - Assis Chateaubriand | C95: 01 | D95: Assis Chateaubriand | E95: 12/15/2024 | F95: Receita da venda de recicláveis | G95: Papéis | H95: Papel Misto | I95: 0 | J95: 9462 | K95: 2838.6 | L95: 0.3 | M95: 0
A96: Gabriel | B96: UVR 01 - Assis Chateaubriand | C96: 01 | D96: Assis Chateaubriand | E96: 12/15/2024 | F96: Receita da venda de recicláveis | G96: Papéis | H96: Papel Branco | I96: 0 | J96: 2525 | K96: 1641.57 | L96: 0.65 | M96: 0
A97: Gabriel | B97: UVR 01 - Assis Chateaubriand | C97: 01 | D97: Assis Chateaubriand | E97: 12/15/2024 | F97: Receita da venda de recicláveis | G97: Papéis | H97: Tetra Pack | I97: 0 | J97: 1763.5 | K97: 617.22 | L97: 0.35 | M97: 0
A98: Gabriel | B98: UVR 01 - Assis Chateaubriand | C98: 01 | D98: Assis Chateaubriand | E98: 12/15/2024 | F98: Receita da venda de recicláveis | G98: Plástico | H98: PVC (Cano, Forro, Tubulação de cano) | I98: 0 | J98: 287 | K98: 287 | L98: 1 | M98: 0
A99: Gabriel | B99: UVR 01 - Assis Chateaubriand | C99: 01 | D99: Assis Chateaubriand | E99: 12/15/2024 | F99: Receita da venda de recicláveis | G99: Plástico | H99: PEAD (Embalagens de produtos de limpeza) | I99: 0 | J99: 1521.5 | K99: 3499.45 | L99: 2.3 | M99: 0
A100: Gabriel | B100: UVR 01 - Assis Chateaubriand | C100: 01 | D100: Assis Chateaubriand | E100: 12/15/2024 | F100: Receita da venda de recicláveis | G100: Plástico | H100: PP Rígido (Balde, bacia, potes de sorvetes, margarina, entre outros) | I100: 0 | J100: 4699 | K100: 5873.75 | L100: 1.25 | M100: 0
... A118: Gabriel | B118: UVR 01 - Assis Chateaubriand | C118: 01 | D118: Assis Chateaubriand | E118: 12/15/2024 | F118: Receita da venda de recicláveis | G118: Metal | H118: Outros Metais | I118: 0 | J118: 2.36 | K118: 896.8 | L118: 380 | M118: 0
A119: Valquiria | B119: {=_xlfn._xlws.FILTER( 'Micro Dados - Todos'!$A$2:$L$20000, ('Micro Dados - Todos'!$C$2:$C$20000=Lacunas!B6) * ('Micro Dados - Todos'!$B$2:$B$20000=Lacunas!C6) * ('Micro Dados - Todos'!$D$2:$D$20000=Lacunas!F6) )} -> UVR 01 - Cafelândia | C119: 01 | D119: Cafelândia | E119: 12/15/2024 | F119: Receita da venda de recicláveis | G119: Plástico | H119: PET Cristal (Embalagens de refrigerante transparente) | I119: 0 | J119: 1755 | K119: 2632.5 | L119: 1.5 | M119: 0
A120: Valquiria | B120: UVR 01 - Cafelândia | C120: 01 | D120: Cafelândia | E120: 12/15/2024 | F120: Receita da venda de recicláveis | G120: Plástico | H120: PET Óleo (Embalagens de óleo de cozinha) | I120: 0 | J120: 122 | K120: 97.6 | L120: 0.8 | M120: 0
A121: Valquiria | B121: UVR 01 - Cafelândia | C121: 01 | D121: Cafelândia | E121: 12/15/2024 | F121: Receita da venda de recicláveis | G121: Plástico | H121: PEAD Filme (Cristal) | I121: 0 | J121: 1763 | K121: 1763 | L121: 1 | M121: 0
A122: Valquiria | B122: UVR 01 - Cafelândia | C122: 01 | D122: Cafelândia | E122: 12/15/2024 | F122: Receita da venda de recicláveis | G122: Plástico | H122: PEAD (Embalagens de produtos de limpeza) | I122: 0 | J122: 505 | K122: 909 | L122: 1.8 | M122: 0
A123: Valquiria | B123: UVR 01 - Cafelândia | C123: 01 | D123: Cafelândia | E123: 12/15/2024 | F123: Receita da venda de recicláveis | G123: Plástico | H123: PEAD (Embalagens de produtos de limpeza) | I123: 0 | J123: 820 | K123: 1640 | L123: 2 | M123: 0
A124: Valquiria | B124: UVR 01 - Cafelândia | C124: 01 | D124: Cafelândia | E124: 12/15/2024 | F124: Receita da venda de recicláveis | G124: Plástico | H124: PP Rígido (Balde, bacia, potes de sorvetes, margarina, entre outros) | I124: 0 | J124: 206 | K124: 164.8 | L124: 0.8 | M124: 0
A125: Valquiria | B125: UVR 01 - Cafelândia | C125: 01 | D125: Cafelândia | E125: 12/15/2024 | F125: Receita da venda de recicláveis | G125: Plástico | H125: PP Ráfia (Sacaria) | I125: 0 | J125: 1813 | K125: 362.6 | L125: 0.2 | M125: 0
A126: Valquiria | B126: UVR 01 - Cafelândia | C126: 01 | D126: Cafelândia | E126: 12/15/2024 | F126: Receita da venda de recicláveis | G126: Plástico | H126: PS (Copos descartáveis) | I126: 0 | J126: 97 | K126: 77.6 | L126: 0.8 | M126: 0
A127: Valquiria | B127: UVR 01 - Cafelândia | C127: 01 | D127: Cafelândia | E127: 12/15/2024 | F127: Receita da venda de recicláveis | G127: Plástico | H127: PEBD Filme (Sacolinha, Sacos de lixo, Lona Preta) | I127: 0 | J127: 662 | K127: 297.9 | L127: 0.45 | M127: 0
A128: Valquiria | B128: UVR 01 - Cafelândia | C128: 01 | D128: Cafelândia | E128: 12/15/2024 | F128: Receita da venda de recicláveis | G128: Plástico | H128: PP Rígido (Balde, bacia, potes de sorvetes, margarina, entre outros) | I128: 0 | J128: 742 | K128: 742 | L128: 1 | M128: 0
A129: Valquiria | B129: UVR 01 - Cafelândia | C129: 01 | D129: Cafelândia | E129: 12/15/2024 | F129: Receita da venda de recicláveis | G129: Plástico | H129: PP Rígido (Balde, bacia, potes de sorvetes, margarina, entre outros) | I129: 0 | J129: 673 | K129: 807.6 | L129: 1.2 | M129: 0
A130: Valquiria | B130: UVR 01 - Cafelândia | C130: 01 | D130: Cafelândia | E130: 12/15/2024 | F130: Receita da venda de recicláveis | G130: Plástico | H130: PEBD Filme (Sacolinha, Sacos de lixo, Lona Preta) | I130: 0 | J130: 2031 | K130: 1421.7 | L130: 0.7 | M130: 0
A131: Valquiria | B131: UVR 01 - Cafelândia | C131: 01 | D131: Cafelândia | E131: 12/15/2024 | F131: Receita da venda de recicláveis | G131: Plástico | H131: PET Verde (Embalagens de refrigerante verde) | I131: 0 | J131: 410 | K131: 615 | L131: 1.5 | M131: 0
... A148: Valquiria | B148: UVR 01 - Cafelândia | C148: 01 | D148: Cafelândia | E148: 12/15/2024 | F148: Receita da venda de recicláveis | G148: Metal | H148: Ferro | I148: 0 | J148: 6785 | K148: 1792.5 | L148: 0.26 | M148: 0
A149: Valquiria | B149: UVR 01 - Cafelândia | C149: 01 | D149: Cafelândia | E149: 12/15/2024 | F149: Rejeito | G149: Rejeito | H149: 0 | I149: 0 | J149: 0 | K149: 0 | L149: 0 | M149: 0
A150: Valquiria | B150: UVR 01 - Cafelândia | C150: 01 | D150: Cafelândia | E150: 12/15/2024 | F150: Receita da prestação de serviços | G150: Contratos | H150: 0 | I150: 0 | J150: 0 | K150: 19985.6 | L150: 0 | M150: 0
A151: Valquiria | B151: UVR 01 - Cafelândia | C151: 01 | D151: Cafelândia | E151: 12/15/2024 | F151: Receita da venda de recicláveis | G151: Plástico | H151: PP Rígido (Balde, bacia, potes de sorvetes, margarina, entre outros) | I151: 0 | J151: 845 | K151: 1098.05 | L151: 1.3 | M151: 0
A152: Valquiria | B152: UVR 01 - Cafelândia | C152: 01 | D152: Cafelândia | E152: 12/15/2024 | F152: Receita da venda de recicláveis | G152: Plástico | H152: PET Cristal (Embalagens de refrigerante transparente) | I152: 0 | J152: 1417 | K152: 5384.6 | L152: 3.8 | M152: 0
...
